{
  "type": "Feature",
  "properties": {
    "gn:admin1_code":"6",
    "gn:asciiname":"Paua",
    "gn:country_code":"MZ",
    "gn:dem":682,
    "gn:feature_class":"P",
    "gn:feature_code":"PPL",
    "gn:name":"P\u00e1ua",
    "gn:population":0,
    "gn:timezone":"Africa/Maputo",
    "iso:country":"MZ",
    "wof:name":"Paua",
    "wof:placetype":"locality"
},
  "geometry": {"coordinates":[37.69806,-14.88917],"type":"Point"}
}