{
  "type": "Feature",
  "properties": {
    "gn:admin1_code":"3",
    "gn:asciiname":"Chicoche",
    "gn:country_code":"MZ",
    "gn:dem":121,
    "gn:feature_class":"P",
    "gn:feature_code":"PPL",
    "gn:name":"Chic\u00f4che",
    "gn:population":0,
    "gn:timezone":"Africa/Maputo",
    "iso:country":"MZ",
    "wof:name":"Chicoche",
    "wof:placetype":"locality"
},
  "geometry": {"coordinates":[33.90555999999999,-22.77944],"type":"Point"}
}