{
  "type": "Feature",
  "properties": {
    "gn:admin1_code":"10.0",
    "gn:asciiname":"Herdade do Ribatejo",
    "gn:country_code":"MZ",
    "gn:dem":620,
    "gn:feature_class":"P",
    "gn:feature_code":"PPL",
    "gn:name":"Herdade do Ribatejo",
    "gn:population":0,
    "gn:timezone":"Africa/Maputo",
    "iso:country":"MZ",
    "wof:name":"Herdade do Ribatejo",
    "wof:placetype":"locality"
},
  "geometry": {"coordinates":[33.23778,-19.39611],"type":"Point"}
}