{
  "type": "Feature",
  "properties": {
    "gn:admin1_code":"8",
    "gn:asciiname":"M'pembezo",
    "gn:country_code":"MZ",
    "gn:dem":1218,
    "gn:feature_class":"P",
    "gn:feature_code":"PPL",
    "gn:name":"M\u2019pembezo",
    "gn:population":0,
    "gn:timezone":"Africa/Maputo",
    "iso:country":"MZ",
    "wof:name":"M'pembezo",
    "wof:placetype":"locality"
},
  "geometry": {"coordinates":[34.21722,-14.60056],"type":"Point"}
}