{
  "type": "Feature",
  "properties": {
    "gn:admin1_code":"3.0",
    "gn:asciiname":"Elias",
    "gn:country_code":"MZ",
    "gn:dem":98,
    "gn:feature_class":"P",
    "gn:feature_code":"PPL",
    "gn:name":"Elias",
    "gn:population":0,
    "gn:timezone":"Africa/Maputo",
    "iso:country":"MZ",
    "name:dan_x_preferred":[
        "Elias"
    ],
    "name:deu_x_preferred":[
        "Elias"
    ],
    "name:est_x_preferred":[
        "Elias"
    ],
    "name:fas_x_preferred":[
        "\u0627\u06cc\u0644\u06cc\u0627"
    ],
    "name:fin_x_preferred":[
        "Elias"
    ],
    "name:hun_x_preferred":[
        "\u00c9li\u00e1s"
    ],
    "name:lat_x_preferred":[
        "Elias"
    ],
    "name:nno_x_preferred":[
        "Elias"
    ],
    "name:nor_x_preferred":[
        "Elias"
    ],
    "name:rus_x_preferred":[
        "\u042d\u043b\u0438\u0430\u0441"
    ],
    "name:swe_x_preferred":[
        "Elias"
    ],
    "wof:name":"Elias",
    "wof:placetype":"locality"
},
  "geometry": {"coordinates":[34.72555999999999,-23.38],"type":"Point"}
}