{
  "type": "Feature",
  "properties": {
    "gn:admin1_code":"3.0",
    "gn:asciiname":"Elias",
    "gn:country_code":"MZ",
    "gn:dem":98,
    "gn:feature_class":"P",
    "gn:feature_code":"PPL",
    "gn:name":"Elias",
    "gn:population":0,
    "gn:timezone":"Africa/Maputo",
    "iso:country":"MZ",
    "wof:name":"Elias",
    "wof:placetype":"locality"
},
  "geometry": {"coordinates":[34.72555999999999,-23.38],"type":"Point"}
}