{
  "type": "Feature",
  "properties": {
    "gn:admin1_code":"9",
    "gn:asciiname":"Munhahea",
    "gn:country_code":"MZ",
    "gn:dem":167,
    "gn:feature_class":"P",
    "gn:feature_code":"PPL",
    "gn:name":"Munhah\u00e9a",
    "gn:population":0,
    "gn:timezone":"Africa/Maputo",
    "iso:country":"MZ",
    "wof:name":"Munhahea",
    "wof:placetype":"locality"
},
  "geometry": {"coordinates":[37.48861,-16.63778],"type":"Point"}
}