{
  "type": "Feature",
  "properties": {
    "gn:admin1_code":"6",
    "gn:asciiname":"Nipucua",
    "gn:country_code":"MZ",
    "gn:dem":350,
    "gn:feature_class":"P",
    "gn:feature_code":"PPL",
    "gn:name":"Nipucua",
    "gn:population":0,
    "gn:timezone":"Africa/Maputo",
    "iso:country":"MZ",
    "wof:name":"Nipucua",
    "wof:placetype":"locality"
},
  "geometry": {"coordinates":[40.02861,-13.79167],"type":"Point"}
}