{
  "type": "Feature",
  "properties": {
    "gn:admin1_code":"2.0",
    "gn:asciiname":"Maunze",
    "gn:country_code":"MZ",
    "gn:dem":120,
    "gn:feature_class":"P",
    "gn:feature_code":"PPL",
    "gn:name":"Maunze",
    "gn:population":0,
    "gn:timezone":"Africa/Maputo",
    "iso:country":"MZ",
    "wof:name":"Maunze",
    "wof:placetype":"locality"
},
  "geometry": {"coordinates":[32.92889,-22.10472],"type":"Point"}
}