{
  "type": "Feature",
  "properties": {
    "gn:admin1_code":"4",
    "gn:asciiname":"Mecisa",
    "gn:country_code":"MZ",
    "gn:dem":17,
    "gn:feature_class":"P",
    "gn:feature_code":"PPL",
    "gn:name":"Mecisa",
    "gn:population":0,
    "gn:timezone":"Africa/Maputo",
    "iso:country":"MZ",
    "wof:name":"Mecisa",
    "wof:placetype":"locality"
},
  "geometry": {"coordinates":[32.78667,-25.59889],"type":"Point"}
}