{
  "type": "Feature",
  "properties": {
    "gn:admin1_code":"1",
    "gn:asciiname":"Namara",
    "gn:country_code":"MZ",
    "gn:dem":118,
    "gn:feature_class":"P",
    "gn:feature_code":"PPL",
    "gn:name":"Namara",
    "gn:population":0,
    "gn:timezone":"Africa/Maputo",
    "iso:country":"MZ",
    "wof:name":"Namara",
    "wof:placetype":"locality"
},
  "geometry": {"coordinates":[40.10667,-13.41028],"type":"Point"}
}