{
  "type": "Feature",
  "properties": {
    "gn:admin1_code":"5.0",
    "gn:asciiname":"Malenguene Massaide",
    "gn:country_code":"MZ",
    "gn:dem":45,
    "gn:feature_class":"P",
    "gn:feature_code":"PPL",
    "gn:name":"Malenguene Massa\u00edde",
    "gn:population":0,
    "gn:timezone":"Africa/Maputo",
    "iso:country":"MZ",
    "wof:name":"Malenguene Massaide",
    "wof:placetype":"locality"
},
  "geometry": {"coordinates":[34.73305999999999,-20.94],"type":"Point"}
}