{
  "type": "Feature",
  "properties": {
    "gn:admin1_code":"9",
    "gn:asciiname":"Regulo Namacala",
    "gn:cc2":"MZ",
    "gn:country_code":"MZ",
    "gn:dem":743,
    "gn:feature_class":"P",
    "gn:feature_code":"PPL",
    "gn:name":"R\u00e9gulo Namacala",
    "gn:population":0,
    "gn:timezone":"Africa/Maputo",
    "iso:country":"MZ",
    "name:und_x_variant":[
        "Namacala",
        "R\u00e9gulo Namacala"
    ],
    "wof:name":"Regulo Namacala",
    "wof:placetype":"locality"
},
  "geometry": {"coordinates":[36.86306,-15.48556],"type":"Point"}
}