{
  "type": "Feature",
  "properties": {
    "gn:admin1_code":"6",
    "gn:asciiname":"Morruto",
    "gn:country_code":"MZ",
    "gn:dem":334,
    "gn:feature_class":"P",
    "gn:feature_code":"PPL",
    "gn:name":"Morruto",
    "gn:population":0,
    "gn:timezone":"Africa/Maputo",
    "iso:country":"MZ",
    "wof:name":"Morruto",
    "wof:placetype":"locality"
},
  "geometry": {"coordinates":[39.33389,-15.01861],"type":"Point"}
}