{
  "type": "Feature",
  "properties": {
    "gn:admin1_code":"6.0",
    "gn:asciiname":"Chefe Raice",
    "gn:country_code":"MZ",
    "gn:dem":69,
    "gn:feature_class":"P",
    "gn:feature_code":"PPL",
    "gn:name":"Chefe Raice",
    "gn:population":0,
    "gn:timezone":"Africa/Maputo",
    "iso:country":"MZ",
    "wof:name":"Chefe Raice",
    "wof:placetype":"locality"
},
  "geometry": {"coordinates":[39.16722,-16.53444],"type":"Point"}
}