{
  "type": "Feature",
  "properties": {
    "gn:admin1_code":"2",
    "gn:asciiname":"Regedor Bango",
    "gn:cc2":"MZ",
    "gn:country_code":"MZ",
    "gn:dem":55,
    "gn:feature_class":"P",
    "gn:feature_code":"PPL",
    "gn:name":"Regedor Bango",
    "gn:population":0,
    "gn:timezone":"Africa/Maputo",
    "iso:country":"MZ",
    "name:und_x_variant":[
        "Bango",
        "Regedor Bango"
    ],
    "wof:name":"Regedor Bango",
    "wof:placetype":"locality"
},
  "geometry": {"coordinates":[33.75360999999999,-24.8325],"type":"Point"}
}