{
  "type": "Feature",
  "properties": {
    "gn:admin1_code":"0",
    "gn:asciiname":"Dama",
    "gn:country_code":"MZ",
    "gn:dem":7,
    "gn:feature_class":"P",
    "gn:feature_code":"PPL",
    "gn:name":"Dama",
    "gn:population":0,
    "gn:timezone":"Africa/Maputo",
    "iso:country":"MZ",
    "wof:name":"Dama",
    "wof:placetype":"locality"
},
  "geometry": {"coordinates":[36.88333,-18.06667],"type":"Point"}
}