{
  "type": "Feature",
  "properties": {
    "gn:admin1_code":"0",
    "gn:asciiname":"Dama",
    "gn:country_code":"MZ",
    "gn:dem":7,
    "gn:feature_class":"P",
    "gn:feature_code":"PPL",
    "gn:name":"Dama",
    "gn:population":0,
    "gn:timezone":"Africa/Maputo",
    "iso:country":"MZ",
    "name:aze_x_preferred":[
        "Dama"
    ],
    "name:bel_x_preferred":[
        "\u0414\u0430\u043c\u0430"
    ],
    "name:bul_x_preferred":[
        "\u0414\u0430\u043c\u0430"
    ],
    "name:cat_x_preferred":[
        "Dama"
    ],
    "name:ceb_x_preferred":[
        "Dama"
    ],
    "name:ces_x_preferred":[
        "D\u00e1ma"
    ],
    "name:deu_x_preferred":[
        "Dama"
    ],
    "name:ell_x_preferred":[
        "\u039d\u03c4\u03ac\u03bc\u03b1"
    ],
    "name:eus_x_preferred":[
        "Dama"
    ],
    "name:fra_x_preferred":[
        "Dama"
    ],
    "name:heb_x_preferred":[
        "\u05d3\u05de\u05d4"
    ],
    "name:ita_x_preferred":[
        "Dama"
    ],
    "name:nor_x_preferred":[
        "Dama"
    ],
    "name:pol_x_preferred":[
        "Dama"
    ],
    "name:por_x_preferred":[
        "Dama"
    ],
    "name:rus_x_preferred":[
        "\u0414\u0430\u043c\u0430"
    ],
    "name:slk_x_preferred":[
        "D\u00e1ma"
    ],
    "name:slv_x_preferred":[
        "Dama"
    ],
    "name:spa_x_preferred":[
        "Dama"
    ],
    "name:srp_x_preferred":[
        "\u0414\u0430\u043c\u0430"
    ],
    "name:swe_x_preferred":[
        "Dama"
    ],
    "name:ukr_x_preferred":[
        "\u0414\u0430\u043c\u0430"
    ],
    "wof:name":"Dama",
    "wof:placetype":"locality"
},
  "geometry": {"coordinates":[36.88333,-18.06667],"type":"Point"}
}