{
  "type": "Feature",
  "properties": {
    "gn:admin1_code":"6",
    "gn:asciiname":"Chefe Rumene",
    "gn:country_code":"MZ",
    "gn:dem":260,
    "gn:feature_class":"P",
    "gn:feature_code":"PPL",
    "gn:name":"Chefe Rumene",
    "gn:population":0,
    "gn:timezone":"Africa/Maputo",
    "iso:country":"MZ",
    "wof:name":"Chefe Rumene",
    "wof:placetype":"locality"
},
  "geometry": {"coordinates":[39.84306,-13.73667],"type":"Point"}
}