{
  "type": "Feature",
  "properties": {
    "gn:admin1_code":"8",
    "gn:asciiname":"Chidote",
    "gn:cc2":"MZ",
    "gn:country_code":"MZ",
    "gn:dem":452,
    "gn:feature_class":"P",
    "gn:feature_code":"PPL",
    "gn:name":"Chidote",
    "gn:population":0,
    "gn:timezone":"Africa/Maputo",
    "iso:country":"MZ",
    "name:und_x_variant":[
        "Chepurpulo",
        "Chidote"
    ],
    "wof:name":"Chidote",
    "wof:placetype":"locality"
},
  "geometry": {"coordinates":[32.6675,-15.86639],"type":"Point"}
}