{
  "type": "Feature",
  "properties": {
    "gn:admin1_code":"4.0",
    "gn:asciiname":"Soc. Ag. de Inconiate",
    "gn:country_code":"MZ",
    "gn:dem":28,
    "gn:feature_class":"P",
    "gn:feature_code":"PPL",
    "gn:name":"Soc. Ag. de Inconiate",
    "gn:population":0,
    "gn:timezone":"Africa/Maputo",
    "iso:country":"MZ",
    "wof:name":"Soc. Ag. de Inconiate",
    "wof:placetype":"locality"
},
  "geometry": {"coordinates":[32.80806,-25.0425],"type":"Point"}
}