{
  "type": "Feature",
  "properties": {
    "gn:admin1_code":"5",
    "gn:asciiname":"Chinhacate",
    "gn:country_code":"MZ",
    "gn:dem":137,
    "gn:feature_class":"P",
    "gn:feature_code":"PPL",
    "gn:name":"Chinhacate",
    "gn:population":0,
    "gn:timezone":"Africa/Maputo",
    "iso:country":"MZ",
    "wof:name":"Chinhacate",
    "wof:placetype":"locality"
},
  "geometry": {"coordinates":[33.84028,-20.13917],"type":"Point"}
}