{
  "type": "Feature",
  "properties": {
    "gn:admin1_code":"1",
    "gn:asciiname":"Paqueli",
    "gn:country_code":"MZ",
    "gn:dem":575,
    "gn:feature_class":"P",
    "gn:feature_code":"PPL",
    "gn:name":"Paqueli",
    "gn:population":0,
    "gn:timezone":"Africa/Maputo",
    "iso:country":"MZ",
    "wof:name":"Paqueli",
    "wof:placetype":"locality"
},
  "geometry": {"coordinates":[39.70028,-11.45972],"type":"Point"}
}