{
  "type": "Feature",
  "properties": {
    "gn:admin1_code":"10.0",
    "gn:asciiname":"Sandobze",
    "gn:country_code":"MZ",
    "gn:dem":95,
    "gn:feature_class":"P",
    "gn:feature_code":"PPL",
    "gn:name":"Sandobze",
    "gn:population":0,
    "gn:timezone":"Africa/Maputo",
    "iso:country":"MZ",
    "wof:name":"Sandobze",
    "wof:placetype":"locality"
},
  "geometry": {"coordinates":[34.30667,-16.73],"type":"Point"}
}