{
  "type": "Feature",
  "properties": {
    "gn:admin1_code":"6",
    "gn:asciiname":"Mujama",
    "gn:country_code":"MZ",
    "gn:dem":246,
    "gn:feature_class":"P",
    "gn:feature_code":"PPL",
    "gn:name":"Mujama",
    "gn:population":0,
    "gn:timezone":"Africa/Maputo",
    "iso:country":"MZ",
    "wof:name":"Mujama",
    "wof:placetype":"locality"
},
  "geometry": {"coordinates":[39.83194,-14.92861],"type":"Point"}
}