{
  "type": "Feature",
  "properties": {
    "gn:admin1_code":"6",
    "gn:asciiname":"Eurripa",
    "gn:country_code":"MZ",
    "gn:dem":640,
    "gn:feature_class":"P",
    "gn:feature_code":"PPL",
    "gn:name":"Eurripa",
    "gn:population":0,
    "gn:timezone":"Africa/Maputo",
    "iso:country":"MZ",
    "wof:name":"Eurripa",
    "wof:placetype":"locality"
},
  "geometry": {"coordinates":[37.41694,-14.87194],"type":"Point"}
}