{
  "type": "Feature",
  "properties": {
    "gn:admin1_code":"6",
    "gn:asciiname":"Chefe Sabao",
    "gn:country_code":"MZ",
    "gn:dem":334,
    "gn:feature_class":"P",
    "gn:feature_code":"PPL",
    "gn:name":"Chefe Sab\u00e3o",
    "gn:population":0,
    "gn:timezone":"Africa/Maputo",
    "iso:country":"MZ",
    "wof:name":"Chefe Sabao",
    "wof:placetype":"locality"
},
  "geometry": {"coordinates":[40.01667,-13.7075],"type":"Point"}
}