{
  "type": "Feature",
  "properties": {
    "gn:admin1_code":"3.0",
    "gn:asciiname":"Cabo Madangela",
    "gn:country_code":"MZ",
    "gn:dem":36,
    "gn:feature_class":"P",
    "gn:feature_code":"PPL",
    "gn:name":"Cabo Madangela",
    "gn:population":0,
    "gn:timezone":"Africa/Maputo",
    "iso:country":"MZ",
    "wof:name":"Cabo Madangela",
    "wof:placetype":"locality"
},
  "geometry": {"coordinates":[35.31361,-23.6075],"type":"Point"}
}