{
  "type": "Feature",
  "properties": {
    "gn:admin1_code":"0.0",
    "gn:asciiname":"Ussata",
    "gn:country_code":"MZ",
    "gn:dem":469,
    "gn:feature_class":"P",
    "gn:feature_code":"PPL",
    "gn:name":"Ussata",
    "gn:population":0,
    "gn:timezone":"Africa/Maputo",
    "iso:country":"MZ",
    "wof:name":"Ussata",
    "wof:placetype":"locality"
},
  "geometry": {"coordinates":[32.83333,-14.78333],"type":"Point"}
}