{
  "type": "Feature",
  "properties": {
    "gn:admin1_code":"3",
    "gn:asciiname":"Baxavane",
    "gn:cc2":"MZ",
    "gn:country_code":"MZ",
    "gn:dem":27,
    "gn:feature_class":"P",
    "gn:feature_code":"PPL",
    "gn:name":"Baxavane",
    "gn:population":0,
    "gn:timezone":"Africa/Maputo",
    "iso:country":"MZ",
    "name:und_x_variant":[
        "Baxavana",
        "Baxavane"
    ],
    "wof:name":"Baxavane",
    "wof:placetype":"locality"
},
  "geometry": {"coordinates":[34.22111,-24.36528],"type":"Point"}
}