{
  "type": "Feature",
  "properties": {
    "gn:admin1_code":"8",
    "gn:asciiname":"Ntembwe",
    "gn:country_code":"MZ",
    "gn:dem":858,
    "gn:feature_class":"P",
    "gn:feature_code":"PPL",
    "gn:name":"Ntembwe",
    "gn:population":0,
    "gn:timezone":"Africa/Maputo",
    "iso:country":"MZ",
    "wof:name":"Ntembwe",
    "wof:placetype":"locality"
},
  "geometry": {"coordinates":[31.88222,-15.16667],"type":"Point"}
}