{
  "type": "Feature",
  "properties": {
    "gn:admin1_code":"10",
    "gn:asciiname":"Chapalira",
    "gn:country_code":"MZ",
    "gn:dem":397,
    "gn:feature_class":"P",
    "gn:feature_code":"PPL",
    "gn:name":"Chapalira",
    "gn:population":0,
    "gn:timezone":"Africa/Maputo",
    "iso:country":"MZ",
    "wof:name":"Chapalira",
    "wof:placetype":"locality"
},
  "geometry": {"coordinates":[33.75444,-17.02444],"type":"Point"}
}