{
  "type": "Feature",
  "properties": {
    "gn:admin1_code":"0",
    "gn:asciiname":"Mulendema",
    "gn:country_code":"MZ",
    "gn:dem":487,
    "gn:feature_class":"P",
    "gn:feature_code":"PPL",
    "gn:name":"Mulendema",
    "gn:population":0,
    "gn:timezone":"Africa/Maputo",
    "iso:country":"MZ",
    "wof:name":"Mulendema",
    "wof:placetype":"locality"
},
  "geometry": {"coordinates":[32.25,-16.36667000000001],"type":"Point"}
}