{
  "type": "Feature",
  "properties": {
    "gn:admin1_code":"4.0",
    "gn:asciiname":"Sousa",
    "gn:country_code":"MZ",
    "gn:dem":0,
    "gn:feature_class":"P",
    "gn:feature_code":"PPL",
    "gn:name":"Sousa",
    "gn:population":0,
    "gn:timezone":"Africa/Maputo",
    "iso:country":"MZ",
    "name:bpy_x_preferred":[
        "\u09b8\u09cc\u09b8\u09be"
    ],
    "name:cat_x_preferred":[
        "Sousa"
    ],
    "name:ceb_x_preferred":[
        "Sousa"
    ],
    "name:deu_x_preferred":[
        "Sousa"
    ],
    "name:fin_x_preferred":[
        "Sousa"
    ],
    "name:fra_x_preferred":[
        "Sousa"
    ],
    "name:glg_x_preferred":[
        "Sousa"
    ],
    "name:heb_x_preferred":[
        "\u05e1\u05d5\u05d6\u05d4"
    ],
    "name:hun_x_preferred":[
        "Sousa"
    ],
    "name:hye_x_preferred":[
        "\u054d\u0578\u0566\u0561"
    ],
    "name:ita_x_preferred":[
        "Sousa"
    ],
    "name:jpn_x_preferred":[
        "\u30bd\u30a6\u30b6"
    ],
    "name:lit_x_preferred":[
        "Sousa"
    ],
    "name:nld_x_preferred":[
        "Sousa"
    ],
    "name:pol_x_preferred":[
        "Sousa"
    ],
    "name:por_x_preferred":[
        "Sousa"
    ],
    "name:ron_x_preferred":[
        "Sousa"
    ],
    "name:rus_x_preferred":[
        "\u0421\u043e\u0437\u0430"
    ],
    "name:sco_x_preferred":[
        "Sousa"
    ],
    "name:spa_x_preferred":[
        "Sousa"
    ],
    "name:swe_x_preferred":[
        "Sousa"
    ],
    "name:ukr_x_preferred":[
        "\u0421\u043e\u0437\u0430"
    ],
    "wof:name":"Sousa",
    "wof:placetype":"locality"
},
  "geometry": {"coordinates":[32.88333,-25.43333],"type":"Point"}
}