{
  "type": "Feature",
  "properties": {
    "gn:admin1_code":"1.0",
    "gn:asciiname":"Rimela",
    "gn:country_code":"MZ",
    "gn:dem":110,
    "gn:feature_class":"P",
    "gn:feature_code":"PPL",
    "gn:name":"Rimela",
    "gn:population":0,
    "gn:timezone":"Africa/Maputo",
    "iso:country":"MZ",
    "wof:name":"Rimela",
    "wof:placetype":"locality"
},
  "geometry": {"coordinates":[40.18278,-12.71722],"type":"Point"}
}