{
  "type": "Feature",
  "properties": {
    "gn:admin1_code":"6",
    "gn:asciiname":"Tinua",
    "gn:country_code":"MZ",
    "gn:dem":413,
    "gn:feature_class":"P",
    "gn:feature_code":"PPL",
    "gn:name":"Tinua",
    "gn:population":0,
    "gn:timezone":"Africa/Maputo",
    "iso:country":"MZ",
    "wof:name":"Tinua",
    "wof:placetype":"locality"
},
  "geometry": {"coordinates":[39.45806,-14.66083],"type":"Point"}
}