{
  "type": "Feature",
  "properties": {
    "gn:admin1_code":"1",
    "gn:asciiname":"Mazeze",
    "gn:country_code":"MZ",
    "gn:dem":219,
    "gn:feature_class":"P",
    "gn:feature_code":"PPL",
    "gn:name":"Mazeze",
    "gn:population":0,
    "gn:timezone":"Africa/Maputo",
    "iso:country":"MZ",
    "wof:name":"Mazeze",
    "wof:placetype":"locality"
},
  "geometry": {"coordinates":[40.19694000000001,-13.36361],"type":"Point"}
}