{
  "type": "Feature",
  "properties": {
    "gn:admin1_code":"2",
    "gn:asciiname":"Chidumo",
    "gn:country_code":"MZ",
    "gn:dem":99,
    "gn:feature_class":"P",
    "gn:feature_code":"PPL",
    "gn:name":"Chidumo",
    "gn:population":0,
    "gn:timezone":"Africa/Maputo",
    "iso:country":"MZ",
    "wof:name":"Chidumo",
    "wof:placetype":"locality"
},
  "geometry": {"coordinates":[33.81083,-24.52111],"type":"Point"}
}