{
  "type": "Feature",
  "properties": {
    "gn:admin1_code":"6",
    "gn:asciiname":"Ioburro",
    "gn:country_code":"MZ",
    "gn:dem":372,
    "gn:feature_class":"P",
    "gn:feature_code":"PPL",
    "gn:name":"Ioburro",
    "gn:population":0,
    "gn:timezone":"Africa/Maputo",
    "iso:country":"MZ",
    "wof:name":"Ioburro",
    "wof:placetype":"locality"
},
  "geometry": {"coordinates":[39.94056,-13.92528],"type":"Point"}
}