{
  "type": "Feature",
  "properties": {
    "gn:admin1_code":"7",
    "gn:asciiname":"Madeira",
    "gn:country_code":"MZ",
    "gn:dem":748,
    "gn:feature_class":"P",
    "gn:feature_code":"PPL",
    "gn:name":"Madeira",
    "gn:population":0,
    "gn:timezone":"Africa/Maputo",
    "iso:country":"MZ",
    "wof:name":"Madeira",
    "wof:placetype":"locality"
},
  "geometry": {"coordinates":[35.52583,-12.18],"type":"Point"}
}