{
  "type": "Feature",
  "properties": {
    "gn:admin1_code":"6",
    "gn:asciiname":"Mepita",
    "gn:country_code":"MZ",
    "gn:dem":151,
    "gn:feature_class":"P",
    "gn:feature_code":"PPL",
    "gn:name":"Mepita",
    "gn:population":0,
    "gn:timezone":"Africa/Maputo",
    "iso:country":"MZ",
    "wof:name":"Mepita",
    "wof:placetype":"locality"
},
  "geometry": {"coordinates":[39.28306,-15.75611],"type":"Point"}
}