{
  "type": "Feature",
  "properties": {
    "gn:admin1_code":"6",
    "gn:asciiname":"Ecuba",
    "gn:country_code":"MZ",
    "gn:dem":276,
    "gn:feature_class":"P",
    "gn:feature_code":"PPL",
    "gn:name":"Ecuba",
    "gn:population":0,
    "gn:timezone":"Africa/Maputo",
    "iso:country":"MZ",
    "wof:name":"Ecuba",
    "wof:placetype":"locality"
},
  "geometry": {"coordinates":[40.03444,-14.05833],"type":"Point"}
}