{
  "type": "Feature",
  "properties": {
    "gn:admin1_code":"7",
    "gn:asciiname":"Lombaiomba",
    "gn:cc2":"MZ",
    "gn:country_code":"MZ",
    "gn:dem":889,
    "gn:feature_class":"P",
    "gn:feature_code":"PPL",
    "gn:name":"Lombaiomba",
    "gn:population":0,
    "gn:timezone":"Africa/Maputo",
    "iso:country":"MZ",
    "name:und_x_variant":[
        "Iombaiomba",
        "Lombaiomba"
    ],
    "wof:name":"Lombaiomba",
    "wof:placetype":"locality"
},
  "geometry": {"coordinates":[34.97028,-12.38917],"type":"Point"}
}