{
  "type": "Feature",
  "properties": {
    "gn:admin1_code":"9.0",
    "gn:asciiname":"Ruciua",
    "gn:country_code":"MZ",
    "gn:dem":316,
    "gn:feature_class":"P",
    "gn:feature_code":"PPL",
    "gn:name":"Ruciua",
    "gn:population":0,
    "gn:timezone":"Africa/Maputo",
    "iso:country":"MZ",
    "wof:name":"Ruciua",
    "wof:placetype":"locality"
},
  "geometry": {"coordinates":[36.46278,-16.41583],"type":"Point"}
}