{
  "type": "Feature",
  "properties": {
    "gn:admin1_code":"1",
    "gn:asciiname":"Beunga",
    "gn:country_code":"MZ",
    "gn:dem":660,
    "gn:feature_class":"P",
    "gn:feature_code":"PPL",
    "gn:name":"Beunga",
    "gn:population":0,
    "gn:timezone":"Africa/Maputo",
    "iso:country":"MZ",
    "wof:name":"Beunga",
    "wof:placetype":"locality"
},
  "geometry": {"coordinates":[39.62444,-11.44167],"type":"Point"}
}