{
  "type": "Feature",
  "properties": {
    "gn:admin1_code":"5.0",
    "gn:asciiname":"Promeiro",
    "gn:country_code":"MZ",
    "gn:dem":362,
    "gn:feature_class":"P",
    "gn:feature_code":"PPL",
    "gn:name":"Promeiro",
    "gn:population":0,
    "gn:timezone":"Africa/Maputo",
    "iso:country":"MZ",
    "wof:name":"Promeiro",
    "wof:placetype":"locality"
},
  "geometry": {"coordinates":[33.93,-18.80444],"type":"Point"}
}