{
  "type": "Feature",
  "properties": {
    "gn:admin1_code":"8",
    "gn:asciiname":"Bongo",
    "gn:country_code":"MZ",
    "gn:dem":497,
    "gn:feature_class":"P",
    "gn:feature_code":"PPL",
    "gn:name":"Bongo",
    "gn:population":0,
    "gn:timezone":"Africa/Maputo",
    "iso:country":"MZ",
    "wof:name":"Bongo",
    "wof:placetype":"locality"
},
  "geometry": {"coordinates":[33.10556,-15.49417],"type":"Point"}
}