{
  "type": "Feature",
  "properties": {
    "gn:admin1_code":"5.0",
    "gn:asciiname":"Simanco",
    "gn:country_code":"MZ",
    "gn:dem":61,
    "gn:feature_class":"P",
    "gn:feature_code":"PPL",
    "gn:name":"Simanco",
    "gn:population":0,
    "gn:timezone":"Africa/Maputo",
    "iso:country":"MZ",
    "wof:name":"Simanco",
    "wof:placetype":"locality"
},
  "geometry": {"coordinates":[34.33722,-21.29667],"type":"Point"}
}