{
  "type": "Feature",
  "properties": {
    "gn:admin1_code":"8.0",
    "gn:asciiname":"Mualadze",
    "gn:cc2":"MZ",
    "gn:country_code":"MZ",
    "gn:dem":919,
    "gn:feature_class":"P",
    "gn:feature_code":"PPL",
    "gn:name":"Mualadze",
    "gn:population":0,
    "gn:timezone":"Africa/Maputo",
    "iso:country":"MZ",
    "name:und_x_variant":[
        "Vila Gamito",
        "Mualadzi",
        "Mualadze"
    ],
    "wof:name":"Mualadze",
    "wof:placetype":"locality"
},
  "geometry": {"coordinates":[32.98694,-14.16639],"type":"Point"}
}