{
  "type": "Feature",
  "properties": {
    "gn:admin1_code":"8.0",
    "gn:asciiname":"Supedi",
    "gn:country_code":"MZ",
    "gn:dem":1103,
    "gn:feature_class":"P",
    "gn:feature_code":"PPL",
    "gn:name":"Sup\u00e9di",
    "gn:population":0,
    "gn:timezone":"Africa/Maputo",
    "iso:country":"MZ",
    "wof:name":"Supedi",
    "wof:placetype":"locality"
},
  "geometry": {"coordinates":[34.23972,-14.70667],"type":"Point"}
}