{
  "type": "Feature",
  "properties": {
    "gn:admin1_code":"9",
    "gn:asciiname":"Nantuto",
    "gn:cc2":"MZ",
    "gn:country_code":"MZ",
    "gn:dem":726,
    "gn:feature_class":"P",
    "gn:feature_code":"PPL",
    "gn:name":"Nantuto",
    "gn:population":0,
    "gn:timezone":"Africa/Maputo",
    "iso:country":"MZ",
    "name:und_x_variant":[
        "Nantuta",
        "Nantuto"
    ],
    "wof:name":"Nantuto",
    "wof:placetype":"locality"
},
  "geometry": {"coordinates":[36.55111,-15.63722],"type":"Point"}
}