{
  "type": "Feature",
  "properties": {
    "gn:admin1_code":"3.0",
    "gn:asciiname":"Induna Farnela",
    "gn:country_code":"MZ",
    "gn:dem":72,
    "gn:feature_class":"P",
    "gn:feature_code":"PPL",
    "gn:name":"Induna Farnela",
    "gn:population":0,
    "gn:timezone":"Africa/Maputo",
    "iso:country":"MZ",
    "wof:name":"Induna Farnela",
    "wof:placetype":"locality"
},
  "geometry": {"coordinates":[34.81028,-21.36694],"type":"Point"}
}