{
  "type": "Feature",
  "properties": {
    "gn:admin1_code":"7",
    "gn:asciiname":"Namaumba",
    "gn:cc2":"MZ",
    "gn:country_code":"MZ",
    "gn:dem":760,
    "gn:feature_class":"P",
    "gn:feature_code":"PPL",
    "gn:name":"Namaumba",
    "gn:population":0,
    "gn:timezone":"Africa/Maputo",
    "iso:country":"MZ",
    "name:und_x_variant":[
        "Namaumbo",
        "Namaumba"
    ],
    "wof:name":"Namaumba",
    "wof:placetype":"locality"
},
  "geometry": {"coordinates":[35.12167,-12.41361],"type":"Point"}
}