{
  "type": "Feature",
  "properties": {
    "gn:admin1_code":"6",
    "gn:asciiname":"Maquina",
    "gn:country_code":"MZ",
    "gn:dem":5,
    "gn:feature_class":"P",
    "gn:feature_code":"PPL",
    "gn:name":"M\u00e1quina",
    "gn:population":0,
    "gn:timezone":"Africa/Maputo",
    "iso:country":"MZ",
    "wof:name":"Maquina",
    "wof:placetype":"locality"
},
  "geometry": {"coordinates":[40.03861,-16.09333],"type":"Point"}
}