{
  "type": "Feature",
  "properties": {
    "gn:admin1_code":"1",
    "gn:asciiname":"Chaibo",
    "gn:country_code":"MZ",
    "gn:dem":433,
    "gn:feature_class":"P",
    "gn:feature_code":"PPL",
    "gn:name":"Chaibo",
    "gn:population":0,
    "gn:timezone":"Africa/Maputo",
    "iso:country":"MZ",
    "wof:name":"Chaibo",
    "wof:placetype":"locality"
},
  "geometry": {"coordinates":[39.32083,-11.28778],"type":"Point"}
}