{
  "type": "Feature",
  "properties": {
    "gn:admin1_code":"1",
    "gn:asciiname":"Calani",
    "gn:country_code":"MZ",
    "gn:dem":76,
    "gn:feature_class":"P",
    "gn:feature_code":"PPL",
    "gn:name":"Calani",
    "gn:population":0,
    "gn:timezone":"Africa/Maputo",
    "iso:country":"MZ",
    "wof:name":"Calani",
    "wof:placetype":"locality"
},
  "geometry": {"coordinates":[40.40722,-13.06583],"type":"Point"}
}