{
  "type": "Feature",
  "properties": {
    "gn:admin1_code":"6",
    "gn:asciiname":"Motiua",
    "gn:country_code":"MZ",
    "gn:dem":539,
    "gn:feature_class":"P",
    "gn:feature_code":"PPL",
    "gn:name":"Motiua",
    "gn:population":0,
    "gn:timezone":"Africa/Maputo",
    "iso:country":"MZ",
    "wof:name":"Motiua",
    "wof:placetype":"locality"
},
  "geometry": {"coordinates":[38.79278,-14.60222],"type":"Point"}
}