{
  "type": "Feature",
  "properties": {
    "gn:admin1_code":"1.0",
    "gn:asciiname":"Revia",
    "gn:country_code":"MZ",
    "gn:dem":378,
    "gn:feature_class":"P",
    "gn:feature_code":"PPL",
    "gn:name":"R\u00e9via",
    "gn:population":0,
    "gn:timezone":"Africa/Maputo",
    "iso:country":"MZ",
    "wof:name":"Revia",
    "wof:placetype":"locality"
},
  "geometry": {"coordinates":[39.48528,-13.39694],"type":"Point"}
}