{
  "type": "Feature",
  "properties": {
    "gn:admin1_code":"8",
    "gn:asciiname":"Metacha",
    "gn:country_code":"MZ",
    "gn:dem":595,
    "gn:feature_class":"P",
    "gn:feature_code":"PPL",
    "gn:name":"Metacha",
    "gn:population":0,
    "gn:timezone":"Africa/Maputo",
    "iso:country":"MZ",
    "wof:name":"Metacha",
    "wof:placetype":"locality"
},
  "geometry": {"coordinates":[32.96417,-14.75444],"type":"Point"}
}