{
  "type": "Feature",
  "properties": {
    "gn:admin1_code":"7",
    "gn:asciiname":"Candulo",
    "gn:country_code":"MZ",
    "gn:dem":980,
    "gn:feature_class":"P",
    "gn:feature_code":"PPL",
    "gn:name":"Candulo",
    "gn:population":0,
    "gn:timezone":"Africa/Maputo",
    "iso:country":"MZ",
    "wof:name":"Candulo",
    "wof:placetype":"locality"
},
  "geometry": {"coordinates":[35.40333,-12.46278],"type":"Point"}
}