{
  "type": "Feature",
  "properties": {
    "gn:admin1_code":"1",
    "gn:asciiname":"Chefe Namatupune",
    "gn:cc2":"MZ",
    "gn:country_code":"MZ",
    "gn:dem":445,
    "gn:feature_class":"P",
    "gn:feature_code":"PPL",
    "gn:name":"Chefe Namatupune",
    "gn:population":0,
    "gn:timezone":"Africa/Maputo",
    "iso:country":"MZ",
    "name:und_x_variant":[
        "Namantupune",
        "Chefe Namatupune"
    ],
    "wof:name":"Chefe Namatupune",
    "wof:placetype":"locality"
},
  "geometry": {"coordinates":[39.32306,-13.42222],"type":"Point"}
}