{
  "type": "Feature",
  "properties": {
    "gn:admin1_code":"1.0",
    "gn:asciiname":"Pora",
    "gn:country_code":"MZ",
    "gn:dem":577,
    "gn:feature_class":"P",
    "gn:feature_code":"PPL",
    "gn:name":"Pora",
    "gn:population":0,
    "gn:timezone":"Africa/Maputo",
    "iso:country":"MZ",
    "wof:name":"Pora",
    "wof:placetype":"locality"
},
  "geometry": {"coordinates":[38.55722,-13.35333],"type":"Point"}
}