{
  "type": "Feature",
  "properties": {
    "gn:admin1_code":"9.0",
    "gn:asciiname":"Chefe Rosa",
    "gn:country_code":"MZ",
    "gn:dem":160,
    "gn:feature_class":"P",
    "gn:feature_code":"PPL",
    "gn:name":"Chefe Rosa",
    "gn:population":0,
    "gn:timezone":"Africa/Maputo",
    "iso:country":"MZ",
    "wof:name":"Chefe Rosa",
    "wof:placetype":"locality"
},
  "geometry": {"coordinates":[37.14639,-16.74194],"type":"Point"}
}