{
  "type": "Feature",
  "properties": {
    "gn:admin1_code":"1",
    "gn:asciiname":"Cadi",
    "gn:country_code":"MZ",
    "gn:dem":93,
    "gn:feature_class":"P",
    "gn:feature_code":"PPL",
    "gn:name":"Cadi",
    "gn:population":0,
    "gn:timezone":"Africa/Maputo",
    "iso:country":"MZ",
    "name:bar_x_preferred":[
        "Cadi"
    ],
    "name:cat_x_preferred":[
        "Cad\u00ed"
    ],
    "name:ceb_x_preferred":[
        "Cadi"
    ],
    "name:deu_x_preferred":[
        "Cadi"
    ],
    "name:spa_x_preferred":[
        "Cadi"
    ],
    "name:swe_x_preferred":[
        "Cadi"
    ],
    "wof:name":"Cadi",
    "wof:placetype":"locality"
},
  "geometry": {"coordinates":[40.22,-12.90139],"type":"Point"}
}