{
  "type": "Feature",
  "properties": {
    "gn:admin1_code":"2",
    "gn:asciiname":"Macuruja",
    "gn:country_code":"MZ",
    "gn:dem":133,
    "gn:feature_class":"P",
    "gn:feature_code":"PPL",
    "gn:name":"Macuruja",
    "gn:population":0,
    "gn:timezone":"Africa/Maputo",
    "iso:country":"MZ",
    "wof:name":"Macuruja",
    "wof:placetype":"locality"
},
  "geometry": {"coordinates":[32.87806,-21.51472],"type":"Point"}
}