{
  "type": "Feature",
  "properties": {
    "gn:admin1_code":"0",
    "gn:asciiname":"Laquia",
    "gn:country_code":"MZ",
    "gn:dem":449,
    "gn:feature_class":"P",
    "gn:feature_code":"PPL",
    "gn:name":"Laquia",
    "gn:population":0,
    "gn:timezone":"Africa/Maputo",
    "iso:country":"MZ",
    "wof:name":"Laquia",
    "wof:placetype":"locality"
},
  "geometry": {"coordinates":[33.53333,-18.56667],"type":"Point"}
}