{
  "type": "Feature",
  "properties": {
    "gn:admin1_code":"3.0",
    "gn:asciiname":"Siani",
    "gn:country_code":"MZ",
    "gn:dem":143,
    "gn:feature_class":"P",
    "gn:feature_code":"PPL",
    "gn:name":"Siani",
    "gn:population":0,
    "gn:timezone":"Africa/Maputo",
    "iso:country":"MZ",
    "wof:name":"Siani",
    "wof:placetype":"locality"
},
  "geometry": {"coordinates":[34.03055999999999,-22.67806],"type":"Point"}
}