{
  "type": "Feature",
  "properties": {
    "gn:admin1_code":"7",
    "gn:asciiname":"Catur",
    "gn:country_code":"MZ",
    "gn:dem":1026,
    "gn:feature_class":"P",
    "gn:feature_code":"PPL",
    "gn:name":"Catur",
    "gn:population":0,
    "gn:timezone":"Africa/Maputo",
    "iso:country":"MZ",
    "wof:name":"Catur",
    "wof:placetype":"locality"
},
  "geometry": {"coordinates":[35.49944,-13.79278],"type":"Point"}
}