{
  "type": "Feature",
  "properties": {
    "gn:admin1_code":"3.0",
    "gn:asciiname":"Laquene",
    "gn:country_code":"MZ",
    "gn:dem":170,
    "gn:feature_class":"P",
    "gn:feature_code":"PPL",
    "gn:name":"Laquene",
    "gn:population":0,
    "gn:timezone":"Africa/Maputo",
    "iso:country":"MZ",
    "wof:name":"Laquene",
    "wof:placetype":"locality"
},
  "geometry": {"coordinates":[34.55306,-22.61167],"type":"Point"}
}