{
  "type": "Feature",
  "properties": {
    "gn:admin1_code":"3.0",
    "gn:asciiname":"Quissico",
    "gn:country_code":"MZ",
    "gn:dem":144,
    "gn:feature_class":"P",
    "gn:feature_code":"PPL",
    "gn:name":"Quissico",
    "gn:population":0,
    "gn:timezone":"Africa/Maputo",
    "iso:country":"MZ",
    "wof:name":"Quissico",
    "wof:placetype":"locality"
},
  "geometry": {"coordinates":[35.27861,-23.54528],"type":"Point"}
}