{
  "type": "Feature",
  "properties": {
    "gn:admin1_code":"3.0",
    "gn:asciiname":"Quissico",
    "gn:country_code":"MZ",
    "gn:dem":144,
    "gn:feature_class":"P",
    "gn:feature_code":"PPL",
    "gn:name":"Quissico",
    "gn:population":0,
    "gn:timezone":"Africa/Maputo",
    "iso:country":"MZ",
    "name:ara_x_preferred":[
        "\u0643\u064a\u0648\u0633\u064a\u0643\u0648"
    ],
    "name:ben_x_preferred":[
        "\u0995\u09c1\u0987\u09b8\u09bf\u0995\u09cb"
    ],
    "name:ell_x_preferred":[
        "\u039a\u03bf\u03c5\u03af\u03c3\u03b9\u03ba\u03bf"
    ],
    "name:heb_x_preferred":[
        "\u05e7\u05d5\u05d5\u05d9\u05e1\u05d9\u05e7\u05d5"
    ],
    "name:hin_x_preferred":[
        "\u0915\u094d\u0935\u093f\u0938\u093f\u0915\u094b"
    ],
    "name:hun_x_preferred":[
        "Quissico"
    ],
    "name:ind_x_preferred":[
        "Quissico"
    ],
    "name:kor_x_preferred":[
        "\ud0a4\uc2dc\ucf54"
    ],
    "name:pol_x_preferred":[
        "Quissico"
    ],
    "name:rus_x_preferred":[
        "\u041a\u0443\u0438\u0441\u0441\u0438\u043a\u043e"
    ],
    "name:swe_x_preferred":[
        "Quissico"
    ],
    "name:tur_x_preferred":[
        "Quissico"
    ],
    "name:ukr_x_preferred":[
        "\u041a\u0456\u0441\u0441\u0456\u043a\u043e"
    ],
    "name:urd_x_preferred":[
        "\u06a9\u0648\u0626\u0633\u06cc\u06a9\u0648"
    ],
    "name:vie_x_preferred":[
        "Quissico"
    ],
    "wof:name":"Quissico",
    "wof:placetype":"locality"
},
  "geometry": {"coordinates":[35.27861,-23.54528],"type":"Point"}
}