{
  "type": "Feature",
  "properties": {
    "gn:admin1_code":"5",
    "gn:asciiname":"Chingondo",
    "gn:country_code":"MZ",
    "gn:dem":159,
    "gn:feature_class":"P",
    "gn:feature_code":"PPL",
    "gn:name":"Chingondo",
    "gn:population":0,
    "gn:timezone":"Africa/Maputo",
    "iso:country":"MZ",
    "wof:name":"Chingondo",
    "wof:placetype":"locality"
},
  "geometry": {"coordinates":[33.80056,-20.65611],"type":"Point"}
}