{
  "type": "Feature",
  "properties": {
    "gn:admin1_code":"3.0",
    "gn:asciiname":"Gustavo",
    "gn:country_code":"MZ",
    "gn:dem":106,
    "gn:feature_class":"P",
    "gn:feature_code":"PPL",
    "gn:name":"Gustavo",
    "gn:population":0,
    "gn:timezone":"Africa/Maputo",
    "iso:country":"MZ",
    "wof:name":"Gustavo",
    "wof:placetype":"locality"
},
  "geometry": {"coordinates":[34.64944000000001,-23.2625],"type":"Point"}
}