{
  "type": "Feature",
  "properties": {
    "gn:admin1_code":"1",
    "gn:asciiname":"Xixano",
    "gn:country_code":"MZ",
    "gn:dem":410,
    "gn:feature_class":"P",
    "gn:feature_code":"PPL",
    "gn:name":"Xixano",
    "gn:population":0,
    "gn:timezone":"Africa/Maputo",
    "iso:country":"MZ",
    "wof:name":"Xixano",
    "wof:placetype":"locality"
},
  "geometry": {"coordinates":[38.75722,-12.16917],"type":"Point"}
}