{
  "type": "Feature",
  "properties": {
    "gn:admin1_code":"1",
    "gn:asciiname":"Assimo",
    "gn:cc2":"MZ",
    "gn:country_code":"MZ",
    "gn:dem":104,
    "gn:feature_class":"P",
    "gn:feature_code":"PPL",
    "gn:name":"Assimo",
    "gn:population":0,
    "gn:timezone":"Africa/Maputo",
    "iso:country":"MZ",
    "name:und_x_variant":[
        "Assima",
        "Assimo"
    ],
    "wof:name":"Assimo",
    "wof:placetype":"locality"
},
  "geometry": {"coordinates":[39.74583,-12.07944],"type":"Point"}
}