{
  "type": "Feature",
  "properties": {
    "gn:admin1_code":"6",
    "gn:asciiname":"Muquela",
    "gn:cc2":"MZ",
    "gn:country_code":"MZ",
    "gn:dem":160,
    "gn:feature_class":"P",
    "gn:feature_code":"PPL",
    "gn:name":"Muquela",
    "gn:population":0,
    "gn:timezone":"Africa/Maputo",
    "iso:country":"MZ",
    "name:und_x_variant":[
        "Muguela",
        "Muquela"
    ],
    "wof:name":"Muquela",
    "wof:placetype":"locality"
},
  "geometry": {"coordinates":[39.17611,-15.8275],"type":"Point"}
}