{
  "type": "Feature",
  "properties": {
    "gn:admin1_code":"2.0",
    "gn:asciiname":"Induna Macale",
    "gn:country_code":"MZ",
    "gn:dem":50,
    "gn:feature_class":"P",
    "gn:feature_code":"PPL",
    "gn:name":"Induna Macale",
    "gn:population":0,
    "gn:timezone":"Africa/Maputo",
    "iso:country":"MZ",
    "wof:name":"Induna Macale",
    "wof:placetype":"locality"
},
  "geometry": {"coordinates":[33.38806,-24.17944],"type":"Point"}
}