{
  "type": "Feature",
  "properties": {
    "gn:admin1_code":"3",
    "gn:asciiname":"Julai",
    "gn:country_code":"MZ",
    "gn:dem":85,
    "gn:feature_class":"P",
    "gn:feature_code":"PPL",
    "gn:name":"Julai",
    "gn:population":0,
    "gn:timezone":"Africa/Maputo",
    "iso:country":"MZ",
    "wof:name":"Julai",
    "wof:placetype":"locality"
},
  "geometry": {"coordinates":[34.47944,-23.37222],"type":"Point"}
}