{
  "type": "Feature",
  "properties": {
    "gn:admin1_code":"5",
    "gn:asciiname":"Najiji",
    "gn:country_code":"MZ",
    "gn:dem":141,
    "gn:feature_class":"P",
    "gn:feature_code":"PPL",
    "gn:name":"Najiji",
    "gn:population":0,
    "gn:timezone":"Africa/Maputo",
    "iso:country":"MZ",
    "wof:name":"Najiji",
    "wof:placetype":"locality"
},
  "geometry": {"coordinates":[34.16917,-20.065],"type":"Point"}
}