{
  "type": "Feature",
  "properties": {
    "gn:admin1_code":"6.0",
    "gn:asciiname":"Sariela",
    "gn:country_code":"MZ",
    "gn:dem":425,
    "gn:feature_class":"P",
    "gn:feature_code":"PPL",
    "gn:name":"Sariela",
    "gn:population":0,
    "gn:timezone":"Africa/Maputo",
    "iso:country":"MZ",
    "wof:name":"Sariela",
    "wof:placetype":"locality"
},
  "geometry": {"coordinates":[38.86833,-15.23333],"type":"Point"}
}