{
  "type": "Feature",
  "properties": {
    "gn:admin1_code":"5",
    "gn:asciiname":"Macarate",
    "gn:country_code":"MZ",
    "gn:dem":283,
    "gn:feature_class":"P",
    "gn:feature_code":"PPL",
    "gn:name":"Macarate",
    "gn:population":0,
    "gn:timezone":"Africa/Maputo",
    "iso:country":"MZ",
    "wof:name":"Macarate",
    "wof:placetype":"locality"
},
  "geometry": {"coordinates":[33.77222,-20.46361],"type":"Point"}
}