{
  "type": "Feature",
  "properties": {
    "gn:admin1_code":"8.0",
    "gn:asciiname":"Polasi",
    "gn:country_code":"MZ",
    "gn:dem":250,
    "gn:feature_class":"P",
    "gn:feature_code":"PPL",
    "gn:name":"Pol\u00e1si",
    "gn:population":0,
    "gn:timezone":"Africa/Maputo",
    "iso:country":"MZ",
    "wof:name":"Polasi",
    "wof:placetype":"locality"
},
  "geometry": {"coordinates":[33.07694,-16.43278],"type":"Point"}
}