{
  "type": "Feature",
  "properties": {
    "gn:admin1_code":"8.0",
    "gn:asciiname":"Salumoni",
    "gn:country_code":"MZ",
    "gn:dem":933,
    "gn:feature_class":"P",
    "gn:feature_code":"PPL",
    "gn:name":"Salumoni",
    "gn:population":0,
    "gn:timezone":"Africa/Maputo",
    "iso:country":"MZ",
    "wof:name":"Salumoni",
    "wof:placetype":"locality"
},
  "geometry": {"coordinates":[30.9625,-15.04528],"type":"Point"}
}