{
  "type": "Feature",
  "properties": {
    "gn:admin1_code":"0",
    "gn:asciiname":"Muguonde",
    "gn:country_code":"MZ",
    "gn:dem":48,
    "gn:feature_class":"P",
    "gn:feature_code":"PPL",
    "gn:name":"Muguonde",
    "gn:population":0,
    "gn:timezone":"Africa/Maputo",
    "iso:country":"MZ",
    "wof:name":"Muguonde",
    "wof:placetype":"locality"
},
  "geometry": {"coordinates":[33.93333,-19.83333],"type":"Point"}
}