{
  "type": "Feature",
  "properties": {
    "gn:admin1_code":"5",
    "gn:asciiname":"Cavambiri",
    "gn:cc2":"MZ",
    "gn:country_code":"MZ",
    "gn:dem":54,
    "gn:feature_class":"P",
    "gn:feature_code":"PPL",
    "gn:name":"Cavambiri",
    "gn:population":0,
    "gn:timezone":"Africa/Maputo",
    "iso:country":"MZ",
    "name:und_x_variant":[
        "Pita",
        "Cavambiri"
    ],
    "wof:name":"Cavambiri",
    "wof:placetype":"locality"
},
  "geometry": {"coordinates":[34.93222,-17.23444],"type":"Point"}
}