{
  "type": "Feature",
  "properties": {
    "gn:admin1_code":"6",
    "gn:asciiname":"Catava",
    "gn:country_code":"MZ",
    "gn:dem":302,
    "gn:feature_class":"P",
    "gn:feature_code":"PPL",
    "gn:name":"Catava",
    "gn:population":0,
    "gn:timezone":"Africa/Maputo",
    "iso:country":"MZ",
    "wof:name":"Catava",
    "wof:placetype":"locality"
},
  "geometry": {"coordinates":[39.10444,-15.43333],"type":"Point"}
}