{
  "type": "Feature",
  "properties": {
    "gn:admin1_code":"3",
    "gn:asciiname":"J. Nhacule",
    "gn:cc2":"MZ",
    "gn:country_code":"MZ",
    "gn:dem":41,
    "gn:feature_class":"P",
    "gn:feature_code":"PPL",
    "gn:name":"J. Nhacule",
    "gn:population":0,
    "gn:timezone":"Africa/Maputo",
    "iso:country":"MZ",
    "name:und_x_variant":[
        "Ingale",
        "J. Nhacule"
    ],
    "wof:name":"J. Nhacule",
    "wof:placetype":"locality"
},
  "geometry": {"coordinates":[35.49472,-23.98139],"type":"Point"}
}