{
  "type": "Feature",
  "properties": {
    "gn:admin1_code":"4.0",
    "gn:asciiname":"Muvunja",
    "gn:country_code":"MZ",
    "gn:dem":30,
    "gn:feature_class":"P",
    "gn:feature_code":"PPL",
    "gn:name":"Muvunja",
    "gn:population":0,
    "gn:timezone":"Africa/Maputo",
    "iso:country":"MZ",
    "wof:name":"Muvunja",
    "wof:placetype":"locality"
},
  "geometry": {"coordinates":[32.53778,-25.99639],"type":"Point"}
}