{
  "type": "Feature",
  "properties": {
    "gn:admin1_code":"4",
    "gn:asciiname":"Muoi",
    "gn:country_code":"MZ",
    "gn:dem":147,
    "gn:feature_class":"P",
    "gn:feature_code":"PPL",
    "gn:name":"Muoi",
    "gn:population":0,
    "gn:timezone":"Africa/Maputo",
    "iso:country":"MZ",
    "wof:name":"Muoi",
    "wof:placetype":"locality"
},
  "geometry": {"coordinates":[32.07528,-24.45722],"type":"Point"}
}