{
  "type": "Feature",
  "properties": {
    "gn:admin1_code":"9",
    "gn:asciiname":"Majogue",
    "gn:country_code":"MZ",
    "gn:dem":225,
    "gn:feature_class":"P",
    "gn:feature_code":"PPL",
    "gn:name":"Maj\u00f3gu\u00e8",
    "gn:population":0,
    "gn:timezone":"Africa/Maputo",
    "iso:country":"MZ",
    "wof:name":"Majogue",
    "wof:placetype":"locality"
},
  "geometry": {"coordinates":[36.62056,-17.03472],"type":"Point"}
}