{
  "type": "Feature",
  "properties": {
    "gn:admin1_code":"7",
    "gn:asciiname":"Caquelele",
    "gn:country_code":"MZ",
    "gn:dem":744,
    "gn:feature_class":"P",
    "gn:feature_code":"PPL",
    "gn:name":"Caquel\u00eale",
    "gn:population":0,
    "gn:timezone":"Africa/Maputo",
    "iso:country":"MZ",
    "wof:name":"Caquelele",
    "wof:placetype":"locality"
},
  "geometry": {"coordinates":[36.11444,-15.22444],"type":"Point"}
}