{
  "type": "Feature",
  "properties": {
    "gn:admin1_code":"5",
    "gn:asciiname":"Alface",
    "gn:country_code":"MZ",
    "gn:dem":66,
    "gn:feature_class":"P",
    "gn:feature_code":"PPL",
    "gn:name":"Alface",
    "gn:population":0,
    "gn:timezone":"Africa/Maputo",
    "iso:country":"MZ",
    "wof:name":"Alface",
    "wof:placetype":"locality"
},
  "geometry": {"coordinates":[35.04222,-17.67833],"type":"Point"}
}