{
  "type": "Feature",
  "properties": {
    "gn:admin1_code":"3.0",
    "gn:asciiname":"Queme",
    "gn:country_code":"MZ",
    "gn:dem":152,
    "gn:feature_class":"P",
    "gn:feature_code":"PPL",
    "gn:name":"Queme",
    "gn:population":0,
    "gn:timezone":"Africa/Maputo",
    "iso:country":"MZ",
    "wof:name":"Queme",
    "wof:placetype":"locality"
},
  "geometry": {"coordinates":[35.36889,-23.37917],"type":"Point"}
}