{
  "type": "Feature",
  "properties": {
    "gn:admin1_code":"2",
    "gn:asciiname":"Mucai",
    "gn:country_code":"MZ",
    "gn:dem":51,
    "gn:feature_class":"P",
    "gn:feature_code":"PPL",
    "gn:name":"Mucai",
    "gn:population":0,
    "gn:timezone":"Africa/Maputo",
    "iso:country":"MZ",
    "wof:name":"Mucai",
    "wof:placetype":"locality"
},
  "geometry": {"coordinates":[33.66611,-23.905],"type":"Point"}
}