{
  "type": "Feature",
  "properties": {
    "gn:admin1_code":"4",
    "gn:asciiname":"Sao Gabriel das Dores",
    "gn:country_code":"MZ",
    "gn:dem":56,
    "gn:feature_class":"P",
    "gn:feature_code":"PPL",
    "gn:name":"S\u00e3o Gabriel das Dores",
    "gn:population":0,
    "gn:timezone":"Africa/Maputo",
    "iso:country":"MZ",
    "wof:name":"Sao Gabriel das Dores",
    "wof:placetype":"locality"
},
  "geometry": {"coordinates":[32.52833,-25.79306],"type":"Point"}
}