{
  "type": "Feature",
  "properties": {
    "gn:admin1_code":"7.0",
    "gn:asciiname":"Ziquenda",
    "gn:country_code":"MZ",
    "gn:dem":809,
    "gn:feature_class":"P",
    "gn:feature_code":"PPL",
    "gn:name":"Ziquenda",
    "gn:population":0,
    "gn:timezone":"Africa/Maputo",
    "iso:country":"MZ",
    "wof:name":"Ziquenda",
    "wof:placetype":"locality"
},
  "geometry": {"coordinates":[35.80778,-13.74861],"type":"Point"}
}