{
  "type": "Feature",
  "properties": {
    "gn:admin1_code":"9",
    "gn:asciiname":"Jumea",
    "gn:country_code":"MZ",
    "gn:dem":53,
    "gn:feature_class":"P",
    "gn:feature_code":"PPL",
    "gn:name":"Jumea",
    "gn:population":0,
    "gn:timezone":"Africa/Maputo",
    "iso:country":"MZ",
    "wof:name":"Jumea",
    "wof:placetype":"locality"
},
  "geometry": {"coordinates":[38.08694000000001,-17.03833],"type":"Point"}
}