{
  "type": "Feature",
  "properties": {
    "gn:admin1_code":"3",
    "gn:asciiname":"Regulo Machavela",
    "gn:cc2":"MZ",
    "gn:country_code":"MZ",
    "gn:dem":125,
    "gn:feature_class":"P",
    "gn:feature_code":"PPL",
    "gn:name":"R\u00e9gulo Machavela",
    "gn:population":0,
    "gn:timezone":"Africa/Maputo",
    "iso:country":"MZ",
    "name:und_x_variant":[
        "Machavela",
        "R\u00e9gulo Machavela"
    ],
    "wof:name":"Regulo Machavela",
    "wof:placetype":"locality"
},
  "geometry": {"coordinates":[35.12860999999999,-23.78917],"type":"Point"}
}