{
  "type": "Feature",
  "properties": {
    "gn:admin1_code":"1",
    "gn:asciiname":"Cambala",
    "gn:country_code":"MZ",
    "gn:dem":10,
    "gn:feature_class":"P",
    "gn:feature_code":"PPL",
    "gn:name":"Cambala",
    "gn:population":0,
    "gn:timezone":"Africa/Maputo",
    "iso:country":"MZ",
    "name:ceb_x_preferred":[
        "Cambala"
    ],
    "name:swe_x_preferred":[
        "Cambala"
    ],
    "name:war_x_preferred":[
        "Cambala"
    ],
    "wof:name":"Cambala",
    "wof:placetype":"locality"
},
  "geometry": {"coordinates":[40.56,-13.2825],"type":"Point"}
}