{
  "type": "Feature",
  "properties": {
    "gn:admin1_code":"7",
    "gn:asciiname":"Pacarre",
    "gn:country_code":"MZ",
    "gn:dem":436,
    "gn:feature_class":"P",
    "gn:feature_code":"PPL",
    "gn:name":"Pacarre",
    "gn:population":0,
    "gn:timezone":"Africa/Maputo",
    "iso:country":"MZ",
    "wof:name":"Pacarre",
    "wof:placetype":"locality"
},
  "geometry": {"coordinates":[37.6975,-14.27611],"type":"Point"}
}