{
  "type": "Feature",
  "properties": {
    "gn:admin1_code":"9.0",
    "gn:asciiname":"Tomodo",
    "gn:cc2":"MZ",
    "gn:country_code":"MZ",
    "gn:dem":12,
    "gn:feature_class":"P",
    "gn:feature_code":"PPL",
    "gn:name":"Tomodo",
    "gn:population":0,
    "gn:timezone":"Africa/Maputo",
    "iso:country":"MZ",
    "name:und_x_variant":[
        "Tum\u00f4do",
        "Tomodo"
    ],
    "wof:name":"Tomodo",
    "wof:placetype":"locality"
},
  "geometry": {"coordinates":[37.29417,-17.65889],"type":"Point"}
}