{
  "type": "Feature",
  "properties": {
    "gn:admin1_code":"2",
    "gn:asciiname":"Chefe Matangane",
    "gn:cc2":"MZ",
    "gn:country_code":"MZ",
    "gn:dem":70,
    "gn:feature_class":"P",
    "gn:feature_code":"PPL",
    "gn:name":"Chefe Matangane",
    "gn:population":0,
    "gn:timezone":"Africa/Maputo",
    "iso:country":"MZ",
    "name:und_x_variant":[
        "Matangane",
        "Chefe Matangane"
    ],
    "wof:name":"Chefe Matangane",
    "wof:placetype":"locality"
},
  "geometry": {"coordinates":[33.87722,-24.64611],"type":"Point"}
}