{
  "type": "Feature",
  "properties": {
    "gn:admin1_code":"8",
    "gn:asciiname":"Manguiza",
    "gn:country_code":"MZ",
    "gn:dem":870,
    "gn:feature_class":"P",
    "gn:feature_code":"PPL",
    "gn:name":"Manguiza",
    "gn:population":0,
    "gn:timezone":"Africa/Maputo",
    "iso:country":"MZ",
    "wof:name":"Manguiza",
    "wof:placetype":"locality"
},
  "geometry": {"coordinates":[31.70361,-15.16167],"type":"Point"}
}