{
  "type": "Feature",
  "properties": {
    "gn:admin1_code":"7",
    "gn:asciiname":"Aldeia Nauca",
    "gn:country_code":"MZ",
    "gn:dem":1267,
    "gn:feature_class":"P",
    "gn:feature_code":"PPL",
    "gn:name":"Aldeia Nauca",
    "gn:population":0,
    "gn:timezone":"Africa/Maputo",
    "iso:country":"MZ",
    "wof:name":"Aldeia Nauca",
    "wof:placetype":"locality"
},
  "geometry": {"coordinates":[35.21139,-13.22111],"type":"Point"}
}