{
  "type": "Feature",
  "properties": {
    "gn:admin1_code":"1",
    "gn:asciiname":"Puia Muene",
    "gn:country_code":"MZ",
    "gn:dem":328,
    "gn:feature_class":"P",
    "gn:feature_code":"PPL",
    "gn:name":"Puia Muene",
    "gn:population":0,
    "gn:timezone":"Africa/Maputo",
    "iso:country":"MZ",
    "wof:name":"Puia Muene",
    "wof:placetype":"locality"
},
  "geometry": {"coordinates":[39.11917,-13.85722],"type":"Point"}
}