{
  "type": "Feature",
  "properties": {
    "gn:admin1_code":"1",
    "gn:asciiname":"Pacora",
    "gn:country_code":"MZ",
    "gn:dem":207,
    "gn:feature_class":"P",
    "gn:feature_code":"PPL",
    "gn:name":"Pacora",
    "gn:population":0,
    "gn:timezone":"Africa/Maputo",
    "iso:country":"MZ",
    "name:ceb_x_preferred":[
        "Pacora"
    ],
    "name:fra_x_preferred":[
        "Pacora"
    ],
    "name:ita_x_preferred":[
        "Pacora"
    ],
    "name:jpn_x_preferred":[
        "\u30d1\u30b3\u30e9"
    ],
    "name:kat_x_preferred":[
        "\u10de\u10d0\u10d9\u10dd\u10e0\u10d0"
    ],
    "name:nld_x_preferred":[
        "Pacora"
    ],
    "name:pol_x_preferred":[
        "Pacora"
    ],
    "name:sco_x_preferred":[
        "Pacora"
    ],
    "name:spa_x_preferred":[
        "Pacora"
    ],
    "name:zho_x_preferred":[
        "\u5e15\u79d1\u62c9"
    ],
    "wof:name":"Pacora",
    "wof:placetype":"locality"
},
  "geometry": {"coordinates":[39.39111,-12.12944],"type":"Point"}
}