{
  "type": "Feature",
  "properties": {
    "gn:admin1_code":"6",
    "gn:asciiname":"John",
    "gn:country_code":"MZ",
    "gn:dem":474,
    "gn:feature_class":"P",
    "gn:feature_code":"PPL",
    "gn:name":"John",
    "gn:population":0,
    "gn:timezone":"Africa/Maputo",
    "iso:country":"MZ",
    "wof:name":"John",
    "wof:placetype":"locality"
},
  "geometry": {"coordinates":[37.89694,-14.51972],"type":"Point"}
}