{
  "type": "Feature",
  "properties": {
    "gn:admin1_code":"9",
    "gn:asciiname":"Rombo",
    "gn:country_code":"MZ",
    "gn:dem":345,
    "gn:feature_class":"P",
    "gn:feature_code":"PPL",
    "gn:name":"Rombo",
    "gn:population":0,
    "gn:timezone":"Africa/Maputo",
    "iso:country":"MZ",
    "wof:name":"Rombo",
    "wof:placetype":"locality"
},
  "geometry": {"coordinates":[35.61972,-16.57972],"type":"Point"}
}