{
  "type": "Feature",
  "properties": {
    "gn:admin1_code":"3",
    "gn:asciiname":"Guize",
    "gn:country_code":"MZ",
    "gn:dem":154,
    "gn:feature_class":"P",
    "gn:feature_code":"PPL",
    "gn:name":"Guize",
    "gn:population":0,
    "gn:timezone":"Africa/Maputo",
    "iso:country":"MZ",
    "wof:name":"Guize",
    "wof:placetype":"locality"
},
  "geometry": {"coordinates":[34.14667,-21.90778],"type":"Point"}
}