{
  "type": "Feature",
  "properties": {
    "gn:admin1_code":"4",
    "gn:asciiname":"Babalala",
    "gn:country_code":"MZ",
    "gn:dem":49,
    "gn:feature_class":"P",
    "gn:feature_code":"PPL",
    "gn:name":"Babalala",
    "gn:population":0,
    "gn:timezone":"Africa/Maputo",
    "iso:country":"MZ",
    "wof:name":"Babalala",
    "wof:placetype":"locality"
},
  "geometry": {"coordinates":[32.55278,-24.93222],"type":"Point"}
}