{
  "type": "Feature",
  "properties": {
    "gn:admin1_code":"8",
    "gn:asciiname":"Gerama",
    "gn:country_code":"MZ",
    "gn:dem":375,
    "gn:feature_class":"P",
    "gn:feature_code":"PPL",
    "gn:name":"Gerama",
    "gn:population":0,
    "gn:timezone":"Africa/Maputo",
    "iso:country":"MZ",
    "wof:name":"Gerama",
    "wof:placetype":"locality"
},
  "geometry": {"coordinates":[31.875,-15.80333],"type":"Point"}
}