{
  "type": "Feature",
  "properties": {
    "gn:admin1_code":"2",
    "gn:asciiname":"Javanhana",
    "gn:country_code":"MZ",
    "gn:dem":28,
    "gn:feature_class":"P",
    "gn:feature_code":"PPL",
    "gn:name":"Javanhana",
    "gn:population":0,
    "gn:timezone":"Africa/Maputo",
    "iso:country":"MZ",
    "wof:name":"Javanhana",
    "wof:placetype":"locality"
},
  "geometry": {"coordinates":[33.16417,-24.56028],"type":"Point"}
}