{
  "type": "Feature",
  "properties": {
    "gn:admin1_code":"3.0",
    "gn:asciiname":"G. Nhaume",
    "gn:country_code":"MZ",
    "gn:dem":57,
    "gn:feature_class":"P",
    "gn:feature_code":"PPL",
    "gn:name":"G. Nha\u00fame",
    "gn:population":0,
    "gn:timezone":"Africa/Maputo",
    "iso:country":"MZ",
    "wof:name":"G. Nhaume",
    "wof:placetype":"locality"
},
  "geometry": {"coordinates":[34.49444,-24.60333],"type":"Point"}
}