{
  "type": "Feature",
  "properties": {
    "gn:admin1_code":"0",
    "gn:asciiname":"Nhamacolomo",
    "gn:cc2":"MZ",
    "gn:country_code":"MZ",
    "gn:dem":180,
    "gn:feature_class":"P",
    "gn:feature_code":"PPL",
    "gn:name":"Nhamacolomo",
    "gn:population":0,
    "gn:timezone":"Africa/Maputo",
    "iso:country":"MZ",
    "name:und_x_variant":[
        "Nhamdsolonga",
        "Nhamacolomo"
    ],
    "wof:name":"Nhamacolomo",
    "wof:placetype":"locality"
},
  "geometry": {"coordinates":[34.43333,-18.16667],"type":"Point"}
}