{
  "type": "Feature",
  "properties": {
    "gn:admin1_code":"2",
    "gn:asciiname":"Mavaza",
    "gn:country_code":"MZ",
    "gn:dem":83,
    "gn:feature_class":"P",
    "gn:feature_code":"PPL",
    "gn:name":"Mavaza",
    "gn:population":0,
    "gn:timezone":"Africa/Maputo",
    "iso:country":"MZ",
    "wof:name":"Mavaza",
    "wof:placetype":"locality"
},
  "geometry": {"coordinates":[32.91194,-22.69556],"type":"Point"}
}