{
  "type": "Feature",
  "properties": {
    "gn:admin1_code":"9",
    "gn:asciiname":"Amice",
    "gn:country_code":"MZ",
    "gn:dem":264,
    "gn:feature_class":"P",
    "gn:feature_code":"PPL",
    "gn:name":"Amice",
    "gn:population":0,
    "gn:timezone":"Africa/Maputo",
    "iso:country":"MZ",
    "wof:name":"Amice",
    "wof:placetype":"locality"
},
  "geometry": {"coordinates":[38.09972,-16.23472000000001],"type":"Point"}
}