{
  "type": "Feature",
  "properties": {
    "gn:admin1_code":"1",
    "gn:asciiname":"Muissana",
    "gn:country_code":"MZ",
    "gn:dem":17,
    "gn:feature_class":"P",
    "gn:feature_code":"PPL",
    "gn:name":"Muissana",
    "gn:population":0,
    "gn:timezone":"Africa/Maputo",
    "iso:country":"MZ",
    "wof:name":"Muissana",
    "wof:placetype":"locality"
},
  "geometry": {"coordinates":[40.43944000000001,-11.74361],"type":"Point"}
}