{
  "type": "Feature",
  "properties": {
    "gn:admin1_code":"6",
    "gn:asciiname":"Muvuruta",
    "gn:country_code":"MZ",
    "gn:dem":158,
    "gn:feature_class":"P",
    "gn:feature_code":"PPL",
    "gn:name":"Muvuruta",
    "gn:population":0,
    "gn:timezone":"Africa/Maputo",
    "iso:country":"MZ",
    "wof:name":"Muvuruta",
    "wof:placetype":"locality"
},
  "geometry": {"coordinates":[39.62611,-15.81528],"type":"Point"}
}