{
  "type": "Feature",
  "properties": {
    "gn:admin1_code":"9",
    "gn:asciiname":"Regulo Metovola",
    "gn:country_code":"MZ",
    "gn:dem":793,
    "gn:feature_class":"P",
    "gn:feature_code":"PPL",
    "gn:name":"R\u00e9gulo Metovola",
    "gn:population":0,
    "gn:timezone":"Africa/Maputo",
    "iso:country":"MZ",
    "wof:name":"Regulo Metovola",
    "wof:placetype":"locality"
},
  "geometry": {"coordinates":[36.80111,-15.28889],"type":"Point"}
}