{
  "type": "Feature",
  "properties": {
    "gn:admin1_code":"6",
    "gn:asciiname":"Navila",
    "gn:country_code":"MZ",
    "gn:dem":292,
    "gn:feature_class":"P",
    "gn:feature_code":"PPL",
    "gn:name":"Navila",
    "gn:population":0,
    "gn:timezone":"Africa/Maputo",
    "iso:country":"MZ",
    "wof:name":"Navila",
    "wof:placetype":"locality"
},
  "geometry": {"coordinates":[39.83944,-14.03861],"type":"Point"}
}