{
  "type": "Feature",
  "properties": {
    "gn:admin1_code":"2.0",
    "gn:asciiname":"Chefe M'Bocho",
    "gn:country_code":"MZ",
    "gn:dem":24,
    "gn:feature_class":"P",
    "gn:feature_code":"PPL",
    "gn:name":"Chefe M\u2019Bocho",
    "gn:population":0,
    "gn:timezone":"Africa/Maputo",
    "iso:country":"MZ",
    "wof:name":"Chefe M'Bocho",
    "wof:placetype":"locality"
},
  "geometry": {"coordinates":[33.5725,-24.32639],"type":"Point"}
}