{
  "type": "Feature",
  "properties": {
    "gn:admin1_code":"3.0",
    "gn:asciiname":"Nhauaque",
    "gn:country_code":"MZ",
    "gn:dem":61,
    "gn:feature_class":"P",
    "gn:feature_code":"PPL",
    "gn:name":"Nha\u00faaque",
    "gn:population":0,
    "gn:timezone":"Africa/Maputo",
    "iso:country":"MZ",
    "wof:name":"Nhauaque",
    "wof:placetype":"locality"
},
  "geometry": {"coordinates":[35.00389000000001,-24.39306],"type":"Point"}
}