{
  "type": "Feature",
  "properties": {
    "gn:admin1_code":"1.0",
    "gn:asciiname":"Tutala",
    "gn:country_code":"MZ",
    "gn:dem":356,
    "gn:feature_class":"P",
    "gn:feature_code":"PPL",
    "gn:name":"Tutala",
    "gn:population":0,
    "gn:timezone":"Africa/Maputo",
    "iso:country":"MZ",
    "wof:name":"Tutala",
    "wof:placetype":"locality"
},
  "geometry": {"coordinates":[39.35611,-11.81111],"type":"Point"}
}