{
  "type": "Feature",
  "properties": {
    "gn:admin1_code":"5",
    "gn:asciiname":"Nhacuecha",
    "gn:country_code":"MZ",
    "gn:dem":42,
    "gn:feature_class":"P",
    "gn:feature_code":"PPL",
    "gn:name":"Nhacuecha",
    "gn:population":0,
    "gn:timezone":"Africa/Maputo",
    "iso:country":"MZ",
    "wof:name":"Nhacuecha",
    "wof:placetype":"locality"
},
  "geometry": {"coordinates":[35.10333,-17.64444],"type":"Point"}
}