{
  "type": "Feature",
  "properties": {
    "gn:admin1_code":"4",
    "gn:asciiname":"Debinduana",
    "gn:cc2":"MZ",
    "gn:country_code":"MZ",
    "gn:dem":62,
    "gn:feature_class":"P",
    "gn:feature_code":"PPL",
    "gn:name":"Debinduana",
    "gn:population":0,
    "gn:timezone":"Africa/Maputo",
    "iso:country":"MZ",
    "name:und_x_variant":[
        "Debinduane",
        "Debinduana"
    ],
    "wof:name":"Debinduana",
    "wof:placetype":"locality"
},
  "geometry": {"coordinates":[32.23860999999999,-26.43333],"type":"Point"}
}