{
  "type": "Feature",
  "properties": {
    "gn:admin1_code":"6",
    "gn:asciiname":"Muecua",
    "gn:country_code":"MZ",
    "gn:dem":225,
    "gn:feature_class":"P",
    "gn:feature_code":"PPL",
    "gn:name":"Muecua",
    "gn:population":0,
    "gn:timezone":"Africa/Maputo",
    "iso:country":"MZ",
    "wof:name":"Muecua",
    "wof:placetype":"locality"
},
  "geometry": {"coordinates":[39.33778,-15.55361],"type":"Point"}
}