{
  "type": "Feature",
  "properties": {
    "gn:admin1_code":"9.0",
    "gn:asciiname":"Randau",
    "gn:country_code":"MZ",
    "gn:dem":474,
    "gn:feature_class":"P",
    "gn:feature_code":"PPL",
    "gn:name":"Randau",
    "gn:population":0,
    "gn:timezone":"Africa/Maputo",
    "iso:country":"MZ",
    "wof:name":"Randau",
    "wof:placetype":"locality"
},
  "geometry": {"coordinates":[37.12056,-16.00806],"type":"Point"}
}