{
  "type": "Feature",
  "properties": {
    "gn:admin1_code":"0",
    "gn:asciiname":"Machambo",
    "gn:country_code":"MZ",
    "gn:dem":191,
    "gn:feature_class":"P",
    "gn:feature_code":"PPL",
    "gn:name":"Machambo",
    "gn:population":0,
    "gn:timezone":"Africa/Maputo",
    "iso:country":"MZ",
    "wof:name":"Machambo",
    "wof:placetype":"locality"
},
  "geometry": {"coordinates":[31.46667,-22.45],"type":"Point"}
}