{
  "type": "Feature",
  "properties": {
    "gn:admin1_code":"7",
    "gn:asciiname":"Nanlicha",
    "gn:cc2":"MZ",
    "gn:country_code":"MZ",
    "gn:dem":514,
    "gn:feature_class":"P",
    "gn:feature_code":"PPL",
    "gn:name":"Nanlicha",
    "gn:population":0,
    "gn:timezone":"Africa/Maputo",
    "iso:country":"MZ",
    "name:und_x_variant":[
        "Nanlixa",
        "Nanlicha"
    ],
    "wof:name":"Nanlicha",
    "wof:placetype":"locality"
},
  "geometry": {"coordinates":[37.69028,-12.88417],"type":"Point"}
}