{
  "type": "Feature",
  "properties": {
    "gn:admin1_code":"8",
    "gn:asciiname":"Gueza",
    "gn:country_code":"MZ",
    "gn:dem":1314,
    "gn:feature_class":"P",
    "gn:feature_code":"PPL",
    "gn:name":"Gueza",
    "gn:population":0,
    "gn:timezone":"Africa/Maputo",
    "iso:country":"MZ",
    "wof:name":"Gueza",
    "wof:placetype":"locality"
},
  "geometry": {"coordinates":[34.11583,-14.45417],"type":"Point"}
}