{
  "type": "Feature",
  "properties": {
    "gn:admin1_code":"1",
    "gn:asciiname":"Chefe Vita",
    "gn:country_code":"MZ",
    "gn:dem":209,
    "gn:feature_class":"P",
    "gn:feature_code":"PPL",
    "gn:name":"Chefe Vita",
    "gn:population":0,
    "gn:timezone":"Africa/Maputo",
    "iso:country":"MZ",
    "wof:name":"Chefe Vita",
    "wof:placetype":"locality"
},
  "geometry": {"coordinates":[39.95194,-13.41417],"type":"Point"}
}