{
  "type": "Feature",
  "properties": {
    "gn:admin1_code":"9.0",
    "gn:asciiname":"Zangarote",
    "gn:country_code":"MZ",
    "gn:dem":22,
    "gn:feature_class":"P",
    "gn:feature_code":"PPL",
    "gn:name":"Zangarote",
    "gn:population":0,
    "gn:timezone":"Africa/Maputo",
    "iso:country":"MZ",
    "wof:name":"Zangarote",
    "wof:placetype":"locality"
},
  "geometry": {"coordinates":[35.80611,-17.93722],"type":"Point"}
}