{
  "type": "Feature",
  "properties": {
    "gn:admin1_code":"1",
    "gn:asciiname":"Regulo Mepima",
    "gn:cc2":"MZ",
    "gn:country_code":"MZ",
    "gn:dem":417,
    "gn:feature_class":"P",
    "gn:feature_code":"PPL",
    "gn:name":"R\u00e9gulo Mepima",
    "gn:population":0,
    "gn:timezone":"Africa/Maputo",
    "iso:country":"MZ",
    "name:und_x_variant":[
        "Mepima",
        "R\u00e9gulo Mepima"
    ],
    "wof:name":"Regulo Mepima",
    "wof:placetype":"locality"
},
  "geometry": {"coordinates":[39.56056,-13.02278],"type":"Point"}
}