{
  "type": "Feature",
  "properties": {
    "gn:admin1_code":"10",
    "gn:asciiname":"Messangaze",
    "gn:cc2":"MZ",
    "gn:country_code":"MZ",
    "gn:dem":604,
    "gn:feature_class":"P",
    "gn:feature_code":"PPL",
    "gn:name":"Messangaze",
    "gn:population":0,
    "gn:timezone":"Africa/Maputo",
    "iso:country":"MZ",
    "name:und_x_variant":[
        "Messangate",
        "Messangaze"
    ],
    "wof:name":"Messangaze",
    "wof:placetype":"locality"
},
  "geometry": {"coordinates":[33.62917,-17.445],"type":"Point"}
}