{
  "type": "Feature",
  "properties": {
    "gn:admin1_code":"9",
    "gn:asciiname":"Belua",
    "gn:country_code":"MZ",
    "gn:dem":649,
    "gn:feature_class":"P",
    "gn:feature_code":"PPL",
    "gn:name":"Belua",
    "gn:population":0,
    "gn:timezone":"Africa/Maputo",
    "iso:country":"MZ",
    "wof:name":"Belua",
    "wof:placetype":"locality"
},
  "geometry": {"coordinates":[35.79833,-16.18806],"type":"Point"}
}