{
  "type": "Feature",
  "properties": {
    "gn:admin1_code":"3",
    "gn:asciiname":"G. Chivangue",
    "gn:cc2":"MZ",
    "gn:country_code":"MZ",
    "gn:dem":61,
    "gn:feature_class":"P",
    "gn:feature_code":"PPL",
    "gn:name":"G. Chivangue",
    "gn:population":0,
    "gn:timezone":"Africa/Maputo",
    "iso:country":"MZ",
    "name:und_x_variant":[
        "Filipe",
        "G. Chivangue"
    ],
    "wof:name":"G. Chivangue",
    "wof:placetype":"locality"
},
  "geometry": {"coordinates":[34.54583,-24.57],"type":"Point"}
}