{
  "type": "Feature",
  "properties": {
    "gn:admin1_code":"7",
    "gn:asciiname":"Amurri",
    "gn:country_code":"MZ",
    "gn:dem":520,
    "gn:feature_class":"P",
    "gn:feature_code":"PPL",
    "gn:name":"Amurri",
    "gn:population":0,
    "gn:timezone":"Africa/Maputo",
    "iso:country":"MZ",
    "wof:name":"Amurri",
    "wof:placetype":"locality"
},
  "geometry": {"coordinates":[37.44,-14.3375],"type":"Point"}
}