{
  "type": "Feature",
  "properties": {
    "gn:admin1_code":"1",
    "gn:asciiname":"Chefe Chachia",
    "gn:country_code":"MZ",
    "gn:dem":264,
    "gn:feature_class":"P",
    "gn:feature_code":"PPL",
    "gn:name":"Chefe Chachia",
    "gn:population":0,
    "gn:timezone":"Africa/Maputo",
    "iso:country":"MZ",
    "wof:name":"Chefe Chachia",
    "wof:placetype":"locality"
},
  "geometry": {"coordinates":[39.50556,-13.73722],"type":"Point"}
}