{
  "type": "Feature",
  "properties": {
    "gn:admin1_code":"6",
    "gn:asciiname":"Casa Jagu",
    "gn:country_code":"MZ",
    "gn:dem":164,
    "gn:feature_class":"P",
    "gn:feature_code":"PPL",
    "gn:name":"Casa Jagu",
    "gn:population":0,
    "gn:timezone":"Africa/Maputo",
    "iso:country":"MZ",
    "wof:name":"Casa Jagu",
    "wof:placetype":"locality"
},
  "geometry": {"coordinates":[40.51806,-14.34056],"type":"Point"}
}