{
  "type": "Feature",
  "properties": {
    "gn:admin1_code":"1",
    "gn:asciiname":"Nantipe",
    "gn:country_code":"MZ",
    "gn:dem":206,
    "gn:feature_class":"P",
    "gn:feature_code":"PPL",
    "gn:name":"Nantipe",
    "gn:population":0,
    "gn:timezone":"Africa/Maputo",
    "iso:country":"MZ",
    "wof:name":"Nantipe",
    "wof:placetype":"locality"
},
  "geometry": {"coordinates":[40.195,-12.24583],"type":"Point"}
}