{
  "type": "Feature",
  "properties": {
    "gn:admin1_code":"9",
    "gn:asciiname":"Ramos",
    "gn:country_code":"MZ",
    "gn:dem":760,
    "gn:feature_class":"P",
    "gn:feature_code":"PPL",
    "gn:name":"Ramos",
    "gn:population":0,
    "gn:timezone":"Africa/Maputo",
    "iso:country":"MZ",
    "name:ces_x_preferred":[
        "Ramos"
    ],
    "name:fin_x_preferred":[
        "Ramos"
    ],
    "name:lav_x_preferred":[
        "Ramos"
    ],
    "name:pol_x_preferred":[
        "Ramos"
    ],
    "name:spa_x_preferred":[
        "Ramos"
    ],
    "name:ukr_x_preferred":[
        "\u0420\u0430\u043c\u043e\u0441"
    ],
    "wof:name":"Ramos",
    "wof:placetype":"locality"
},
  "geometry": {"coordinates":[37.51722,-15.3225],"type":"Point"}
}