{
  "type": "Feature",
  "properties": {
    "gn:admin1_code":"3.0",
    "gn:asciiname":"Cabo F. Nhanale",
    "gn:country_code":"MZ",
    "gn:dem":31,
    "gn:feature_class":"P",
    "gn:feature_code":"PPL",
    "gn:name":"Cabo F. Nhanale",
    "gn:population":0,
    "gn:timezone":"Africa/Maputo",
    "iso:country":"MZ",
    "wof:name":"Cabo F. Nhanale",
    "wof:placetype":"locality"
},
  "geometry": {"coordinates":[35.38139,-23.99694],"type":"Point"}
}