{
  "type": "Feature",
  "properties": {
    "gn:admin1_code":"9",
    "gn:asciiname":"Mepulula",
    "gn:cc2":"MZ",
    "gn:country_code":"MZ",
    "gn:dem":256,
    "gn:feature_class":"P",
    "gn:feature_code":"PPL",
    "gn:name":"Mepulula",
    "gn:population":0,
    "gn:timezone":"Africa/Maputo",
    "iso:country":"MZ",
    "name:und_x_variant":[
        "Impulula",
        "Mepulula"
    ],
    "wof:name":"Mepulula",
    "wof:placetype":"locality"
},
  "geometry": {"coordinates":[37.07917,-16.50361],"type":"Point"}
}