{
  "type": "Feature",
  "properties": {
    "gn:admin1_code":"3.0",
    "gn:asciiname":"Uanesselane",
    "gn:country_code":"MZ",
    "gn:dem":119,
    "gn:feature_class":"P",
    "gn:feature_code":"PPL",
    "gn:name":"Uanesselane",
    "gn:population":0,
    "gn:timezone":"Africa/Maputo",
    "iso:country":"MZ",
    "wof:name":"Uanesselane",
    "wof:placetype":"locality"
},
  "geometry": {"coordinates":[34.82083,-22.30417000000001],"type":"Point"}
}