{
  "type": "Feature",
  "properties": {
    "gn:admin1_code":"5",
    "gn:asciiname":"Amusse",
    "gn:country_code":"MZ",
    "gn:dem":235,
    "gn:feature_class":"P",
    "gn:feature_code":"PPL",
    "gn:name":"Amusse",
    "gn:population":0,
    "gn:timezone":"Africa/Maputo",
    "iso:country":"MZ",
    "wof:name":"Amusse",
    "wof:placetype":"locality"
},
  "geometry": {"coordinates":[33.69528,-20.40889],"type":"Point"}
}