{
  "type": "Feature",
  "properties": {
    "gn:admin1_code":"4",
    "gn:asciiname":"Chefe Macassane",
    "gn:country_code":"MZ",
    "gn:dem":46,
    "gn:feature_class":"P",
    "gn:feature_code":"PPL",
    "gn:name":"Chefe Macassane",
    "gn:population":0,
    "gn:timezone":"Africa/Maputo",
    "iso:country":"MZ",
    "wof:name":"Chefe Macassane",
    "wof:placetype":"locality"
},
  "geometry": {"coordinates":[32.605,-26.42111],"type":"Point"}
}