{
  "type": "Feature",
  "properties": {
    "gn:admin1_code":"3",
    "gn:asciiname":"Nhacundela",
    "gn:cc2":"MZ",
    "gn:country_code":"MZ",
    "gn:dem":40,
    "gn:feature_class":"P",
    "gn:feature_code":"PPL",
    "gn:name":"Nhacundela",
    "gn:population":0,
    "gn:timezone":"Africa/Maputo",
    "iso:country":"MZ",
    "name:und_x_variant":[
        "Inhacondela",
        "Nhacundela"
    ],
    "wof:name":"Nhacundela",
    "wof:placetype":"locality"
},
  "geometry": {"coordinates":[34.97833,-24.51389],"type":"Point"}
}