{
  "type": "Feature",
  "properties": {
    "gn:admin1_code":"6.0",
    "gn:asciiname":"Zauela",
    "gn:country_code":"MZ",
    "gn:dem":207,
    "gn:feature_class":"P",
    "gn:feature_code":"PPL",
    "gn:name":"Zauela",
    "gn:population":0,
    "gn:timezone":"Africa/Maputo",
    "iso:country":"MZ",
    "wof:name":"Zauela",
    "wof:placetype":"locality"
},
  "geometry": {"coordinates":[39.97861,-15.06056],"type":"Point"}
}