{
  "type": "Feature",
  "properties": {
    "gn:admin1_code":"1",
    "gn:asciiname":"Alotancomba",
    "gn:country_code":"MZ",
    "gn:dem":736,
    "gn:feature_class":"P",
    "gn:feature_code":"PPL",
    "gn:name":"Alotancomba",
    "gn:population":0,
    "gn:timezone":"Africa/Maputo",
    "iso:country":"MZ",
    "wof:name":"Alotancomba",
    "wof:placetype":"locality"
},
  "geometry": {"coordinates":[39.68722,-11.78667],"type":"Point"}
}