{
  "type": "Feature",
  "properties": {
    "gn:admin1_code":"10",
    "gn:asciiname":"Maquiua",
    "gn:country_code":"MZ",
    "gn:dem":590,
    "gn:feature_class":"P",
    "gn:feature_code":"PPL",
    "gn:name":"Maquiua",
    "gn:population":0,
    "gn:timezone":"Africa/Maputo",
    "iso:country":"MZ",
    "name:por_x_preferred":[
        "Maquiua"
    ],
    "wof:name":"Maquiua",
    "wof:placetype":"locality"
},
  "geometry": {"coordinates":[32.95194,-20.27222],"type":"Point"}
}