{
  "type": "Feature",
  "properties": {
    "gn:admin1_code":"8",
    "gn:asciiname":"Candedza",
    "gn:country_code":"MZ",
    "gn:dem":410,
    "gn:feature_class":"P",
    "gn:feature_code":"PPL",
    "gn:name":"Candedza",
    "gn:population":0,
    "gn:timezone":"Africa/Maputo",
    "iso:country":"MZ",
    "wof:name":"Candedza",
    "wof:placetype":"locality"
},
  "geometry": {"coordinates":[33.79444,-15.52833],"type":"Point"}
}