{
  "type": "Feature",
  "properties": {
    "gn:admin1_code":"3.0",
    "gn:asciiname":"Silva",
    "gn:country_code":"MZ",
    "gn:dem":47,
    "gn:feature_class":"P",
    "gn:feature_code":"PPL",
    "gn:name":"Silva",
    "gn:population":0,
    "gn:timezone":"Africa/Maputo",
    "iso:country":"MZ",
    "wof:name":"Silva",
    "wof:placetype":"locality"
},
  "geometry": {"coordinates":[35.20917,-22.27361],"type":"Point"}
}