{
  "type": "Feature",
  "properties": {
    "gn:admin1_code":"3",
    "gn:asciiname":"Maachule",
    "gn:country_code":"MZ",
    "gn:dem":54,
    "gn:feature_class":"P",
    "gn:feature_code":"PPL",
    "gn:name":"Maachule",
    "gn:population":0,
    "gn:timezone":"Africa/Maputo",
    "iso:country":"MZ",
    "wof:name":"Maachule",
    "wof:placetype":"locality"
},
  "geometry": {"coordinates":[34.99528,-21.97],"type":"Point"}
}