{
  "type": "Feature",
  "properties": {
    "gn:admin1_code":"8",
    "gn:asciiname":"Chimiane",
    "gn:country_code":"MZ",
    "gn:dem":374,
    "gn:feature_class":"P",
    "gn:feature_code":"PPL",
    "gn:name":"Chimiane",
    "gn:population":0,
    "gn:timezone":"Africa/Maputo",
    "iso:country":"MZ",
    "wof:name":"Chimiane",
    "wof:placetype":"locality"
},
  "geometry": {"coordinates":[32.825,-15.41444],"type":"Point"}
}