{
  "type": "Feature",
  "properties": {
    "gn:admin1_code":"6",
    "gn:asciiname":"Regulo Morrola",
    "gn:cc2":"MZ",
    "gn:country_code":"MZ",
    "gn:dem":196,
    "gn:feature_class":"P",
    "gn:feature_code":"PPL",
    "gn:name":"R\u00e9gulo Morrola",
    "gn:population":0,
    "gn:timezone":"Africa/Maputo",
    "iso:country":"MZ",
    "name:und_x_variant":[
        "Morola",
        "R\u00e9gulo Morrola"
    ],
    "wof:name":"Regulo Morrola",
    "wof:placetype":"locality"
},
  "geometry": {"coordinates":[40.33306,-13.85417],"type":"Point"}
}