{
  "type": "Feature",
  "properties": {
    "gn:admin1_code":"3.0",
    "gn:asciiname":"Sevanetine",
    "gn:country_code":"MZ",
    "gn:dem":105,
    "gn:feature_class":"P",
    "gn:feature_code":"PPL",
    "gn:name":"S\u00e9vanetine",
    "gn:population":0,
    "gn:timezone":"Africa/Maputo",
    "iso:country":"MZ",
    "wof:name":"Sevanetine",
    "wof:placetype":"locality"
},
  "geometry": {"coordinates":[34.16806,-23.26361],"type":"Point"}
}