{
  "type": "Feature",
  "properties": {
    "gn:admin1_code":"9",
    "gn:asciiname":"Regulo Lioma",
    "gn:country_code":"MZ",
    "gn:dem":670,
    "gn:feature_class":"P",
    "gn:feature_code":"PPL",
    "gn:name":"R\u00e9gulo Lioma",
    "gn:population":0,
    "gn:timezone":"Africa/Maputo",
    "iso:country":"MZ",
    "wof:name":"Regulo Lioma",
    "wof:placetype":"locality"
},
  "geometry": {"coordinates":[36.82,-15.12889],"type":"Point"}
}