{
  "type": "Feature",
  "properties": {
    "gn:admin1_code":"6",
    "gn:asciiname":"Mocassula",
    "gn:country_code":"MZ",
    "gn:dem":620,
    "gn:feature_class":"P",
    "gn:feature_code":"PPL",
    "gn:name":"Mocassula",
    "gn:population":0,
    "gn:timezone":"Africa/Maputo",
    "iso:country":"MZ",
    "wof:name":"Mocassula",
    "wof:placetype":"locality"
},
  "geometry": {"coordinates":[37.59639,-14.86278],"type":"Point"}
}