{
  "type": "Feature",
  "properties": {
    "gn:admin1_code":"2.0",
    "gn:asciiname":"Macaiane",
    "gn:country_code":"MZ",
    "gn:dem":84,
    "gn:feature_class":"P",
    "gn:feature_code":"PPL",
    "gn:name":"Macaiane",
    "gn:population":0,
    "gn:timezone":"Africa/Maputo",
    "iso:country":"MZ",
    "wof:name":"Macaiane",
    "wof:placetype":"locality"
},
  "geometry": {"coordinates":[32.94694,-23.58833],"type":"Point"}
}