{
  "type": "Feature",
  "properties": {
    "gn:admin1_code":"10",
    "gn:asciiname":"M'panza",
    "gn:country_code":"MZ",
    "gn:dem":568,
    "gn:feature_class":"P",
    "gn:feature_code":"PPL",
    "gn:name":"M\u2019panza",
    "gn:population":0,
    "gn:timezone":"Africa/Maputo",
    "iso:country":"MZ",
    "wof:name":"M'panza",
    "wof:placetype":"locality"
},
  "geometry": {"coordinates":[33.32833,-18.13],"type":"Point"}
}