{
  "type": "Feature",
  "properties": {
    "gn:admin1_code":"9",
    "gn:asciiname":"Muenhe",
    "gn:country_code":"MZ",
    "gn:dem":731,
    "gn:feature_class":"P",
    "gn:feature_code":"PPL",
    "gn:name":"Muenhe",
    "gn:population":0,
    "gn:timezone":"Africa/Maputo",
    "iso:country":"MZ",
    "wof:name":"Muenhe",
    "wof:placetype":"locality"
},
  "geometry": {"coordinates":[36.16167,-15.74639],"type":"Point"}
}