{
  "type": "Feature",
  "properties": {
    "gn:admin1_code":"6.0",
    "gn:asciiname":"Vaossa",
    "gn:country_code":"MZ",
    "gn:dem":107,
    "gn:feature_class":"P",
    "gn:feature_code":"PPL",
    "gn:name":"Vaossa",
    "gn:population":0,
    "gn:timezone":"Africa/Maputo",
    "iso:country":"MZ",
    "wof:name":"Vaossa",
    "wof:placetype":"locality"
},
  "geometry": {"coordinates":[40.44444,-13.87833],"type":"Point"}
}