{
  "type": "Feature",
  "properties": {
    "gn:admin1_code":"7",
    "gn:asciiname":"Juma",
    "gn:country_code":"MZ",
    "gn:dem":713,
    "gn:feature_class":"P",
    "gn:feature_code":"PPL",
    "gn:name":"Juma",
    "gn:population":0,
    "gn:timezone":"Africa/Maputo",
    "iso:country":"MZ",
    "wof:name":"Juma",
    "wof:placetype":"locality"
},
  "geometry": {"coordinates":[35.9375,-13.97361],"type":"Point"}
}