{
  "type": "Feature",
  "properties": {
    "gn:admin1_code":"9",
    "gn:asciiname":"Napeu",
    "gn:country_code":"MZ",
    "gn:dem":516,
    "gn:feature_class":"P",
    "gn:feature_code":"PPL",
    "gn:name":"Nap\u00e9u",
    "gn:population":0,
    "gn:timezone":"Africa/Maputo",
    "iso:country":"MZ",
    "wof:name":"Napeu",
    "wof:placetype":"locality"
},
  "geometry": {"coordinates":[37.36667,-15.80278],"type":"Point"}
}