{
  "type": "Feature",
  "properties": {
    "gn:admin1_code":"10.0",
    "gn:asciiname":"Tombatia",
    "gn:cc2":"MZ",
    "gn:country_code":"MZ",
    "gn:dem":695,
    "gn:feature_class":"P",
    "gn:feature_code":"PPL",
    "gn:name":"Tombatia",
    "gn:population":0,
    "gn:timezone":"Africa/Maputo",
    "iso:country":"MZ",
    "name:und_x_variant":[
        "Tombotia",
        "Tombatia"
    ],
    "wof:name":"Tombatia",
    "wof:placetype":"locality"
},
  "geometry": {"coordinates":[33.00972,-18.70806],"type":"Point"}
}