{
  "type": "Feature",
  "properties": {
    "gn:admin1_code":"3",
    "gn:asciiname":"Muchacha",
    "gn:country_code":"MZ",
    "gn:dem":183,
    "gn:feature_class":"P",
    "gn:feature_code":"PPL",
    "gn:name":"Muchacha",
    "gn:population":0,
    "gn:timezone":"Africa/Maputo",
    "iso:country":"MZ",
    "wof:name":"Muchacha",
    "wof:placetype":"locality"
},
  "geometry": {"coordinates":[34.22278,-21.93306],"type":"Point"}
}