{
  "type": "Feature",
  "properties": {
    "gn:admin1_code":"6.0",
    "gn:asciiname":"Tarrua",
    "gn:country_code":"MZ",
    "gn:dem":433,
    "gn:feature_class":"P",
    "gn:feature_code":"PPL",
    "gn:name":"Tarrua",
    "gn:population":0,
    "gn:timezone":"Africa/Maputo",
    "iso:country":"MZ",
    "wof:name":"Tarrua",
    "wof:placetype":"locality"
},
  "geometry": {"coordinates":[38.39028,-14.53444],"type":"Point"}
}