{
  "type": "Feature",
  "properties": {
    "gn:admin1_code":"10.0",
    "gn:asciiname":"Sabandare",
    "gn:country_code":"MZ",
    "gn:dem":91,
    "gn:feature_class":"P",
    "gn:feature_code":"PPL",
    "gn:name":"Sabandare",
    "gn:population":0,
    "gn:timezone":"Africa/Maputo",
    "iso:country":"MZ",
    "wof:name":"Sabandare",
    "wof:placetype":"locality"
},
  "geometry": {"coordinates":[34.42139,-16.75556],"type":"Point"}
}