{
  "type": "Feature",
  "properties": {
    "gn:admin1_code":"0.0",
    "gn:asciiname":"Uncualo",
    "gn:country_code":"MZ",
    "gn:dem":892,
    "gn:feature_class":"P",
    "gn:feature_code":"PPL",
    "gn:name":"Uncualo",
    "gn:population":0,
    "gn:timezone":"Africa/Maputo",
    "iso:country":"MZ",
    "wof:name":"Uncualo",
    "wof:placetype":"locality"
},
  "geometry": {"coordinates":[31.23333,-14.98333],"type":"Point"}
}