{
  "type": "Feature",
  "properties": {
    "gn:admin1_code":"1",
    "gn:asciiname":"Muade",
    "gn:country_code":"MZ",
    "gn:dem":717,
    "gn:feature_class":"P",
    "gn:feature_code":"PPL",
    "gn:name":"Muade",
    "gn:population":0,
    "gn:timezone":"Africa/Maputo",
    "iso:country":"MZ",
    "wof:name":"Muade",
    "wof:placetype":"locality"
},
  "geometry": {"coordinates":[39.57361,-11.44667],"type":"Point"}
}