{
  "type": "Feature",
  "properties": {
    "gn:admin1_code":"9",
    "gn:asciiname":"Mucanheia",
    "gn:country_code":"MZ",
    "gn:dem":404,
    "gn:feature_class":"P",
    "gn:feature_code":"PPL",
    "gn:name":"Mucanheia",
    "gn:population":0,
    "gn:timezone":"Africa/Maputo",
    "iso:country":"MZ",
    "wof:name":"Mucanheia",
    "wof:placetype":"locality"
},
  "geometry": {"coordinates":[37.66139,-15.9625],"type":"Point"}
}