{
  "type": "Feature",
  "properties": {
    "gn:admin1_code":"1",
    "gn:asciiname":"Namuede",
    "gn:country_code":"MZ",
    "gn:dem":538,
    "gn:feature_class":"P",
    "gn:feature_code":"PPL",
    "gn:name":"Namuede",
    "gn:population":0,
    "gn:timezone":"Africa/Maputo",
    "iso:country":"MZ",
    "wof:name":"Namuede",
    "wof:placetype":"locality"
},
  "geometry": {"coordinates":[39.66278,-11.36361],"type":"Point"}
}