{
  "type": "Feature",
  "properties": {
    "gn:admin1_code":"2.0",
    "gn:asciiname":"Mamade",
    "gn:country_code":"MZ",
    "gn:dem":57,
    "gn:feature_class":"P",
    "gn:feature_code":"PPL",
    "gn:name":"Mamade",
    "gn:population":0,
    "gn:timezone":"Africa/Maputo",
    "iso:country":"MZ",
    "wof:name":"Mamade",
    "wof:placetype":"locality"
},
  "geometry": {"coordinates":[33.84028,-24.61528],"type":"Point"}
}