{
  "type": "Feature",
  "properties": {
    "gn:admin1_code":"8.0",
    "gn:asciiname":"Tesoura",
    "gn:country_code":"MZ",
    "gn:dem":336,
    "gn:feature_class":"P",
    "gn:feature_code":"PPL",
    "gn:name":"Tesoura",
    "gn:population":0,
    "gn:timezone":"Africa/Maputo",
    "iso:country":"MZ",
    "wof:name":"Tesoura",
    "wof:placetype":"locality"
},
  "geometry": {"coordinates":[33.47722,-15.82972],"type":"Point"}
}