{
  "type": "Feature",
  "properties": {
    "gn:admin1_code":"8",
    "gn:asciiname":"Muririma",
    "gn:country_code":"MZ",
    "gn:dem":1120,
    "gn:feature_class":"P",
    "gn:feature_code":"PPL",
    "gn:name":"Muririma",
    "gn:population":0,
    "gn:timezone":"Africa/Maputo",
    "iso:country":"MZ",
    "wof:name":"Muririma",
    "wof:placetype":"locality"
},
  "geometry": {"coordinates":[33.69444,-14.85111],"type":"Point"}
}