{
  "type": "Feature",
  "properties": {
    "gn:admin1_code":"9",
    "gn:asciiname":"Messame",
    "gn:country_code":"MZ",
    "gn:dem":212,
    "gn:feature_class":"P",
    "gn:feature_code":"PPL",
    "gn:name":"Messame",
    "gn:population":0,
    "gn:timezone":"Africa/Maputo",
    "iso:country":"MZ",
    "wof:name":"Messame",
    "wof:placetype":"locality"
},
  "geometry": {"coordinates":[37.90111,-16.57944],"type":"Point"}
}