{
  "type": "Feature",
  "properties": {
    "gn:admin1_code":"3.0",
    "gn:asciiname":"Senda",
    "gn:country_code":"MZ",
    "gn:dem":136,
    "gn:feature_class":"P",
    "gn:feature_code":"PPL",
    "gn:name":"Senda",
    "gn:population":0,
    "gn:timezone":"Africa/Maputo",
    "iso:country":"MZ",
    "wof:name":"Senda",
    "wof:placetype":"locality"
},
  "geometry": {"coordinates":[34.79139,-22.33722],"type":"Point"}
}