{
  "type": "Feature",
  "properties": {
    "gn:admin1_code":"9",
    "gn:asciiname":"Regulo Amela",
    "gn:country_code":"MZ",
    "gn:dem":137,
    "gn:feature_class":"P",
    "gn:feature_code":"PPL",
    "gn:name":"R\u00e9gulo Amela",
    "gn:population":0,
    "gn:timezone":"Africa/Maputo",
    "iso:country":"MZ",
    "wof:name":"Regulo Amela",
    "wof:placetype":"locality"
},
  "geometry": {"coordinates":[38.90889,-16.22833],"type":"Point"}
}