{
  "type": "Feature",
  "properties": {
    "gn:admin1_code":"6",
    "gn:asciiname":"Namiroa",
    "gn:cc2":"MZ",
    "gn:country_code":"MZ",
    "gn:dem":345,
    "gn:feature_class":"P",
    "gn:feature_code":"PPL",
    "gn:name":"Namir\u00f4a",
    "gn:population":0,
    "gn:timezone":"Africa/Maputo",
    "iso:country":"MZ",
    "name:und_x_variant":[
        "Nameneva",
        "Namir\u00f4a"
    ],
    "wof:name":"Namiroa",
    "wof:placetype":"locality"
},
  "geometry": {"coordinates":[39.45,-14.06306],"type":"Point"}
}