{
  "type": "Feature",
  "properties": {
    "gn:admin1_code":"10",
    "gn:asciiname":"Dabassoa",
    "gn:country_code":"MZ",
    "gn:dem":450,
    "gn:feature_class":"P",
    "gn:feature_code":"PPL",
    "gn:name":"Dabass\u00f4a",
    "gn:population":0,
    "gn:timezone":"Africa/Maputo",
    "iso:country":"MZ",
    "wof:name":"Dabassoa",
    "wof:placetype":"locality"
},
  "geometry": {"coordinates":[34.11528,-17.62167],"type":"Point"}
}