{
  "type": "Feature",
  "properties": {
    "gn:admin1_code":"1",
    "gn:asciiname":"Maiongo",
    "gn:country_code":"MZ",
    "gn:dem":548,
    "gn:feature_class":"P",
    "gn:feature_code":"PPL",
    "gn:name":"Maiongo",
    "gn:population":0,
    "gn:timezone":"Africa/Maputo",
    "iso:country":"MZ",
    "wof:name":"Maiongo",
    "wof:placetype":"locality"
},
  "geometry": {"coordinates":[39.53167,-11.32861],"type":"Point"}
}