{
  "type": "Feature",
  "properties": {
    "gn:admin1_code":"6",
    "gn:asciiname":"Mepaco",
    "gn:country_code":"MZ",
    "gn:dem":90,
    "gn:feature_class":"P",
    "gn:feature_code":"PPL",
    "gn:name":"Mepaco",
    "gn:population":0,
    "gn:timezone":"Africa/Maputo",
    "iso:country":"MZ",
    "wof:name":"Mepaco",
    "wof:placetype":"locality"
},
  "geometry": {"coordinates":[39.80667,-15.92361],"type":"Point"}
}