{
  "type": "Feature",
  "properties": {
    "gn:admin1_code":"6",
    "gn:asciiname":"Chefe Eduardo",
    "gn:country_code":"MZ",
    "gn:dem":151,
    "gn:feature_class":"P",
    "gn:feature_code":"PPL",
    "gn:name":"Chefe Eduardo",
    "gn:population":0,
    "gn:timezone":"Africa/Maputo",
    "iso:country":"MZ",
    "wof:name":"Chefe Eduardo",
    "wof:placetype":"locality"
},
  "geometry": {"coordinates":[39.14056,-16.07444],"type":"Point"}
}