{
  "type": "Feature",
  "properties": {
    "gn:admin1_code":"2.0",
    "gn:asciiname":"Chefe Bocoda",
    "gn:country_code":"MZ",
    "gn:dem":197,
    "gn:feature_class":"P",
    "gn:feature_code":"PPL",
    "gn:name":"Chefe Bocoda",
    "gn:population":0,
    "gn:timezone":"Africa/Maputo",
    "iso:country":"MZ",
    "wof:name":"Chefe Bocoda",
    "wof:placetype":"locality"
},
  "geometry": {"coordinates":[31.54,-22.36611],"type":"Point"}
}