{
  "type": "Feature",
  "properties": {
    "gn:admin1_code":"3",
    "gn:asciiname":"Changuane",
    "gn:cc2":"MZ",
    "gn:country_code":"MZ",
    "gn:dem":42,
    "gn:feature_class":"P",
    "gn:feature_code":"PPL",
    "gn:name":"Changuane",
    "gn:population":0,
    "gn:timezone":"Africa/Maputo",
    "iso:country":"MZ",
    "name:und_x_variant":[
        "Nati\u00e7a",
        "Changuane"
    ],
    "wof:name":"Changuane",
    "wof:placetype":"locality"
},
  "geometry": {"coordinates":[35.33194,-22.46194],"type":"Point"}
}