{
  "type": "Feature",
  "properties": {
    "gn:admin1_code":"1.0",
    "gn:asciiname":"Chefe Saide",
    "gn:cc2":"MZ",
    "gn:country_code":"MZ",
    "gn:dem":439,
    "gn:feature_class":"P",
    "gn:feature_code":"PPL",
    "gn:name":"Chefe Sa\u00edde",
    "gn:population":0,
    "gn:timezone":"Africa/Maputo",
    "iso:country":"MZ",
    "name:und_x_variant":[
        "Saide",
        "Chefe Sa\u00edde"
    ],
    "wof:name":"Chefe Saide",
    "wof:placetype":"locality"
},
  "geometry": {"coordinates":[38.82917,-13.77806],"type":"Point"}
}