{
  "type": "Feature",
  "properties": {
    "gn:admin1_code":"2.0",
    "gn:asciiname":"Djimo",
    "gn:country_code":"MZ",
    "gn:dem":129,
    "gn:feature_class":"P",
    "gn:feature_code":"PPL",
    "gn:name":"Djimo",
    "gn:population":0,
    "gn:timezone":"Africa/Maputo",
    "iso:country":"MZ",
    "wof:name":"Djimo",
    "wof:placetype":"locality"
},
  "geometry": {"coordinates":[32.68028,-23.37694],"type":"Point"}
}