{
  "type": "Feature",
  "properties": {
    "gn:admin1_code":"9",
    "gn:asciiname":"Mauia",
    "gn:country_code":"MZ",
    "gn:dem":29,
    "gn:feature_class":"P",
    "gn:feature_code":"PPL",
    "gn:name":"Mauia",
    "gn:population":0,
    "gn:timezone":"Africa/Maputo",
    "iso:country":"MZ",
    "wof:name":"Mauia",
    "wof:placetype":"locality"
},
  "geometry": {"coordinates":[38.13917,-17.09917],"type":"Point"}
}