{
  "type": "Feature",
  "properties": {
    "gn:admin1_code":"3.0",
    "gn:asciiname":"Mucale",
    "gn:country_code":"MZ",
    "gn:dem":15,
    "gn:feature_class":"P",
    "gn:feature_code":"PPL",
    "gn:name":"Mucale",
    "gn:population":0,
    "gn:timezone":"Africa/Maputo",
    "iso:country":"MZ",
    "wof:name":"Mucale",
    "wof:placetype":"locality"
},
  "geometry": {"coordinates":[34.81306,-21.08889],"type":"Point"}
}