{
  "type": "Feature",
  "properties": {
    "gn:admin1_code":"4.0",
    "gn:asciiname":"Uasquete",
    "gn:country_code":"MZ",
    "gn:dem":118,
    "gn:feature_class":"P",
    "gn:feature_code":"PPL",
    "gn:name":"Uasquete",
    "gn:population":0,
    "gn:timezone":"Africa/Maputo",
    "iso:country":"MZ",
    "wof:name":"Uasquete",
    "wof:placetype":"locality"
},
  "geometry": {"coordinates":[32.26667,-25.18333],"type":"Point"}
}