{
  "type": "Feature",
  "properties": {
    "gn:admin1_code":"5",
    "gn:asciiname":"Peto",
    "gn:country_code":"MZ",
    "gn:dem":263,
    "gn:feature_class":"P",
    "gn:feature_code":"PPL",
    "gn:name":"Peto",
    "gn:population":0,
    "gn:timezone":"Africa/Maputo",
    "iso:country":"MZ",
    "wof:name":"Peto",
    "wof:placetype":"locality"
},
  "geometry": {"coordinates":[33.65278,-20.4225],"type":"Point"}
}