{
  "type": "Feature",
  "properties": {
    "gn:admin1_code":"9.0",
    "gn:asciiname":"Uarrica",
    "gn:country_code":"MZ",
    "gn:dem":303,
    "gn:feature_class":"P",
    "gn:feature_code":"PPL",
    "gn:name":"U\u00e1rrica",
    "gn:population":0,
    "gn:timezone":"Africa/Maputo",
    "iso:country":"MZ",
    "wof:name":"Uarrica",
    "wof:placetype":"locality"
},
  "geometry": {"coordinates":[38.29333,-15.93472],"type":"Point"}
}