{
  "type": "Feature",
  "properties": {
    "gn:admin1_code":"9",
    "gn:asciiname":"Vaquiua",
    "gn:country_code":"MZ",
    "gn:dem":985,
    "gn:feature_class":"P",
    "gn:feature_code":"PPL",
    "gn:name":"Vaquiua",
    "gn:population":0,
    "gn:timezone":"Africa/Maputo",
    "iso:country":"MZ",
    "wof:name":"Vaquiua",
    "wof:placetype":"locality"
},
  "geometry": {"coordinates":[37.18833,-15.36],"type":"Point"}
}