{
  "type": "Feature",
  "properties": {
    "gn:admin1_code":"6.0",
    "gn:asciiname":"Chefe Matos",
    "gn:country_code":"MZ",
    "gn:dem":85,
    "gn:feature_class":"P",
    "gn:feature_code":"PPL",
    "gn:name":"Chefe Matos",
    "gn:population":0,
    "gn:timezone":"Africa/Maputo",
    "iso:country":"MZ",
    "wof:name":"Chefe Matos",
    "wof:placetype":"locality"
},
  "geometry": {"coordinates":[39.15417,-16.41333],"type":"Point"}
}