{
  "type": "Feature",
  "properties": {
    "gn:admin1_code":"3",
    "gn:asciiname":"Chefe Ancoca",
    "gn:cc2":"MZ",
    "gn:country_code":"MZ",
    "gn:dem":84,
    "gn:feature_class":"P",
    "gn:feature_code":"PPL",
    "gn:name":"Chefe Ancoca",
    "gn:population":0,
    "gn:timezone":"Africa/Maputo",
    "iso:country":"MZ",
    "name:und_x_variant":[
        "Ancoque",
        "Chefe Ancoca"
    ],
    "wof:name":"Chefe Ancoca",
    "wof:placetype":"locality"
},
  "geometry": {"coordinates":[34.63889,-24.47778],"type":"Point"}
}