{
  "type": "Feature",
  "properties": {
    "gn:admin1_code":"9",
    "gn:asciiname":"Mivalarra",
    "gn:cc2":"MZ",
    "gn:country_code":"MZ",
    "gn:dem":66,
    "gn:feature_class":"P",
    "gn:feature_code":"PPL",
    "gn:name":"Mivalarra",
    "gn:population":0,
    "gn:timezone":"Africa/Maputo",
    "iso:country":"MZ",
    "name:und_x_variant":[
        "Nivalama",
        "Mivalarra"
    ],
    "wof:name":"Mivalarra",
    "wof:placetype":"locality"
},
  "geometry": {"coordinates":[37.41944,-17.17889],"type":"Point"}
}