{
  "type": "Feature",
  "properties": {
    "gn:admin1_code":"3",
    "gn:asciiname":"Magavane",
    "gn:country_code":"MZ",
    "gn:dem":81,
    "gn:feature_class":"P",
    "gn:feature_code":"PPL",
    "gn:name":"Magavane",
    "gn:population":0,
    "gn:timezone":"Africa/Maputo",
    "iso:country":"MZ",
    "wof:name":"Magavane",
    "wof:placetype":"locality"
},
  "geometry": {"coordinates":[35.22889,-23.81667],"type":"Point"}
}