{
  "type": "Feature",
  "properties": {
    "gn:admin1_code":"10",
    "gn:asciiname":"Mupendezua",
    "gn:country_code":"MZ",
    "gn:dem":248,
    "gn:feature_class":"P",
    "gn:feature_code":"PPL",
    "gn:name":"Mupendezua",
    "gn:population":0,
    "gn:timezone":"Africa/Maputo",
    "iso:country":"MZ",
    "wof:name":"Mupendezua",
    "wof:placetype":"locality"
},
  "geometry": {"coordinates":[33.86722,-19.19778],"type":"Point"}
}