{
  "type": "Feature",
  "properties": {
    "gn:admin1_code":"1",
    "gn:asciiname":"Nazombe",
    "gn:cc2":"MZ",
    "gn:country_code":"MZ",
    "gn:dem":201,
    "gn:feature_class":"P",
    "gn:feature_code":"PPL",
    "gn:name":"Nazombe",
    "gn:population":0,
    "gn:timezone":"Africa/Maputo",
    "iso:country":"MZ",
    "name:und_x_variant":[
        "Nassombe",
        "Nazombe"
    ],
    "wof:name":"Nazombe",
    "wof:placetype":"locality"
},
  "geometry": {"coordinates":[38.84167,-11.35972],"type":"Point"}
}