{
  "type": "Feature",
  "properties": {
    "gn:admin1_code":"1",
    "gn:asciiname":"Chefe Perevere",
    "gn:country_code":"MZ",
    "gn:dem":511,
    "gn:feature_class":"P",
    "gn:feature_code":"PPL",
    "gn:name":"Chefe Perevere",
    "gn:population":0,
    "gn:timezone":"Africa/Maputo",
    "iso:country":"MZ",
    "wof:name":"Chefe Perevere",
    "wof:placetype":"locality"
},
  "geometry": {"coordinates":[38.95833,-13.49528],"type":"Point"}
}