{
  "type": "Feature",
  "properties": {
    "gn:admin1_code":"9",
    "gn:asciiname":"Muanheu",
    "gn:country_code":"MZ",
    "gn:dem":732,
    "gn:feature_class":"P",
    "gn:feature_code":"PPL",
    "gn:name":"Muanheu",
    "gn:population":0,
    "gn:timezone":"Africa/Maputo",
    "iso:country":"MZ",
    "wof:name":"Muanheu",
    "wof:placetype":"locality"
},
  "geometry": {"coordinates":[37.49056,-15.42778],"type":"Point"}
}