{
  "type": "Feature",
  "properties": {
    "gn:admin1_code":"3.0",
    "gn:asciiname":"Matchucane",
    "gn:country_code":"MZ",
    "gn:dem":131,
    "gn:feature_class":"P",
    "gn:feature_code":"PPL",
    "gn:name":"Matchucane",
    "gn:population":0,
    "gn:timezone":"Africa/Maputo",
    "iso:country":"MZ",
    "wof:name":"Matchucane",
    "wof:placetype":"locality"
},
  "geometry": {"coordinates":[34.25083,-21.43194],"type":"Point"}
}