{
  "type": "Feature",
  "properties": {
    "gn:admin1_code":"8",
    "gn:asciiname":"Chundiza",
    "gn:country_code":"MZ",
    "gn:dem":346,
    "gn:feature_class":"P",
    "gn:feature_code":"PPL",
    "gn:name":"Chundiza",
    "gn:population":0,
    "gn:timezone":"Africa/Maputo",
    "iso:country":"MZ",
    "wof:name":"Chundiza",
    "wof:placetype":"locality"
},
  "geometry": {"coordinates":[33.18806,-16.09472],"type":"Point"}
}