{
  "type": "Feature",
  "properties": {
    "gn:admin1_code":"5",
    "gn:asciiname":"M'sunza",
    "gn:country_code":"MZ",
    "gn:dem":145,
    "gn:feature_class":"P",
    "gn:feature_code":"PPL",
    "gn:name":"M\u2019sunza",
    "gn:population":0,
    "gn:timezone":"Africa/Maputo",
    "iso:country":"MZ",
    "wof:name":"M'sunza",
    "wof:placetype":"locality"
},
  "geometry": {"coordinates":[34.48167,-18.30083],"type":"Point"}
}