{
  "type": "Feature",
  "properties": {
    "gn:admin1_code":"4.0",
    "gn:asciiname":"Mangungane",
    "gn:country_code":"MZ",
    "gn:dem":159,
    "gn:feature_class":"P",
    "gn:feature_code":"PPL",
    "gn:name":"Mangungane",
    "gn:population":0,
    "gn:timezone":"Africa/Maputo",
    "iso:country":"MZ",
    "wof:name":"Mangungane",
    "wof:placetype":"locality"
},
  "geometry": {"coordinates":[32.10833,-24.94583],"type":"Point"}
}