{
  "type": "Feature",
  "properties": {
    "gn:admin1_code":"7",
    "gn:asciiname":"Chefe Jossemira",
    "gn:country_code":"MZ",
    "gn:dem":667,
    "gn:feature_class":"P",
    "gn:feature_code":"PPL",
    "gn:name":"Chefe Jossemira",
    "gn:population":0,
    "gn:timezone":"Africa/Maputo",
    "iso:country":"MZ",
    "wof:name":"Chefe Jossemira",
    "wof:placetype":"locality"
},
  "geometry": {"coordinates":[35.93861,-15.13583],"type":"Point"}
}