{
  "type": "Feature",
  "properties": {
    "gn:admin1_code":"10",
    "gn:asciiname":"Guro",
    "gn:country_code":"MZ",
    "gn:dem":744,
    "gn:feature_class":"P",
    "gn:feature_code":"PPL",
    "gn:name":"Guro",
    "gn:population":0,
    "gn:timezone":"Africa/Maputo",
    "iso:country":"MZ",
    "wof:name":"Guro",
    "wof:placetype":"locality"
},
  "geometry": {"coordinates":[33.35444,-17.42167],"type":"Point"}
}