{
  "type": "Feature",
  "properties": {
    "gn:admin1_code":"10",
    "gn:asciiname":"Guro",
    "gn:country_code":"MZ",
    "gn:dem":744,
    "gn:feature_class":"P",
    "gn:feature_code":"PPL",
    "gn:name":"Guro",
    "gn:population":0,
    "gn:timezone":"Africa/Maputo",
    "iso:country":"MZ",
    "name:ceb_x_preferred":[
        "Guro"
    ],
    "name:deu_x_preferred":[
        "Guro"
    ],
    "name:ita_x_preferred":[
        "Guro"
    ],
    "name:nld_x_preferred":[
        "Guro"
    ],
    "name:nor_x_preferred":[
        "Guro"
    ],
    "name:rus_x_preferred":[
        "\u0413\u0443\u0440\u043e"
    ],
    "name:sco_x_preferred":[
        "Guro"
    ],
    "name:spa_x_preferred":[
        "Guro"
    ],
    "name:swe_x_preferred":[
        "Guro"
    ],
    "wof:name":"Guro",
    "wof:placetype":"locality"
},
  "geometry": {"coordinates":[33.35444,-17.42167],"type":"Point"}
}