{
  "type": "Feature",
  "properties": {
    "gn:admin1_code":"4",
    "gn:asciiname":"Cavasse",
    "gn:country_code":"MZ",
    "gn:dem":109,
    "gn:feature_class":"P",
    "gn:feature_code":"PPL",
    "gn:name":"Cavasse",
    "gn:population":0,
    "gn:timezone":"Africa/Maputo",
    "iso:country":"MZ",
    "wof:name":"Cavasse",
    "wof:placetype":"locality"
},
  "geometry": {"coordinates":[32.20861,-25.20111],"type":"Point"}
}