{
  "type": "Feature",
  "properties": {
    "gn:admin1_code":"3.0",
    "gn:asciiname":"Zato",
    "gn:country_code":"MZ",
    "gn:dem":122,
    "gn:feature_class":"P",
    "gn:feature_code":"PPL",
    "gn:name":"Zato",
    "gn:population":0,
    "gn:timezone":"Africa/Maputo",
    "iso:country":"MZ",
    "wof:name":"Zato",
    "wof:placetype":"locality"
},
  "geometry": {"coordinates":[34.00694,-22.79083],"type":"Point"}
}