{
  "type": "Feature",
  "properties": {
    "gn:admin1_code":"10",
    "gn:asciiname":"Joanguete",
    "gn:country_code":"MZ",
    "gn:dem":474,
    "gn:feature_class":"P",
    "gn:feature_code":"PPL",
    "gn:name":"Joanguete",
    "gn:population":0,
    "gn:timezone":"Africa/Maputo",
    "iso:country":"MZ",
    "wof:name":"Joanguete",
    "wof:placetype":"locality"
},
  "geometry": {"coordinates":[33.63861,-18.94389],"type":"Point"}
}