{
  "type": "Feature",
  "properties": {
    "gn:admin1_code":"3",
    "gn:asciiname":"Estata",
    "gn:country_code":"MZ",
    "gn:dem":187,
    "gn:feature_class":"P",
    "gn:feature_code":"PPL",
    "gn:name":"Estata",
    "gn:population":0,
    "gn:timezone":"Africa/Maputo",
    "iso:country":"MZ",
    "wof:name":"Estata",
    "wof:placetype":"locality"
},
  "geometry": {"coordinates":[34.28222,-21.79472],"type":"Point"}
}