{
  "type": "Feature",
  "properties": {
    "gn:admin1_code":"4",
    "gn:asciiname":"Chamussa",
    "gn:country_code":"MZ",
    "gn:dem":143,
    "gn:feature_class":"P",
    "gn:feature_code":"PPL",
    "gn:name":"Chamussa",
    "gn:population":0,
    "gn:timezone":"Africa/Maputo",
    "iso:country":"MZ",
    "wof:name":"Chamussa",
    "wof:placetype":"locality"
},
  "geometry": {"coordinates":[32.05,-25.15],"type":"Point"}
}