{
  "type": "Feature",
  "properties": {
    "gn:admin1_code":"10.0",
    "gn:asciiname":"Pofo",
    "gn:country_code":"MZ",
    "gn:dem":809,
    "gn:feature_class":"P",
    "gn:feature_code":"PPL",
    "gn:name":"P\u00f4fo",
    "gn:population":0,
    "gn:timezone":"Africa/Maputo",
    "iso:country":"MZ",
    "wof:name":"Pofo",
    "wof:placetype":"locality"
},
  "geometry": {"coordinates":[33.06333,-18.10694],"type":"Point"}
}