{
  "type": "Feature",
  "properties": {
    "gn:admin1_code":"2.0",
    "gn:asciiname":"Pongonhe",
    "gn:country_code":"MZ",
    "gn:dem":179,
    "gn:feature_class":"P",
    "gn:feature_code":"PPL",
    "gn:name":"Pongonhe",
    "gn:population":0,
    "gn:timezone":"Africa/Maputo",
    "iso:country":"MZ",
    "wof:name":"Pongonhe",
    "wof:placetype":"locality"
},
  "geometry": {"coordinates":[31.73778,-22.6025],"type":"Point"}
}