{
  "type": "Feature",
  "properties": {
    "gn:admin1_code":"9.0",
    "gn:asciiname":"Chefe Mologa",
    "gn:country_code":"MZ",
    "gn:dem":34,
    "gn:feature_class":"P",
    "gn:feature_code":"PPL",
    "gn:name":"Chefe Mol\u00f3ga",
    "gn:population":0,
    "gn:timezone":"Africa/Maputo",
    "iso:country":"MZ",
    "wof:name":"Chefe Mologa",
    "wof:placetype":"locality"
},
  "geometry": {"coordinates":[38.97306,-16.89944],"type":"Point"}
}