{
  "type": "Feature",
  "properties": {
    "gn:admin1_code":"6",
    "gn:asciiname":"Chefe Nonianane",
    "gn:country_code":"MZ",
    "gn:dem":249,
    "gn:feature_class":"P",
    "gn:feature_code":"PPL",
    "gn:name":"Chefe Nonianane",
    "gn:population":0,
    "gn:timezone":"Africa/Maputo",
    "iso:country":"MZ",
    "wof:name":"Chefe Nonianane",
    "wof:placetype":"locality"
},
  "geometry": {"coordinates":[39.75333,-13.7075],"type":"Point"}
}