{
  "type": "Feature",
  "properties": {
    "gn:admin1_code":"6.0",
    "gn:asciiname":"Chefe Puca",
    "gn:country_code":"MZ",
    "gn:dem":83,
    "gn:feature_class":"P",
    "gn:feature_code":"PPL",
    "gn:name":"Chefe Puca",
    "gn:population":0,
    "gn:timezone":"Africa/Maputo",
    "iso:country":"MZ",
    "wof:name":"Chefe Puca",
    "wof:placetype":"locality"
},
  "geometry": {"coordinates":[39.45167,-16.65306],"type":"Point"}
}