{
  "type": "Feature",
  "properties": {
    "gn:admin1_code":"10",
    "gn:asciiname":"Chicuaja",
    "gn:country_code":"MZ",
    "gn:dem":260,
    "gn:feature_class":"P",
    "gn:feature_code":"PPL",
    "gn:name":"Chicuaja",
    "gn:population":0,
    "gn:timezone":"Africa/Maputo",
    "iso:country":"MZ",
    "wof:name":"Chicuaja",
    "wof:placetype":"locality"
},
  "geometry": {"coordinates":[33.19333,-20.6325],"type":"Point"}
}