{
  "type": "Feature",
  "properties": {
    "gn:admin1_code":"2.0",
    "gn:asciiname":"Cocmela",
    "gn:country_code":"MZ",
    "gn:dem":98,
    "gn:feature_class":"P",
    "gn:feature_code":"PPL",
    "gn:name":"Cocmela",
    "gn:population":0,
    "gn:timezone":"Africa/Maputo",
    "iso:country":"MZ",
    "wof:name":"Cocmela",
    "wof:placetype":"locality"
},
  "geometry": {"coordinates":[32.33889,-23.38278],"type":"Point"}
}