{
  "type": "Feature",
  "properties": {
    "gn:admin1_code":"7",
    "gn:asciiname":"Manlia",
    "gn:country_code":"MZ",
    "gn:dem":440,
    "gn:feature_class":"P",
    "gn:feature_code":"PPL",
    "gn:name":"Manlia",
    "gn:population":0,
    "gn:timezone":"Africa/Maputo",
    "iso:country":"MZ",
    "wof:name":"Manlia",
    "wof:placetype":"locality"
},
  "geometry": {"coordinates":[37.97222,-13.94056],"type":"Point"}
}