{
  "type": "Feature",
  "properties": {
    "gn:admin1_code":"7.0",
    "gn:asciiname":"Uncula",
    "gn:country_code":"MZ",
    "gn:dem":1232,
    "gn:feature_class":"P",
    "gn:feature_code":"PPL",
    "gn:name":"Uncula",
    "gn:population":0,
    "gn:timezone":"Africa/Maputo",
    "iso:country":"MZ",
    "name:ceb_x_preferred":[
        "Uncula"
    ],
    "name:swe_x_preferred":[
        "Uncula"
    ],
    "name:vie_x_preferred":[
        "Uncula"
    ],
    "name:war_x_preferred":[
        "Uncula"
    ],
    "wof:name":"Uncula",
    "wof:placetype":"locality"
},
  "geometry": {"coordinates":[35.28917,-13.85472],"type":"Point"}
}