{
  "type": "Feature",
  "properties": {
    "gn:admin1_code":"1.0",
    "gn:asciiname":"Urucumo",
    "gn:country_code":"MZ",
    "gn:dem":308,
    "gn:feature_class":"P",
    "gn:feature_code":"PPL",
    "gn:name":"Urucumo",
    "gn:population":0,
    "gn:timezone":"Africa/Maputo",
    "iso:country":"MZ",
    "wof:name":"Urucumo",
    "wof:placetype":"locality"
},
  "geometry": {"coordinates":[39.17861,-12.44056],"type":"Point"}
}