{
  "type": "Feature",
  "properties": {
    "gn:admin1_code":"1",
    "gn:asciiname":"Nanzarro",
    "gn:country_code":"MZ",
    "gn:dem":327,
    "gn:feature_class":"P",
    "gn:feature_code":"PPL",
    "gn:name":"Nanzarro",
    "gn:population":0,
    "gn:timezone":"Africa/Maputo",
    "iso:country":"MZ",
    "wof:name":"Nanzarro",
    "wof:placetype":"locality"
},
  "geometry": {"coordinates":[39.86833,-13.06306],"type":"Point"}
}