{
  "type": "Feature",
  "properties": {
    "gn:admin1_code":"5.0",
    "gn:asciiname":"Tongo",
    "gn:country_code":"MZ",
    "gn:dem":434,
    "gn:feature_class":"P",
    "gn:feature_code":"PPL",
    "gn:name":"Tongo",
    "gn:population":0,
    "gn:timezone":"Africa/Maputo",
    "iso:country":"MZ",
    "wof:name":"Tongo",
    "wof:placetype":"locality"
},
  "geometry": {"coordinates":[34.03639,-18.27556],"type":"Point"}
}