{
  "type": "Feature",
  "properties": {
    "gn:admin1_code":"9",
    "gn:asciiname":"Congono",
    "gn:country_code":"MZ",
    "gn:dem":381,
    "gn:feature_class":"P",
    "gn:feature_code":"PPL",
    "gn:name":"Congono",
    "gn:population":0,
    "gn:timezone":"Africa/Maputo",
    "iso:country":"MZ",
    "wof:name":"Congono",
    "wof:placetype":"locality"
},
  "geometry": {"coordinates":[36.05806,-16.4075],"type":"Point"}
}