{
  "type": "Feature",
  "properties": {
    "gn:admin1_code":"7",
    "gn:asciiname":"Mucomo",
    "gn:country_code":"MZ",
    "gn:dem":719,
    "gn:feature_class":"P",
    "gn:feature_code":"PPL",
    "gn:name":"Mucomo",
    "gn:population":0,
    "gn:timezone":"Africa/Maputo",
    "iso:country":"MZ",
    "wof:name":"Mucomo",
    "wof:placetype":"locality"
},
  "geometry": {"coordinates":[36.23583,-15.24083],"type":"Point"}
}