{
  "type": "Feature",
  "properties": {
    "gn:admin1_code":"1",
    "gn:asciiname":"Liasse",
    "gn:country_code":"MZ",
    "gn:dem":260,
    "gn:feature_class":"P",
    "gn:feature_code":"PPL",
    "gn:name":"Liasse",
    "gn:population":0,
    "gn:timezone":"Africa/Maputo",
    "iso:country":"MZ",
    "wof:name":"Liasse",
    "wof:placetype":"locality"
},
  "geometry": {"coordinates":[39.52111,-13.73917],"type":"Point"}
}