{
  "type": "Feature",
  "properties": {
    "gn:admin1_code":"10",
    "gn:asciiname":"Mataba",
    "gn:country_code":"MZ",
    "gn:dem":272,
    "gn:feature_class":"P",
    "gn:feature_code":"PPL",
    "gn:name":"Mataba",
    "gn:population":0,
    "gn:timezone":"Africa/Maputo",
    "iso:country":"MZ",
    "wof:name":"Mataba",
    "wof:placetype":"locality"
},
  "geometry": {"coordinates":[33.56139,-20.58583],"type":"Point"}
}