{
  "type": "Feature",
  "properties": {
    "gn:admin1_code":"1",
    "gn:asciiname":"Chicuemba",
    "gn:country_code":"MZ",
    "gn:dem":155,
    "gn:feature_class":"P",
    "gn:feature_code":"PPL",
    "gn:name":"Chicuemba",
    "gn:population":0,
    "gn:timezone":"Africa/Maputo",
    "iso:country":"MZ",
    "wof:name":"Chicuemba",
    "wof:placetype":"locality"
},
  "geometry": {"coordinates":[40.0925,-11.56083],"type":"Point"}
}