{
  "type": "Feature",
  "properties": {
    "gn:admin1_code":"7",
    "gn:asciiname":"Iaissa",
    "gn:cc2":"MZ",
    "gn:country_code":"MZ",
    "gn:dem":1233,
    "gn:feature_class":"P",
    "gn:feature_code":"PPL",
    "gn:name":"Ia\u00edssa",
    "gn:population":0,
    "gn:timezone":"Africa/Maputo",
    "iso:country":"MZ",
    "name:und_x_variant":[
        "Ia\u00edsse",
        "Ia\u00edssa"
    ],
    "wof:name":"Iaissa",
    "wof:placetype":"locality"
},
  "geometry": {"coordinates":[35.51110999999999,-13.30861],"type":"Point"}
}