{
  "type": "Feature",
  "properties": {
    "gn:admin1_code":"4",
    "gn:asciiname":"Majojo",
    "gn:country_code":"MZ",
    "gn:dem":20,
    "gn:feature_class":"P",
    "gn:feature_code":"PPL",
    "gn:name":"Majojo",
    "gn:population":0,
    "gn:timezone":"Africa/Maputo",
    "iso:country":"MZ",
    "wof:name":"Majojo",
    "wof:placetype":"locality"
},
  "geometry": {"coordinates":[32.85194,-24.98139],"type":"Point"}
}