{
  "type": "Feature",
  "properties": {
    "gn:admin1_code":"9",
    "gn:asciiname":"Mecona",
    "gn:country_code":"MZ",
    "gn:dem":473,
    "gn:feature_class":"P",
    "gn:feature_code":"PPL",
    "gn:name":"Mecona",
    "gn:population":0,
    "gn:timezone":"Africa/Maputo",
    "iso:country":"MZ",
    "wof:name":"Mecona",
    "wof:placetype":"locality"
},
  "geometry": {"coordinates":[37.55194,-16.05194],"type":"Point"}
}