{
  "type": "Feature",
  "properties": {
    "gn:admin1_code":"4",
    "gn:asciiname":"B. Popular",
    "gn:country_code":"MZ",
    "gn:dem":27,
    "gn:feature_class":"P",
    "gn:feature_code":"PPL",
    "gn:name":"B. Popular",
    "gn:population":0,
    "gn:timezone":"Africa/Maputo",
    "iso:country":"MZ",
    "wof:name":"B. Popular",
    "wof:placetype":"locality"
},
  "geometry": {"coordinates":[32.46778,-25.92917000000001],"type":"Point"}
}