{
  "type": "Feature",
  "properties": {
    "gn:admin1_code":"10",
    "gn:asciiname":"Ghemete",
    "gn:country_code":"MZ",
    "gn:dem":143,
    "gn:feature_class":"P",
    "gn:feature_code":"PPL",
    "gn:name":"Ghemete",
    "gn:population":0,
    "gn:timezone":"Africa/Maputo",
    "iso:country":"MZ",
    "wof:name":"Ghemete",
    "wof:placetype":"locality"
},
  "geometry": {"coordinates":[33.57056,-21.285],"type":"Point"}
}