{
  "type": "Feature",
  "properties": {
    "gn:admin1_code":"1",
    "gn:asciiname":"Chefe Adriano",
    "gn:country_code":"MZ",
    "gn:dem":256,
    "gn:feature_class":"P",
    "gn:feature_code":"PPL",
    "gn:name":"Chefe Adriano",
    "gn:population":0,
    "gn:timezone":"Africa/Maputo",
    "iso:country":"MZ",
    "wof:name":"Chefe Adriano",
    "wof:placetype":"locality"
},
  "geometry": {"coordinates":[39.96139,-13.47583],"type":"Point"}
}