{
  "type": "Feature",
  "properties": {
    "gn:admin1_code":"7",
    "gn:asciiname":"Lovele",
    "gn:country_code":"MZ",
    "gn:dem":1204,
    "gn:feature_class":"P",
    "gn:feature_code":"PPL",
    "gn:name":"Lovel\u00e8",
    "gn:population":0,
    "gn:timezone":"Africa/Maputo",
    "iso:country":"MZ",
    "wof:name":"Lovele",
    "wof:placetype":"locality"
},
  "geometry": {"coordinates":[35.32222,-13.77333],"type":"Point"}
}