{
  "type": "Feature",
  "properties": {
    "gn:admin1_code":"1",
    "gn:asciiname":"Dhalman",
    "gn:country_code":"MZ",
    "gn:dem":363,
    "gn:feature_class":"P",
    "gn:feature_code":"PPL",
    "gn:name":"Dhalman",
    "gn:population":0,
    "gn:timezone":"Africa/Maputo",
    "iso:country":"MZ",
    "wof:name":"Dhalman",
    "wof:placetype":"locality"
},
  "geometry": {"coordinates":[39.69278,-12.86556],"type":"Point"}
}