{
  "type": "Feature",
  "properties": {
    "gn:admin1_code":"9",
    "gn:asciiname":"Chefe Muaile",
    "gn:country_code":"MZ",
    "gn:dem":332,
    "gn:feature_class":"P",
    "gn:feature_code":"PPL",
    "gn:name":"Chefe Muaile",
    "gn:population":0,
    "gn:timezone":"Africa/Maputo",
    "iso:country":"MZ",
    "wof:name":"Chefe Muaile",
    "wof:placetype":"locality"
},
  "geometry": {"coordinates":[38.50472,-16.03972000000001],"type":"Point"}
}