{
  "type": "Feature",
  "properties": {
    "gn:admin1_code":"3",
    "gn:asciiname":"Massavolane",
    "gn:country_code":"MZ",
    "gn:dem":158,
    "gn:feature_class":"P",
    "gn:feature_code":"PPL",
    "gn:name":"Massavolane",
    "gn:population":0,
    "gn:timezone":"Africa/Maputo",
    "iso:country":"MZ",
    "wof:name":"Massavolane",
    "wof:placetype":"locality"
},
  "geometry": {"coordinates":[33.86722,-22.5175],"type":"Point"}
}