{
  "type": "Feature",
  "properties": {
    "gn:admin1_code":"2.0",
    "gn:asciiname":"Chefe Matigane",
    "gn:country_code":"MZ",
    "gn:dem":106,
    "gn:feature_class":"P",
    "gn:feature_code":"PPL",
    "gn:name":"Chefe Matigane",
    "gn:population":0,
    "gn:timezone":"Africa/Maputo",
    "iso:country":"MZ",
    "wof:name":"Chefe Matigane",
    "wof:placetype":"locality"
},
  "geometry": {"coordinates":[32.305,-23.88917],"type":"Point"}
}