{
  "type": "Feature",
  "properties": {
    "gn:admin1_code":"1",
    "gn:asciiname":"Nassue",
    "gn:country_code":"MZ",
    "gn:dem":70,
    "gn:feature_class":"P",
    "gn:feature_code":"PPL",
    "gn:name":"Nassue",
    "gn:population":0,
    "gn:timezone":"Africa/Maputo",
    "iso:country":"MZ",
    "wof:name":"Nassue",
    "wof:placetype":"locality"
},
  "geometry": {"coordinates":[40.53278,-13.28472],"type":"Point"}
}