{
  "type": "Feature",
  "properties": {
    "gn:admin1_code":"3.0",
    "gn:asciiname":"Xavier",
    "gn:country_code":"MZ",
    "gn:dem":39,
    "gn:feature_class":"P",
    "gn:feature_code":"PPL",
    "gn:name":"Xavier",
    "gn:population":0,
    "gn:timezone":"Africa/Maputo",
    "iso:country":"MZ",
    "name:bre_x_preferred":[
        "Xavier"
    ],
    "name:deu_x_preferred":[
        "Xavier"
    ],
    "name:eus_x_preferred":[
        "Xabier"
    ],
    "name:fra_x_preferred":[
        "Xavier"
    ],
    "name:ita_x_preferred":[
        "Xavier"
    ],
    "name:jpn_x_preferred":[
        "\u30b7\u30e3\u30d3\u30a8\u30eb"
    ],
    "name:kor_x_preferred":[
        "\uc0ac\ube44\uc5d0\ub974"
    ],
    "name:nld_x_preferred":[
        "Xavier"
    ],
    "name:por_x_preferred":[
        "Xavier"
    ],
    "name:rus_x_preferred":[
        "\u041a\u0441\u0430\u0432\u044c\u0435"
    ],
    "name:spa_x_preferred":[
        "Xavier"
    ],
    "name:swe_x_preferred":[
        "Xavier"
    ],
    "wof:name":"Xavier",
    "wof:placetype":"locality"
},
  "geometry": {"coordinates":[35.21194000000001,-22.22444],"type":"Point"}
}