{
  "type": "Feature",
  "properties": {
    "gn:admin1_code":"2.0",
    "gn:asciiname":"Filipe",
    "gn:country_code":"MZ",
    "gn:dem":53,
    "gn:feature_class":"P",
    "gn:feature_code":"PPL",
    "gn:name":"Filipe",
    "gn:population":0,
    "gn:timezone":"Africa/Maputo",
    "iso:country":"MZ",
    "name:bre_x_preferred":[
        "Filipe"
    ],
    "name:deu_x_preferred":[
        "Filipe"
    ],
    "name:glg_x_preferred":[
        "Filipe"
    ],
    "name:jpn_x_preferred":[
        "\u30d5\u30a3\u30ea\u30da"
    ],
    "name:por_x_preferred":[
        "Filipe"
    ],
    "wof:name":"Filipe",
    "wof:placetype":"locality"
},
  "geometry": {"coordinates":[33.80972,-23.4775],"type":"Point"}
}