{
  "type": "Feature",
  "properties": {
    "gn:admin1_code":"9",
    "gn:asciiname":"Chefe Macuia",
    "gn:country_code":"MZ",
    "gn:dem":109,
    "gn:feature_class":"P",
    "gn:feature_code":"PPL",
    "gn:name":"Chefe Macuia",
    "gn:population":0,
    "gn:timezone":"Africa/Maputo",
    "iso:country":"MZ",
    "wof:name":"Chefe Macuia",
    "wof:placetype":"locality"
},
  "geometry": {"coordinates":[37.09556,-16.95889],"type":"Point"}
}