{
  "type": "Feature",
  "properties": {
    "gn:admin1_code":"4.0",
    "gn:asciiname":"Jone",
    "gn:country_code":"MZ",
    "gn:dem":181,
    "gn:feature_class":"P",
    "gn:feature_code":"PPL",
    "gn:name":"Jone",
    "gn:population":0,
    "gn:timezone":"Africa/Maputo",
    "iso:country":"MZ",
    "name:deu_x_preferred":[
        "Jone"
    ],
    "name:por_x_preferred":[
        "Jone"
    ],
    "wof:name":"Jone",
    "wof:placetype":"locality"
},
  "geometry": {"coordinates":[32.09583,-24.73556],"type":"Point"}
}