{
  "type": "Feature",
  "properties": {
    "gn:admin1_code":"6",
    "gn:asciiname":"Cassamo",
    "gn:country_code":"MZ",
    "gn:dem":244,
    "gn:feature_class":"P",
    "gn:feature_code":"PPL",
    "gn:name":"Cassamo",
    "gn:population":0,
    "gn:timezone":"Africa/Maputo",
    "iso:country":"MZ",
    "wof:name":"Cassamo",
    "wof:placetype":"locality"
},
  "geometry": {"coordinates":[39.6975,-13.71694],"type":"Point"}
}