{
  "type": "Feature",
  "properties": {
    "gn:admin1_code":"1.0",
    "gn:asciiname":"Tindingo",
    "gn:country_code":"MZ",
    "gn:dem":760,
    "gn:feature_class":"P",
    "gn:feature_code":"PPL",
    "gn:name":"Tindingo",
    "gn:population":0,
    "gn:timezone":"Africa/Maputo",
    "iso:country":"MZ",
    "wof:name":"Tindingo",
    "wof:placetype":"locality"
},
  "geometry": {"coordinates":[39.43167,-11.37028],"type":"Point"}
}