{
  "type": "Feature",
  "properties": {
    "gn:admin1_code":"9",
    "gn:asciiname":"Mecoto",
    "gn:cc2":"MZ",
    "gn:country_code":"MZ",
    "gn:dem":755,
    "gn:feature_class":"P",
    "gn:feature_code":"PPL",
    "gn:name":"Mec\u00f3to",
    "gn:population":0,
    "gn:timezone":"Africa/Maputo",
    "iso:country":"MZ",
    "name:und_x_variant":[
        "Mecolo",
        "Mec\u00f3to"
    ],
    "wof:name":"Mecoto",
    "wof:placetype":"locality"
},
  "geometry": {"coordinates":[37.34139,-15.51361],"type":"Point"}
}