{
  "type": "Feature",
  "properties": {
    "gn:admin1_code":"3.0",
    "gn:asciiname":"Chefe Canhanga",
    "gn:country_code":"MZ",
    "gn:dem":73,
    "gn:feature_class":"P",
    "gn:feature_code":"PPL",
    "gn:name":"Chefe Canhanga",
    "gn:population":0,
    "gn:timezone":"Africa/Maputo",
    "iso:country":"MZ",
    "wof:name":"Chefe Canhanga",
    "wof:placetype":"locality"
},
  "geometry": {"coordinates":[35.10472,-24.3875],"type":"Point"}
}