{
  "type": "Feature",
  "properties": {
    "gn:admin1_code":"7",
    "gn:asciiname":"Inchoia",
    "gn:country_code":"MZ",
    "gn:dem":636,
    "gn:feature_class":"P",
    "gn:feature_code":"PPL",
    "gn:name":"Inchoia",
    "gn:population":0,
    "gn:timezone":"Africa/Maputo",
    "iso:country":"MZ",
    "wof:name":"Inchoia",
    "wof:placetype":"locality"
},
  "geometry": {"coordinates":[37.44472,-13.80861],"type":"Point"}
}