{
  "type": "Feature",
  "properties": {
    "gn:admin1_code":"6",
    "gn:asciiname":"Regulo Ossene",
    "gn:country_code":"MZ",
    "gn:dem":48,
    "gn:feature_class":"P",
    "gn:feature_code":"PPL",
    "gn:name":"R\u00e9gulo Ossene",
    "gn:population":0,
    "gn:timezone":"Africa/Maputo",
    "iso:country":"MZ",
    "wof:name":"Regulo Ossene",
    "wof:placetype":"locality"
},
  "geometry": {"coordinates":[40.01306,-16.12917],"type":"Point"}
}