{
  "type": "Feature",
  "properties": {
    "gn:admin1_code":"9",
    "gn:asciiname":"Alfaiate",
    "gn:country_code":"MZ",
    "gn:dem":244,
    "gn:feature_class":"P",
    "gn:feature_code":"PPL",
    "gn:name":"Alfaiate",
    "gn:population":0,
    "gn:timezone":"Africa/Maputo",
    "iso:country":"MZ",
    "wof:name":"Alfaiate",
    "wof:placetype":"locality"
},
  "geometry": {"coordinates":[36.20278,-17.07194],"type":"Point"}
}