{
  "type": "Feature",
  "properties": {
    "gn:admin1_code":"10",
    "gn:asciiname":"Garvin",
    "gn:country_code":"MZ",
    "gn:dem":720,
    "gn:feature_class":"P",
    "gn:feature_code":"PPL",
    "gn:name":"Garvin",
    "gn:population":0,
    "gn:timezone":"Africa/Maputo",
    "iso:country":"MZ",
    "wof:name":"Garvin",
    "wof:placetype":"locality"
},
  "geometry": {"coordinates":[33.01861,-18.83417],"type":"Point"}
}