{
  "type": "Feature",
  "properties": {
    "gn:admin1_code":"1",
    "gn:asciiname":"Assamo",
    "gn:country_code":"MZ",
    "gn:dem":223,
    "gn:feature_class":"P",
    "gn:feature_code":"PPL",
    "gn:name":"Assamo",
    "gn:population":0,
    "gn:timezone":"Africa/Maputo",
    "iso:country":"MZ",
    "name:ara_x_preferred":[
        "\u0623\u0633\u0627\u0645\u0648"
    ],
    "name:azb_x_preferred":[
        "\u0627\u0633\u0627\u0645\u0648"
    ],
    "name:ceb_x_preferred":[
        "\u2018As\u00e2mo"
    ],
    "name:fas_x_preferred":[
        "\u0627\u0633\u0627\u0645\u0648"
    ],
    "name:swe_x_preferred":[
        "\u2018As\u00e2mo"
    ],
    "name:urd_x_preferred":[
        "\u0627\u0633\u0627\u0645\u0648"
    ],
    "wof:name":"Assamo",
    "wof:placetype":"locality"
},
  "geometry": {"coordinates":[40.10139,-12.39194],"type":"Point"}
}