{
  "type": "Feature",
  "properties": {
    "gn:admin1_code":"0",
    "gn:asciiname":"Alfaiate",
    "gn:country_code":"MZ",
    "gn:dem":10,
    "gn:feature_class":"P",
    "gn:feature_code":"PPL",
    "gn:name":"Alfaiate",
    "gn:population":0,
    "gn:timezone":"Africa/Maputo",
    "iso:country":"MZ",
    "wof:name":"Alfaiate",
    "wof:placetype":"locality"
},
  "geometry": {"coordinates":[35.91667,-18.28333],"type":"Point"}
}