{
  "type": "Feature",
  "properties": {
    "gn:admin1_code":"3",
    "gn:asciiname":"Matoloquico",
    "gn:country_code":"MZ",
    "gn:dem":70,
    "gn:feature_class":"P",
    "gn:feature_code":"PPL",
    "gn:name":"Mat\u00f3l\u00f3qui\u00e7o",
    "gn:population":0,
    "gn:timezone":"Africa/Maputo",
    "iso:country":"MZ",
    "wof:name":"Matoloquico",
    "wof:placetype":"locality"
},
  "geometry": {"coordinates":[33.74417,-23.00361],"type":"Point"}
}