{
  "type": "Feature",
  "properties": {
    "gn:admin1_code":"7",
    "gn:asciiname":"Mepeluia",
    "gn:country_code":"MZ",
    "gn:dem":549,
    "gn:feature_class":"P",
    "gn:feature_code":"PPL",
    "gn:name":"Mepeluia",
    "gn:population":0,
    "gn:timezone":"Africa/Maputo",
    "iso:country":"MZ",
    "wof:name":"Mepeluia",
    "wof:placetype":"locality"
},
  "geometry": {"coordinates":[36.53806,-13.19444],"type":"Point"}
}