{
  "type": "Feature",
  "properties": {
    "gn:admin1_code":"8",
    "gn:asciiname":"Massano",
    "gn:country_code":"MZ",
    "gn:dem":651,
    "gn:feature_class":"P",
    "gn:feature_code":"PPL",
    "gn:name":"Massano",
    "gn:population":0,
    "gn:timezone":"Africa/Maputo",
    "iso:country":"MZ",
    "wof:name":"Massano",
    "wof:placetype":"locality"
},
  "geometry": {"coordinates":[34.35028,-15.69472],"type":"Point"}
}