{
  "type": "Feature",
  "properties": {
    "gn:admin1_code":"10",
    "gn:asciiname":"Penicela",
    "gn:country_code":"MZ",
    "gn:dem":207,
    "gn:feature_class":"P",
    "gn:feature_code":"PPL",
    "gn:name":"Penicela",
    "gn:population":0,
    "gn:timezone":"Africa/Maputo",
    "iso:country":"MZ",
    "wof:name":"Penicela",
    "wof:placetype":"locality"
},
  "geometry": {"coordinates":[33.57528,-20.79056],"type":"Point"}
}