{
  "type": "Feature",
  "properties": {
    "gn:admin1_code":"3",
    "gn:asciiname":"Pangue",
    "gn:country_code":"MZ",
    "gn:dem":46,
    "gn:feature_class":"P",
    "gn:feature_code":"PPL",
    "gn:name":"Pangue",
    "gn:population":0,
    "gn:timezone":"Africa/Maputo",
    "iso:country":"MZ",
    "wof:name":"Pangue",
    "wof:placetype":"locality"
},
  "geometry": {"coordinates":[34.89278,-21.285],"type":"Point"}
}