{
  "type": "Feature",
  "properties": {
    "gn:admin1_code":"3.0",
    "gn:asciiname":"Chefe Chiguemane",
    "gn:country_code":"MZ",
    "gn:dem":55,
    "gn:feature_class":"P",
    "gn:feature_code":"PPL",
    "gn:name":"Chefe Chiguemane",
    "gn:population":0,
    "gn:timezone":"Africa/Maputo",
    "iso:country":"MZ",
    "wof:name":"Chefe Chiguemane",
    "wof:placetype":"locality"
},
  "geometry": {"coordinates":[34.27806,-21.3425],"type":"Point"}
}