{
  "type": "Feature",
  "properties": {
    "gn:admin1_code":"5.0",
    "gn:asciiname":"Sombreiro",
    "gn:country_code":"MZ",
    "gn:dem":73,
    "gn:feature_class":"P",
    "gn:feature_code":"PPL",
    "gn:name":"Sombreiro",
    "gn:population":0,
    "gn:timezone":"Africa/Maputo",
    "iso:country":"MZ",
    "wof:name":"Sombreiro",
    "wof:placetype":"locality"
},
  "geometry": {"coordinates":[35.05417,-18.14167],"type":"Point"}
}