{
  "type": "Feature",
  "properties": {
    "gn:admin1_code":"1",
    "gn:asciiname":"Ahema",
    "gn:country_code":"MZ",
    "gn:dem":377,
    "gn:feature_class":"P",
    "gn:feature_code":"PPL",
    "gn:name":"Ahema",
    "gn:population":0,
    "gn:timezone":"Africa/Maputo",
    "iso:country":"MZ",
    "wof:name":"Ahema",
    "wof:placetype":"locality"
},
  "geometry": {"coordinates":[39.85472,-11.35889],"type":"Point"}
}