{
  "type": "Feature",
  "properties": {
    "gn:admin1_code":"7.0",
    "gn:asciiname":"Tavatava",
    "gn:country_code":"MZ",
    "gn:dem":142,
    "gn:feature_class":"P",
    "gn:feature_code":"PPL",
    "gn:name":"Tavatava",
    "gn:population":0,
    "gn:timezone":"Africa/Maputo",
    "iso:country":"MZ",
    "wof:name":"Tavatava",
    "wof:placetype":"locality"
},
  "geometry": {"coordinates":[38.44889000000001,-11.47694],"type":"Point"}
}