{
  "type": "Feature",
  "properties": {
    "gn:admin1_code":"6",
    "gn:asciiname":"Amade",
    "gn:country_code":"MZ",
    "gn:dem":70,
    "gn:feature_class":"P",
    "gn:feature_code":"PPL",
    "gn:name":"Amade",
    "gn:population":0,
    "gn:timezone":"Africa/Maputo",
    "iso:country":"MZ",
    "wof:name":"Amade",
    "wof:placetype":"locality"
},
  "geometry": {"coordinates":[40.79194,-14.65361],"type":"Point"}
}