{
  "type": "Feature",
  "properties": {
    "gn:admin1_code":"9",
    "gn:asciiname":"Casteano",
    "gn:country_code":"MZ",
    "gn:dem":205,
    "gn:feature_class":"P",
    "gn:feature_code":"PPL",
    "gn:name":"Casteano",
    "gn:population":0,
    "gn:timezone":"Africa/Maputo",
    "iso:country":"MZ",
    "wof:name":"Casteano",
    "wof:placetype":"locality"
},
  "geometry": {"coordinates":[35.8025,-17.49417],"type":"Point"}
}