{
  "type": "Feature",
  "properties": {
    "gn:admin1_code":"3",
    "gn:asciiname":"Medau",
    "gn:country_code":"MZ",
    "gn:dem":190,
    "gn:feature_class":"P",
    "gn:feature_code":"PPL",
    "gn:name":"Medau",
    "gn:population":0,
    "gn:timezone":"Africa/Maputo",
    "iso:country":"MZ",
    "wof:name":"Medau",
    "wof:placetype":"locality"
},
  "geometry": {"coordinates":[33.8025,-22.11611],"type":"Point"}
}