{
  "type": "Feature",
  "properties": {
    "gn:admin1_code":"6.0",
    "gn:asciiname":"Rivai",
    "gn:country_code":"MZ",
    "gn:dem":191,
    "gn:feature_class":"P",
    "gn:feature_code":"PPL",
    "gn:name":"Rivai",
    "gn:population":0,
    "gn:timezone":"Africa/Maputo",
    "iso:country":"MZ",
    "wof:name":"Rivai",
    "wof:placetype":"locality"
},
  "geometry": {"coordinates":[40.36889,-14.46389],"type":"Point"}
}