{
  "type": "Feature",
  "properties": {
    "gn:admin1_code":"9",
    "gn:asciiname":"Minato",
    "gn:country_code":"MZ",
    "gn:dem":71,
    "gn:feature_class":"P",
    "gn:feature_code":"PPL",
    "gn:name":"Minato",
    "gn:population":0,
    "gn:timezone":"Africa/Maputo",
    "iso:country":"MZ",
    "name:deu_x_preferred":[
        "Minato"
    ],
    "name:fin_x_preferred":[
        "Minato"
    ],
    "name:fra_x_preferred":[
        "Minato"
    ],
    "name:ind_x_preferred":[
        "Minato"
    ],
    "name:ita_x_preferred":[
        "Minato"
    ],
    "name:jpn_x_preferred":[
        "\u307f\u306a\u3068"
    ],
    "name:kor_x_preferred":[
        "\ubbf8\ub098\ud1a0"
    ],
    "name:mlg_x_preferred":[
        "Minato"
    ],
    "name:pol_x_preferred":[
        "Minato"
    ],
    "name:sco_x_preferred":[
        "Minato"
    ],
    "wof:name":"Minato",
    "wof:placetype":"locality"
},
  "geometry": {"coordinates":[37.65389,-17.13694],"type":"Point"}
}