{
  "type": "Feature",
  "properties": {
    "gn:admin1_code":"2.0",
    "gn:asciiname":"Chefe Maciene",
    "gn:country_code":"MZ",
    "gn:dem":35,
    "gn:feature_class":"P",
    "gn:feature_code":"PPL",
    "gn:name":"Chefe Maciene",
    "gn:population":0,
    "gn:timezone":"Africa/Maputo",
    "iso:country":"MZ",
    "wof:name":"Chefe Maciene",
    "wof:placetype":"locality"
},
  "geometry": {"coordinates":[33.84472,-25.04361],"type":"Point"}
}