{
  "type": "Feature",
  "properties": {
    "gn:admin1_code":"9",
    "gn:asciiname":"Mategamuno",
    "gn:country_code":"MZ",
    "gn:dem":7,
    "gn:feature_class":"P",
    "gn:feature_code":"PPL",
    "gn:name":"Mategamuno",
    "gn:population":0,
    "gn:timezone":"Africa/Maputo",
    "iso:country":"MZ",
    "wof:name":"Mategamuno",
    "wof:placetype":"locality"
},
  "geometry": {"coordinates":[37.445,-17.46861],"type":"Point"}
}