{
  "type": "Feature",
  "properties": {
    "gn:admin1_code":"1",
    "gn:asciiname":"More",
    "gn:country_code":"MZ",
    "gn:dem":627,
    "gn:feature_class":"P",
    "gn:feature_code":"PPL",
    "gn:name":"More",
    "gn:population":0,
    "gn:timezone":"Africa/Maputo",
    "iso:country":"MZ",
    "name:bos_x_preferred":[
        "More"
    ],
    "name:ceb_x_preferred":[
        "More"
    ],
    "name:ces_x_preferred":[
        "More"
    ],
    "name:dan_x_preferred":[
        "More"
    ],
    "name:deu_x_preferred":[
        "More"
    ],
    "name:est_x_preferred":[
        "More"
    ],
    "name:fas_x_preferred":[
        "\u0628\u06cc\u0634\u062a\u0631"
    ],
    "name:fin_x_preferred":[
        "More"
    ],
    "name:fra_x_preferred":[
        "More"
    ],
    "name:hrv_x_preferred":[
        "More"
    ],
    "name:hun_x_preferred":[
        "More"
    ],
    "name:ita_x_preferred":[
        "More"
    ],
    "name:kor_x_preferred":[
        "\ubaa8\uc5b4"
    ],
    "name:ltz_x_preferred":[
        "More"
    ],
    "name:nld_x_preferred":[
        "More"
    ],
    "name:nor_x_preferred":[
        "More"
    ],
    "name:pol_x_preferred":[
        "More"
    ],
    "name:por_x_preferred":[
        "More"
    ],
    "name:rus_x_preferred":[
        "More"
    ],
    "name:slk_x_preferred":[
        "More"
    ],
    "name:slv_x_preferred":[
        "More"
    ],
    "name:spa_x_preferred":[
        "More"
    ],
    "name:swe_x_preferred":[
        "More"
    ],
    "name:zho_x_preferred":[
        "More"
    ],
    "wof:name":"More",
    "wof:placetype":"locality"
},
  "geometry": {"coordinates":[38.415,-13.55389],"type":"Point"}
}