{
  "type": "Feature",
  "properties": {
    "gn:admin1_code":"1",
    "gn:asciiname":"More",
    "gn:country_code":"MZ",
    "gn:dem":627,
    "gn:feature_class":"P",
    "gn:feature_code":"PPL",
    "gn:name":"More",
    "gn:population":0,
    "gn:timezone":"Africa/Maputo",
    "iso:country":"MZ",
    "wof:name":"More",
    "wof:placetype":"locality"
},
  "geometry": {"coordinates":[38.415,-13.55389],"type":"Point"}
}