{
  "type": "Feature",
  "properties": {
    "gn:admin1_code":"3",
    "gn:asciiname":"Inhacumana",
    "gn:country_code":"MZ",
    "gn:dem":152,
    "gn:feature_class":"P",
    "gn:feature_code":"PPL",
    "gn:name":"Inhacumana",
    "gn:population":0,
    "gn:timezone":"Africa/Maputo",
    "iso:country":"MZ",
    "wof:name":"Inhacumana",
    "wof:placetype":"locality"
},
  "geometry": {"coordinates":[33.61222,-22.50639],"type":"Point"}
}