{
  "type": "Feature",
  "properties": {
    "gn:admin1_code":"6",
    "gn:asciiname":"Mecueia",
    "gn:country_code":"MZ",
    "gn:dem":219,
    "gn:feature_class":"P",
    "gn:feature_code":"PPL",
    "gn:name":"Mecueia",
    "gn:population":0,
    "gn:timezone":"Africa/Maputo",
    "iso:country":"MZ",
    "wof:name":"Mecueia",
    "wof:placetype":"locality"
},
  "geometry": {"coordinates":[40.28722,-14.52056],"type":"Point"}
}