{
  "type": "Feature",
  "properties": {
    "gn:admin1_code":"3",
    "gn:asciiname":"Matorrane",
    "gn:country_code":"MZ",
    "gn:dem":128,
    "gn:feature_class":"P",
    "gn:feature_code":"PPL",
    "gn:name":"Matorrane",
    "gn:population":0,
    "gn:timezone":"Africa/Maputo",
    "iso:country":"MZ",
    "wof:name":"Matorrane",
    "wof:placetype":"locality"
},
  "geometry": {"coordinates":[33.98139,-22.84472],"type":"Point"}
}