{
  "type": "Feature",
  "properties": {
    "gn:admin1_code":"7",
    "gn:asciiname":"Machele",
    "gn:country_code":"MZ",
    "gn:dem":598,
    "gn:feature_class":"P",
    "gn:feature_code":"PPL",
    "gn:name":"Machele",
    "gn:population":0,
    "gn:timezone":"Africa/Maputo",
    "iso:country":"MZ",
    "wof:name":"Machele",
    "wof:placetype":"locality"
},
  "geometry": {"coordinates":[34.89111,-13.37389],"type":"Point"}
}