{
  "type": "Feature",
  "properties": {
    "gn:admin1_code":"8",
    "gn:asciiname":"Aldeia Chapaluca",
    "gn:country_code":"MZ",
    "gn:dem":446,
    "gn:feature_class":"P",
    "gn:feature_code":"PPL",
    "gn:name":"Aldeia Chapaluca",
    "gn:population":0,
    "gn:timezone":"Africa/Maputo",
    "iso:country":"MZ",
    "wof:name":"Aldeia Chapaluca",
    "wof:placetype":"locality"
},
  "geometry": {"coordinates":[33.6575,-15.51556],"type":"Point"}
}