{
  "type": "Feature",
  "properties": {
    "gn:admin1_code":"1",
    "gn:asciiname":"Guatche",
    "gn:country_code":"MZ",
    "gn:dem":284,
    "gn:feature_class":"P",
    "gn:feature_code":"PPL",
    "gn:name":"Guatche",
    "gn:population":0,
    "gn:timezone":"Africa/Maputo",
    "iso:country":"MZ",
    "wof:name":"Guatche",
    "wof:placetype":"locality"
},
  "geometry": {"coordinates":[39.96194000000001,-12.29972],"type":"Point"}
}