{
  "type": "Feature",
  "properties": {
    "gn:admin1_code":"6",
    "gn:asciiname":"Lurio",
    "gn:country_code":"MZ",
    "gn:dem":359,
    "gn:feature_class":"P",
    "gn:feature_code":"PPL",
    "gn:name":"L\u00fario",
    "gn:population":0,
    "gn:timezone":"Africa/Maputo",
    "iso:country":"MZ",
    "wof:name":"Lurio",
    "wof:placetype":"locality"
},
  "geometry": {"coordinates":[38.60194,-14.20167],"type":"Point"}
}