{
  "type": "Feature",
  "properties": {
    "gn:admin1_code":"9",
    "gn:asciiname":"Mucarara",
    "gn:country_code":"MZ",
    "gn:dem":584,
    "gn:feature_class":"P",
    "gn:feature_code":"PPL",
    "gn:name":"Mucarara",
    "gn:population":0,
    "gn:timezone":"Africa/Maputo",
    "iso:country":"MZ",
    "wof:name":"Mucarara",
    "wof:placetype":"locality"
},
  "geometry": {"coordinates":[38.02167,-15.3925],"type":"Point"}
}