{
  "type": "Feature",
  "properties": {
    "gn:admin1_code":"10.0",
    "gn:asciiname":"Zixixe",
    "gn:country_code":"MZ",
    "gn:dem":747,
    "gn:feature_class":"P",
    "gn:feature_code":"PPL",
    "gn:name":"Zixixe",
    "gn:population":0,
    "gn:timezone":"Africa/Maputo",
    "iso:country":"MZ",
    "wof:name":"Zixixe",
    "wof:placetype":"locality"
},
  "geometry": {"coordinates":[33.1275,-19.35806],"type":"Point"}
}