{
  "type": "Feature",
  "properties": {
    "gn:admin1_code":"7",
    "gn:asciiname":"Chefe Nanchapa",
    "gn:country_code":"MZ",
    "gn:dem":695,
    "gn:feature_class":"P",
    "gn:feature_code":"PPL",
    "gn:name":"Chefe Nanchapa",
    "gn:population":0,
    "gn:timezone":"Africa/Maputo",
    "iso:country":"MZ",
    "wof:name":"Chefe Nanchapa",
    "wof:placetype":"locality"
},
  "geometry": {"coordinates":[36.12583,-15.05778],"type":"Point"}
}