{
  "type": "Feature",
  "properties": {
    "gn:admin1_code":"3",
    "gn:asciiname":"Morrumbene",
    "gn:country_code":"MZ",
    "gn:dem":48,
    "gn:feature_class":"P",
    "gn:feature_code":"PPL",
    "gn:name":"Morrumbene",
    "gn:population":0,
    "gn:timezone":"Africa/Maputo",
    "iso:country":"MZ",
    "wof:name":"Morrumbene",
    "wof:placetype":"locality"
},
  "geometry": {"coordinates":[35.345,-23.65778],"type":"Point"}
}