{
  "type": "Feature",
  "properties": {
    "gn:admin1_code":"9",
    "gn:asciiname":"Muue",
    "gn:country_code":"MZ",
    "gn:dem":282,
    "gn:feature_class":"P",
    "gn:feature_code":"PPL",
    "gn:name":"Muue",
    "gn:population":0,
    "gn:timezone":"Africa/Maputo",
    "iso:country":"MZ",
    "wof:name":"Muue",
    "wof:placetype":"locality"
},
  "geometry": {"coordinates":[37.63917,-16.31194],"type":"Point"}
}