{
  "type": "Feature",
  "properties": {
    "iso:country":"MZ",
    "name:und_x_variant":[
        "Alto Limpopo"
    ],
    "qs:gn_country":"MZ",
    "qs:gn_fcode":"PPL",
    "qs:gn_pop":0,
    "qs:name":"Paf\u00fari",
    "qs:name_adm0":"Mo\u00e7ambique",
    "qs:name_adm1":"Gaza",
    "qs:photos":58,
    "qs:photos_1k":12,
    "qs:photos_9k":1,
    "qs:photos_9r":2,
    "qs:photos_all":58,
    "qs:photos_sr":2,
    "qs:placetype":"Town",
    "qs:pop_sr":"4",
    "qs:woe_adm0":23424902,
    "wof:name":"Paf\u00fari",
    "wof:placetype":"locality"
},
  "geometry": {"coordinates":[31.33278,-22.45306],"type":"Point"}
}