{
  "type": "Feature",
  "properties": {
    "gn:admin1_code":"7",
    "gn:asciiname":"Messiage",
    "gn:country_code":"MZ",
    "gn:dem":641,
    "gn:feature_class":"P",
    "gn:feature_code":"PPL",
    "gn:name":"Messiage",
    "gn:population":0,
    "gn:timezone":"Africa/Maputo",
    "iso:country":"MZ",
    "wof:name":"Messiage",
    "wof:placetype":"locality"
},
  "geometry": {"coordinates":[36.07583,-13.77806],"type":"Point"}
}