{
  "type": "Feature",
  "properties": {
    "gn:admin1_code":"3",
    "gn:asciiname":"Chefe Magoba",
    "gn:cc2":"MZ",
    "gn:country_code":"MZ",
    "gn:dem":55,
    "gn:feature_class":"P",
    "gn:feature_code":"PPL",
    "gn:name":"Chefe Magoba",
    "gn:population":0,
    "gn:timezone":"Africa/Maputo",
    "iso:country":"MZ",
    "name:und_x_variant":[
        "Naife",
        "Chefe Magoba"
    ],
    "wof:name":"Chefe Magoba",
    "wof:placetype":"locality"
},
  "geometry": {"coordinates":[35.36944000000001,-24.21556],"type":"Point"}
}