{
  "type": "Feature",
  "properties": {
    "gn:admin1_code":"3.0",
    "gn:asciiname":"Feniasse Bie",
    "gn:country_code":"MZ",
    "gn:dem":82,
    "gn:feature_class":"P",
    "gn:feature_code":"PPL",
    "gn:name":"Feniasse Bie",
    "gn:population":0,
    "gn:timezone":"Africa/Maputo",
    "iso:country":"MZ",
    "wof:name":"Feniasse Bie",
    "wof:placetype":"locality"
},
  "geometry": {"coordinates":[34.71944000000001,-24.50833],"type":"Point"}
}