{
  "type": "Feature",
  "properties": {
    "gn:admin1_code":"6",
    "gn:asciiname":"Saua-Saua",
    "gn:country_code":"MZ",
    "gn:dem":280,
    "gn:feature_class":"P",
    "gn:feature_code":"PPL",
    "gn:name":"Saua-Saua",
    "gn:population":0,
    "gn:timezone":"Africa/Maputo",
    "iso:country":"MZ",
    "wof:name":"Saua-Saua",
    "wof:placetype":"locality"
},
  "geometry": {"coordinates":[39.7975,-14.2325],"type":"Point"}
}