{
  "type": "Feature",
  "properties": {
    "gn:admin1_code":"4",
    "gn:asciiname":"O. Bruheim",
    "gn:country_code":"MZ",
    "gn:dem":11,
    "gn:feature_class":"P",
    "gn:feature_code":"PPL",
    "gn:name":"O. Bruheim",
    "gn:population":0,
    "gn:timezone":"Africa/Maputo",
    "iso:country":"MZ",
    "wof:name":"O. Bruheim",
    "wof:placetype":"locality"
},
  "geometry": {"coordinates":[32.54611,-26.035],"type":"Point"}
}