{
  "type": "Feature",
  "properties": {
    "gn:admin1_code":"1",
    "gn:asciiname":"Chefo",
    "gn:country_code":"MZ",
    "gn:dem":58,
    "gn:feature_class":"P",
    "gn:feature_code":"PPL",
    "gn:name":"Chefo",
    "gn:population":0,
    "gn:timezone":"Africa/Maputo",
    "iso:country":"MZ",
    "wof:name":"Chefo",
    "wof:placetype":"locality"
},
  "geometry": {"coordinates":[40.125,-11.76361],"type":"Point"}
}