{
  "type": "Feature",
  "properties": {
    "gn:admin1_code":"8",
    "gn:asciiname":"Cusaduca",
    "gn:country_code":"MZ",
    "gn:dem":46,
    "gn:feature_class":"P",
    "gn:feature_code":"PPL",
    "gn:name":"Cusaduca",
    "gn:population":0,
    "gn:timezone":"Africa/Maputo",
    "iso:country":"MZ",
    "wof:name":"Cusaduca",
    "wof:placetype":"locality"
},
  "geometry": {"coordinates":[35.14139,-17.3375],"type":"Point"}
}