{
  "type": "Feature",
  "properties": {
    "gn:admin1_code":"3.0",
    "gn:asciiname":"Penicele Guambe",
    "gn:country_code":"MZ",
    "gn:dem":95,
    "gn:feature_class":"P",
    "gn:feature_code":"PPL",
    "gn:name":"Penicele Guambe",
    "gn:population":0,
    "gn:timezone":"Africa/Maputo",
    "iso:country":"MZ",
    "wof:name":"Penicele Guambe",
    "wof:placetype":"locality"
},
  "geometry": {"coordinates":[34.81694,-24.39611],"type":"Point"}
}