{
  "type": "Feature",
  "properties": {
    "gn:admin1_code":"8",
    "gn:asciiname":"Metaruca",
    "gn:cc2":"MZ",
    "gn:country_code":"MZ",
    "gn:dem":520,
    "gn:feature_class":"P",
    "gn:feature_code":"PPL",
    "gn:name":"Metaruca",
    "gn:population":0,
    "gn:timezone":"Africa/Maputo",
    "iso:country":"MZ",
    "name:und_x_variant":[
        "Metarurca",
        "Metaruca"
    ],
    "wof:name":"Metaruca",
    "wof:placetype":"locality"
},
  "geometry": {"coordinates":[32.57,-15.23722],"type":"Point"}
}