{
  "type": "Feature",
  "properties": {
    "iso:country":"MZ",
    "name:afr_x_preferred":[
        "Ponta do Ouro"
    ],
    "name:cat_x_preferred":[
        "Ponta do Ouro"
    ],
    "name:deu_x_preferred":[
        "Ponta do Ouro"
    ],
    "name:eng_x_preferred":[
        "Ponta do Ouro"
    ],
    "name:fra_x_preferred":[
        "Ponta do Ouro"
    ],
    "name:jpn_x_preferred":[
        "\u30dd\u30f3\u30bf\u30fb\u30c9\u30a6\u30ed"
    ],
    "name:nld_x_preferred":[
        "Ponta do Ouro"
    ],
    "name:por_x_preferred":[
        "Ponta do Ouro"
    ],
    "name:ron_x_preferred":[
        "Ponta d'Ouro"
    ],
    "qs:gn_country":"MZ",
    "qs:gn_fcode":"PPL",
    "qs:gn_pop":0,
    "qs:name":"Ponta do Ouro",
    "qs:name_adm0":"Mo\u00e7ambique",
    "qs:name_adm1":"Maputo",
    "qs:photos":451,
    "qs:photos_1k":91,
    "qs:photos_9k":2,
    "qs:photos_9r":5,
    "qs:photos_all":451,
    "qs:photos_sr":7,
    "qs:placetype":"Town",
    "qs:pop_sr":"0",
    "qs:woe_adm0":23424902,
    "wd:wordcount":393,
    "wof:name":"Ponta do Ouro",
    "wof:placetype":"locality"
},
  "geometry": {"coordinates":[32.88783,-26.84781],"type":"Point"}
}