{
  "type": "Feature",
  "properties": {
    "gn:admin1_code":"5",
    "gn:asciiname":"Gore",
    "gn:country_code":"MZ",
    "gn:dem":14,
    "gn:feature_class":"P",
    "gn:feature_code":"PPL",
    "gn:name":"Gore",
    "gn:population":0,
    "gn:timezone":"Africa/Maputo",
    "iso:country":"MZ",
    "wof:name":"Gore",
    "wof:placetype":"locality"
},
  "geometry": {"coordinates":[34.33861,-19.49417],"type":"Point"}
}