{
  "type": "Feature",
  "properties": {
    "gn:admin1_code":"7",
    "gn:asciiname":"Namanha",
    "gn:country_code":"MZ",
    "gn:dem":325,
    "gn:feature_class":"P",
    "gn:feature_code":"PPL",
    "gn:name":"Namanha",
    "gn:population":0,
    "gn:timezone":"Africa/Maputo",
    "iso:country":"MZ",
    "wof:name":"Namanha",
    "wof:placetype":"locality"
},
  "geometry": {"coordinates":[37.84972,-11.84139],"type":"Point"}
}