{
  "type": "Feature",
  "properties": {
    "gn:admin1_code":"10.0",
    "gn:asciiname":"Uncuzaduto",
    "gn:country_code":"MZ",
    "gn:dem":484,
    "gn:feature_class":"P",
    "gn:feature_code":"PPL",
    "gn:name":"Uncuzaduto",
    "gn:population":0,
    "gn:timezone":"Africa/Maputo",
    "iso:country":"MZ",
    "wof:name":"Uncuzaduto",
    "wof:placetype":"locality"
},
  "geometry": {"coordinates":[33.78805999999999,-17.17611],"type":"Point"}
}