{
  "type": "Feature",
  "properties": {
    "gn:admin1_code":"5",
    "gn:asciiname":"Candieiro",
    "gn:country_code":"MZ",
    "gn:dem":346,
    "gn:feature_class":"P",
    "gn:feature_code":"PPL",
    "gn:name":"Candieiro",
    "gn:population":0,
    "gn:timezone":"Africa/Maputo",
    "iso:country":"MZ",
    "wof:name":"Candieiro",
    "wof:placetype":"locality"
},
  "geometry": {"coordinates":[33.69917,-18.71722],"type":"Point"}
}