{
  "type": "Feature",
  "properties": {
    "gn:admin1_code":"1",
    "gn:asciiname":"Dade Bacar",
    "gn:country_code":"MZ",
    "gn:dem":110,
    "gn:feature_class":"P",
    "gn:feature_code":"PPL",
    "gn:name":"Dade Bacar",
    "gn:population":0,
    "gn:timezone":"Africa/Maputo",
    "iso:country":"MZ",
    "wof:name":"Dade Bacar",
    "wof:placetype":"locality"
},
  "geometry": {"coordinates":[40.22278,-10.68611],"type":"Point"}
}