{
  "type": "Feature",
  "properties": {
    "gn:admin1_code":"9",
    "gn:asciiname":"Mecula",
    "gn:country_code":"MZ",
    "gn:dem":198,
    "gn:feature_class":"P",
    "gn:feature_code":"PPL",
    "gn:name":"Mecula",
    "gn:population":0,
    "gn:timezone":"Africa/Maputo",
    "iso:country":"MZ",
    "wof:name":"Mecula",
    "wof:placetype":"locality"
},
  "geometry": {"coordinates":[36.68389000000001,-17.09889],"type":"Point"}
}