{
  "type": "Feature",
  "properties": {
    "gn:admin1_code":"1",
    "gn:asciiname":"Nambule",
    "gn:country_code":"MZ",
    "gn:dem":900,
    "gn:feature_class":"P",
    "gn:feature_code":"PPL",
    "gn:name":"Nambul\u00e8",
    "gn:population":0,
    "gn:timezone":"Africa/Maputo",
    "iso:country":"MZ",
    "wof:name":"Nambule",
    "wof:placetype":"locality"
},
  "geometry": {"coordinates":[39.37194,-11.43778],"type":"Point"}
}