{
  "type": "Feature",
  "properties": {
    "gn:admin1_code":"4",
    "gn:asciiname":"Santana de Tinonganine",
    "gn:cc2":"MZ",
    "gn:country_code":"MZ",
    "gn:dem":53,
    "gn:feature_class":"P",
    "gn:feature_code":"PPL",
    "gn:name":"Santana de Tinonganine",
    "gn:population":0,
    "gn:timezone":"Africa/Maputo",
    "iso:country":"MZ",
    "name:und_x_variant":[
        "Tinonganine",
        "Santana de Tinonganine"
    ],
    "wof:name":"Santana de Tinonganine",
    "wof:placetype":"locality"
},
  "geometry": {"coordinates":[32.57472,-26.48833],"type":"Point"}
}