{
  "type": "Feature",
  "properties": {
    "gn:admin1_code":"10",
    "gn:asciiname":"Muquasi",
    "gn:cc2":"MZ",
    "gn:country_code":"MZ",
    "gn:dem":145,
    "gn:feature_class":"P",
    "gn:feature_code":"PPL",
    "gn:name":"Muquasi",
    "gn:population":0,
    "gn:timezone":"Africa/Maputo",
    "iso:country":"MZ",
    "name:und_x_variant":[
        "Muguasi",
        "Muquasi"
    ],
    "wof:name":"Muquasi",
    "wof:placetype":"locality"
},
  "geometry": {"coordinates":[33.22167,-20.42139],"type":"Point"}
}