{
  "type": "Feature",
  "properties": {
    "gn:admin1_code":"7",
    "gn:asciiname":"Nicole",
    "gn:country_code":"MZ",
    "gn:dem":1248,
    "gn:feature_class":"P",
    "gn:feature_code":"PPL",
    "gn:name":"Nicole",
    "gn:population":0,
    "gn:timezone":"Africa/Maputo",
    "iso:country":"MZ",
    "wof:name":"Nicole",
    "wof:placetype":"locality"
},
  "geometry": {"coordinates":[35.20667,-13.1275],"type":"Point"}
}