{
  "type": "Feature",
  "properties": {
    "gn:admin1_code":"7",
    "gn:asciiname":"Nicole",
    "gn:country_code":"MZ",
    "gn:dem":1248,
    "gn:feature_class":"P",
    "gn:feature_code":"PPL",
    "gn:name":"Nicole",
    "gn:population":0,
    "gn:timezone":"Africa/Maputo",
    "iso:country":"MZ",
    "name:bul_x_preferred":[
        "\u041d\u0438\u043a\u043e\u043b"
    ],
    "name:ces_x_preferred":[
        "Nicole"
    ],
    "name:dan_x_preferred":[
        "Nicole"
    ],
    "name:deu_x_preferred":[
        "Nicole"
    ],
    "name:epo_x_preferred":[
        "Nicole"
    ],
    "name:est_x_preferred":[
        "Nicole"
    ],
    "name:eus_x_preferred":[
        "Nicole"
    ],
    "name:fas_x_preferred":[
        "\u0646\u06cc\u06a9\u0648\u0644"
    ],
    "name:fin_x_preferred":[
        "Nicole"
    ],
    "name:fra_x_preferred":[
        "Nicole"
    ],
    "name:heb_x_preferred":[
        "\u05e0\u05d9\u05e7\u05d5\u05dc"
    ],
    "name:ita_x_preferred":[
        "Nicole"
    ],
    "name:nds_x_preferred":[
        "Nicole"
    ],
    "name:nld_x_preferred":[
        "Nicole"
    ],
    "name:pol_x_preferred":[
        "Nicole"
    ],
    "name:por_x_preferred":[
        "Nicole"
    ],
    "name:ron_x_preferred":[
        "Nicole"
    ],
    "name:rus_x_preferred":[
        "\u041d\u0438\u043a\u043e\u043b\u044c"
    ],
    "name:sco_x_preferred":[
        "Nicole"
    ],
    "name:spa_x_preferred":[
        "Nicole"
    ],
    "name:tur_x_preferred":[
        "Nicole"
    ],
    "name:ukr_x_preferred":[
        "\u041d\u0456\u043a\u043e\u043b\u044c"
    ],
    "name:vie_x_preferred":[
        "Nicole"
    ],
    "name:zho_x_preferred":[
        "\u59ae\u79d1\u5c14"
    ],
    "wof:name":"Nicole",
    "wof:placetype":"locality"
},
  "geometry": {"coordinates":[35.20667,-13.1275],"type":"Point"}
}