{
  "type": "Feature",
  "properties": {
    "gn:admin1_code":"1",
    "gn:asciiname":"Taipo",
    "gn:country_code":"MZ",
    "gn:dem":218,
    "gn:feature_class":"P",
    "gn:feature_code":"PPL",
    "gn:name":"Taipo",
    "gn:population":0,
    "gn:timezone":"Africa/Maputo",
    "iso:country":"MZ",
    "wof:name":"Taipo",
    "wof:placetype":"locality"
},
  "geometry": {"coordinates":[40.02056,-13.40472],"type":"Point"}
}