{
  "type": "Feature",
  "properties": {
    "gn:admin1_code":"6",
    "gn:asciiname":"Romao",
    "gn:country_code":"MZ",
    "gn:dem":577,
    "gn:feature_class":"P",
    "gn:feature_code":"PPL",
    "gn:name":"Romao",
    "gn:population":0,
    "gn:timezone":"Africa/Maputo",
    "iso:country":"MZ",
    "wof:name":"Romao",
    "wof:placetype":"locality"
},
  "geometry": {"coordinates":[37.84222000000001,-14.92528],"type":"Point"}
}