{
  "type": "Feature",
  "properties": {
    "gn:admin1_code":"3.0",
    "gn:asciiname":"J. Zimanhane",
    "gn:country_code":"MZ",
    "gn:dem":83,
    "gn:feature_class":"P",
    "gn:feature_code":"PPL",
    "gn:name":"J. Zimanhane",
    "gn:population":0,
    "gn:timezone":"Africa/Maputo",
    "iso:country":"MZ",
    "wof:name":"J. Zimanhane",
    "wof:placetype":"locality"
},
  "geometry": {"coordinates":[34.8225,-24.45944],"type":"Point"}
}