{
  "type": "Feature",
  "properties": {
    "gn:admin1_code":"9",
    "gn:asciiname":"Enchaua",
    "gn:country_code":"MZ",
    "gn:dem":263,
    "gn:feature_class":"P",
    "gn:feature_code":"PPL",
    "gn:name":"Enchaua",
    "gn:population":0,
    "gn:timezone":"Africa/Maputo",
    "iso:country":"MZ",
    "wof:name":"Enchaua",
    "wof:placetype":"locality"
},
  "geometry": {"coordinates":[35.48305999999999,-17.49639],"type":"Point"}
}