{
  "type": "Feature",
  "properties": {
    "gn:admin1_code":"5",
    "gn:asciiname":"Mangaze",
    "gn:cc2":"MZ",
    "gn:country_code":"MZ",
    "gn:dem":26,
    "gn:feature_class":"P",
    "gn:feature_code":"PPL",
    "gn:name":"Mangaze",
    "gn:population":0,
    "gn:timezone":"Africa/Maputo",
    "iso:country":"MZ",
    "name:und_x_variant":[
        "Mangaz",
        "Mangaze"
    ],
    "wof:name":"Mangaze",
    "wof:placetype":"locality"
},
  "geometry": {"coordinates":[35.43194000000001,-17.92361],"type":"Point"}
}