{
  "type": "Feature",
  "properties": {
    "gn:admin1_code":"2",
    "gn:asciiname":"Regedor Chaquelane",
    "gn:cc2":"MZ",
    "gn:country_code":"MZ",
    "gn:dem":41,
    "gn:feature_class":"P",
    "gn:feature_code":"PPL",
    "gn:name":"Regedor Chaquelane",
    "gn:population":0,
    "gn:timezone":"Africa/Maputo",
    "iso:country":"MZ",
    "name:und_x_variant":[
        "Chaquelane",
        "Regedor Chaquelane"
    ],
    "wof:name":"Regedor Chaquelane",
    "wof:placetype":"locality"
},
  "geometry": {"coordinates":[33.12944,-24.80917],"type":"Point"}
}