{
  "type": "Feature",
  "properties": {
    "gn:admin1_code":"9",
    "gn:asciiname":"Chefe Sirapa",
    "gn:country_code":"MZ",
    "gn:dem":704,
    "gn:feature_class":"P",
    "gn:feature_code":"PPL",
    "gn:name":"Chefe Sirapa",
    "gn:population":0,
    "gn:timezone":"Africa/Maputo",
    "iso:country":"MZ",
    "wof:name":"Chefe Sirapa",
    "wof:placetype":"locality"
},
  "geometry": {"coordinates":[35.82139,-15.93],"type":"Point"}
}