{
  "type": "Feature",
  "properties": {
    "gn:admin1_code":"6",
    "gn:asciiname":"Chefe Marue",
    "gn:country_code":"MZ",
    "gn:dem":48,
    "gn:feature_class":"P",
    "gn:feature_code":"PPL",
    "gn:name":"Chefe Maru\u00e9",
    "gn:population":0,
    "gn:timezone":"Africa/Maputo",
    "iso:country":"MZ",
    "wof:name":"Chefe Marue",
    "wof:placetype":"locality"
},
  "geometry": {"coordinates":[39.49361,-16.20194],"type":"Point"}
}