{
  "type": "Feature",
  "properties": {
    "gn:admin1_code":"2",
    "gn:asciiname":"Vila Eduardo Mondlane",
    "gn:country_code":"MZ",
    "gn:dem":456,
    "gn:feature_class":"P",
    "gn:feature_code":"PPL",
    "gn:name":"Vila Eduardo Mondlane",
    "gn:population":0,
    "gn:timezone":"Africa/Maputo",
    "iso:country":"MZ",
    "name:gag_x_preferred":[
        "Chicualacuala"
    ],
    "name:ind_x_preferred":[
        "Chicualacuala"
    ],
    "name:ita_x_preferred":[
        "Chicualacuala"
    ],
    "name:nld_x_preferred":[
        "Chicualacuala"
    ],
    "name:por_x_preferred":[
        "Chicualacuala"
    ],
    "name:ron_x_preferred":[
        "Chicualacuala"
    ],
    "name:spa_x_preferred":[
        "Chicualacuala"
    ],
    "name:und_x_variant":[
        "Chirotera",
        "Vila Eduardo Mondlane",
        "Chiqualaquala",
        "Malv\u00e9rnia"
    ],
    "name:vie_x_preferred":[
        "Malvernia"
    ],
    "name:zho_x_preferred":[
        "\u5e0c\u5938\u62c9\u5938\u62c9"
    ],
    "wof:name":"Vila Eduardo Mondlane",
    "wof:placetype":"locality"
},
  "geometry": {"coordinates":[31.67861,-22.07917],"type":"Point"}
}