{
  "type": "Feature",
  "properties": {
    "gn:admin1_code":"10.0",
    "gn:asciiname":"Quembo",
    "gn:country_code":"MZ",
    "gn:dem":561,
    "gn:feature_class":"P",
    "gn:feature_code":"PPL",
    "gn:name":"Quembo",
    "gn:population":0,
    "gn:timezone":"Africa/Maputo",
    "iso:country":"MZ",
    "wof:name":"Quembo",
    "wof:placetype":"locality"
},
  "geometry": {"coordinates":[33.24583,-18.73111],"type":"Point"}
}