{
  "type": "Feature",
  "properties": {
    "gn:admin1_code":"5.0",
    "gn:asciiname":"Sucudona",
    "gn:country_code":"MZ",
    "gn:dem":45,
    "gn:feature_class":"P",
    "gn:feature_code":"PPL",
    "gn:name":"Sucudona",
    "gn:population":0,
    "gn:timezone":"Africa/Maputo",
    "iso:country":"MZ",
    "wof:name":"Sucudona",
    "wof:placetype":"locality"
},
  "geometry": {"coordinates":[33.91778,-19.85167],"type":"Point"}
}