{
  "type": "Feature",
  "properties": {
    "gn:admin1_code":"1",
    "gn:asciiname":"Anena",
    "gn:country_code":"MZ",
    "gn:dem":311,
    "gn:feature_class":"P",
    "gn:feature_code":"PPL",
    "gn:name":"An\u00e9na",
    "gn:population":0,
    "gn:timezone":"Africa/Maputo",
    "iso:country":"MZ",
    "wof:name":"Anena",
    "wof:placetype":"locality"
},
  "geometry": {"coordinates":[38.84417,-14.06694],"type":"Point"}
}