{
  "type": "Feature",
  "properties": {
    "gn:admin1_code":"1",
    "gn:asciiname":"Metina",
    "gn:country_code":"MZ",
    "gn:dem":571,
    "gn:feature_class":"P",
    "gn:feature_code":"PPL",
    "gn:name":"Metina",
    "gn:population":0,
    "gn:timezone":"Africa/Maputo",
    "iso:country":"MZ",
    "name:vie_x_preferred":[
        "Metina"
    ],
    "wof:name":"Metina",
    "wof:placetype":"locality"
},
  "geometry": {"coordinates":[38.85139,-13.34694],"type":"Point"}
}