{
  "type": "Feature",
  "properties": {
    "gn:admin1_code":"6",
    "gn:asciiname":"Namico",
    "gn:country_code":"MZ",
    "gn:dem":116,
    "gn:feature_class":"P",
    "gn:feature_code":"PPL",
    "gn:name":"Namico",
    "gn:population":0,
    "gn:timezone":"Africa/Maputo",
    "iso:country":"MZ",
    "wof:name":"Namico",
    "wof:placetype":"locality"
},
  "geometry": {"coordinates":[39.94583,-15.51889],"type":"Point"}
}