{
  "type": "Feature",
  "properties": {
    "gn:admin1_code":"4",
    "gn:asciiname":"Chefe Mubabase",
    "gn:country_code":"MZ",
    "gn:dem":13,
    "gn:feature_class":"P",
    "gn:feature_code":"PPL",
    "gn:name":"Chefe Mub\u00e2base",
    "gn:population":0,
    "gn:timezone":"Africa/Maputo",
    "iso:country":"MZ",
    "wof:name":"Chefe Mubabase",
    "wof:placetype":"locality"
},
  "geometry": {"coordinates":[32.82972,-26.44611],"type":"Point"}
}