{
  "type": "Feature",
  "properties": {
    "gn:admin1_code":"9",
    "gn:asciiname":"Chire",
    "gn:cc2":"MZ",
    "gn:country_code":"MZ",
    "gn:dem":59,
    "gn:feature_class":"P",
    "gn:feature_code":"PPL",
    "gn:name":"Chire",
    "gn:population":0,
    "gn:timezone":"Africa/Maputo",
    "iso:country":"MZ",
    "name:und_x_variant":[
        "Chirombe",
        "Chire"
    ],
    "wof:name":"Chire",
    "wof:placetype":"locality"
},
  "geometry": {"coordinates":[35.34611,-16.69194],"type":"Point"}
}