{
  "type": "Feature",
  "properties": {
    "gn:admin1_code":"1",
    "gn:asciiname":"Diancar",
    "gn:country_code":"MZ",
    "gn:dem":970,
    "gn:feature_class":"P",
    "gn:feature_code":"PPL",
    "gn:name":"Diancar",
    "gn:population":0,
    "gn:timezone":"Africa/Maputo",
    "iso:country":"MZ",
    "wof:name":"Diancar",
    "wof:placetype":"locality"
},
  "geometry": {"coordinates":[39.44278,-11.55278],"type":"Point"}
}