{
  "type": "Feature",
  "properties": {
    "gn:admin1_code":"6.0",
    "gn:asciiname":"Quissimajula",
    "gn:cc2":"MZ",
    "gn:country_code":"MZ",
    "gn:dem":33,
    "gn:feature_class":"P",
    "gn:feature_code":"PPL",
    "gn:name":"Quissimajula",
    "gn:population":0,
    "gn:timezone":"Africa/Maputo",
    "iso:country":"MZ",
    "name:und_x_variant":[
        "Quissimajulo",
        "Quissemajulo",
        "Quissimajula"
    ],
    "wof:name":"Quissimajula",
    "wof:placetype":"locality"
},
  "geometry": {"coordinates":[40.79778,-14.51833],"type":"Point"}
}