{
  "type": "Feature",
  "properties": {
    "gn:admin1_code":"9.0",
    "gn:asciiname":"Uatea",
    "gn:country_code":"MZ",
    "gn:dem":183,
    "gn:feature_class":"P",
    "gn:feature_code":"PPL",
    "gn:name":"Uate\u00e0",
    "gn:population":0,
    "gn:timezone":"Africa/Maputo",
    "iso:country":"MZ",
    "wof:name":"Uatea",
    "wof:placetype":"locality"
},
  "geometry": {"coordinates":[37.86722,-16.60944],"type":"Point"}
}