{
  "type": "Feature",
  "properties": {
    "gn:admin1_code":"9",
    "gn:asciiname":"Cocarra",
    "gn:country_code":"MZ",
    "gn:dem":304,
    "gn:feature_class":"P",
    "gn:feature_code":"PPL",
    "gn:name":"Cocarra",
    "gn:population":0,
    "gn:timezone":"Africa/Maputo",
    "iso:country":"MZ",
    "wof:name":"Cocarra",
    "wof:placetype":"locality"
},
  "geometry": {"coordinates":[37.52722,-16.27417],"type":"Point"}
}