{
  "type": "Feature",
  "properties": {
    "gn:admin1_code":"9",
    "gn:asciiname":"Comua",
    "gn:cc2":"MZ",
    "gn:country_code":"MZ",
    "gn:dem":697,
    "gn:feature_class":"P",
    "gn:feature_code":"PPL",
    "gn:name":"Comua",
    "gn:population":0,
    "gn:timezone":"Africa/Maputo",
    "iso:country":"MZ",
    "name:und_x_variant":[
        "Comum-a",
        "Comua"
    ],
    "wof:name":"Comua",
    "wof:placetype":"locality"
},
  "geometry": {"coordinates":[37.56306,-15.26417],"type":"Point"}
}