{
  "type": "Feature",
  "properties": {
    "gn:admin1_code":"7",
    "gn:asciiname":"Minicua",
    "gn:country_code":"MZ",
    "gn:dem":654,
    "gn:feature_class":"P",
    "gn:feature_code":"PPL",
    "gn:name":"Minicua",
    "gn:population":0,
    "gn:timezone":"Africa/Maputo",
    "iso:country":"MZ",
    "wof:name":"Minicua",
    "wof:placetype":"locality"
},
  "geometry": {"coordinates":[36.09083,-13.60833],"type":"Point"}
}