{
  "type": "Feature",
  "properties": {
    "gn:admin1_code":"5",
    "gn:asciiname":"Mafambice",
    "gn:cc2":"MZ",
    "gn:country_code":"MZ",
    "gn:dem":14,
    "gn:feature_class":"P",
    "gn:feature_code":"PPL",
    "gn:name":"Mafambice",
    "gn:population":0,
    "gn:timezone":"Africa/Maputo",
    "iso:country":"MZ",
    "name:und_x_variant":[
        "Mafambisse",
        "Mafambice"
    ],
    "wof:name":"Mafambice",
    "wof:placetype":"locality"
},
  "geometry": {"coordinates":[34.62444,-19.54917],"type":"Point"}
}