{
  "type": "Feature",
  "properties": {
    "gn:admin1_code":"3",
    "gn:asciiname":"Macalacate",
    "gn:country_code":"MZ",
    "gn:dem":134,
    "gn:feature_class":"P",
    "gn:feature_code":"PPL",
    "gn:name":"Macalacate",
    "gn:population":0,
    "gn:timezone":"Africa/Maputo",
    "iso:country":"MZ",
    "wof:name":"Macalacate",
    "wof:placetype":"locality"
},
  "geometry": {"coordinates":[34.1725,-21.8225],"type":"Point"}
}