{
  "type": "Feature",
  "properties": {
    "gn:admin1_code":"7",
    "gn:asciiname":"Aldeia Lumbe",
    "gn:country_code":"MZ",
    "gn:dem":1266,
    "gn:feature_class":"P",
    "gn:feature_code":"PPL",
    "gn:name":"Aldeia Lumbe",
    "gn:population":0,
    "gn:timezone":"Africa/Maputo",
    "iso:country":"MZ",
    "wof:name":"Aldeia Lumbe",
    "wof:placetype":"locality"
},
  "geometry": {"coordinates":[35.25944000000001,-13.42056],"type":"Point"}
}