{
  "type": "Feature",
  "properties": {
    "gn:admin1_code":"4",
    "gn:asciiname":"Memo",
    "gn:country_code":"MZ",
    "gn:dem":276,
    "gn:feature_class":"P",
    "gn:feature_code":"PPL",
    "gn:name":"Memo",
    "gn:population":0,
    "gn:timezone":"Africa/Maputo",
    "iso:country":"MZ",
    "wof:name":"Memo",
    "wof:placetype":"locality"
},
  "geometry": {"coordinates":[32.11889,-26.42833],"type":"Point"}
}