{
  "type": "Feature",
  "properties": {
    "gn:admin1_code":"3",
    "gn:asciiname":"Gonhamo",
    "gn:country_code":"MZ",
    "gn:dem":138,
    "gn:feature_class":"P",
    "gn:feature_code":"PPL",
    "gn:name":"Gonhamo",
    "gn:population":0,
    "gn:timezone":"Africa/Maputo",
    "iso:country":"MZ",
    "wof:name":"Gonhamo",
    "wof:placetype":"locality"
},
  "geometry": {"coordinates":[34.50778,-21.71417000000001],"type":"Point"}
}