{
  "type": "Feature",
  "properties": {
    "gn:admin1_code":"3.0",
    "gn:asciiname":"Saisse",
    "gn:country_code":"MZ",
    "gn:dem":129,
    "gn:feature_class":"P",
    "gn:feature_code":"PPL",
    "gn:name":"Saisse",
    "gn:population":0,
    "gn:timezone":"Africa/Maputo",
    "iso:country":"MZ",
    "wof:name":"Saisse",
    "wof:placetype":"locality"
},
  "geometry": {"coordinates":[34.00778,-22.63639],"type":"Point"}
}