{
  "type": "Feature",
  "properties": {
    "gn:admin1_code":"1",
    "gn:asciiname":"Ametina",
    "gn:country_code":"MZ",
    "gn:dem":349,
    "gn:feature_class":"P",
    "gn:feature_code":"PPL",
    "gn:name":"Ametina",
    "gn:population":0,
    "gn:timezone":"Africa/Maputo",
    "iso:country":"MZ",
    "wof:name":"Ametina",
    "wof:placetype":"locality"
},
  "geometry": {"coordinates":[39.81639000000001,-13.27278],"type":"Point"}
}