{
  "type": "Feature",
  "properties": {
    "gn:admin1_code":"10",
    "gn:asciiname":"Arucato",
    "gn:country_code":"MZ",
    "gn:dem":238,
    "gn:feature_class":"P",
    "gn:feature_code":"PPL",
    "gn:name":"Arucato",
    "gn:population":0,
    "gn:timezone":"Africa/Maputo",
    "iso:country":"MZ",
    "wof:name":"Arucato",
    "wof:placetype":"locality"
},
  "geometry": {"coordinates":[33.53972,-20.6625],"type":"Point"}
}