{
  "type": "Feature",
  "properties": {
    "gn:admin1_code":"1",
    "gn:asciiname":"Chefe Aquimo",
    "gn:country_code":"MZ",
    "gn:dem":259,
    "gn:feature_class":"P",
    "gn:feature_code":"PPL",
    "gn:name":"Chefe Aquimo",
    "gn:population":0,
    "gn:timezone":"Africa/Maputo",
    "iso:country":"MZ",
    "wof:name":"Chefe Aquimo",
    "wof:placetype":"locality"
},
  "geometry": {"coordinates":[39.86472,-13.20194],"type":"Point"}
}