{
  "type": "Feature",
  "properties": {
    "gn:admin1_code":"8.0",
    "gn:asciiname":"Tchapita",
    "gn:country_code":"MZ",
    "gn:dem":71,
    "gn:feature_class":"P",
    "gn:feature_code":"PPL",
    "gn:name":"Tchapita",
    "gn:population":0,
    "gn:timezone":"Africa/Maputo",
    "iso:country":"MZ",
    "wof:name":"Tchapita",
    "wof:placetype":"locality"
},
  "geometry": {"coordinates":[34.78,-16.86277999999999],"type":"Point"}
}