{
  "type": "Feature",
  "properties": {
    "gn:admin1_code":"7",
    "gn:asciiname":"Aiuda",
    "gn:country_code":"MZ",
    "gn:dem":1189,
    "gn:feature_class":"P",
    "gn:feature_code":"PPL",
    "gn:name":"Aiuda",
    "gn:population":0,
    "gn:timezone":"Africa/Maputo",
    "iso:country":"MZ",
    "wof:name":"Aiuda",
    "wof:placetype":"locality"
},
  "geometry": {"coordinates":[35.56944,-13.32278],"type":"Point"}
}