{
  "type": "Feature",
  "properties": {
    "gn:admin1_code":"9",
    "gn:asciiname":"Gondoa",
    "gn:country_code":"MZ",
    "gn:dem":429,
    "gn:feature_class":"P",
    "gn:feature_code":"PPL",
    "gn:name":"Gond\u00f4a",
    "gn:population":0,
    "gn:timezone":"Africa/Maputo",
    "iso:country":"MZ",
    "wof:name":"Gondoa",
    "wof:placetype":"locality"
},
  "geometry": {"coordinates":[35.63778,-17.28278],"type":"Point"}
}