{
  "type": "Feature",
  "properties": {
    "gn:admin1_code":"7",
    "gn:asciiname":"Artur",
    "gn:country_code":"MZ",
    "gn:dem":476,
    "gn:feature_class":"P",
    "gn:feature_code":"PPL",
    "gn:name":"Artur",
    "gn:population":0,
    "gn:timezone":"Africa/Maputo",
    "iso:country":"MZ",
    "name:aze_x_preferred":[
        "Artur"
    ],
    "name:ces_x_preferred":[
        "Artur"
    ],
    "name:est_x_preferred":[
        "Artur"
    ],
    "name:fra_x_preferred":[
        "Artur"
    ],
    "name:glg_x_preferred":[
        "Artur"
    ],
    "name:nno_x_preferred":[
        "Artur"
    ],
    "name:nor_x_preferred":[
        "Artur"
    ],
    "name:pol_x_preferred":[
        "Artur"
    ],
    "name:slv_x_preferred":[
        "Artur"
    ],
    "name:swe_x_preferred":[
        "Artur"
    ],
    "wof:name":"Artur",
    "wof:placetype":"locality"
},
  "geometry": {"coordinates":[34.73139,-12.16],"type":"Point"}
}