{
  "type": "Feature",
  "properties": {
    "gn:admin1_code":"9",
    "gn:asciiname":"Chefe Mucajo",
    "gn:country_code":"MZ",
    "gn:dem":723,
    "gn:feature_class":"P",
    "gn:feature_code":"PPL",
    "gn:name":"Chefe Mucajo",
    "gn:population":0,
    "gn:timezone":"Africa/Maputo",
    "iso:country":"MZ",
    "wof:name":"Chefe Mucajo",
    "wof:placetype":"locality"
},
  "geometry": {"coordinates":[36.10278,-15.49167],"type":"Point"}
}