{
  "type": "Feature",
  "properties": {
    "gn:admin1_code":"3",
    "gn:asciiname":"Maquichilane",
    "gn:country_code":"MZ",
    "gn:dem":100,
    "gn:feature_class":"P",
    "gn:feature_code":"PPL",
    "gn:name":"Maquichilane",
    "gn:population":0,
    "gn:timezone":"Africa/Maputo",
    "iso:country":"MZ",
    "wof:name":"Maquichilane",
    "wof:placetype":"locality"
},
  "geometry": {"coordinates":[34.60889,-23.70111],"type":"Point"}
}