{
  "type": "Feature",
  "properties": {
    "gn:admin1_code":"9",
    "gn:asciiname":"Murrociua",
    "gn:country_code":"MZ",
    "gn:dem":79,
    "gn:feature_class":"P",
    "gn:feature_code":"PPL",
    "gn:name":"Murrociua",
    "gn:population":0,
    "gn:timezone":"Africa/Maputo",
    "iso:country":"MZ",
    "wof:name":"Murrociua",
    "wof:placetype":"locality"
},
  "geometry": {"coordinates":[37.92611,-17.20194],"type":"Point"}
}