{
  "type": "Feature",
  "properties": {
    "gn:admin1_code":"2.0",
    "gn:asciiname":"Leopoldina",
    "gn:country_code":"MZ",
    "gn:dem":77,
    "gn:feature_class":"P",
    "gn:feature_code":"PPL",
    "gn:name":"Leopoldina",
    "gn:population":0,
    "gn:timezone":"Africa/Maputo",
    "iso:country":"MZ",
    "name:ara_x_preferred":[
        "\u0644\u064a\u0648\u0628\u0648\u0644\u062f\u064a\u0646\u0627"
    ],
    "name:ben_x_preferred":[
        "\u09b2\u09c7\u0993\u09aa\u09b2\u09a6\u09bf\u09a8\u09be"
    ],
    "name:bre_x_preferred":[
        "Leopoldina"
    ],
    "name:ceb_x_preferred":[
        "Leopoldina"
    ],
    "name:deu_x_preferred":[
        "Leopoldina"
    ],
    "name:ell_x_preferred":[
        "\u039b\u03b5\u03bf\u03c0\u03bf\u03bb\u03b4\u03af\u03bd\u03b1"
    ],
    "name:fra_x_preferred":[
        "Leopoldina"
    ],
    "name:heb_x_preferred":[
        "\u05dc\u05d0\u05d5\u05e4\u05d5\u05dc\u05d3\u05d9\u05e0\u05d4"
    ],
    "name:hin_x_preferred":[
        "\u0932\u093f\u092f\u094b\u092a\u094b\u0932\u094d\u0921\u0940\u0928\u093e"
    ],
    "name:ind_x_preferred":[
        "Leopoldina"
    ],
    "name:ita_x_preferred":[
        "Leopoldina"
    ],
    "name:jpn_x_preferred":[
        "\u30ec\u30aa\u30dd\u30eb\u30c7\u30a3\u30fc\u30ca"
    ],
    "name:kor_x_preferred":[
        "\ub808\uc624\ud3f4\ub514\ub098"
    ],
    "name:mlg_x_preferred":[
        "Leopoldina"
    ],
    "name:nds_x_preferred":[
        "Leopoldina"
    ],
    "name:nld_x_preferred":[
        "Leopoldina"
    ],
    "name:por_x_preferred":[
        "Leopoldina"
    ],
    "name:slv_x_preferred":[
        "Leopoldina"
    ],
    "name:swe_x_preferred":[
        "Leopoldina"
    ],
    "name:tur_x_preferred":[
        "Leopoldina"
    ],
    "name:ukr_x_preferred":[
        "\u041b\u0435\u043e\u043f\u043e\u043b\u044c\u0434\u0456\u043d\u0430"
    ],
    "name:urd_x_preferred":[
        "\u0644\u06cc\u0648\u067e\u0648\u0644\u0688\u06cc\u0646\u0627"
    ],
    "wof:name":"Leopoldina",
    "wof:placetype":"locality"
},
  "geometry": {"coordinates":[33.66528,-24.76778],"type":"Point"}
}