{
  "type": "Feature",
  "properties": {
    "gn:admin1_code":"2.0",
    "gn:asciiname":"Leopoldina",
    "gn:country_code":"MZ",
    "gn:dem":77,
    "gn:feature_class":"P",
    "gn:feature_code":"PPL",
    "gn:name":"Leopoldina",
    "gn:population":0,
    "gn:timezone":"Africa/Maputo",
    "iso:country":"MZ",
    "name:bre_x_preferred":[
        "Leopoldina"
    ],
    "name:ceb_x_preferred":[
        "Leopoldina"
    ],
    "name:deu_x_preferred":[
        "Leopoldina"
    ],
    "name:fra_x_preferred":[
        "Leopoldina"
    ],
    "name:ita_x_preferred":[
        "Leopoldina"
    ],
    "name:mlg_x_preferred":[
        "Leopoldina"
    ],
    "name:nds_x_preferred":[
        "Leopoldina"
    ],
    "name:nld_x_preferred":[
        "Leopoldina"
    ],
    "name:por_x_preferred":[
        "Leopoldina"
    ],
    "name:slv_x_preferred":[
        "Leopoldina"
    ],
    "name:swe_x_preferred":[
        "Leopoldina"
    ],
    "wof:name":"Leopoldina",
    "wof:placetype":"locality"
},
  "geometry": {"coordinates":[33.66528,-24.76778],"type":"Point"}
}