{
  "type": "Feature",
  "properties": {
    "gn:admin1_code":"3.0",
    "gn:asciiname":"Uane",
    "gn:country_code":"MZ",
    "gn:dem":167,
    "gn:feature_class":"P",
    "gn:feature_code":"PPL",
    "gn:name":"Uane",
    "gn:population":0,
    "gn:timezone":"Africa/Maputo",
    "iso:country":"MZ",
    "wof:name":"Uane",
    "wof:placetype":"locality"
},
  "geometry": {"coordinates":[35.03278,-23.60667],"type":"Point"}
}