{
  "type": "Feature",
  "properties": {
    "gn:admin1_code":"10.0",
    "gn:asciiname":"Raposo",
    "gn:country_code":"MZ",
    "gn:dem":716,
    "gn:feature_class":"P",
    "gn:feature_code":"PPL",
    "gn:name":"Raposo",
    "gn:population":0,
    "gn:timezone":"Africa/Maputo",
    "iso:country":"MZ",
    "wof:name":"Raposo",
    "wof:placetype":"locality"
},
  "geometry": {"coordinates":[32.9675,-18.48917],"type":"Point"}
}