{
  "type": "Feature",
  "properties": {
    "gn:admin1_code":"2.0",
    "gn:asciiname":"Barragem",
    "gn:country_code":"MZ",
    "gn:dem":42,
    "gn:feature_class":"P",
    "gn:feature_code":"PPL",
    "gn:name":"Barragem",
    "gn:population":0,
    "gn:timezone":"Africa/Maputo",
    "iso:country":"MZ",
    "wof:name":"Barragem",
    "wof:placetype":"locality"
},
  "geometry": {"coordinates":[32.8725,-24.40806],"type":"Point"}
}