{
  "type": "Feature",
  "properties": {
    "gn:admin1_code":"6",
    "gn:asciiname":"Lanca",
    "gn:country_code":"MZ",
    "gn:dem":330,
    "gn:feature_class":"P",
    "gn:feature_code":"PPL",
    "gn:name":"Lanca",
    "gn:population":0,
    "gn:timezone":"Africa/Maputo",
    "iso:country":"MZ",
    "wof:name":"Lanca",
    "wof:placetype":"locality"
},
  "geometry": {"coordinates":[39.33417,-14.00472],"type":"Point"}
}