{
  "type": "Feature",
  "properties": {
    "gn:admin1_code":"0",
    "gn:asciiname":"Agi",
    "gn:country_code":"MZ",
    "gn:dem":32,
    "gn:feature_class":"P",
    "gn:feature_code":"PPL",
    "gn:name":"Agi",
    "gn:population":0,
    "gn:timezone":"Africa/Maputo",
    "iso:country":"MZ",
    "wof:name":"Agi",
    "wof:placetype":"locality"
},
  "geometry": {"coordinates":[40.75,-14.63333],"type":"Point"}
}