{
  "type": "Feature",
  "properties": {
    "gn:admin1_code":"7",
    "gn:asciiname":"Humo Nicuncune",
    "gn:country_code":"MZ",
    "gn:dem":492,
    "gn:feature_class":"P",
    "gn:feature_code":"PPL",
    "gn:name":"Humo Nicuncune",
    "gn:population":0,
    "gn:timezone":"Africa/Maputo",
    "iso:country":"MZ",
    "wof:name":"Humo Nicuncune",
    "wof:placetype":"locality"
},
  "geometry": {"coordinates":[38.12667,-13.95722],"type":"Point"}
}