{
  "type": "Feature",
  "properties": {
    "gn:admin1_code":"2.0",
    "gn:asciiname":"Davide",
    "gn:country_code":"MZ",
    "gn:dem":80,
    "gn:feature_class":"P",
    "gn:feature_code":"PPL",
    "gn:name":"Davide",
    "gn:population":0,
    "gn:timezone":"Africa/Maputo",
    "iso:country":"MZ",
    "wof:name":"Davide",
    "wof:placetype":"locality"
},
  "geometry": {"coordinates":[33.83028,-24.77139],"type":"Point"}
}