{
  "type": "Feature",
  "properties": {
    "gn:admin1_code":"4.0",
    "gn:asciiname":"C. Ungubana",
    "gn:country_code":"MZ",
    "gn:dem":57,
    "gn:feature_class":"P",
    "gn:feature_code":"PPL",
    "gn:name":"C. Ungubana",
    "gn:population":0,
    "gn:timezone":"Africa/Maputo",
    "iso:country":"MZ",
    "wof:name":"C. Ungubana",
    "wof:placetype":"locality"
},
  "geometry": {"coordinates":[32.4125,-25.1125],"type":"Point"}
}