{
  "type": "Feature",
  "properties": {
    "gn:admin1_code":"5",
    "gn:asciiname":"Bovana",
    "gn:country_code":"MZ",
    "gn:dem":158,
    "gn:feature_class":"P",
    "gn:feature_code":"PPL",
    "gn:name":"Bovana",
    "gn:population":0,
    "gn:timezone":"Africa/Maputo",
    "iso:country":"MZ",
    "wof:name":"Bovana",
    "wof:placetype":"locality"
},
  "geometry": {"coordinates":[34.15694000000001,-20.07806],"type":"Point"}
}