{
  "type": "Feature",
  "properties": {
    "gn:admin1_code":"6",
    "gn:asciiname":"Muatama",
    "gn:country_code":"MZ",
    "gn:dem":707,
    "gn:feature_class":"P",
    "gn:feature_code":"PPL",
    "gn:name":"Muatama",
    "gn:population":0,
    "gn:timezone":"Africa/Maputo",
    "iso:country":"MZ",
    "wof:name":"Muatama",
    "wof:placetype":"locality"
},
  "geometry": {"coordinates":[37.30889000000001,-15.005],"type":"Point"}
}