{
  "type": "Feature",
  "properties": {
    "gn:admin1_code":"8.0",
    "gn:asciiname":"Temba",
    "gn:country_code":"MZ",
    "gn:dem":875,
    "gn:feature_class":"P",
    "gn:feature_code":"PPL",
    "gn:name":"Temba",
    "gn:population":0,
    "gn:timezone":"Africa/Maputo",
    "iso:country":"MZ",
    "wof:name":"Temba",
    "wof:placetype":"locality"
},
  "geometry": {"coordinates":[34.17833,-15.1675],"type":"Point"}
}