{
  "type": "Feature",
  "properties": {
    "gn:admin1_code":"7",
    "gn:asciiname":"Nziro",
    "gn:country_code":"MZ",
    "gn:dem":652,
    "gn:feature_class":"P",
    "gn:feature_code":"PPL",
    "gn:name":"Nziro",
    "gn:population":0,
    "gn:timezone":"Africa/Maputo",
    "iso:country":"MZ",
    "wof:name":"Nziro",
    "wof:placetype":"locality"
},
  "geometry": {"coordinates":[36.11056,-13.38278],"type":"Point"}
}