{
  "type": "Feature",
  "properties": {
    "gn:admin1_code":"3.0",
    "gn:asciiname":"Zaiambo",
    "gn:country_code":"MZ",
    "gn:dem":122,
    "gn:feature_class":"P",
    "gn:feature_code":"PPL",
    "gn:name":"Zaiambo",
    "gn:population":0,
    "gn:timezone":"Africa/Maputo",
    "iso:country":"MZ",
    "wof:name":"Zaiambo",
    "wof:placetype":"locality"
},
  "geometry": {"coordinates":[33.96306,-22.69167],"type":"Point"}
}