{
  "type": "Feature",
  "properties": {
    "gn:admin1_code":"9.0",
    "gn:asciiname":"Tacaia",
    "gn:country_code":"MZ",
    "gn:dem":780,
    "gn:feature_class":"P",
    "gn:feature_code":"PPL",
    "gn:name":"Tacaia",
    "gn:population":0,
    "gn:timezone":"Africa/Maputo",
    "iso:country":"MZ",
    "wof:name":"Tacaia",
    "wof:placetype":"locality"
},
  "geometry": {"coordinates":[37.48278,-15.17694],"type":"Point"}
}