{
  "type": "Feature",
  "properties": {
    "gn:admin1_code":"3",
    "gn:asciiname":"Mateus",
    "gn:country_code":"MZ",
    "gn:dem":173,
    "gn:feature_class":"P",
    "gn:feature_code":"PPL",
    "gn:name":"Mateus",
    "gn:population":0,
    "gn:timezone":"Africa/Maputo",
    "iso:country":"MZ",
    "name:deu_x_preferred":[
        "Mateus"
    ],
    "name:fra_x_preferred":[
        "Mateus"
    ],
    "name:heb_x_preferred":[
        "\u05de\u05ea\u05d0\u05d5\u05e1"
    ],
    "name:por_x_preferred":[
        "Mateus"
    ],
    "name:rus_x_preferred":[
        "\u041c\u0430\u0442\u0435\u0443\u0441"
    ],
    "wof:name":"Mateus",
    "wof:placetype":"locality"
},
  "geometry": {"coordinates":[34.95611,-23.63333],"type":"Point"}
}