{
  "type": "Feature",
  "properties": {
    "gn:admin1_code":"9",
    "gn:asciiname":"Duruma",
    "gn:country_code":"MZ",
    "gn:dem":65,
    "gn:feature_class":"P",
    "gn:feature_code":"PPL",
    "gn:name":"Duruma",
    "gn:population":0,
    "gn:timezone":"Africa/Maputo",
    "iso:country":"MZ",
    "wof:name":"Duruma",
    "wof:placetype":"locality"
},
  "geometry": {"coordinates":[36.84,-17.34556],"type":"Point"}
}