{
  "type": "Feature",
  "properties": {
    "gn:admin1_code":"8",
    "gn:asciiname":"Muanza",
    "gn:cc2":"MZ",
    "gn:country_code":"MZ",
    "gn:dem":941,
    "gn:feature_class":"P",
    "gn:feature_code":"PPL",
    "gn:name":"Muanza",
    "gn:population":0,
    "gn:timezone":"Africa/Maputo",
    "iso:country":"MZ",
    "name:por_x_preferred":[
        "Muanza"
    ],
    "name:und_x_variant":[
        "Muanxa",
        "Muanza"
    ],
    "name:zho_x_preferred":[
        "\u59c6\u5b89\u624e"
    ],
    "wof:name":"Muanza",
    "wof:placetype":"locality"
},
  "geometry": {"coordinates":[31.005,-15.06306],"type":"Point"}
}