{
  "type": "Feature",
  "properties": {
    "gn:admin1_code":"5",
    "gn:asciiname":"Macuro",
    "gn:country_code":"MZ",
    "gn:dem":97,
    "gn:feature_class":"P",
    "gn:feature_code":"PPL",
    "gn:name":"Macuro",
    "gn:population":0,
    "gn:timezone":"Africa/Maputo",
    "iso:country":"MZ",
    "name:ceb_x_preferred":[
        "Macuro"
    ],
    "name:spa_x_preferred":[
        "Macuro"
    ],
    "name:urd_x_preferred":[
        "\u0645\u06cc\u06a9\u0648\u0631\u0648"
    ],
    "wof:name":"Macuro",
    "wof:placetype":"locality"
},
  "geometry": {"coordinates":[34.08639,-20.00778],"type":"Point"}
}