{
  "type": "Feature",
  "properties": {
    "gn:admin1_code":"1.0",
    "gn:asciiname":"Ualicholo",
    "gn:country_code":"MZ",
    "gn:dem":162,
    "gn:feature_class":"P",
    "gn:feature_code":"PPL",
    "gn:name":"Ualicholo",
    "gn:population":0,
    "gn:timezone":"Africa/Maputo",
    "iso:country":"MZ",
    "wof:name":"Ualicholo",
    "wof:placetype":"locality"
},
  "geometry": {"coordinates":[39.94194,-11.03639],"type":"Point"}
}