{
  "type": "Feature",
  "properties": {
    "gn:admin1_code":"3",
    "gn:asciiname":"Pangur",
    "gn:country_code":"MZ",
    "gn:dem":124,
    "gn:feature_class":"P",
    "gn:feature_code":"PPL",
    "gn:name":"Pangur",
    "gn:population":0,
    "gn:timezone":"Africa/Maputo",
    "iso:country":"MZ",
    "wof:name":"Pangur",
    "wof:placetype":"locality"
},
  "geometry": {"coordinates":[34.85306,-22.57528],"type":"Point"}
}