{
  "type": "Feature",
  "properties": {
    "gn:admin1_code":"9",
    "gn:asciiname":"Muinhacane",
    "gn:country_code":"MZ",
    "gn:dem":831,
    "gn:feature_class":"P",
    "gn:feature_code":"PPL",
    "gn:name":"Muinhacane",
    "gn:population":0,
    "gn:timezone":"Africa/Maputo",
    "iso:country":"MZ",
    "wof:name":"Muinhacane",
    "wof:placetype":"locality"
},
  "geometry": {"coordinates":[37.36222,-15.19306],"type":"Point"}
}