{
  "type": "Feature",
  "properties": {
    "gn:admin1_code":"6",
    "gn:asciiname":"Alipo",
    "gn:country_code":"MZ",
    "gn:dem":143,
    "gn:feature_class":"P",
    "gn:feature_code":"PPL",
    "gn:name":"Alipo",
    "gn:population":0,
    "gn:timezone":"Africa/Maputo",
    "iso:country":"MZ",
    "wof:name":"Alipo",
    "wof:placetype":"locality"
},
  "geometry": {"coordinates":[39.56917,-15.80028],"type":"Point"}
}