{
  "type": "Feature",
  "properties": {
    "gn:admin1_code":"2.0",
    "gn:asciiname":"A. Moaianine",
    "gn:country_code":"MZ",
    "gn:dem":63,
    "gn:feature_class":"P",
    "gn:feature_code":"PPL",
    "gn:name":"A. Moaianine",
    "gn:population":0,
    "gn:timezone":"Africa/Maputo",
    "iso:country":"MZ",
    "wof:name":"A. Moaianine",
    "wof:placetype":"locality"
},
  "geometry": {"coordinates":[33.21472,-25.03417],"type":"Point"}
}