{
  "type": "Feature",
  "properties": {
    "gn:admin1_code":"1",
    "gn:asciiname":"Nicupi",
    "gn:country_code":"MZ",
    "gn:dem":531,
    "gn:feature_class":"P",
    "gn:feature_code":"PPL",
    "gn:name":"Nicupi",
    "gn:population":0,
    "gn:timezone":"Africa/Maputo",
    "iso:country":"MZ",
    "wof:name":"Nicupi",
    "wof:placetype":"locality"
},
  "geometry": {"coordinates":[38.64444,-13.24944],"type":"Point"}
}