{
  "type": "Feature",
  "properties": {
    "gn:admin1_code":"3.0",
    "gn:asciiname":"Zenane",
    "gn:country_code":"MZ",
    "gn:dem":197,
    "gn:feature_class":"P",
    "gn:feature_code":"PPL",
    "gn:name":"Zenane",
    "gn:population":0,
    "gn:timezone":"Africa/Maputo",
    "iso:country":"MZ",
    "wof:name":"Zenane",
    "wof:placetype":"locality"
},
  "geometry": {"coordinates":[34.0975,-21.87444],"type":"Point"}
}