{
  "type": "Feature",
  "properties": {
    "gn:admin1_code":"10",
    "gn:asciiname":"Jornal",
    "gn:country_code":"MZ",
    "gn:dem":667,
    "gn:feature_class":"P",
    "gn:feature_code":"PPL",
    "gn:name":"Jornal",
    "gn:population":0,
    "gn:timezone":"Africa/Maputo",
    "iso:country":"MZ",
    "wof:name":"Jornal",
    "wof:placetype":"locality"
},
  "geometry": {"coordinates":[33.45917,-19.17056],"type":"Point"}
}