{
  "type": "Feature",
  "properties": {
    "gn:admin1_code":"5",
    "gn:asciiname":"Guno",
    "gn:country_code":"MZ",
    "gn:dem":193,
    "gn:feature_class":"P",
    "gn:feature_code":"PPL",
    "gn:name":"Guno",
    "gn:population":0,
    "gn:timezone":"Africa/Maputo",
    "iso:country":"MZ",
    "wof:name":"Guno",
    "wof:placetype":"locality"
},
  "geometry": {"coordinates":[34.02667,-20.04306],"type":"Point"}
}