{
  "type": "Feature",
  "properties": {
    "gn:admin1_code":"1.0",
    "gn:asciiname":"Sadima",
    "gn:country_code":"MZ",
    "gn:dem":560,
    "gn:feature_class":"P",
    "gn:feature_code":"PPL",
    "gn:name":"Sadima",
    "gn:population":0,
    "gn:timezone":"Africa/Maputo",
    "iso:country":"MZ",
    "wof:name":"Sadima",
    "wof:placetype":"locality"
},
  "geometry": {"coordinates":[39.66472,-11.44444],"type":"Point"}
}