{
  "type": "Feature",
  "properties": {
    "gn:admin1_code":"7.0",
    "gn:asciiname":"Uncula",
    "gn:country_code":"MZ",
    "gn:dem":1000,
    "gn:feature_class":"P",
    "gn:feature_code":"PPL",
    "gn:name":"Uncula",
    "gn:population":0,
    "gn:timezone":"Africa/Maputo",
    "iso:country":"MZ",
    "wof:name":"Uncula",
    "wof:placetype":"locality"
},
  "geometry": {"coordinates":[35.44917,-13.54972],"type":"Point"}
}