{
  "type": "Feature",
  "properties": {
    "gn:admin1_code":"6",
    "gn:asciiname":"Alave",
    "gn:country_code":"MZ",
    "gn:dem":54,
    "gn:feature_class":"P",
    "gn:feature_code":"PPL",
    "gn:name":"Alave",
    "gn:population":0,
    "gn:timezone":"Africa/Maputo",
    "iso:country":"MZ",
    "wof:name":"Alave",
    "wof:placetype":"locality"
},
  "geometry": {"coordinates":[40.16222,-15.64444],"type":"Point"}
}