{
  "type": "Feature",
  "properties": {
    "gn:admin1_code":"4",
    "gn:asciiname":"Malengana",
    "gn:cc2":"MZ",
    "gn:country_code":"MZ",
    "gn:dem":52,
    "gn:feature_class":"P",
    "gn:feature_code":"PPL",
    "gn:name":"Malengana",
    "gn:population":0,
    "gn:timezone":"Africa/Maputo",
    "iso:country":"MZ",
    "name:und_x_variant":[
        "Malangane",
        "Malengana"
    ],
    "wof:name":"Malengana",
    "wof:placetype":"locality"
},
  "geometry": {"coordinates":[32.62417,-25.31361],"type":"Point"}
}