{
  "type": "Feature",
  "properties": {
    "gn:admin1_code":"5",
    "gn:asciiname":"Camba",
    "gn:country_code":"MZ",
    "gn:dem":12,
    "gn:feature_class":"P",
    "gn:feature_code":"PPL",
    "gn:name":"Camba",
    "gn:population":0,
    "gn:timezone":"Africa/Maputo",
    "iso:country":"MZ",
    "name:ita_x_preferred":[
        "Camba"
    ],
    "name:jpn_x_preferred":[
        "\u30ab\u30f3\u30d0"
    ],
    "name:por_x_preferred":[
        "Camba"
    ],
    "name:spa_x_preferred":[
        "Camba"
    ],
    "wof:name":"Camba",
    "wof:placetype":"locality"
},
  "geometry": {"coordinates":[35.87167,-18.26833],"type":"Point"}
}