{
  "type": "Feature",
  "properties": {
    "gn:admin1_code":"3.0",
    "gn:asciiname":"Alfeu",
    "gn:country_code":"MZ",
    "gn:dem":100,
    "gn:feature_class":"P",
    "gn:feature_code":"PPL",
    "gn:name":"Alfeu",
    "gn:population":0,
    "gn:timezone":"Africa/Maputo",
    "iso:country":"MZ",
    "wof:name":"Alfeu",
    "wof:placetype":"locality"
},
  "geometry": {"coordinates":[35.38778,-23.03111],"type":"Point"}
}