{
  "type": "Feature",
  "properties": {
    "gn:admin1_code":"2.0",
    "gn:asciiname":"Companhia das Lezirias",
    "gn:country_code":"MZ",
    "gn:dem":38,
    "gn:feature_class":"P",
    "gn:feature_code":"PPL",
    "gn:name":"Companhia das Lezirias",
    "gn:population":0,
    "gn:timezone":"Africa/Maputo",
    "iso:country":"MZ",
    "wof:name":"Companhia das Lezirias",
    "wof:placetype":"locality"
},
  "geometry": {"coordinates":[33.51944,-24.91472000000001],"type":"Point"}
}