{
  "type": "Feature",
  "properties": {
    "gn:admin1_code":"3.0",
    "gn:asciiname":"Chefe Checane",
    "gn:country_code":"MZ",
    "gn:dem":24,
    "gn:feature_class":"P",
    "gn:feature_code":"PPL",
    "gn:name":"Chefe Checane",
    "gn:population":0,
    "gn:timezone":"Africa/Maputo",
    "iso:country":"MZ",
    "wof:name":"Chefe Checane",
    "wof:placetype":"locality"
},
  "geometry": {"coordinates":[35.11444,-21.76222000000001],"type":"Point"}
}