{
  "type": "Feature",
  "properties": {
    "gn:admin1_code":"5",
    "gn:asciiname":"Mapungana",
    "gn:country_code":"MZ",
    "gn:dem":148,
    "gn:feature_class":"P",
    "gn:feature_code":"PPL",
    "gn:name":"Mapungana",
    "gn:population":0,
    "gn:timezone":"Africa/Maputo",
    "iso:country":"MZ",
    "wof:name":"Mapungana",
    "wof:placetype":"locality"
},
  "geometry": {"coordinates":[34.1675,-20.34778],"type":"Point"}
}