{
  "type": "Feature",
  "properties": {
    "gn:admin1_code":"6",
    "gn:asciiname":"Opacarra",
    "gn:country_code":"MZ",
    "gn:dem":175,
    "gn:feature_class":"P",
    "gn:feature_code":"PPL",
    "gn:name":"Opacarra",
    "gn:population":0,
    "gn:timezone":"Africa/Maputo",
    "iso:country":"MZ",
    "wof:name":"Opacarra",
    "wof:placetype":"locality"
},
  "geometry": {"coordinates":[40.37833,-14.18778],"type":"Point"}
}