{
  "type": "Feature",
  "properties": {
    "gn:admin1_code":"9",
    "gn:asciiname":"Nhalune",
    "gn:cc2":"MZ",
    "gn:country_code":"MZ",
    "gn:dem":9,
    "gn:feature_class":"P",
    "gn:feature_code":"PPL",
    "gn:name":"Nhalune",
    "gn:population":0,
    "gn:timezone":"Africa/Maputo",
    "iso:country":"MZ",
    "name:und_x_variant":[
        "Nhaiuhe",
        "Nhalune"
    ],
    "wof:name":"Nhalune",
    "wof:placetype":"locality"
},
  "geometry": {"coordinates":[36.43667,-18.59972],"type":"Point"}
}