{
  "type": "Feature",
  "properties": {
    "gn:admin1_code":"10.0",
    "gn:asciiname":"Sevene",
    "gn:country_code":"MZ",
    "gn:dem":219,
    "gn:feature_class":"P",
    "gn:feature_code":"PPL",
    "gn:name":"Sevene",
    "gn:population":0,
    "gn:timezone":"Africa/Maputo",
    "iso:country":"MZ",
    "wof:name":"Sevene",
    "wof:placetype":"locality"
},
  "geometry": {"coordinates":[33.655,-20.72917],"type":"Point"}
}