{
  "type": "Feature",
  "properties": {
    "gn:admin1_code":"1",
    "gn:asciiname":"M'Tamba",
    "gn:country_code":"MZ",
    "gn:dem":323,
    "gn:feature_class":"P",
    "gn:feature_code":"PPL",
    "gn:name":"M\u2019Tamba",
    "gn:population":0,
    "gn:timezone":"Africa/Maputo",
    "iso:country":"MZ",
    "wof:name":"M'Tamba",
    "wof:placetype":"locality"
},
  "geometry": {"coordinates":[39.77083,-11.42417],"type":"Point"}
}