{
  "type": "Feature",
  "properties": {
    "gn:admin1_code":"6",
    "gn:asciiname":"Malua",
    "gn:cc2":"MZ",
    "gn:country_code":"MZ",
    "gn:dem":538,
    "gn:feature_class":"P",
    "gn:feature_code":"PPL",
    "gn:name":"Malua",
    "gn:population":0,
    "gn:timezone":"Africa/Maputo",
    "iso:country":"MZ",
    "name:ceb_x_preferred":[
        "Malua"
    ],
    "name:und_x_variant":[
        "Mai\u00faa",
        "Malua"
    ],
    "wof:name":"Malua",
    "wof:placetype":"locality"
},
  "geometry": {"coordinates":[38.75028,-14.69667],"type":"Point"}
}