{
  "type": "Feature",
  "properties": {
    "gn:admin1_code":"10",
    "gn:asciiname":"Cafunganedo",
    "gn:country_code":"MZ",
    "gn:dem":594,
    "gn:feature_class":"P",
    "gn:feature_code":"PPL",
    "gn:name":"Cafungan\u00eado",
    "gn:population":0,
    "gn:timezone":"Africa/Maputo",
    "iso:country":"MZ",
    "wof:name":"Cafunganedo",
    "wof:placetype":"locality"
},
  "geometry": {"coordinates":[33.06833,-18.49472],"type":"Point"}
}