{
  "type": "Feature",
  "properties": {
    "gn:admin1_code":"3.0",
    "gn:asciiname":"Balata",
    "gn:country_code":"MZ",
    "gn:dem":144,
    "gn:feature_class":"P",
    "gn:feature_code":"PPL",
    "gn:name":"Balata",
    "gn:population":0,
    "gn:timezone":"Africa/Maputo",
    "iso:country":"MZ",
    "wof:name":"Balata",
    "wof:placetype":"locality"
},
  "geometry": {"coordinates":[34.47694,-22.84639],"type":"Point"}
}