{
  "type": "Feature",
  "properties": {
    "gn:admin1_code":"6",
    "gn:asciiname":"Namialo",
    "gn:country_code":"MZ",
    "gn:dem":201,
    "gn:feature_class":"P",
    "gn:feature_code":"PPL",
    "gn:name":"Namialo",
    "gn:population":0,
    "gn:timezone":"Africa/Maputo",
    "iso:country":"MZ",
    "name:ast_x_preferred":[
        "Namialo"
    ],
    "name:deu_x_preferred":[
        "Namialo"
    ],
    "name:fra_x_preferred":[
        "Namialo"
    ],
    "name:kat_x_preferred":[
        "\u10dc\u10d0\u10db\u10d8\u10d0\u10da\u10e3"
    ],
    "name:swa_x_preferred":[
        "Namialo"
    ],
    "wof:name":"Namialo",
    "wof:placetype":"locality"
},
  "geometry": {"coordinates":[39.98361,-14.92056],"type":"Point"}
}