{
  "type": "Feature",
  "properties": {
    "gn:admin1_code":"9",
    "gn:asciiname":"Mucuarege",
    "gn:country_code":"MZ",
    "gn:dem":18,
    "gn:feature_class":"P",
    "gn:feature_code":"PPL",
    "gn:name":"Mucuarege",
    "gn:population":0,
    "gn:timezone":"Africa/Maputo",
    "iso:country":"MZ",
    "wof:name":"Mucuarege",
    "wof:placetype":"locality"
},
  "geometry": {"coordinates":[37.26361,-17.48417],"type":"Point"}
}