{
  "type": "Feature",
  "properties": {
    "gn:admin1_code":"6",
    "gn:asciiname":"Jacau",
    "gn:country_code":"MZ",
    "gn:dem":311,
    "gn:feature_class":"P",
    "gn:feature_code":"PPL",
    "gn:name":"Jacau",
    "gn:population":0,
    "gn:timezone":"Africa/Maputo",
    "iso:country":"MZ",
    "wof:name":"Jacau",
    "wof:placetype":"locality"
},
  "geometry": {"coordinates":[39.82389000000001,-13.89917],"type":"Point"}
}