{
  "type": "Feature",
  "properties": {
    "gn:admin1_code":"7",
    "gn:asciiname":"Meute",
    "gn:country_code":"MZ",
    "gn:dem":1206,
    "gn:feature_class":"P",
    "gn:feature_code":"PPL",
    "gn:name":"M\u00eaute",
    "gn:population":0,
    "gn:timezone":"Africa/Maputo",
    "iso:country":"MZ",
    "wof:name":"Meute",
    "wof:placetype":"locality"
},
  "geometry": {"coordinates":[35.79861,-12.78111],"type":"Point"}
}