{
  "type": "Feature",
  "properties": {
    "gn:admin1_code":"6",
    "gn:asciiname":"Nampuia",
    "gn:country_code":"MZ",
    "gn:dem":410,
    "gn:feature_class":"P",
    "gn:feature_code":"PPL",
    "gn:name":"Nampuia",
    "gn:population":0,
    "gn:timezone":"Africa/Maputo",
    "iso:country":"MZ",
    "wof:name":"Nampuia",
    "wof:placetype":"locality"
},
  "geometry": {"coordinates":[38.87111,-15.31333],"type":"Point"}
}