{
  "type": "Feature",
  "properties": {
    "gn:admin1_code":"10.0",
    "gn:asciiname":"Cunha",
    "gn:country_code":"MZ",
    "gn:dem":1048,
    "gn:feature_class":"P",
    "gn:feature_code":"PPL",
    "gn:name":"Cunha",
    "gn:population":0,
    "gn:timezone":"Africa/Maputo",
    "iso:country":"MZ",
    "wof:name":"Cunha",
    "wof:placetype":"locality"
},
  "geometry": {"coordinates":[32.86222,-18.81167],"type":"Point"}
}