{
  "type": "Feature",
  "properties": {
    "gn:admin1_code":"3",
    "gn:asciiname":"Chiulo",
    "gn:country_code":"MZ",
    "gn:dem":164,
    "gn:feature_class":"P",
    "gn:feature_code":"PPL",
    "gn:name":"Chiulo",
    "gn:population":0,
    "gn:timezone":"Africa/Maputo",
    "iso:country":"MZ",
    "wof:name":"Chiulo",
    "wof:placetype":"locality"
},
  "geometry": {"coordinates":[34.61528,-21.83833],"type":"Point"}
}