{
  "type": "Feature",
  "properties": {
    "gn:admin1_code":"10",
    "gn:asciiname":"Choa",
    "gn:country_code":"MZ",
    "gn:dem":1474,
    "gn:feature_class":"P",
    "gn:feature_code":"PPL",
    "gn:name":"Choa",
    "gn:population":0,
    "gn:timezone":"Africa/Maputo",
    "iso:country":"MZ",
    "name:und_x_variant":[
        "Chicumba",
        "Choa"
    ],
    "wof:name":"Choa",
    "wof:placetype":"locality"
},
  "geometry": {"coordinates":[33.06227,-17.95477],"type":"Point"}
}