{
  "type": "Feature",
  "properties": {
    "gn:admin1_code":"9.0",
    "gn:asciiname":"Uaua",
    "gn:country_code":"MZ",
    "gn:dem":34,
    "gn:feature_class":"P",
    "gn:feature_code":"PPL",
    "gn:name":"Uaua",
    "gn:population":0,
    "gn:timezone":"Africa/Maputo",
    "iso:country":"MZ",
    "wof:name":"Uaua",
    "wof:placetype":"locality"
},
  "geometry": {"coordinates":[38.13833,-17.08333],"type":"Point"}
}