{
  "type": "Feature",
  "properties": {
    "gn:admin1_code":"0",
    "gn:asciiname":"Muda",
    "gn:country_code":"MZ",
    "gn:dem":15,
    "gn:feature_class":"P",
    "gn:feature_code":"PPL",
    "gn:name":"Muda",
    "gn:population":0,
    "gn:timezone":"Africa/Maputo",
    "iso:country":"MZ",
    "wof:name":"Muda",
    "wof:placetype":"locality"
},
  "geometry": {"coordinates":[34.41278,-19.37861],"type":"Point"}
}