{
  "type": "Feature",
  "properties": {
    "gn:admin1_code":"7",
    "gn:asciiname":"Nanco",
    "gn:country_code":"MZ",
    "gn:dem":588,
    "gn:feature_class":"P",
    "gn:feature_code":"PPL",
    "gn:name":"Nanco",
    "gn:population":0,
    "gn:timezone":"Africa/Maputo",
    "iso:country":"MZ",
    "wof:name":"Nanco",
    "wof:placetype":"locality"
},
  "geometry": {"coordinates":[35.31833,-11.67639],"type":"Point"}
}