{
  "type": "Feature",
  "properties": {
    "gn:admin1_code":"7",
    "gn:asciiname":"Mojava",
    "gn:country_code":"MZ",
    "gn:dem":778,
    "gn:feature_class":"P",
    "gn:feature_code":"PPL",
    "gn:name":"Mojava",
    "gn:population":0,
    "gn:timezone":"Africa/Maputo",
    "iso:country":"MZ",
    "wof:name":"Mojava",
    "wof:placetype":"locality"
},
  "geometry": {"coordinates":[35.62417,-14.36722],"type":"Point"}
}