{
  "type": "Feature",
  "properties": {
    "gn:admin1_code":"4",
    "gn:asciiname":"Goba Fronteira",
    "gn:country_code":"MZ",
    "gn:dem":398,
    "gn:feature_class":"P",
    "gn:feature_code":"PPL",
    "gn:name":"Goba Fronteira",
    "gn:population":0,
    "gn:timezone":"Africa/Maputo",
    "iso:country":"MZ",
    "wof:name":"Goba Fronteira",
    "wof:placetype":"locality"
},
  "geometry": {"coordinates":[32.08861,-26.25389],"type":"Point"}
}