{
  "type": "Feature",
  "properties": {
    "gn:admin1_code":"3",
    "gn:asciiname":"Helene",
    "gn:country_code":"MZ",
    "gn:dem":55,
    "gn:feature_class":"P",
    "gn:feature_code":"PPL",
    "gn:name":"Helene",
    "gn:population":0,
    "gn:timezone":"Africa/Maputo",
    "iso:country":"MZ",
    "name:bre_x_preferred":[
        "H\u00e9l\u00e8ne"
    ],
    "name:cym_x_preferred":[
        "Helene"
    ],
    "name:deu_x_preferred":[
        "Helene"
    ],
    "name:fin_x_preferred":[
        "Helene"
    ],
    "name:fra_x_preferred":[
        "H\u00e9l\u00e8ne"
    ],
    "name:jpn_x_preferred":[
        "\u30a8\u30ec\u30fc\u30cc"
    ],
    "name:nds_x_preferred":[
        "Helene"
    ],
    "name:nld_x_preferred":[
        "Helene"
    ],
    "name:nno_x_preferred":[
        "Helene"
    ],
    "name:nor_x_preferred":[
        "Helene"
    ],
    "name:pol_x_preferred":[
        "Helene"
    ],
    "name:por_x_preferred":[
        "Helene"
    ],
    "name:rus_x_preferred":[
        "\u042d\u043b\u0435\u043d"
    ],
    "name:slk_x_preferred":[
        "Helen\u00e9"
    ],
    "name:swe_x_preferred":[
        "Helene"
    ],
    "name:ukr_x_preferred":[
        "\u0415\u043b\u0435\u043d"
    ],
    "wof:name":"Helene",
    "wof:placetype":"locality"
},
  "geometry": {"coordinates":[34.88528,-24.53778],"type":"Point"}
}