{
  "type": "Feature",
  "properties": {
    "gn:admin1_code":"3",
    "gn:asciiname":"Cabo Chichole",
    "gn:cc2":"MZ",
    "gn:country_code":"MZ",
    "gn:dem":149,
    "gn:feature_class":"P",
    "gn:feature_code":"PPL",
    "gn:name":"Cabo Chichole",
    "gn:population":0,
    "gn:timezone":"Africa/Maputo",
    "iso:country":"MZ",
    "name:und_x_variant":[
        "Macarringue Chichole",
        "Cabo Chichole"
    ],
    "wof:name":"Cabo Chichole",
    "wof:placetype":"locality"
},
  "geometry": {"coordinates":[35.1175,-23.56944],"type":"Point"}
}