{
  "type": "Feature",
  "properties": {
    "gn:admin1_code":"6",
    "gn:asciiname":"Retiua",
    "gn:cc2":"MZ",
    "gn:country_code":"MZ",
    "gn:dem":328,
    "gn:feature_class":"P",
    "gn:feature_code":"PPL",
    "gn:name":"Retiua",
    "gn:population":0,
    "gn:timezone":"Africa/Maputo",
    "iso:country":"MZ",
    "name:und_x_variant":[
        "Nhooua",
        "Retiua"
    ],
    "wof:name":"Retiua",
    "wof:placetype":"locality"
},
  "geometry": {"coordinates":[39.4675,-15.13056],"type":"Point"}
}