{
  "type": "Feature",
  "properties": {
    "gn:admin1_code":"1.0",
    "gn:asciiname":"Saide",
    "gn:country_code":"MZ",
    "gn:dem":305,
    "gn:feature_class":"P",
    "gn:feature_code":"PPL",
    "gn:name":"Saide",
    "gn:population":0,
    "gn:timezone":"Africa/Maputo",
    "iso:country":"MZ",
    "wof:name":"Saide",
    "wof:placetype":"locality"
},
  "geometry": {"coordinates":[39.85278,-13.34694],"type":"Point"}
}