{
  "type": "Feature",
  "properties": {
    "gn:admin1_code":"10",
    "gn:asciiname":"Macupi",
    "gn:country_code":"MZ",
    "gn:dem":317,
    "gn:feature_class":"P",
    "gn:feature_code":"PPL",
    "gn:name":"Macupi",
    "gn:population":0,
    "gn:timezone":"Africa/Maputo",
    "iso:country":"MZ",
    "wof:name":"Macupi",
    "wof:placetype":"locality"
},
  "geometry": {"coordinates":[33.35,-20.88722000000001],"type":"Point"}
}