{
  "type": "Feature",
  "properties": {
    "gn:admin1_code":"3.0",
    "gn:asciiname":"Chavamuzonde",
    "gn:country_code":"MZ",
    "gn:dem":92,
    "gn:feature_class":"P",
    "gn:feature_code":"PPL",
    "gn:name":"Chavamuzonde",
    "gn:population":0,
    "gn:timezone":"Africa/Maputo",
    "iso:country":"MZ",
    "wof:name":"Chavamuzonde",
    "wof:placetype":"locality"
},
  "geometry": {"coordinates":[33.63722,-22.87639],"type":"Point"}
}