{
  "type": "Feature",
  "properties": {
    "gn:admin1_code":"8",
    "gn:asciiname":"Capanda",
    "gn:country_code":"MZ",
    "gn:dem":961,
    "gn:feature_class":"P",
    "gn:feature_code":"PPL",
    "gn:name":"Capanda",
    "gn:population":0,
    "gn:timezone":"Africa/Maputo",
    "iso:country":"MZ",
    "wof:name":"Capanda",
    "wof:placetype":"locality"
},
  "geometry": {"coordinates":[31.63889,-14.96111],"type":"Point"}
}