{
  "type": "Feature",
  "properties": {
    "gn:admin1_code":"1",
    "gn:asciiname":"Alumar",
    "gn:country_code":"MZ",
    "gn:dem":346,
    "gn:feature_class":"P",
    "gn:feature_code":"PPL",
    "gn:name":"Alumar",
    "gn:population":0,
    "gn:timezone":"Africa/Maputo",
    "iso:country":"MZ",
    "name:azb_x_preferred":[
        "\u0627\u0644\u0648\u0645\u0627\u0631"
    ],
    "name:fas_x_preferred":[
        "\u0627\u0644\u0648\u0645\u0627\u0631"
    ],
    "wof:name":"Alumar",
    "wof:placetype":"locality"
},
  "geometry": {"coordinates":[39.75417,-12.92306],"type":"Point"}
}