{
  "type": "Feature",
  "properties": {
    "gn:admin1_code":"6",
    "gn:asciiname":"Muamuquina",
    "gn:cc2":"MZ",
    "gn:country_code":"MZ",
    "gn:dem":125,
    "gn:feature_class":"P",
    "gn:feature_code":"PPL",
    "gn:name":"Muamuquina",
    "gn:population":0,
    "gn:timezone":"Africa/Maputo",
    "iso:country":"MZ",
    "name:und_x_variant":[
        "Muamuguina",
        "Muamuquina"
    ],
    "wof:name":"Muamuquina",
    "wof:placetype":"locality"
},
  "geometry": {"coordinates":[40.23639,-15.29722],"type":"Point"}
}