{
  "type": "Feature",
  "properties": {
    "gn:admin1_code":"8",
    "gn:asciiname":"Ganunga",
    "gn:country_code":"MZ",
    "gn:dem":29,
    "gn:feature_class":"P",
    "gn:feature_code":"PPL",
    "gn:name":"Ganunga",
    "gn:population":0,
    "gn:timezone":"Africa/Maputo",
    "iso:country":"MZ",
    "wof:name":"Ganunga",
    "wof:placetype":"locality"
},
  "geometry": {"coordinates":[35.2675,-17.32667],"type":"Point"}
}