{
  "type": "Feature",
  "properties": {
    "gn:admin1_code":"2.0",
    "gn:asciiname":"Aldeia Bingo",
    "gn:country_code":"MZ",
    "gn:dem":169,
    "gn:feature_class":"P",
    "gn:feature_code":"PPL",
    "gn:name":"Aldeia Bingo",
    "gn:population":0,
    "gn:timezone":"Africa/Maputo",
    "iso:country":"MZ",
    "wof:name":"Aldeia Bingo",
    "wof:placetype":"locality"
},
  "geometry": {"coordinates":[31.92972,-23.63611],"type":"Point"}
}