{
  "type": "Feature",
  "properties": {
    "gn:admin1_code":"3.0",
    "gn:asciiname":"Tanela",
    "gn:country_code":"MZ",
    "gn:dem":149,
    "gn:feature_class":"P",
    "gn:feature_code":"PPL",
    "gn:name":"Tanela",
    "gn:population":0,
    "gn:timezone":"Africa/Maputo",
    "iso:country":"MZ",
    "name:vie_x_preferred":[
        "Tanela"
    ],
    "wof:name":"Tanela",
    "wof:placetype":"locality"
},
  "geometry": {"coordinates":[34.59611,-21.72556],"type":"Point"}
}