{
  "type": "Feature",
  "properties": {
    "gn:admin1_code":"10",
    "gn:asciiname":"Mandalasse",
    "gn:country_code":"MZ",
    "gn:dem":348,
    "gn:feature_class":"P",
    "gn:feature_code":"PPL",
    "gn:name":"Mandalasse",
    "gn:population":0,
    "gn:timezone":"Africa/Maputo",
    "iso:country":"MZ",
    "wof:name":"Mandalasse",
    "wof:placetype":"locality"
},
  "geometry": {"coordinates":[33.31667,-20.72528],"type":"Point"}
}