{
  "type": "Feature",
  "properties": {
    "gn:admin1_code":"7",
    "gn:asciiname":"Magiga",
    "gn:country_code":"MZ",
    "gn:dem":1200,
    "gn:feature_class":"P",
    "gn:feature_code":"PPL",
    "gn:name":"Magiga",
    "gn:population":0,
    "gn:timezone":"Africa/Maputo",
    "iso:country":"MZ",
    "wof:name":"Magiga",
    "wof:placetype":"locality"
},
  "geometry": {"coordinates":[35.26222,-13.74806],"type":"Point"}
}