{
  "type": "Feature",
  "properties": {
    "gn:admin1_code":"8",
    "gn:asciiname":"Jasse",
    "gn:country_code":"MZ",
    "gn:dem":737,
    "gn:feature_class":"P",
    "gn:feature_code":"PPL",
    "gn:name":"Jasse",
    "gn:population":0,
    "gn:timezone":"Africa/Maputo",
    "iso:country":"MZ",
    "wof:name":"Jasse",
    "wof:placetype":"locality"
},
  "geometry": {"coordinates":[33.8325,-15.35194],"type":"Point"}
}