{
  "type": "Feature",
  "properties": {
    "gn:admin1_code":"7.0",
    "gn:asciiname":"Chefe Cussupa",
    "gn:cc2":"MZ",
    "gn:country_code":"MZ",
    "gn:dem":656,
    "gn:feature_class":"P",
    "gn:feature_code":"PPL",
    "gn:name":"Chefe Cussupa",
    "gn:population":0,
    "gn:timezone":"Africa/Maputo",
    "iso:country":"MZ",
    "name:und_x_variant":[
        "Quisapa",
        "Chefe Cussupa"
    ],
    "wof:name":"Chefe Cussupa",
    "wof:placetype":"locality"
},
  "geometry": {"coordinates":[35.98806,-14.2725],"type":"Point"}
}