{
  "type": "Feature",
  "properties": {
    "gn:admin1_code":"3.0",
    "gn:asciiname":"Mainato",
    "gn:country_code":"MZ",
    "gn:dem":43,
    "gn:feature_class":"P",
    "gn:feature_code":"PPL",
    "gn:name":"Mainato",
    "gn:population":0,
    "gn:timezone":"Africa/Maputo",
    "iso:country":"MZ",
    "wof:name":"Mainato",
    "wof:placetype":"locality"
},
  "geometry": {"coordinates":[34.94110999999999,-21.47528],"type":"Point"}
}