{
  "type": "Feature",
  "properties": {
    "gn:admin1_code":"7",
    "gn:asciiname":"Landa",
    "gn:country_code":"MZ",
    "gn:dem":517,
    "gn:feature_class":"P",
    "gn:feature_code":"PPL",
    "gn:name":"Landa",
    "gn:population":0,
    "gn:timezone":"Africa/Maputo",
    "iso:country":"MZ",
    "name:arg_x_preferred":[
        "Landa"
    ],
    "name:cat_x_preferred":[
        "Landa"
    ],
    "name:ceb_x_preferred":[
        "Landa"
    ],
    "name:deu_x_preferred":[
        "Landa"
    ],
    "name:eus_x_preferred":[
        "Landa"
    ],
    "name:fra_x_preferred":[
        "Landa"
    ],
    "name:ita_x_preferred":[
        "Landa"
    ],
    "name:nds_x_preferred":[
        "Landa"
    ],
    "name:por_x_preferred":[
        "Landa"
    ],
    "name:spa_x_preferred":[
        "Landa"
    ],
    "name:swe_x_preferred":[
        "Landa"
    ],
    "name:ukr_x_preferred":[
        "\u041b\u0430\u043d\u0434\u0430"
    ],
    "wof:name":"Landa",
    "wof:placetype":"locality"
},
  "geometry": {"coordinates":[34.89028,-12.57944],"type":"Point"}
}