{
  "type": "Feature",
  "properties": {
    "gn:admin1_code":"3.0",
    "gn:asciiname":"F. Chiquepo",
    "gn:country_code":"MZ",
    "gn:dem":62,
    "gn:feature_class":"P",
    "gn:feature_code":"PPL",
    "gn:name":"F. Chiquepo",
    "gn:population":0,
    "gn:timezone":"Africa/Maputo",
    "iso:country":"MZ",
    "wof:name":"F. Chiquepo",
    "wof:placetype":"locality"
},
  "geometry": {"coordinates":[34.42055999999999,-24.75611],"type":"Point"}
}