{
  "type": "Feature",
  "properties": {
    "gn:admin1_code":"1",
    "gn:asciiname":"Mitende",
    "gn:country_code":"MZ",
    "gn:dem":744,
    "gn:feature_class":"P",
    "gn:feature_code":"PPL",
    "gn:name":"Mitende",
    "gn:population":0,
    "gn:timezone":"Africa/Maputo",
    "iso:country":"MZ",
    "wof:name":"Mitende",
    "wof:placetype":"locality"
},
  "geometry": {"coordinates":[39.43556,-11.33139],"type":"Point"}
}