{
  "type": "Feature",
  "properties": {
    "gn:admin1_code":"8",
    "gn:asciiname":"Botao",
    "gn:country_code":"MZ",
    "gn:dem":175,
    "gn:feature_class":"P",
    "gn:feature_code":"PPL",
    "gn:name":"Bot\u00e3o",
    "gn:population":0,
    "gn:timezone":"Africa/Maputo",
    "iso:country":"MZ",
    "wof:name":"Botao",
    "wof:placetype":"locality"
},
  "geometry": {"coordinates":[33.08222,-15.67556],"type":"Point"}
}