{
  "type": "Feature",
  "properties": {
    "gn:admin1_code":"8",
    "gn:asciiname":"Massanangoe",
    "gn:cc2":"MZ",
    "gn:country_code":"MZ",
    "gn:dem":173,
    "gn:feature_class":"P",
    "gn:feature_code":"PPL",
    "gn:name":"Massanango\u00e8",
    "gn:population":0,
    "gn:timezone":"Africa/Maputo",
    "iso:country":"MZ",
    "name:und_x_variant":[
        "Massanangua",
        "Massanango\u00e8"
    ],
    "wof:name":"Massanangoe",
    "wof:placetype":"locality"
},
  "geometry": {"coordinates":[33.10583,-15.74389],"type":"Point"}
}