{
  "type": "Feature",
  "properties": {
    "gn:admin1_code":"2.0",
    "gn:asciiname":"Jemisse",
    "gn:country_code":"MZ",
    "gn:dem":182,
    "gn:feature_class":"P",
    "gn:feature_code":"PPL",
    "gn:name":"Jemisse",
    "gn:population":0,
    "gn:timezone":"Africa/Maputo",
    "iso:country":"MZ",
    "wof:name":"Jemisse",
    "wof:placetype":"locality"
},
  "geometry": {"coordinates":[31.725,-22.51917000000001],"type":"Point"}
}