{
  "type": "Feature",
  "properties": {
    "gn:admin1_code":"8",
    "gn:asciiname":"Cassepa",
    "gn:country_code":"MZ",
    "gn:dem":918,
    "gn:feature_class":"P",
    "gn:feature_code":"PPL",
    "gn:name":"Cassepa",
    "gn:population":0,
    "gn:timezone":"Africa/Maputo",
    "iso:country":"MZ",
    "wof:name":"Cassepa",
    "wof:placetype":"locality"
},
  "geometry": {"coordinates":[30.82694,-14.88694],"type":"Point"}
}