{
  "type": "Feature",
  "properties": {
    "gn:admin1_code":"2",
    "gn:asciiname":"Chefe Nenguassuna",
    "gn:cc2":"MZ",
    "gn:country_code":"MZ",
    "gn:dem":129,
    "gn:feature_class":"P",
    "gn:feature_code":"PPL",
    "gn:name":"Chefe Nenguassuna",
    "gn:population":0,
    "gn:timezone":"Africa/Maputo",
    "iso:country":"MZ",
    "name:und_x_variant":[
        "Nenguassuna",
        "Chefe Nenguassuna"
    ],
    "wof:name":"Chefe Nenguassuna",
    "wof:placetype":"locality"
},
  "geometry": {"coordinates":[32.6225,-22.47694],"type":"Point"}
}