{
  "type": "Feature",
  "properties": {
    "gn:admin1_code":"3",
    "gn:asciiname":"Macasse",
    "gn:country_code":"MZ",
    "gn:dem":135,
    "gn:feature_class":"P",
    "gn:feature_code":"PPL",
    "gn:name":"Macasse",
    "gn:population":0,
    "gn:timezone":"Africa/Maputo",
    "iso:country":"MZ",
    "wof:name":"Macasse",
    "wof:placetype":"locality"
},
  "geometry": {"coordinates":[34.51472,-21.72556],"type":"Point"}
}