{
  "type": "Feature",
  "properties": {
    "gn:admin1_code":"10",
    "gn:asciiname":"Inhadiro",
    "gn:country_code":"MZ",
    "gn:dem":640,
    "gn:feature_class":"P",
    "gn:feature_code":"PPL",
    "gn:name":"Inhadiro",
    "gn:population":0,
    "gn:timezone":"Africa/Maputo",
    "iso:country":"MZ",
    "wof:name":"Inhadiro",
    "wof:placetype":"locality"
},
  "geometry": {"coordinates":[33.03028,-18.56361],"type":"Point"}
}