{
  "type": "Feature",
  "properties": {
    "gn:admin1_code":"10",
    "gn:asciiname":"Cavalarica",
    "gn:cc2":"MZ",
    "gn:country_code":"MZ",
    "gn:dem":646,
    "gn:feature_class":"P",
    "gn:feature_code":"PPL",
    "gn:name":"Cavalarica",
    "gn:population":0,
    "gn:timezone":"Africa/Maputo",
    "iso:country":"MZ",
    "name:und_x_variant":[
        "Cavalari\u00e7a",
        "Cavalarica"
    ],
    "wof:name":"Cavalarica",
    "wof:placetype":"locality"
},
  "geometry": {"coordinates":[33.06861,-18.29472],"type":"Point"}
}