{
  "type": "Feature",
  "properties": {
    "gn:admin1_code":"9",
    "gn:asciiname":"Cagema",
    "gn:country_code":"MZ",
    "gn:dem":279,
    "gn:feature_class":"P",
    "gn:feature_code":"PPL",
    "gn:name":"Cagema",
    "gn:population":0,
    "gn:timezone":"Africa/Maputo",
    "iso:country":"MZ",
    "wof:name":"Cagema",
    "wof:placetype":"locality"
},
  "geometry": {"coordinates":[38.11167,-16.02889],"type":"Point"}
}