{
  "type": "Feature",
  "properties": {
    "gn:admin1_code":"3",
    "gn:asciiname":"Manuel",
    "gn:country_code":"MZ",
    "gn:dem":32,
    "gn:feature_class":"P",
    "gn:feature_code":"PPL",
    "gn:name":"Manuel",
    "gn:population":0,
    "gn:timezone":"Africa/Maputo",
    "iso:country":"MZ",
    "name:bre_x_preferred":[
        "Manuel"
    ],
    "name:ceb_x_preferred":[
        "Manuel"
    ],
    "name:deu_x_preferred":[
        "Manuel"
    ],
    "name:ell_x_preferred":[
        "\u039c\u03b1\u03bd\u03bf\u03c5\u03ae\u03bb"
    ],
    "name:fra_x_preferred":[
        "Manuel"
    ],
    "name:heb_x_preferred":[
        "\u05de\u05e0\u05d5\u05d0\u05dc"
    ],
    "name:ita_x_preferred":[
        "Manuel"
    ],
    "name:jpn_x_preferred":[
        "\u30de\u30cc\u30a8\u30eb"
    ],
    "name:nah_x_preferred":[
        "Manuel"
    ],
    "name:nld_x_preferred":[
        "Manuel"
    ],
    "name:por_x_preferred":[
        "Manuel"
    ],
    "name:rus_x_preferred":[
        "\u041c\u0430\u043d\u0443\u0438\u043b"
    ],
    "name:spa_x_preferred":[
        "Manuel"
    ],
    "name:srp_x_preferred":[
        "\u041c\u0430\u043d\u0443\u0435\u043b"
    ],
    "name:swe_x_preferred":[
        "Manuel"
    ],
    "name:ukr_x_preferred":[
        "\u041c\u0430\u043d\u0443\u0457\u043b"
    ],
    "wof:name":"Manuel",
    "wof:placetype":"locality"
},
  "geometry": {"coordinates":[35.19667000000001,-21.94361],"type":"Point"}
}