{
  "type": "Feature",
  "properties": {
    "gn:admin1_code":"3",
    "gn:asciiname":"Manuel",
    "gn:country_code":"MZ",
    "gn:dem":32,
    "gn:feature_class":"P",
    "gn:feature_code":"PPL",
    "gn:name":"Manuel",
    "gn:population":0,
    "gn:timezone":"Africa/Maputo",
    "iso:country":"MZ",
    "wof:name":"Manuel",
    "wof:placetype":"locality"
},
  "geometry": {"coordinates":[35.19667000000001,-21.94361],"type":"Point"}
}