{
  "type": "Feature",
  "properties": {
    "gn:admin1_code":"3.0",
    "gn:asciiname":"Tesambo",
    "gn:country_code":"MZ",
    "gn:dem":115,
    "gn:feature_class":"P",
    "gn:feature_code":"PPL",
    "gn:name":"Tesambo",
    "gn:population":0,
    "gn:timezone":"Africa/Maputo",
    "iso:country":"MZ",
    "wof:name":"Tesambo",
    "wof:placetype":"locality"
},
  "geometry": {"coordinates":[34.00917,-22.69139],"type":"Point"}
}