{
  "type": "Feature",
  "properties": {
    "gn:admin1_code":"9",
    "gn:asciiname":"Campo",
    "gn:country_code":"MZ",
    "gn:dem":36,
    "gn:feature_class":"P",
    "gn:feature_code":"PPL",
    "gn:name":"Campo",
    "gn:population":0,
    "gn:timezone":"Africa/Maputo",
    "iso:country":"MZ",
    "wof:name":"Campo",
    "wof:placetype":"locality"
},
  "geometry": {"coordinates":[36.32917,-17.76083],"type":"Point"}
}