{
  "type": "Feature",
  "properties": {
    "gn:admin1_code":"1",
    "gn:asciiname":"Antumano",
    "gn:country_code":"MZ",
    "gn:dem":228,
    "gn:feature_class":"P",
    "gn:feature_code":"PPL",
    "gn:name":"Antumano",
    "gn:population":0,
    "gn:timezone":"Africa/Maputo",
    "iso:country":"MZ",
    "wof:name":"Antumano",
    "wof:placetype":"locality"
},
  "geometry": {"coordinates":[40.23167,-12.40833],"type":"Point"}
}