{
  "type": "Feature",
  "properties": {
    "gn:admin1_code":"10",
    "gn:asciiname":"Bacequete",
    "gn:country_code":"MZ",
    "gn:dem":454,
    "gn:feature_class":"P",
    "gn:feature_code":"PPL",
    "gn:name":"Bacequete",
    "gn:population":0,
    "gn:timezone":"Africa/Maputo",
    "iso:country":"MZ",
    "name:por_x_preferred":[
        "Bacequete"
    ],
    "wof:name":"Bacequete",
    "wof:placetype":"locality"
},
  "geometry": {"coordinates":[33.01833,-20.29833],"type":"Point"}
}