{
  "type": "Feature",
  "properties": {
    "gn:admin1_code":"9",
    "gn:asciiname":"Mindai",
    "gn:country_code":"MZ",
    "gn:dem":278,
    "gn:feature_class":"P",
    "gn:feature_code":"PPL",
    "gn:name":"Mindai",
    "gn:population":0,
    "gn:timezone":"Africa/Maputo",
    "iso:country":"MZ",
    "wof:name":"Mindai",
    "wof:placetype":"locality"
},
  "geometry": {"coordinates":[35.9325,-17.13444],"type":"Point"}
}