{
  "type": "Feature",
  "properties": {
    "gn:admin1_code":"9",
    "gn:asciiname":"Milato",
    "gn:country_code":"MZ",
    "gn:dem":3,
    "gn:feature_class":"P",
    "gn:feature_code":"PPL",
    "gn:name":"Milato",
    "gn:population":0,
    "gn:timezone":"Africa/Maputo",
    "iso:country":"MZ",
    "wof:name":"Milato",
    "wof:placetype":"locality"
},
  "geometry": {"coordinates":[36.92167,-17.79083],"type":"Point"}
}