{
  "type": "Feature",
  "properties": {
    "gn:admin1_code":"3",
    "gn:asciiname":"Massinga",
    "gn:country_code":"MZ",
    "gn:dem":111,
    "gn:feature_class":"P",
    "gn:feature_code":"PPL",
    "gn:name":"Massinga",
    "gn:population":0,
    "gn:timezone":"Africa/Maputo",
    "iso:country":"MZ",
    "wof:name":"Massinga",
    "wof:placetype":"locality"
},
  "geometry": {"coordinates":[35.38139,-23.32917],"type":"Point"}
}