{
  "type": "Feature",
  "properties": {
    "gn:admin1_code":"3.0",
    "gn:asciiname":"Cabo Uiane",
    "gn:country_code":"MZ",
    "gn:dem":117,
    "gn:feature_class":"P",
    "gn:feature_code":"PPL",
    "gn:name":"Cabo Uiane",
    "gn:population":0,
    "gn:timezone":"Africa/Maputo",
    "iso:country":"MZ",
    "wof:name":"Cabo Uiane",
    "wof:placetype":"locality"
},
  "geometry": {"coordinates":[35.04944,-22.97861],"type":"Point"}
}