{
  "type": "Feature",
  "properties": {
    "gn:admin1_code":"5",
    "gn:asciiname":"Massacage",
    "gn:country_code":"MZ",
    "gn:dem":243,
    "gn:feature_class":"P",
    "gn:feature_code":"PPL",
    "gn:name":"Massacage",
    "gn:population":0,
    "gn:timezone":"Africa/Maputo",
    "iso:country":"MZ",
    "wof:name":"Massacage",
    "wof:placetype":"locality"
},
  "geometry": {"coordinates":[33.74889,-20.3675],"type":"Point"}
}