{
  "type": "Feature",
  "properties": {
    "gn:admin1_code":"2.0",
    "gn:asciiname":"Serpa",
    "gn:country_code":"MZ",
    "gn:dem":126,
    "gn:feature_class":"P",
    "gn:feature_code":"PPL",
    "gn:name":"Serpa",
    "gn:population":0,
    "gn:timezone":"Africa/Maputo",
    "iso:country":"MZ",
    "name:ara_x_preferred":[
        "\u0633\u0631\u0628\u0627"
    ],
    "name:cat_x_preferred":[
        "Serpa"
    ],
    "name:ceb_x_preferred":[
        "Serpa"
    ],
    "name:deu_x_preferred":[
        "Serpa"
    ],
    "name:eus_x_preferred":[
        "Serpa"
    ],
    "name:fas_x_preferred":[
        "\u0633\u0631\u067e\u0627"
    ],
    "name:fin_x_preferred":[
        "Serpa"
    ],
    "name:fra_x_preferred":[
        "Serpa"
    ],
    "name:ita_x_preferred":[
        "Serpa"
    ],
    "name:jpn_x_preferred":[
        "\u30bb\u30eb\u30d1"
    ],
    "name:kat_x_preferred":[
        "\u10e1\u10d4\u10e0\u10de\u10d0"
    ],
    "name:mzn_x_preferred":[
        "\u0633\u0631\u067e\u0627"
    ],
    "name:nld_x_preferred":[
        "Serpa"
    ],
    "name:nor_x_preferred":[
        "Serpa"
    ],
    "name:pol_x_preferred":[
        "Serpa"
    ],
    "name:por_x_preferred":[
        "Serpa"
    ],
    "name:ron_x_preferred":[
        "Serpa"
    ],
    "name:rus_x_preferred":[
        "\u0421\u0435\u0440\u043f\u0430"
    ],
    "name:spa_x_preferred":[
        "Serpa"
    ],
    "name:tur_x_preferred":[
        "Serpa"
    ],
    "name:ukr_x_preferred":[
        "\u0421\u0435\u0440\u043f\u0430"
    ],
    "name:vie_x_preferred":[
        "Serpa"
    ],
    "name:vol_x_preferred":[
        "Serpa"
    ],
    "name:war_x_preferred":[
        "Serpa"
    ],
    "name:zho_x_preferred":[
        "\u585e\u723e\u5e15"
    ],
    "wof:name":"Serpa",
    "wof:placetype":"locality"
},
  "geometry": {"coordinates":[32.58972,-23.5675],"type":"Point"}
}