{
  "type": "Feature",
  "properties": {
    "gn:admin1_code":"8",
    "gn:asciiname":"Catavinha",
    "gn:country_code":"MZ",
    "gn:dem":316,
    "gn:feature_class":"P",
    "gn:feature_code":"PPL",
    "gn:name":"Catavinha",
    "gn:population":0,
    "gn:timezone":"Africa/Maputo",
    "iso:country":"MZ",
    "wof:name":"Catavinha",
    "wof:placetype":"locality"
},
  "geometry": {"coordinates":[33.21778,-16.395],"type":"Point"}
}