{
  "type": "Feature",
  "properties": {
    "gn:admin1_code":"1",
    "gn:asciiname":"Nagen",
    "gn:country_code":"MZ",
    "gn:dem":341,
    "gn:feature_class":"P",
    "gn:feature_code":"PPL",
    "gn:name":"Nagen",
    "gn:population":0,
    "gn:timezone":"Africa/Maputo",
    "iso:country":"MZ",
    "wof:name":"Nagen",
    "wof:placetype":"locality"
},
  "geometry": {"coordinates":[39.65833,-13.36194],"type":"Point"}
}