{
  "type": "Feature",
  "properties": {
    "gn:admin1_code":"3.0",
    "gn:asciiname":"Sautane",
    "gn:country_code":"MZ",
    "gn:dem":63,
    "gn:feature_class":"P",
    "gn:feature_code":"PPL",
    "gn:name":"Sautane",
    "gn:population":0,
    "gn:timezone":"Africa/Maputo",
    "iso:country":"MZ",
    "wof:name":"Sautane",
    "wof:placetype":"locality"
},
  "geometry": {"coordinates":[33.98806,-23.69111],"type":"Point"}
}