{
  "type": "Feature",
  "properties": {
    "gn:admin1_code":"8",
    "gn:asciiname":"Nhenda",
    "gn:country_code":"MZ",
    "gn:dem":422,
    "gn:feature_class":"P",
    "gn:feature_code":"PPL",
    "gn:name":"Nhenda",
    "gn:population":0,
    "gn:timezone":"Africa/Maputo",
    "iso:country":"MZ",
    "wof:name":"Nhenda",
    "wof:placetype":"locality"
},
  "geometry": {"coordinates":[31.96944,-15.56583],"type":"Point"}
}