{
  "type": "Feature",
  "properties": {
    "gn:admin1_code":"3",
    "gn:asciiname":"Macuanine",
    "gn:country_code":"MZ",
    "gn:dem":88,
    "gn:feature_class":"P",
    "gn:feature_code":"PPL",
    "gn:name":"Macuanine",
    "gn:population":0,
    "gn:timezone":"Africa/Maputo",
    "iso:country":"MZ",
    "wof:name":"Macuanine",
    "wof:placetype":"locality"
},
  "geometry": {"coordinates":[34.46889,-23.59778],"type":"Point"}
}