{
  "type": "Feature",
  "properties": {
    "gn:admin1_code":"9.0",
    "gn:asciiname":"Suale",
    "gn:country_code":"MZ",
    "gn:dem":56,
    "gn:feature_class":"P",
    "gn:feature_code":"PPL",
    "gn:name":"Sual\u00e8",
    "gn:population":0,
    "gn:timezone":"Africa/Maputo",
    "iso:country":"MZ",
    "wof:name":"Suale",
    "wof:placetype":"locality"
},
  "geometry": {"coordinates":[37.81722,-17.08167000000001],"type":"Point"}
}