{
  "type": "Feature",
  "properties": {
    "gn:admin1_code":"1",
    "gn:asciiname":"Lusso",
    "gn:country_code":"MZ",
    "gn:dem":480,
    "gn:feature_class":"P",
    "gn:feature_code":"PPL",
    "gn:name":"Lusso",
    "gn:population":0,
    "gn:timezone":"Africa/Maputo",
    "iso:country":"MZ",
    "wof:name":"Lusso",
    "wof:placetype":"locality"
},
  "geometry": {"coordinates":[38.97611,-13.11806],"type":"Point"}
}