{
  "type": "Feature",
  "properties": {
    "gn:admin1_code":"9",
    "gn:asciiname":"Pedro",
    "gn:country_code":"MZ",
    "gn:dem":114,
    "gn:feature_class":"P",
    "gn:feature_code":"PPL",
    "gn:name":"Pedro",
    "gn:population":0,
    "gn:timezone":"Africa/Maputo",
    "iso:country":"MZ",
    "wof:name":"Pedro",
    "wof:placetype":"locality"
},
  "geometry": {"coordinates":[37.72944,-16.9525],"type":"Point"}
}