{
  "type": "Feature",
  "properties": {
    "gn:admin1_code":"1",
    "gn:asciiname":"Muala",
    "gn:country_code":"MZ",
    "gn:dem":386,
    "gn:feature_class":"P",
    "gn:feature_code":"PPL",
    "gn:name":"Muala",
    "gn:population":0,
    "gn:timezone":"Africa/Maputo",
    "iso:country":"MZ",
    "wof:name":"Muala",
    "wof:placetype":"locality"
},
  "geometry": {"coordinates":[40.14083,-12.2575],"type":"Point"}
}