{
  "type": "Feature",
  "properties": {
    "gn:admin1_code":"3",
    "gn:asciiname":"Cabo Catine",
    "gn:cc2":"MZ",
    "gn:country_code":"MZ",
    "gn:dem":164,
    "gn:feature_class":"P",
    "gn:feature_code":"PPL",
    "gn:name":"Cabo Catine",
    "gn:population":0,
    "gn:timezone":"Africa/Maputo",
    "iso:country":"MZ",
    "name:und_x_variant":[
        "Catine",
        "Cabo Catine"
    ],
    "wof:name":"Cabo Catine",
    "wof:placetype":"locality"
},
  "geometry": {"coordinates":[34.88389,-23.74194],"type":"Point"}
}