{
  "type": "Feature",
  "properties": {
    "gn:admin1_code":"1",
    "gn:asciiname":"Olumbe",
    "gn:cc2":"MZ",
    "gn:country_code":"MZ",
    "gn:dem":12,
    "gn:feature_class":"P",
    "gn:feature_code":"PPL",
    "gn:name":"Olumbe",
    "gn:population":0,
    "gn:timezone":"Africa/Maputo",
    "iso:country":"MZ",
    "name:und_x_variant":[
        "Olumbi",
        "Olumbe"
    ],
    "wof:name":"Olumbe",
    "wof:placetype":"locality"
},
  "geometry": {"coordinates":[40.47389,-10.99306],"type":"Point"}
}