{
  "type": "Feature",
  "properties": {
    "gn:admin1_code":"3.0",
    "gn:asciiname":"Macachocho",
    "gn:country_code":"MZ",
    "gn:dem":-9999,
    "gn:feature_class":"P",
    "gn:feature_code":"PPL",
    "gn:name":"Macachocho",
    "gn:population":0,
    "gn:timezone":"Africa/Maputo",
    "iso:country":"MZ",
    "wof:name":"Macachocho",
    "wof:placetype":"locality"
},
  "geometry": {"coordinates":[35.53111,-22.15833],"type":"Point"}
}