{
  "type": "Feature",
  "properties": {
    "gn:admin1_code":"1.0",
    "gn:asciiname":"Teucha",
    "gn:country_code":"MZ",
    "gn:dem":401,
    "gn:feature_class":"P",
    "gn:feature_code":"PPL",
    "gn:name":"Teucha",
    "gn:population":0,
    "gn:timezone":"Africa/Maputo",
    "iso:country":"MZ",
    "wof:name":"Teucha",
    "wof:placetype":"locality"
},
  "geometry": {"coordinates":[39.40472000000001,-12.81778],"type":"Point"}
}