{
  "type": "Feature",
  "properties": {
    "gn:admin1_code":"2.0",
    "gn:asciiname":"Alfredo",
    "gn:country_code":"MZ",
    "gn:dem":97,
    "gn:feature_class":"P",
    "gn:feature_code":"PPL",
    "gn:name":"Alfredo",
    "gn:population":0,
    "gn:timezone":"Africa/Maputo",
    "iso:country":"MZ",
    "name:aze_x_preferred":[
        "Alfredo"
    ],
    "name:bre_x_preferred":[
        "Alfredo"
    ],
    "name:epo_x_preferred":[
        "Alfredo"
    ],
    "name:fas_x_preferred":[
        "\u0622\u0644\u0641\u0631\u062f\u0648"
    ],
    "name:glg_x_preferred":[
        "Alfredo"
    ],
    "name:ita_x_preferred":[
        "Alfredo"
    ],
    "name:jpn_x_preferred":[
        "\u30a2\u30eb\u30d5\u30ec\u30fc\u30c9"
    ],
    "name:lat_x_preferred":[
        "Alfredus"
    ],
    "name:por_x_preferred":[
        "Alfredo"
    ],
    "name:scn_x_preferred":[
        "Arfredu"
    ],
    "name:spa_x_preferred":[
        "Alfredo"
    ],
    "wof:name":"Alfredo",
    "wof:placetype":"locality"
},
  "geometry": {"coordinates":[33.95389,-24.82667],"type":"Point"}
}