{
  "type": "Feature",
  "properties": {
    "gn:admin1_code":"6",
    "gn:asciiname":"Regulo Muaquia",
    "gn:country_code":"MZ",
    "gn:dem":297,
    "gn:feature_class":"P",
    "gn:feature_code":"PPL",
    "gn:name":"R\u00e9gulo Muaquia",
    "gn:population":0,
    "gn:timezone":"Africa/Maputo",
    "iso:country":"MZ",
    "wof:name":"Regulo Muaquia",
    "wof:placetype":"locality"
},
  "geometry": {"coordinates":[39.15833,-13.99667],"type":"Point"}
}