{
  "type": "Feature",
  "properties": {
    "gn:admin1_code":"1",
    "gn:asciiname":"Netonia",
    "gn:country_code":"MZ",
    "gn:dem":861,
    "gn:feature_class":"P",
    "gn:feature_code":"PPL",
    "gn:name":"Netonia",
    "gn:population":0,
    "gn:timezone":"Africa/Maputo",
    "iso:country":"MZ",
    "wof:name":"Netonia",
    "wof:placetype":"locality"
},
  "geometry": {"coordinates":[39.5275,-11.54389],"type":"Point"}
}