{
  "type": "Feature",
  "properties": {
    "gn:admin1_code":"7",
    "gn:asciiname":"Natuco",
    "gn:country_code":"MZ",
    "gn:dem":669,
    "gn:feature_class":"P",
    "gn:feature_code":"PPL",
    "gn:name":"Natuco",
    "gn:population":0,
    "gn:timezone":"Africa/Maputo",
    "iso:country":"MZ",
    "wof:name":"Natuco",
    "wof:placetype":"locality"
},
  "geometry": {"coordinates":[36.66056,-13.40389],"type":"Point"}
}