{
  "type": "Feature",
  "properties": {
    "gn:admin1_code":"1",
    "gn:asciiname":"Palovi",
    "gn:country_code":"MZ",
    "gn:dem":152,
    "gn:feature_class":"P",
    "gn:feature_code":"PPL",
    "gn:name":"Palovi",
    "gn:population":0,
    "gn:timezone":"Africa/Maputo",
    "iso:country":"MZ",
    "wof:name":"Palovi",
    "wof:placetype":"locality"
},
  "geometry": {"coordinates":[40.05278,-13.28611],"type":"Point"}
}