{
  "type": "Feature",
  "properties": {
    "gn:admin1_code":"7",
    "gn:asciiname":"Chaul",
    "gn:country_code":"MZ",
    "gn:dem":722,
    "gn:feature_class":"P",
    "gn:feature_code":"PPL",
    "gn:name":"Chaul",
    "gn:population":0,
    "gn:timezone":"Africa/Maputo",
    "iso:country":"MZ",
    "name:ara_x_preferred":[
        "\u0634\u0627\u0648\u0644"
    ],
    "name:deu_x_preferred":[
        "Chaul"
    ],
    "name:jpn_x_preferred":[
        "\u30c1\u30e3\u30a6\u30eb"
    ],
    "name:nor_x_preferred":[
        "Chaul"
    ],
    "name:por_x_preferred":[
        "Chaul"
    ],
    "name:spa_x_preferred":[
        "Chaul"
    ],
    "name:urd_x_preferred":[
        "\u0686\u0648\u0644"
    ],
    "wof:name":"Chaul",
    "wof:placetype":"locality"
},
  "geometry": {"coordinates":[34.98028,-12.06778],"type":"Point"}
}