{
  "type": "Feature",
  "properties": {
    "gn:admin1_code":"7",
    "gn:asciiname":"Chaul",
    "gn:country_code":"MZ",
    "gn:dem":722,
    "gn:feature_class":"P",
    "gn:feature_code":"PPL",
    "gn:name":"Chaul",
    "gn:population":0,
    "gn:timezone":"Africa/Maputo",
    "iso:country":"MZ",
    "wof:name":"Chaul",
    "wof:placetype":"locality"
},
  "geometry": {"coordinates":[34.98028,-12.06778],"type":"Point"}
}