{
  "type": "Feature",
  "properties": {
    "gn:admin1_code":"2",
    "gn:asciiname":"Maponisse",
    "gn:country_code":"MZ",
    "gn:dem":47,
    "gn:feature_class":"P",
    "gn:feature_code":"PPL",
    "gn:name":"Maponisse",
    "gn:population":0,
    "gn:timezone":"Africa/Maputo",
    "iso:country":"MZ",
    "wof:name":"Maponisse",
    "wof:placetype":"locality"
},
  "geometry": {"coordinates":[32.73278,-24.21056],"type":"Point"}
}