{
  "type": "Feature",
  "properties": {
    "gn:admin1_code":"0",
    "gn:asciiname":"Maganame",
    "gn:country_code":"MZ",
    "gn:dem":75,
    "gn:feature_class":"P",
    "gn:feature_code":"PPL",
    "gn:name":"Maganame",
    "gn:population":0,
    "gn:timezone":"Africa/Maputo",
    "iso:country":"MZ",
    "wof:name":"Maganame",
    "wof:placetype":"locality"
},
  "geometry": {"coordinates":[32.21667,-25.35],"type":"Point"}
}