{
  "type": "Feature",
  "properties": {
    "gn:admin1_code":"7",
    "gn:asciiname":"Chirangue",
    "gn:cc2":"MZ",
    "gn:country_code":"MZ",
    "gn:dem":176,
    "gn:feature_class":"P",
    "gn:feature_code":"PPL",
    "gn:name":"Chirangue",
    "gn:population":0,
    "gn:timezone":"Africa/Maputo",
    "iso:country":"MZ",
    "name:und_x_variant":[
        "Ch\u00edrangue",
        "Chirangue"
    ],
    "wof:name":"Chirangue",
    "wof:placetype":"locality"
},
  "geometry": {"coordinates":[38.39944000000001,-11.69667],"type":"Point"}
}