{
  "type": "Feature",
  "properties": {
    "gn:admin1_code":"3",
    "gn:asciiname":"Mufemane",
    "gn:country_code":"MZ",
    "gn:dem":134,
    "gn:feature_class":"P",
    "gn:feature_code":"PPL",
    "gn:name":"Mufemane",
    "gn:population":0,
    "gn:timezone":"Africa/Maputo",
    "iso:country":"MZ",
    "wof:name":"Mufemane",
    "wof:placetype":"locality"
},
  "geometry": {"coordinates":[34.87,-23.80222],"type":"Point"}
}