{
  "type": "Feature",
  "properties": {
    "gn:admin1_code":"2.0",
    "gn:asciiname":"Muhutuani",
    "gn:country_code":"MZ",
    "gn:dem":72,
    "gn:feature_class":"P",
    "gn:feature_code":"PPL",
    "gn:name":"Muhutuani",
    "gn:population":0,
    "gn:timezone":"Africa/Maputo",
    "iso:country":"MZ",
    "wof:name":"Muhutuani",
    "wof:placetype":"locality"
},
  "geometry": {"coordinates":[33.41305999999999,-23.00556],"type":"Point"}
}