{
  "type": "Feature",
  "properties": {
    "gn:admin1_code":"9",
    "gn:asciiname":"Campiria",
    "gn:country_code":"MZ",
    "gn:dem":500,
    "gn:feature_class":"P",
    "gn:feature_code":"PPL",
    "gn:name":"Campiria",
    "gn:population":0,
    "gn:timezone":"Africa/Maputo",
    "iso:country":"MZ",
    "wof:name":"Campiria",
    "wof:placetype":"locality"
},
  "geometry": {"coordinates":[37.64528,-15.90806],"type":"Point"}
}