{
  "type": "Feature",
  "properties": {
    "gn:admin1_code":"6",
    "gn:asciiname":"Amela",
    "gn:country_code":"MZ",
    "gn:dem":95,
    "gn:feature_class":"P",
    "gn:feature_code":"PPL",
    "gn:name":"Amela",
    "gn:population":0,
    "gn:timezone":"Africa/Maputo",
    "iso:country":"MZ",
    "wof:name":"Amela",
    "wof:placetype":"locality"
},
  "geometry": {"coordinates":[39.10222,-16.56694],"type":"Point"}
}