{
  "type": "Feature",
  "properties": {
    "gn:admin1_code":"9.0",
    "gn:asciiname":"Batista",
    "gn:country_code":"MZ",
    "gn:dem":202,
    "gn:feature_class":"P",
    "gn:feature_code":"PPL",
    "gn:name":"Batista",
    "gn:population":0,
    "gn:timezone":"Africa/Maputo",
    "iso:country":"MZ",
    "wof:name":"Batista",
    "wof:placetype":"locality"
},
  "geometry": {"coordinates":[37.14278,-16.61528],"type":"Point"}
}