{
  "type": "Feature",
  "properties": {
    "gn:admin1_code":"10.0",
    "gn:asciiname":"Serenga",
    "gn:country_code":"MZ",
    "gn:dem":132,
    "gn:feature_class":"P",
    "gn:feature_code":"PPL",
    "gn:name":"Serenga",
    "gn:population":0,
    "gn:timezone":"Africa/Maputo",
    "iso:country":"MZ",
    "wof:name":"Serenga",
    "wof:placetype":"locality"
},
  "geometry": {"coordinates":[33.63889,-16.43222],"type":"Point"}
}