{
  "type": "Feature",
  "properties": {
    "gn:admin1_code":"6",
    "gn:asciiname":"Muezia",
    "gn:country_code":"MZ",
    "gn:dem":329,
    "gn:feature_class":"P",
    "gn:feature_code":"PPL",
    "gn:name":"Mu\u00e9zia",
    "gn:population":0,
    "gn:timezone":"Africa/Maputo",
    "iso:country":"MZ",
    "wof:name":"Muezia",
    "wof:placetype":"locality"
},
  "geometry": {"coordinates":[39.51083,-15.05694],"type":"Point"}
}