{
  "type": "Feature",
  "properties": {
    "gn:admin1_code":"6.0",
    "gn:asciiname":"Quatieque",
    "gn:cc2":"MZ",
    "gn:country_code":"MZ",
    "gn:dem":153,
    "gn:feature_class":"P",
    "gn:feature_code":"PPL",
    "gn:name":"Quatieque",
    "gn:population":0,
    "gn:timezone":"Africa/Maputo",
    "iso:country":"MZ",
    "name:und_x_variant":[
        "Quatiegue",
        "Quatieque"
    ],
    "wof:name":"Quatieque",
    "wof:placetype":"locality"
},
  "geometry": {"coordinates":[39.24972,-15.81889],"type":"Point"}
}