{
  "type": "Feature",
  "properties": {
    "gn:admin1_code":"2",
    "gn:asciiname":"Licose",
    "gn:country_code":"MZ",
    "gn:dem":118,
    "gn:feature_class":"P",
    "gn:feature_code":"PPL",
    "gn:name":"Lic\u00f3se",
    "gn:population":0,
    "gn:timezone":"Africa/Maputo",
    "iso:country":"MZ",
    "wof:name":"Licose",
    "wof:placetype":"locality"
},
  "geometry": {"coordinates":[32.09583,-23.03167],"type":"Point"}
}