{
  "type": "Feature",
  "properties": {
    "gn:admin1_code":"8.0",
    "gn:asciiname":"Tumbuca",
    "gn:country_code":"MZ",
    "gn:dem":1306,
    "gn:feature_class":"P",
    "gn:feature_code":"PPL",
    "gn:name":"Tumbuca",
    "gn:population":0,
    "gn:timezone":"Africa/Maputo",
    "iso:country":"MZ",
    "wof:name":"Tumbuca",
    "wof:placetype":"locality"
},
  "geometry": {"coordinates":[34.43056,-14.83222],"type":"Point"}
}