{
  "type": "Feature",
  "properties": {
    "gn:admin1_code":"9",
    "gn:asciiname":"Calanhama",
    "gn:country_code":"MZ",
    "gn:dem":13,
    "gn:feature_class":"P",
    "gn:feature_code":"PPL",
    "gn:name":"Calanhama",
    "gn:population":0,
    "gn:timezone":"Africa/Maputo",
    "iso:country":"MZ",
    "wof:name":"Calanhama",
    "wof:placetype":"locality"
},
  "geometry": {"coordinates":[35.93083,-18.06],"type":"Point"}
}