{
  "type": "Feature",
  "properties": {
    "gn:admin1_code":"2.0",
    "gn:asciiname":"Muomena",
    "gn:country_code":"MZ",
    "gn:dem":74,
    "gn:feature_class":"P",
    "gn:feature_code":"PPL",
    "gn:name":"Muomena",
    "gn:population":0,
    "gn:timezone":"Africa/Maputo",
    "iso:country":"MZ",
    "wof:name":"Muomena",
    "wof:placetype":"locality"
},
  "geometry": {"coordinates":[32.55833,-23.98917],"type":"Point"}
}