{
  "type": "Feature",
  "properties": {
    "gn:admin1_code":"10.0",
    "gn:asciiname":"Chimuanda",
    "gn:country_code":"MZ",
    "gn:dem":543,
    "gn:feature_class":"P",
    "gn:feature_code":"PPL",
    "gn:name":"Chimuanda",
    "gn:population":0,
    "gn:timezone":"Africa/Maputo",
    "iso:country":"MZ",
    "wof:name":"Chimuanda",
    "wof:placetype":"locality"
},
  "geometry": {"coordinates":[33.72778,-19.01389],"type":"Point"}
}