{
  "type": "Feature",
  "properties": {
    "gn:admin1_code":"1",
    "gn:asciiname":"Almeida",
    "gn:country_code":"MZ",
    "gn:dem":104,
    "gn:feature_class":"P",
    "gn:feature_code":"PPL",
    "gn:name":"Almeida",
    "gn:population":0,
    "gn:timezone":"Africa/Maputo",
    "iso:country":"MZ",
    "name:bel_x_preferred":[
        "\u0410\u043b\u043c\u0435\u0439\u0434\u0430"
    ],
    "name:bul_x_preferred":[
        "\u0410\u043b\u043c\u0435\u0439\u0434\u0430"
    ],
    "name:ceb_x_preferred":[
        "Almeida"
    ],
    "name:ces_x_preferred":[
        "Almeida"
    ],
    "name:deu_x_preferred":[
        "Almeida"
    ],
    "name:eus_x_preferred":[
        "Almeida"
    ],
    "name:fra_x_preferred":[
        "Almeida"
    ],
    "name:ita_x_preferred":[
        "Almeida"
    ],
    "name:jpn_x_preferred":[
        "\u30a2\u30eb\u30e1\u30a4\u30c0"
    ],
    "name:kor_x_preferred":[
        "\uc54c\uba54\uc774\ub2e4"
    ],
    "name:nld_x_preferred":[
        "Almeida"
    ],
    "name:por_x_preferred":[
        "Almeida"
    ],
    "name:rus_x_preferred":[
        "\u0410\u043b\u043c\u0435\u0439\u0434\u0430"
    ],
    "name:slv_x_preferred":[
        "Almeida"
    ],
    "name:spa_x_preferred":[
        "Almeida"
    ],
    "name:swe_x_preferred":[
        "Almeida"
    ],
    "name:ukr_x_preferred":[
        "\u0410\u043b\u043c\u0435\u0439\u0434\u0430"
    ],
    "wof:name":"Almeida",
    "wof:placetype":"locality"
},
  "geometry": {"coordinates":[40.19333,-11.59639],"type":"Point"}
}