{
  "type": "Feature",
  "properties": {
    "gn:admin1_code":"4.0",
    "gn:asciiname":"Uamahula",
    "gn:cc2":"MZ",
    "gn:country_code":"MZ",
    "gn:dem":66,
    "gn:feature_class":"P",
    "gn:feature_code":"PPL",
    "gn:name":"Uamahula",
    "gn:population":0,
    "gn:timezone":"Africa/Maputo",
    "iso:country":"MZ",
    "name:und_x_variant":[
        "Uamuhamele",
        "Uamahula"
    ],
    "wof:name":"Uamahula",
    "wof:placetype":"locality"
},
  "geometry": {"coordinates":[32.52417,-24.8425],"type":"Point"}
}