{
  "type": "Feature",
  "properties": {
    "gn:admin1_code":"3",
    "gn:asciiname":"Lifande",
    "gn:country_code":"MZ",
    "gn:dem":32,
    "gn:feature_class":"P",
    "gn:feature_code":"PPL",
    "gn:name":"Lifande",
    "gn:population":0,
    "gn:timezone":"Africa/Maputo",
    "iso:country":"MZ",
    "wof:name":"Lifande",
    "wof:placetype":"locality"
},
  "geometry": {"coordinates":[35.10972,-21.4475],"type":"Point"}
}