{
  "type": "Feature",
  "properties": {
    "gn:admin1_code":"7.0",
    "gn:asciiname":"Vanavegua",
    "gn:country_code":"MZ",
    "gn:dem":686,
    "gn:feature_class":"P",
    "gn:feature_code":"PPL",
    "gn:name":"Vanavegua",
    "gn:population":0,
    "gn:timezone":"Africa/Maputo",
    "iso:country":"MZ",
    "wof:name":"Vanavegua",
    "wof:placetype":"locality"
},
  "geometry": {"coordinates":[36.06028,-15.36083],"type":"Point"}
}