{
  "type": "Feature",
  "properties": {
    "gn:admin1_code":"0.0",
    "gn:asciiname":"Sunda",
    "gn:country_code":"MZ",
    "gn:dem":794,
    "gn:feature_class":"P",
    "gn:feature_code":"PPL",
    "gn:name":"Sunda",
    "gn:population":0,
    "gn:timezone":"Africa/Maputo",
    "iso:country":"MZ",
    "wof:name":"Sunda",
    "wof:placetype":"locality"
},
  "geometry": {"coordinates":[31.45,-15.15],"type":"Point"}
}