{
  "type": "Feature",
  "properties": {
    "gn:admin1_code":"9.0",
    "gn:asciiname":"Mucuti",
    "gn:country_code":"MZ",
    "gn:dem":286,
    "gn:feature_class":"P",
    "gn:feature_code":"PPL",
    "gn:name":"Mucuti",
    "gn:population":0,
    "gn:timezone":"Africa/Maputo",
    "iso:country":"MZ",
    "wof:name":"Mucuti",
    "wof:placetype":"locality"
},
  "geometry": {"coordinates":[37.64083,-16.39194],"type":"Point"}
}