{
  "type": "Feature",
  "properties": {
    "gn:admin1_code":"6.0",
    "gn:asciiname":"Xaramatane",
    "gn:country_code":"MZ",
    "gn:dem":15,
    "gn:feature_class":"P",
    "gn:feature_code":"PPL",
    "gn:name":"Xaramatane",
    "gn:population":0,
    "gn:timezone":"Africa/Maputo",
    "iso:country":"MZ",
    "wof:name":"Xaramatane",
    "wof:placetype":"locality"
},
  "geometry": {"coordinates":[40.01917,-15.91056],"type":"Point"}
}