{
  "type": "Feature",
  "properties": {
    "gn:admin1_code":"7",
    "gn:asciiname":"Cajama",
    "gn:cc2":"MZ",
    "gn:country_code":"MZ",
    "gn:dem":680,
    "gn:feature_class":"P",
    "gn:feature_code":"PPL",
    "gn:name":"Cajama",
    "gn:population":0,
    "gn:timezone":"Africa/Maputo",
    "iso:country":"MZ",
    "name:und_x_variant":[
        "Mucajama",
        "Cajama"
    ],
    "wof:name":"Cajama",
    "wof:placetype":"locality"
},
  "geometry": {"coordinates":[36.03778,-15.4375],"type":"Point"}
}