{
  "type": "Feature",
  "properties": {
    "gn:admin1_code":"7",
    "gn:asciiname":"Namacaca",
    "gn:country_code":"MZ",
    "gn:dem":652,
    "gn:feature_class":"P",
    "gn:feature_code":"PPL",
    "gn:name":"Namacaca",
    "gn:population":0,
    "gn:timezone":"Africa/Maputo",
    "iso:country":"MZ",
    "wof:name":"Namacaca",
    "wof:placetype":"locality"
},
  "geometry": {"coordinates":[35.94694000000001,-15.28639],"type":"Point"}
}