{
  "type": "Feature",
  "properties": {
    "gn:admin1_code":"2",
    "gn:asciiname":"Chiconela",
    "gn:country_code":"MZ",
    "gn:dem":43,
    "gn:feature_class":"P",
    "gn:feature_code":"PPL",
    "gn:name":"Chiconela",
    "gn:population":0,
    "gn:timezone":"Africa/Maputo",
    "iso:country":"MZ",
    "wof:name":"Chiconela",
    "wof:placetype":"locality"
},
  "geometry": {"coordinates":[33.49806,-24.99528],"type":"Point"}
}