{
  "type": "Feature",
  "properties": {
    "gn:admin1_code":"7",
    "gn:asciiname":"Quemuenhe",
    "gn:country_code":"MZ",
    "gn:dem":585,
    "gn:feature_class":"P",
    "gn:feature_code":"PPL",
    "gn:name":"Quemuenhe",
    "gn:population":0,
    "gn:timezone":"Africa/Maputo",
    "iso:country":"MZ",
    "wof:name":"Quemuenhe",
    "wof:placetype":"locality"
},
  "geometry": {"coordinates":[36.71833,-14.9775],"type":"Point"}
}