{
  "type": "Feature",
  "properties": {
    "gn:admin1_code":"8",
    "gn:asciiname":"Caloa",
    "gn:country_code":"MZ",
    "gn:dem":810,
    "gn:feature_class":"P",
    "gn:feature_code":"PPL",
    "gn:name":"Cal\u00f4a",
    "gn:population":0,
    "gn:timezone":"Africa/Maputo",
    "iso:country":"MZ",
    "wof:name":"Caloa",
    "wof:placetype":"locality"
},
  "geometry": {"coordinates":[34.06917,-15.06583],"type":"Point"}
}