{
  "type": "Feature",
  "properties": {
    "gn:admin1_code":"2",
    "gn:asciiname":"Cale",
    "gn:country_code":"MZ",
    "gn:dem":24,
    "gn:feature_class":"P",
    "gn:feature_code":"PPL",
    "gn:name":"Cale",
    "gn:population":0,
    "gn:timezone":"Africa/Maputo",
    "iso:country":"MZ",
    "name:ceb_x_preferred":[
        "Cale"
    ],
    "name:ces_x_preferred":[
        "Cale"
    ],
    "name:deu_x_preferred":[
        "Cale"
    ],
    "name:fra_x_preferred":[
        "Cale"
    ],
    "name:ita_x_preferred":[
        "Cale"
    ],
    "name:jpn_x_preferred":[
        "\u30b1\u30fc\u30eb"
    ],
    "name:lat_x_preferred":[
        "Cale"
    ],
    "name:nld_x_preferred":[
        "Cale"
    ],
    "name:por_x_preferred":[
        "Cale"
    ],
    "name:rus_x_preferred":[
        "\u041a\u0435\u0439\u043b"
    ],
    "name:spa_x_preferred":[
        "Cale"
    ],
    "name:swe_x_preferred":[
        "Cale"
    ],
    "wof:name":"Cale",
    "wof:placetype":"locality"
},
  "geometry": {"coordinates":[33.19556,-25.25167],"type":"Point"}
}