{
  "type": "Feature",
  "properties": {
    "gn:admin1_code":"3.0",
    "gn:asciiname":"Filambo",
    "gn:country_code":"MZ",
    "gn:dem":125,
    "gn:feature_class":"P",
    "gn:feature_code":"PPL",
    "gn:name":"Filambo",
    "gn:population":0,
    "gn:timezone":"Africa/Maputo",
    "iso:country":"MZ",
    "wof:name":"Filambo",
    "wof:placetype":"locality"
},
  "geometry": {"coordinates":[34.88056,-22.51639],"type":"Point"}
}