{
  "type": "Feature",
  "properties": {
    "gn:admin1_code":"9",
    "gn:asciiname":"Mucorra",
    "gn:cc2":"MZ",
    "gn:country_code":"MZ",
    "gn:dem":583,
    "gn:feature_class":"P",
    "gn:feature_code":"PPL",
    "gn:name":"Mucorra",
    "gn:population":0,
    "gn:timezone":"Africa/Maputo",
    "iso:country":"MZ",
    "name:und_x_variant":[
        "Mec\u00f3rro",
        "Mucorra"
    ],
    "wof:name":"Mucorra",
    "wof:placetype":"locality"
},
  "geometry": {"coordinates":[37.74056,-15.63306],"type":"Point"}
}