{
  "type": "Feature",
  "properties": {
    "gn:admin1_code":"1",
    "gn:asciiname":"Nechapi",
    "gn:country_code":"MZ",
    "gn:dem":685,
    "gn:feature_class":"P",
    "gn:feature_code":"PPL",
    "gn:name":"Nechapi",
    "gn:population":0,
    "gn:timezone":"Africa/Maputo",
    "iso:country":"MZ",
    "wof:name":"Nechapi",
    "wof:placetype":"locality"
},
  "geometry": {"coordinates":[39.50111,-11.35694],"type":"Point"}
}