{
  "type": "Feature",
  "properties": {
    "gn:admin1_code":"3",
    "gn:asciiname":"Chefe Daiacambe",
    "gn:cc2":"MZ",
    "gn:country_code":"MZ",
    "gn:dem":59,
    "gn:feature_class":"P",
    "gn:feature_code":"PPL",
    "gn:name":"Chefe Daiacambe",
    "gn:population":0,
    "gn:timezone":"Africa/Maputo",
    "iso:country":"MZ",
    "name:und_x_variant":[
        "Malukissa",
        "Dacambe",
        "Chefe Daiacambe"
    ],
    "wof:name":"Chefe Daiacambe",
    "wof:placetype":"locality"
},
  "geometry": {"coordinates":[34.89056,-24.66889],"type":"Point"}
}