{
  "type": "Feature",
  "properties": {
    "gn:admin1_code":"2",
    "gn:asciiname":"Chimutezuane",
    "gn:country_code":"MZ",
    "gn:dem":117,
    "gn:feature_class":"P",
    "gn:feature_code":"PPL",
    "gn:name":"Chimutezuane",
    "gn:population":0,
    "gn:timezone":"Africa/Maputo",
    "iso:country":"MZ",
    "wof:name":"Chimutezuane",
    "wof:placetype":"locality"
},
  "geometry": {"coordinates":[33.02944,-22.07278],"type":"Point"}
}