{
  "type": "Feature",
  "properties": {
    "gn:admin1_code":"1",
    "gn:asciiname":"Nechica",
    "gn:country_code":"MZ",
    "gn:dem":471,
    "gn:feature_class":"P",
    "gn:feature_code":"PPL",
    "gn:name":"Nechica",
    "gn:population":0,
    "gn:timezone":"Africa/Maputo",
    "iso:country":"MZ",
    "wof:name":"Nechica",
    "wof:placetype":"locality"
},
  "geometry": {"coordinates":[38.92556,-13.53278],"type":"Point"}
}