{
  "type": "Feature",
  "properties": {
    "gn:admin1_code":"10",
    "gn:asciiname":"Dondoe",
    "gn:country_code":"MZ",
    "gn:dem":147,
    "gn:feature_class":"P",
    "gn:feature_code":"PPL",
    "gn:name":"Dondo\u00e9",
    "gn:population":0,
    "gn:timezone":"Africa/Maputo",
    "iso:country":"MZ",
    "wof:name":"Dondoe",
    "wof:placetype":"locality"
},
  "geometry": {"coordinates":[33.74944,-20.71833],"type":"Point"}
}