{
  "type": "Feature",
  "properties": {
    "gn:admin1_code":"9",
    "gn:asciiname":"Grande",
    "gn:country_code":"MZ",
    "gn:dem":368,
    "gn:feature_class":"P",
    "gn:feature_code":"PPL",
    "gn:name":"Grande",
    "gn:population":0,
    "gn:timezone":"Africa/Maputo",
    "iso:country":"MZ",
    "name:ara_x_preferred":[
        "\u063a\u0631\u0627\u0646\u062f\u064a"
    ],
    "name:ben_x_preferred":[
        "\u0997\u09cd\u09b0\u09cd\u09af\u09be\u09a8\u09cd\u09a1\u09c7"
    ],
    "name:ceb_x_preferred":[
        "Grande"
    ],
    "name:deu_x_preferred":[
        "Grande"
    ],
    "name:ell_x_preferred":[
        "\u0393\u03ba\u03c1\u03ac\u03bd\u03c4\u03b5"
    ],
    "name:fas_x_preferred":[
        "\u06af\u0631\u0627\u0646\u062f"
    ],
    "name:fra_x_preferred":[
        "Grande"
    ],
    "name:fry_x_preferred":[
        "Grande"
    ],
    "name:glg_x_preferred":[
        "Grande"
    ],
    "name:heb_x_preferred":[
        "\u05d2\u05e8\u05d0\u05e0\u05d3"
    ],
    "name:hin_x_preferred":[
        "\u0917\u094d\u0930\u0948\u0902\u0921\u0947"
    ],
    "name:hun_x_preferred":[
        "Grande"
    ],
    "name:ind_x_preferred":[
        "Grande"
    ],
    "name:ita_x_preferred":[
        "Grande"
    ],
    "name:jpn_x_preferred":[
        "\u30b0\u30e9\u30f3\u30c7"
    ],
    "name:kor_x_preferred":[
        "\uadf8\ub780\ub370"
    ],
    "name:nld_x_preferred":[
        "Grande"
    ],
    "name:pol_x_preferred":[
        "Rio Grande"
    ],
    "name:pol_x_variant":[
        "Grande"
    ],
    "name:por_x_preferred":[
        "Grande"
    ],
    "name:ron_x_preferred":[
        "Grande"
    ],
    "name:rus_x_preferred":[
        "\u0413\u0440\u0430\u043d\u0434\u0435\u043d"
    ],
    "name:slk_x_preferred":[
        "Grande"
    ],
    "name:spa_x_preferred":[
        "Grande"
    ],
    "name:srp_x_preferred":[
        "Grande"
    ],
    "name:swe_x_preferred":[
        "Grande"
    ],
    "name:tur_x_preferred":[
        "Grande"
    ],
    "name:urd_x_preferred":[
        "\u06af\u0631\u0627\u0646\u0688\u06d2"
    ],
    "name:vie_x_preferred":[
        "S\u00f4ng Grande"
    ],
    "wof:name":"Grande",
    "wof:placetype":"locality"
},
  "geometry": {"coordinates":[36.13722,-16.29083],"type":"Point"}
}