{
  "type": "Feature",
  "properties": {
    "gn:admin1_code":"9",
    "gn:asciiname":"Grande",
    "gn:country_code":"MZ",
    "gn:dem":368,
    "gn:feature_class":"P",
    "gn:feature_code":"PPL",
    "gn:name":"Grande",
    "gn:population":0,
    "gn:timezone":"Africa/Maputo",
    "iso:country":"MZ",
    "wof:name":"Grande",
    "wof:placetype":"locality"
},
  "geometry": {"coordinates":[36.13722,-16.29083],"type":"Point"}
}