{
  "type": "Feature",
  "properties": {
    "gn:admin1_code":"3",
    "gn:asciiname":"Mangueze",
    "gn:country_code":"MZ",
    "gn:dem":44,
    "gn:feature_class":"P",
    "gn:feature_code":"PPL",
    "gn:name":"Mangueze",
    "gn:population":0,
    "gn:timezone":"Africa/Maputo",
    "iso:country":"MZ",
    "wof:name":"Mangueze",
    "wof:placetype":"locality"
},
  "geometry": {"coordinates":[34.97056,-21.68444],"type":"Point"}
}