{
  "type": "Feature",
  "properties": {
    "gn:admin1_code":"1",
    "gn:asciiname":"Necavandano",
    "gn:country_code":"MZ",
    "gn:dem":336,
    "gn:feature_class":"P",
    "gn:feature_code":"PPL",
    "gn:name":"Necavandano",
    "gn:population":0,
    "gn:timezone":"Africa/Maputo",
    "iso:country":"MZ",
    "wof:name":"Necavandano",
    "wof:placetype":"locality"
},
  "geometry": {"coordinates":[39.72944,-11.28222],"type":"Point"}
}