{
  "type": "Feature",
  "properties": {
    "gn:admin1_code":"3.0",
    "gn:asciiname":"Muchungo",
    "gn:country_code":"MZ",
    "gn:dem":83,
    "gn:feature_class":"P",
    "gn:feature_code":"PPL",
    "gn:name":"Muchungo",
    "gn:population":0,
    "gn:timezone":"Africa/Maputo",
    "iso:country":"MZ",
    "wof:name":"Muchungo",
    "wof:placetype":"locality"
},
  "geometry": {"coordinates":[35.46639000000001,-22.94167],"type":"Point"}
}