{
  "type": "Feature",
  "properties": {
    "gn:admin1_code":"7",
    "gn:asciiname":"Cassane",
    "gn:country_code":"MZ",
    "gn:dem":712,
    "gn:feature_class":"P",
    "gn:feature_code":"PPL",
    "gn:name":"Cassane",
    "gn:population":0,
    "gn:timezone":"Africa/Maputo",
    "iso:country":"MZ",
    "wof:name":"Cassane",
    "wof:placetype":"locality"
},
  "geometry": {"coordinates":[36.00583,-13.1375],"type":"Point"}
}