{
  "type": "Feature",
  "properties": {
    "gn:admin1_code":"2",
    "gn:asciiname":"Pebene",
    "gn:country_code":"MZ",
    "gn:dem":90,
    "gn:feature_class":"P",
    "gn:feature_code":"PPL",
    "gn:name":"Pebene",
    "gn:population":0,
    "gn:timezone":"Africa/Maputo",
    "iso:country":"MZ",
    "wof:name":"Pebene",
    "wof:placetype":"locality"
},
  "geometry": {"coordinates":[33.44889000000001,-22.74167000000001],"type":"Point"}
}