{
  "type": "Feature",
  "properties": {
    "gn:admin1_code":"2",
    "gn:asciiname":"Namborrete",
    "gn:country_code":"MZ",
    "gn:dem":117,
    "gn:feature_class":"P",
    "gn:feature_code":"PPL",
    "gn:name":"Namborrete",
    "gn:population":0,
    "gn:timezone":"Africa/Maputo",
    "iso:country":"MZ",
    "wof:name":"Namborrete",
    "wof:placetype":"locality"
},
  "geometry": {"coordinates":[32.41778,-24.25306],"type":"Point"}
}