{
  "type": "Feature",
  "properties": {
    "gn:admin1_code":"9",
    "gn:asciiname":"Pacala",
    "gn:country_code":"MZ",
    "gn:dem":33,
    "gn:feature_class":"P",
    "gn:feature_code":"PPL",
    "gn:name":"Pacala",
    "gn:population":0,
    "gn:timezone":"Africa/Maputo",
    "iso:country":"MZ",
    "wof:name":"Pacala",
    "wof:placetype":"locality"
},
  "geometry": {"coordinates":[37.76861,-17.26556],"type":"Point"}
}