{
  "type": "Feature",
  "properties": {
    "gn:admin1_code":"6",
    "gn:asciiname":"Puia",
    "gn:country_code":"MZ",
    "gn:dem":202,
    "gn:feature_class":"P",
    "gn:feature_code":"PPL",
    "gn:name":"Pu\u00eda",
    "gn:population":0,
    "gn:timezone":"Africa/Maputo",
    "iso:country":"MZ",
    "wof:name":"Puia",
    "wof:placetype":"locality"
},
  "geometry": {"coordinates":[39.95389,-13.59556],"type":"Point"}
}