{
  "type": "Feature",
  "properties": {
    "gn:admin1_code":"8",
    "gn:asciiname":"Chiremboe",
    "gn:country_code":"MZ",
    "gn:dem":730,
    "gn:feature_class":"P",
    "gn:feature_code":"PPL",
    "gn:name":"Chirembo\u00e8",
    "gn:population":0,
    "gn:timezone":"Africa/Maputo",
    "iso:country":"MZ",
    "wof:name":"Chiremboe",
    "wof:placetype":"locality"
},
  "geometry": {"coordinates":[33.26222,-14.71583],"type":"Point"}
}