{
  "type": "Feature",
  "properties": {
    "gn:admin1_code":"4",
    "gn:asciiname":"Feijao",
    "gn:country_code":"MZ",
    "gn:dem":26,
    "gn:feature_class":"P",
    "gn:feature_code":"PPL",
    "gn:name":"Feij\u00e3o",
    "gn:population":0,
    "gn:timezone":"Africa/Maputo",
    "iso:country":"MZ",
    "wof:name":"Feijao",
    "wof:placetype":"locality"
},
  "geometry": {"coordinates":[32.98278,-25.35722],"type":"Point"}
}