{
  "type": "Feature",
  "properties": {
    "gn:admin1_code":"8",
    "gn:asciiname":"Mefideze",
    "gn:country_code":"MZ",
    "gn:dem":179,
    "gn:feature_class":"P",
    "gn:feature_code":"PPL",
    "gn:name":"Mefideze",
    "gn:population":0,
    "gn:timezone":"Africa/Maputo",
    "iso:country":"MZ",
    "wof:name":"Mefideze",
    "wof:placetype":"locality"
},
  "geometry": {"coordinates":[33.27667,-15.88361],"type":"Point"}
}