{
  "type": "Feature",
  "properties": {
    "gn:admin1_code":"2.0",
    "gn:asciiname":"Chauque",
    "gn:country_code":"MZ",
    "gn:dem":76,
    "gn:feature_class":"P",
    "gn:feature_code":"PPL",
    "gn:name":"Cha\u00faque",
    "gn:population":0,
    "gn:timezone":"Africa/Maputo",
    "iso:country":"MZ",
    "wof:name":"Chauque",
    "wof:placetype":"locality"
},
  "geometry": {"coordinates":[33.01889,-23.70333],"type":"Point"}
}