{
  "type": "Feature",
  "properties": {
    "gn:admin1_code":"1",
    "gn:asciiname":"Metama",
    "gn:country_code":"MZ",
    "gn:dem":613,
    "gn:feature_class":"P",
    "gn:feature_code":"PPL",
    "gn:name":"Metama",
    "gn:population":0,
    "gn:timezone":"Africa/Maputo",
    "iso:country":"MZ",
    "wof:name":"Metama",
    "wof:placetype":"locality"
},
  "geometry": {"coordinates":[39.44333,-11.35944],"type":"Point"}
}