{
  "type": "Feature",
  "properties": {
    "gn:admin1_code":"3",
    "gn:asciiname":"Andela",
    "gn:country_code":"MZ",
    "gn:dem":128,
    "gn:feature_class":"P",
    "gn:feature_code":"PPL",
    "gn:name":"Andela",
    "gn:population":0,
    "gn:timezone":"Africa/Maputo",
    "iso:country":"MZ",
    "wof:name":"Andela",
    "wof:placetype":"locality"
},
  "geometry": {"coordinates":[34.73889,-22.87806],"type":"Point"}
}