{
  "type": "Feature",
  "properties": {
    "gn:admin1_code":"3",
    "gn:asciiname":"Maave",
    "gn:cc2":"MZ",
    "gn:country_code":"MZ",
    "gn:dem":15,
    "gn:feature_class":"P",
    "gn:feature_code":"PPL",
    "gn:name":"Maave",
    "gn:population":0,
    "gn:timezone":"Africa/Maputo",
    "iso:country":"MZ",
    "name:und_x_variant":[
        "Mahave",
        "Maave"
    ],
    "wof:name":"Maave",
    "wof:placetype":"locality"
},
  "geometry": {"coordinates":[34.82972,-21.07444],"type":"Point"}
}