{
  "type": "Feature",
  "properties": {
    "gn:admin1_code":"4",
    "gn:asciiname":"Chibuni",
    "gn:cc2":"MZ",
    "gn:country_code":"MZ",
    "gn:dem":90,
    "gn:feature_class":"P",
    "gn:feature_code":"PPL",
    "gn:name":"Chibuni",
    "gn:population":0,
    "gn:timezone":"Africa/Maputo",
    "iso:country":"MZ",
    "name:und_x_variant":[
        "Isac",
        "Chibuni"
    ],
    "wof:name":"Chibuni",
    "wof:placetype":"locality"
},
  "geometry": {"coordinates":[32.44278,-24.71194],"type":"Point"}
}