{
  "type": "Feature",
  "properties": {
    "gn:admin1_code":"10",
    "gn:asciiname":"Maera",
    "gn:country_code":"MZ",
    "gn:dem":122,
    "gn:feature_class":"P",
    "gn:feature_code":"PPL",
    "gn:name":"Maera",
    "gn:population":0,
    "gn:timezone":"Africa/Maputo",
    "iso:country":"MZ",
    "wof:name":"Maera",
    "wof:placetype":"locality"
},
  "geometry": {"coordinates":[33.48111,-20.28278],"type":"Point"}
}