{
  "type": "Feature",
  "properties": {
    "gn:admin1_code":"3",
    "gn:asciiname":"Chinabetane",
    "gn:country_code":"MZ",
    "gn:dem":177,
    "gn:feature_class":"P",
    "gn:feature_code":"PPL",
    "gn:name":"Chinabetane",
    "gn:population":0,
    "gn:timezone":"Africa/Maputo",
    "iso:country":"MZ",
    "wof:name":"Chinabetane",
    "wof:placetype":"locality"
},
  "geometry": {"coordinates":[34.10833,-21.66944],"type":"Point"}
}