{
  "type": "Feature",
  "properties": {
    "gn:admin1_code":"5",
    "gn:asciiname":"Subwe",
    "gn:cc2":"MZ",
    "gn:country_code":"MZ",
    "gn:dem":161,
    "gn:feature_class":"P",
    "gn:feature_code":"PPL",
    "gn:name":"Subw\u00e8",
    "gn:population":0,
    "gn:timezone":"Africa/Maputo",
    "iso:country":"MZ",
    "name:und_x_variant":[
        "Chuva",
        "Subw\u00e8"
    ],
    "wof:name":"Subwe",
    "wof:placetype":"locality"
},
  "geometry": {"coordinates":[34.42861,-18.13472],"type":"Point"}
}