{
  "type": "Feature",
  "properties": {
    "gn:admin1_code":"5.0",
    "gn:asciiname":"Tomecena",
    "gn:cc2":"MZ",
    "gn:country_code":"MZ",
    "gn:dem":133,
    "gn:feature_class":"P",
    "gn:feature_code":"PPL",
    "gn:name":"Tomecena",
    "gn:population":0,
    "gn:timezone":"Africa/Maputo",
    "iso:country":"MZ",
    "name:und_x_variant":[
        "Tomeceni",
        "Tomecena"
    ],
    "wof:name":"Tomecena",
    "wof:placetype":"locality"
},
  "geometry": {"coordinates":[34.69139000000001,-17.31028],"type":"Point"}
}