{
  "type": "Feature",
  "properties": {
    "gn:admin1_code":"2.0",
    "gn:asciiname":"Senganhane",
    "gn:country_code":"MZ",
    "gn:dem":153,
    "gn:feature_class":"P",
    "gn:feature_code":"PPL",
    "gn:name":"Senganhane",
    "gn:population":0,
    "gn:timezone":"Africa/Maputo",
    "iso:country":"MZ",
    "wof:name":"Senganhane",
    "wof:placetype":"locality"
},
  "geometry": {"coordinates":[33.00417,-21.75222],"type":"Point"}
}