{
  "type": "Feature",
  "properties": {
    "gn:admin1_code":"7",
    "gn:asciiname":"Banaaque",
    "gn:country_code":"MZ",
    "gn:dem":477,
    "gn:feature_class":"P",
    "gn:feature_code":"PPL",
    "gn:name":"Bana\u00e1que",
    "gn:population":0,
    "gn:timezone":"Africa/Maputo",
    "iso:country":"MZ",
    "wof:name":"Banaaque",
    "wof:placetype":"locality"
},
  "geometry": {"coordinates":[37.45556,-14.40194],"type":"Point"}
}