{
  "type": "Feature",
  "properties": {
    "gn:admin1_code":"10",
    "gn:asciiname":"Diquia",
    "gn:country_code":"MZ",
    "gn:dem":757,
    "gn:feature_class":"P",
    "gn:feature_code":"PPL",
    "gn:name":"Diquia",
    "gn:population":0,
    "gn:timezone":"Africa/Maputo",
    "iso:country":"MZ",
    "name:por_x_preferred":[
        "Diquia"
    ],
    "wof:name":"Diquia",
    "wof:placetype":"locality"
},
  "geometry": {"coordinates":[32.785,-20.50333],"type":"Point"}
}