{
  "type": "Feature",
  "properties": {
    "gn:admin1_code":"9",
    "gn:asciiname":"Muliquela",
    "gn:cc2":"MZ",
    "gn:country_code":"MZ",
    "gn:dem":424,
    "gn:feature_class":"P",
    "gn:feature_code":"PPL",
    "gn:name":"Muliquela",
    "gn:population":0,
    "gn:timezone":"Africa/Maputo",
    "iso:country":"MZ",
    "name:und_x_variant":[
        "Mim\u00e1ua",
        "Muliquela"
    ],
    "wof:name":"Muliquela",
    "wof:placetype":"locality"
},
  "geometry": {"coordinates":[37.11944,-15.95278],"type":"Point"}
}