{
  "type": "Feature",
  "properties": {
    "gn:admin1_code":"1",
    "gn:asciiname":"Namuero",
    "gn:country_code":"MZ",
    "gn:dem":303,
    "gn:feature_class":"P",
    "gn:feature_code":"PPL",
    "gn:name":"Namuero",
    "gn:population":0,
    "gn:timezone":"Africa/Maputo",
    "iso:country":"MZ",
    "wof:name":"Namuero",
    "wof:placetype":"locality"
},
  "geometry": {"coordinates":[39.13917,-14.00972],"type":"Point"}
}