{
  "type": "Feature",
  "properties": {
    "gn:admin1_code":"9",
    "gn:asciiname":"Fernando",
    "gn:country_code":"MZ",
    "gn:dem":87,
    "gn:feature_class":"P",
    "gn:feature_code":"PPL",
    "gn:name":"Fernando",
    "gn:population":0,
    "gn:timezone":"Africa/Maputo",
    "iso:country":"MZ",
    "name:aze_x_preferred":[
        "Fernando"
    ],
    "name:bre_x_preferred":[
        "Fernando"
    ],
    "name:ces_x_preferred":[
        "Ferdinand"
    ],
    "name:deu_x_preferred":[
        "Ferdinand"
    ],
    "name:epo_x_preferred":[
        "Ferdinando"
    ],
    "name:fin_x_preferred":[
        "Ferdinand"
    ],
    "name:glg_x_preferred":[
        "Fernando"
    ],
    "name:hun_x_preferred":[
        "Ferdin\u00e1nd"
    ],
    "name:ita_x_preferred":[
        "Ferdinando"
    ],
    "name:lat_x_preferred":[
        "Ferdinandus"
    ],
    "name:nor_x_preferred":[
        "Ferdinand"
    ],
    "name:pol_x_preferred":[
        "Ferdynand"
    ],
    "name:por_x_preferred":[
        "Fernando"
    ],
    "name:rus_x_preferred":[
        "Fernando"
    ],
    "name:slk_x_preferred":[
        "Ferdinand"
    ],
    "name:slv_x_preferred":[
        "Ferdinand"
    ],
    "name:spa_x_preferred":[
        "Fernando"
    ],
    "name:ukr_x_preferred":[
        "\u0424\u0435\u0440\u043d\u0430\u043d\u0434\u0443"
    ],
    "wof:name":"Fernando",
    "wof:placetype":"locality"
},
  "geometry": {"coordinates":[37.29889,-17.28833],"type":"Point"}
}