{
  "type": "Feature",
  "properties": {
    "gn:admin1_code":"1",
    "gn:asciiname":"Namoera",
    "gn:country_code":"MZ",
    "gn:dem":125,
    "gn:feature_class":"P",
    "gn:feature_code":"PPL",
    "gn:name":"Namoera",
    "gn:population":0,
    "gn:timezone":"Africa/Maputo",
    "iso:country":"MZ",
    "wof:name":"Namoera",
    "wof:placetype":"locality"
},
  "geometry": {"coordinates":[40.015,-12.44222],"type":"Point"}
}