{
  "type": "Feature",
  "properties": {
    "gn:admin1_code":"3",
    "gn:asciiname":"Duane",
    "gn:country_code":"MZ",
    "gn:dem":162,
    "gn:feature_class":"P",
    "gn:feature_code":"PPL",
    "gn:name":"Duane",
    "gn:population":0,
    "gn:timezone":"Africa/Maputo",
    "iso:country":"MZ",
    "name:deu_x_preferred":[
        "Duane"
    ],
    "name:fra_x_preferred":[
        "Duane"
    ],
    "name:por_x_preferred":[
        "Duane"
    ],
    "wof:name":"Duane",
    "wof:placetype":"locality"
},
  "geometry": {"coordinates":[33.895,-21.96167],"type":"Point"}
}