{
  "type": "Feature",
  "properties": {
    "gn:admin1_code":"10",
    "gn:asciiname":"Nhadota",
    "gn:cc2":"MZ",
    "gn:country_code":"MZ",
    "gn:dem":488,
    "gn:feature_class":"P",
    "gn:feature_code":"PPL",
    "gn:name":"Nhadota",
    "gn:population":0,
    "gn:timezone":"Africa/Maputo",
    "iso:country":"MZ",
    "name:und_x_variant":[
        "Nhauate",
        "Nhadota"
    ],
    "wof:name":"Nhadota",
    "wof:placetype":"locality"
},
  "geometry": {"coordinates":[33.93639,-17.93361],"type":"Point"}
}