{
  "type": "Feature",
  "properties": {
    "gn:admin1_code":"5",
    "gn:asciiname":"Chiganda",
    "gn:country_code":"MZ",
    "gn:dem":78,
    "gn:feature_class":"P",
    "gn:feature_code":"PPL",
    "gn:name":"Chiganda",
    "gn:population":0,
    "gn:timezone":"Africa/Maputo",
    "iso:country":"MZ",
    "wof:name":"Chiganda",
    "wof:placetype":"locality"
},
  "geometry": {"coordinates":[34.70639,-18.18861],"type":"Point"}
}