{
  "type": "Feature",
  "properties": {
    "gn:admin1_code":"7",
    "gn:asciiname":"Matondovela",
    "gn:country_code":"MZ",
    "gn:dem":449,
    "gn:feature_class":"P",
    "gn:feature_code":"PPL",
    "gn:name":"Matondovela",
    "gn:population":0,
    "gn:timezone":"Africa/Maputo",
    "iso:country":"MZ",
    "wof:name":"Matondovela",
    "wof:placetype":"locality"
},
  "geometry": {"coordinates":[37.00278,-12.08167],"type":"Point"}
}