{
  "type": "Feature",
  "properties": {
    "gn:admin1_code":"6",
    "gn:asciiname":"Nacorrele",
    "gn:country_code":"MZ",
    "gn:dem":379,
    "gn:feature_class":"P",
    "gn:feature_code":"PPL",
    "gn:name":"Nacorrele",
    "gn:population":0,
    "gn:timezone":"Africa/Maputo",
    "iso:country":"MZ",
    "wof:name":"Nacorrele",
    "wof:placetype":"locality"
},
  "geometry": {"coordinates":[39.56167,-14.68222],"type":"Point"}
}