{
  "type": "Feature",
  "properties": {
    "gn:admin1_code":"5",
    "gn:asciiname":"Mafunaire",
    "gn:country_code":"MZ",
    "gn:dem":80,
    "gn:feature_class":"P",
    "gn:feature_code":"PPL",
    "gn:name":"Mafunaire",
    "gn:population":0,
    "gn:timezone":"Africa/Maputo",
    "iso:country":"MZ",
    "wof:name":"Mafunaire",
    "wof:placetype":"locality"
},
  "geometry": {"coordinates":[34.10861,-19.60111],"type":"Point"}
}