{
  "type": "Feature",
  "properties": {
    "gn:admin1_code":"9",
    "gn:asciiname":"Corromana",
    "gn:cc2":"MZ",
    "gn:country_code":"MZ",
    "gn:dem":742,
    "gn:feature_class":"P",
    "gn:feature_code":"PPL",
    "gn:name":"Corromana",
    "gn:population":0,
    "gn:timezone":"Africa/Maputo",
    "iso:country":"MZ",
    "name:und_x_variant":[
        "Coromane",
        "Corromana"
    ],
    "wof:name":"Corromana",
    "wof:placetype":"locality"
},
  "geometry": {"coordinates":[36.01667,-15.77389],"type":"Point"}
}