{
  "type": "Feature",
  "properties": {
    "gn:admin1_code":"2",
    "gn:asciiname":"Mavaivane",
    "gn:country_code":"MZ",
    "gn:dem":82,
    "gn:feature_class":"P",
    "gn:feature_code":"PPL",
    "gn:name":"Mavaivane",
    "gn:population":0,
    "gn:timezone":"Africa/Maputo",
    "iso:country":"MZ",
    "wof:name":"Mavaivane",
    "wof:placetype":"locality"
},
  "geometry": {"coordinates":[33.06778,-23.37333],"type":"Point"}
}