{
  "type": "Feature",
  "properties": {
    "gn:admin1_code":"5",
    "gn:asciiname":"Fundisse",
    "gn:country_code":"MZ",
    "gn:dem":144,
    "gn:feature_class":"P",
    "gn:feature_code":"PPL",
    "gn:name":"Fundisse",
    "gn:population":0,
    "gn:timezone":"Africa/Maputo",
    "iso:country":"MZ",
    "wof:name":"Fundisse",
    "wof:placetype":"locality"
},
  "geometry": {"coordinates":[34.51472,-18.15667],"type":"Point"}
}