{
  "type": "Feature",
  "properties": {
    "gn:admin1_code":"9.0",
    "gn:asciiname":"Chefe Camaquela",
    "gn:country_code":"MZ",
    "gn:dem":149,
    "gn:feature_class":"P",
    "gn:feature_code":"PPL",
    "gn:name":"Chefe Camaquela",
    "gn:population":0,
    "gn:timezone":"Africa/Maputo",
    "iso:country":"MZ",
    "wof:name":"Chefe Camaquela",
    "wof:placetype":"locality"
},
  "geometry": {"coordinates":[37.48472,-16.75944],"type":"Point"}
}