{
  "type": "Feature",
  "properties": {
    "gn:admin1_code":"1.0",
    "gn:asciiname":"Reteta",
    "gn:cc2":"MZ",
    "gn:country_code":"MZ",
    "gn:dem":629,
    "gn:feature_class":"P",
    "gn:feature_code":"PPL",
    "gn:name":"Reteta",
    "gn:population":0,
    "gn:timezone":"Africa/Maputo",
    "iso:country":"MZ",
    "name:und_x_variant":[
        "Ku\u00e9ku\u00e8",
        "Reteta"
    ],
    "wof:name":"Reteta",
    "wof:placetype":"locality"
},
  "geometry": {"coordinates":[38.42139,-13.54806],"type":"Point"}
}