{
  "type": "Feature",
  "properties": {
    "gn:admin1_code":"3.0",
    "gn:asciiname":"Safo",
    "gn:country_code":"MZ",
    "gn:dem":156,
    "gn:feature_class":"P",
    "gn:feature_code":"PPL",
    "gn:name":"Safo",
    "gn:population":0,
    "gn:timezone":"Africa/Maputo",
    "iso:country":"MZ",
    "name:ceb_x_preferred":[
        "Safo"
    ],
    "name:deu_x_preferred":[
        "Safo"
    ],
    "name:ita_x_preferred":[
        "Safo"
    ],
    "name:por_x_preferred":[
        "Safo"
    ],
    "name:swe_x_preferred":[
        "Safo"
    ],
    "wof:name":"Safo",
    "wof:placetype":"locality"
},
  "geometry": {"coordinates":[34.30860999999999,-22.5525],"type":"Point"}
}