{
  "type": "Feature",
  "properties": {
    "gn:admin1_code":"10",
    "gn:asciiname":"Joane",
    "gn:country_code":"MZ",
    "gn:dem":279,
    "gn:feature_class":"P",
    "gn:feature_code":"PPL",
    "gn:name":"Joane",
    "gn:population":0,
    "gn:timezone":"Africa/Maputo",
    "iso:country":"MZ",
    "name:ceb_x_preferred":[
        "Joane"
    ],
    "name:deu_x_preferred":[
        "Joane"
    ],
    "name:kaz_x_preferred":[
        "\u0416\u043e\u0430\u043d\u0435"
    ],
    "name:msa_x_preferred":[
        "Joane"
    ],
    "name:por_x_preferred":[
        "Joane"
    ],
    "name:rus_x_preferred":[
        "\u0416\u0443\u0430\u043d\u0438"
    ],
    "name:spa_x_preferred":[
        "Joane"
    ],
    "name:tur_x_preferred":[
        "Joane"
    ],
    "name:ukr_x_preferred":[
        "\u0416\u0443\u0430\u043d\u0435"
    ],
    "wof:name":"Joane",
    "wof:placetype":"locality"
},
  "geometry": {"coordinates":[33.56667,-20.57306],"type":"Point"}
}