{
  "type": "Feature",
  "properties": {
    "gn:admin1_code":"9.0",
    "gn:asciiname":"Latifo",
    "gn:country_code":"MZ",
    "gn:dem":44,
    "gn:feature_class":"P",
    "gn:feature_code":"PPL",
    "gn:name":"Latifo",
    "gn:population":0,
    "gn:timezone":"Africa/Maputo",
    "iso:country":"MZ",
    "wof:name":"Latifo",
    "wof:placetype":"locality"
},
  "geometry": {"coordinates":[38.48972,-16.92194],"type":"Point"}
}