{
  "type": "Feature",
  "properties": {
    "gn:admin1_code":"3",
    "gn:asciiname":"Massetela",
    "gn:country_code":"MZ",
    "gn:dem":117,
    "gn:feature_class":"P",
    "gn:feature_code":"PPL",
    "gn:name":"Massetela",
    "gn:population":0,
    "gn:timezone":"Africa/Maputo",
    "iso:country":"MZ",
    "wof:name":"Massetela",
    "wof:placetype":"locality"
},
  "geometry": {"coordinates":[35.39444,-23.36611],"type":"Point"}
}