{
  "type": "Feature",
  "properties": {
    "gn:admin1_code":"5",
    "gn:asciiname":"Laisse",
    "gn:country_code":"MZ",
    "gn:dem":50,
    "gn:feature_class":"P",
    "gn:feature_code":"PPL",
    "gn:name":"Laisse",
    "gn:population":0,
    "gn:timezone":"Africa/Maputo",
    "iso:country":"MZ",
    "name:ita_x_preferred":[
        "Lassa"
    ],
    "name:pol_x_preferred":[
        "Laisse"
    ],
    "name:rus_x_preferred":[
        "\u041b\u0435\u0441\u0441\u0430"
    ],
    "name:spa_x_preferred":[
        "Laisse"
    ],
    "wof:name":"Laisse",
    "wof:placetype":"locality"
},
  "geometry": {"coordinates":[34.19694,-21.26472],"type":"Point"}
}