{
  "type": "Feature",
  "properties": {
    "gn:admin1_code":"7",
    "gn:asciiname":"Netilo",
    "gn:country_code":"MZ",
    "gn:dem":830,
    "gn:feature_class":"P",
    "gn:feature_code":"PPL",
    "gn:name":"Netilo",
    "gn:population":0,
    "gn:timezone":"Africa/Maputo",
    "iso:country":"MZ",
    "wof:name":"Netilo",
    "wof:placetype":"locality"
},
  "geometry": {"coordinates":[35.82583,-13.22778],"type":"Point"}
}