{
  "type": "Feature",
  "properties": {
    "gn:admin1_code":"7",
    "gn:asciiname":"Chefe Mepemba",
    "gn:country_code":"MZ",
    "gn:dem":669,
    "gn:feature_class":"P",
    "gn:feature_code":"PPL",
    "gn:name":"Chefe Mepemba",
    "gn:population":0,
    "gn:timezone":"Africa/Maputo",
    "iso:country":"MZ",
    "wof:name":"Chefe Mepemba",
    "wof:placetype":"locality"
},
  "geometry": {"coordinates":[35.975,-15.31139],"type":"Point"}
}