{
  "type": "Feature",
  "properties": {
    "gn:admin1_code":"0",
    "gn:asciiname":"Munhangana",
    "gn:country_code":"MZ",
    "gn:dem":79,
    "gn:feature_class":"P",
    "gn:feature_code":"PPL",
    "gn:name":"Munhangana",
    "gn:population":0,
    "gn:timezone":"Africa/Maputo",
    "iso:country":"MZ",
    "wof:name":"Munhangana",
    "wof:placetype":"locality"
},
  "geometry": {"coordinates":[32.25,-25.53333],"type":"Point"}
}