{
  "type": "Feature",
  "properties": {
    "gn:admin1_code":"9",
    "gn:asciiname":"Namerrogolo",
    "gn:country_code":"MZ",
    "gn:dem":176,
    "gn:feature_class":"P",
    "gn:feature_code":"PPL",
    "gn:name":"Namerrogolo",
    "gn:population":0,
    "gn:timezone":"Africa/Maputo",
    "iso:country":"MZ",
    "wof:name":"Namerrogolo",
    "wof:placetype":"locality"
},
  "geometry": {"coordinates":[37.04944,-16.73222],"type":"Point"}
}