{
  "type": "Feature",
  "properties": {
    "gn:admin1_code":"3",
    "gn:asciiname":"Barrana",
    "gn:country_code":"MZ",
    "gn:dem":98,
    "gn:feature_class":"P",
    "gn:feature_code":"PPL",
    "gn:name":"Barrana",
    "gn:population":0,
    "gn:timezone":"Africa/Maputo",
    "iso:country":"MZ",
    "wof:name":"Barrana",
    "wof:placetype":"locality"
},
  "geometry": {"coordinates":[35.165,-23.28667],"type":"Point"}
}