{
  "type": "Feature",
  "properties": {
    "gn:admin1_code":"4",
    "gn:asciiname":"Gatou",
    "gn:country_code":"MZ",
    "gn:dem":59,
    "gn:feature_class":"P",
    "gn:feature_code":"PPL",
    "gn:name":"G\u00e0tou",
    "gn:population":0,
    "gn:timezone":"Africa/Maputo",
    "iso:country":"MZ",
    "wof:name":"Gatou",
    "wof:placetype":"locality"
},
  "geometry": {"coordinates":[32.27917,-25.32722],"type":"Point"}
}