{
  "type": "Feature",
  "properties": {
    "gn:admin1_code":"4",
    "gn:asciiname":"Chefe Massaca",
    "gn:country_code":"MZ",
    "gn:dem":20,
    "gn:feature_class":"P",
    "gn:feature_code":"PPL",
    "gn:name":"Chefe Massaca",
    "gn:population":0,
    "gn:timezone":"Africa/Maputo",
    "iso:country":"MZ",
    "wof:name":"Chefe Massaca",
    "wof:placetype":"locality"
},
  "geometry": {"coordinates":[32.29167,-26.04333],"type":"Point"}
}