{
  "type": "Feature",
  "properties": {
    "gn:admin1_code":"4",
    "gn:asciiname":"Chioque",
    "gn:country_code":"MZ",
    "gn:dem":53,
    "gn:feature_class":"P",
    "gn:feature_code":"PPL",
    "gn:name":"Chioque",
    "gn:population":0,
    "gn:timezone":"Africa/Maputo",
    "iso:country":"MZ",
    "wof:name":"Chioque",
    "wof:placetype":"locality"
},
  "geometry": {"coordinates":[32.54694,-24.99056],"type":"Point"}
}