{
  "type": "Feature",
  "properties": {
    "gn:admin1_code":"6",
    "gn:asciiname":"Joaquim",
    "gn:country_code":"MZ",
    "gn:dem":138,
    "gn:feature_class":"P",
    "gn:feature_code":"PPL",
    "gn:name":"Joaquim",
    "gn:population":0,
    "gn:timezone":"Africa/Maputo",
    "iso:country":"MZ",
    "name:bre_x_preferred":[
        "Joaquim"
    ],
    "name:cat_x_preferred":[
        "Joaquim"
    ],
    "name:rus_x_preferred":[
        "\u0416\u0443\u0430\u043a\u0438\u043d"
    ],
    "wof:name":"Joaquim",
    "wof:placetype":"locality"
},
  "geometry": {"coordinates":[39.46806,-15.90889],"type":"Point"}
}