{
  "type": "Feature",
  "properties": {
    "gn:admin1_code":"6",
    "gn:asciiname":"Joaquim",
    "gn:country_code":"MZ",
    "gn:dem":138,
    "gn:feature_class":"P",
    "gn:feature_code":"PPL",
    "gn:name":"Joaquim",
    "gn:population":0,
    "gn:timezone":"Africa/Maputo",
    "iso:country":"MZ",
    "wof:name":"Joaquim",
    "wof:placetype":"locality"
},
  "geometry": {"coordinates":[39.46806,-15.90889],"type":"Point"}
}