{
  "type": "Feature",
  "properties": {
    "gn:admin1_code":"4",
    "gn:asciiname":"Aldeia Comunais Mingonzo",
    "gn:cc2":"MZ",
    "gn:country_code":"MZ",
    "gn:dem":200,
    "gn:feature_class":"P",
    "gn:feature_code":"PPL",
    "gn:name":"Aldeia Comunais Mingonzo",
    "gn:population":0,
    "gn:timezone":"Africa/Maputo",
    "iso:country":"MZ",
    "name:und_x_variant":[
        "Mangondzo",
        "Mangonzo",
        "Aldeia Comunais Mingonzo"
    ],
    "wof:name":"Aldeia Comunais Mingonzo",
    "wof:placetype":"locality"
},
  "geometry": {"coordinates":[32.20139,-24.23694],"type":"Point"}
}