{
  "type": "Feature",
  "properties": {
    "gn:admin1_code":"9.0",
    "gn:asciiname":"Chefe Mulimia",
    "gn:country_code":"MZ",
    "gn:dem":373,
    "gn:feature_class":"P",
    "gn:feature_code":"PPL",
    "gn:name":"Chefe Mulimia",
    "gn:population":0,
    "gn:timezone":"Africa/Maputo",
    "iso:country":"MZ",
    "wof:name":"Chefe Mulimia",
    "wof:placetype":"locality"
},
  "geometry": {"coordinates":[37.14028,-16.24944],"type":"Point"}
}