{
  "type": "Feature",
  "properties": {
    "gn:admin1_code":"1.0",
    "gn:asciiname":"Quissanga",
    "gn:country_code":"MZ",
    "gn:dem":28,
    "gn:feature_class":"P",
    "gn:feature_code":"PPL",
    "gn:name":"Quissanga",
    "gn:population":0,
    "gn:timezone":"Africa/Maputo",
    "iso:country":"MZ",
    "name:ceb_x_preferred":[
        "Quissanga"
    ],
    "name:swe_x_preferred":[
        "Quissanga"
    ],
    "wof:name":"Quissanga",
    "wof:placetype":"locality"
},
  "geometry": {"coordinates":[40.4875,-12.43306],"type":"Point"}
}