{
  "type": "Feature",
  "properties": {
    "gn:admin1_code":"2.0",
    "gn:asciiname":"Simao Nhantumbo",
    "gn:country_code":"MZ",
    "gn:dem":36,
    "gn:feature_class":"P",
    "gn:feature_code":"PPL",
    "gn:name":"Sim\u00e3o Nhantumbo",
    "gn:population":0,
    "gn:timezone":"Africa/Maputo",
    "iso:country":"MZ",
    "wof:name":"Simao Nhantumbo",
    "wof:placetype":"locality"
},
  "geometry": {"coordinates":[34.25360999999999,-24.745],"type":"Point"}
}