{
  "type": "Feature",
  "properties": {
    "gn:admin1_code":"4",
    "gn:asciiname":"Nassone",
    "gn:country_code":"MZ",
    "gn:dem":163,
    "gn:feature_class":"P",
    "gn:feature_code":"PPL",
    "gn:name":"Nassone",
    "gn:population":0,
    "gn:timezone":"Africa/Maputo",
    "iso:country":"MZ",
    "wof:name":"Nassone",
    "wof:placetype":"locality"
},
  "geometry": {"coordinates":[32.27833,-24.42778],"type":"Point"}
}