{
  "type": "Feature",
  "properties": {
    "gn:admin1_code":"6",
    "gn:asciiname":"Neruculo",
    "gn:country_code":"MZ",
    "gn:dem":649,
    "gn:feature_class":"P",
    "gn:feature_code":"PPL",
    "gn:name":"N\u00e9ruc\u00falo",
    "gn:population":0,
    "gn:timezone":"Africa/Maputo",
    "iso:country":"MZ",
    "wof:name":"Neruculo",
    "wof:placetype":"locality"
},
  "geometry": {"coordinates":[37.29056,-14.78528],"type":"Point"}
}