{
  "type": "Feature",
  "properties": {
    "gn:admin1_code":"3.0",
    "gn:asciiname":"D. Diegues",
    "gn:country_code":"MZ",
    "gn:dem":69,
    "gn:feature_class":"P",
    "gn:feature_code":"PPL",
    "gn:name":"D. Diegues",
    "gn:population":0,
    "gn:timezone":"Africa/Maputo",
    "iso:country":"MZ",
    "wof:name":"D. Diegues",
    "wof:placetype":"locality"
},
  "geometry": {"coordinates":[35.42805999999999,-23.34611],"type":"Point"}
}