{
  "type": "Feature",
  "properties": {
    "gn:admin1_code":"1",
    "gn:asciiname":"Chefe Ingori",
    "gn:country_code":"MZ",
    "gn:dem":224,
    "gn:feature_class":"P",
    "gn:feature_code":"PPL",
    "gn:name":"Chefe Ingori",
    "gn:population":0,
    "gn:timezone":"Africa/Maputo",
    "iso:country":"MZ",
    "wof:name":"Chefe Ingori",
    "wof:placetype":"locality"
},
  "geometry": {"coordinates":[40.22639,-13.14417],"type":"Point"}
}