{
  "type": "Feature",
  "properties": {
    "gn:admin1_code":"6",
    "gn:asciiname":"Moia",
    "gn:country_code":"MZ",
    "gn:dem":74,
    "gn:feature_class":"P",
    "gn:feature_code":"PPL",
    "gn:name":"Mo\u00eda",
    "gn:population":0,
    "gn:timezone":"Africa/Maputo",
    "iso:country":"MZ",
    "wof:name":"Moia",
    "wof:placetype":"locality"
},
  "geometry": {"coordinates":[40.38167,-15.17917],"type":"Point"}
}