{
  "type": "Feature",
  "properties": {
    "gn:admin1_code":"7.0",
    "gn:asciiname":"Tuma",
    "gn:country_code":"MZ",
    "gn:dem":719,
    "gn:feature_class":"P",
    "gn:feature_code":"PPL",
    "gn:name":"Tuma",
    "gn:population":0,
    "gn:timezone":"Africa/Maputo",
    "iso:country":"MZ",
    "name:ceb_x_preferred":[
        "Tuma"
    ],
    "name:deu_x_preferred":[
        "Tuma"
    ],
    "name:fra_x_preferred":[
        "Tuma"
    ],
    "name:ita_x_preferred":[
        "Tuma"
    ],
    "name:rus_x_preferred":[
        "\u0422\u0443\u043c\u0430"
    ],
    "name:slk_x_preferred":[
        "Tuma"
    ],
    "name:spa_x_preferred":[
        "Tuma"
    ],
    "name:swe_x_preferred":[
        "Tuma"
    ],
    "wof:name":"Tuma",
    "wof:placetype":"locality"
},
  "geometry": {"coordinates":[35.6225,-12.02806],"type":"Point"}
}