{
  "type": "Feature",
  "properties": {
    "gn:admin1_code":"8",
    "gn:asciiname":"Cinturao",
    "gn:country_code":"MZ",
    "gn:dem":1112,
    "gn:feature_class":"P",
    "gn:feature_code":"PPL",
    "gn:name":"Cintur\u00e3o",
    "gn:population":0,
    "gn:timezone":"Africa/Maputo",
    "iso:country":"MZ",
    "wof:name":"Cinturao",
    "wof:placetype":"locality"
},
  "geometry": {"coordinates":[34.01472,-14.65278],"type":"Point"}
}