{
  "type": "Feature",
  "properties": {
    "gn:admin1_code":"8",
    "gn:asciiname":"Gimo",
    "gn:country_code":"MZ",
    "gn:dem":547,
    "gn:feature_class":"P",
    "gn:feature_code":"PPL",
    "gn:name":"Gimo",
    "gn:population":0,
    "gn:timezone":"Africa/Maputo",
    "iso:country":"MZ",
    "name:ita_x_preferred":[
        "Gimo"
    ],
    "name:por_x_preferred":[
        "Gimo"
    ],
    "wof:name":"Gimo",
    "wof:placetype":"locality"
},
  "geometry": {"coordinates":[32.05457,-16.36775],"type":"Point"}
}