{
  "type": "Feature",
  "properties": {
    "gn:admin1_code":"6",
    "gn:asciiname":"Nassequia",
    "gn:country_code":"MZ",
    "gn:dem":303,
    "gn:feature_class":"P",
    "gn:feature_code":"PPL",
    "gn:name":"Nassequia",
    "gn:population":0,
    "gn:timezone":"Africa/Maputo",
    "iso:country":"MZ",
    "wof:name":"Nassequia",
    "wof:placetype":"locality"
},
  "geometry": {"coordinates":[39.58472,-13.85806],"type":"Point"}
}