{
  "type": "Feature",
  "properties": {
    "gn:admin1_code":"5",
    "gn:asciiname":"Mabeleza",
    "gn:country_code":"MZ",
    "gn:dem":190,
    "gn:feature_class":"P",
    "gn:feature_code":"PPL",
    "gn:name":"Mabeleza",
    "gn:population":0,
    "gn:timezone":"Africa/Maputo",
    "iso:country":"MZ",
    "wof:name":"Mabeleza",
    "wof:placetype":"locality"
},
  "geometry": {"coordinates":[33.76611,-20.65083],"type":"Point"}
}