{
  "type": "Feature",
  "properties": {
    "gn:admin1_code":"9",
    "gn:asciiname":"Colico",
    "gn:cc2":"MZ",
    "gn:country_code":"MZ",
    "gn:dem":471,
    "gn:feature_class":"P",
    "gn:feature_code":"PPL",
    "gn:name":"Colico",
    "gn:population":0,
    "gn:timezone":"Africa/Maputo",
    "iso:country":"MZ",
    "name:und_x_variant":[
        "Colioo",
        "Colico"
    ],
    "wof:name":"Colico",
    "wof:placetype":"locality"
},
  "geometry": {"coordinates":[35.81861,-16.42861],"type":"Point"}
}