{
  "type": "Feature",
  "properties": {
    "gn:admin1_code":"9",
    "gn:asciiname":"Colico",
    "gn:cc2":"MZ",
    "gn:country_code":"MZ",
    "gn:dem":471,
    "gn:feature_class":"P",
    "gn:feature_code":"PPL",
    "gn:name":"Colico",
    "gn:population":0,
    "gn:timezone":"Africa/Maputo",
    "iso:country":"MZ",
    "name:azb_x_preferred":[
        "\u06a9\u0648\u0644\u06cc\u06a9\u0648"
    ],
    "name:bul_x_preferred":[
        "\u041a\u043e\u043b\u0438\u043a\u043e"
    ],
    "name:cat_x_preferred":[
        "Colico"
    ],
    "name:ceb_x_preferred":[
        "Colico"
    ],
    "name:deu_x_preferred":[
        "Colico"
    ],
    "name:epo_x_preferred":[
        "Colico"
    ],
    "name:eus_x_preferred":[
        "Colico"
    ],
    "name:fas_x_preferred":[
        "\u06a9\u0648\u0644\u06cc\u06a9\u0648"
    ],
    "name:fra_x_preferred":[
        "Colico"
    ],
    "name:hun_x_preferred":[
        "Colico"
    ],
    "name:hye_x_preferred":[
        "\u053f\u0578\u056c\u056b\u056f\u0578"
    ],
    "name:ita_x_preferred":[
        "Colico"
    ],
    "name:jpn_x_preferred":[
        "\u30b3\u30fc\u30ea\u30b3"
    ],
    "name:kaz_x_preferred":[
        "\u041a\u043e\u043b\u0438\u043a\u043e"
    ],
    "name:lat_x_preferred":[
        "Colicum"
    ],
    "name:lmo_x_preferred":[
        "C\u00f2legh"
    ],
    "name:msa_x_preferred":[
        "Colico"
    ],
    "name:nap_x_preferred":[
        "Colico"
    ],
    "name:nld_x_preferred":[
        "Colico"
    ],
    "name:pms_x_preferred":[
        "Colico"
    ],
    "name:pol_x_preferred":[
        "Colico"
    ],
    "name:por_x_preferred":[
        "Colico"
    ],
    "name:roh_x_preferred":[
        "Colico"
    ],
    "name:ron_x_preferred":[
        "Colico"
    ],
    "name:rus_x_preferred":[
        "\u041a\u043e\u043b\u0438\u043a\u043e"
    ],
    "name:scn_x_preferred":[
        "Colico"
    ],
    "name:spa_x_preferred":[
        "C\u00f3lico"
    ],
    "name:srp_x_preferred":[
        "\u041a\u043e\u043b\u0438\u043a\u043e"
    ],
    "name:tgl_x_preferred":[
        "Colico"
    ],
    "name:ukr_x_preferred":[
        "\u041a\u043e\u043b\u0456\u043a\u043e"
    ],
    "name:und_x_variant":[
        "Colioo"
    ],
    "name:uzb_x_preferred":[
        "Colico"
    ],
    "name:vie_x_preferred":[
        "Colico"
    ],
    "name:vol_x_preferred":[
        "Colico"
    ],
    "name:war_x_preferred":[
        "Colico"
    ],
    "name:zho_x_preferred":[
        "\u79d1\u5229\u79d1"
    ],
    "wof:name":"Colico",
    "wof:placetype":"locality"
},
  "geometry": {"coordinates":[35.81861,-16.42861],"type":"Point"}
}