{
  "type": "Feature",
  "properties": {
    "gn:admin1_code":"2",
    "gn:asciiname":"Magulane",
    "gn:country_code":"MZ",
    "gn:dem":65,
    "gn:feature_class":"P",
    "gn:feature_code":"PPL",
    "gn:name":"Magulane",
    "gn:population":0,
    "gn:timezone":"Africa/Maputo",
    "iso:country":"MZ",
    "wof:name":"Magulane",
    "wof:placetype":"locality"
},
  "geometry": {"coordinates":[33.66194,-23.23472000000001],"type":"Point"}
}