{
  "type": "Feature",
  "properties": {
    "gn:admin1_code":"3.0",
    "gn:asciiname":"Bento",
    "gn:country_code":"MZ",
    "gn:dem":50,
    "gn:feature_class":"P",
    "gn:feature_code":"PPL",
    "gn:name":"Bento",
    "gn:population":0,
    "gn:timezone":"Africa/Maputo",
    "iso:country":"MZ",
    "name:ara_x_preferred":[
        "\u0628\u0646\u062a\u0648"
    ],
    "name:aze_x_preferred":[
        "Bento"
    ],
    "name:bre_x_preferred":[
        "Bent\u014d"
    ],
    "name:ces_x_preferred":[
        "Bent\u00f3"
    ],
    "name:dan_x_preferred":[
        "Bento"
    ],
    "name:deu_x_preferred":[
        "Bent\u014d"
    ],
    "name:epo_x_preferred":[
        "Portlun\u0109o"
    ],
    "name:fas_x_preferred":[
        "\u0628\u0646\u062a\u0648"
    ],
    "name:fin_x_preferred":[
        "Bent\u014d"
    ],
    "name:fra_x_preferred":[
        "Bent\u014d"
    ],
    "name:hak_x_preferred":[
        "Phien-t\u00f4ng"
    ],
    "name:heb_x_preferred":[
        "\u05d1\u05e0\u05d8\u05d5"
    ],
    "name:hun_x_preferred":[
        "Bent\u00f3"
    ],
    "name:ina_x_preferred":[
        "Bento"
    ],
    "name:ind_x_preferred":[
        "Bent\u014d"
    ],
    "name:ita_x_preferred":[
        "Bent\u014d"
    ],
    "name:kir_x_preferred":[
        "\u0411\u044d\u043d\u0442\u043e"
    ],
    "name:mar_x_preferred":[
        "\u092c\u0947\u0928\u094d\u0924\u094b"
    ],
    "name:msa_x_preferred":[
        "Bent\u014d"
    ],
    "name:nld_x_preferred":[
        "Bent\u014d"
    ],
    "name:nor_x_preferred":[
        "Bento"
    ],
    "name:pol_x_preferred":[
        "Bent\u014d"
    ],
    "name:por_x_preferred":[
        "Bent\u014d"
    ],
    "name:ron_x_preferred":[
        "Bent\u014d"
    ],
    "name:rus_x_preferred":[
        "\u0411\u044d\u043d\u0442\u043e"
    ],
    "name:slk_x_preferred":[
        "Bent\u00f3"
    ],
    "name:spa_x_preferred":[
        "Bent\u014d"
    ],
    "name:swe_x_preferred":[
        "Bento"
    ],
    "name:tha_x_preferred":[
        "\u0e40\u0e1a\u0e47\u0e19\u0e42\u0e15"
    ],
    "name:tur_x_preferred":[
        "Bent\u014d"
    ],
    "name:ukr_x_preferred":[
        "\u0411\u0435\u043d\u0442\u043e"
    ],
    "name:vie_x_preferred":[
        "Bent\u014d"
    ],
    "wof:name":"Bento",
    "wof:placetype":"locality"
},
  "geometry": {"coordinates":[35.48694000000001,-22.76556],"type":"Point"}
}