{
  "type": "Feature",
  "properties": {
    "gn:admin1_code":"3.0",
    "gn:asciiname":"Bento",
    "gn:country_code":"MZ",
    "gn:dem":50,
    "gn:feature_class":"P",
    "gn:feature_code":"PPL",
    "gn:name":"Bento",
    "gn:population":0,
    "gn:timezone":"Africa/Maputo",
    "iso:country":"MZ",
    "wof:name":"Bento",
    "wof:placetype":"locality"
},
  "geometry": {"coordinates":[35.48694000000001,-22.76556],"type":"Point"}
}