{
  "type": "Feature",
  "properties": {
    "gn:admin1_code":"3",
    "gn:asciiname":"Niquice",
    "gn:country_code":"MZ",
    "gn:dem":115,
    "gn:feature_class":"P",
    "gn:feature_code":"PPL",
    "gn:name":"Niquice",
    "gn:population":0,
    "gn:timezone":"Africa/Maputo",
    "iso:country":"MZ",
    "wof:name":"Niquice",
    "wof:placetype":"locality"
},
  "geometry": {"coordinates":[35.43583,-23.39889],"type":"Point"}
}