{
  "type": "Feature",
  "properties": {
    "gn:admin1_code":"9",
    "gn:asciiname":"Nantala",
    "gn:country_code":"MZ",
    "gn:dem":506,
    "gn:feature_class":"P",
    "gn:feature_code":"PPL",
    "gn:name":"Nantala",
    "gn:population":0,
    "gn:timezone":"Africa/Maputo",
    "iso:country":"MZ",
    "wof:name":"Nantala",
    "wof:placetype":"locality"
},
  "geometry": {"coordinates":[37.86722,-15.62917],"type":"Point"}
}