{
  "type": "Feature",
  "properties": {
    "gn:admin1_code":"1",
    "gn:asciiname":"Massomue",
    "gn:country_code":"MZ",
    "gn:dem":170,
    "gn:feature_class":"P",
    "gn:feature_code":"PPL",
    "gn:name":"Massomue",
    "gn:population":0,
    "gn:timezone":"Africa/Maputo",
    "iso:country":"MZ",
    "wof:name":"Massomue",
    "wof:placetype":"locality"
},
  "geometry": {"coordinates":[39.67611,-12.00583],"type":"Point"}
}