{
  "type": "Feature",
  "properties": {
    "gn:admin1_code":"7",
    "gn:asciiname":"Nambingo",
    "gn:country_code":"MZ",
    "gn:dem":161,
    "gn:feature_class":"P",
    "gn:feature_code":"PPL",
    "gn:name":"Nambingo",
    "gn:population":0,
    "gn:timezone":"Africa/Maputo",
    "iso:country":"MZ",
    "wof:name":"Nambingo",
    "wof:placetype":"locality"
},
  "geometry": {"coordinates":[38.41778,-11.52861],"type":"Point"}
}