{
  "type": "Feature",
  "properties": {
    "gn:admin1_code":"5",
    "gn:asciiname":"Alface",
    "gn:country_code":"MZ",
    "gn:dem":21,
    "gn:feature_class":"P",
    "gn:feature_code":"PPL",
    "gn:name":"Alface",
    "gn:population":0,
    "gn:timezone":"Africa/Maputo",
    "iso:country":"MZ",
    "wof:name":"Alface",
    "wof:placetype":"locality"
},
  "geometry": {"coordinates":[34.95,-19.63333],"type":"Point"}
}