{
  "type": "Feature",
  "properties": {
    "gn:admin1_code":"6",
    "gn:asciiname":"Moreira",
    "gn:country_code":"MZ",
    "gn:dem":134,
    "gn:feature_class":"P",
    "gn:feature_code":"PPL",
    "gn:name":"Moreira",
    "gn:population":0,
    "gn:timezone":"Africa/Maputo",
    "iso:country":"MZ",
    "name:ceb_x_preferred":[
        "Moreira"
    ],
    "name:ces_x_preferred":[
        "Moreira"
    ],
    "name:deu_x_preferred":[
        "Moreira"
    ],
    "name:fin_x_preferred":[
        "Moreira"
    ],
    "name:fra_x_preferred":[
        "Moreira"
    ],
    "name:glg_x_preferred":[
        "Moreira"
    ],
    "name:ita_x_preferred":[
        "Moreira"
    ],
    "name:lav_x_preferred":[
        "Moreira"
    ],
    "name:nld_x_preferred":[
        "Moreira"
    ],
    "name:pol_x_preferred":[
        "Moreira"
    ],
    "name:por_x_preferred":[
        "Moreira"
    ],
    "name:rus_x_preferred":[
        "\u041c\u043e\u0440\u0435\u0439\u0440\u0430"
    ],
    "name:swe_x_preferred":[
        "Moreira"
    ],
    "name:ukr_x_preferred":[
        "\u041c\u043e\u0440\u0435\u0439\u0440\u0430"
    ],
    "wof:name":"Moreira",
    "wof:placetype":"locality"
},
  "geometry": {"coordinates":[40.28583,-14.41889],"type":"Point"}
}