{
  "type": "Feature",
  "properties": {
    "gn:admin1_code":"6",
    "gn:asciiname":"Moreira",
    "gn:country_code":"MZ",
    "gn:dem":134,
    "gn:feature_class":"P",
    "gn:feature_code":"PPL",
    "gn:name":"Moreira",
    "gn:population":0,
    "gn:timezone":"Africa/Maputo",
    "iso:country":"MZ",
    "wof:name":"Moreira",
    "wof:placetype":"locality"
},
  "geometry": {"coordinates":[40.28583,-14.41889],"type":"Point"}
}