{
  "type": "Feature",
  "properties": {
    "gn:admin1_code":"3",
    "gn:asciiname":"Cabo Fequete",
    "gn:cc2":"MZ",
    "gn:country_code":"MZ",
    "gn:dem":42,
    "gn:feature_class":"P",
    "gn:feature_code":"PPL",
    "gn:name":"Cabo Fequete",
    "gn:population":0,
    "gn:timezone":"Africa/Maputo",
    "iso:country":"MZ",
    "name:und_x_variant":[
        "Fran\u00e7a",
        "Cabo Fequete"
    ],
    "wof:name":"Cabo Fequete",
    "wof:placetype":"locality"
},
  "geometry": {"coordinates":[35.22027999999999,-22.0275],"type":"Point"}
}