{
  "type": "Feature",
  "properties": {
    "gn:admin1_code":"2.0",
    "gn:asciiname":"Regulo Bique",
    "gn:country_code":"MZ",
    "gn:dem":34,
    "gn:feature_class":"P",
    "gn:feature_code":"PPL",
    "gn:name":"R\u00e9gulo Bique",
    "gn:population":0,
    "gn:timezone":"Africa/Maputo",
    "iso:country":"MZ",
    "wof:name":"Regulo Bique",
    "wof:placetype":"locality"
},
  "geometry": {"coordinates":[33.01278,-24.44139],"type":"Point"}
}