{
  "type": "Feature",
  "properties": {
    "gn:admin1_code":"1",
    "gn:asciiname":"Cavinga",
    "gn:country_code":"MZ",
    "gn:dem":130,
    "gn:feature_class":"P",
    "gn:feature_code":"PPL",
    "gn:name":"Cavinga",
    "gn:population":0,
    "gn:timezone":"Africa/Maputo",
    "iso:country":"MZ",
    "wof:name":"Cavinga",
    "wof:placetype":"locality"
},
  "geometry": {"coordinates":[39.92,-11.62944],"type":"Point"}
}