{
  "type": "Feature",
  "properties": {
    "gn:admin1_code":"6",
    "gn:asciiname":"Cabo Rila",
    "gn:country_code":"MZ",
    "gn:dem":287,
    "gn:feature_class":"P",
    "gn:feature_code":"PPL",
    "gn:name":"Cabo Rila",
    "gn:population":0,
    "gn:timezone":"Africa/Maputo",
    "iso:country":"MZ",
    "wof:name":"Cabo Rila",
    "wof:placetype":"locality"
},
  "geometry": {"coordinates":[39.99528,-14.47167],"type":"Point"}
}