{
  "type": "Feature",
  "properties": {
    "gn:admin1_code":"5",
    "gn:asciiname":"Cherinfume",
    "gn:country_code":"MZ",
    "gn:dem":86,
    "gn:feature_class":"P",
    "gn:feature_code":"PPL",
    "gn:name":"Cherinfume",
    "gn:population":0,
    "gn:timezone":"Africa/Maputo",
    "iso:country":"MZ",
    "wof:name":"Cherinfume",
    "wof:placetype":"locality"
},
  "geometry": {"coordinates":[34.21889,-18.85139],"type":"Point"}
}