{
  "type": "Feature",
  "properties": {
    "gn:admin1_code":"9.0",
    "gn:asciiname":"Marreca",
    "gn:country_code":"MZ",
    "gn:dem":334,
    "gn:feature_class":"P",
    "gn:feature_code":"PPL",
    "gn:name":"Marreca",
    "gn:population":0,
    "gn:timezone":"Africa/Maputo",
    "iso:country":"MZ",
    "wof:name":"Marreca",
    "wof:placetype":"locality"
},
  "geometry": {"coordinates":[37.6525,-16.24778],"type":"Point"}
}