{
  "type": "Feature",
  "properties": {
    "gn:admin1_code":"3",
    "gn:asciiname":"Inguani",
    "gn:country_code":"MZ",
    "gn:dem":129,
    "gn:feature_class":"P",
    "gn:feature_code":"PPL",
    "gn:name":"Inguani",
    "gn:population":0,
    "gn:timezone":"Africa/Maputo",
    "iso:country":"MZ",
    "wof:name":"Inguani",
    "wof:placetype":"locality"
},
  "geometry": {"coordinates":[35.15861,-23.73194],"type":"Point"}
}