{
  "type": "Feature",
  "properties": {
    "gn:admin1_code":"3",
    "gn:asciiname":"Chapo",
    "gn:country_code":"MZ",
    "gn:dem":110,
    "gn:feature_class":"P",
    "gn:feature_code":"PPL",
    "gn:name":"Chapo",
    "gn:population":0,
    "gn:timezone":"Africa/Maputo",
    "iso:country":"MZ",
    "name:ceb_x_preferred":[
        "El Chapo"
    ],
    "name:deu_x_preferred":[
        "El Chapo"
    ],
    "name:fra_x_preferred":[
        "Chapo"
    ],
    "name:ita_x_preferred":[
        "El Chapo"
    ],
    "name:nld_x_preferred":[
        "Chapo"
    ],
    "name:sco_x_preferred":[
        "El Chapo"
    ],
    "name:spa_x_preferred":[
        "Chapo"
    ],
    "name:swe_x_preferred":[
        "El Chapo"
    ],
    "wof:name":"Chapo",
    "wof:placetype":"locality"
},
  "geometry": {"coordinates":[34.74778,-21.84833],"type":"Point"}
}