{
  "type": "Feature",
  "properties": {
    "gn:admin1_code":"10",
    "gn:asciiname":"Naveneque",
    "gn:country_code":"MZ",
    "gn:dem":178,
    "gn:feature_class":"P",
    "gn:feature_code":"PPL",
    "gn:name":"Naveneque",
    "gn:population":0,
    "gn:timezone":"Africa/Maputo",
    "iso:country":"MZ",
    "wof:name":"Naveneque",
    "wof:placetype":"locality"
},
  "geometry": {"coordinates":[33.3575,-19.91583],"type":"Point"}
}