{
  "type": "Feature",
  "properties": {
    "gn:admin1_code":"6",
    "gn:asciiname":"Chiirre",
    "gn:country_code":"MZ",
    "gn:dem":168,
    "gn:feature_class":"P",
    "gn:feature_code":"PPL",
    "gn:name":"Chiirre",
    "gn:population":0,
    "gn:timezone":"Africa/Maputo",
    "iso:country":"MZ",
    "wof:name":"Chiirre",
    "wof:placetype":"locality"
},
  "geometry": {"coordinates":[40.16083,-14.91361],"type":"Point"}
}