{
  "type": "Feature",
  "properties": {
    "gn:admin1_code":"2",
    "gn:asciiname":"Chiconge",
    "gn:country_code":"MZ",
    "gn:dem":62,
    "gn:feature_class":"P",
    "gn:feature_code":"PPL",
    "gn:name":"Chiconge",
    "gn:population":0,
    "gn:timezone":"Africa/Maputo",
    "iso:country":"MZ",
    "wof:name":"Chiconge",
    "wof:placetype":"locality"
},
  "geometry": {"coordinates":[33.0075,-23.97778],"type":"Point"}
}