{
  "type": "Feature",
  "properties": {
    "gn:admin1_code":"7",
    "gn:asciiname":"Mtacurro",
    "gn:country_code":"MZ",
    "gn:dem":422,
    "gn:feature_class":"P",
    "gn:feature_code":"PPL",
    "gn:name":"Mtacurro",
    "gn:population":0,
    "gn:timezone":"Africa/Maputo",
    "iso:country":"MZ",
    "wof:name":"Mtacurro",
    "wof:placetype":"locality"
},
  "geometry": {"coordinates":[38.02806,-14.11972],"type":"Point"}
}