{
  "type": "Feature",
  "properties": {
    "gn:admin1_code":"9",
    "gn:asciiname":"Mateus",
    "gn:country_code":"MZ",
    "gn:dem":267,
    "gn:feature_class":"P",
    "gn:feature_code":"PPL",
    "gn:name":"Mateus",
    "gn:population":0,
    "gn:timezone":"Africa/Maputo",
    "iso:country":"MZ",
    "wof:name":"Mateus",
    "wof:placetype":"locality"
},
  "geometry": {"coordinates":[36.59667,-16.86667000000001],"type":"Point"}
}