{
  "type": "Feature",
  "properties": {
    "gn:admin1_code":"1",
    "gn:asciiname":"Nampuita",
    "gn:country_code":"MZ",
    "gn:dem":503,
    "gn:feature_class":"P",
    "gn:feature_code":"PPL",
    "gn:name":"Nampuita",
    "gn:population":0,
    "gn:timezone":"Africa/Maputo",
    "iso:country":"MZ",
    "wof:name":"Nampuita",
    "wof:placetype":"locality"
},
  "geometry": {"coordinates":[38.99389,-13.17833],"type":"Point"}
}