{
  "type": "Feature",
  "properties": {
    "gn:admin1_code":"1",
    "gn:asciiname":"Namungua",
    "gn:country_code":"MZ",
    "gn:dem":109,
    "gn:feature_class":"P",
    "gn:feature_code":"PPL",
    "gn:name":"Nam\u00fangua",
    "gn:population":0,
    "gn:timezone":"Africa/Maputo",
    "iso:country":"MZ",
    "wof:name":"Namungua",
    "wof:placetype":"locality"
},
  "geometry": {"coordinates":[40.43528,-12.74306],"type":"Point"}
}