{
  "type": "Feature",
  "properties": {
    "gn:admin1_code":"4",
    "gn:asciiname":"Chinhoane",
    "gn:country_code":"MZ",
    "gn:dem":14,
    "gn:feature_class":"P",
    "gn:feature_code":"PPL",
    "gn:name":"Chinhoane",
    "gn:population":0,
    "gn:timezone":"Africa/Maputo",
    "iso:country":"MZ",
    "wof:name":"Chinhoane",
    "wof:placetype":"locality"
},
  "geometry": {"coordinates":[32.82528,-25.35944],"type":"Point"}
}