{
  "type": "Feature",
  "properties": {
    "gn:admin1_code":"9",
    "gn:asciiname":"Chefe Chuliua",
    "gn:country_code":"MZ",
    "gn:dem":702,
    "gn:feature_class":"P",
    "gn:feature_code":"PPL",
    "gn:name":"Chefe Chuliua",
    "gn:population":0,
    "gn:timezone":"Africa/Maputo",
    "iso:country":"MZ",
    "wof:name":"Chefe Chuliua",
    "wof:placetype":"locality"
},
  "geometry": {"coordinates":[36.38639000000001,-15.36111],"type":"Point"}
}