{
  "type": "Feature",
  "properties": {
    "gn:admin1_code":"6",
    "gn:asciiname":"Mualata",
    "gn:country_code":"MZ",
    "gn:dem":389,
    "gn:feature_class":"P",
    "gn:feature_code":"PPL",
    "gn:name":"Mual\u00e0ta",
    "gn:population":0,
    "gn:timezone":"Africa/Maputo",
    "iso:country":"MZ",
    "wof:name":"Mualata",
    "wof:placetype":"locality"
},
  "geometry": {"coordinates":[38.42194,-14.23222],"type":"Point"}
}