{
  "type": "Feature",
  "properties": {
    "gn:admin1_code":"7",
    "gn:asciiname":"Chefe Chitimbe",
    "gn:cc2":"MZ",
    "gn:country_code":"MZ",
    "gn:dem":659,
    "gn:feature_class":"P",
    "gn:feature_code":"PPL",
    "gn:name":"Chefe Chitimbe",
    "gn:population":0,
    "gn:timezone":"Africa/Maputo",
    "iso:country":"MZ",
    "name:und_x_variant":[
        "Chitimbe",
        "Chefe Chitimbe"
    ],
    "wof:name":"Chefe Chitimbe",
    "wof:placetype":"locality"
},
  "geometry": {"coordinates":[35.90583,-15.33889],"type":"Point"}
}