{
  "type": "Feature",
  "properties": {
    "gn:admin1_code":"9.0",
    "gn:asciiname":"Chefe Tibiua",
    "gn:cc2":"MZ",
    "gn:country_code":"MZ",
    "gn:dem":209,
    "gn:feature_class":"P",
    "gn:feature_code":"PPL",
    "gn:name":"Chefe Tibiua",
    "gn:population":0,
    "gn:timezone":"Africa/Maputo",
    "iso:country":"MZ",
    "name:und_x_variant":[
        "Tipiua",
        "Chefe Tibiua"
    ],
    "wof:name":"Chefe Tibiua",
    "wof:placetype":"locality"
},
  "geometry": {"coordinates":[37.64583,-16.49056],"type":"Point"}
}