{
  "type": "Feature",
  "properties": {
    "gn:admin1_code":"4.0",
    "gn:asciiname":"Ezequiel",
    "gn:country_code":"MZ",
    "gn:dem":150,
    "gn:feature_class":"P",
    "gn:feature_code":"PPL",
    "gn:name":"Ezequiel",
    "gn:population":0,
    "gn:timezone":"Africa/Maputo",
    "iso:country":"MZ",
    "name:deu_x_preferred":[
        "Ezechiel"
    ],
    "name:fin_x_preferred":[
        "Ezequiel"
    ],
    "name:fra_x_preferred":[
        "\u00c9z\u00e9chiel"
    ],
    "name:por_x_preferred":[
        "Ezequiel"
    ],
    "name:rus_x_preferred":[
        "\u042d\u0441\u0435\u043a\u044c\u0435\u043b\u044c"
    ],
    "name:slv_x_preferred":[
        "Ezekiel"
    ],
    "name:spa_x_preferred":[
        "Ezequiel"
    ],
    "wof:name":"Ezequiel",
    "wof:placetype":"locality"
},
  "geometry": {"coordinates":[32.12917,-24.60222000000001],"type":"Point"}
}