{
  "type": "Feature",
  "properties": {
    "gn:admin1_code":"10",
    "gn:asciiname":"Ingrije",
    "gn:country_code":"MZ",
    "gn:dem":455,
    "gn:feature_class":"P",
    "gn:feature_code":"PPL",
    "gn:name":"Ingrije",
    "gn:population":0,
    "gn:timezone":"Africa/Maputo",
    "iso:country":"MZ",
    "wof:name":"Ingrije",
    "wof:placetype":"locality"
},
  "geometry": {"coordinates":[33.26639,-19.74222],"type":"Point"}
}