{
  "type": "Feature",
  "properties": {
    "gn:admin1_code":"3",
    "gn:asciiname":"Lambo",
    "gn:country_code":"MZ",
    "gn:dem":101,
    "gn:feature_class":"P",
    "gn:feature_code":"PPL",
    "gn:name":"Lambo",
    "gn:population":0,
    "gn:timezone":"Africa/Maputo",
    "iso:country":"MZ",
    "wof:name":"Lambo",
    "wof:placetype":"locality"
},
  "geometry": {"coordinates":[34.67583,-23.61056],"type":"Point"}
}