{
  "type": "Feature",
  "properties": {
    "gn:admin1_code":"8.0",
    "gn:asciiname":"Tchindime",
    "gn:country_code":"MZ",
    "gn:dem":422,
    "gn:feature_class":"P",
    "gn:feature_code":"PPL",
    "gn:name":"Tchindime",
    "gn:population":0,
    "gn:timezone":"Africa/Maputo",
    "iso:country":"MZ",
    "wof:name":"Tchindime",
    "wof:placetype":"locality"
},
  "geometry": {"coordinates":[33.56889,-15.72056],"type":"Point"}
}