{
  "type": "Feature",
  "properties": {
    "gn:admin1_code":"2",
    "gn:asciiname":"Chivaca",
    "gn:country_code":"MZ",
    "gn:dem":167,
    "gn:feature_class":"P",
    "gn:feature_code":"PPL",
    "gn:name":"Chiva\u00e7a",
    "gn:population":0,
    "gn:timezone":"Africa/Maputo",
    "iso:country":"MZ",
    "wof:name":"Chivaca",
    "wof:placetype":"locality"
},
  "geometry": {"coordinates":[32.40833,-23.14583],"type":"Point"}
}