{
  "type": "Feature",
  "properties": {
    "gn:admin1_code":"6",
    "gn:asciiname":"Meca",
    "gn:country_code":"MZ",
    "gn:dem":484,
    "gn:feature_class":"P",
    "gn:feature_code":"PPL",
    "gn:name":"Meca",
    "gn:population":0,
    "gn:timezone":"Africa/Maputo",
    "iso:country":"MZ",
    "wof:name":"Meca",
    "wof:placetype":"locality"
},
  "geometry": {"coordinates":[38.56694,-15.37917],"type":"Point"}
}