{
  "type": "Feature",
  "properties": {
    "gn:admin1_code":"8",
    "gn:asciiname":"Estima",
    "gn:cc2":"MZ",
    "gn:country_code":"MZ",
    "gn:dem":326,
    "gn:feature_class":"P",
    "gn:feature_code":"PPL",
    "gn:name":"Estima",
    "gn:population":0,
    "gn:timezone":"Africa/Maputo",
    "iso:country":"MZ",
    "name:und_x_variant":[
        "Chissua",
        "Chitima",
        "Estima"
    ],
    "wof:name":"Estima",
    "wof:placetype":"locality"
},
  "geometry": {"coordinates":[32.77194,-15.73722],"type":"Point"}
}