{
  "type": "Feature",
  "properties": {
    "gn:admin1_code":"6",
    "gn:asciiname":"Nametelia",
    "gn:country_code":"MZ",
    "gn:dem":253,
    "gn:feature_class":"P",
    "gn:feature_code":"PPL",
    "gn:name":"Nametelia",
    "gn:population":0,
    "gn:timezone":"Africa/Maputo",
    "iso:country":"MZ",
    "wof:name":"Nametelia",
    "wof:placetype":"locality"
},
  "geometry": {"coordinates":[39.97139,-13.62472],"type":"Point"}
}