{
  "type": "Feature",
  "properties": {
    "gn:admin1_code":"1",
    "gn:asciiname":"Malico",
    "gn:country_code":"MZ",
    "gn:dem":447,
    "gn:feature_class":"P",
    "gn:feature_code":"PPL",
    "gn:name":"Malico",
    "gn:population":0,
    "gn:timezone":"Africa/Maputo",
    "iso:country":"MZ",
    "wof:name":"Malico",
    "wof:placetype":"locality"
},
  "geometry": {"coordinates":[38.80361,-13.64667],"type":"Point"}
}