{
  "type": "Feature",
  "properties": {
    "gn:admin1_code":"10",
    "gn:asciiname":"Mutali",
    "gn:country_code":"MZ",
    "gn:dem":1108,
    "gn:feature_class":"P",
    "gn:feature_code":"PPL",
    "gn:name":"Mut\u00e1li",
    "gn:population":0,
    "gn:timezone":"Africa/Maputo",
    "iso:country":"MZ",
    "wof:name":"Mutali",
    "wof:placetype":"locality"
},
  "geometry": {"coordinates":[33.09417,-18.03028],"type":"Point"}
}