{
  "type": "Feature",
  "properties": {
    "gn:admin1_code":"3.0",
    "gn:asciiname":"Nhuane",
    "gn:country_code":"MZ",
    "gn:dem":172,
    "gn:feature_class":"P",
    "gn:feature_code":"PPL",
    "gn:name":"Nhuane",
    "gn:population":0,
    "gn:timezone":"Africa/Maputo",
    "iso:country":"MZ",
    "wof:name":"Nhuane",
    "wof:placetype":"locality"
},
  "geometry": {"coordinates":[34.54417,-22.71528],"type":"Point"}
}