{
  "type": "Feature",
  "properties": {
    "gn:admin1_code":"7",
    "gn:asciiname":"Nesalo",
    "gn:cc2":"MZ",
    "gn:country_code":"MZ",
    "gn:dem":806,
    "gn:feature_class":"P",
    "gn:feature_code":"PPL",
    "gn:name":"Nesalo",
    "gn:population":0,
    "gn:timezone":"Africa/Maputo",
    "iso:country":"MZ",
    "name:und_x_variant":[
        "Nezalo",
        "Nesalo"
    ],
    "wof:name":"Nesalo",
    "wof:placetype":"locality"
},
  "geometry": {"coordinates":[35.81083,-13.75472],"type":"Point"}
}