{
  "type": "Feature",
  "properties": {
    "gn:admin1_code":"3.0",
    "gn:asciiname":"Umbane",
    "gn:country_code":"MZ",
    "gn:dem":180,
    "gn:feature_class":"P",
    "gn:feature_code":"PPL",
    "gn:name":"Umbane",
    "gn:population":0,
    "gn:timezone":"Africa/Maputo",
    "iso:country":"MZ",
    "wof:name":"Umbane",
    "wof:placetype":"locality"
},
  "geometry": {"coordinates":[34.04639,-21.66083],"type":"Point"}
}