{
  "type": "Feature",
  "properties": {
    "gn:admin1_code":"1",
    "gn:asciiname":"Assane",
    "gn:country_code":"MZ",
    "gn:dem":16,
    "gn:feature_class":"P",
    "gn:feature_code":"PPL",
    "gn:name":"Assane",
    "gn:population":0,
    "gn:timezone":"Africa/Maputo",
    "iso:country":"MZ",
    "wof:name":"Assane",
    "wof:placetype":"locality"
},
  "geometry": {"coordinates":[40.23389,-10.61806],"type":"Point"}
}