{
  "type": "Feature",
  "properties": {
    "gn:admin1_code":"4",
    "gn:asciiname":"Maponde",
    "gn:country_code":"MZ",
    "gn:dem":12,
    "gn:feature_class":"P",
    "gn:feature_code":"PPL",
    "gn:name":"Maponde",
    "gn:population":0,
    "gn:timezone":"Africa/Maputo",
    "iso:country":"MZ",
    "wof:name":"Maponde",
    "wof:placetype":"locality"
},
  "geometry": {"coordinates":[32.91667,-26.01667],"type":"Point"}
}