{
  "type": "Feature",
  "properties": {
    "gn:admin1_code":"8.0",
    "gn:asciiname":"Vicente",
    "gn:country_code":"MZ",
    "gn:dem":54,
    "gn:feature_class":"P",
    "gn:feature_code":"PPL",
    "gn:name":"Vicente",
    "gn:population":0,
    "gn:timezone":"Africa/Maputo",
    "iso:country":"MZ",
    "name:cat_x_preferred":[
        "Vicente"
    ],
    "name:ceb_x_preferred":[
        "Vicente"
    ],
    "name:fra_x_preferred":[
        "Vicente"
    ],
    "name:ita_x_preferred":[
        "Vicente"
    ],
    "name:jpn_x_preferred":[
        "\u30d3\u30bb\u30f3\u30c6"
    ],
    "name:por_x_preferred":[
        "Vicente"
    ],
    "name:rus_x_preferred":[
        "\u0412\u0438\u0441\u0435\u043d\u0442\u0435"
    ],
    "name:spa_x_preferred":[
        "Vicente"
    ],
    "name:swe_x_preferred":[
        "Vicente"
    ],
    "wof:name":"Vicente",
    "wof:placetype":"locality"
},
  "geometry": {"coordinates":[35.13667,-17.34528],"type":"Point"}
}