{
  "type": "Feature",
  "properties": {
    "gn:admin1_code":"4",
    "gn:asciiname":"Palazano",
    "gn:country_code":"MZ",
    "gn:dem":43,
    "gn:feature_class":"P",
    "gn:feature_code":"PPL",
    "gn:name":"Palazano",
    "gn:population":0,
    "gn:timezone":"Africa/Maputo",
    "iso:country":"MZ",
    "wof:name":"Palazano",
    "wof:placetype":"locality"
},
  "geometry": {"coordinates":[32.59556,-26.16778],"type":"Point"}
}