{
  "type": "Feature",
  "properties": {
    "gn:admin1_code":"3.0",
    "gn:asciiname":"Chitine",
    "gn:country_code":"MZ",
    "gn:dem":175,
    "gn:feature_class":"P",
    "gn:feature_code":"PPL",
    "gn:name":"Chitine",
    "gn:population":0,
    "gn:timezone":"Africa/Maputo",
    "iso:country":"MZ",
    "wof:name":"Chitine",
    "wof:placetype":"locality"
},
  "geometry": {"coordinates":[34.40833,-22.46194],"type":"Point"}
}