{
  "type": "Feature",
  "properties": {
    "gn:admin1_code":"2",
    "gn:asciiname":"Mahutsane",
    "gn:country_code":"MZ",
    "gn:dem":43,
    "gn:feature_class":"P",
    "gn:feature_code":"PPL",
    "gn:name":"Mahutsane",
    "gn:population":0,
    "gn:timezone":"Africa/Maputo",
    "iso:country":"MZ",
    "wof:name":"Mahutsane",
    "wof:placetype":"locality"
},
  "geometry": {"coordinates":[34.01583,-24.58694],"type":"Point"}
}