{
  "type": "Feature",
  "properties": {
    "gn:admin1_code":"10.0",
    "gn:asciiname":"Repungo",
    "gn:country_code":"MZ",
    "gn:dem":188,
    "gn:feature_class":"P",
    "gn:feature_code":"PPL",
    "gn:name":"Repungo",
    "gn:population":0,
    "gn:timezone":"Africa/Maputo",
    "iso:country":"MZ",
    "wof:name":"Repungo",
    "wof:placetype":"locality"
},
  "geometry": {"coordinates":[33.58194,-20.99667],"type":"Point"}
}