{
  "type": "Feature",
  "properties": {
    "gn:admin1_code":"3",
    "gn:asciiname":"Meganguene",
    "gn:country_code":"MZ",
    "gn:dem":155,
    "gn:feature_class":"P",
    "gn:feature_code":"PPL",
    "gn:name":"Meganguene",
    "gn:population":0,
    "gn:timezone":"Africa/Maputo",
    "iso:country":"MZ",
    "wof:name":"Meganguene",
    "wof:placetype":"locality"
},
  "geometry": {"coordinates":[34.445,-21.75889],"type":"Point"}
}