{
  "type": "Feature",
  "properties": {
    "gn:admin1_code":"10.0",
    "gn:asciiname":"Mpatanguenha",
    "gn:cc2":"MZ",
    "gn:country_code":"MZ",
    "gn:dem":936,
    "gn:feature_class":"P",
    "gn:feature_code":"PPL",
    "gn:name":"Mpatanguenha",
    "gn:population":0,
    "gn:timezone":"Africa/Maputo",
    "iso:country":"MZ",
    "name:und_x_variant":[
        "Samanhanga",
        "Mpatanguenha"
    ],
    "wof:name":"Mpatanguenha",
    "wof:placetype":"locality"
},
  "geometry": {"coordinates":[33.16528,-17.57611],"type":"Point"}
}