{
  "type": "Feature",
  "properties": {
    "gn:admin1_code":"7",
    "gn:asciiname":"Amice",
    "gn:country_code":"MZ",
    "gn:dem":1418,
    "gn:feature_class":"P",
    "gn:feature_code":"PPL",
    "gn:name":"Amice",
    "gn:population":0,
    "gn:timezone":"Africa/Maputo",
    "iso:country":"MZ",
    "wof:name":"Amice",
    "wof:placetype":"locality"
},
  "geometry": {"coordinates":[35.1075,-12.84917],"type":"Point"}
}