{
  "type": "Feature",
  "properties": {
    "gn:admin1_code":"6",
    "gn:asciiname":"Leal",
    "gn:country_code":"MZ",
    "gn:dem":720,
    "gn:feature_class":"P",
    "gn:feature_code":"PPL",
    "gn:name":"Leal",
    "gn:population":0,
    "gn:timezone":"Africa/Maputo",
    "iso:country":"MZ",
    "name:ceb_x_preferred":[
        "Leal"
    ],
    "name:deu_x_preferred":[
        "Leal"
    ],
    "name:fra_x_preferred":[
        "Leal"
    ],
    "name:ita_x_preferred":[
        "Leal"
    ],
    "name:por_x_preferred":[
        "Leal"
    ],
    "name:rus_x_preferred":[
        "\u041b\u0435\u0430\u043b\u044c"
    ],
    "name:srp_x_preferred":[
        "\u041b\u0435\u0430\u043b"
    ],
    "name:swe_x_preferred":[
        "Leal"
    ],
    "wof:name":"Leal",
    "wof:placetype":"locality"
},
  "geometry": {"coordinates":[37.72556,-14.86667],"type":"Point"}
}