{
  "type": "Feature",
  "properties": {
    "gn:admin1_code":"9",
    "gn:asciiname":"Labissone",
    "gn:country_code":"MZ",
    "gn:dem":830,
    "gn:feature_class":"P",
    "gn:feature_code":"PPL",
    "gn:name":"Labissone",
    "gn:population":0,
    "gn:timezone":"Africa/Maputo",
    "iso:country":"MZ",
    "wof:name":"Labissone",
    "wof:placetype":"locality"
},
  "geometry": {"coordinates":[37.41917,-15.23667],"type":"Point"}
}