{
  "type": "Feature",
  "properties": {
    "gn:admin1_code":"7",
    "gn:asciiname":"Chefe Tiole",
    "gn:country_code":"MZ",
    "gn:dem":552,
    "gn:feature_class":"P",
    "gn:feature_code":"PPL",
    "gn:name":"Chefe Tiole",
    "gn:population":0,
    "gn:timezone":"Africa/Maputo",
    "iso:country":"MZ",
    "wof:name":"Chefe Tiole",
    "wof:placetype":"locality"
},
  "geometry": {"coordinates":[36.92972,-14.68389],"type":"Point"}
}