{
  "type": "Feature",
  "properties": {
    "gn:admin1_code":"10",
    "gn:asciiname":"Muzanga",
    "gn:country_code":"MZ",
    "gn:dem":157,
    "gn:feature_class":"P",
    "gn:feature_code":"PPL",
    "gn:name":"Muzanga",
    "gn:population":0,
    "gn:timezone":"Africa/Maputo",
    "iso:country":"MZ",
    "wof:name":"Muzanga",
    "wof:placetype":"locality"
},
  "geometry": {"coordinates":[33.27472,-19.88944],"type":"Point"}
}