{
  "type": "Feature",
  "properties": {
    "gn:admin1_code":"2.0",
    "gn:asciiname":"Chefe Manguana",
    "gn:country_code":"MZ",
    "gn:dem":201,
    "gn:feature_class":"P",
    "gn:feature_code":"PPL",
    "gn:name":"Chefe Manguana",
    "gn:population":0,
    "gn:timezone":"Africa/Maputo",
    "iso:country":"MZ",
    "wof:name":"Chefe Manguana",
    "wof:placetype":"locality"
},
  "geometry": {"coordinates":[31.55139,-22.32972],"type":"Point"}
}