{
  "type": "Feature",
  "properties": {
    "gn:admin1_code":"2.0",
    "gn:asciiname":"C. Tuvana",
    "gn:country_code":"MZ",
    "gn:dem":38,
    "gn:feature_class":"P",
    "gn:feature_code":"PPL",
    "gn:name":"C. Tuvana",
    "gn:population":0,
    "gn:timezone":"Africa/Maputo",
    "iso:country":"MZ",
    "wof:name":"C. Tuvana",
    "wof:placetype":"locality"
},
  "geometry": {"coordinates":[32.81610999999999,-24.62389],"type":"Point"}
}