{
  "type": "Feature",
  "properties": {
    "gn:admin1_code":"7",
    "gn:asciiname":"Imete",
    "gn:country_code":"MZ",
    "gn:dem":460,
    "gn:feature_class":"P",
    "gn:feature_code":"PPL",
    "gn:name":"Imete",
    "gn:population":0,
    "gn:timezone":"Africa/Maputo",
    "iso:country":"MZ",
    "wof:name":"Imete",
    "wof:placetype":"locality"
},
  "geometry": {"coordinates":[37.80472,-12.94694],"type":"Point"}
}