{
  "type": "Feature",
  "properties": {
    "gn:admin1_code":"10",
    "gn:asciiname":"Madjadiri",
    "gn:country_code":"MZ",
    "gn:dem":541,
    "gn:feature_class":"P",
    "gn:feature_code":"PPL",
    "gn:name":"Madj\u00e1diri",
    "gn:population":0,
    "gn:timezone":"Africa/Maputo",
    "iso:country":"MZ",
    "wof:name":"Madjadiri",
    "wof:placetype":"locality"
},
  "geometry": {"coordinates":[33.73583,-19.04806],"type":"Point"}
}