{
  "type": "Feature",
  "properties": {
    "gn:admin1_code":"3",
    "gn:asciiname":"Elefante",
    "gn:cc2":"MZ",
    "gn:country_code":"MZ",
    "gn:dem":174,
    "gn:feature_class":"P",
    "gn:feature_code":"PPL",
    "gn:name":"Elefante",
    "gn:population":0,
    "gn:timezone":"Africa/Maputo",
    "iso:country":"MZ",
    "name:ceb_x_preferred":[
        "Elefante"
    ],
    "name:por_x_preferred":[
        "Elefante"
    ],
    "name:spa_x_preferred":[
        "Elefante"
    ],
    "name:swe_x_preferred":[
        "Elefante"
    ],
    "name:tgl_x_preferred":[
        "Elepante"
    ],
    "name:und_x_variant":[
        "Lissante",
        "Elefante"
    ],
    "wof:name":"Elefante",
    "wof:placetype":"locality"
},
  "geometry": {"coordinates":[34.29611,-22.23194],"type":"Point"}
}