{
  "type": "Feature",
  "properties": {
    "gn:admin1_code":"9",
    "gn:asciiname":"Gomo",
    "gn:country_code":"MZ",
    "gn:dem":52,
    "gn:feature_class":"P",
    "gn:feature_code":"PPL",
    "gn:name":"Gomo",
    "gn:population":0,
    "gn:timezone":"Africa/Maputo",
    "iso:country":"MZ",
    "wof:name":"Gomo",
    "wof:placetype":"locality"
},
  "geometry": {"coordinates":[35.25639,-16.6425],"type":"Point"}
}