{
  "type": "Feature",
  "properties": {
    "gn:admin1_code":"7",
    "gn:asciiname":"Antonio",
    "gn:country_code":"MZ",
    "gn:dem":605,
    "gn:feature_class":"P",
    "gn:feature_code":"PPL",
    "gn:name":"Ant\u00f3nio",
    "gn:population":0,
    "gn:timezone":"Africa/Maputo",
    "iso:country":"MZ",
    "name:epo_x_preferred":[
        "Antonio"
    ],
    "name:fra_x_preferred":[
        "Antonio"
    ],
    "name:hye_x_preferred":[
        "\u0531\u0576\u057f\u0578\u0576\u056b\u0578"
    ],
    "name:ita_x_preferred":[
        "Antonio"
    ],
    "name:jpn_x_preferred":[
        "\u30a2\u30f3\u30c8\u30cb\u30aa"
    ],
    "name:nld_x_preferred":[
        "Antonio"
    ],
    "name:nor_x_preferred":[
        "Antonio"
    ],
    "name:slv_x_preferred":[
        "Antonio"
    ],
    "name:spa_x_preferred":[
        "Antonio"
    ],
    "wof:name":"Antonio",
    "wof:placetype":"locality"
},
  "geometry": {"coordinates":[36.62944,-14.43972],"type":"Point"}
}