{
  "type": "Feature",
  "properties": {
    "gn:admin1_code":"6.0",
    "gn:asciiname":"Tuela",
    "gn:country_code":"MZ",
    "gn:dem":242,
    "gn:feature_class":"P",
    "gn:feature_code":"PPL",
    "gn:name":"Tuela",
    "gn:population":0,
    "gn:timezone":"Africa/Maputo",
    "iso:country":"MZ",
    "wof:name":"Tuela",
    "wof:placetype":"locality"
},
  "geometry": {"coordinates":[39.89972,-14.74528],"type":"Point"}
}