{
  "type": "Feature",
  "properties": {
    "gn:admin1_code":"6",
    "gn:asciiname":"Mutolia",
    "gn:country_code":"MZ",
    "gn:dem":119,
    "gn:feature_class":"P",
    "gn:feature_code":"PPL",
    "gn:name":"Mutolia",
    "gn:population":0,
    "gn:timezone":"Africa/Maputo",
    "iso:country":"MZ",
    "wof:name":"Mutolia",
    "wof:placetype":"locality"
},
  "geometry": {"coordinates":[39.23,-15.92417],"type":"Point"}
}