{
  "type": "Feature",
  "properties": {
    "gn:admin1_code":"6.0",
    "gn:asciiname":"Regedor Macone",
    "gn:country_code":"MZ",
    "gn:dem":9,
    "gn:feature_class":"P",
    "gn:feature_code":"PPL",
    "gn:name":"Regedor Macone",
    "gn:population":0,
    "gn:timezone":"Africa/Maputo",
    "iso:country":"MZ",
    "wof:name":"Regedor Macone",
    "wof:placetype":"locality"
},
  "geometry": {"coordinates":[39.21472,-16.75306],"type":"Point"}
}