{
  "type": "Feature",
  "properties": {
    "gn:admin1_code":"9",
    "gn:asciiname":"Pinda",
    "gn:country_code":"MZ",
    "gn:dem":37,
    "gn:feature_class":"P",
    "gn:feature_code":"PPL",
    "gn:name":"Pinda",
    "gn:population":0,
    "gn:timezone":"Africa/Maputo",
    "iso:country":"MZ",
    "name:ceb_x_preferred":[
        "Pinda"
    ],
    "name:pol_x_preferred":[
        "Pinda"
    ],
    "name:por_x_preferred":[
        "Pinda"
    ],
    "name:swe_x_preferred":[
        "Pinda"
    ],
    "wof:name":"Pinda",
    "wof:placetype":"locality"
},
  "geometry": {"coordinates":[35.34917,-17.36694],"type":"Point"}
}