{
  "type": "Feature",
  "properties": {
    "gn:admin1_code":"3.0",
    "gn:asciiname":"Chefe Maimelane",
    "gn:country_code":"MZ",
    "gn:dem":27,
    "gn:feature_class":"P",
    "gn:feature_code":"PPL",
    "gn:name":"Chefe Maimelane",
    "gn:population":0,
    "gn:timezone":"Africa/Maputo",
    "iso:country":"MZ",
    "wof:name":"Chefe Maimelane",
    "wof:placetype":"locality"
},
  "geometry": {"coordinates":[35.09917,-21.64722],"type":"Point"}
}