{
  "type": "Feature",
  "properties": {
    "gn:admin1_code":"0.0",
    "gn:asciiname":"S. Alende",
    "gn:country_code":"MZ",
    "gn:dem":2,
    "gn:feature_class":"P",
    "gn:feature_code":"PPL",
    "gn:name":"S. Alende",
    "gn:population":0,
    "gn:timezone":"Africa/Maputo",
    "iso:country":"MZ",
    "wof:name":"S. Alende",
    "wof:placetype":"locality"
},
  "geometry": {"coordinates":[33.52306,-25.12972],"type":"Point"}
}