{
  "type": "Feature",
  "properties": {
    "gn:admin1_code":"6",
    "gn:asciiname":"Mepunha",
    "gn:country_code":"MZ",
    "gn:dem":106,
    "gn:feature_class":"P",
    "gn:feature_code":"PPL",
    "gn:name":"Mepunha",
    "gn:population":0,
    "gn:timezone":"Africa/Maputo",
    "iso:country":"MZ",
    "wof:name":"Mepunha",
    "wof:placetype":"locality"
},
  "geometry": {"coordinates":[39.32111,-15.86861],"type":"Point"}
}