{
  "type": "Feature",
  "properties": {
    "gn:admin1_code":"3.0",
    "gn:asciiname":"Siquela",
    "gn:country_code":"MZ",
    "gn:dem":139,
    "gn:feature_class":"P",
    "gn:feature_code":"PPL",
    "gn:name":"Siquela",
    "gn:population":0,
    "gn:timezone":"Africa/Maputo",
    "iso:country":"MZ",
    "wof:name":"Siquela",
    "wof:placetype":"locality"
},
  "geometry": {"coordinates":[34.97417,-23.09944],"type":"Point"}
}