{
  "type": "Feature",
  "properties": {
    "gn:admin1_code":"6",
    "gn:asciiname":"Uantera",
    "gn:country_code":"MZ",
    "gn:dem":312,
    "gn:feature_class":"P",
    "gn:feature_code":"PPL",
    "gn:name":"Uantera",
    "gn:population":0,
    "gn:timezone":"Africa/Maputo",
    "iso:country":"MZ",
    "wof:name":"Uantera",
    "wof:placetype":"locality"
},
  "geometry": {"coordinates":[39.28556,-14.0275],"type":"Point"}
}