{
  "type": "Feature",
  "properties": {
    "gn:admin1_code":"3",
    "gn:asciiname":"Marrumelane",
    "gn:country_code":"MZ",
    "gn:dem":130,
    "gn:feature_class":"P",
    "gn:feature_code":"PPL",
    "gn:name":"Marrumelane",
    "gn:population":0,
    "gn:timezone":"Africa/Maputo",
    "iso:country":"MZ",
    "wof:name":"Marrumelane",
    "wof:placetype":"locality"
},
  "geometry": {"coordinates":[33.89611,-22.04889],"type":"Point"}
}