{
  "type": "Feature",
  "properties": {
    "gn:admin1_code":"4",
    "gn:asciiname":"Machanza",
    "gn:cc2":"MZ",
    "gn:country_code":"MZ",
    "gn:dem":61,
    "gn:feature_class":"P",
    "gn:feature_code":"PPL",
    "gn:name":"Machanza",
    "gn:population":0,
    "gn:timezone":"Africa/Maputo",
    "iso:country":"MZ",
    "name:und_x_variant":[
        "Muchaza",
        "Machanza"
    ],
    "wof:name":"Machanza",
    "wof:placetype":"locality"
},
  "geometry": {"coordinates":[32.37528,-25.04667],"type":"Point"}
}