{
  "type": "Feature",
  "properties": {
    "gn:admin1_code":"1",
    "gn:asciiname":"Dali",
    "gn:country_code":"MZ",
    "gn:dem":156,
    "gn:feature_class":"P",
    "gn:feature_code":"PPL",
    "gn:name":"D\u00e1li",
    "gn:population":0,
    "gn:timezone":"Africa/Maputo",
    "iso:country":"MZ",
    "wof:name":"Dali",
    "wof:placetype":"locality"
},
  "geometry": {"coordinates":[40.28833,-12.44194],"type":"Point"}
}