{
  "type": "Feature",
  "properties": {
    "gn:admin1_code":"4",
    "gn:asciiname":"Cocolo",
    "gn:country_code":"MZ",
    "gn:dem":60,
    "gn:feature_class":"P",
    "gn:feature_code":"PPL",
    "gn:name":"Cocolo",
    "gn:population":0,
    "gn:timezone":"Africa/Maputo",
    "iso:country":"MZ",
    "wof:name":"Cocolo",
    "wof:placetype":"locality"
},
  "geometry": {"coordinates":[32.56056,-25.65056],"type":"Point"}
}