{
  "type": "Feature",
  "properties": {
    "gn:admin1_code":"7",
    "gn:asciiname":"Amuri",
    "gn:country_code":"MZ",
    "gn:dem":1198,
    "gn:feature_class":"P",
    "gn:feature_code":"PPL",
    "gn:name":"Amuri",
    "gn:population":0,
    "gn:timezone":"Africa/Maputo",
    "iso:country":"MZ",
    "wof:name":"Amuri",
    "wof:placetype":"locality"
},
  "geometry": {"coordinates":[35.31222,-13.93444],"type":"Point"}
}