{
  "type": "Feature",
  "properties": {
    "gn:admin1_code":"1",
    "gn:asciiname":"Ibraimo",
    "gn:country_code":"MZ",
    "gn:dem":246,
    "gn:feature_class":"P",
    "gn:feature_code":"PPL",
    "gn:name":"Ibra\u00edmo",
    "gn:population":0,
    "gn:timezone":"Africa/Maputo",
    "iso:country":"MZ",
    "wof:name":"Ibraimo",
    "wof:placetype":"locality"
},
  "geometry": {"coordinates":[39.91472,-12.46833],"type":"Point"}
}