{
  "type": "Feature",
  "properties": {
    "gn:admin1_code":"3.0",
    "gn:asciiname":"Mussuto Gonhamo",
    "gn:country_code":"MZ",
    "gn:dem":80,
    "gn:feature_class":"P",
    "gn:feature_code":"PPL",
    "gn:name":"Mussuto Gonhamo",
    "gn:population":0,
    "gn:timezone":"Africa/Maputo",
    "iso:country":"MZ",
    "wof:name":"Mussuto Gonhamo",
    "wof:placetype":"locality"
},
  "geometry": {"coordinates":[34.19139000000001,-24.12722],"type":"Point"}
}