{
  "type": "Feature",
  "properties": {
    "gn:admin1_code":"1",
    "gn:asciiname":"Chefe Nigoeleua",
    "gn:country_code":"MZ",
    "gn:dem":268,
    "gn:feature_class":"P",
    "gn:feature_code":"PPL",
    "gn:name":"Chefe Nigoeleua",
    "gn:population":0,
    "gn:timezone":"Africa/Maputo",
    "iso:country":"MZ",
    "wof:name":"Chefe Nigoeleua",
    "wof:placetype":"locality"
},
  "geometry": {"coordinates":[39.86556,-13.22833],"type":"Point"}
}