{
  "type": "Feature",
  "properties": {
    "gn:admin1_code":"4",
    "gn:asciiname":"Buzo",
    "gn:country_code":"MZ",
    "gn:dem":62,
    "gn:feature_class":"P",
    "gn:feature_code":"PPL",
    "gn:name":"Buzo",
    "gn:population":0,
    "gn:timezone":"Africa/Maputo",
    "iso:country":"MZ",
    "wof:name":"Buzo",
    "wof:placetype":"locality"
},
  "geometry": {"coordinates":[32.62833,-25.56417],"type":"Point"}
}