{
  "type": "Feature",
  "properties": {
    "gn:admin1_code":"2",
    "gn:asciiname":"Maxinho",
    "gn:cc2":"MZ",
    "gn:country_code":"MZ",
    "gn:dem":51,
    "gn:feature_class":"P",
    "gn:feature_code":"PPL",
    "gn:name":"Maxinho",
    "gn:population":0,
    "gn:timezone":"Africa/Maputo",
    "iso:country":"MZ",
    "name:und_x_variant":[
        "Macinho",
        "Maxinho"
    ],
    "wof:name":"Maxinho",
    "wof:placetype":"locality"
},
  "geometry": {"coordinates":[32.72333,-24.19083],"type":"Point"}
}