{
  "type": "Feature",
  "properties": {
    "gn:admin1_code":"0",
    "gn:asciiname":"Mavurabuzi",
    "gn:country_code":"MZ",
    "gn:dem":38,
    "gn:feature_class":"P",
    "gn:feature_code":"PPL",
    "gn:name":"Mavurabuzi",
    "gn:population":0,
    "gn:timezone":"Africa/Maputo",
    "iso:country":"MZ",
    "wof:name":"Mavurabuzi",
    "wof:placetype":"locality"
},
  "geometry": {"coordinates":[34.93333,-18.08333],"type":"Point"}
}