{
  "type": "Feature",
  "properties": {
    "gn:admin1_code":"10",
    "gn:asciiname":"Bessuca",
    "gn:country_code":"MZ",
    "gn:dem":218,
    "gn:feature_class":"P",
    "gn:feature_code":"PPL",
    "gn:name":"Bessuca",
    "gn:population":0,
    "gn:timezone":"Africa/Maputo",
    "iso:country":"MZ",
    "wof:name":"Bessuca",
    "wof:placetype":"locality"
},
  "geometry": {"coordinates":[33.5275,-20.89389],"type":"Point"}
}