{
  "type": "Feature",
  "properties": {
    "gn:admin1_code":"3.0",
    "gn:asciiname":"Chapo",
    "gn:country_code":"MZ",
    "gn:dem":115,
    "gn:feature_class":"P",
    "gn:feature_code":"PPL",
    "gn:name":"Chapo",
    "gn:population":0,
    "gn:timezone":"Africa/Maputo",
    "iso:country":"MZ",
    "wof:name":"Chapo",
    "wof:placetype":"locality"
},
  "geometry": {"coordinates":[34.495,-21.58194],"type":"Point"}
}