{
  "type": "Feature",
  "properties": {
    "gn:admin1_code":"10",
    "gn:asciiname":"Jone",
    "gn:country_code":"MZ",
    "gn:dem":406,
    "gn:feature_class":"P",
    "gn:feature_code":"PPL",
    "gn:name":"Jone",
    "gn:population":0,
    "gn:timezone":"Africa/Maputo",
    "iso:country":"MZ",
    "name:deu_x_preferred":[
        "Jone"
    ],
    "name:por_x_preferred":[
        "Jone"
    ],
    "wof:name":"Jone",
    "wof:placetype":"locality"
},
  "geometry": {"coordinates":[32.58,-20.92944],"type":"Point"}
}