{
  "type": "Feature",
  "properties": {
    "gn:admin1_code":"9",
    "gn:asciiname":"Cocuania",
    "gn:country_code":"MZ",
    "gn:dem":211,
    "gn:feature_class":"P",
    "gn:feature_code":"PPL",
    "gn:name":"Cocuania",
    "gn:population":0,
    "gn:timezone":"Africa/Maputo",
    "iso:country":"MZ",
    "wof:name":"Cocuania",
    "wof:placetype":"locality"
},
  "geometry": {"coordinates":[36.66028,-17.07777999999999],"type":"Point"}
}