{
  "type": "Feature",
  "properties": {
    "gn:admin1_code":"6.0",
    "gn:asciiname":"Recua",
    "gn:country_code":"MZ",
    "gn:dem":125,
    "gn:feature_class":"P",
    "gn:feature_code":"PPL",
    "gn:name":"R\u00e9cua",
    "gn:population":0,
    "gn:timezone":"Africa/Maputo",
    "iso:country":"MZ",
    "wof:name":"Recua",
    "wof:placetype":"locality"
},
  "geometry": {"coordinates":[40.1475,-15.31861],"type":"Point"}
}