{
  "type": "Feature",
  "properties": {
    "gn:admin1_code":"7.0",
    "gn:asciiname":"Tempue",
    "gn:country_code":"MZ",
    "gn:dem":609,
    "gn:feature_class":"P",
    "gn:feature_code":"PPL",
    "gn:name":"Tempu\u00e9",
    "gn:population":0,
    "gn:timezone":"Africa/Maputo",
    "iso:country":"MZ",
    "wof:name":"Tempue",
    "wof:placetype":"locality"
},
  "geometry": {"coordinates":[37.68694,-12.93694],"type":"Point"}
}