{
  "type": "Feature",
  "properties": {
    "gn:admin1_code":"6",
    "gn:asciiname":"Panto",
    "gn:country_code":"MZ",
    "gn:dem":69,
    "gn:feature_class":"P",
    "gn:feature_code":"PPL",
    "gn:name":"Panto",
    "gn:population":0,
    "gn:timezone":"Africa/Maputo",
    "iso:country":"MZ",
    "name:ceb_x_preferred":[
        "Panto"
    ],
    "name:swe_x_preferred":[
        "Panto"
    ],
    "wof:name":"Panto",
    "wof:placetype":"locality"
},
  "geometry": {"coordinates":[40.35056,-15.04944],"type":"Point"}
}