{
  "type": "Feature",
  "properties": {
    "gn:admin1_code":"2.0",
    "gn:asciiname":"Oliveira",
    "gn:country_code":"MZ",
    "gn:dem":175,
    "gn:feature_class":"P",
    "gn:feature_code":"PPL",
    "gn:name":"Oliveira",
    "gn:population":0,
    "gn:timezone":"Africa/Maputo",
    "iso:country":"MZ",
    "name:ast_x_preferred":[
        "Oliveira"
    ],
    "name:bul_x_preferred":[
        "\u041e\u043b\u0438\u0432\u0435\u0439\u0440\u0430"
    ],
    "name:cat_x_preferred":[
        "Oliveira"
    ],
    "name:ceb_x_preferred":[
        "Oliveira"
    ],
    "name:deu_x_preferred":[
        "Oliveira"
    ],
    "name:fas_x_preferred":[
        "\u0627\u0648\u0644\u06cc\u0648\u06cc\u0631\u0627"
    ],
    "name:fin_x_preferred":[
        "Oliveira"
    ],
    "name:fra_x_preferred":[
        "Oliveira"
    ],
    "name:glg_x_preferred":[
        "Oliveira"
    ],
    "name:jpn_x_preferred":[
        "\u30aa\u30ea\u30d9\u30a4\u30e9"
    ],
    "name:lit_x_preferred":[
        "Oliveira"
    ],
    "name:nld_x_preferred":[
        "Oliveira"
    ],
    "name:por_x_preferred":[
        "Oliveira"
    ],
    "name:rus_x_preferred":[
        "\u041e\u043b\u0438\u0432\u0435\u0439\u0440\u0430"
    ],
    "name:spa_x_preferred":[
        "Oliveira"
    ],
    "name:swe_x_preferred":[
        "Oliveira"
    ],
    "name:ukr_x_preferred":[
        "\u041e\u043b\u0456\u0432\u0435\u0439\u0440\u0430"
    ],
    "name:zho_x_preferred":[
        "\u5965\u5229\u97e6\u62c9"
    ],
    "wof:name":"Oliveira",
    "wof:placetype":"locality"
},
  "geometry": {"coordinates":[31.71833,-22.52472],"type":"Point"}
}