{
  "type": "Feature",
  "properties": {
    "gn:admin1_code":"2.0",
    "gn:asciiname":"Oliveira",
    "gn:country_code":"MZ",
    "gn:dem":175,
    "gn:feature_class":"P",
    "gn:feature_code":"PPL",
    "gn:name":"Oliveira",
    "gn:population":0,
    "gn:timezone":"Africa/Maputo",
    "iso:country":"MZ",
    "wof:name":"Oliveira",
    "wof:placetype":"locality"
},
  "geometry": {"coordinates":[31.71833,-22.52472],"type":"Point"}
}