{
  "type": "Feature",
  "properties": {
    "gn:admin1_code":"5",
    "gn:asciiname":"Jeque",
    "gn:country_code":"MZ",
    "gn:dem":167,
    "gn:feature_class":"P",
    "gn:feature_code":"PPL",
    "gn:name":"Jeque",
    "gn:population":0,
    "gn:timezone":"Africa/Maputo",
    "iso:country":"MZ",
    "wof:name":"Jeque",
    "wof:placetype":"locality"
},
  "geometry": {"coordinates":[34.09222,-18.96778],"type":"Point"}
}