{
  "type": "Feature",
  "properties": {
    "gn:admin1_code":"0",
    "gn:asciiname":"Manhame",
    "gn:country_code":"MZ",
    "gn:dem":346,
    "gn:feature_class":"P",
    "gn:feature_code":"PPL",
    "gn:name":"Manhame",
    "gn:population":0,
    "gn:timezone":"Africa/Maputo",
    "iso:country":"MZ",
    "wof:name":"Manhame",
    "wof:placetype":"locality"
},
  "geometry": {"coordinates":[31.41667,-15.75],"type":"Point"}
}