{
  "type": "Feature",
  "properties": {
    "gn:admin1_code":"1",
    "gn:asciiname":"Maite",
    "gn:country_code":"MZ",
    "gn:dem":246,
    "gn:feature_class":"P",
    "gn:feature_code":"PPL",
    "gn:name":"Ma\u00edte",
    "gn:population":0,
    "gn:timezone":"Africa/Maputo",
    "iso:country":"MZ",
    "name:und_x_variant":[
        "Ma\u00edte"
    ],
    "wof:name":"Maite",
    "wof:placetype":"locality"
},
  "geometry": {"coordinates":[39.93833,-13.37417],"type":"Point"}
}