{
  "type": "Feature",
  "properties": {
    "gn:admin1_code":"9",
    "gn:asciiname":"Dessiua",
    "gn:country_code":"MZ",
    "gn:dem":94,
    "gn:feature_class":"P",
    "gn:feature_code":"PPL",
    "gn:name":"Dessiua",
    "gn:population":0,
    "gn:timezone":"Africa/Maputo",
    "iso:country":"MZ",
    "wof:name":"Dessiua",
    "wof:placetype":"locality"
},
  "geometry": {"coordinates":[38.265,-16.79139],"type":"Point"}
}