{
  "type": "Feature",
  "properties": {
    "gn:admin1_code":"3.0",
    "gn:asciiname":"Joao Tai",
    "gn:country_code":"MZ",
    "gn:dem":32,
    "gn:feature_class":"P",
    "gn:feature_code":"PPL",
    "gn:name":"Jo\u00e3o Tai",
    "gn:population":0,
    "gn:timezone":"Africa/Maputo",
    "iso:country":"MZ",
    "wof:name":"Joao Tai",
    "wof:placetype":"locality"
},
  "geometry": {"coordinates":[35.08194,-21.66361],"type":"Point"}
}