{
  "type": "Feature",
  "properties": {
    "gn:admin1_code":"1.0",
    "gn:asciiname":"Mirate",
    "gn:cc2":"MZ",
    "gn:country_code":"MZ",
    "gn:dem":534,
    "gn:feature_class":"P",
    "gn:feature_code":"PPL",
    "gn:name":"Mirate",
    "gn:population":0,
    "gn:timezone":"Africa/Maputo",
    "iso:country":"MZ",
    "name:und_x_variant":[
        "Toma",
        "Mirate"
    ],
    "wof:name":"Mirate",
    "wof:placetype":"locality"
},
  "geometry": {"coordinates":[38.81528,-12.97806],"type":"Point"}
}