{
  "type": "Feature",
  "properties": {
    "gn:admin1_code":"6",
    "gn:asciiname":"Mocuassula",
    "gn:country_code":"MZ",
    "gn:dem":699,
    "gn:feature_class":"P",
    "gn:feature_code":"PPL",
    "gn:name":"Mocuassula",
    "gn:population":0,
    "gn:timezone":"Africa/Maputo",
    "iso:country":"MZ",
    "wof:name":"Mocuassula",
    "wof:placetype":"locality"
},
  "geometry": {"coordinates":[37.26,-15.02222],"type":"Point"}
}