{
  "type": "Feature",
  "properties": {
    "gn:admin1_code":"9",
    "gn:asciiname":"Mulia",
    "gn:country_code":"MZ",
    "gn:dem":11,
    "gn:feature_class":"P",
    "gn:feature_code":"PPL",
    "gn:name":"Mulia",
    "gn:population":0,
    "gn:timezone":"Africa/Maputo",
    "iso:country":"MZ",
    "wof:name":"Mulia",
    "wof:placetype":"locality"
},
  "geometry": {"coordinates":[36.68306,-18.34611],"type":"Point"}
}