{
  "type": "Feature",
  "properties": {
    "gn:admin1_code":"3.0",
    "gn:asciiname":"Sambula",
    "gn:country_code":"MZ",
    "gn:dem":63,
    "gn:feature_class":"P",
    "gn:feature_code":"PPL",
    "gn:name":"Sambula",
    "gn:population":0,
    "gn:timezone":"Africa/Maputo",
    "iso:country":"MZ",
    "wof:name":"Sambula",
    "wof:placetype":"locality"
},
  "geometry": {"coordinates":[35.15056,-22.49167000000001],"type":"Point"}
}