{
  "type": "Feature",
  "properties": {
    "gn:admin1_code":"10",
    "gn:asciiname":"Gueliehe",
    "gn:country_code":"MZ",
    "gn:dem":200,
    "gn:feature_class":"P",
    "gn:feature_code":"PPL",
    "gn:name":"Gueliehe",
    "gn:population":0,
    "gn:timezone":"Africa/Maputo",
    "iso:country":"MZ",
    "wof:name":"Gueliehe",
    "wof:placetype":"locality"
},
  "geometry": {"coordinates":[33.39556,-21.23611],"type":"Point"}
}