{
  "type": "Feature",
  "properties": {
    "gn:admin1_code":"9",
    "gn:asciiname":"Jone",
    "gn:country_code":"MZ",
    "gn:dem":697,
    "gn:feature_class":"P",
    "gn:feature_code":"PPL",
    "gn:name":"Jone",
    "gn:population":0,
    "gn:timezone":"Africa/Maputo",
    "iso:country":"MZ",
    "wof:name":"Jone",
    "wof:placetype":"locality"
},
  "geometry": {"coordinates":[35.98444,-15.77833],"type":"Point"}
}