{
  "type": "Feature",
  "properties": {
    "gn:admin1_code":"9",
    "gn:asciiname":"Nampada",
    "gn:country_code":"MZ",
    "gn:dem":304,
    "gn:feature_class":"P",
    "gn:feature_code":"PPL",
    "gn:name":"Nampada",
    "gn:population":0,
    "gn:timezone":"Africa/Maputo",
    "iso:country":"MZ",
    "wof:name":"Nampada",
    "wof:placetype":"locality"
},
  "geometry": {"coordinates":[37.22056,-16.43694],"type":"Point"}
}