{
  "type": "Feature",
  "properties": {
    "gn:admin1_code":"4",
    "gn:asciiname":"Matias",
    "gn:country_code":"MZ",
    "gn:dem":22,
    "gn:feature_class":"P",
    "gn:feature_code":"PPL",
    "gn:name":"Matias",
    "gn:population":0,
    "gn:timezone":"Africa/Maputo",
    "iso:country":"MZ",
    "wof:name":"Matias",
    "wof:placetype":"locality"
},
  "geometry": {"coordinates":[32.33722,-26.29778],"type":"Point"}
}