{
  "type": "Feature",
  "properties": {
    "gn:admin1_code":"1",
    "gn:asciiname":"Amade",
    "gn:country_code":"MZ",
    "gn:dem":560,
    "gn:feature_class":"P",
    "gn:feature_code":"PPL",
    "gn:name":"Amade",
    "gn:population":0,
    "gn:timezone":"Africa/Maputo",
    "iso:country":"MZ",
    "wof:name":"Amade",
    "wof:placetype":"locality"
},
  "geometry": {"coordinates":[38.50722,-13.36389],"type":"Point"}
}