{
  "type": "Feature",
  "properties": {
    "gn:admin1_code":"9.0",
    "gn:asciiname":"Sone",
    "gn:country_code":"MZ",
    "gn:dem":156,
    "gn:feature_class":"P",
    "gn:feature_code":"PPL",
    "gn:name":"Sone",
    "gn:population":0,
    "gn:timezone":"Africa/Maputo",
    "iso:country":"MZ",
    "wof:name":"Sone",
    "wof:placetype":"locality"
},
  "geometry": {"coordinates":[37.75444,-16.77139],"type":"Point"}
}