{
  "type": "Feature",
  "properties": {
    "gn:admin1_code":"7",
    "gn:asciiname":"Mucalapa",
    "gn:country_code":"MZ",
    "gn:dem":807,
    "gn:feature_class":"P",
    "gn:feature_code":"PPL",
    "gn:name":"Mucalapa",
    "gn:population":0,
    "gn:timezone":"Africa/Maputo",
    "iso:country":"MZ",
    "wof:name":"Mucalapa",
    "wof:placetype":"locality"
},
  "geometry": {"coordinates":[35.42722,-12.13861],"type":"Point"}
}