{
  "type": "Feature",
  "properties": {
    "gn:admin1_code":"10",
    "gn:asciiname":"Machuza",
    "gn:country_code":"MZ",
    "gn:dem":241,
    "gn:feature_class":"P",
    "gn:feature_code":"PPL",
    "gn:name":"Machuza",
    "gn:population":0,
    "gn:timezone":"Africa/Maputo",
    "iso:country":"MZ",
    "wof:name":"Machuza",
    "wof:placetype":"locality"
},
  "geometry": {"coordinates":[33.1675,-21.10694],"type":"Point"}
}