{
  "type": "Feature",
  "properties": {
    "gn:admin1_code":"1.0",
    "gn:asciiname":"Rati",
    "gn:country_code":"MZ",
    "gn:dem":496,
    "gn:feature_class":"P",
    "gn:feature_code":"PPL",
    "gn:name":"Rati",
    "gn:population":0,
    "gn:timezone":"Africa/Maputo",
    "iso:country":"MZ",
    "wof:name":"Rati",
    "wof:placetype":"locality"
},
  "geometry": {"coordinates":[39.23167,-13.37056],"type":"Point"}
}