{
  "type": "Feature",
  "properties": {
    "gn:admin1_code":"1.0",
    "gn:asciiname":"Rati",
    "gn:country_code":"MZ",
    "gn:dem":496,
    "gn:feature_class":"P",
    "gn:feature_code":"PPL",
    "gn:name":"Rati",
    "gn:population":0,
    "gn:timezone":"Africa/Maputo",
    "iso:country":"MZ",
    "name:ben_x_preferred":[
        "\u09b0\u09a4\u09bf"
    ],
    "name:cat_x_preferred":[
        "Rati"
    ],
    "name:epo_x_preferred":[
        "Rati"
    ],
    "name:fra_x_preferred":[
        "Rati"
    ],
    "name:hin_x_preferred":[
        "\u0930\u0924\u093f"
    ],
    "name:hrv_x_preferred":[
        "Rati"
    ],
    "name:ind_x_preferred":[
        "Kamaratih"
    ],
    "name:jav_x_preferred":[
        "Bathari Kamaratih"
    ],
    "name:nep_x_preferred":[
        "\u0930\u0924\u093f"
    ],
    "name:pan_x_preferred":[
        "\u0a30\u0a24\u0a40"
    ],
    "name:pol_x_preferred":[
        "Rati"
    ],
    "name:por_x_preferred":[
        "Rati"
    ],
    "name:rus_x_preferred":[
        "\u0420\u0430\u0442\u0438"
    ],
    "name:snd_x_preferred":[
        "\u0631\u062a\u064a"
    ],
    "name:spa_x_preferred":[
        "Rati"
    ],
    "name:swe_x_preferred":[
        "Rati"
    ],
    "name:tam_x_preferred":[
        "\u0b87\u0bb0\u0ba4\u0bbf \u0ba4\u0bc7\u0bb5\u0bbf"
    ],
    "name:tel_x_preferred":[
        "\u0c30\u0c24\u0c40\u0c26\u0c47\u0c35\u0c3f"
    ],
    "name:tur_x_preferred":[
        "Rati"
    ],
    "name:ukr_x_preferred":[
        "\u0420\u0430\u0442\u0456"
    ],
    "wof:name":"Rati",
    "wof:placetype":"locality"
},
  "geometry": {"coordinates":[39.23167,-13.37056],"type":"Point"}
}