{
  "type": "Feature",
  "properties": {
    "gn:admin1_code":"5.0",
    "gn:asciiname":"Pondo",
    "gn:country_code":"MZ",
    "gn:dem":139,
    "gn:feature_class":"P",
    "gn:feature_code":"PPL",
    "gn:name":"Pondo",
    "gn:population":0,
    "gn:timezone":"Africa/Maputo",
    "iso:country":"MZ",
    "name:swe_x_preferred":[
        "Pondo"
    ],
    "wof:name":"Pondo",
    "wof:placetype":"locality"
},
  "geometry": {"coordinates":[34.21667,-20.29361],"type":"Point"}
}