{
  "type": "Feature",
  "properties": {
    "gn:admin1_code":"0",
    "gn:asciiname":"Cassenga",
    "gn:country_code":"MZ",
    "gn:dem":3,
    "gn:feature_class":"P",
    "gn:feature_code":"PPL",
    "gn:name":"Cassenga",
    "gn:population":0,
    "gn:timezone":"Africa/Maputo",
    "iso:country":"MZ",
    "wof:name":"Cassenga",
    "wof:placetype":"locality"
},
  "geometry": {"coordinates":[36.23333,-18.55],"type":"Point"}
}