{
  "type": "Feature",
  "properties": {
    "gn:admin1_code":"1",
    "gn:asciiname":"Alita",
    "gn:cc2":"MZ",
    "gn:country_code":"MZ",
    "gn:dem":211,
    "gn:feature_class":"P",
    "gn:feature_code":"PPL",
    "gn:name":"Alita",
    "gn:population":0,
    "gn:timezone":"Africa/Maputo",
    "iso:country":"MZ",
    "name:deu_x_preferred":[
        "Alita"
    ],
    "name:fra_x_preferred":[
        "Alita"
    ],
    "name:kor_x_preferred":[
        "\uc54c\ub9ac\ud0c0"
    ],
    "name:und_x_variant":[
        "Alite",
        "Alita"
    ],
    "wof:name":"Alita",
    "wof:placetype":"locality"
},
  "geometry": {"coordinates":[38.885,-11.24583],"type":"Point"}
}