{
  "type": "Feature",
  "properties": {
    "gn:admin1_code":"9",
    "gn:asciiname":"Chefe Mucolo",
    "gn:country_code":"MZ",
    "gn:dem":344,
    "gn:feature_class":"P",
    "gn:feature_code":"PPL",
    "gn:name":"Chefe Mucolo",
    "gn:population":0,
    "gn:timezone":"Africa/Maputo",
    "iso:country":"MZ",
    "wof:name":"Chefe Mucolo",
    "wof:placetype":"locality"
},
  "geometry": {"coordinates":[37.87806,-16.00694],"type":"Point"}
}