{
  "type": "Feature",
  "properties": {
    "gn:admin1_code":"1",
    "gn:asciiname":"Regulo Nevila",
    "gn:cc2":"MZ",
    "gn:country_code":"MZ",
    "gn:dem":483,
    "gn:feature_class":"P",
    "gn:feature_code":"PPL",
    "gn:name":"R\u00e9gulo Nevila",
    "gn:population":0,
    "gn:timezone":"Africa/Maputo",
    "iso:country":"MZ",
    "name:und_x_variant":[
        "Nevila",
        "R\u00e9gulo Nevila"
    ],
    "wof:name":"Regulo Nevila",
    "wof:placetype":"locality"
},
  "geometry": {"coordinates":[38.63444000000001,-13.66833],"type":"Point"}
}