{
  "type": "Feature",
  "properties": {
    "gn:admin1_code":"0",
    "gn:asciiname":"Mocorrene",
    "gn:country_code":"MZ",
    "gn:dem":20,
    "gn:feature_class":"P",
    "gn:feature_code":"PPL",
    "gn:name":"Mocorrene",
    "gn:population":0,
    "gn:timezone":"Africa/Maputo",
    "iso:country":"MZ",
    "wof:name":"Mocorrene",
    "wof:placetype":"locality"
},
  "geometry": {"coordinates":[40.58333,-14.23333],"type":"Point"}
}