{
  "type": "Feature",
  "properties": {
    "gn:admin1_code":"10",
    "gn:asciiname":"Nhantulo",
    "gn:country_code":"MZ",
    "gn:dem":797,
    "gn:feature_class":"P",
    "gn:feature_code":"PPL",
    "gn:name":"Nhantulo",
    "gn:population":0,
    "gn:timezone":"Africa/Maputo",
    "iso:country":"MZ",
    "wof:name":"Nhantulo",
    "wof:placetype":"locality"
},
  "geometry": {"coordinates":[33.28944,-17.53111],"type":"Point"}
}