{
  "type": "Feature",
  "properties": {
    "gn:admin1_code":"10.0",
    "gn:asciiname":"Quembo",
    "gn:country_code":"MZ",
    "gn:dem":410,
    "gn:feature_class":"P",
    "gn:feature_code":"PPL",
    "gn:name":"Quembo",
    "gn:population":0,
    "gn:timezone":"Africa/Maputo",
    "iso:country":"MZ",
    "wof:name":"Quembo",
    "wof:placetype":"locality"
},
  "geometry": {"coordinates":[33.54139,-18.63111],"type":"Point"}
}