{
  "type": "Feature",
  "properties": {
    "gn:admin1_code":"6",
    "gn:asciiname":"Jorje",
    "gn:country_code":"MZ",
    "gn:dem":706,
    "gn:feature_class":"P",
    "gn:feature_code":"PPL",
    "gn:name":"Jorje",
    "gn:population":0,
    "gn:timezone":"Africa/Maputo",
    "iso:country":"MZ",
    "wof:name":"Jorje",
    "wof:placetype":"locality"
},
  "geometry": {"coordinates":[37.72889,-14.98444],"type":"Point"}
}