{
  "type": "Feature",
  "properties": {
    "gn:admin1_code":"9.0",
    "gn:asciiname":"Sombo",
    "gn:country_code":"MZ",
    "gn:dem":1,
    "gn:feature_class":"P",
    "gn:feature_code":"PPL",
    "gn:name":"Sombo",
    "gn:population":0,
    "gn:timezone":"Africa/Maputo",
    "iso:country":"MZ",
    "wof:name":"Sombo",
    "wof:placetype":"locality"
},
  "geometry": {"coordinates":[36.33806,-18.62444],"type":"Point"}
}