{
  "type": "Feature",
  "properties": {
    "gn:admin1_code":"6",
    "gn:asciiname":"Mucuna",
    "gn:cc2":"MZ",
    "gn:country_code":"MZ",
    "gn:dem":617,
    "gn:feature_class":"P",
    "gn:feature_code":"PPL",
    "gn:name":"Mucuna",
    "gn:population":0,
    "gn:timezone":"Africa/Maputo",
    "iso:country":"MZ",
    "name:ara_x_preferred":[
        "\u0645\u064a\u0642\u0648\u0646\u0629"
    ],
    "name:cat_x_preferred":[
        "Mucuna"
    ],
    "name:ceb_x_preferred":[
        "Mucuna"
    ],
    "name:ces_x_preferred":[
        "Mukuna"
    ],
    "name:fas_x_preferred":[
        "\u0645\u0627\u06a9\u0627\u0646\u0627"
    ],
    "name:fra_x_preferred":[
        "Mucuna"
    ],
    "name:ita_x_preferred":[
        "Mucuna"
    ],
    "name:jpn_x_preferred":[
        "\u30c8\u30d3\u30ab\u30ba\u30e9\u5c5e"
    ],
    "name:kor_x_preferred":[
        "\uc6b0\ub2e8\ucf69\uc18d"
    ],
    "name:pol_x_preferred":[
        "\u015awierzbiec"
    ],
    "name:por_x_preferred":[
        "Mucuna"
    ],
    "name:rus_x_preferred":[
        "\u041c\u0443\u043a\u0443\u043d\u0430"
    ],
    "name:spa_x_preferred":[
        "Mucuna"
    ],
    "name:swe_x_preferred":[
        "Mucuna"
    ],
    "name:tel_x_preferred":[
        "\u0c2e\u0c41\u0c15\u0c41\u0c28\u0c3e"
    ],
    "name:tha_x_preferred":[
        "\u0e2a\u0e01\u0e38\u0e25\u0e2b\u0e21\u0e32\u0e21\u0e38\u0e48\u0e22"
    ],
    "name:ton_x_preferred":[
        "V\u0101lai"
    ],
    "name:und_x_variant":[
        "Mcuna",
        "Mucuna"
    ],
    "name:war_x_preferred":[
        "Mucuna"
    ],
    "name:zho_x_preferred":[
        "\u9ece\u8c46\u5c5e"
    ],
    "wof:name":"Mucuna",
    "wof:placetype":"locality"
},
  "geometry": {"coordinates":[37.16917,-14.82417],"type":"Point"}
}