{
  "type": "Feature",
  "properties": {
    "gn:admin1_code":"6",
    "gn:asciiname":"Mucuna",
    "gn:cc2":"MZ",
    "gn:country_code":"MZ",
    "gn:dem":617,
    "gn:feature_class":"P",
    "gn:feature_code":"PPL",
    "gn:name":"Mucuna",
    "gn:population":0,
    "gn:timezone":"Africa/Maputo",
    "iso:country":"MZ",
    "name:und_x_variant":[
        "Mcuna",
        "Mucuna"
    ],
    "wof:name":"Mucuna",
    "wof:placetype":"locality"
},
  "geometry": {"coordinates":[37.16917,-14.82417],"type":"Point"}
}