{
  "type": "Feature",
  "properties": {
    "gn:admin1_code":"7",
    "gn:asciiname":"Chefe Mevava",
    "gn:country_code":"MZ",
    "gn:dem":664,
    "gn:feature_class":"P",
    "gn:feature_code":"PPL",
    "gn:name":"Chefe Mevava",
    "gn:population":0,
    "gn:timezone":"Africa/Maputo",
    "iso:country":"MZ",
    "wof:name":"Chefe Mevava",
    "wof:placetype":"locality"
},
  "geometry": {"coordinates":[36.52417,-14.98222],"type":"Point"}
}