{
  "type": "Feature",
  "properties": {
    "gn:admin1_code":"2.0",
    "gn:asciiname":"Chefe Munhaca",
    "gn:country_code":"MZ",
    "gn:dem":12,
    "gn:feature_class":"P",
    "gn:feature_code":"PPL",
    "gn:name":"Chefe Munhaca",
    "gn:population":0,
    "gn:timezone":"Africa/Maputo",
    "iso:country":"MZ",
    "wof:name":"Chefe Munhaca",
    "wof:placetype":"locality"
},
  "geometry": {"coordinates":[33.49556,-24.80528],"type":"Point"}
}