{
  "type": "Feature",
  "properties": {
    "gn:admin1_code":"3.0",
    "gn:asciiname":"Cabo Mahate",
    "gn:country_code":"MZ",
    "gn:dem":107,
    "gn:feature_class":"P",
    "gn:feature_code":"PPL",
    "gn:name":"Cabo Mahate",
    "gn:population":0,
    "gn:timezone":"Africa/Maputo",
    "iso:country":"MZ",
    "wof:name":"Cabo Mahate",
    "wof:placetype":"locality"
},
  "geometry": {"coordinates":[35.04806,-23.19056],"type":"Point"}
}