{
  "type": "Feature",
  "properties": {
    "gn:admin1_code":"9",
    "gn:asciiname":"Nihoma",
    "gn:country_code":"MZ",
    "gn:dem":671,
    "gn:feature_class":"P",
    "gn:feature_code":"PPL",
    "gn:name":"Nihoma",
    "gn:population":0,
    "gn:timezone":"Africa/Maputo",
    "iso:country":"MZ",
    "wof:name":"Nihoma",
    "wof:placetype":"locality"
},
  "geometry": {"coordinates":[36.81417,-15.15083],"type":"Point"}
}