{
  "type": "Feature",
  "properties": {
    "gn:admin1_code":"0.0",
    "gn:asciiname":"Xuambo",
    "gn:country_code":"MZ",
    "gn:dem":783,
    "gn:feature_class":"P",
    "gn:feature_code":"PPL",
    "gn:name":"Xuambo",
    "gn:population":0,
    "gn:timezone":"Africa/Maputo",
    "iso:country":"MZ",
    "wof:name":"Xuambo",
    "wof:placetype":"locality"
},
  "geometry": {"coordinates":[31.43333,-15.15],"type":"Point"}
}