{
  "type": "Feature",
  "properties": {
    "gn:admin1_code":"10",
    "gn:asciiname":"Jaquessene",
    "gn:country_code":"MZ",
    "gn:dem":717,
    "gn:feature_class":"P",
    "gn:feature_code":"PPL",
    "gn:name":"Jaquessene",
    "gn:population":0,
    "gn:timezone":"Africa/Maputo",
    "iso:country":"MZ",
    "name:por_x_preferred":[
        "Jaquessene"
    ],
    "wof:name":"Jaquessene",
    "wof:placetype":"locality"
},
  "geometry": {"coordinates":[32.91833,-20.22],"type":"Point"}
}