{
  "type": "Feature",
  "properties": {
    "gn:admin1_code":"3.0",
    "gn:asciiname":"Sumbulucuane",
    "gn:country_code":"MZ",
    "gn:dem":196,
    "gn:feature_class":"P",
    "gn:feature_code":"PPL",
    "gn:name":"Sumbulucuane",
    "gn:population":0,
    "gn:timezone":"Africa/Maputo",
    "iso:country":"MZ",
    "wof:name":"Sumbulucuane",
    "wof:placetype":"locality"
},
  "geometry": {"coordinates":[34.08111,-21.86639],"type":"Point"}
}