{
  "type": "Feature",
  "properties": {
    "gn:admin1_code":"9",
    "gn:asciiname":"Musuruco",
    "gn:country_code":"MZ",
    "gn:dem":11,
    "gn:feature_class":"P",
    "gn:feature_code":"PPL",
    "gn:name":"Musuruco",
    "gn:population":0,
    "gn:timezone":"Africa/Maputo",
    "iso:country":"MZ",
    "wof:name":"Musuruco",
    "wof:placetype":"locality"
},
  "geometry": {"coordinates":[37.70556,-17.41389],"type":"Point"}
}