{
  "type": "Feature",
  "properties": {
    "gn:admin1_code":"1.0",
    "gn:asciiname":"Quimbundi",
    "gn:country_code":"MZ",
    "gn:dem":718,
    "gn:feature_class":"P",
    "gn:feature_code":"PPL",
    "gn:name":"Quimbundi",
    "gn:population":0,
    "gn:timezone":"Africa/Maputo",
    "iso:country":"MZ",
    "wof:name":"Quimbundi",
    "wof:placetype":"locality"
},
  "geometry": {"coordinates":[39.60667,-11.64694],"type":"Point"}
}