{
  "type": "Feature",
  "properties": {
    "gn:admin1_code":"1",
    "gn:asciiname":"Chunge",
    "gn:country_code":"MZ",
    "gn:dem":221,
    "gn:feature_class":"P",
    "gn:feature_code":"PPL",
    "gn:name":"Chung\u00ea",
    "gn:population":0,
    "gn:timezone":"Africa/Maputo",
    "iso:country":"MZ",
    "wof:name":"Chunge",
    "wof:placetype":"locality"
},
  "geometry": {"coordinates":[39.91361,-11.22722],"type":"Point"}
}