{
  "type": "Feature",
  "properties": {
    "gn:admin1_code":"5.0",
    "gn:asciiname":"Tandigua",
    "gn:country_code":"MZ",
    "gn:dem":21,
    "gn:feature_class":"P",
    "gn:feature_code":"PPL",
    "gn:name":"Tandigua",
    "gn:population":0,
    "gn:timezone":"Africa/Maputo",
    "iso:country":"MZ",
    "wof:name":"Tandigua",
    "wof:placetype":"locality"
},
  "geometry": {"coordinates":[35.7075,-18.07056],"type":"Point"}
}