{
  "type": "Feature",
  "properties": {
    "gn:admin1_code":"1",
    "gn:asciiname":"Colue",
    "gn:country_code":"MZ",
    "gn:dem":281,
    "gn:feature_class":"P",
    "gn:feature_code":"PPL",
    "gn:name":"Col\u00fa\u00e8",
    "gn:population":0,
    "gn:timezone":"Africa/Maputo",
    "iso:country":"MZ",
    "wof:name":"Colue",
    "wof:placetype":"locality"
},
  "geometry": {"coordinates":[40.0175,-12.90917],"type":"Point"}
}