{
  "type": "Feature",
  "properties": {
    "gn:admin1_code":"5.0",
    "gn:asciiname":"Jorge",
    "gn:country_code":"MZ",
    "gn:dem":14,
    "gn:feature_class":"P",
    "gn:feature_code":"PPL",
    "gn:name":"Jorge",
    "gn:population":0,
    "gn:timezone":"Africa/Maputo",
    "iso:country":"MZ",
    "name:bre_x_preferred":[
        "Jorge"
    ],
    "name:deu_x_preferred":[
        "Jorge"
    ],
    "name:hye_x_preferred":[
        "\u053d\u0578\u0580\u056d\u0565"
    ],
    "name:nor_x_preferred":[
        "Jorge"
    ],
    "name:spa_x_preferred":[
        "Jorge"
    ],
    "wof:name":"Jorge",
    "wof:placetype":"locality"
},
  "geometry": {"coordinates":[35.85361,-18.23472000000001],"type":"Point"}
}