{
  "type": "Feature",
  "properties": {
    "gn:admin1_code":"1",
    "gn:asciiname":"Ando",
    "gn:country_code":"MZ",
    "gn:dem":6,
    "gn:feature_class":"P",
    "gn:feature_code":"PPL",
    "gn:name":"Ando",
    "gn:population":0,
    "gn:timezone":"Africa/Maputo",
    "iso:country":"MZ",
    "name:ceb_x_preferred":[
        "Ando"
    ],
    "name:deu_x_preferred":[
        "Ando"
    ],
    "name:fra_x_preferred":[
        "Ando"
    ],
    "name:heb_x_preferred":[
        "\u05d0\u05e0\u05d3\u05d5"
    ],
    "name:ita_x_preferred":[
        "Ando"
    ],
    "name:rus_x_preferred":[
        "\u0410\u043d\u0434\u043e"
    ],
    "name:swe_x_preferred":[
        "Ando"
    ],
    "name:ukr_x_preferred":[
        "\u0410\u043d\u0434\u043e"
    ],
    "wof:name":"Ando",
    "wof:placetype":"locality"
},
  "geometry": {"coordinates":[40.44722,-12.88833],"type":"Point"}
}