{
  "type": "Feature",
  "properties": {
    "gn:admin1_code":"5.0",
    "gn:asciiname":"Tito",
    "gn:country_code":"MZ",
    "gn:dem":52,
    "gn:feature_class":"P",
    "gn:feature_code":"PPL",
    "gn:name":"Tito",
    "gn:population":0,
    "gn:timezone":"Africa/Maputo",
    "iso:country":"MZ",
    "wof:name":"Tito",
    "wof:placetype":"locality"
},
  "geometry": {"coordinates":[34.89333,-18.12083],"type":"Point"}
}