{
  "type": "Feature",
  "properties": {
    "iso:country":"MZ",
    "name:ell_x_preferred":[
        "\u03a0\u03b1\u03c1\u03b1\u03bb\u03af\u03b1 \u03a0\u03c1\u03ac\u03b9\u03b1 \u03bd\u03c4\u03bf \u03a3\u03ac\u03b9-\u03a3\u03ac\u03b9"
    ],
    "name:eng_x_preferred":[
        "Praia do Xai-Xai"
    ],
    "name:pol_x_preferred":[
        "Praia do Xai-Xai"
    ],
    "name:spa_x_preferred":[
        "Playa de Xai-Xai"
    ],
    "qs:gn_pop":0,
    "qs:name":"Praia do Xai-Xai",
    "qs:name_adm0":"Mo\u00e7ambique",
    "qs:name_adm1":"Gaza",
    "qs:photos":91,
    "qs:photos_1k":18,
    "qs:photos_9k":1,
    "qs:photos_9r":3,
    "qs:photos_all":91,
    "qs:photos_sr":3,
    "qs:placetype":"Town",
    "qs:pop_sr":"0",
    "qs:woe_adm0":23424902,
    "wd:wordcount":80,
    "wof:name":"Praia do Xai-Xai",
    "wof:placetype":"locality"
},
  "geometry": {"coordinates":[33.716182,-25.100833],"type":"Point"}
}