{
  "type": "Feature",
  "properties": {
    "gn:admin1_code":"3.0",
    "gn:asciiname":"M. Mubai",
    "gn:country_code":"MZ",
    "gn:dem":65,
    "gn:feature_class":"P",
    "gn:feature_code":"PPL",
    "gn:name":"M. Mubai",
    "gn:population":0,
    "gn:timezone":"Africa/Maputo",
    "iso:country":"MZ",
    "wof:name":"M. Mubai",
    "wof:placetype":"locality"
},
  "geometry": {"coordinates":[34.09111,-24.31528],"type":"Point"}
}