{
  "type": "Feature",
  "properties": {
    "gn:admin1_code":"1",
    "gn:asciiname":"Ntolia",
    "gn:country_code":"MZ",
    "gn:dem":573,
    "gn:feature_class":"P",
    "gn:feature_code":"PPL",
    "gn:name":"Ntolia",
    "gn:population":0,
    "gn:timezone":"Africa/Maputo",
    "iso:country":"MZ",
    "wof:name":"Ntolia",
    "wof:placetype":"locality"
},
  "geometry": {"coordinates":[38.46944000000001,-13.3775],"type":"Point"}
}