{
  "type": "Feature",
  "properties": {
    "gn:admin1_code":"7",
    "gn:asciiname":"Beira-Rio",
    "gn:country_code":"MZ",
    "gn:dem":575,
    "gn:feature_class":"P",
    "gn:feature_code":"PPL",
    "gn:name":"Beira-Rio",
    "gn:population":0,
    "gn:timezone":"Africa/Maputo",
    "iso:country":"MZ",
    "wof:name":"Beira-Rio",
    "wof:placetype":"locality"
},
  "geometry": {"coordinates":[36.70278,-14.78444],"type":"Point"}
}