{
  "type": "Feature",
  "properties": {
    "gn:admin1_code":"3",
    "gn:asciiname":"Chelene",
    "gn:country_code":"MZ",
    "gn:dem":173,
    "gn:feature_class":"P",
    "gn:feature_code":"PPL",
    "gn:name":"Chelene",
    "gn:population":0,
    "gn:timezone":"Africa/Maputo",
    "iso:country":"MZ",
    "wof:name":"Chelene",
    "wof:placetype":"locality"
},
  "geometry": {"coordinates":[34.46333,-21.82306],"type":"Point"}
}