{
  "type": "Feature",
  "properties": {
    "gn:admin1_code":"2.0",
    "gn:asciiname":"Assane",
    "gn:country_code":"MZ",
    "gn:dem":208,
    "gn:feature_class":"P",
    "gn:feature_code":"PPL",
    "gn:name":"Assane",
    "gn:population":0,
    "gn:timezone":"Africa/Maputo",
    "iso:country":"MZ",
    "name:fra_x_preferred":[
        "Assane"
    ],
    "wof:name":"Assane",
    "wof:placetype":"locality"
},
  "geometry": {"coordinates":[31.47444,-22.30222],"type":"Point"}
}