{
  "type": "Feature",
  "properties": {
    "gn:admin1_code":"4",
    "gn:asciiname":"Sao Joao de Deus",
    "gn:country_code":"MZ",
    "gn:dem":23,
    "gn:feature_class":"P",
    "gn:feature_code":"PPL",
    "gn:name":"S\u00e3o Jo\u00e3o de Deus",
    "gn:population":0,
    "gn:timezone":"Africa/Maputo",
    "iso:country":"MZ",
    "wof:name":"Sao Joao de Deus",
    "wof:placetype":"locality"
},
  "geometry": {"coordinates":[32.56610999999999,-25.85833],"type":"Point"}
}