{
  "type": "Feature",
  "properties": {
    "gn:admin1_code":"4",
    "gn:asciiname":"Cocoisa",
    "gn:country_code":"MZ",
    "gn:dem":151,
    "gn:feature_class":"P",
    "gn:feature_code":"PPL",
    "gn:name":"Cocoisa",
    "gn:population":0,
    "gn:timezone":"Africa/Maputo",
    "iso:country":"MZ",
    "wof:name":"Cocoisa",
    "wof:placetype":"locality"
},
  "geometry": {"coordinates":[32.07139,-24.41639],"type":"Point"}
}