{
  "type": "Feature",
  "properties": {
    "gn:admin1_code":"7.0",
    "gn:asciiname":"Sole",
    "gn:country_code":"MZ",
    "gn:dem":822,
    "gn:feature_class":"P",
    "gn:feature_code":"PPL",
    "gn:name":"Sole",
    "gn:population":0,
    "gn:timezone":"Africa/Maputo",
    "iso:country":"MZ",
    "name:ceb_x_preferred":[
        "Sole"
    ],
    "name:deu_x_preferred":[
        "Sole"
    ],
    "name:fra_x_preferred":[
        "Sole"
    ],
    "name:ita_x_preferred":[
        "Sole"
    ],
    "name:swe_x_preferred":[
        "Sole"
    ],
    "wof:name":"Sole",
    "wof:placetype":"locality"
},
  "geometry": {"coordinates":[37.51472,-13.19389],"type":"Point"}
}