{
  "type": "Feature",
  "properties": {
    "gn:admin1_code":"3.0",
    "gn:asciiname":"Cabo Guicundo",
    "gn:country_code":"MZ",
    "gn:dem":89,
    "gn:feature_class":"P",
    "gn:feature_code":"PPL",
    "gn:name":"Cabo Guicundo",
    "gn:population":0,
    "gn:timezone":"Africa/Maputo",
    "iso:country":"MZ",
    "wof:name":"Cabo Guicundo",
    "wof:placetype":"locality"
},
  "geometry": {"coordinates":[35.22806,-24.15083],"type":"Point"}
}