{
  "type": "Feature",
  "properties": {
    "gn:admin1_code":"1",
    "gn:asciiname":"Matumula",
    "gn:country_code":"MZ",
    "gn:dem":144,
    "gn:feature_class":"P",
    "gn:feature_code":"PPL",
    "gn:name":"Matumula",
    "gn:population":0,
    "gn:timezone":"Africa/Maputo",
    "iso:country":"MZ",
    "wof:name":"Matumula",
    "wof:placetype":"locality"
},
  "geometry": {"coordinates":[39.57361,-11.08861],"type":"Point"}
}