{
  "type": "Feature",
  "properties": {
    "gn:admin1_code":"2.0",
    "gn:asciiname":"Ernesto",
    "gn:country_code":"MZ",
    "gn:dem":49,
    "gn:feature_class":"P",
    "gn:feature_code":"PPL",
    "gn:name":"Ernesto",
    "gn:population":0,
    "gn:timezone":"Africa/Maputo",
    "iso:country":"MZ",
    "name:bre_x_preferred":[
        "Ernesto"
    ],
    "name:deu_x_preferred":[
        "Ernesto"
    ],
    "name:fra_x_preferred":[
        "Ernesto"
    ],
    "name:ita_x_preferred":[
        "Ernesto"
    ],
    "name:spa_x_preferred":[
        "Ernesto"
    ],
    "wof:name":"Ernesto",
    "wof:placetype":"locality"
},
  "geometry": {"coordinates":[32.77278,-24.4625],"type":"Point"}
}