{
  "type": "Feature",
  "properties": {
    "gn:admin1_code":"9",
    "gn:asciiname":"Magige",
    "gn:country_code":"MZ",
    "gn:dem":723,
    "gn:feature_class":"P",
    "gn:feature_code":"PPL",
    "gn:name":"Magige",
    "gn:population":0,
    "gn:timezone":"Africa/Maputo",
    "iso:country":"MZ",
    "wof:name":"Magige",
    "wof:placetype":"locality"
},
  "geometry": {"coordinates":[36.74306,-15.32861],"type":"Point"}
}