{
  "type": "Feature",
  "properties": {
    "gn:admin1_code":"2.0",
    "gn:asciiname":"Makhuane",
    "gn:country_code":"MZ",
    "gn:dem":49,
    "gn:feature_class":"P",
    "gn:feature_code":"PPL",
    "gn:name":"Makhuane",
    "gn:population":0,
    "gn:timezone":"Africa/Maputo",
    "iso:country":"MZ",
    "wof:name":"Makhuane",
    "wof:placetype":"locality"
},
  "geometry": {"coordinates":[33.18222,-25.07194],"type":"Point"}
}