{
  "type": "Feature",
  "properties": {
    "gn:admin1_code":"3",
    "gn:asciiname":"Longane",
    "gn:country_code":"MZ",
    "gn:dem":167,
    "gn:feature_class":"P",
    "gn:feature_code":"PPL",
    "gn:name":"Longane",
    "gn:population":0,
    "gn:timezone":"Africa/Maputo",
    "iso:country":"MZ",
    "wof:name":"Longane",
    "wof:placetype":"locality"
},
  "geometry": {"coordinates":[34.09556,-21.96806],"type":"Point"}
}