{
  "type": "Feature",
  "properties": {
    "gn:admin1_code":"9",
    "gn:asciiname":"Corongo",
    "gn:country_code":"MZ",
    "gn:dem":62,
    "gn:feature_class":"P",
    "gn:feature_code":"PPL",
    "gn:name":"Corongo",
    "gn:population":0,
    "gn:timezone":"Africa/Maputo",
    "iso:country":"MZ",
    "name:ceb_x_preferred":[
        "Corongo"
    ],
    "name:fra_x_preferred":[
        "Corongo"
    ],
    "name:ita_x_preferred":[
        "Corongo"
    ],
    "name:lit_x_preferred":[
        "Korongas"
    ],
    "name:por_x_preferred":[
        "Corongo"
    ],
    "name:que_x_preferred":[
        "Quriyunka"
    ],
    "name:spa_x_preferred":[
        "Corongo"
    ],
    "name:war_x_preferred":[
        "Corongo"
    ],
    "name:zho_x_preferred":[
        "\u79d1\u9f8d\u6208"
    ],
    "wof:name":"Corongo",
    "wof:placetype":"locality"
},
  "geometry": {"coordinates":[37.64222,-17.12306],"type":"Point"}
}