{
  "type": "Feature",
  "properties": {
    "gn:admin1_code":"7",
    "gn:asciiname":"Luhulo",
    "gn:cc2":"MZ",
    "gn:country_code":"MZ",
    "gn:dem":591,
    "gn:feature_class":"P",
    "gn:feature_code":"PPL",
    "gn:name":"Luhulo",
    "gn:population":0,
    "gn:timezone":"Africa/Maputo",
    "iso:country":"MZ",
    "name:und_x_variant":[
        "Luhula",
        "Luhulo"
    ],
    "wof:name":"Luhulo",
    "wof:placetype":"locality"
},
  "geometry": {"coordinates":[35.0325,-12.49333],"type":"Point"}
}