{
  "type": "Feature",
  "properties": {
    "gn:admin1_code":"1",
    "gn:asciiname":"Ntola",
    "gn:country_code":"MZ",
    "gn:dem":398,
    "gn:feature_class":"P",
    "gn:feature_code":"PPL",
    "gn:name":"Ntola",
    "gn:population":0,
    "gn:timezone":"Africa/Maputo",
    "iso:country":"MZ",
    "wof:name":"Ntola",
    "wof:placetype":"locality"
},
  "geometry": {"coordinates":[38.65,-12.63028],"type":"Point"}
}