{
  "type": "Feature",
  "properties": {
    "gn:admin1_code":"10",
    "gn:asciiname":"Bulau",
    "gn:country_code":"MZ",
    "gn:dem":306,
    "gn:feature_class":"P",
    "gn:feature_code":"PPL",
    "gn:name":"Bulau",
    "gn:population":0,
    "gn:timezone":"Africa/Maputo",
    "iso:country":"MZ",
    "wof:name":"Bulau",
    "wof:placetype":"locality"
},
  "geometry": {"coordinates":[33.36111,-16.81194],"type":"Point"}
}