{
  "type": "Feature",
  "properties": {
    "gn:admin1_code":"3",
    "gn:asciiname":"Massinhe",
    "gn:cc2":"MZ",
    "gn:country_code":"MZ",
    "gn:dem":71,
    "gn:feature_class":"P",
    "gn:feature_code":"PPL",
    "gn:name":"Massinhe",
    "gn:population":0,
    "gn:timezone":"Africa/Maputo",
    "iso:country":"MZ",
    "name:und_x_variant":[
        "Nhiuane",
        "Massinhe"
    ],
    "wof:name":"Massinhe",
    "wof:placetype":"locality"
},
  "geometry": {"coordinates":[34.03583,-23.65333],"type":"Point"}
}