{
  "type": "Feature",
  "properties": {
    "gn:admin1_code":"3.0",
    "gn:asciiname":"Popina Nhatsave",
    "gn:country_code":"MZ",
    "gn:dem":86,
    "gn:feature_class":"P",
    "gn:feature_code":"PPL",
    "gn:name":"Popina Nhatsave",
    "gn:population":0,
    "gn:timezone":"Africa/Maputo",
    "iso:country":"MZ",
    "wof:name":"Popina Nhatsave",
    "wof:placetype":"locality"
},
  "geometry": {"coordinates":[34.51194,-24.16056],"type":"Point"}
}