{
  "type": "Feature",
  "properties": {
    "gn:admin1_code":"10",
    "gn:asciiname":"Birana",
    "gn:country_code":"MZ",
    "gn:dem":183,
    "gn:feature_class":"P",
    "gn:feature_code":"PPL",
    "gn:name":"Birana",
    "gn:population":0,
    "gn:timezone":"Africa/Maputo",
    "iso:country":"MZ",
    "wof:name":"Birana",
    "wof:placetype":"locality"
},
  "geometry": {"coordinates":[33.58278,-21.00444],"type":"Point"}
}