{
  "type": "Feature",
  "properties": {
    "gn:admin1_code":"2",
    "gn:asciiname":"Languene",
    "gn:country_code":"MZ",
    "gn:dem":20,
    "gn:feature_class":"P",
    "gn:feature_code":"PPL",
    "gn:name":"Languene",
    "gn:population":0,
    "gn:timezone":"Africa/Maputo",
    "iso:country":"MZ",
    "wof:name":"Languene",
    "wof:placetype":"locality"
},
  "geometry": {"coordinates":[33.30583,-24.6825],"type":"Point"}
}