{
  "type": "Feature",
  "properties": {
    "gn:admin1_code":"10",
    "gn:asciiname":"Magomba",
    "gn:country_code":"MZ",
    "gn:dem":331,
    "gn:feature_class":"P",
    "gn:feature_code":"PPL",
    "gn:name":"Magomba",
    "gn:population":0,
    "gn:timezone":"Africa/Maputo",
    "iso:country":"MZ",
    "wof:name":"Magomba",
    "wof:placetype":"locality"
},
  "geometry": {"coordinates":[33.20972,-20.98528],"type":"Point"}
}