{
  "type": "Feature",
  "properties": {
    "gn:admin1_code":"6.0",
    "gn:asciiname":"Tocoloa",
    "gn:country_code":"MZ",
    "gn:dem":60,
    "gn:feature_class":"P",
    "gn:feature_code":"PPL",
    "gn:name":"Tocol\u00f4a",
    "gn:population":0,
    "gn:timezone":"Africa/Maputo",
    "iso:country":"MZ",
    "wof:name":"Tocoloa",
    "wof:placetype":"locality"
},
  "geometry": {"coordinates":[39.05111,-16.58],"type":"Point"}
}