{
  "type": "Feature",
  "properties": {
    "gn:admin1_code":"6",
    "gn:asciiname":"Muculoene",
    "gn:country_code":"MZ",
    "gn:dem":392,
    "gn:feature_class":"P",
    "gn:feature_code":"PPL",
    "gn:name":"Muculoene",
    "gn:population":0,
    "gn:timezone":"Africa/Maputo",
    "iso:country":"MZ",
    "wof:name":"Muculoene",
    "wof:placetype":"locality"
},
  "geometry": {"coordinates":[39.37278,-14.94139],"type":"Point"}
}