{
  "type": "Feature",
  "properties": {
    "gn:admin1_code":"2",
    "gn:asciiname":"Mangueze",
    "gn:country_code":"MZ",
    "gn:dem":168,
    "gn:feature_class":"P",
    "gn:feature_code":"PPL",
    "gn:name":"Mangueze",
    "gn:population":0,
    "gn:timezone":"Africa/Maputo",
    "iso:country":"MZ",
    "wof:name":"Mangueze",
    "wof:placetype":"locality"
},
  "geometry": {"coordinates":[32.87417,-21.78306],"type":"Point"}
}