{
  "type": "Feature",
  "properties": {
    "gn:admin1_code":"1",
    "gn:asciiname":"Nampiali",
    "gn:country_code":"MZ",
    "gn:dem":409,
    "gn:feature_class":"P",
    "gn:feature_code":"PPL",
    "gn:name":"Nampiali",
    "gn:population":0,
    "gn:timezone":"Africa/Maputo",
    "iso:country":"MZ",
    "wof:name":"Nampiali",
    "wof:placetype":"locality"
},
  "geometry": {"coordinates":[39.59278,-11.21889],"type":"Point"}
}