{
  "type": "Feature",
  "properties": {
    "gn:admin1_code":"1.0",
    "gn:asciiname":"Tutuma",
    "gn:country_code":"MZ",
    "gn:dem":527,
    "gn:feature_class":"P",
    "gn:feature_code":"PPL",
    "gn:name":"Tutuma",
    "gn:population":0,
    "gn:timezone":"Africa/Maputo",
    "iso:country":"MZ",
    "wof:name":"Tutuma",
    "wof:placetype":"locality"
},
  "geometry": {"coordinates":[38.81833,-12.99278],"type":"Point"}
}