{
  "type": "Feature",
  "properties": {
    "gn:admin1_code":"6",
    "gn:asciiname":"Cica",
    "gn:country_code":"MZ",
    "gn:dem":567,
    "gn:feature_class":"P",
    "gn:feature_code":"PPL",
    "gn:name":"Cica",
    "gn:population":0,
    "gn:timezone":"Africa/Maputo",
    "iso:country":"MZ",
    "wof:name":"Cica",
    "wof:placetype":"locality"
},
  "geometry": {"coordinates":[37.03528,-14.85278],"type":"Point"}
}