{
  "type": "Feature",
  "properties": {
    "gn:admin1_code":"6",
    "gn:asciiname":"Nuala",
    "gn:country_code":"MZ",
    "gn:dem":133,
    "gn:feature_class":"P",
    "gn:feature_code":"PPL",
    "gn:name":"Nuala",
    "gn:population":0,
    "gn:timezone":"Africa/Maputo",
    "iso:country":"MZ",
    "name:deu_x_preferred":[
        "Nuala"
    ],
    "name:fra_x_preferred":[
        "Nuala"
    ],
    "wof:name":"Nuala",
    "wof:placetype":"locality"
},
  "geometry": {"coordinates":[39.17556,-15.99028],"type":"Point"}
}