{
  "type": "Feature",
  "properties": {
    "gn:admin1_code":"2.0",
    "gn:asciiname":"F. Sinequico",
    "gn:country_code":"MZ",
    "gn:dem":39,
    "gn:feature_class":"P",
    "gn:feature_code":"PPL",
    "gn:name":"F. Sinequi\u00e7o",
    "gn:population":0,
    "gn:timezone":"Africa/Maputo",
    "iso:country":"MZ",
    "wof:name":"F. Sinequico",
    "wof:placetype":"locality"
},
  "geometry": {"coordinates":[34.2975,-24.66472000000001],"type":"Point"}
}