{
  "type": "Feature",
  "properties": {
    "gn:admin1_code":"3",
    "gn:asciiname":"Naite",
    "gn:country_code":"MZ",
    "gn:dem":16,
    "gn:feature_class":"P",
    "gn:feature_code":"PPL",
    "gn:name":"Naite",
    "gn:population":0,
    "gn:timezone":"Africa/Maputo",
    "iso:country":"MZ",
    "wof:name":"Naite",
    "wof:placetype":"locality"
},
  "geometry": {"coordinates":[35.12472,-21.68333],"type":"Point"}
}