{
  "type": "Feature",
  "properties": {
    "gn:admin1_code":"0",
    "gn:asciiname":"Nhapese",
    "gn:country_code":"MZ",
    "gn:dem":752,
    "gn:feature_class":"P",
    "gn:feature_code":"PPL",
    "gn:name":"Nhapese",
    "gn:population":0,
    "gn:timezone":"Africa/Maputo",
    "iso:country":"MZ",
    "wof:name":"Nhapese",
    "wof:placetype":"locality"
},
  "geometry": {"coordinates":[35.73333,-14.23333],"type":"Point"}
}