{
  "type": "Feature",
  "properties": {
    "gn:admin1_code":"0.0",
    "gn:asciiname":"Zafania",
    "gn:country_code":"MZ",
    "gn:dem":36,
    "gn:feature_class":"P",
    "gn:feature_code":"PPL",
    "gn:name":"Zafania",
    "gn:population":0,
    "gn:timezone":"Africa/Maputo",
    "iso:country":"MZ",
    "wof:name":"Zafania",
    "wof:placetype":"locality"
},
  "geometry": {"coordinates":[33.68333,-25.05],"type":"Point"}
}