{
  "type": "Feature",
  "properties": {
    "gn:admin1_code":"10",
    "gn:asciiname":"Chimuanza",
    "gn:country_code":"MZ",
    "gn:dem":399,
    "gn:feature_class":"P",
    "gn:feature_code":"PPL",
    "gn:name":"Chimuanza",
    "gn:population":0,
    "gn:timezone":"Africa/Maputo",
    "iso:country":"MZ",
    "wof:name":"Chimuanza",
    "wof:placetype":"locality"
},
  "geometry": {"coordinates":[34.08833,-17.48333],"type":"Point"}
}