{
  "type": "Feature",
  "properties": {
    "gn:admin1_code":"5.0",
    "gn:asciiname":"Zinharimue",
    "gn:country_code":"MZ",
    "gn:dem":105,
    "gn:feature_class":"P",
    "gn:feature_code":"PPL",
    "gn:name":"Zinharimue",
    "gn:population":0,
    "gn:timezone":"Africa/Maputo",
    "iso:country":"MZ",
    "wof:name":"Zinharimue",
    "wof:placetype":"locality"
},
  "geometry": {"coordinates":[33.92722,-19.99306],"type":"Point"}
}