{
  "type": "Feature",
  "properties": {
    "gn:admin1_code":"8",
    "gn:asciiname":"Conhenze",
    "gn:cc2":"MZ",
    "gn:country_code":"MZ",
    "gn:dem":169,
    "gn:feature_class":"P",
    "gn:feature_code":"PPL",
    "gn:name":"Conhenze",
    "gn:population":0,
    "gn:timezone":"Africa/Maputo",
    "iso:country":"MZ",
    "name:und_x_variant":[
        "Cohenze",
        "Conhenze"
    ],
    "wof:name":"Conhenze",
    "wof:placetype":"locality"
},
  "geometry": {"coordinates":[34.50583,-16.54444],"type":"Point"}
}