{
  "type": "Feature",
  "properties": {
    "gn:admin1_code":"7",
    "gn:asciiname":"Natenga",
    "gn:cc2":"MZ",
    "gn:country_code":"MZ",
    "gn:dem":538,
    "gn:feature_class":"P",
    "gn:feature_code":"PPL",
    "gn:name":"Natenga",
    "gn:population":0,
    "gn:timezone":"Africa/Maputo",
    "iso:country":"MZ",
    "name:und_x_variant":[
        "Nadenga",
        "Natenga"
    ],
    "wof:name":"Natenga",
    "wof:placetype":"locality"
},
  "geometry": {"coordinates":[34.93472,-12.555],"type":"Point"}
}