{
  "type": "Feature",
  "properties": {
    "gn:admin1_code":"5",
    "gn:asciiname":"Gimo",
    "gn:country_code":"MZ",
    "gn:dem":152,
    "gn:feature_class":"P",
    "gn:feature_code":"PPL",
    "gn:name":"Gimo",
    "gn:population":0,
    "gn:timezone":"Africa/Maputo",
    "iso:country":"MZ",
    "name:ita_x_preferred":[
        "Gimo"
    ],
    "wof:name":"Gimo",
    "wof:placetype":"locality"
},
  "geometry": {"coordinates":[34.19556,-20.31083],"type":"Point"}
}