{
  "type": "Feature",
  "properties": {
    "gn:admin1_code":"9",
    "gn:asciiname":"Novateiua",
    "gn:country_code":"MZ",
    "gn:dem":340,
    "gn:feature_class":"P",
    "gn:feature_code":"PPL",
    "gn:name":"Novateiua",
    "gn:population":0,
    "gn:timezone":"Africa/Maputo",
    "iso:country":"MZ",
    "wof:name":"Novateiua",
    "wof:placetype":"locality"
},
  "geometry": {"coordinates":[37.75861,-16.09806],"type":"Point"}
}