{
  "type": "Feature",
  "properties": {
    "gn:admin1_code":"8",
    "gn:asciiname":"Tomo-Gimo",
    "gn:country_code":"MZ",
    "gn:dem":1450,
    "gn:feature_class":"P",
    "gn:feature_code":"PPL",
    "gn:name":"Tomo-Gimo",
    "gn:population":0,
    "gn:timezone":"Africa/Maputo",
    "iso:country":"MZ",
    "wof:name":"Tomo-Gimo",
    "wof:placetype":"locality"
},
  "geometry": {"coordinates":[34.52194,-14.8925],"type":"Point"}
}