{
  "type": "Feature",
  "properties": {
    "gn:admin1_code":"6.0",
    "gn:asciiname":"Rupia",
    "gn:country_code":"MZ",
    "gn:dem":47,
    "gn:feature_class":"P",
    "gn:feature_code":"PPL",
    "gn:name":"R\u00fapia",
    "gn:population":0,
    "gn:timezone":"Africa/Maputo",
    "iso:country":"MZ",
    "wof:name":"Rupia",
    "wof:placetype":"locality"
},
  "geometry": {"coordinates":[40.55139000000001,-14.03],"type":"Point"}
}