{
  "type": "Feature",
  "properties": {
    "gn:admin1_code":"6.0",
    "gn:asciiname":"Francisco",
    "gn:country_code":"MZ",
    "gn:dem":188,
    "gn:feature_class":"P",
    "gn:feature_code":"PPL",
    "gn:name":"Francisco",
    "gn:population":0,
    "gn:timezone":"Africa/Maputo",
    "iso:country":"MZ",
    "wof:name":"Francisco",
    "wof:placetype":"locality"
},
  "geometry": {"coordinates":[38.93778,-16.03806],"type":"Point"}
}