{
  "type": "Feature",
  "properties": {
    "gn:admin1_code":"6.0",
    "gn:asciiname":"Francisco",
    "gn:country_code":"MZ",
    "gn:dem":188,
    "gn:feature_class":"P",
    "gn:feature_code":"PPL",
    "gn:name":"Francisco",
    "gn:population":0,
    "gn:timezone":"Africa/Maputo",
    "iso:country":"MZ",
    "name:arg_x_preferred":[
        "Francisco"
    ],
    "name:bre_x_preferred":[
        "Francisco"
    ],
    "name:deu_x_preferred":[
        "Francisco"
    ],
    "name:fra_x_preferred":[
        "Francisco"
    ],
    "name:jpn_x_preferred":[
        "\u30d5\u30e9\u30f3\u30b7\u30b9\u30b3"
    ],
    "name:kor_x_preferred":[
        "\ud504\ub780\uce58\uc2a4\ucf54"
    ],
    "name:nds_x_preferred":[
        "Francisco"
    ],
    "name:nld_x_preferred":[
        "Francisco"
    ],
    "name:nor_x_preferred":[
        "Francisco"
    ],
    "name:rus_x_preferred":[
        "\u0424\u0440\u0430\u043d\u0441\u0438\u0441\u043a\u043e"
    ],
    "name:spa_x_preferred":[
        "Francisco"
    ],
    "wof:name":"Francisco",
    "wof:placetype":"locality"
},
  "geometry": {"coordinates":[38.93778,-16.03806],"type":"Point"}
}