{
  "type": "Feature",
  "properties": {
    "gn:admin1_code":"10.0",
    "gn:asciiname":"Paulo",
    "gn:country_code":"MZ",
    "gn:dem":257,
    "gn:feature_class":"P",
    "gn:feature_code":"PPL",
    "gn:name":"Paulo",
    "gn:population":0,
    "gn:timezone":"Africa/Maputo",
    "iso:country":"MZ",
    "name:deu_x_preferred":[
        "Paulo"
    ],
    "name:fra_x_preferred":[
        "Paulo"
    ],
    "name:ita_x_preferred":[
        "Paulo"
    ],
    "name:jpn_x_preferred":[
        "\u30d1\u30a6\u30ed"
    ],
    "name:kor_x_preferred":[
        "\ud30c\uc6b8\ub8e8"
    ],
    "name:spa_x_preferred":[
        "Paulo"
    ],
    "wof:name":"Paulo",
    "wof:placetype":"locality"
},
  "geometry": {"coordinates":[33.48222,-20.84306],"type":"Point"}
}