{
  "type": "Feature",
  "properties": {
    "gn:admin1_code":"7.0",
    "gn:asciiname":"Uliane",
    "gn:cc2":"MZ",
    "gn:country_code":"MZ",
    "gn:dem":1418,
    "gn:feature_class":"P",
    "gn:feature_code":"PPL",
    "gn:name":"Uliane",
    "gn:population":0,
    "gn:timezone":"Africa/Maputo",
    "iso:country":"MZ",
    "name:und_x_variant":[
        "Tuliane",
        "Uliane"
    ],
    "wof:name":"Uliane",
    "wof:placetype":"locality"
},
  "geometry": {"coordinates":[35.15917,-11.59472],"type":"Point"}
}