{
  "type": "Feature",
  "properties": {
    "gn:admin1_code":"5",
    "gn:asciiname":"Calezera",
    "gn:country_code":"MZ",
    "gn:dem":228,
    "gn:feature_class":"P",
    "gn:feature_code":"PPL",
    "gn:name":"Calezera",
    "gn:population":0,
    "gn:timezone":"Africa/Maputo",
    "iso:country":"MZ",
    "wof:name":"Calezera",
    "wof:placetype":"locality"
},
  "geometry": {"coordinates":[34.28,-18.63861],"type":"Point"}
}