{
  "type": "Feature",
  "properties": {
    "gn:admin1_code":"3",
    "gn:asciiname":"Chavanguane",
    "gn:country_code":"MZ",
    "gn:dem":99,
    "gn:feature_class":"P",
    "gn:feature_code":"PPL",
    "gn:name":"Chavanguane",
    "gn:population":0,
    "gn:timezone":"Africa/Maputo",
    "iso:country":"MZ",
    "wof:name":"Chavanguane",
    "wof:placetype":"locality"
},
  "geometry": {"coordinates":[34.76194,-21.6625],"type":"Point"}
}