{
  "type": "Feature",
  "properties": {
    "gn:admin1_code":"6",
    "gn:asciiname":"Corrane",
    "gn:country_code":"MZ",
    "gn:dem":215,
    "gn:feature_class":"P",
    "gn:feature_code":"PPL",
    "gn:name":"Corrane",
    "gn:population":0,
    "gn:timezone":"Africa/Maputo",
    "iso:country":"MZ",
    "wof:name":"Corrane",
    "wof:placetype":"locality"
},
  "geometry": {"coordinates":[39.62444,-15.45944],"type":"Point"}
}