{
  "type": "Feature",
  "properties": {
    "gn:admin1_code":"3",
    "gn:asciiname":"Jimussene",
    "gn:country_code":"MZ",
    "gn:dem":186,
    "gn:feature_class":"P",
    "gn:feature_code":"PPL",
    "gn:name":"Jimussene",
    "gn:population":0,
    "gn:timezone":"Africa/Maputo",
    "iso:country":"MZ",
    "wof:name":"Jimussene",
    "wof:placetype":"locality"
},
  "geometry": {"coordinates":[34.35778,-21.92778],"type":"Point"}
}