{
  "type": "Feature",
  "properties": {
    "gn:admin1_code":"1",
    "gn:asciiname":"Muande",
    "gn:country_code":"MZ",
    "gn:dem":579,
    "gn:feature_class":"P",
    "gn:feature_code":"PPL",
    "gn:name":"Muande",
    "gn:population":0,
    "gn:timezone":"Africa/Maputo",
    "iso:country":"MZ",
    "wof:name":"Muande",
    "wof:placetype":"locality"
},
  "geometry": {"coordinates":[39.83389,-11.77278],"type":"Point"}
}