{
  "type": "Feature",
  "properties": {
    "gn:admin1_code":"6.0",
    "gn:asciiname":"Toleia",
    "gn:country_code":"MZ",
    "gn:dem":205,
    "gn:feature_class":"P",
    "gn:feature_code":"PPL",
    "gn:name":"Toleia",
    "gn:population":0,
    "gn:timezone":"Africa/Maputo",
    "iso:country":"MZ",
    "wof:name":"Toleia",
    "wof:placetype":"locality"
},
  "geometry": {"coordinates":[39.13917,-15.65056],"type":"Point"}
}