{
  "type": "Feature",
  "properties": {
    "gn:admin1_code":"3",
    "gn:asciiname":"Chiboma",
    "gn:country_code":"MZ",
    "gn:dem":122,
    "gn:feature_class":"P",
    "gn:feature_code":"PPL",
    "gn:name":"Chiboma",
    "gn:population":0,
    "gn:timezone":"Africa/Maputo",
    "iso:country":"MZ",
    "wof:name":"Chiboma",
    "wof:placetype":"locality"
},
  "geometry": {"coordinates":[34.10028,-21.46278],"type":"Point"}
}