{
  "type": "Feature",
  "properties": {
    "gn:admin1_code":"2.0",
    "gn:asciiname":"Magulane",
    "gn:country_code":"MZ",
    "gn:dem":67,
    "gn:feature_class":"P",
    "gn:feature_code":"PPL",
    "gn:name":"Magulane",
    "gn:population":0,
    "gn:timezone":"Africa/Maputo",
    "iso:country":"MZ",
    "wof:name":"Magulane",
    "wof:placetype":"locality"
},
  "geometry": {"coordinates":[33.61528,-23.20083],"type":"Point"}
}