{
  "type": "Feature",
  "properties": {
    "gn:admin1_code":"3",
    "gn:asciiname":"Mechine",
    "gn:country_code":"MZ",
    "gn:dem":110,
    "gn:feature_class":"P",
    "gn:feature_code":"PPL",
    "gn:name":"Mechine",
    "gn:population":0,
    "gn:timezone":"Africa/Maputo",
    "iso:country":"MZ",
    "wof:name":"Mechine",
    "wof:placetype":"locality"
},
  "geometry": {"coordinates":[34.81694,-22.97083],"type":"Point"}
}