{
  "type": "Feature",
  "properties": {
    "gn:admin1_code":"8",
    "gn:asciiname":"Chipenga",
    "gn:country_code":"MZ",
    "gn:dem":208,
    "gn:feature_class":"P",
    "gn:feature_code":"PPL",
    "gn:name":"Chipenga",
    "gn:population":0,
    "gn:timezone":"Africa/Maputo",
    "iso:country":"MZ",
    "wof:name":"Chipenga",
    "wof:placetype":"locality"
},
  "geometry": {"coordinates":[33.77583,-16.14694],"type":"Point"}
}