{
  "type": "Feature",
  "properties": {
    "gn:admin1_code":"3.0",
    "gn:asciiname":"Cat. Met. Episcopal",
    "gn:country_code":"MZ",
    "gn:dem":57,
    "gn:feature_class":"P",
    "gn:feature_code":"PPL",
    "gn:name":"Cat. Met. Episcopal",
    "gn:population":0,
    "gn:timezone":"Africa/Maputo",
    "iso:country":"MZ",
    "wof:name":"Cat. Met. Episcopal",
    "wof:placetype":"locality"
},
  "geometry": {"coordinates":[35.36194000000001,-24.07667],"type":"Point"}
}