{
  "type": "Feature",
  "properties": {
    "gn:admin1_code":"7.0",
    "gn:asciiname":"Quiuvela",
    "gn:cc2":"MZ",
    "gn:country_code":"MZ",
    "gn:dem":606,
    "gn:feature_class":"P",
    "gn:feature_code":"PPL",
    "gn:name":"Quiuvela",
    "gn:population":0,
    "gn:timezone":"Africa/Maputo",
    "iso:country":"MZ",
    "name:und_x_variant":[
        "Quiuv\u00e0le",
        "Quiuvela"
    ],
    "wof:name":"Quiuvela",
    "wof:placetype":"locality"
},
  "geometry": {"coordinates":[36.41806,-13.15861],"type":"Point"}
}