{
  "type": "Feature",
  "properties": {
    "gn:admin1_code":"3.0",
    "gn:asciiname":"Vetela",
    "gn:country_code":"MZ",
    "gn:dem":95,
    "gn:feature_class":"P",
    "gn:feature_code":"PPL",
    "gn:name":"Vetela",
    "gn:population":0,
    "gn:timezone":"Africa/Maputo",
    "iso:country":"MZ",
    "wof:name":"Vetela",
    "wof:placetype":"locality"
},
  "geometry": {"coordinates":[34.88667,-22.19167],"type":"Point"}
}