{
  "type": "Feature",
  "properties": {
    "gn:admin1_code":"9.0",
    "gn:asciiname":"Porraimo",
    "gn:country_code":"MZ",
    "gn:dem":60,
    "gn:feature_class":"P",
    "gn:feature_code":"PPL",
    "gn:name":"Porraimo",
    "gn:population":0,
    "gn:timezone":"Africa/Maputo",
    "iso:country":"MZ",
    "wof:name":"Porraimo",
    "wof:placetype":"locality"
},
  "geometry": {"coordinates":[38.37972,-16.80611],"type":"Point"}
}