{
  "type": "Feature",
  "properties": {
    "gn:admin1_code":"7",
    "gn:asciiname":"Chefe Quirasse",
    "gn:country_code":"MZ",
    "gn:dem":681,
    "gn:feature_class":"P",
    "gn:feature_code":"PPL",
    "gn:name":"Chefe Quirasse",
    "gn:population":0,
    "gn:timezone":"Africa/Maputo",
    "iso:country":"MZ",
    "wof:name":"Chefe Quirasse",
    "wof:placetype":"locality"
},
  "geometry": {"coordinates":[36.60472,-14.90472],"type":"Point"}
}