{
  "type": "Feature",
  "properties": {
    "gn:admin1_code":"6",
    "gn:asciiname":"Napurra",
    "gn:country_code":"MZ",
    "gn:dem":87,
    "gn:feature_class":"P",
    "gn:feature_code":"PPL",
    "gn:name":"Napurra",
    "gn:population":0,
    "gn:timezone":"Africa/Maputo",
    "iso:country":"MZ",
    "wof:name":"Napurra",
    "wof:placetype":"locality"
},
  "geometry": {"coordinates":[39.03472,-16.3225],"type":"Point"}
}