{
  "type": "Feature",
  "properties": {
    "gn:admin1_code":"6",
    "gn:asciiname":"Camueto",
    "gn:country_code":"MZ",
    "gn:dem":136,
    "gn:feature_class":"P",
    "gn:feature_code":"PPL",
    "gn:name":"Camueto",
    "gn:population":0,
    "gn:timezone":"Africa/Maputo",
    "iso:country":"MZ",
    "wof:name":"Camueto",
    "wof:placetype":"locality"
},
  "geometry": {"coordinates":[40.03528,-15.035],"type":"Point"}
}