{
  "type": "Feature",
  "properties": {
    "gn:admin1_code":"2.0",
    "gn:asciiname":"Sacabuiane",
    "gn:country_code":"MZ",
    "gn:dem":64,
    "gn:feature_class":"P",
    "gn:feature_code":"PPL",
    "gn:name":"Sacabuiane",
    "gn:population":0,
    "gn:timezone":"Africa/Maputo",
    "iso:country":"MZ",
    "wof:name":"Sacabuiane",
    "wof:placetype":"locality"
},
  "geometry": {"coordinates":[33.825,-24.58806],"type":"Point"}
}