{
  "type": "Feature",
  "properties": {
    "gn:admin1_code":"7",
    "gn:asciiname":"Manhunho",
    "gn:country_code":"MZ",
    "gn:dem":668,
    "gn:feature_class":"P",
    "gn:feature_code":"PPL",
    "gn:name":"Manhunho",
    "gn:population":0,
    "gn:timezone":"Africa/Maputo",
    "iso:country":"MZ",
    "wof:name":"Manhunho",
    "wof:placetype":"locality"
},
  "geometry": {"coordinates":[35.93667,-14.95222],"type":"Point"}
}