{
  "type": "Feature",
  "properties": {
    "gn:admin1_code":"6",
    "gn:asciiname":"Maiuta",
    "gn:country_code":"MZ",
    "gn:dem":588,
    "gn:feature_class":"P",
    "gn:feature_code":"PPL",
    "gn:name":"Maiuta",
    "gn:population":0,
    "gn:timezone":"Africa/Maputo",
    "iso:country":"MZ",
    "wof:name":"Maiuta",
    "wof:placetype":"locality"
},
  "geometry": {"coordinates":[37.9875,-14.655],"type":"Point"}
}