{
  "type": "Feature",
  "properties": {
    "gn:admin1_code":"6",
    "gn:asciiname":"Maia",
    "gn:country_code":"MZ",
    "gn:dem":138,
    "gn:feature_class":"P",
    "gn:feature_code":"PPL",
    "gn:name":"Maia",
    "gn:population":0,
    "gn:timezone":"Africa/Maputo",
    "iso:country":"MZ",
    "name:afr_x_preferred":[
        "Maia"
    ],
    "name:bos_x_preferred":[
        "Maja"
    ],
    "name:bre_x_preferred":[
        "Maia"
    ],
    "name:bul_x_preferred":[
        "\u041c\u0430\u044f"
    ],
    "name:cat_x_preferred":[
        "Maia"
    ],
    "name:ces_x_preferred":[
        "Maia"
    ],
    "name:dan_x_preferred":[
        "Maia"
    ],
    "name:deu_x_preferred":[
        "Maia"
    ],
    "name:ell_x_preferred":[
        "\u039c\u03b1\u03af\u03b1"
    ],
    "name:epo_x_preferred":[
        "Maio"
    ],
    "name:est_x_preferred":[
        "Maia"
    ],
    "name:eus_x_preferred":[
        "Maia"
    ],
    "name:fas_x_preferred":[
        "\u0645\u0627\u06cc\u0627"
    ],
    "name:fin_x_preferred":[
        "Maia"
    ],
    "name:fra_x_preferred":[
        "Ma\u00efa"
    ],
    "name:fry_x_preferred":[
        "Maja"
    ],
    "name:heb_x_preferred":[
        "\u05de\u05d0\u05d9\u05d4"
    ],
    "name:hrv_x_preferred":[
        "Maja"
    ],
    "name:hun_x_preferred":[
        "Maia"
    ],
    "name:ina_x_preferred":[
        "Maia"
    ],
    "name:ind_x_preferred":[
        "Maia"
    ],
    "name:ita_x_preferred":[
        "Maia"
    ],
    "name:jpn_x_preferred":[
        "\u30de\u30a4\u30a2"
    ],
    "name:kor_x_preferred":[
        "\ub9c8\uc774\uc544"
    ],
    "name:lat_x_preferred":[
        "Maia"
    ],
    "name:lit_x_preferred":[
        "Maja"
    ],
    "name:nld_x_preferred":[
        "Maia"
    ],
    "name:nor_x_preferred":[
        "Maia"
    ],
    "name:pol_x_preferred":[
        "Maja"
    ],
    "name:por_x_preferred":[
        "Maia"
    ],
    "name:ron_x_preferred":[
        "Maia"
    ],
    "name:rus_x_preferred":[
        "\u041c\u0430\u0439\u044f"
    ],
    "name:slk_x_preferred":[
        "Maia"
    ],
    "name:spa_x_preferred":[
        "Maya"
    ],
    "name:srp_x_preferred":[
        "\u041c\u0430\u0458\u0430"
    ],
    "name:swe_x_preferred":[
        "Maia"
    ],
    "name:tur_x_preferred":[
        "Maia"
    ],
    "name:ukr_x_preferred":[
        "\u041c\u0430\u0439\u044f"
    ],
    "name:zho_x_preferred":[
        "\u8fc8\u4e9a"
    ],
    "wof:name":"Maia",
    "wof:placetype":"locality"
},
  "geometry": {"coordinates":[39.07889,-15.99194],"type":"Point"}
}