{
  "type": "Feature",
  "properties": {
    "gn:admin1_code":"10.0",
    "gn:asciiname":"Aldeia Moronde",
    "gn:country_code":"MZ",
    "gn:dem":585,
    "gn:feature_class":"P",
    "gn:feature_code":"PPL",
    "gn:name":"Aldeia Moronde",
    "gn:population":0,
    "gn:timezone":"Africa/Maputo",
    "iso:country":"MZ",
    "wof:name":"Aldeia Moronde",
    "wof:placetype":"locality"
},
  "geometry": {"coordinates":[33.04083,-18.53139],"type":"Point"}
}