{
  "type": "Feature",
  "properties": {
    "gn:admin1_code":"2.0",
    "gn:asciiname":"Txizuca",
    "gn:country_code":"MZ",
    "gn:dem":88,
    "gn:feature_class":"P",
    "gn:feature_code":"PPL",
    "gn:name":"Txizuca",
    "gn:population":0,
    "gn:timezone":"Africa/Maputo",
    "iso:country":"MZ",
    "wof:name":"Txizuca",
    "wof:placetype":"locality"
},
  "geometry": {"coordinates":[32.23972,-23.86556],"type":"Point"}
}