{
  "type": "Feature",
  "properties": {
    "gn:admin1_code":"2.0",
    "gn:asciiname":"Regedor Chicungulo",
    "gn:country_code":"MZ",
    "gn:dem":68,
    "gn:feature_class":"P",
    "gn:feature_code":"PPL",
    "gn:name":"Regedor Chicungulo",
    "gn:population":0,
    "gn:timezone":"Africa/Maputo",
    "iso:country":"MZ",
    "wof:name":"Regedor Chicungulo",
    "wof:placetype":"locality"
},
  "geometry": {"coordinates":[32.57139,-23.87722],"type":"Point"}
}