{
  "type": "Feature",
  "properties": {
    "gn:admin1_code":"0",
    "gn:asciiname":"Lifidezi",
    "gn:cc2":"MZ",
    "gn:country_code":"MZ",
    "gn:dem":1252,
    "gn:feature_class":"P",
    "gn:feature_code":"PPL",
    "gn:name":"Lifidezi",
    "gn:population":0,
    "gn:timezone":"Africa/Maputo",
    "iso:country":"MZ",
    "name:und_x_variant":[
        "Lifidzi",
        "Lifidezi"
    ],
    "wof:name":"Lifidezi",
    "wof:placetype":"locality"
},
  "geometry": {"coordinates":[34.23333,-14.55],"type":"Point"}
}