{
  "type": "Feature",
  "properties": {
    "gn:admin1_code":"9",
    "gn:asciiname":"Galave",
    "gn:country_code":"MZ",
    "gn:dem":215,
    "gn:feature_class":"P",
    "gn:feature_code":"PPL",
    "gn:name":"Galave",
    "gn:population":0,
    "gn:timezone":"Africa/Maputo",
    "iso:country":"MZ",
    "wof:name":"Galave",
    "wof:placetype":"locality"
},
  "geometry": {"coordinates":[36.14139,-17.04222],"type":"Point"}
}