{
  "type": "Feature",
  "properties": {
    "gn:admin1_code":"7",
    "gn:asciiname":"Rapissone",
    "gn:country_code":"MZ",
    "gn:dem":543,
    "gn:feature_class":"P",
    "gn:feature_code":"PPL",
    "gn:name":"Rapissone",
    "gn:population":0,
    "gn:timezone":"Africa/Maputo",
    "iso:country":"MZ",
    "wof:name":"Rapissone",
    "wof:placetype":"locality"
},
  "geometry": {"coordinates":[37.14333,-14.48028],"type":"Point"}
}