{
  "type": "Feature",
  "properties": {
    "gn:admin1_code":"2.0",
    "gn:asciiname":"Puluane",
    "gn:country_code":"MZ",
    "gn:dem":74,
    "gn:feature_class":"P",
    "gn:feature_code":"PPL",
    "gn:name":"Puluane",
    "gn:population":0,
    "gn:timezone":"Africa/Maputo",
    "iso:country":"MZ",
    "wof:name":"Puluane",
    "wof:placetype":"locality"
},
  "geometry": {"coordinates":[32.5125,-23.78389],"type":"Point"}
}