{
  "type": "Feature",
  "properties": {
    "gn:admin1_code":"9",
    "gn:asciiname":"Cueteia",
    "gn:country_code":"MZ",
    "gn:dem":21,
    "gn:feature_class":"P",
    "gn:feature_code":"PPL",
    "gn:name":"Cueteia",
    "gn:population":0,
    "gn:timezone":"Africa/Maputo",
    "iso:country":"MZ",
    "wof:name":"Cueteia",
    "wof:placetype":"locality"
},
  "geometry": {"coordinates":[37.50194000000001,-17.33694],"type":"Point"}
}