{
  "type": "Feature",
  "properties": {
    "gn:admin1_code":"10",
    "gn:asciiname":"Nheuane",
    "gn:country_code":"MZ",
    "gn:dem":241,
    "gn:feature_class":"P",
    "gn:feature_code":"PPL",
    "gn:name":"Nheuane",
    "gn:population":0,
    "gn:timezone":"Africa/Maputo",
    "iso:country":"MZ",
    "wof:name":"Nheuane",
    "wof:placetype":"locality"
},
  "geometry": {"coordinates":[33.51583,-20.80972],"type":"Point"}
}