{
  "type": "Feature",
  "properties": {
    "gn:admin1_code":"9",
    "gn:asciiname":"Muieva",
    "gn:country_code":"MZ",
    "gn:dem":87,
    "gn:feature_class":"P",
    "gn:feature_code":"PPL",
    "gn:name":"Muieva",
    "gn:population":0,
    "gn:timezone":"Africa/Maputo",
    "iso:country":"MZ",
    "wof:name":"Muieva",
    "wof:placetype":"locality"
},
  "geometry": {"coordinates":[37.7975,-17.09778],"type":"Point"}
}