{
  "type": "Feature",
  "properties": {
    "gn:admin1_code":"7",
    "gn:asciiname":"Cuchi",
    "gn:cc2":"MZ",
    "gn:country_code":"MZ",
    "gn:dem":606,
    "gn:feature_class":"P",
    "gn:feature_code":"PPL",
    "gn:name":"Cuchi",
    "gn:population":0,
    "gn:timezone":"Africa/Maputo",
    "iso:country":"MZ",
    "name:und_x_variant":[
        "Cuiche",
        "Cuchi"
    ],
    "wof:name":"Cuchi",
    "wof:placetype":"locality"
},
  "geometry": {"coordinates":[34.82972,-13.20722],"type":"Point"}
}