{
  "type": "Feature",
  "properties": {
    "gn:admin1_code":"7",
    "gn:asciiname":"Cuchi",
    "gn:cc2":"MZ",
    "gn:country_code":"MZ",
    "gn:dem":606,
    "gn:feature_class":"P",
    "gn:feature_code":"PPL",
    "gn:name":"Cuchi",
    "gn:population":0,
    "gn:timezone":"Africa/Maputo",
    "iso:country":"MZ",
    "name:azb_x_preferred":[
        "\u06a9\u0648\u0634\u06cc"
    ],
    "name:cat_x_preferred":[
        "Cuchi"
    ],
    "name:ceb_x_preferred":[
        "Munic\u00edpio Cuchi"
    ],
    "name:deu_x_preferred":[
        "Cuchi"
    ],
    "name:fas_x_preferred":[
        "\u06a9\u0648\u0634\u06cc"
    ],
    "name:ita_x_preferred":[
        "Kuchi"
    ],
    "name:por_x_preferred":[
        "Cuchi"
    ],
    "name:ron_x_preferred":[
        "Cuchi"
    ],
    "name:spa_x_preferred":[
        "Cuchi"
    ],
    "name:swe_x_preferred":[
        "Munic\u00edpio Cuchi"
    ],
    "name:und_x_variant":[
        "Cuiche",
        "Cuchi"
    ],
    "name:zho_x_preferred":[
        "\u5eab\u5e0c"
    ],
    "wof:name":"Cuchi",
    "wof:placetype":"locality"
},
  "geometry": {"coordinates":[34.82972,-13.20722],"type":"Point"}
}