{
  "type": "Feature",
  "properties": {
    "gn:admin1_code":"6",
    "gn:asciiname":"Intete",
    "gn:country_code":"MZ",
    "gn:dem":278,
    "gn:feature_class":"P",
    "gn:feature_code":"PPL",
    "gn:name":"Intete",
    "gn:population":0,
    "gn:timezone":"Africa/Maputo",
    "iso:country":"MZ",
    "wof:name":"Intete",
    "wof:placetype":"locality"
},
  "geometry": {"coordinates":[40.06806,-14.41806],"type":"Point"}
}