{
  "type": "Feature",
  "properties": {
    "gn:admin1_code":"4.0",
    "gn:asciiname":"Simione",
    "gn:country_code":"MZ",
    "gn:dem":118,
    "gn:feature_class":"P",
    "gn:feature_code":"PPL",
    "gn:name":"Simione",
    "gn:population":0,
    "gn:timezone":"Africa/Maputo",
    "iso:country":"MZ",
    "wof:name":"Simione",
    "wof:placetype":"locality"
},
  "geometry": {"coordinates":[32.25360999999999,-24.86389],"type":"Point"}
}