{
  "type": "Feature",
  "properties": {
    "gn:admin1_code":"9",
    "gn:asciiname":"Marruo",
    "gn:country_code":"MZ",
    "gn:dem":275,
    "gn:feature_class":"P",
    "gn:feature_code":"PPL",
    "gn:name":"Marruo",
    "gn:population":0,
    "gn:timezone":"Africa/Maputo",
    "iso:country":"MZ",
    "wof:name":"Marruo",
    "wof:placetype":"locality"
},
  "geometry": {"coordinates":[36.23639,-16.97194],"type":"Point"}
}