{
  "type": "Feature",
  "properties": {
    "gn:admin1_code":"10",
    "gn:asciiname":"Magava",
    "gn:country_code":"MZ",
    "gn:dem":159,
    "gn:feature_class":"P",
    "gn:feature_code":"PPL",
    "gn:name":"Magava",
    "gn:population":0,
    "gn:timezone":"Africa/Maputo",
    "iso:country":"MZ",
    "wof:name":"Magava",
    "wof:placetype":"locality"
},
  "geometry": {"coordinates":[33.75278,-20.74361],"type":"Point"}
}