{
  "type": "Feature",
  "properties": {
    "gn:admin1_code":"1",
    "gn:asciiname":"Cucuta",
    "gn:country_code":"MZ",
    "gn:dem":98,
    "gn:feature_class":"P",
    "gn:feature_code":"PPL",
    "gn:name":"Cucuta",
    "gn:population":0,
    "gn:timezone":"Africa/Maputo",
    "iso:country":"MZ",
    "name:nld_x_preferred":[
        "Cucuta"
    ],
    "wof:name":"Cucuta",
    "wof:placetype":"locality"
},
  "geometry": {"coordinates":[40.24111,-11.83611],"type":"Point"}
}