{
  "type": "Feature",
  "properties": {
    "gn:admin1_code":"6.0",
    "gn:asciiname":"Tiago",
    "gn:country_code":"MZ",
    "gn:dem":66,
    "gn:feature_class":"P",
    "gn:feature_code":"PPL",
    "gn:name":"Tiago",
    "gn:population":0,
    "gn:timezone":"Africa/Maputo",
    "iso:country":"MZ",
    "name:ceb_x_preferred":[
        "Tiago"
    ],
    "name:deu_x_preferred":[
        "Tiago"
    ],
    "name:fas_x_preferred":[
        "\u062a\u06cc\u0627\u06af\u0648"
    ],
    "name:fin_x_preferred":[
        "Tiago"
    ],
    "name:heb_x_preferred":[
        "\u05d8\u05d9\u05d0\u05d2\u05d5"
    ],
    "name:ita_x_preferred":[
        "Tiago"
    ],
    "name:jpn_x_preferred":[
        "\u30c1\u30a2\u30b4"
    ],
    "name:pol_x_preferred":[
        "Tiago"
    ],
    "name:por_x_preferred":[
        "Tiago"
    ],
    "name:ron_x_preferred":[
        "Tiago"
    ],
    "name:swe_x_preferred":[
        "Tiago"
    ],
    "wof:name":"Tiago",
    "wof:placetype":"locality"
},
  "geometry": {"coordinates":[39.10639000000001,-16.49361],"type":"Point"}
}