{
  "type": "Feature",
  "properties": {
    "gn:admin1_code":"2",
    "gn:asciiname":"Mavande",
    "gn:country_code":"MZ",
    "gn:dem":93,
    "gn:feature_class":"P",
    "gn:feature_code":"PPL",
    "gn:name":"Mavande",
    "gn:population":0,
    "gn:timezone":"Africa/Maputo",
    "iso:country":"MZ",
    "wof:name":"Mavande",
    "wof:placetype":"locality"
},
  "geometry": {"coordinates":[32.86667,-23.58333],"type":"Point"}
}