{
  "type": "Feature",
  "properties": {
    "gn:admin1_code":"3.0",
    "gn:asciiname":"Chefe Mafacaviana",
    "gn:country_code":"MZ",
    "gn:dem":149,
    "gn:feature_class":"P",
    "gn:feature_code":"PPL",
    "gn:name":"Chefe Mafacaviana",
    "gn:population":0,
    "gn:timezone":"Africa/Maputo",
    "iso:country":"MZ",
    "wof:name":"Chefe Mafacaviana",
    "wof:placetype":"locality"
},
  "geometry": {"coordinates":[35.23889000000001,-24.05028],"type":"Point"}
}