{
  "type": "Feature",
  "properties": {
    "gn:admin1_code":"7",
    "gn:asciiname":"Dinis",
    "gn:country_code":"MZ",
    "gn:dem":537,
    "gn:feature_class":"P",
    "gn:feature_code":"PPL",
    "gn:name":"Dinis",
    "gn:population":0,
    "gn:timezone":"Africa/Maputo",
    "iso:country":"MZ",
    "wof:name":"Dinis",
    "wof:placetype":"locality"
},
  "geometry": {"coordinates":[37.01361,-14.62028],"type":"Point"}
}