{
  "type": "Feature",
  "properties": {
    "gn:admin1_code":"8",
    "gn:asciiname":"Aldeia Cumbe",
    "gn:country_code":"MZ",
    "gn:dem":1148,
    "gn:feature_class":"P",
    "gn:feature_code":"PPL",
    "gn:name":"Aldeia Cumbe",
    "gn:population":0,
    "gn:timezone":"Africa/Maputo",
    "iso:country":"MZ",
    "wof:name":"Aldeia Cumbe",
    "wof:placetype":"locality"
},
  "geometry": {"coordinates":[34.07778,-14.62222],"type":"Point"}
}