{
  "type": "Feature",
  "properties": {
    "gn:admin1_code":"8.0",
    "gn:asciiname":"Visa",
    "gn:country_code":"MZ",
    "gn:dem":75,
    "gn:feature_class":"P",
    "gn:feature_code":"PPL",
    "gn:name":"Visa",
    "gn:population":0,
    "gn:timezone":"Africa/Maputo",
    "iso:country":"MZ",
    "name:ben_x_preferred":[
        "\u09ad\u09bf\u09b8\u09be"
    ],
    "name:bul_x_preferred":[
        "\u0412\u0438\u0437\u0430"
    ],
    "name:ceb_x_preferred":[
        "Visa"
    ],
    "name:dan_x_preferred":[
        "Visa"
    ],
    "name:deu_x_preferred":[
        "Visa"
    ],
    "name:epo_x_preferred":[
        "Visa"
    ],
    "name:fin_x_preferred":[
        "Visa"
    ],
    "name:fra_x_preferred":[
        "Visa"
    ],
    "name:heb_x_preferred":[
        "\u05d5\u05d9\u05d6\u05d4"
    ],
    "name:hun_x_preferred":[
        "Visa"
    ],
    "name:kat_x_preferred":[
        "\u10d5\u10d8\u10d6\u10d0"
    ],
    "name:ltz_x_preferred":[
        "Visa"
    ],
    "name:nep_x_preferred":[
        "\u092a\u094d\u0930\u0935\u0947\u0936\u093e\u091c\u094d\u091e\u093e"
    ],
    "name:nld_x_preferred":[
        "Visa"
    ],
    "name:nor_x_preferred":[
        "Visa"
    ],
    "name:por_x_preferred":[
        "Visa"
    ],
    "name:rus_x_preferred":[
        "\u0412\u0438\u0437\u0430"
    ],
    "name:spa_x_preferred":[
        "Visa"
    ],
    "name:tha_x_preferred":[
        "\u0e27\u0e35\u0e0b\u0e48\u0e32"
    ],
    "name:vie_x_preferred":[
        "Visa"
    ],
    "wof:name":"Visa",
    "wof:placetype":"locality"
},
  "geometry": {"coordinates":[34.75472,-16.88417],"type":"Point"}
}