{
  "type": "Feature",
  "properties": {
    "gn:admin1_code":"4",
    "gn:asciiname":"Chefe Muchocolote",
    "gn:cc2":"MZ",
    "gn:country_code":"MZ",
    "gn:dem":37,
    "gn:feature_class":"P",
    "gn:feature_code":"PPL",
    "gn:name":"Chefe Muchocolote",
    "gn:population":0,
    "gn:timezone":"Africa/Maputo",
    "iso:country":"MZ",
    "name:und_x_variant":[
        "Muchuculuto",
        "Chefe Muchocolote"
    ],
    "wof:name":"Chefe Muchocolote",
    "wof:placetype":"locality"
},
  "geometry": {"coordinates":[32.44639,-26.28056],"type":"Point"}
}