{
  "type": "Feature",
  "properties": {
    "gn:admin1_code":"3.0",
    "gn:asciiname":"Cabo Macuacua",
    "gn:country_code":"MZ",
    "gn:dem":26,
    "gn:feature_class":"P",
    "gn:feature_code":"PPL",
    "gn:name":"Cabo Macu\u00e1cua",
    "gn:population":0,
    "gn:timezone":"Africa/Maputo",
    "iso:country":"MZ",
    "wof:name":"Cabo Macuacua",
    "wof:placetype":"locality"
},
  "geometry": {"coordinates":[35.47583,-23.9675],"type":"Point"}
}