{
  "type": "Feature",
  "properties": {
    "gn:admin1_code":"6",
    "gn:asciiname":"Tenda",
    "gn:country_code":"MZ",
    "gn:dem":48,
    "gn:feature_class":"P",
    "gn:feature_code":"PPL",
    "gn:name":"Tenda",
    "gn:population":0,
    "gn:timezone":"Africa/Maputo",
    "iso:country":"MZ",
    "name:ceb_x_preferred":[
        "Tenda"
    ],
    "name:deu_x_preferred":[
        "Tenda"
    ],
    "name:fra_x_preferred":[
        "Tenda"
    ],
    "name:ita_x_preferred":[
        "Tenda"
    ],
    "name:swe_x_preferred":[
        "Tenda"
    ],
    "name:zho_x_preferred":[
        "Tenda"
    ],
    "wof:name":"Tenda",
    "wof:placetype":"locality"
},
  "geometry": {"coordinates":[40.10861,-16.02778],"type":"Point"}
}