{
  "type": "Feature",
  "properties": {
    "gn:admin1_code":"9",
    "gn:asciiname":"Afreda",
    "gn:country_code":"MZ",
    "gn:dem":275,
    "gn:feature_class":"P",
    "gn:feature_code":"PPL",
    "gn:name":"Afr\u00eada",
    "gn:population":0,
    "gn:timezone":"Africa/Maputo",
    "iso:country":"MZ",
    "wof:name":"Afreda",
    "wof:placetype":"locality"
},
  "geometry": {"coordinates":[37.10917,-16.66583],"type":"Point"}
}