{
  "type": "Feature",
  "properties": {
    "gn:admin1_code":"8",
    "gn:asciiname":"Aldeia Ntayansupa",
    "gn:country_code":"MZ",
    "gn:dem":624,
    "gn:feature_class":"P",
    "gn:feature_code":"PPL",
    "gn:name":"Aldeia Ntayansupa",
    "gn:population":0,
    "gn:timezone":"Africa/Maputo",
    "iso:country":"MZ",
    "wof:name":"Aldeia Ntayansupa",
    "wof:placetype":"locality"
},
  "geometry": {"coordinates":[32.21361,-15.22833],"type":"Point"}
}