{
  "type": "Feature",
  "properties": {
    "gn:admin1_code":"6",
    "gn:asciiname":"Arame",
    "gn:country_code":"MZ",
    "gn:dem":68,
    "gn:feature_class":"P",
    "gn:feature_code":"PPL",
    "gn:name":"Arame",
    "gn:population":0,
    "gn:timezone":"Africa/Maputo",
    "iso:country":"MZ",
    "name:ara_x_preferred":[
        "\u0623\u0631\u0627\u0645\u064a"
    ],
    "name:cat_x_preferred":[
        "Arame"
    ],
    "name:eus_x_preferred":[
        "Arame"
    ],
    "name:fra_x_preferred":[
        "Aram\u00e9"
    ],
    "name:ita_x_preferred":[
        "Ecklonia bicyclis"
    ],
    "name:jpn_x_preferred":[
        "\u30a2\u30e9\u30e1"
    ],
    "name:spa_x_preferred":[
        "Eisenia bicyclis"
    ],
    "name:ukr_x_preferred":[
        "\u0410\u0440\u0430\u043c\u0435"
    ],
    "wof:name":"Arame",
    "wof:placetype":"locality"
},
  "geometry": {"coordinates":[39.44306,-16.41917],"type":"Point"}
}