{
  "type": "Feature",
  "properties": {
    "gn:admin1_code":"3",
    "gn:asciiname":"Cabala",
    "gn:country_code":"MZ",
    "gn:dem":177,
    "gn:feature_class":"P",
    "gn:feature_code":"PPL",
    "gn:name":"Cabala",
    "gn:population":0,
    "gn:timezone":"Africa/Maputo",
    "iso:country":"MZ",
    "name:ceb_x_preferred":[
        "Cabala"
    ],
    "name:deu_x_preferred":[
        "Cabala"
    ],
    "name:ita_x_preferred":[
        "Cabala"
    ],
    "name:kat_x_preferred":[
        "\u10d9\u10d0\u10d1\u10d0\u10da\u10d0"
    ],
    "name:rus_x_preferred":[
        "\u041a\u0430\u0431\u0431\u0430\u043b\u0430"
    ],
    "name:spa_x_preferred":[
        "C\u00e1bala"
    ],
    "name:swe_x_preferred":[
        "Cabala"
    ],
    "wof:name":"Cabala",
    "wof:placetype":"locality"
},
  "geometry": {"coordinates":[34.16806,-21.99194],"type":"Point"}
}