{
  "type": "Feature",
  "properties": {
    "gn:admin1_code":"6",
    "gn:asciiname":"Chefe Rafael",
    "gn:country_code":"MZ",
    "gn:dem":244,
    "gn:feature_class":"P",
    "gn:feature_code":"PPL",
    "gn:name":"Chefe Rafael",
    "gn:population":0,
    "gn:timezone":"Africa/Maputo",
    "iso:country":"MZ",
    "wof:name":"Chefe Rafael",
    "wof:placetype":"locality"
},
  "geometry": {"coordinates":[39.74694,-13.70333],"type":"Point"}
}