{
  "type": "Feature",
  "properties": {
    "gn:admin1_code":"10",
    "gn:asciiname":"Cantine",
    "gn:country_code":"MZ",
    "gn:dem":504,
    "gn:feature_class":"P",
    "gn:feature_code":"PPL",
    "gn:name":"Cantine",
    "gn:population":0,
    "gn:timezone":"Africa/Maputo",
    "iso:country":"MZ",
    "wof:name":"Cantine",
    "wof:placetype":"locality"
},
  "geometry": {"coordinates":[33.65667,-19.15944],"type":"Point"}
}