{
  "type": "Feature",
  "properties": {
    "gn:admin1_code":"6",
    "gn:asciiname":"Nipurro",
    "gn:country_code":"MZ",
    "gn:dem":316,
    "gn:feature_class":"P",
    "gn:feature_code":"PPL",
    "gn:name":"Nipurro",
    "gn:population":0,
    "gn:timezone":"Africa/Maputo",
    "iso:country":"MZ",
    "wof:name":"Nipurro",
    "wof:placetype":"locality"
},
  "geometry": {"coordinates":[39.58889,-15.0625],"type":"Point"}
}