{
  "type": "Feature",
  "properties": {
    "gn:admin1_code":"1",
    "gn:asciiname":"Muicamela",
    "gn:country_code":"MZ",
    "gn:dem":465,
    "gn:feature_class":"P",
    "gn:feature_code":"PPL",
    "gn:name":"Muicamela",
    "gn:population":0,
    "gn:timezone":"Africa/Maputo",
    "iso:country":"MZ",
    "wof:name":"Muicamela",
    "wof:placetype":"locality"
},
  "geometry": {"coordinates":[39.14694,-12.89139],"type":"Point"}
}