{
  "type": "Feature",
  "properties": {
    "gn:admin1_code":"9",
    "gn:asciiname":"Costema",
    "gn:cc2":"MZ",
    "gn:country_code":"MZ",
    "gn:dem":28,
    "gn:feature_class":"P",
    "gn:feature_code":"PPL",
    "gn:name":"Costema",
    "gn:population":0,
    "gn:timezone":"Africa/Maputo",
    "iso:country":"MZ",
    "name:und_x_variant":[
        "Papagaio",
        "Costema"
    ],
    "wof:name":"Costema",
    "wof:placetype":"locality"
},
  "geometry": {"coordinates":[36.20694,-17.85472],"type":"Point"}
}