{
  "type": "Feature",
  "properties": {
    "gn:admin1_code":"1",
    "gn:asciiname":"Chikalango",
    "gn:country_code":"MZ",
    "gn:dem":870,
    "gn:feature_class":"P",
    "gn:feature_code":"PPL",
    "gn:name":"Chikalango",
    "gn:population":0,
    "gn:timezone":"Africa/Maputo",
    "iso:country":"MZ",
    "wof:name":"Chikalango",
    "wof:placetype":"locality"
},
  "geometry": {"coordinates":[39.43306,-11.47278],"type":"Point"}
}