{
  "type": "Feature",
  "properties": {
    "gn:admin1_code":"9",
    "gn:asciiname":"Inago",
    "gn:country_code":"MZ",
    "gn:dem":825,
    "gn:feature_class":"P",
    "gn:feature_code":"PPL",
    "gn:name":"Inago",
    "gn:population":0,
    "gn:timezone":"Africa/Maputo",
    "iso:country":"MZ",
    "wof:name":"Inago",
    "wof:placetype":"locality"
},
  "geometry": {"coordinates":[37.41944,-15.24667],"type":"Point"}
}