{
  "type": "Feature",
  "properties": {
    "gn:admin1_code":"5",
    "gn:asciiname":"Chala",
    "gn:country_code":"MZ",
    "gn:dem":261,
    "gn:feature_class":"P",
    "gn:feature_code":"PPL",
    "gn:name":"Chala",
    "gn:population":0,
    "gn:timezone":"Africa/Maputo",
    "iso:country":"MZ",
    "name:aym_x_preferred":[
        "Ch'alla"
    ],
    "name:ces_x_preferred":[
        "Chala"
    ],
    "name:deu_x_preferred":[
        "Chala"
    ],
    "name:lit_x_preferred":[
        "\u010cala"
    ],
    "name:que_x_preferred":[
        "Chala"
    ],
    "name:ukr_x_preferred":[
        "\u0427\u0430\u043b\u0430"
    ],
    "wof:name":"Chala",
    "wof:placetype":"locality"
},
  "geometry": {"coordinates":[33.67055999999999,-20.46167],"type":"Point"}
}