{
  "type": "Feature",
  "properties": {
    "gn:admin1_code":"5",
    "gn:asciiname":"Magrasse",
    "gn:country_code":"MZ",
    "gn:dem":198,
    "gn:feature_class":"P",
    "gn:feature_code":"PPL",
    "gn:name":"Magrasse",
    "gn:population":0,
    "gn:timezone":"Africa/Maputo",
    "iso:country":"MZ",
    "wof:name":"Magrasse",
    "wof:placetype":"locality"
},
  "geometry": {"coordinates":[34.67972,-17.10667],"type":"Point"}
}