{
  "type": "Feature",
  "properties": {
    "gn:admin1_code":"8",
    "gn:asciiname":"Calcao",
    "gn:country_code":"MZ",
    "gn:dem":936,
    "gn:feature_class":"P",
    "gn:feature_code":"PPL",
    "gn:name":"Cal\u00e7\u00e3o",
    "gn:population":0,
    "gn:timezone":"Africa/Maputo",
    "iso:country":"MZ",
    "wof:name":"Calcao",
    "wof:placetype":"locality"
},
  "geometry": {"coordinates":[31.55333,-14.935],"type":"Point"}
}