{
  "type": "Feature",
  "properties": {
    "gn:admin1_code":"3.0",
    "gn:asciiname":"Cat. Congregacional",
    "gn:country_code":"MZ",
    "gn:dem":63,
    "gn:feature_class":"P",
    "gn:feature_code":"PPL",
    "gn:name":"Cat. Congregacional",
    "gn:population":0,
    "gn:timezone":"Africa/Maputo",
    "iso:country":"MZ",
    "wof:name":"Cat. Congregacional",
    "wof:placetype":"locality"
},
  "geometry": {"coordinates":[34.98083,-24.04528],"type":"Point"}
}