{
  "type": "Feature",
  "properties": {
    "gn:admin1_code":"7",
    "gn:asciiname":"Matipa",
    "gn:country_code":"MZ",
    "gn:dem":563,
    "gn:feature_class":"P",
    "gn:feature_code":"PPL",
    "gn:name":"Matipa",
    "gn:population":0,
    "gn:timezone":"Africa/Maputo",
    "iso:country":"MZ",
    "wof:name":"Matipa",
    "wof:placetype":"locality"
},
  "geometry": {"coordinates":[34.95389,-13.54639],"type":"Point"}
}