{
  "type": "Feature",
  "properties": {
    "gn:admin1_code":"4.0",
    "gn:asciiname":"Maholela",
    "gn:country_code":"MZ",
    "gn:dem":54,
    "gn:feature_class":"P",
    "gn:feature_code":"PPL",
    "gn:name":"Maholela",
    "gn:population":0,
    "gn:timezone":"Africa/Maputo",
    "iso:country":"MZ",
    "wof:name":"Maholela",
    "wof:placetype":"locality"
},
  "geometry": {"coordinates":[32.58917,-25.12194],"type":"Point"}
}