{
  "type": "Feature",
  "properties": {
    "gn:admin1_code":"0",
    "gn:asciiname":"Pangura",
    "gn:country_code":"MZ",
    "gn:dem":341,
    "gn:feature_class":"P",
    "gn:feature_code":"PPL",
    "gn:name":"Pangura",
    "gn:population":0,
    "gn:timezone":"Africa/Maputo",
    "iso:country":"MZ",
    "wof:name":"Pangura",
    "wof:placetype":"locality"
},
  "geometry": {"coordinates":[30.71667,-15.58333],"type":"Point"}
}