{
  "type": "Feature",
  "properties": {
    "gn:admin1_code":"1",
    "gn:asciiname":"Jahabo",
    "gn:country_code":"MZ",
    "gn:dem":520,
    "gn:feature_class":"P",
    "gn:feature_code":"PPL",
    "gn:name":"Jahabo",
    "gn:population":0,
    "gn:timezone":"Africa/Maputo",
    "iso:country":"MZ",
    "wof:name":"Jahabo",
    "wof:placetype":"locality"
},
  "geometry": {"coordinates":[39.72667,-11.48139],"type":"Point"}
}