{
  "type": "Feature",
  "properties": {
    "gn:admin1_code":"9",
    "gn:asciiname":"Olima",
    "gn:country_code":"MZ",
    "gn:dem":23,
    "gn:feature_class":"P",
    "gn:feature_code":"PPL",
    "gn:name":"Olima",
    "gn:population":0,
    "gn:timezone":"Africa/Maputo",
    "iso:country":"MZ",
    "wof:name":"Olima",
    "wof:placetype":"locality"
},
  "geometry": {"coordinates":[38.06361,-17.08806],"type":"Point"}
}