{
  "type": "Feature",
  "properties": {
    "gn:admin1_code":"2",
    "gn:asciiname":"Magumbene",
    "gn:country_code":"MZ",
    "gn:dem":232,
    "gn:feature_class":"P",
    "gn:feature_code":"PPL",
    "gn:name":"Magumbene",
    "gn:population":0,
    "gn:timezone":"Africa/Maputo",
    "iso:country":"MZ",
    "wof:name":"Magumbene",
    "wof:placetype":"locality"
},
  "geometry": {"coordinates":[32.17194,-24.205],"type":"Point"}
}