{
  "type": "Feature",
  "properties": {
    "gn:admin1_code":"1.0",
    "gn:asciiname":"Timaquela",
    "gn:country_code":"MZ",
    "gn:dem":384,
    "gn:feature_class":"P",
    "gn:feature_code":"PPL",
    "gn:name":"Timaquela",
    "gn:population":0,
    "gn:timezone":"Africa/Maputo",
    "iso:country":"MZ",
    "wof:name":"Timaquela",
    "wof:placetype":"locality"
},
  "geometry": {"coordinates":[38.53361,-14.04389],"type":"Point"}
}