{
  "type": "Feature",
  "properties": {
    "gn:admin1_code":"1",
    "gn:asciiname":"Nanduadua",
    "gn:country_code":"MZ",
    "gn:dem":28,
    "gn:feature_class":"P",
    "gn:feature_code":"PPL",
    "gn:name":"Nanduadua",
    "gn:population":0,
    "gn:timezone":"Africa/Maputo",
    "iso:country":"MZ",
    "wof:name":"Nanduadua",
    "wof:placetype":"locality"
},
  "geometry": {"coordinates":[40.33861,-11.35167],"type":"Point"}
}