{
  "type": "Feature",
  "properties": {
    "gn:admin1_code":"3",
    "gn:asciiname":"Madavela",
    "gn:country_code":"MZ",
    "gn:dem":101,
    "gn:feature_class":"P",
    "gn:feature_code":"PPL",
    "gn:name":"Madavela",
    "gn:population":0,
    "gn:timezone":"Africa/Maputo",
    "iso:country":"MZ",
    "wof:name":"Madavela",
    "wof:placetype":"locality"
},
  "geometry": {"coordinates":[35.38583,-23.64444],"type":"Point"}
}