{
  "type": "Feature",
  "properties": {
    "gn:admin1_code":"9.0",
    "gn:asciiname":"Raraga",
    "gn:country_code":"MZ",
    "gn:dem":11,
    "gn:feature_class":"P",
    "gn:feature_code":"PPL",
    "gn:name":"Raraga",
    "gn:population":0,
    "gn:timezone":"Africa/Maputo",
    "iso:country":"MZ",
    "wof:name":"Raraga",
    "wof:placetype":"locality"
},
  "geometry": {"coordinates":[37.69917,-17.44667],"type":"Point"}
}