{
  "type": "Feature",
  "properties": {
    "gn:admin1_code":"2.0",
    "gn:asciiname":"Chefe Congolo",
    "gn:country_code":"MZ",
    "gn:dem":9,
    "gn:feature_class":"P",
    "gn:feature_code":"PPL",
    "gn:name":"Chefe Congolo",
    "gn:population":0,
    "gn:timezone":"Africa/Maputo",
    "iso:country":"MZ",
    "wof:name":"Chefe Congolo",
    "wof:placetype":"locality"
},
  "geometry": {"coordinates":[33.62917,-24.82861],"type":"Point"}
}