{
  "type": "Feature",
  "properties": {
    "gn:admin1_code":"0",
    "gn:asciiname":"Matibene",
    "gn:country_code":"MZ",
    "gn:dem":120,
    "gn:feature_class":"P",
    "gn:feature_code":"PPL",
    "gn:name":"Matibene",
    "gn:population":0,
    "gn:timezone":"Africa/Maputo",
    "iso:country":"MZ",
    "wof:name":"Matibene",
    "wof:placetype":"locality"
},
  "geometry": {"coordinates":[32.11667,-25.11667000000001],"type":"Point"}
}