{
  "type": "Feature",
  "properties": {
    "gn:admin1_code":"5",
    "gn:asciiname":"Malaca",
    "gn:country_code":"MZ",
    "gn:dem":13,
    "gn:feature_class":"P",
    "gn:feature_code":"PPL",
    "gn:name":"Malaca",
    "gn:population":0,
    "gn:timezone":"Africa/Maputo",
    "iso:country":"MZ",
    "name:bul_x_preferred":[
        "\u041c\u0430\u043b\u0430\u043a\u0430"
    ],
    "name:spa_x_preferred":[
        "Malaca"
    ],
    "wof:name":"Malaca",
    "wof:placetype":"locality"
},
  "geometry": {"coordinates":[34.47528,-20.16056],"type":"Point"}
}