{
  "type": "Feature",
  "properties": {
    "gn:admin1_code":"3.0",
    "gn:asciiname":"Bulafo",
    "gn:country_code":"MZ",
    "gn:dem":108,
    "gn:feature_class":"P",
    "gn:feature_code":"PPL",
    "gn:name":"Bulafo",
    "gn:population":0,
    "gn:timezone":"Africa/Maputo",
    "iso:country":"MZ",
    "wof:name":"Bulafo",
    "wof:placetype":"locality"
},
  "geometry": {"coordinates":[34.93639,-22.54528],"type":"Point"}
}