{
  "type": "Feature",
  "properties": {
    "gn:admin1_code":"10",
    "gn:asciiname":"Mabuto",
    "gn:country_code":"MZ",
    "gn:dem":397,
    "gn:feature_class":"P",
    "gn:feature_code":"PPL",
    "gn:name":"Mabuto",
    "gn:population":0,
    "gn:timezone":"Africa/Maputo",
    "iso:country":"MZ",
    "name:por_x_preferred":[
        "Mabuto"
    ],
    "wof:name":"Mabuto",
    "wof:placetype":"locality"
},
  "geometry": {"coordinates":[33.00278,-20.03583],"type":"Point"}
}