{
  "type": "Feature",
  "properties": {
    "gn:admin1_code":"1",
    "gn:asciiname":"Bagar",
    "gn:country_code":"MZ",
    "gn:dem":133,
    "gn:feature_class":"P",
    "gn:feature_code":"PPL",
    "gn:name":"Bagar",
    "gn:population":0,
    "gn:timezone":"Africa/Maputo",
    "iso:country":"MZ",
    "name:ceb_x_preferred":[
        "Bagar"
    ],
    "name:slv_x_preferred":[
        "Bagar"
    ],
    "name:swe_x_preferred":[
        "Bagar"
    ],
    "wof:name":"Bagar",
    "wof:placetype":"locality"
},
  "geometry": {"coordinates":[40.09361,-12.54694],"type":"Point"}
}