{
  "type": "Feature",
  "properties": {
    "gn:admin1_code":"3.0",
    "gn:asciiname":"Sainda",
    "gn:country_code":"MZ",
    "gn:dem":75,
    "gn:feature_class":"P",
    "gn:feature_code":"PPL",
    "gn:name":"Sainda",
    "gn:population":0,
    "gn:timezone":"Africa/Maputo",
    "iso:country":"MZ",
    "wof:name":"Sainda",
    "wof:placetype":"locality"
},
  "geometry": {"coordinates":[34.93472,-22.15889],"type":"Point"}
}