{
  "type": "Feature",
  "properties": {
    "gn:admin1_code":"3",
    "gn:asciiname":"Maviane",
    "gn:country_code":"MZ",
    "gn:dem":145,
    "gn:feature_class":"P",
    "gn:feature_code":"PPL",
    "gn:name":"Maviane",
    "gn:population":0,
    "gn:timezone":"Africa/Maputo",
    "iso:country":"MZ",
    "wof:name":"Maviane",
    "wof:placetype":"locality"
},
  "geometry": {"coordinates":[33.64778,-21.66417],"type":"Point"}
}