{
  "type": "Feature",
  "properties": {
    "gn:admin1_code":"9",
    "gn:asciiname":"Mpatchocalo",
    "gn:country_code":"MZ",
    "gn:dem":828,
    "gn:feature_class":"P",
    "gn:feature_code":"PPL",
    "gn:name":"Mpatch\u00f2c\u00e1lo",
    "gn:population":0,
    "gn:timezone":"Africa/Maputo",
    "iso:country":"MZ",
    "wof:name":"Mpatchocalo",
    "wof:placetype":"locality"
},
  "geometry": {"coordinates":[37.18917,-15.1625],"type":"Point"}
}