{
  "type": "Feature",
  "properties": {
    "gn:admin1_code":"10",
    "gn:asciiname":"Facanhe",
    "gn:country_code":"MZ",
    "gn:dem":151,
    "gn:feature_class":"P",
    "gn:feature_code":"PPL",
    "gn:name":"Facanhe",
    "gn:population":0,
    "gn:timezone":"Africa/Maputo",
    "iso:country":"MZ",
    "wof:name":"Facanhe",
    "wof:placetype":"locality"
},
  "geometry": {"coordinates":[33.32222,-19.91306],"type":"Point"}
}