{
  "type": "Feature",
  "properties": {
    "gn:admin1_code":"6",
    "gn:asciiname":"Catchave",
    "gn:country_code":"MZ",
    "gn:dem":131,
    "gn:feature_class":"P",
    "gn:feature_code":"PPL",
    "gn:name":"Catchave",
    "gn:population":0,
    "gn:timezone":"Africa/Maputo",
    "iso:country":"MZ",
    "wof:name":"Catchave",
    "wof:placetype":"locality"
},
  "geometry": {"coordinates":[40.53,-14.55361],"type":"Point"}
}