{
  "type": "Feature",
  "properties": {
    "gn:admin1_code":"2.0",
    "gn:asciiname":"Pio Alberto de Miranda Cabral",
    "gn:country_code":"MZ",
    "gn:dem":71,
    "gn:feature_class":"P",
    "gn:feature_code":"PPL",
    "gn:name":"Pio Alberto de Miranda Cabral",
    "gn:population":0,
    "gn:timezone":"Africa/Maputo",
    "iso:country":"MZ",
    "wof:name":"Pio Alberto de Miranda Cabral",
    "wof:placetype":"locality"
},
  "geometry": {"coordinates":[33.26944,-22.63056],"type":"Point"}
}