{
  "type": "Feature",
  "properties": {
    "gn:admin1_code":"2",
    "gn:asciiname":"Micevene",
    "gn:country_code":"MZ",
    "gn:dem":14,
    "gn:feature_class":"P",
    "gn:feature_code":"PPL",
    "gn:name":"Micevene",
    "gn:population":0,
    "gn:timezone":"Africa/Maputo",
    "iso:country":"MZ",
    "wof:name":"Micevene",
    "wof:placetype":"locality"
},
  "geometry": {"coordinates":[33.63667,-24.23083],"type":"Point"}
}