{
  "type": "Feature",
  "properties": {
    "gn:admin1_code":"6",
    "gn:asciiname":"Matipela",
    "gn:country_code":"MZ",
    "gn:dem":278,
    "gn:feature_class":"P",
    "gn:feature_code":"PPL",
    "gn:name":"Matipela",
    "gn:population":0,
    "gn:timezone":"Africa/Maputo",
    "iso:country":"MZ",
    "wof:name":"Matipela",
    "wof:placetype":"locality"
},
  "geometry": {"coordinates":[39.02222,-15.63389],"type":"Point"}
}