{
  "type": "Feature",
  "properties": {
    "gn:admin1_code":"6",
    "gn:asciiname":"Mauio",
    "gn:country_code":"MZ",
    "gn:dem":472,
    "gn:feature_class":"P",
    "gn:feature_code":"PPL",
    "gn:name":"Mauio",
    "gn:population":0,
    "gn:timezone":"Africa/Maputo",
    "iso:country":"MZ",
    "wof:name":"Mauio",
    "wof:placetype":"locality"
},
  "geometry": {"coordinates":[38.96833,-14.50139],"type":"Point"}
}