{
  "type": "Feature",
  "properties": {
    "gn:admin1_code":"2.0",
    "gn:asciiname":"Issai",
    "gn:country_code":"MZ",
    "gn:dem":75,
    "gn:feature_class":"P",
    "gn:feature_code":"PPL",
    "gn:name":"Issai",
    "gn:population":0,
    "gn:timezone":"Africa/Maputo",
    "iso:country":"MZ",
    "wof:name":"Issai",
    "wof:placetype":"locality"
},
  "geometry": {"coordinates":[32.9025,-23.86778],"type":"Point"}
}