{
  "type": "Feature",
  "properties": {
    "gn:admin1_code":"8",
    "gn:asciiname":"Nhana-Joana",
    "gn:country_code":"MZ",
    "gn:dem":413,
    "gn:feature_class":"P",
    "gn:feature_code":"PPL",
    "gn:name":"Nhana-Joana",
    "gn:population":0,
    "gn:timezone":"Africa/Maputo",
    "iso:country":"MZ",
    "wof:name":"Nhana-Joana",
    "wof:placetype":"locality"
},
  "geometry": {"coordinates":[33.42944,-16.25167],"type":"Point"}
}