{
  "type": "Feature",
  "properties": {
    "gn:admin1_code":"10",
    "gn:asciiname":"Niquice",
    "gn:country_code":"MZ",
    "gn:dem":397,
    "gn:feature_class":"P",
    "gn:feature_code":"PPL",
    "gn:name":"Niquice",
    "gn:population":0,
    "gn:timezone":"Africa/Maputo",
    "iso:country":"MZ",
    "wof:name":"Niquice",
    "wof:placetype":"locality"
},
  "geometry": {"coordinates":[33.20722,-20.85778],"type":"Point"}
}