{
  "type": "Feature",
  "properties": {
    "gn:admin1_code":"5.0",
    "gn:asciiname":"Conjane",
    "gn:country_code":"MZ",
    "gn:dem":64,
    "gn:feature_class":"P",
    "gn:feature_code":"PPL",
    "gn:name":"Conjane",
    "gn:population":0,
    "gn:timezone":"Africa/Maputo",
    "iso:country":"MZ",
    "wof:name":"Conjane",
    "wof:placetype":"locality"
},
  "geometry": {"coordinates":[34.20139,-21.24528],"type":"Point"}
}