{
  "type": "Feature",
  "properties": {
    "gn:admin1_code":"1",
    "gn:asciiname":"Chitima",
    "gn:country_code":"MZ",
    "gn:dem":420,
    "gn:feature_class":"P",
    "gn:feature_code":"PPL",
    "gn:name":"Chitima",
    "gn:population":0,
    "gn:timezone":"Africa/Maputo",
    "iso:country":"MZ",
    "wof:name":"Chitima",
    "wof:placetype":"locality"
},
  "geometry": {"coordinates":[39.42556,-13.00806],"type":"Point"}
}