{
  "type": "Feature",
  "properties": {
    "gn:admin1_code":"0",
    "gn:asciiname":"Ingoma",
    "gn:country_code":"MZ",
    "gn:dem":1108,
    "gn:feature_class":"P",
    "gn:feature_code":"PPL",
    "gn:name":"Ingoma",
    "gn:population":0,
    "gn:timezone":"Africa/Maputo",
    "iso:country":"MZ",
    "wof:name":"Ingoma",
    "wof:placetype":"locality"
},
  "geometry": {"coordinates":[35.31667,-13.01667],"type":"Point"}
}