{
  "type": "Feature",
  "properties": {
    "gn:admin1_code":"8.0",
    "gn:asciiname":"Rampi",
    "gn:country_code":"MZ",
    "gn:dem":360,
    "gn:feature_class":"P",
    "gn:feature_code":"PPL",
    "gn:name":"Rampi",
    "gn:population":0,
    "gn:timezone":"Africa/Maputo",
    "iso:country":"MZ",
    "wof:name":"Rampi",
    "wof:placetype":"locality"
},
  "geometry": {"coordinates":[33.16694,-16.10361],"type":"Point"}
}