{
  "type": "Feature",
  "properties": {
    "gn:admin1_code":"4",
    "gn:asciiname":"Canoca",
    "gn:country_code":"MZ",
    "gn:dem":94,
    "gn:feature_class":"P",
    "gn:feature_code":"PPL",
    "gn:name":"Canoca",
    "gn:population":0,
    "gn:timezone":"Africa/Maputo",
    "iso:country":"MZ",
    "wof:name":"Canoca",
    "wof:placetype":"locality"
},
  "geometry": {"coordinates":[32.13917,-26.02778],"type":"Point"}
}