{
  "type": "Feature",
  "properties": {
    "gn:admin1_code":"3.0",
    "gn:asciiname":"Maulungue",
    "gn:country_code":"MZ",
    "gn:dem":134,
    "gn:feature_class":"P",
    "gn:feature_code":"PPL",
    "gn:name":"Maulungue",
    "gn:population":0,
    "gn:timezone":"Africa/Maputo",
    "iso:country":"MZ",
    "wof:name":"Maulungue",
    "wof:placetype":"locality"
},
  "geometry": {"coordinates":[34.52111,-22.91917],"type":"Point"}
}