{
  "type": "Feature",
  "properties": {
    "gn:admin1_code":"6",
    "gn:asciiname":"Bernardo",
    "gn:country_code":"MZ",
    "gn:dem":169,
    "gn:feature_class":"P",
    "gn:feature_code":"PPL",
    "gn:name":"Bernardo",
    "gn:population":0,
    "gn:timezone":"Africa/Maputo",
    "iso:country":"MZ",
    "name:bel_x_preferred":[
        "\u0411\u0435\u0440\u043d\u0430\u0440\u0434\u0443"
    ],
    "name:deu_x_preferred":[
        "Bernardo"
    ],
    "name:ita_x_preferred":[
        "Bernardo"
    ],
    "name:slv_x_preferred":[
        "Bernardo"
    ],
    "name:spa_x_preferred":[
        "Bernardo"
    ],
    "wof:name":"Bernardo",
    "wof:placetype":"locality"
},
  "geometry": {"coordinates":[39.51028,-15.8425],"type":"Point"}
}