{
  "type": "Feature",
  "properties": {
    "gn:admin1_code":"9",
    "gn:asciiname":"Morroa",
    "gn:cc2":"MZ",
    "gn:country_code":"MZ",
    "gn:dem":14,
    "gn:feature_class":"P",
    "gn:feature_code":"PPL",
    "gn:name":"Morroa",
    "gn:population":0,
    "gn:timezone":"Africa/Maputo",
    "iso:country":"MZ",
    "name:und_x_variant":[
        "Morrua",
        "Morroa"
    ],
    "wof:name":"Morroa",
    "wof:placetype":"locality"
},
  "geometry": {"coordinates":[36.86944,-17.57917],"type":"Point"}
}