{
  "type": "Feature",
  "properties": {
    "gn:admin1_code":"9",
    "gn:asciiname":"Morroa",
    "gn:cc2":"MZ",
    "gn:country_code":"MZ",
    "gn:dem":14,
    "gn:feature_class":"P",
    "gn:feature_code":"PPL",
    "gn:name":"Morroa",
    "gn:population":0,
    "gn:timezone":"Africa/Maputo",
    "iso:country":"MZ",
    "name:ceb_x_preferred":[
        "Morroa"
    ],
    "name:fra_x_preferred":[
        "Morroa"
    ],
    "name:ita_x_preferred":[
        "Morroa"
    ],
    "name:kat_x_preferred":[
        "\u10db\u10dd\u10e0\u10dd\u10d0"
    ],
    "name:msa_x_preferred":[
        "Morroa"
    ],
    "name:nld_x_preferred":[
        "Morroa"
    ],
    "name:spa_x_preferred":[
        "Morroa"
    ],
    "name:swe_x_preferred":[
        "Morroa"
    ],
    "name:und_x_variant":[
        "Morrua"
    ],
    "name:vie_x_preferred":[
        "Morroa"
    ],
    "name:war_x_preferred":[
        "Morroa"
    ],
    "name:zho_x_preferred":[
        "\u83ab\u7f85\u963f"
    ],
    "wof:name":"Morroa",
    "wof:placetype":"locality"
},
  "geometry": {"coordinates":[36.86944,-17.57917],"type":"Point"}
}