{
  "type": "Feature",
  "properties": {
    "gn:admin1_code":"3.0",
    "gn:asciiname":"Regulo Machacame",
    "gn:country_code":"MZ",
    "gn:dem":18,
    "gn:feature_class":"P",
    "gn:feature_code":"PPL",
    "gn:name":"R\u00e9gulo Machacame",
    "gn:population":0,
    "gn:timezone":"Africa/Maputo",
    "iso:country":"MZ",
    "wof:name":"Regulo Machacame",
    "wof:placetype":"locality"
},
  "geometry": {"coordinates":[34.62472,-21.10694],"type":"Point"}
}