{
  "type": "Feature",
  "properties": {
    "gn:admin1_code":"8",
    "gn:asciiname":"Funchal",
    "gn:country_code":"MZ",
    "gn:dem":361,
    "gn:feature_class":"P",
    "gn:feature_code":"PPL",
    "gn:name":"Funchal",
    "gn:population":0,
    "gn:timezone":"Africa/Maputo",
    "iso:country":"MZ",
    "wof:name":"Funchal",
    "wof:placetype":"locality"
},
  "geometry": {"coordinates":[30.54972,-15.99556],"type":"Point"}
}