{
  "type": "Feature",
  "properties": {
    "gn:admin1_code":"6",
    "gn:asciiname":"Muala",
    "gn:country_code":"MZ",
    "gn:dem":566,
    "gn:feature_class":"P",
    "gn:feature_code":"PPL",
    "gn:name":"Muala",
    "gn:population":0,
    "gn:timezone":"Africa/Maputo",
    "iso:country":"MZ",
    "wof:name":"Muala",
    "wof:placetype":"locality"
},
  "geometry": {"coordinates":[37.58944,-14.7025],"type":"Point"}
}