{
  "type": "Feature",
  "properties": {
    "gn:admin1_code":"1",
    "gn:asciiname":"Auazi",
    "gn:country_code":"MZ",
    "gn:dem":49,
    "gn:feature_class":"P",
    "gn:feature_code":"PPL",
    "gn:name":"Auazi",
    "gn:population":0,
    "gn:timezone":"Africa/Maputo",
    "iso:country":"MZ",
    "wof:name":"Auazi",
    "wof:placetype":"locality"
},
  "geometry": {"coordinates":[40.22583,-12.57389],"type":"Point"}
}