{
  "type": "Feature",
  "properties": {
    "gn:admin1_code":"3.0",
    "gn:asciiname":"Malavane",
    "gn:country_code":"MZ",
    "gn:dem":133,
    "gn:feature_class":"P",
    "gn:feature_code":"PPL",
    "gn:name":"Malavane",
    "gn:population":0,
    "gn:timezone":"Africa/Maputo",
    "iso:country":"MZ",
    "wof:name":"Malavane",
    "wof:placetype":"locality"
},
  "geometry": {"coordinates":[34.525,-22.97028],"type":"Point"}
}