{
  "type": "Feature",
  "properties": {
    "gn:admin1_code":"9",
    "gn:asciiname":"Maco",
    "gn:country_code":"MZ",
    "gn:dem":320,
    "gn:feature_class":"P",
    "gn:feature_code":"PPL",
    "gn:name":"Maco",
    "gn:population":0,
    "gn:timezone":"Africa/Maputo",
    "iso:country":"MZ",
    "name:ceb_x_preferred":[
        "Maco"
    ],
    "name:deu_x_preferred":[
        "Maco"
    ],
    "name:fra_x_preferred":[
        "Maco"
    ],
    "name:nld_x_preferred":[
        "Maco"
    ],
    "name:slk_x_preferred":[
        "Maco"
    ],
    "name:spa_x_preferred":[
        "Maco"
    ],
    "name:swe_x_preferred":[
        "Maco"
    ],
    "wof:name":"Maco",
    "wof:placetype":"locality"
},
  "geometry": {"coordinates":[37.70444000000001,-16.13194],"type":"Point"}
}