{
  "type": "Feature",
  "properties": {
    "gn:admin1_code":"1",
    "gn:asciiname":"Cobela",
    "gn:country_code":"MZ",
    "gn:dem":480,
    "gn:feature_class":"P",
    "gn:feature_code":"PPL",
    "gn:name":"Cobela",
    "gn:population":0,
    "gn:timezone":"Africa/Maputo",
    "iso:country":"MZ",
    "wof:name":"Cobela",
    "wof:placetype":"locality"
},
  "geometry": {"coordinates":[38.81917,-13.10361],"type":"Point"}
}