{
  "type": "Feature",
  "properties": {
    "gn:admin1_code":"9",
    "gn:asciiname":"Quimeca",
    "gn:country_code":"MZ",
    "gn:dem":418,
    "gn:feature_class":"P",
    "gn:feature_code":"PPL",
    "gn:name":"Quimeca",
    "gn:population":0,
    "gn:timezone":"Africa/Maputo",
    "iso:country":"MZ",
    "wof:name":"Quimeca",
    "wof:placetype":"locality"
},
  "geometry": {"coordinates":[37.82944000000001,-15.94083],"type":"Point"}
}