{
  "type": "Feature",
  "properties": {
    "gn:admin1_code":"7",
    "gn:asciiname":"Chefe Mongorra",
    "gn:country_code":"MZ",
    "gn:dem":645,
    "gn:feature_class":"P",
    "gn:feature_code":"PPL",
    "gn:name":"Chefe Mongorra",
    "gn:population":0,
    "gn:timezone":"Africa/Maputo",
    "iso:country":"MZ",
    "wof:name":"Chefe Mongorra",
    "wof:placetype":"locality"
},
  "geometry": {"coordinates":[35.96805999999999,-14.75111],"type":"Point"}
}