{
  "type": "Feature",
  "properties": {
    "gn:admin1_code":"7",
    "gn:asciiname":"Abudo",
    "gn:country_code":"MZ",
    "gn:dem":736,
    "gn:feature_class":"P",
    "gn:feature_code":"PPL",
    "gn:name":"Abudo",
    "gn:population":0,
    "gn:timezone":"Africa/Maputo",
    "iso:country":"MZ",
    "wof:name":"Abudo",
    "wof:placetype":"locality"
},
  "geometry": {"coordinates":[35.66222,-14.36583],"type":"Point"}
}