{
  "type": "Feature",
  "properties": {
    "gn:admin1_code":"6",
    "gn:asciiname":"Macuto",
    "gn:country_code":"MZ",
    "gn:dem":353,
    "gn:feature_class":"P",
    "gn:feature_code":"PPL",
    "gn:name":"Macuto",
    "gn:population":0,
    "gn:timezone":"Africa/Maputo",
    "iso:country":"MZ",
    "name:ita_x_preferred":[
        "Maclovio"
    ],
    "wof:name":"Macuto",
    "wof:placetype":"locality"
},
  "geometry": {"coordinates":[39.60278,-14.02389],"type":"Point"}
}