{
  "type": "Feature",
  "properties": {
    "gn:admin1_code":"3.0",
    "gn:asciiname":"Zambetane",
    "gn:country_code":"MZ",
    "gn:dem":107,
    "gn:feature_class":"P",
    "gn:feature_code":"PPL",
    "gn:name":"Zambetane",
    "gn:population":0,
    "gn:timezone":"Africa/Maputo",
    "iso:country":"MZ",
    "wof:name":"Zambetane",
    "wof:placetype":"locality"
},
  "geometry": {"coordinates":[34.855,-22.19222],"type":"Point"}
}