{
  "type": "Feature",
  "properties": {
    "gn:admin1_code":"1",
    "gn:asciiname":"Chefe Puepue",
    "gn:country_code":"MZ",
    "gn:dem":423,
    "gn:feature_class":"P",
    "gn:feature_code":"PPL",
    "gn:name":"Chefe Pu\u00e9pu\u00e8",
    "gn:population":0,
    "gn:timezone":"Africa/Maputo",
    "iso:country":"MZ",
    "wof:name":"Chefe Puepue",
    "wof:placetype":"locality"
},
  "geometry": {"coordinates":[38.84806,-13.77],"type":"Point"}
}