{
  "type": "Feature",
  "properties": {
    "gn:admin1_code":"5",
    "gn:asciiname":"Cavalane",
    "gn:country_code":"MZ",
    "gn:dem":51,
    "gn:feature_class":"P",
    "gn:feature_code":"PPL",
    "gn:name":"Cavalane",
    "gn:population":0,
    "gn:timezone":"Africa/Maputo",
    "iso:country":"MZ",
    "wof:name":"Cavalane",
    "wof:placetype":"locality"
},
  "geometry": {"coordinates":[34.34833,-21.28694],"type":"Point"}
}