{
  "type": "Feature",
  "properties": {
    "gn:admin1_code":"6",
    "gn:asciiname":"Mussa",
    "gn:country_code":"MZ",
    "gn:dem":357,
    "gn:feature_class":"P",
    "gn:feature_code":"PPL",
    "gn:name":"Mussa",
    "gn:population":0,
    "gn:timezone":"Africa/Maputo",
    "iso:country":"MZ",
    "name:cat_x_preferred":[
        "Mussa"
    ],
    "name:ceb_x_preferred":[
        "Mussa"
    ],
    "name:deu_x_preferred":[
        "Mussa"
    ],
    "name:ita_x_preferred":[
        "Mussa"
    ],
    "name:swe_x_preferred":[
        "Mussa"
    ],
    "wof:name":"Mussa",
    "wof:placetype":"locality"
},
  "geometry": {"coordinates":[39.40639,-15.25],"type":"Point"}
}