{
  "type": "Feature",
  "properties": {
    "gn:admin1_code":"8",
    "gn:asciiname":"Chaconda",
    "gn:country_code":"MZ",
    "gn:dem":678,
    "gn:feature_class":"P",
    "gn:feature_code":"PPL",
    "gn:name":"Chaconda",
    "gn:population":0,
    "gn:timezone":"Africa/Maputo",
    "iso:country":"MZ",
    "wof:name":"Chaconda",
    "wof:placetype":"locality"
},
  "geometry": {"coordinates":[32.32333,-14.97944],"type":"Point"}
}