{
  "type": "Feature",
  "properties": {
    "gn:admin1_code":"7",
    "gn:asciiname":"Catial",
    "gn:country_code":"MZ",
    "gn:dem":1297,
    "gn:feature_class":"P",
    "gn:feature_code":"PPL",
    "gn:name":"Catial",
    "gn:population":0,
    "gn:timezone":"Africa/Maputo",
    "iso:country":"MZ",
    "wof:name":"Catial",
    "wof:placetype":"locality"
},
  "geometry": {"coordinates":[35.06417,-11.57556],"type":"Point"}
}