{
  "type": "Feature",
  "properties": {
    "gn:admin1_code":"2",
    "gn:asciiname":"Dumela",
    "gn:country_code":"MZ",
    "gn:dem":206,
    "gn:feature_class":"P",
    "gn:feature_code":"PPL",
    "gn:name":"Dumela",
    "gn:population":0,
    "gn:timezone":"Africa/Maputo",
    "iso:country":"MZ",
    "wof:name":"Dumela",
    "wof:placetype":"locality"
},
  "geometry": {"coordinates":[31.32806,-22.42444],"type":"Point"}
}