{
  "type": "Feature",
  "properties": {
    "gn:admin1_code":"3",
    "gn:asciiname":"Muguebo",
    "gn:country_code":"MZ",
    "gn:dem":163,
    "gn:feature_class":"P",
    "gn:feature_code":"PPL",
    "gn:name":"Muguebo",
    "gn:population":0,
    "gn:timezone":"Africa/Maputo",
    "iso:country":"MZ",
    "wof:name":"Muguebo",
    "wof:placetype":"locality"
},
  "geometry": {"coordinates":[33.77111,-21.68806],"type":"Point"}
}