{
  "type": "Feature",
  "properties": {
    "gn:admin1_code":"3",
    "gn:asciiname":"Macave",
    "gn:country_code":"MZ",
    "gn:dem":146,
    "gn:feature_class":"P",
    "gn:feature_code":"PPL",
    "gn:name":"Macave",
    "gn:population":0,
    "gn:timezone":"Africa/Maputo",
    "iso:country":"MZ",
    "wof:name":"Macave",
    "wof:placetype":"locality"
},
  "geometry": {"coordinates":[34.36944,-22.54972],"type":"Point"}
}