{
  "type": "Feature",
  "properties": {
    "gn:admin1_code":"4",
    "gn:asciiname":"Constantino",
    "gn:country_code":"MZ",
    "gn:dem":83,
    "gn:feature_class":"P",
    "gn:feature_code":"PPL",
    "gn:name":"Constantino",
    "gn:population":0,
    "gn:timezone":"Africa/Maputo",
    "iso:country":"MZ",
    "name:deu_x_preferred":[
        "Constantino"
    ],
    "name:glg_x_preferred":[
        "Constantino"
    ],
    "name:ita_x_preferred":[
        "Constantino"
    ],
    "name:por_x_preferred":[
        "Constantino"
    ],
    "name:spa_x_preferred":[
        "Constantino"
    ],
    "wof:name":"Constantino",
    "wof:placetype":"locality"
},
  "geometry": {"coordinates":[32.49056,-24.72806],"type":"Point"}
}