{
  "type": "Feature",
  "properties": {
    "gn:admin1_code":"7",
    "gn:asciiname":"Mbamba",
    "gn:country_code":"MZ",
    "gn:dem":476,
    "gn:feature_class":"P",
    "gn:feature_code":"PPL",
    "gn:name":"Mbamba",
    "gn:population":0,
    "gn:timezone":"Africa/Maputo",
    "iso:country":"MZ",
    "wof:name":"Mbamba",
    "wof:placetype":"locality"
},
  "geometry": {"coordinates":[34.755,-12.55111],"type":"Point"}
}