{
  "type": "Feature",
  "properties": {
    "gn:admin1_code":"3.0",
    "gn:asciiname":"Naite Maoiane",
    "gn:country_code":"MZ",
    "gn:dem":59,
    "gn:feature_class":"P",
    "gn:feature_code":"PPL",
    "gn:name":"Na\u00edte Mao\u00edane",
    "gn:population":0,
    "gn:timezone":"Africa/Maputo",
    "iso:country":"MZ",
    "wof:name":"Naite Maoiane",
    "wof:placetype":"locality"
},
  "geometry": {"coordinates":[35.09028,-24.02972],"type":"Point"}
}