{
  "type": "Feature",
  "properties": {
    "gn:admin1_code":"6",
    "gn:asciiname":"Namputa",
    "gn:country_code":"MZ",
    "gn:dem":279,
    "gn:feature_class":"P",
    "gn:feature_code":"PPL",
    "gn:name":"Namputa",
    "gn:population":0,
    "gn:timezone":"Africa/Maputo",
    "iso:country":"MZ",
    "wof:name":"Namputa",
    "wof:placetype":"locality"
},
  "geometry": {"coordinates":[39.57833,-15.34278],"type":"Point"}
}