{
  "type": "Feature",
  "properties": {
    "gn:admin1_code":"1",
    "gn:asciiname":"Muadi",
    "gn:country_code":"MZ",
    "gn:dem":577,
    "gn:feature_class":"P",
    "gn:feature_code":"PPL",
    "gn:name":"Muadi",
    "gn:population":0,
    "gn:timezone":"Africa/Maputo",
    "iso:country":"MZ",
    "wof:name":"Muadi",
    "wof:placetype":"locality"
},
  "geometry": {"coordinates":[39.67417,-11.40139],"type":"Point"}
}