{
  "type": "Feature",
  "properties": {
    "gn:admin1_code":"6",
    "gn:asciiname":"Napela",
    "gn:country_code":"MZ",
    "gn:dem":578,
    "gn:feature_class":"P",
    "gn:feature_code":"PPL",
    "gn:name":"Nap\u00e9la",
    "gn:population":0,
    "gn:timezone":"Africa/Maputo",
    "iso:country":"MZ",
    "wof:name":"Napela",
    "wof:placetype":"locality"
},
  "geometry": {"coordinates":[38.63944,-14.86722],"type":"Point"}
}