{
  "type": "Feature",
  "properties": {
    "gn:admin1_code":"8",
    "gn:asciiname":"Aldeia Chivungo",
    "gn:country_code":"MZ",
    "gn:dem":524,
    "gn:feature_class":"P",
    "gn:feature_code":"PPL",
    "gn:name":"Aldeia Chivungo",
    "gn:population":0,
    "gn:timezone":"Africa/Maputo",
    "iso:country":"MZ",
    "wof:name":"Aldeia Chivungo",
    "wof:placetype":"locality"
},
  "geometry": {"coordinates":[32.45806,-15.28611],"type":"Point"}
}