{
  "type": "Feature",
  "properties": {
    "gn:admin1_code":"9.0",
    "gn:asciiname":"Vaissele",
    "gn:country_code":"MZ",
    "gn:dem":243,
    "gn:feature_class":"P",
    "gn:feature_code":"PPL",
    "gn:name":"Vaissele",
    "gn:population":0,
    "gn:timezone":"Africa/Maputo",
    "iso:country":"MZ",
    "wof:name":"Vaissele",
    "wof:placetype":"locality"
},
  "geometry": {"coordinates":[38.23472,-16.28306],"type":"Point"}
}