{
  "type": "Feature",
  "properties": {
    "gn:admin1_code":"9",
    "gn:asciiname":"Murrebua",
    "gn:country_code":"MZ",
    "gn:dem":192,
    "gn:feature_class":"P",
    "gn:feature_code":"PPL",
    "gn:name":"Murrebua",
    "gn:population":0,
    "gn:timezone":"Africa/Maputo",
    "iso:country":"MZ",
    "wof:name":"Murrebua",
    "wof:placetype":"locality"
},
  "geometry": {"coordinates":[37.84972,-16.615],"type":"Point"}
}