{
  "type": "Feature",
  "properties": {
    "gn:admin1_code":"1",
    "gn:asciiname":"Adala",
    "gn:country_code":"MZ",
    "gn:dem":141,
    "gn:feature_class":"P",
    "gn:feature_code":"PPL",
    "gn:name":"Adala",
    "gn:population":0,
    "gn:timezone":"Africa/Maputo",
    "iso:country":"MZ",
    "wof:name":"Adala",
    "wof:placetype":"locality"
},
  "geometry": {"coordinates":[40.13333,-10.87667],"type":"Point"}
}