{
  "type": "Feature",
  "properties": {
    "gn:admin1_code":"6",
    "gn:asciiname":"Suale",
    "gn:country_code":"MZ",
    "gn:dem":26,
    "gn:feature_class":"P",
    "gn:feature_code":"PPL",
    "gn:name":"Suale",
    "gn:population":0,
    "gn:timezone":"Africa/Maputo",
    "iso:country":"MZ",
    "wof:name":"Suale",
    "wof:placetype":"locality"
},
  "geometry": {"coordinates":[39.70222,-16.18],"type":"Point"}
}