{
  "type": "Feature",
  "properties": {
    "gn:admin1_code":"4",
    "gn:asciiname":"J. Buissa",
    "gn:country_code":"MZ",
    "gn:dem":289,
    "gn:feature_class":"P",
    "gn:feature_code":"PPL",
    "gn:name":"J. Buissa",
    "gn:population":0,
    "gn:timezone":"Africa/Maputo",
    "iso:country":"MZ",
    "wof:name":"J. Buissa",
    "wof:placetype":"locality"
},
  "geometry": {"coordinates":[32.09472,-26.32389],"type":"Point"}
}