{
  "type": "Feature",
  "properties": {
    "gn:admin1_code":"3",
    "gn:asciiname":"Cabo Massemane",
    "gn:cc2":"MZ",
    "gn:country_code":"MZ",
    "gn:dem":121,
    "gn:feature_class":"P",
    "gn:feature_code":"PPL",
    "gn:name":"Cabo Massemane",
    "gn:population":0,
    "gn:timezone":"Africa/Maputo",
    "iso:country":"MZ",
    "name:und_x_variant":[
        "Massemane",
        "Cabo Massemane"
    ],
    "wof:name":"Cabo Massemane",
    "wof:placetype":"locality"
},
  "geometry": {"coordinates":[34.66556,-24.04111],"type":"Point"}
}