{
  "type": "Feature",
  "properties": {
    "gn:admin1_code":"1",
    "gn:asciiname":"Chapa",
    "gn:country_code":"MZ",
    "gn:dem":305,
    "gn:feature_class":"P",
    "gn:feature_code":"PPL",
    "gn:name":"Chapa",
    "gn:population":0,
    "gn:timezone":"Africa/Maputo",
    "iso:country":"MZ",
    "name:ceb_x_preferred":[
        "Chapa"
    ],
    "name:deu_x_preferred":[
        "Chapa"
    ],
    "name:glg_x_preferred":[
        "Chapa"
    ],
    "name:nld_x_preferred":[
        "Chapa"
    ],
    "name:por_x_preferred":[
        "Chapa"
    ],
    "name:swe_x_preferred":[
        "Chapa"
    ],
    "wof:name":"Chapa",
    "wof:placetype":"locality"
},
  "geometry": {"coordinates":[39.41806,-11.84],"type":"Point"}
}