{
  "type": "Feature",
  "properties": {
    "gn:admin1_code":"8",
    "gn:asciiname":"Aldeia Mpuephue",
    "gn:country_code":"MZ",
    "gn:dem":775,
    "gn:feature_class":"P",
    "gn:feature_code":"PPL",
    "gn:name":"Aldeia Mpuephue",
    "gn:population":0,
    "gn:timezone":"Africa/Maputo",
    "iso:country":"MZ",
    "wof:name":"Aldeia Mpuephue",
    "wof:placetype":"locality"
},
  "geometry": {"coordinates":[31.49333,-15.365],"type":"Point"}
}