{
  "type": "Feature",
  "properties": {
    "gn:admin1_code":"4",
    "gn:asciiname":"Jojo",
    "gn:country_code":"MZ",
    "gn:dem":85,
    "gn:feature_class":"P",
    "gn:feature_code":"PPL",
    "gn:name":"J\u00f4jo",
    "gn:population":0,
    "gn:timezone":"Africa/Maputo",
    "iso:country":"MZ",
    "name:nor_x_preferred":[
        "Jojo"
    ],
    "wof:name":"Jojo",
    "wof:placetype":"locality"
},
  "geometry": {"coordinates":[32.2475,-25.3925],"type":"Point"}
}