{
  "type": "Feature",
  "properties": {
    "gn:admin1_code":"7",
    "gn:asciiname":"Chefe Mupina",
    "gn:country_code":"MZ",
    "gn:dem":731,
    "gn:feature_class":"P",
    "gn:feature_code":"PPL",
    "gn:name":"Chefe Mupina",
    "gn:population":0,
    "gn:timezone":"Africa/Maputo",
    "iso:country":"MZ",
    "wof:name":"Chefe Mupina",
    "wof:placetype":"locality"
},
  "geometry": {"coordinates":[35.74694,-14.26694],"type":"Point"}
}