{
  "type": "Feature",
  "properties": {
    "gn:admin1_code":"6.0",
    "gn:asciiname":"Prima",
    "gn:country_code":"MZ",
    "gn:dem":310,
    "gn:feature_class":"P",
    "gn:feature_code":"PPL",
    "gn:name":"Prima",
    "gn:population":0,
    "gn:timezone":"Africa/Maputo",
    "iso:country":"MZ",
    "wof:name":"Prima",
    "wof:placetype":"locality"
},
  "geometry": {"coordinates":[38.92556,-15.42722],"type":"Point"}
}