{
  "type": "Feature",
  "properties": {
    "gn:admin1_code":"6.0",
    "gn:asciiname":"Prima",
    "gn:country_code":"MZ",
    "gn:dem":310,
    "gn:feature_class":"P",
    "gn:feature_code":"PPL",
    "gn:name":"Prima",
    "gn:population":0,
    "gn:timezone":"Africa/Maputo",
    "iso:country":"MZ",
    "name:ces_x_preferred":[
        "Prima"
    ],
    "name:deu_x_preferred":[
        "Prima"
    ],
    "name:eus_x_preferred":[
        "Prima"
    ],
    "name:fin_x_preferred":[
        "Prima"
    ],
    "name:fra_x_preferred":[
        "Prima"
    ],
    "name:heb_x_preferred":[
        "\u05e4\u05e8\u05d9\u05de\u05d4"
    ],
    "name:hye_x_preferred":[
        "\u054a\u0580\u056b\u0574\u0561"
    ],
    "name:ita_x_preferred":[
        "Prima"
    ],
    "name:nld_x_preferred":[
        "Prima"
    ],
    "name:por_x_preferred":[
        "Prima"
    ],
    "name:rus_x_preferred":[
        "\u041f\u0440\u0438\u043c\u0430"
    ],
    "name:slv_x_preferred":[
        "Prima"
    ],
    "name:spa_x_preferred":[
        "Prima"
    ],
    "name:ukr_x_preferred":[
        "\u041f\u0440\u0438\u043c\u0430"
    ],
    "wof:name":"Prima",
    "wof:placetype":"locality"
},
  "geometry": {"coordinates":[38.92556,-15.42722],"type":"Point"}
}