{
  "type": "Feature",
  "properties": {
    "gn:admin1_code":"1",
    "gn:asciiname":"Bissee",
    "gn:country_code":"MZ",
    "gn:dem":56,
    "gn:feature_class":"P",
    "gn:feature_code":"PPL",
    "gn:name":"Biss\u00e9e",
    "gn:population":0,
    "gn:timezone":"Africa/Maputo",
    "iso:country":"MZ",
    "wof:name":"Bissee",
    "wof:placetype":"locality"
},
  "geometry": {"coordinates":[40.19889000000001,-12.5075],"type":"Point"}
}