{
  "type": "Feature",
  "properties": {
    "gn:admin1_code":"1",
    "gn:asciiname":"Bissee",
    "gn:country_code":"MZ",
    "gn:dem":56,
    "gn:feature_class":"P",
    "gn:feature_code":"PPL",
    "gn:name":"Biss\u00e9e",
    "gn:population":0,
    "gn:timezone":"Africa/Maputo",
    "iso:country":"MZ",
    "name:ceb_x_preferred":[
        "Bissee"
    ],
    "name:dan_x_preferred":[
        "Bissee"
    ],
    "name:deu_x_preferred":[
        "Bissee"
    ],
    "name:epo_x_preferred":[
        "Bissee"
    ],
    "name:eus_x_preferred":[
        "Bissee"
    ],
    "name:fra_x_preferred":[
        "Bissee"
    ],
    "name:hun_x_preferred":[
        "Bissee"
    ],
    "name:ita_x_preferred":[
        "Bissee"
    ],
    "name:mkd_x_preferred":[
        "\u0411\u0438\u0441\u0437\u0435"
    ],
    "name:msa_x_preferred":[
        "Bissee"
    ],
    "name:nld_x_preferred":[
        "Bissee"
    ],
    "name:pol_x_preferred":[
        "Bissee"
    ],
    "name:por_x_preferred":[
        "Bissee"
    ],
    "name:ron_x_preferred":[
        "Bissee"
    ],
    "name:rus_x_preferred":[
        "\u0411\u0438\u0441\u0437\u0435"
    ],
    "name:spa_x_preferred":[
        "Bissee"
    ],
    "name:srp_x_preferred":[
        "\u0411\u0438\u0441\u0437\u0435"
    ],
    "name:tur_x_preferred":[
        "Bissee"
    ],
    "name:ukr_x_preferred":[
        "\u0411\u0456\u0441\u0441\u0435"
    ],
    "name:uzb_x_preferred":[
        "Bissee"
    ],
    "name:vie_x_preferred":[
        "Bissee"
    ],
    "name:vol_x_preferred":[
        "Bissee"
    ],
    "name:war_x_preferred":[
        "Bissee"
    ],
    "wof:name":"Bissee",
    "wof:placetype":"locality"
},
  "geometry": {"coordinates":[40.19889000000001,-12.5075],"type":"Point"}
}