{
  "type": "Feature",
  "properties": {
    "gn:admin1_code":"7.0",
    "gn:asciiname":"Vipo",
    "gn:country_code":"MZ",
    "gn:dem":485,
    "gn:feature_class":"P",
    "gn:feature_code":"PPL",
    "gn:name":"Vipo",
    "gn:population":0,
    "gn:timezone":"Africa/Maputo",
    "iso:country":"MZ",
    "wof:name":"Vipo",
    "wof:placetype":"locality"
},
  "geometry": {"coordinates":[34.78028,-12.84861],"type":"Point"}
}