{
  "type": "Feature",
  "properties": {
    "gn:admin1_code":"5",
    "gn:asciiname":"Bingue",
    "gn:country_code":"MZ",
    "gn:dem":9,
    "gn:feature_class":"P",
    "gn:feature_code":"PPL",
    "gn:name":"Bingu\u00e8",
    "gn:population":0,
    "gn:timezone":"Africa/Maputo",
    "iso:country":"MZ",
    "wof:name":"Bingue",
    "wof:placetype":"locality"
},
  "geometry": {"coordinates":[35.39556,-19.38667],"type":"Point"}
}