{
  "type": "Feature",
  "properties": {
    "gn:admin1_code":"3.0",
    "gn:asciiname":"Julai",
    "gn:country_code":"MZ",
    "gn:dem":64,
    "gn:feature_class":"P",
    "gn:feature_code":"PPL",
    "gn:name":"Julai",
    "gn:population":0,
    "gn:timezone":"Africa/Maputo",
    "iso:country":"MZ",
    "name:ara_x_preferred":[
        "\u062c\u0648\u0644\u0627\u064a"
    ],
    "name:fas_x_preferred":[
        "\u062c\u0648\u0644\u0627\u06cc"
    ],
    "name:fin_x_preferred":[
        "Julayi"
    ],
    "name:tel_x_preferred":[
        "\u0c1c\u0c41\u0c32\u0c3e\u0c2f\u0c3f"
    ],
    "name:urd_x_preferred":[
        "\u062c\u0648\u0644\u0627\u0626\u06cc"
    ],
    "wof:name":"Julai",
    "wof:placetype":"locality"
},
  "geometry": {"coordinates":[34.87972,-21.58694],"type":"Point"}
}