{
  "type": "Feature",
  "properties": {
    "gn:admin1_code":"2.0",
    "gn:asciiname":"Regulo Chicualacuala",
    "gn:country_code":"MZ",
    "gn:dem":177,
    "gn:feature_class":"P",
    "gn:feature_code":"PPL",
    "gn:name":"Regulo Chicualacuala",
    "gn:population":0,
    "gn:timezone":"Africa/Maputo",
    "iso:country":"MZ",
    "wof:name":"Regulo Chicualacuala",
    "wof:placetype":"locality"
},
  "geometry": {"coordinates":[31.72472,-22.59528],"type":"Point"}
}