{
  "type": "Feature",
  "properties": {
    "gn:admin1_code":"9.0",
    "gn:asciiname":"Chefe Mualota",
    "gn:country_code":"MZ",
    "gn:dem":50,
    "gn:feature_class":"P",
    "gn:feature_code":"PPL",
    "gn:name":"Chefe Mualota",
    "gn:population":0,
    "gn:timezone":"Africa/Maputo",
    "iso:country":"MZ",
    "wof:name":"Chefe Mualota",
    "wof:placetype":"locality"
},
  "geometry": {"coordinates":[38.25694,-17.11861],"type":"Point"}
}