{
  "type": "Feature",
  "properties": {
    "gn:admin1_code":"6",
    "gn:asciiname":"Periqueia",
    "gn:country_code":"MZ",
    "gn:dem":608,
    "gn:feature_class":"P",
    "gn:feature_code":"PPL",
    "gn:name":"Periqueia",
    "gn:population":0,
    "gn:timezone":"Africa/Maputo",
    "iso:country":"MZ",
    "wof:name":"Periqueia",
    "wof:placetype":"locality"
},
  "geometry": {"coordinates":[36.925,-14.83056],"type":"Point"}
}