{
  "type": "Feature",
  "properties": {
    "gn:admin1_code":"9",
    "gn:asciiname":"Natepo",
    "gn:country_code":"MZ",
    "gn:dem":13,
    "gn:feature_class":"P",
    "gn:feature_code":"PPL",
    "gn:name":"Natepo",
    "gn:population":0,
    "gn:timezone":"Africa/Maputo",
    "iso:country":"MZ",
    "wof:name":"Natepo",
    "wof:placetype":"locality"
},
  "geometry": {"coordinates":[37.70611,-17.41139],"type":"Point"}
}