{
  "type": "Feature",
  "properties": {
    "gn:admin1_code":"9.0",
    "gn:asciiname":"Tondue",
    "gn:country_code":"MZ",
    "gn:dem":263,
    "gn:feature_class":"P",
    "gn:feature_code":"PPL",
    "gn:name":"Tondu\u00e8",
    "gn:population":0,
    "gn:timezone":"Africa/Maputo",
    "iso:country":"MZ",
    "wof:name":"Tondue",
    "wof:placetype":"locality"
},
  "geometry": {"coordinates":[36.705,-16.91528],"type":"Point"}
}