{
  "type": "Feature",
  "properties": {
    "gn:admin1_code":"6",
    "gn:asciiname":"Cabo Munisai",
    "gn:country_code":"MZ",
    "gn:dem":246,
    "gn:feature_class":"P",
    "gn:feature_code":"PPL",
    "gn:name":"Cabo Munisai",
    "gn:population":0,
    "gn:timezone":"Africa/Maputo",
    "iso:country":"MZ",
    "wof:name":"Cabo Munisai",
    "wof:placetype":"locality"
},
  "geometry": {"coordinates":[40.29389000000001,-13.76556],"type":"Point"}
}