{
  "type": "Feature",
  "properties": {
    "gn:admin1_code":"9.0",
    "gn:asciiname":"Rezendo",
    "gn:cc2":"MZ",
    "gn:country_code":"MZ",
    "gn:dem":99,
    "gn:feature_class":"P",
    "gn:feature_code":"PPL",
    "gn:name":"Rezendo",
    "gn:population":0,
    "gn:timezone":"Africa/Maputo",
    "iso:country":"MZ",
    "name:und_x_variant":[
        "Rozendo",
        "Rezendo"
    ],
    "wof:name":"Rezendo",
    "wof:placetype":"locality"
},
  "geometry": {"coordinates":[36.31361,-17.5325],"type":"Point"}
}