{
  "type": "Feature",
  "properties": {
    "gn:admin1_code":"10",
    "gn:asciiname":"Guelande",
    "gn:country_code":"MZ",
    "gn:dem":137,
    "gn:feature_class":"P",
    "gn:feature_code":"PPL",
    "gn:name":"Guelande",
    "gn:population":0,
    "gn:timezone":"Africa/Maputo",
    "iso:country":"MZ",
    "wof:name":"Guelande",
    "wof:placetype":"locality"
},
  "geometry": {"coordinates":[33.79278,-20.76611],"type":"Point"}
}