{
  "type": "Feature",
  "properties": {
    "gn:admin1_code":"3.0",
    "gn:asciiname":"Laco",
    "gn:country_code":"MZ",
    "gn:dem":174,
    "gn:feature_class":"P",
    "gn:feature_code":"PPL",
    "gn:name":"La\u00e7o",
    "gn:population":0,
    "gn:timezone":"Africa/Maputo",
    "iso:country":"MZ",
    "wof:name":"Laco",
    "wof:placetype":"locality"
},
  "geometry": {"coordinates":[34.44694,-22.28889],"type":"Point"}
}