{
  "type": "Feature",
  "properties": {
    "gn:admin1_code":"1",
    "gn:asciiname":"Mitope",
    "gn:country_code":"MZ",
    "gn:dem":163,
    "gn:feature_class":"P",
    "gn:feature_code":"PPL",
    "gn:name":"Mitope",
    "gn:population":0,
    "gn:timezone":"Africa/Maputo",
    "iso:country":"MZ",
    "wof:name":"Mitope",
    "wof:placetype":"locality"
},
  "geometry": {"coordinates":[40.03889,-11.32722],"type":"Point"}
}