{
  "type": "Feature",
  "properties": {
    "gn:admin1_code":"6.0",
    "gn:asciiname":"Unrate",
    "gn:country_code":"MZ",
    "gn:dem":49,
    "gn:feature_class":"P",
    "gn:feature_code":"PPL",
    "gn:name":"Unrate",
    "gn:population":0,
    "gn:timezone":"Africa/Maputo",
    "iso:country":"MZ",
    "wof:name":"Unrate",
    "wof:placetype":"locality"
},
  "geometry": {"coordinates":[40.56528,-14.9825],"type":"Point"}
}