{
  "type": "Feature",
  "properties": {
    "gn:admin1_code":"9",
    "gn:asciiname":"Mutecua",
    "gn:cc2":"MZ",
    "gn:country_code":"MZ",
    "gn:dem":259,
    "gn:feature_class":"P",
    "gn:feature_code":"PPL",
    "gn:name":"Mutecua",
    "gn:population":0,
    "gn:timezone":"Africa/Maputo",
    "iso:country":"MZ",
    "name:und_x_variant":[
        "Mug\u00eama",
        "Mutecua"
    ],
    "wof:name":"Mutecua",
    "wof:placetype":"locality"
},
  "geometry": {"coordinates":[37.20889,-16.48111],"type":"Point"}
}