{
  "type": "Feature",
  "properties": {
    "gn:admin1_code":"1",
    "gn:asciiname":"Chilangade",
    "gn:country_code":"MZ",
    "gn:dem":555,
    "gn:feature_class":"P",
    "gn:feature_code":"PPL",
    "gn:name":"Chilangade",
    "gn:population":0,
    "gn:timezone":"Africa/Maputo",
    "iso:country":"MZ",
    "wof:name":"Chilangade",
    "wof:placetype":"locality"
},
  "geometry": {"coordinates":[39.89917,-11.7725],"type":"Point"}
}