{
  "type": "Feature",
  "properties": {
    "gn:admin1_code":"2",
    "gn:asciiname":"Chizavane",
    "gn:cc2":"MZ",
    "gn:country_code":"MZ",
    "gn:dem":60,
    "gn:feature_class":"P",
    "gn:feature_code":"PPL",
    "gn:name":"Chizavane",
    "gn:population":0,
    "gn:timezone":"Africa/Maputo",
    "iso:country":"MZ",
    "name:und_x_variant":[
        "Bahane",
        "Chizavane"
    ],
    "wof:name":"Chizavane",
    "wof:placetype":"locality"
},
  "geometry": {"coordinates":[33.995,-24.94806],"type":"Point"}
}