{
  "type": "Feature",
  "properties": {
    "gn:admin1_code":"6",
    "gn:asciiname":"Regulo Mucalava",
    "gn:country_code":"MZ",
    "gn:dem":241,
    "gn:feature_class":"P",
    "gn:feature_code":"PPL",
    "gn:name":"R\u00e9gulo Mucalava",
    "gn:population":0,
    "gn:timezone":"Africa/Maputo",
    "iso:country":"MZ",
    "wof:name":"Regulo Mucalava",
    "wof:placetype":"locality"
},
  "geometry": {"coordinates":[40.05556,-13.57333],"type":"Point"}
}