{
  "type": "Feature",
  "properties": {
    "gn:admin1_code":"3",
    "gn:asciiname":"Meleca",
    "gn:country_code":"MZ",
    "gn:dem":209,
    "gn:feature_class":"P",
    "gn:feature_code":"PPL",
    "gn:name":"Meleca",
    "gn:population":0,
    "gn:timezone":"Africa/Maputo",
    "iso:country":"MZ",
    "wof:name":"Meleca",
    "wof:placetype":"locality"
},
  "geometry": {"coordinates":[34.01111,-21.83278],"type":"Point"}
}