{
  "type": "Feature",
  "properties": {
    "gn:admin1_code":"6",
    "gn:asciiname":"Chefe Munrria",
    "gn:country_code":"MZ",
    "gn:dem":238,
    "gn:feature_class":"P",
    "gn:feature_code":"PPL",
    "gn:name":"Chefe Munrria",
    "gn:population":0,
    "gn:timezone":"Africa/Maputo",
    "iso:country":"MZ",
    "wof:name":"Chefe Munrria",
    "wof:placetype":"locality"
},
  "geometry": {"coordinates":[39.80556,-13.74639],"type":"Point"}
}