{
  "type": "Feature",
  "properties": {
    "gn:admin1_code":"8",
    "gn:asciiname":"Catanguro",
    "gn:country_code":"MZ",
    "gn:dem":84,
    "gn:feature_class":"P",
    "gn:feature_code":"PPL",
    "gn:name":"Catanguro",
    "gn:population":0,
    "gn:timezone":"Africa/Maputo",
    "iso:country":"MZ",
    "wof:name":"Catanguro",
    "wof:placetype":"locality"
},
  "geometry": {"coordinates":[34.83417,-16.89944],"type":"Point"}
}