{
  "type": "Feature",
  "properties": {
    "gn:admin1_code":"3",
    "gn:asciiname":"Foquico",
    "gn:country_code":"MZ",
    "gn:dem":94,
    "gn:feature_class":"P",
    "gn:feature_code":"PPL",
    "gn:name":"Foqui\u00e7o",
    "gn:population":0,
    "gn:timezone":"Africa/Maputo",
    "iso:country":"MZ",
    "wof:name":"Foquico",
    "wof:placetype":"locality"
},
  "geometry": {"coordinates":[35.31472,-23.39972],"type":"Point"}
}