{
  "type": "Feature",
  "properties": {
    "gn:admin1_code":"7",
    "gn:asciiname":"Nanqueja",
    "gn:country_code":"MZ",
    "gn:dem":620,
    "gn:feature_class":"P",
    "gn:feature_code":"PPL",
    "gn:name":"Nanqueja",
    "gn:population":0,
    "gn:timezone":"Africa/Maputo",
    "iso:country":"MZ",
    "wof:name":"Nanqueja",
    "wof:placetype":"locality"
},
  "geometry": {"coordinates":[37.36528,-13.74472],"type":"Point"}
}