{
  "type": "Feature",
  "properties": {
    "gn:admin1_code":"3.0",
    "gn:asciiname":"Nhacoongo",
    "gn:country_code":"MZ",
    "gn:dem":30,
    "gn:feature_class":"P",
    "gn:feature_code":"PPL",
    "gn:name":"Nhacoongo",
    "gn:population":0,
    "gn:timezone":"Africa/Maputo",
    "iso:country":"MZ",
    "wof:name":"Nhacoongo",
    "wof:placetype":"locality"
},
  "geometry": {"coordinates":[35.25083,-24.37528],"type":"Point"}
}