{
  "type": "Feature",
  "properties": {
    "gn:admin1_code":"3",
    "gn:asciiname":"Cumone",
    "gn:country_code":"MZ",
    "gn:dem":180,
    "gn:feature_class":"P",
    "gn:feature_code":"PPL",
    "gn:name":"Cumone",
    "gn:population":0,
    "gn:timezone":"Africa/Maputo",
    "iso:country":"MZ",
    "wof:name":"Cumone",
    "wof:placetype":"locality"
},
  "geometry": {"coordinates":[34.35389,-21.86889],"type":"Point"}
}