{
  "type": "Feature",
  "properties": {
    "gn:admin1_code":"8",
    "gn:asciiname":"Caetano",
    "gn:country_code":"MZ",
    "gn:dem":237,
    "gn:feature_class":"P",
    "gn:feature_code":"PPL",
    "gn:name":"Caetano",
    "gn:population":0,
    "gn:timezone":"Africa/Maputo",
    "iso:country":"MZ",
    "wof:name":"Caetano",
    "wof:placetype":"locality"
},
  "geometry": {"coordinates":[33.08639,-16.67778],"type":"Point"}
}