{
  "type": "Feature",
  "properties": {
    "gn:admin1_code":"1",
    "gn:asciiname":"Domaqui",
    "gn:country_code":"MZ",
    "gn:dem":208,
    "gn:feature_class":"P",
    "gn:feature_code":"PPL",
    "gn:name":"Domaqui",
    "gn:population":0,
    "gn:timezone":"Africa/Maputo",
    "iso:country":"MZ",
    "wof:name":"Domaqui",
    "wof:placetype":"locality"
},
  "geometry": {"coordinates":[39.36778,-12.25028],"type":"Point"}
}