{
  "type": "Feature",
  "properties": {
    "gn:admin1_code":"7",
    "gn:asciiname":"Melina",
    "gn:cc2":"MZ",
    "gn:country_code":"MZ",
    "gn:dem":873,
    "gn:feature_class":"P",
    "gn:feature_code":"PPL",
    "gn:name":"Melina",
    "gn:population":0,
    "gn:timezone":"Africa/Maputo",
    "iso:country":"MZ",
    "name:und_x_variant":[
        "Melima",
        "Melina"
    ],
    "wof:name":"Melina",
    "wof:placetype":"locality"
},
  "geometry": {"coordinates":[35.77722,-13.30333],"type":"Point"}
}