{
  "type": "Feature",
  "properties": {
    "gn:admin1_code":"7",
    "gn:asciiname":"Melina",
    "gn:cc2":"MZ",
    "gn:country_code":"MZ",
    "gn:dem":873,
    "gn:feature_class":"P",
    "gn:feature_code":"PPL",
    "gn:name":"Melina",
    "gn:population":0,
    "gn:timezone":"Africa/Maputo",
    "iso:country":"MZ",
    "name:bos_x_preferred":[
        "Melina"
    ],
    "name:deu_x_preferred":[
        "Melina"
    ],
    "name:ell_x_preferred":[
        "\u039c\u03b5\u03bb\u03af\u03bd\u03b1"
    ],
    "name:fin_x_preferred":[
        "Melina"
    ],
    "name:fra_x_preferred":[
        "Melina"
    ],
    "name:hrv_x_preferred":[
        "Melina"
    ],
    "name:hun_x_preferred":[
        "Melina"
    ],
    "name:ita_x_preferred":[
        "Melina"
    ],
    "name:por_x_preferred":[
        "Melina"
    ],
    "name:rus_x_preferred":[
        "\u041c\u0435\u043b\u0438\u043d\u0430"
    ],
    "name:srp_x_preferred":[
        "\u041c\u0435\u043b\u0438\u043d\u0430"
    ],
    "name:swe_x_preferred":[
        "Melina"
    ],
    "name:und_x_variant":[
        "Melima",
        "Melina"
    ],
    "wof:name":"Melina",
    "wof:placetype":"locality"
},
  "geometry": {"coordinates":[35.77722,-13.30333],"type":"Point"}
}