{
  "type": "Feature",
  "properties": {
    "gn:admin1_code":"0",
    "gn:asciiname":"Nicuma",
    "gn:country_code":"MZ",
    "gn:dem":556,
    "gn:feature_class":"P",
    "gn:feature_code":"PPL",
    "gn:name":"Nicuma",
    "gn:population":0,
    "gn:timezone":"Africa/Maputo",
    "iso:country":"MZ",
    "wof:name":"Nicuma",
    "wof:placetype":"locality"
},
  "geometry": {"coordinates":[37.9275,-15.22917],"type":"Point"}
}