{
  "type": "Feature",
  "properties": {
    "gn:admin1_code":"9",
    "gn:asciiname":"Macurre",
    "gn:country_code":"MZ",
    "gn:dem":220,
    "gn:feature_class":"P",
    "gn:feature_code":"PPL",
    "gn:name":"Macurr\u00e9",
    "gn:population":0,
    "gn:timezone":"Africa/Maputo",
    "iso:country":"MZ",
    "wof:name":"Macurre",
    "wof:placetype":"locality"
},
  "geometry": {"coordinates":[37.1525,-16.60472],"type":"Point"}
}