{
  "type": "Feature",
  "properties": {
    "gn:admin1_code":"6",
    "gn:asciiname":"Miguel",
    "gn:country_code":"MZ",
    "gn:dem":481,
    "gn:feature_class":"P",
    "gn:feature_code":"PPL",
    "gn:name":"Miguel",
    "gn:population":0,
    "gn:timezone":"Africa/Maputo",
    "iso:country":"MZ",
    "name:bre_x_preferred":[
        "Miguel"
    ],
    "name:cat_x_preferred":[
        "Miguel"
    ],
    "name:ceb_x_preferred":[
        "Miguel"
    ],
    "name:deu_x_preferred":[
        "Miguel"
    ],
    "name:fra_x_preferred":[
        "Miguel"
    ],
    "name:heb_x_preferred":[
        "\u05de\u05d9\u05d2\u05dc"
    ],
    "name:hye_x_preferred":[
        "\u0544\u056b\u0563\u0565\u056c"
    ],
    "name:ita_x_preferred":[
        "Miguel"
    ],
    "name:jpn_x_preferred":[
        "\u30df\u30b2\u30eb"
    ],
    "name:nld_x_preferred":[
        "Miguel"
    ],
    "name:por_x_preferred":[
        "Miguel"
    ],
    "name:rus_x_preferred":[
        "\u041c\u0438\u0433\u0435\u043b\u044c"
    ],
    "name:spa_x_preferred":[
        "Miguel"
    ],
    "name:swe_x_preferred":[
        "Miguel"
    ],
    "name:ukr_x_preferred":[
        "\u041c\u0456\u0433\u0435\u043b"
    ],
    "name:vie_x_preferred":[
        "Miguel"
    ],
    "wof:name":"Miguel",
    "wof:placetype":"locality"
},
  "geometry": {"coordinates":[39.05528,-15.01528],"type":"Point"}
}