{
  "type": "Feature",
  "properties": {
    "gn:admin1_code":"6",
    "gn:asciiname":"Miguel",
    "gn:country_code":"MZ",
    "gn:dem":481,
    "gn:feature_class":"P",
    "gn:feature_code":"PPL",
    "gn:name":"Miguel",
    "gn:population":0,
    "gn:timezone":"Africa/Maputo",
    "iso:country":"MZ",
    "wof:name":"Miguel",
    "wof:placetype":"locality"
},
  "geometry": {"coordinates":[39.05528,-15.01528],"type":"Point"}
}