{
  "type": "Feature",
  "properties": {
    "gn:admin1_code":"9",
    "gn:asciiname":"Megarula",
    "gn:country_code":"MZ",
    "gn:dem":489,
    "gn:feature_class":"P",
    "gn:feature_code":"PPL",
    "gn:name":"Megarula",
    "gn:population":0,
    "gn:timezone":"Africa/Maputo",
    "iso:country":"MZ",
    "wof:name":"Megarula",
    "wof:placetype":"locality"
},
  "geometry": {"coordinates":[36.64056,-16.26417],"type":"Point"}
}