{
  "type": "Feature",
  "properties": {
    "gn:admin1_code":"2.0",
    "gn:asciiname":"Barradas",
    "gn:country_code":"MZ",
    "gn:dem":5,
    "gn:feature_class":"P",
    "gn:feature_code":"PPL",
    "gn:name":"Barradas",
    "gn:population":0,
    "gn:timezone":"Africa/Maputo",
    "iso:country":"MZ",
    "wof:name":"Barradas",
    "wof:placetype":"locality"
},
  "geometry": {"coordinates":[33.65528,-24.97944],"type":"Point"}
}