{
  "type": "Feature",
  "properties": {
    "gn:admin1_code":"7",
    "gn:asciiname":"Matimbe",
    "gn:country_code":"MZ",
    "gn:dem":672,
    "gn:feature_class":"P",
    "gn:feature_code":"PPL",
    "gn:name":"Matimbe",
    "gn:population":0,
    "gn:timezone":"Africa/Maputo",
    "iso:country":"MZ",
    "wof:name":"Matimbe",
    "wof:placetype":"locality"
},
  "geometry": {"coordinates":[35.96972,-15.10139],"type":"Point"}
}