{
  "type": "Feature",
  "properties": {
    "gn:admin1_code":"7",
    "gn:asciiname":"Matchedje",
    "gn:country_code":"MZ",
    "gn:dem":602,
    "gn:feature_class":"P",
    "gn:feature_code":"PPL",
    "gn:name":"Matchedje",
    "gn:population":0,
    "gn:timezone":"Africa/Maputo",
    "iso:country":"MZ",
    "wof:name":"Matchedje",
    "wof:placetype":"locality"
},
  "geometry": {"coordinates":[35.43833,-11.59639],"type":"Point"}
}