{
  "type": "Feature",
  "properties": {
    "gn:admin1_code":"8",
    "gn:asciiname":"Montes Sale",
    "gn:country_code":"MZ",
    "gn:dem":1020,
    "gn:feature_class":"P",
    "gn:feature_code":"PPL",
    "gn:name":"Montes Sale",
    "gn:population":0,
    "gn:timezone":"Africa/Maputo",
    "iso:country":"MZ",
    "wof:name":"Montes Sale",
    "wof:placetype":"locality"
},
  "geometry": {"coordinates":[31.32083,-14.9825],"type":"Point"}
}