{
  "type": "Feature",
  "properties": {
    "gn:admin1_code":"3",
    "gn:asciiname":"Chefe Murriane",
    "gn:cc2":"MZ",
    "gn:country_code":"MZ",
    "gn:dem":42,
    "gn:feature_class":"P",
    "gn:feature_code":"PPL",
    "gn:name":"Chefe Murriane",
    "gn:population":0,
    "gn:timezone":"Africa/Maputo",
    "iso:country":"MZ",
    "name:und_x_variant":[
        "Muzimbane",
        "Chefe Murriane"
    ],
    "wof:name":"Chefe Murriane",
    "wof:placetype":"locality"
},
  "geometry": {"coordinates":[35.14167,-22.43667],"type":"Point"}
}