{
  "type": "Feature",
  "properties": {
    "gn:admin1_code":"6.0",
    "gn:asciiname":"Tomola",
    "gn:country_code":"MZ",
    "gn:dem":116,
    "gn:feature_class":"P",
    "gn:feature_code":"PPL",
    "gn:name":"Tomola",
    "gn:population":0,
    "gn:timezone":"Africa/Maputo",
    "iso:country":"MZ",
    "wof:name":"Tomola",
    "wof:placetype":"locality"
},
  "geometry": {"coordinates":[40.37389,-14.94056],"type":"Point"}
}