{
  "type": "Feature",
  "properties": {
    "gn:admin1_code":"1",
    "gn:asciiname":"M'Caveia",
    "gn:country_code":"MZ",
    "gn:dem":444,
    "gn:feature_class":"P",
    "gn:feature_code":"PPL",
    "gn:name":"M\u2019Caveia",
    "gn:population":0,
    "gn:timezone":"Africa/Maputo",
    "iso:country":"MZ",
    "wof:name":"M'Caveia",
    "wof:placetype":"locality"
},
  "geometry": {"coordinates":[38.99306,-12.86194],"type":"Point"}
}