{
  "type": "Feature",
  "properties": {
    "gn:admin1_code":"5",
    "gn:asciiname":"Goonda",
    "gn:cc2":"MZ",
    "gn:country_code":"MZ",
    "gn:dem":39,
    "gn:feature_class":"P",
    "gn:feature_code":"PPL",
    "gn:name":"Goonda",
    "gn:population":0,
    "gn:timezone":"Africa/Maputo",
    "iso:country":"MZ",
    "name:und_x_variant":[
        "Goanda",
        "Goonda"
    ],
    "wof:name":"Goonda",
    "wof:placetype":"locality"
},
  "geometry": {"coordinates":[34.01056,-19.84083],"type":"Point"}
}