{
  "type": "Feature",
  "properties": {
    "gn:admin1_code":"4",
    "gn:asciiname":"S. Vincente de Paulo",
    "gn:country_code":"MZ",
    "gn:dem":39,
    "gn:feature_class":"P",
    "gn:feature_code":"PPL",
    "gn:name":"S. Vincente de Paulo",
    "gn:population":0,
    "gn:timezone":"Africa/Maputo",
    "iso:country":"MZ",
    "wof:name":"S. Vincente de Paulo",
    "wof:placetype":"locality"
},
  "geometry": {"coordinates":[32.47778,-25.87194],"type":"Point"}
}