{
  "type": "Feature",
  "properties": {
    "gn:admin1_code":"8",
    "gn:asciiname":"Cabaira",
    "gn:country_code":"MZ",
    "gn:dem":481,
    "gn:feature_class":"P",
    "gn:feature_code":"PPL",
    "gn:name":"Caba\u00edra",
    "gn:population":0,
    "gn:timezone":"Africa/Maputo",
    "iso:country":"MZ",
    "name:por_x_preferred":[
        "Caba\u00edra"
    ],
    "wof:name":"Cabaira",
    "wof:placetype":"locality"
},
  "geometry": {"coordinates":[31.76035,-16.20746],"type":"Point"}
}