{
  "type": "Feature",
  "properties": {
    "gn:admin1_code":"6",
    "gn:asciiname":"Maeca",
    "gn:country_code":"MZ",
    "gn:dem":17,
    "gn:feature_class":"P",
    "gn:feature_code":"PPL",
    "gn:name":"Maeca",
    "gn:population":0,
    "gn:timezone":"Africa/Maputo",
    "iso:country":"MZ",
    "wof:name":"Maeca",
    "wof:placetype":"locality"
},
  "geometry": {"coordinates":[40.50889,-14.14028],"type":"Point"}
}