{
  "type": "Feature",
  "properties": {
    "gn:admin1_code":"7",
    "gn:asciiname":"Chiloela",
    "gn:country_code":"MZ",
    "gn:dem":597,
    "gn:feature_class":"P",
    "gn:feature_code":"PPL",
    "gn:name":"Chiloela",
    "gn:population":0,
    "gn:timezone":"Africa/Maputo",
    "iso:country":"MZ",
    "wof:name":"Chiloela",
    "wof:placetype":"locality"
},
  "geometry": {"coordinates":[34.80611,-13.1725],"type":"Point"}
}