{
  "type": "Feature",
  "properties": {
    "gn:admin1_code":"3.0",
    "gn:asciiname":"Guilande",
    "gn:country_code":"MZ",
    "gn:dem":88,
    "gn:feature_class":"P",
    "gn:feature_code":"PPL",
    "gn:name":"Guilande",
    "gn:population":0,
    "gn:timezone":"Africa/Maputo",
    "iso:country":"MZ",
    "wof:name":"Guilande",
    "wof:placetype":"locality"
},
  "geometry": {"coordinates":[34.99583,-22.57333],"type":"Point"}
}