{
  "type": "Feature",
  "properties": {
    "gn:admin1_code":"7",
    "gn:asciiname":"Malucula",
    "gn:country_code":"MZ",
    "gn:dem":957,
    "gn:feature_class":"P",
    "gn:feature_code":"PPL",
    "gn:name":"Malucula",
    "gn:population":0,
    "gn:timezone":"Africa/Maputo",
    "iso:country":"MZ",
    "wof:name":"Malucula",
    "wof:placetype":"locality"
},
  "geometry": {"coordinates":[35.48917,-12.93111],"type":"Point"}
}