{
  "type": "Feature",
  "properties": {
    "gn:admin1_code":"0",
    "gn:asciiname":"Cualeupa",
    "gn:country_code":"MZ",
    "gn:dem":235,
    "gn:feature_class":"P",
    "gn:feature_code":"PPL",
    "gn:name":"Cualeupa",
    "gn:population":0,
    "gn:timezone":"Africa/Maputo",
    "iso:country":"MZ",
    "wof:name":"Cualeupa",
    "wof:placetype":"locality"
},
  "geometry": {"coordinates":[39.61667,-12.15],"type":"Point"}
}