{
  "type": "Feature",
  "properties": {
    "gn:admin1_code":"4.0",
    "gn:asciiname":"Aldeia Comunais Chicutso",
    "gn:country_code":"MZ",
    "gn:dem":54,
    "gn:feature_class":"P",
    "gn:feature_code":"PPL",
    "gn:name":"Aldeia Comunais Chicutso",
    "gn:population":0,
    "gn:timezone":"Africa/Maputo",
    "iso:country":"MZ",
    "wof:name":"Aldeia Comunais Chicutso",
    "wof:placetype":"locality"
},
  "geometry": {"coordinates":[32.66472,-24.57083],"type":"Point"}
}