{
  "type": "Feature",
  "properties": {
    "gn:admin1_code":"8",
    "gn:asciiname":"Cansau",
    "gn:country_code":"MZ",
    "gn:dem":502,
    "gn:feature_class":"P",
    "gn:feature_code":"PPL",
    "gn:name":"Cansau",
    "gn:population":0,
    "gn:timezone":"Africa/Maputo",
    "iso:country":"MZ",
    "wof:name":"Cansau",
    "wof:placetype":"locality"
},
  "geometry": {"coordinates":[33.56472,-15.85444],"type":"Point"}
}