{
  "type": "Feature",
  "properties": {
    "gn:admin1_code":"7",
    "gn:asciiname":"Josefa",
    "gn:cc2":"MZ",
    "gn:country_code":"MZ",
    "gn:dem":1232,
    "gn:feature_class":"P",
    "gn:feature_code":"PPL",
    "gn:name":"Josefa",
    "gn:population":0,
    "gn:timezone":"Africa/Maputo",
    "iso:country":"MZ",
    "name:und_x_variant":[
        "Josefo",
        "Josefa"
    ],
    "wof:name":"Josefa",
    "wof:placetype":"locality"
},
  "geometry": {"coordinates":[35.03667,-11.70972],"type":"Point"}
}