{
  "type": "Feature",
  "properties": {
    "gn:admin1_code":"0.0",
    "gn:asciiname":"Vazoacoma",
    "gn:country_code":"MZ",
    "gn:dem":420,
    "gn:feature_class":"P",
    "gn:feature_code":"PPL",
    "gn:name":"Vazoacoma",
    "gn:population":0,
    "gn:timezone":"Africa/Maputo",
    "iso:country":"MZ",
    "wof:name":"Vazoacoma",
    "wof:placetype":"locality"
},
  "geometry": {"coordinates":[33.48333,-15.43333],"type":"Point"}
}