{
  "type": "Feature",
  "properties": {
    "gn:admin1_code":"6.0",
    "gn:asciiname":"Vacara",
    "gn:country_code":"MZ",
    "gn:dem":140,
    "gn:feature_class":"P",
    "gn:feature_code":"PPL",
    "gn:name":"Vacara",
    "gn:population":0,
    "gn:timezone":"Africa/Maputo",
    "iso:country":"MZ",
    "wof:name":"Vacara",
    "wof:placetype":"locality"
},
  "geometry": {"coordinates":[40.15083,-14.96056],"type":"Point"}
}