{
  "type": "Feature",
  "properties": {
    "gn:admin1_code":"10",
    "gn:asciiname":"Alfandega",
    "gn:country_code":"MZ",
    "gn:dem":259,
    "gn:feature_class":"P",
    "gn:feature_code":"PPL",
    "gn:name":"Alfandega",
    "gn:population":0,
    "gn:timezone":"Africa/Maputo",
    "iso:country":"MZ",
    "wof:name":"Alfandega",
    "wof:placetype":"locality"
},
  "geometry": {"coordinates":[34.18417,-17.145],"type":"Point"}
}