{
  "type": "Feature",
  "properties": {
    "gn:admin1_code":"3",
    "gn:asciiname":"Caetano",
    "gn:country_code":"MZ",
    "gn:dem":96,
    "gn:feature_class":"P",
    "gn:feature_code":"PPL",
    "gn:name":"Caetano",
    "gn:population":0,
    "gn:timezone":"Africa/Maputo",
    "iso:country":"MZ",
    "name:deu_x_preferred":[
        "Caetano"
    ],
    "name:fra_x_preferred":[
        "Caetano"
    ],
    "name:nld_x_preferred":[
        "Caetano"
    ],
    "name:por_x_preferred":[
        "Caetano"
    ],
    "name:rus_x_preferred":[
        "\u041a\u0430\u044d\u0442\u0430\u043d\u043e"
    ],
    "wof:name":"Caetano",
    "wof:placetype":"locality"
},
  "geometry": {"coordinates":[34.65,-23.55],"type":"Point"}
}