{
  "type": "Feature",
  "properties": {
    "gn:admin1_code":"8",
    "gn:asciiname":"Belo",
    "gn:country_code":"MZ",
    "gn:dem":324,
    "gn:feature_class":"P",
    "gn:feature_code":"PPL",
    "gn:name":"Belo",
    "gn:population":0,
    "gn:timezone":"Africa/Maputo",
    "iso:country":"MZ",
    "name:deu_x_preferred":[
        "Belo"
    ],
    "name:ita_x_preferred":[
        "Belo"
    ],
    "name:swe_x_preferred":[
        "Belo"
    ],
    "wof:name":"Belo",
    "wof:placetype":"locality"
},
  "geometry": {"coordinates":[33.06417,-15.97528],"type":"Point"}
}