{
  "type": "Feature",
  "properties": {
    "gn:admin1_code":"10",
    "gn:asciiname":"Guebo",
    "gn:country_code":"MZ",
    "gn:dem":251,
    "gn:feature_class":"P",
    "gn:feature_code":"PPL",
    "gn:name":"Guebo",
    "gn:population":0,
    "gn:timezone":"Africa/Maputo",
    "iso:country":"MZ",
    "wof:name":"Guebo",
    "wof:placetype":"locality"
},
  "geometry": {"coordinates":[33.40972,-20.89444],"type":"Point"}
}