{
  "type": "Feature",
  "properties": {
    "gn:admin1_code":"4",
    "gn:asciiname":"Gumbane",
    "gn:cc2":"MZ",
    "gn:country_code":"MZ",
    "gn:dem":19,
    "gn:feature_class":"P",
    "gn:feature_code":"PPL",
    "gn:name":"Gumbane",
    "gn:population":0,
    "gn:timezone":"Africa/Maputo",
    "iso:country":"MZ",
    "name:und_x_variant":[
        "Guane",
        "Gumbane"
    ],
    "wof:name":"Gumbane",
    "wof:placetype":"locality"
},
  "geometry": {"coordinates":[32.65028,-26.37028],"type":"Point"}
}