{
  "type": "Feature",
  "properties": {
    "gn:admin1_code":"7",
    "gn:asciiname":"Contende",
    "gn:country_code":"MZ",
    "gn:dem":535,
    "gn:feature_class":"P",
    "gn:feature_code":"PPL",
    "gn:name":"Contend\u00ea",
    "gn:population":0,
    "gn:timezone":"Africa/Maputo",
    "iso:country":"MZ",
    "wof:name":"Contende",
    "wof:placetype":"locality"
},
  "geometry": {"coordinates":[37.73556,-12.8975],"type":"Point"}
}