{
  "type": "Feature",
  "properties": {
    "gn:admin1_code":"10",
    "gn:asciiname":"Estacatira",
    "gn:country_code":"MZ",
    "gn:dem":594,
    "gn:feature_class":"P",
    "gn:feature_code":"PPL",
    "gn:name":"Estacatira",
    "gn:population":0,
    "gn:timezone":"Africa/Maputo",
    "iso:country":"MZ",
    "wof:name":"Estacatira",
    "wof:placetype":"locality"
},
  "geometry": {"coordinates":[33.54555999999999,-19.18417],"type":"Point"}
}