{
  "type": "Feature",
  "properties": {
    "gn:admin1_code":"5.0",
    "gn:asciiname":"Nazare",
    "gn:country_code":"MZ",
    "gn:dem":24,
    "gn:feature_class":"P",
    "gn:feature_code":"PPL",
    "gn:name":"Nazar\u00e9",
    "gn:population":0,
    "gn:timezone":"Africa/Maputo",
    "iso:country":"MZ",
    "wof:name":"Nazare",
    "wof:placetype":"locality"
},
  "geometry": {"coordinates":[35.46444,-17.94333],"type":"Point"}
}