{
  "type": "Feature",
  "properties": {
    "gn:admin1_code":"9",
    "gn:asciiname":"Aciate",
    "gn:country_code":"MZ",
    "gn:dem":13,
    "gn:feature_class":"P",
    "gn:feature_code":"PPL",
    "gn:name":"Aciate",
    "gn:population":0,
    "gn:timezone":"Africa/Maputo",
    "iso:country":"MZ",
    "wof:name":"Aciate",
    "wof:placetype":"locality"
},
  "geometry": {"coordinates":[36.49278,-17.79917],"type":"Point"}
}