{
  "type": "Feature",
  "properties": {
    "gn:admin1_code":"9",
    "gn:asciiname":"Manlaco",
    "gn:country_code":"MZ",
    "gn:dem":1296,
    "gn:feature_class":"P",
    "gn:feature_code":"PPL",
    "gn:name":"Manlaco",
    "gn:population":0,
    "gn:timezone":"Africa/Maputo",
    "iso:country":"MZ",
    "wof:name":"Manlaco",
    "wof:placetype":"locality"
},
  "geometry": {"coordinates":[37.13222,-15.30083],"type":"Point"}
}