{
  "type": "Feature",
  "properties": {
    "gn:admin1_code":"1",
    "gn:asciiname":"Nancocho",
    "gn:country_code":"MZ",
    "gn:dem":581,
    "gn:feature_class":"P",
    "gn:feature_code":"PPL",
    "gn:name":"Nancocho",
    "gn:population":0,
    "gn:timezone":"Africa/Maputo",
    "iso:country":"MZ",
    "wof:name":"Nancocho",
    "wof:placetype":"locality"
},
  "geometry": {"coordinates":[38.53528,-13.50472],"type":"Point"}
}