{
  "type": "Feature",
  "properties": {
    "gn:admin1_code":"9",
    "gn:asciiname":"Mussaiua",
    "gn:country_code":"MZ",
    "gn:dem":124,
    "gn:feature_class":"P",
    "gn:feature_code":"PPL",
    "gn:name":"Mussaiua",
    "gn:population":0,
    "gn:timezone":"Africa/Maputo",
    "iso:country":"MZ",
    "wof:name":"Mussaiua",
    "wof:placetype":"locality"
},
  "geometry": {"coordinates":[37.87611,-16.81528],"type":"Point"}
}