{
  "type": "Feature",
  "properties": {
    "gn:admin1_code":"10",
    "gn:asciiname":"Mateza",
    "gn:country_code":"MZ",
    "gn:dem":628,
    "gn:feature_class":"P",
    "gn:feature_code":"PPL",
    "gn:name":"Mateza",
    "gn:population":0,
    "gn:timezone":"Africa/Maputo",
    "iso:country":"MZ",
    "name:por_x_preferred":[
        "Mateza"
    ],
    "wof:name":"Mateza",
    "wof:placetype":"locality"
},
  "geometry": {"coordinates":[32.94056,-20.14528],"type":"Point"}
}