{
  "type": "Feature",
  "properties": {
    "gn:admin1_code":"5",
    "gn:asciiname":"Daude",
    "gn:country_code":"MZ",
    "gn:dem":39,
    "gn:feature_class":"P",
    "gn:feature_code":"PPL",
    "gn:name":"Daude",
    "gn:population":0,
    "gn:timezone":"Africa/Maputo",
    "iso:country":"MZ",
    "wof:name":"Daude",
    "wof:placetype":"locality"
},
  "geometry": {"coordinates":[34.25167,-19.26833],"type":"Point"}
}