{
  "type": "Feature",
  "properties": {
    "gn:admin1_code":"6",
    "gn:asciiname":"Nacote",
    "gn:country_code":"MZ",
    "gn:dem":182,
    "gn:feature_class":"P",
    "gn:feature_code":"PPL",
    "gn:name":"Nac\u00f4te",
    "gn:population":0,
    "gn:timezone":"Africa/Maputo",
    "iso:country":"MZ",
    "wof:name":"Nacote",
    "wof:placetype":"locality"
},
  "geometry": {"coordinates":[39.54806,-15.71722],"type":"Point"}
}