{
  "type": "Feature",
  "properties": {
    "gn:admin1_code":"8",
    "gn:asciiname":"Chiropa",
    "gn:country_code":"MZ",
    "gn:dem":700,
    "gn:feature_class":"P",
    "gn:feature_code":"PPL",
    "gn:name":"Chiropa",
    "gn:population":0,
    "gn:timezone":"Africa/Maputo",
    "iso:country":"MZ",
    "wof:name":"Chiropa",
    "wof:placetype":"locality"
},
  "geometry": {"coordinates":[31.61528,-15.3725],"type":"Point"}
}