{
  "type": "Feature",
  "properties": {
    "gn:admin1_code":"6",
    "gn:asciiname":"Naculua",
    "gn:country_code":"MZ",
    "gn:dem":13,
    "gn:feature_class":"P",
    "gn:feature_code":"PPL",
    "gn:name":"Naculua",
    "gn:population":0,
    "gn:timezone":"Africa/Maputo",
    "iso:country":"MZ",
    "wof:name":"Naculua",
    "wof:placetype":"locality"
},
  "geometry": {"coordinates":[40.69222,-14.89639],"type":"Point"}
}