{
  "type": "Feature",
  "properties": {
    "gn:admin1_code":"6",
    "gn:asciiname":"Araujo",
    "gn:country_code":"MZ",
    "gn:dem":588,
    "gn:feature_class":"P",
    "gn:feature_code":"PPL",
    "gn:name":"Ara\u00fajo",
    "gn:population":0,
    "gn:timezone":"Africa/Maputo",
    "iso:country":"MZ",
    "wof:name":"Araujo",
    "wof:placetype":"locality"
},
  "geometry": {"coordinates":[38.23389,-15.23306],"type":"Point"}
}