{
  "type": "Feature",
  "properties": {
    "gn:admin1_code":"6",
    "gn:asciiname":"Omar",
    "gn:country_code":"MZ",
    "gn:dem":31,
    "gn:feature_class":"P",
    "gn:feature_code":"PPL",
    "gn:name":"Omar",
    "gn:population":0,
    "gn:timezone":"Africa/Maputo",
    "iso:country":"MZ",
    "wof:name":"Omar",
    "wof:placetype":"locality"
},
  "geometry": {"coordinates":[39.50444,-16.54722000000001],"type":"Point"}
}