{
  "type": "Feature",
  "properties": {
    "gn:admin1_code":"6",
    "gn:asciiname":"Omar",
    "gn:country_code":"MZ",
    "gn:dem":31,
    "gn:feature_class":"P",
    "gn:feature_code":"PPL",
    "gn:name":"Omar",
    "gn:population":0,
    "gn:timezone":"Africa/Maputo",
    "iso:country":"MZ",
    "name:ara_x_preferred":[
        "\u0639\u0645\u0631"
    ],
    "name:ast_x_preferred":[
        "Omar"
    ],
    "name:ben_x_preferred":[
        "\u0989\u09ae\u09b0"
    ],
    "name:ceb_x_preferred":[
        "Omar"
    ],
    "name:ckb_x_preferred":[
        "\u0639\u0648\u0645\u06d5\u0631"
    ],
    "name:cym_x_preferred":[
        "Omar"
    ],
    "name:deu_x_preferred":[
        "Omar"
    ],
    "name:fas_x_preferred":[
        "\u0639\u0645\u0631"
    ],
    "name:fin_x_preferred":[
        "Omar"
    ],
    "name:fra_x_preferred":[
        "Omar"
    ],
    "name:heb_x_preferred":[
        "\u05e2\u05d5\u05de\u05d0\u05e8"
    ],
    "name:ita_x_preferred":[
        "Omar"
    ],
    "name:jpn_x_preferred":[
        "\u30aa\u30de\u30fc\u30eb"
    ],
    "name:kor_x_preferred":[
        "\uc624\ub9c8\ub974"
    ],
    "name:min_x_preferred":[
        "Umar"
    ],
    "name:nld_x_preferred":[
        "Omar"
    ],
    "name:pol_x_preferred":[
        "Omar"
    ],
    "name:por_x_preferred":[
        "Omar"
    ],
    "name:ron_x_preferred":[
        "Omar"
    ],
    "name:rus_x_preferred":[
        "\u041e\u043c\u0430\u0440"
    ],
    "name:sco_x_preferred":[
        "Omar"
    ],
    "name:swe_x_preferred":[
        "Omar"
    ],
    "name:ukr_x_preferred":[
        "\u041e\u043c\u0430\u0440"
    ],
    "name:urd_x_preferred":[
        "\u0639\u0645\u0631"
    ],
    "wof:name":"Omar",
    "wof:placetype":"locality"
},
  "geometry": {"coordinates":[39.50444,-16.54722000000001],"type":"Point"}
}