{
  "type": "Feature",
  "properties": {
    "gn:admin1_code":"5",
    "gn:asciiname":"Chipende",
    "gn:country_code":"MZ",
    "gn:dem":35,
    "gn:feature_class":"P",
    "gn:feature_code":"PPL",
    "gn:name":"Chipende",
    "gn:population":0,
    "gn:timezone":"Africa/Maputo",
    "iso:country":"MZ",
    "wof:name":"Chipende",
    "wof:placetype":"locality"
},
  "geometry": {"coordinates":[35.21778,-17.78056],"type":"Point"}
}