{
  "type": "Feature",
  "properties": {
    "gn:admin1_code":"0.0",
    "gn:asciiname":"Sopinho",
    "gn:country_code":"MZ",
    "gn:dem":6,
    "gn:feature_class":"P",
    "gn:feature_code":"PPL",
    "gn:name":"Sopinho",
    "gn:population":0,
    "gn:timezone":"Africa/Maputo",
    "iso:country":"MZ",
    "wof:name":"Sopinho",
    "wof:placetype":"locality"
},
  "geometry": {"coordinates":[37.16667,-17.71667],"type":"Point"}
}