{
  "type": "Feature",
  "properties": {
    "gn:admin1_code":"7",
    "gn:asciiname":"Marquepo",
    "gn:country_code":"MZ",
    "gn:dem":600,
    "gn:feature_class":"P",
    "gn:feature_code":"PPL",
    "gn:name":"Marquepo",
    "gn:population":0,
    "gn:timezone":"Africa/Maputo",
    "iso:country":"MZ",
    "wof:name":"Marquepo",
    "wof:placetype":"locality"
},
  "geometry": {"coordinates":[36.37861,-14.79472],"type":"Point"}
}