{
  "type": "Feature",
  "properties": {
    "gn:admin1_code":"2.0",
    "gn:asciiname":"Dingane",
    "gn:country_code":"MZ",
    "gn:dem":60,
    "gn:feature_class":"P",
    "gn:feature_code":"PPL",
    "gn:name":"Dingane",
    "gn:population":0,
    "gn:timezone":"Africa/Maputo",
    "iso:country":"MZ",
    "wof:name":"Dingane",
    "wof:placetype":"locality"
},
  "geometry": {"coordinates":[32.68139,-24.35944],"type":"Point"}
}