{
  "type": "Feature",
  "properties": {
    "gn:admin1_code":"6.0",
    "gn:asciiname":"Roco",
    "gn:country_code":"MZ",
    "gn:dem":60,
    "gn:feature_class":"P",
    "gn:feature_code":"PPL",
    "gn:name":"Roco",
    "gn:population":0,
    "gn:timezone":"Africa/Maputo",
    "iso:country":"MZ",
    "wof:name":"Roco",
    "wof:placetype":"locality"
},
  "geometry": {"coordinates":[40.31083,-15.39556],"type":"Point"}
}