{
  "type": "Feature",
  "properties": {
    "gn:admin1_code":"6.0",
    "gn:asciiname":"Roco",
    "gn:country_code":"MZ",
    "gn:dem":60,
    "gn:feature_class":"P",
    "gn:feature_code":"PPL",
    "gn:name":"Roco",
    "gn:population":0,
    "gn:timezone":"Africa/Maputo",
    "iso:country":"MZ",
    "name:bel_x_preferred":[
        "Roco"
    ],
    "name:deu_x_preferred":[
        "Roco"
    ],
    "name:fin_x_preferred":[
        "Roco"
    ],
    "name:fra_x_preferred":[
        "Roco"
    ],
    "name:isl_x_preferred":[
        "Roco"
    ],
    "name:ita_x_preferred":[
        "Roco"
    ],
    "name:jpn_x_preferred":[
        "Roco"
    ],
    "name:ltz_x_preferred":[
        "Roco"
    ],
    "name:nor_x_preferred":[
        "Roco"
    ],
    "name:pol_x_preferred":[
        "Roco"
    ],
    "name:por_x_preferred":[
        "Roco"
    ],
    "name:rus_x_preferred":[
        "Roco"
    ],
    "name:swe_x_preferred":[
        "Roco"
    ],
    "name:ukr_x_preferred":[
        "Roco"
    ],
    "wof:name":"Roco",
    "wof:placetype":"locality"
},
  "geometry": {"coordinates":[40.31083,-15.39556],"type":"Point"}
}