{
  "type": "Feature",
  "properties": {
    "gn:admin1_code":"2.0",
    "gn:asciiname":"Vulela",
    "gn:country_code":"MZ",
    "gn:dem":177,
    "gn:feature_class":"P",
    "gn:feature_code":"PPL",
    "gn:name":"Vulela",
    "gn:population":0,
    "gn:timezone":"Africa/Maputo",
    "iso:country":"MZ",
    "wof:name":"Vulela",
    "wof:placetype":"locality"
},
  "geometry": {"coordinates":[31.65889,-22.53361],"type":"Point"}
}