{
  "type": "Feature",
  "properties": {
    "gn:admin1_code":"1",
    "gn:asciiname":"Cuiganga",
    "gn:country_code":"MZ",
    "gn:dem":207,
    "gn:feature_class":"P",
    "gn:feature_code":"PPL",
    "gn:name":"Cuiganga",
    "gn:population":0,
    "gn:timezone":"Africa/Maputo",
    "iso:country":"MZ",
    "wof:name":"Cuiganga",
    "wof:placetype":"locality"
},
  "geometry": {"coordinates":[39.47556,-11.10361],"type":"Point"}
}