{
  "type": "Feature",
  "properties": {
    "gn:admin1_code":"8",
    "gn:asciiname":"Chissinde",
    "gn:country_code":"MZ",
    "gn:dem":943,
    "gn:feature_class":"P",
    "gn:feature_code":"PPL",
    "gn:name":"Chissinde",
    "gn:population":0,
    "gn:timezone":"Africa/Maputo",
    "iso:country":"MZ",
    "wof:name":"Chissinde",
    "wof:placetype":"locality"
},
  "geometry": {"coordinates":[32.9725,-14.29722],"type":"Point"}
}