{
  "type": "Feature",
  "properties": {
    "gn:admin1_code":"7",
    "gn:asciiname":"Maringanha",
    "gn:country_code":"MZ",
    "gn:dem":558,
    "gn:feature_class":"P",
    "gn:feature_code":"PPL",
    "gn:name":"Maringanha",
    "gn:population":0,
    "gn:timezone":"Africa/Maputo",
    "iso:country":"MZ",
    "wof:name":"Maringanha",
    "wof:placetype":"locality"
},
  "geometry": {"coordinates":[37.87944,-13.41778],"type":"Point"}
}