{
  "type": "Feature",
  "properties": {
    "gn:admin1_code":"8.0",
    "gn:asciiname":"Tchirembue",
    "gn:country_code":"MZ",
    "gn:dem":216,
    "gn:feature_class":"P",
    "gn:feature_code":"PPL",
    "gn:name":"Tchirembu\u00e9",
    "gn:population":0,
    "gn:timezone":"Africa/Maputo",
    "iso:country":"MZ",
    "wof:name":"Tchirembue",
    "wof:placetype":"locality"
},
  "geometry": {"coordinates":[35.05306,-16.94917],"type":"Point"}
}