{
  "type": "Feature",
  "properties": {
    "gn:admin1_code":"8",
    "gn:asciiname":"Campira",
    "gn:country_code":"MZ",
    "gn:dem":32,
    "gn:feature_class":"P",
    "gn:feature_code":"PPL",
    "gn:name":"Campira",
    "gn:population":0,
    "gn:timezone":"Africa/Maputo",
    "iso:country":"MZ",
    "name:ita_x_preferred":[
        "Samuel Chapanga"
    ],
    "name:pol_x_preferred":[
        "Samuel Chapanga"
    ],
    "name:vie_x_preferred":[
        "Campira"
    ],
    "wof:name":"Campira",
    "wof:placetype":"locality"
},
  "geometry": {"coordinates":[35.2425,-17.23583],"type":"Point"}
}