{
  "type": "Feature",
  "properties": {
    "gn:admin1_code":"7",
    "gn:asciiname":"Metambuzi",
    "gn:country_code":"MZ",
    "gn:dem":586,
    "gn:feature_class":"P",
    "gn:feature_code":"PPL",
    "gn:name":"Metambuzi",
    "gn:population":0,
    "gn:timezone":"Africa/Maputo",
    "iso:country":"MZ",
    "wof:name":"Metambuzi",
    "wof:placetype":"locality"
},
  "geometry": {"coordinates":[35.36889,-11.62444],"type":"Point"}
}