{
  "type": "Feature",
  "properties": {
    "gn:admin1_code":"6.0",
    "gn:asciiname":"Piteria",
    "gn:country_code":"MZ",
    "gn:dem":265,
    "gn:feature_class":"P",
    "gn:feature_code":"PPL",
    "gn:name":"Piteria",
    "gn:population":0,
    "gn:timezone":"Africa/Maputo",
    "iso:country":"MZ",
    "wof:name":"Piteria",
    "wof:placetype":"locality"
},
  "geometry": {"coordinates":[39.65972,-15.13639],"type":"Point"}
}