{
  "type": "Feature",
  "properties": {
    "gn:admin1_code":"7",
    "gn:asciiname":"Maiaca",
    "gn:country_code":"MZ",
    "gn:dem":469,
    "gn:feature_class":"P",
    "gn:feature_code":"PPL",
    "gn:name":"Maiaca",
    "gn:population":0,
    "gn:timezone":"Africa/Maputo",
    "iso:country":"MZ",
    "wof:name":"Maiaca",
    "wof:placetype":"locality"
},
  "geometry": {"coordinates":[37.56361,-14.30917],"type":"Point"}
}