{
  "type": "Feature",
  "properties": {
    "gn:admin1_code":"9.0",
    "gn:asciiname":"Simogo",
    "gn:country_code":"MZ",
    "gn:dem":91,
    "gn:feature_class":"P",
    "gn:feature_code":"PPL",
    "gn:name":"Sim\u00f4go",
    "gn:population":0,
    "gn:timezone":"Africa/Maputo",
    "iso:country":"MZ",
    "name:ind_x_preferred":[
        "Simogo"
    ],
    "name:swe_x_preferred":[
        "Simogo"
    ],
    "wof:name":"Simogo",
    "wof:placetype":"locality"
},
  "geometry": {"coordinates":[36.36778,-17.52889],"type":"Point"}
}