{
  "type": "Feature",
  "properties": {
    "gn:admin1_code":"1",
    "gn:asciiname":"Chefe Maciquine",
    "gn:country_code":"MZ",
    "gn:dem":362,
    "gn:feature_class":"P",
    "gn:feature_code":"PPL",
    "gn:name":"Chefe Maciquine",
    "gn:population":0,
    "gn:timezone":"Africa/Maputo",
    "iso:country":"MZ",
    "wof:name":"Chefe Maciquine",
    "wof:placetype":"locality"
},
  "geometry": {"coordinates":[39.75667,-13.27417],"type":"Point"}
}