{
  "type": "Feature",
  "properties": {
    "gn:admin1_code":"10",
    "gn:asciiname":"Matemere",
    "gn:country_code":"MZ",
    "gn:dem":228,
    "gn:feature_class":"P",
    "gn:feature_code":"PPL",
    "gn:name":"Matemere",
    "gn:population":0,
    "gn:timezone":"Africa/Maputo",
    "iso:country":"MZ",
    "wof:name":"Matemere",
    "wof:placetype":"locality"
},
  "geometry": {"coordinates":[33.20889,-19.97694],"type":"Point"}
}