{
  "type": "Feature",
  "properties": {
    "gn:admin1_code":"1",
    "gn:asciiname":"Muata",
    "gn:country_code":"MZ",
    "gn:dem":186,
    "gn:feature_class":"P",
    "gn:feature_code":"PPL",
    "gn:name":"Muata",
    "gn:population":0,
    "gn:timezone":"Africa/Maputo",
    "iso:country":"MZ",
    "wof:name":"Muata",
    "wof:placetype":"locality"
},
  "geometry": {"coordinates":[40.22028,-13.38972],"type":"Point"}
}