{
  "type": "Feature",
  "properties": {
    "gn:admin1_code":"3",
    "gn:asciiname":"Peca-Peca",
    "gn:country_code":"MZ",
    "gn:dem":190,
    "gn:feature_class":"P",
    "gn:feature_code":"PPL",
    "gn:name":"Pe\u00e7a-Pe\u00e7a",
    "gn:population":0,
    "gn:timezone":"Africa/Maputo",
    "iso:country":"MZ",
    "wof:name":"Peca-Peca",
    "wof:placetype":"locality"
},
  "geometry": {"coordinates":[34.25,-21.92778],"type":"Point"}
}