{
  "type": "Feature",
  "properties": {
    "gn:admin1_code":"2",
    "gn:asciiname":"James",
    "gn:country_code":"MZ",
    "gn:dem":42,
    "gn:feature_class":"P",
    "gn:feature_code":"PPL",
    "gn:name":"James",
    "gn:population":0,
    "gn:timezone":"Africa/Maputo",
    "iso:country":"MZ",
    "name:ara_x_preferred":[
        "\u062c\u064a\u0645\u0633"
    ],
    "name:aze_x_preferred":[
        "Ceyms"
    ],
    "name:ben_x_preferred":[
        "\u099c\u09c7\u09ae\u09b8"
    ],
    "name:bre_x_preferred":[
        "James"
    ],
    "name:bul_x_preferred":[
        "\u0414\u0436\u0435\u0439\u043c\u0441"
    ],
    "name:ceb_x_preferred":[
        "James"
    ],
    "name:ces_x_preferred":[
        "James"
    ],
    "name:deu_x_preferred":[
        "James"
    ],
    "name:fin_x_preferred":[
        "James"
    ],
    "name:fra_x_preferred":[
        "James"
    ],
    "name:heb_x_preferred":[
        "\u05d2'\u05d9\u05d9\u05de\u05e1"
    ],
    "name:hin_x_preferred":[
        "\u091c\u0947\u092e\u094d\u0938"
    ],
    "name:hye_x_preferred":[
        "\u054b\u0565\u0575\u0574\u057d"
    ],
    "name:ind_x_preferred":[
        "James"
    ],
    "name:ita_x_preferred":[
        "James"
    ],
    "name:jpn_x_preferred":[
        "\u30b8\u30a7\u30fc\u30e0\u30ba"
    ],
    "name:kor_x_preferred":[
        "\uc81c\uc784\uc2a4"
    ],
    "name:lav_x_preferred":[
        "D\u017eeimss"
    ],
    "name:nld_x_preferred":[
        "James"
    ],
    "name:nor_x_preferred":[
        "James"
    ],
    "name:pol_x_preferred":[
        "James"
    ],
    "name:rus_x_preferred":[
        "\u0414\u0436\u0435\u0439\u043c\u0441"
    ],
    "name:slv_x_preferred":[
        "James"
    ],
    "name:spa_x_preferred":[
        "James"
    ],
    "name:srp_x_preferred":[
        "\u040f\u0435\u0458\u043c\u0441"
    ],
    "name:swe_x_preferred":[
        "James"
    ],
    "name:tam_x_preferred":[
        "\u0b9c\u0bc7\u0bae\u0bcd\u0bb8\u0bcd"
    ],
    "name:ukr_x_preferred":[
        "\u0414\u0436\u0435\u0439\u043c\u0441"
    ],
    "name:vie_x_preferred":[
        "James"
    ],
    "name:zho_x_preferred":[
        "James"
    ],
    "wof:name":"James",
    "wof:placetype":"locality"
},
  "geometry": {"coordinates":[34.06944,-24.57917],"type":"Point"}
}