{
  "type": "Feature",
  "properties": {
    "gn:admin1_code":"1.0",
    "gn:asciiname":"Ungungo",
    "gn:country_code":"MZ",
    "gn:dem":261,
    "gn:feature_class":"P",
    "gn:feature_code":"PPL",
    "gn:name":"Ungungo",
    "gn:population":0,
    "gn:timezone":"Africa/Maputo",
    "iso:country":"MZ",
    "wof:name":"Ungungo",
    "wof:placetype":"locality"
},
  "geometry": {"coordinates":[38.7975,-11.32167],"type":"Point"}
}