{
  "type": "Feature",
  "properties": {
    "gn:admin1_code":"6",
    "gn:asciiname":"Metali",
    "gn:country_code":"MZ",
    "gn:dem":179,
    "gn:feature_class":"P",
    "gn:feature_code":"PPL",
    "gn:name":"Metali",
    "gn:population":0,
    "gn:timezone":"Africa/Maputo",
    "iso:country":"MZ",
    "wof:name":"Metali",
    "wof:placetype":"locality"
},
  "geometry": {"coordinates":[40.20639,-14.05167],"type":"Point"}
}