{
  "type": "Feature",
  "properties": {
    "gn:admin1_code":"1.0",
    "gn:asciiname":"Ulua",
    "gn:country_code":"MZ",
    "gn:dem":463,
    "gn:feature_class":"P",
    "gn:feature_code":"PPL",
    "gn:name":"Ulua",
    "gn:population":0,
    "gn:timezone":"Africa/Maputo",
    "iso:country":"MZ",
    "name:pol_x_preferred":[
        "Ulua"
    ],
    "wof:name":"Ulua",
    "wof:placetype":"locality"
},
  "geometry": {"coordinates":[38.72694,-13.01667],"type":"Point"}
}