{
  "type": "Feature",
  "properties": {
    "gn:admin1_code":"6",
    "gn:asciiname":"Cabo Jose",
    "gn:cc2":"MZ",
    "gn:country_code":"MZ",
    "gn:dem":307,
    "gn:feature_class":"P",
    "gn:feature_code":"PPL",
    "gn:name":"Cabo Jos\u00e9",
    "gn:population":0,
    "gn:timezone":"Africa/Maputo",
    "iso:country":"MZ",
    "name:und_x_variant":[
        "Jos\u00e9",
        "Cabo Jos\u00e9"
    ],
    "wof:name":"Cabo Jose",
    "wof:placetype":"locality"
},
  "geometry": {"coordinates":[40.20222,-13.98222],"type":"Point"}
}