{
  "type": "Feature",
  "properties": {
    "gn:admin1_code":"6",
    "gn:asciiname":"Leuria",
    "gn:country_code":"MZ",
    "gn:dem":172,
    "gn:feature_class":"P",
    "gn:feature_code":"PPL",
    "gn:name":"Leuria",
    "gn:population":0,
    "gn:timezone":"Africa/Maputo",
    "iso:country":"MZ",
    "wof:name":"Leuria",
    "wof:placetype":"locality"
},
  "geometry": {"coordinates":[39.95,-15.1175],"type":"Point"}
}