{
  "type": "Feature",
  "properties": {
    "gn:admin1_code":"5",
    "gn:asciiname":"Gulamopinso",
    "gn:country_code":"MZ",
    "gn:dem":22,
    "gn:feature_class":"P",
    "gn:feature_code":"PPL",
    "gn:name":"Gulamopinso",
    "gn:population":0,
    "gn:timezone":"Africa/Maputo",
    "iso:country":"MZ",
    "wof:name":"Gulamopinso",
    "wof:placetype":"locality"
},
  "geometry": {"coordinates":[34.43667,-19.15361],"type":"Point"}
}