{
  "type": "Feature",
  "properties": {
    "gn:admin1_code":"6",
    "gn:asciiname":"Matarij",
    "gn:country_code":"MZ",
    "gn:dem":576,
    "gn:feature_class":"P",
    "gn:feature_code":"PPL",
    "gn:name":"Matarij",
    "gn:population":0,
    "gn:timezone":"Africa/Maputo",
    "iso:country":"MZ",
    "wof:name":"Matarij",
    "wof:placetype":"locality"
},
  "geometry": {"coordinates":[38.13889,-14.93583],"type":"Point"}
}