{
  "type": "Feature",
  "properties": {
    "gn:admin1_code":"7",
    "gn:asciiname":"Aldeia Micuinha",
    "gn:country_code":"MZ",
    "gn:dem":701,
    "gn:feature_class":"P",
    "gn:feature_code":"PPL",
    "gn:name":"Aldeia Micuinha",
    "gn:population":0,
    "gn:timezone":"Africa/Maputo",
    "iso:country":"MZ",
    "wof:name":"Aldeia Micuinha",
    "wof:placetype":"locality"
},
  "geometry": {"coordinates":[36.20472,-13.06417],"type":"Point"}
}