{
  "type": "Feature",
  "properties": {
    "gn:admin1_code":"1.0",
    "gn:asciiname":"Sauali",
    "gn:country_code":"MZ",
    "gn:dem":104,
    "gn:feature_class":"P",
    "gn:feature_code":"PPL",
    "gn:name":"Sauali",
    "gn:population":0,
    "gn:timezone":"Africa/Maputo",
    "iso:country":"MZ",
    "wof:name":"Sauali",
    "wof:placetype":"locality"
},
  "geometry": {"coordinates":[40.32333,-12.41722],"type":"Point"}
}