{
  "type": "Feature",
  "properties": {
    "gn:admin1_code":"7",
    "gn:asciiname":"Muitica",
    "gn:country_code":"MZ",
    "gn:dem":554,
    "gn:feature_class":"P",
    "gn:feature_code":"PPL",
    "gn:name":"Mu\u00edtica",
    "gn:population":0,
    "gn:timezone":"Africa/Maputo",
    "iso:country":"MZ",
    "wof:name":"Muitica",
    "wof:placetype":"locality"
},
  "geometry": {"coordinates":[36.48194,-13.28639],"type":"Point"}
}