{
  "type": "Feature",
  "properties": {
    "gn:admin1_code":"6",
    "gn:asciiname":"Napai",
    "gn:country_code":"MZ",
    "gn:dem":334,
    "gn:feature_class":"P",
    "gn:feature_code":"PPL",
    "gn:name":"Napai",
    "gn:population":0,
    "gn:timezone":"Africa/Maputo",
    "iso:country":"MZ",
    "wof:name":"Napai",
    "wof:placetype":"locality"
},
  "geometry": {"coordinates":[38.70278,-14.19139],"type":"Point"}
}