{
  "type": "Feature",
  "properties": {
    "gn:admin1_code":"3.0",
    "gn:asciiname":"Regedor Zavala",
    "gn:cc2":"MZ",
    "gn:country_code":"MZ",
    "gn:dem":59,
    "gn:feature_class":"P",
    "gn:feature_code":"PPL",
    "gn:name":"Regedor Zavala",
    "gn:population":0,
    "gn:timezone":"Africa/Maputo",
    "iso:country":"MZ",
    "name:und_x_variant":[
        "Zavala",
        "Regedor Zavala"
    ],
    "wof:name":"Regedor Zavala",
    "wof:placetype":"locality"
},
  "geometry": {"coordinates":[34.66861,-24.68278],"type":"Point"}
}