{
  "type": "Feature",
  "properties": {
    "gn:admin1_code":"7",
    "gn:asciiname":"Evace",
    "gn:country_code":"MZ",
    "gn:dem":675,
    "gn:feature_class":"P",
    "gn:feature_code":"PPL",
    "gn:name":"Evace",
    "gn:population":0,
    "gn:timezone":"Africa/Maputo",
    "iso:country":"MZ",
    "wof:name":"Evace",
    "wof:placetype":"locality"
},
  "geometry": {"coordinates":[34.83917,-12.23417],"type":"Point"}
}