{
  "type": "Feature",
  "properties": {
    "gn:admin1_code":"10",
    "gn:asciiname":"Maluzana",
    "gn:country_code":"MZ",
    "gn:dem":212,
    "gn:feature_class":"P",
    "gn:feature_code":"PPL",
    "gn:name":"Maluzana",
    "gn:population":0,
    "gn:timezone":"Africa/Maputo",
    "iso:country":"MZ",
    "wof:name":"Maluzana",
    "wof:placetype":"locality"
},
  "geometry": {"coordinates":[33.52083,-20.89667],"type":"Point"}
}