{
  "type": "Feature",
  "properties": {
    "gn:admin1_code":"9",
    "gn:asciiname":"Chefe Malalo",
    "gn:country_code":"MZ",
    "gn:dem":542,
    "gn:feature_class":"P",
    "gn:feature_code":"PPL",
    "gn:name":"Chefe Malalo",
    "gn:population":0,
    "gn:timezone":"Africa/Maputo",
    "iso:country":"MZ",
    "wof:name":"Chefe Malalo",
    "wof:placetype":"locality"
},
  "geometry": {"coordinates":[36.87472,-15.73278],"type":"Point"}
}