{
  "type": "Feature",
  "properties": {
    "gn:admin1_code":"3.0",
    "gn:asciiname":"Mecano Meque",
    "gn:country_code":"MZ",
    "gn:dem":44,
    "gn:feature_class":"P",
    "gn:feature_code":"PPL",
    "gn:name":"Mecano Meque",
    "gn:population":0,
    "gn:timezone":"Africa/Maputo",
    "iso:country":"MZ",
    "wof:name":"Mecano Meque",
    "wof:placetype":"locality"
},
  "geometry": {"coordinates":[34.74389,-24.57417],"type":"Point"}
}