{
  "type": "Feature",
  "properties": {
    "gn:admin1_code":"1",
    "gn:asciiname":"Panjely",
    "gn:country_code":"MZ",
    "gn:dem":249,
    "gn:feature_class":"P",
    "gn:feature_code":"PPL",
    "gn:name":"Panjely",
    "gn:population":0,
    "gn:timezone":"Africa/Maputo",
    "iso:country":"MZ",
    "wof:name":"Panjely",
    "wof:placetype":"locality"
},
  "geometry": {"coordinates":[39.93222,-11.47306],"type":"Point"}
}