{
  "type": "Feature",
  "properties": {
    "gn:admin1_code":"3.0",
    "gn:asciiname":"Cabo Vavati",
    "gn:country_code":"MZ",
    "gn:dem":203,
    "gn:feature_class":"P",
    "gn:feature_code":"PPL",
    "gn:name":"Cabo Vav\u00e1ti",
    "gn:population":0,
    "gn:timezone":"Africa/Maputo",
    "iso:country":"MZ",
    "wof:name":"Cabo Vavati",
    "wof:placetype":"locality"
},
  "geometry": {"coordinates":[35.04056,-23.77139],"type":"Point"}
}