{
  "type": "Feature",
  "properties": {
    "gn:admin1_code":"3",
    "gn:asciiname":"Macoche",
    "gn:country_code":"MZ",
    "gn:dem":172,
    "gn:feature_class":"P",
    "gn:feature_code":"PPL",
    "gn:name":"Macoche",
    "gn:population":0,
    "gn:timezone":"Africa/Maputo",
    "iso:country":"MZ",
    "wof:name":"Macoche",
    "wof:placetype":"locality"
},
  "geometry": {"coordinates":[34.29806,-21.57083],"type":"Point"}
}