{
  "type": "Feature",
  "properties": {
    "gn:admin1_code":"6",
    "gn:asciiname":"Moevela",
    "gn:country_code":"MZ",
    "gn:dem":745,
    "gn:feature_class":"P",
    "gn:feature_code":"PPL",
    "gn:name":"Moevela",
    "gn:population":0,
    "gn:timezone":"Africa/Maputo",
    "iso:country":"MZ",
    "wof:name":"Moevela",
    "wof:placetype":"locality"
},
  "geometry": {"coordinates":[37.98583,-14.95833],"type":"Point"}
}