{
  "type": "Feature",
  "properties": {
    "gn:admin1_code":"8.0",
    "gn:asciiname":"Zambue",
    "gn:country_code":"MZ",
    "gn:dem":914,
    "gn:feature_class":"P",
    "gn:feature_code":"PPL",
    "gn:name":"Zambue",
    "gn:population":0,
    "gn:timezone":"Africa/Maputo",
    "iso:country":"MZ",
    "wof:name":"Zambue",
    "wof:placetype":"locality"
},
  "geometry": {"coordinates":[30.80472,-15.11556],"type":"Point"}
}