{
  "type": "Feature",
  "properties": {
    "gn:admin1_code":"1",
    "gn:asciiname":"Liautua",
    "gn:country_code":"MZ",
    "gn:dem":573,
    "gn:feature_class":"P",
    "gn:feature_code":"PPL",
    "gn:name":"Liautua",
    "gn:population":0,
    "gn:timezone":"Africa/Maputo",
    "iso:country":"MZ",
    "wof:name":"Liautua",
    "wof:placetype":"locality"
},
  "geometry": {"coordinates":[39.79028,-11.71611],"type":"Point"}
}