{
  "type": "Feature",
  "properties": {
    "gn:admin1_code":"6",
    "gn:asciiname":"Muhia",
    "gn:country_code":"MZ",
    "gn:dem":358,
    "gn:feature_class":"P",
    "gn:feature_code":"PPL",
    "gn:name":"Muhia",
    "gn:population":0,
    "gn:timezone":"Africa/Maputo",
    "iso:country":"MZ",
    "wof:name":"Muhia",
    "wof:placetype":"locality"
},
  "geometry": {"coordinates":[38.725,-15.60056],"type":"Point"}
}