{
  "type": "Feature",
  "properties": {
    "gn:admin1_code":"10",
    "gn:asciiname":"Mucanene",
    "gn:country_code":"MZ",
    "gn:dem":412,
    "gn:feature_class":"P",
    "gn:feature_code":"PPL",
    "gn:name":"Mucanene",
    "gn:population":0,
    "gn:timezone":"Africa/Maputo",
    "iso:country":"MZ",
    "wof:name":"Mucanene",
    "wof:placetype":"locality"
},
  "geometry": {"coordinates":[33.1425,-20.885],"type":"Point"}
}