{
  "type": "Feature",
  "properties": {
    "gn:admin1_code":"2.0",
    "gn:asciiname":"Uachi Nhaluongue",
    "gn:country_code":"MZ",
    "gn:dem":28,
    "gn:feature_class":"P",
    "gn:feature_code":"PPL",
    "gn:name":"Uachi Nhaluongue",
    "gn:population":0,
    "gn:timezone":"Africa/Maputo",
    "iso:country":"MZ",
    "wof:name":"Uachi Nhaluongue",
    "wof:placetype":"locality"
},
  "geometry": {"coordinates":[34.06111,-24.46333],"type":"Point"}
}