{
  "type": "Feature",
  "properties": {
    "gn:admin1_code":"7",
    "gn:asciiname":"Gombe",
    "gn:country_code":"MZ",
    "gn:dem":742,
    "gn:feature_class":"P",
    "gn:feature_code":"PPL",
    "gn:name":"Gombe",
    "gn:population":0,
    "gn:timezone":"Africa/Maputo",
    "iso:country":"MZ",
    "wof:name":"Gombe",
    "wof:placetype":"locality"
},
  "geometry": {"coordinates":[35.1225,-12.40667],"type":"Point"}
}