{
  "type": "Feature",
  "properties": {
    "gn:admin1_code":"10",
    "gn:asciiname":"Chiboma",
    "gn:cc2":"MZ",
    "gn:country_code":"MZ",
    "gn:dem":54,
    "gn:feature_class":"P",
    "gn:feature_code":"PPL",
    "gn:name":"Chiboma",
    "gn:population":0,
    "gn:timezone":"Africa/Maputo",
    "iso:country":"MZ",
    "name:und_x_variant":[
        "Chibamo",
        "Chiboma"
    ],
    "wof:name":"Chiboma",
    "wof:placetype":"locality"
},
  "geometry": {"coordinates":[33.82306,-19.92389],"type":"Point"}
}