{
  "type": "Feature",
  "properties": {
    "gn:admin1_code":"6",
    "gn:asciiname":"Nacua",
    "gn:country_code":"MZ",
    "gn:dem":475,
    "gn:feature_class":"P",
    "gn:feature_code":"PPL",
    "gn:name":"Nacua",
    "gn:population":0,
    "gn:timezone":"Africa/Maputo",
    "iso:country":"MZ",
    "wof:name":"Nacua",
    "wof:placetype":"locality"
},
  "geometry": {"coordinates":[38.37111,-14.82333],"type":"Point"}
}