{
  "type": "Feature",
  "properties": {
    "gn:admin1_code":"7",
    "gn:asciiname":"Aldeia Chiuindi",
    "gn:country_code":"MZ",
    "gn:dem":709,
    "gn:feature_class":"P",
    "gn:feature_code":"PPL",
    "gn:name":"Aldeia Chiuindi",
    "gn:population":0,
    "gn:timezone":"Africa/Maputo",
    "iso:country":"MZ",
    "wof:name":"Aldeia Chiuindi",
    "wof:placetype":"locality"
},
  "geometry": {"coordinates":[34.97167,-11.57889],"type":"Point"}
}