{
  "type": "Feature",
  "properties": {
    "gn:admin1_code":"6",
    "gn:asciiname":"Nanlepa",
    "gn:country_code":"MZ",
    "gn:dem":559,
    "gn:feature_class":"P",
    "gn:feature_code":"PPL",
    "gn:name":"Nanl\u00eapa",
    "gn:population":0,
    "gn:timezone":"Africa/Maputo",
    "iso:country":"MZ",
    "wof:name":"Nanlepa",
    "wof:placetype":"locality"
},
  "geometry": {"coordinates":[38.02556,-14.84972],"type":"Point"}
}