{
  "type": "Feature",
  "properties": {
    "gn:admin1_code":"10",
    "gn:asciiname":"Chagaca",
    "gn:country_code":"MZ",
    "gn:dem":108,
    "gn:feature_class":"P",
    "gn:feature_code":"PPL",
    "gn:name":"Chagaca",
    "gn:population":0,
    "gn:timezone":"Africa/Maputo",
    "iso:country":"MZ",
    "wof:name":"Chagaca",
    "wof:placetype":"locality"
},
  "geometry": {"coordinates":[33.92861,-16.57028],"type":"Point"}
}