{
  "type": "Feature",
  "properties": {
    "gn:admin1_code":"9",
    "gn:asciiname":"Namacaua",
    "gn:country_code":"MZ",
    "gn:dem":743,
    "gn:feature_class":"P",
    "gn:feature_code":"PPL",
    "gn:name":"Namacaua",
    "gn:population":0,
    "gn:timezone":"Africa/Maputo",
    "iso:country":"MZ",
    "wof:name":"Namacaua",
    "wof:placetype":"locality"
},
  "geometry": {"coordinates":[37.48361,-15.18944],"type":"Point"}
}