{
  "type": "Feature",
  "properties": {
    "gn:admin1_code":"4",
    "gn:asciiname":"Augusto Sa",
    "gn:country_code":"MZ",
    "gn:dem":0,
    "gn:feature_class":"P",
    "gn:feature_code":"PPL",
    "gn:name":"Augusto Sa",
    "gn:population":0,
    "gn:timezone":"Africa/Maputo",
    "iso:country":"MZ",
    "wof:name":"Augusto Sa",
    "wof:placetype":"locality"
},
  "geometry": {"coordinates":[32.69,-25.73056],"type":"Point"}
}