{
  "type": "Feature",
  "properties": {
    "gn:admin1_code":"1",
    "gn:asciiname":"Assane",
    "gn:country_code":"MZ",
    "gn:dem":302,
    "gn:feature_class":"P",
    "gn:feature_code":"PPL",
    "gn:name":"Assane",
    "gn:population":0,
    "gn:timezone":"Africa/Maputo",
    "iso:country":"MZ",
    "name:fra_x_preferred":[
        "Assane"
    ],
    "wof:name":"Assane",
    "wof:placetype":"locality"
},
  "geometry": {"coordinates":[40.00389000000001,-12.87389],"type":"Point"}
}