{
  "type": "Feature",
  "properties": {
    "gn:admin1_code":"10",
    "gn:asciiname":"Gobane",
    "gn:country_code":"MZ",
    "gn:dem":395,
    "gn:feature_class":"P",
    "gn:feature_code":"PPL",
    "gn:name":"Gobane",
    "gn:population":0,
    "gn:timezone":"Africa/Maputo",
    "iso:country":"MZ",
    "wof:name":"Gobane",
    "wof:placetype":"locality"
},
  "geometry": {"coordinates":[34.07667,-17.40306],"type":"Point"}
}