{
  "type": "Feature",
  "properties": {
    "gn:admin1_code":"10",
    "gn:asciiname":"Gimo",
    "gn:country_code":"MZ",
    "gn:dem":224,
    "gn:feature_class":"P",
    "gn:feature_code":"PPL",
    "gn:name":"Gimo",
    "gn:population":0,
    "gn:timezone":"Africa/Maputo",
    "iso:country":"MZ",
    "name:ita_x_preferred":[
        "Gimo"
    ],
    "wof:name":"Gimo",
    "wof:placetype":"locality"
},
  "geometry": {"coordinates":[34.00972,-16.90028],"type":"Point"}
}