{
  "type": "Feature",
  "properties": {
    "gn:admin1_code":"3.0",
    "gn:asciiname":"Zefanias Noa",
    "gn:cc2":"MZ",
    "gn:country_code":"MZ",
    "gn:dem":93,
    "gn:feature_class":"P",
    "gn:feature_code":"PPL",
    "gn:name":"Zefanias Noa",
    "gn:population":0,
    "gn:timezone":"Africa/Maputo",
    "iso:country":"MZ",
    "name:und_x_variant":[
        "Cabo",
        "Zefanias Noa"
    ],
    "wof:name":"Zefanias Noa",
    "wof:placetype":"locality"
},
  "geometry": {"coordinates":[35.22611,-24.22944],"type":"Point"}
}