{
  "type": "Feature",
  "properties": {
    "gn:admin1_code":"6",
    "gn:asciiname":"Metita",
    "gn:country_code":"MZ",
    "gn:dem":137,
    "gn:feature_class":"P",
    "gn:feature_code":"PPL",
    "gn:name":"Metita",
    "gn:population":0,
    "gn:timezone":"Africa/Maputo",
    "iso:country":"MZ",
    "wof:name":"Metita",
    "wof:placetype":"locality"
},
  "geometry": {"coordinates":[39.44417,-15.86722],"type":"Point"}
}