{
  "type": "Feature",
  "properties": {
    "gn:admin1_code":"8",
    "gn:asciiname":"Lungue",
    "gn:country_code":"MZ",
    "gn:dem":373,
    "gn:feature_class":"P",
    "gn:feature_code":"PPL",
    "gn:name":"Lungue",
    "gn:population":0,
    "gn:timezone":"Africa/Maputo",
    "iso:country":"MZ",
    "wof:name":"Lungue",
    "wof:placetype":"locality"
},
  "geometry": {"coordinates":[30.23917,-15.08694],"type":"Point"}
}