{
  "type": "Feature",
  "properties": {
    "gn:admin1_code":"9",
    "gn:asciiname":"Nacaje",
    "gn:country_code":"MZ",
    "gn:dem":316,
    "gn:feature_class":"P",
    "gn:feature_code":"PPL",
    "gn:name":"Nacaje",
    "gn:population":0,
    "gn:timezone":"Africa/Maputo",
    "iso:country":"MZ",
    "wof:name":"Nacaje",
    "wof:placetype":"locality"
},
  "geometry": {"coordinates":[37.37278,-16.34832999999999],"type":"Point"}
}