{
  "type": "Feature",
  "properties": {
    "gn:admin1_code":"9",
    "gn:asciiname":"Oliua",
    "gn:country_code":"MZ",
    "gn:dem":706,
    "gn:feature_class":"P",
    "gn:feature_code":"PPL",
    "gn:name":"Oliua",
    "gn:population":0,
    "gn:timezone":"Africa/Maputo",
    "iso:country":"MZ",
    "wof:name":"Oliua",
    "wof:placetype":"locality"
},
  "geometry": {"coordinates":[37.21306,-15.04722],"type":"Point"}
}