{
  "type": "Feature",
  "properties": {
    "gn:admin1_code":"2",
    "gn:asciiname":"Mussengane",
    "gn:country_code":"MZ",
    "gn:dem":70,
    "gn:feature_class":"P",
    "gn:feature_code":"PPL",
    "gn:name":"Mussengane",
    "gn:population":0,
    "gn:timezone":"Africa/Maputo",
    "iso:country":"MZ",
    "wof:name":"Mussengane",
    "wof:placetype":"locality"
},
  "geometry": {"coordinates":[33.81972,-24.63944],"type":"Point"}
}