{
  "type": "Feature",
  "properties": {
    "gn:admin1_code":"1",
    "gn:asciiname":"Nicuimirero",
    "gn:country_code":"MZ",
    "gn:dem":157,
    "gn:feature_class":"P",
    "gn:feature_code":"PPL",
    "gn:name":"Nicuimirero",
    "gn:population":0,
    "gn:timezone":"Africa/Maputo",
    "iso:country":"MZ",
    "wof:name":"Nicuimirero",
    "wof:placetype":"locality"
},
  "geometry": {"coordinates":[40.13417000000001,-11.62861],"type":"Point"}
}