{
  "type": "Feature",
  "properties": {
    "gn:admin1_code":"2.0",
    "gn:asciiname":"Armazens",
    "gn:country_code":"MZ",
    "gn:dem":23,
    "gn:feature_class":"P",
    "gn:feature_code":"PPL",
    "gn:name":"Armaz\u00e9ns",
    "gn:population":0,
    "gn:timezone":"Africa/Maputo",
    "iso:country":"MZ",
    "wof:name":"Armazens",
    "wof:placetype":"locality"
},
  "geometry": {"coordinates":[33.07583,-24.72667],"type":"Point"}
}