{
  "type": "Feature",
  "properties": {
    "gn:admin1_code":"9",
    "gn:asciiname":"Guerrissa",
    "gn:cc2":"MZ",
    "gn:country_code":"MZ",
    "gn:dem":235,
    "gn:feature_class":"P",
    "gn:feature_code":"PPL",
    "gn:name":"Guerrissa",
    "gn:population":0,
    "gn:timezone":"Africa/Maputo",
    "iso:country":"MZ",
    "name:und_x_variant":[
        "Guari\u00e7a",
        "Guerissa",
        "Guerrissa"
    ],
    "wof:name":"Guerrissa",
    "wof:placetype":"locality"
},
  "geometry": {"coordinates":[35.95778,-17.31889],"type":"Point"}
}