{
  "type": "Feature",
  "properties": {
    "gn:admin1_code":"3.0",
    "gn:asciiname":"Matzemane",
    "gn:country_code":"MZ",
    "gn:dem":96,
    "gn:feature_class":"P",
    "gn:feature_code":"PPL",
    "gn:name":"Matzemane",
    "gn:population":0,
    "gn:timezone":"Africa/Maputo",
    "iso:country":"MZ",
    "wof:name":"Matzemane",
    "wof:placetype":"locality"
},
  "geometry": {"coordinates":[33.41861,-22.63944],"type":"Point"}
}