{
  "type": "Feature",
  "properties": {
    "gn:admin1_code":"6",
    "gn:asciiname":"Namago",
    "gn:country_code":"MZ",
    "gn:dem":213,
    "gn:feature_class":"P",
    "gn:feature_code":"PPL",
    "gn:name":"Namago",
    "gn:population":0,
    "gn:timezone":"Africa/Maputo",
    "iso:country":"MZ",
    "wof:name":"Namago",
    "wof:placetype":"locality"
},
  "geometry": {"coordinates":[39.99694,-14.30917],"type":"Point"}
}