{
  "type": "Feature",
  "properties": {
    "gn:admin1_code":"3.0",
    "gn:asciiname":"Choalane",
    "gn:country_code":"MZ",
    "gn:dem":159,
    "gn:feature_class":"P",
    "gn:feature_code":"PPL",
    "gn:name":"Choalane",
    "gn:population":0,
    "gn:timezone":"Africa/Maputo",
    "iso:country":"MZ",
    "wof:name":"Choalane",
    "wof:placetype":"locality"
},
  "geometry": {"coordinates":[34.39889,-22.51556],"type":"Point"}
}