{
  "type": "Feature",
  "properties": {
    "gn:admin1_code":"8.0",
    "gn:asciiname":"Vinho",
    "gn:country_code":"MZ",
    "gn:dem":390,
    "gn:feature_class":"P",
    "gn:feature_code":"PPL",
    "gn:name":"Vinho",
    "gn:population":0,
    "gn:timezone":"Africa/Maputo",
    "iso:country":"MZ",
    "wof:name":"Vinho",
    "wof:placetype":"locality"
},
  "geometry": {"coordinates":[32.0025,-15.56222],"type":"Point"}
}