{
  "type": "Feature",
  "properties": {
    "gn:admin1_code":"0",
    "gn:asciiname":"Chefe Nampepa",
    "gn:cc2":"MZ",
    "gn:country_code":"MZ",
    "gn:dem":489,
    "gn:feature_class":"P",
    "gn:feature_code":"PPL",
    "gn:name":"Chefe Nampepa",
    "gn:population":0,
    "gn:timezone":"Africa/Maputo",
    "iso:country":"MZ",
    "name:und_x_variant":[
        "Nampepa",
        "Chefe Nampepa"
    ],
    "wof:name":"Chefe Nampepa",
    "wof:placetype":"locality"
},
  "geometry": {"coordinates":[38.97889,-13.53778],"type":"Point"}
}