{
  "type": "Feature",
  "properties": {
    "gn:admin1_code":"9",
    "gn:asciiname":"Chefe Boror",
    "gn:country_code":"MZ",
    "gn:dem":483,
    "gn:feature_class":"P",
    "gn:feature_code":"PPL",
    "gn:name":"Chefe Boror",
    "gn:population":0,
    "gn:timezone":"Africa/Maputo",
    "iso:country":"MZ",
    "wof:name":"Chefe Boror",
    "wof:placetype":"locality"
},
  "geometry": {"coordinates":[35.95806,-15.99028],"type":"Point"}
}