{
  "type": "Feature",
  "properties": {
    "gn:admin1_code":"6",
    "gn:asciiname":"Nachele",
    "gn:country_code":"MZ",
    "gn:dem":346,
    "gn:feature_class":"P",
    "gn:feature_code":"PPL",
    "gn:name":"Nachele",
    "gn:population":0,
    "gn:timezone":"Africa/Maputo",
    "iso:country":"MZ",
    "wof:name":"Nachele",
    "wof:placetype":"locality"
},
  "geometry": {"coordinates":[39.74861,-13.99194],"type":"Point"}
}