{
  "type": "Feature",
  "properties": {
    "gn:admin1_code":"6",
    "gn:asciiname":"Murula",
    "gn:country_code":"MZ",
    "gn:dem":672,
    "gn:feature_class":"P",
    "gn:feature_code":"PPL",
    "gn:name":"Murula",
    "gn:population":0,
    "gn:timezone":"Africa/Maputo",
    "iso:country":"MZ",
    "wof:name":"Murula",
    "wof:placetype":"locality"
},
  "geometry": {"coordinates":[38.48778,-14.91139],"type":"Point"}
}