{
  "type": "Feature",
  "properties": {
    "gn:admin1_code":"5",
    "gn:asciiname":"Paza",
    "gn:country_code":"MZ",
    "gn:dem":29,
    "gn:feature_class":"P",
    "gn:feature_code":"PPL",
    "gn:name":"Paza",
    "gn:population":0,
    "gn:timezone":"Africa/Maputo",
    "iso:country":"MZ",
    "name:und_x_variant":[
        "Pazo"
    ],
    "wof:name":"Paza",
    "wof:placetype":"locality"
},
  "geometry": {"coordinates":[35.24556,-17.85361],"type":"Point"}
}