{
  "type": "Feature",
  "properties": {
    "gn:admin1_code":"4.0",
    "gn:asciiname":"Guamba",
    "gn:country_code":"MZ",
    "gn:dem":8,
    "gn:feature_class":"P",
    "gn:feature_code":"PPL",
    "gn:name":"Guamba",
    "gn:population":0,
    "gn:timezone":"Africa/Maputo",
    "iso:country":"MZ",
    "wof:name":"Guamba",
    "wof:placetype":"locality"
},
  "geometry": {"coordinates":[32.67333,-25.78833],"type":"Point"}
}