{
  "type": "Feature",
  "properties": {
    "gn:admin1_code":"8",
    "gn:asciiname":"Aldeia Acupita",
    "gn:country_code":"MZ",
    "gn:dem":1009,
    "gn:feature_class":"P",
    "gn:feature_code":"PPL",
    "gn:name":"Aldeia Acupita",
    "gn:population":0,
    "gn:timezone":"Africa/Maputo",
    "iso:country":"MZ",
    "wof:name":"Aldeia Acupita",
    "wof:placetype":"locality"
},
  "geometry": {"coordinates":[34.26917,-14.86611],"type":"Point"}
}