{
  "type": "Feature",
  "properties": {
    "gn:admin1_code":"9.0",
    "gn:asciiname":"Remego",
    "gn:country_code":"MZ",
    "gn:dem":758,
    "gn:feature_class":"P",
    "gn:feature_code":"PPL",
    "gn:name":"Remego",
    "gn:population":0,
    "gn:timezone":"Africa/Maputo",
    "iso:country":"MZ",
    "wof:name":"Remego",
    "wof:placetype":"locality"
},
  "geometry": {"coordinates":[36.73389,-15.49944],"type":"Point"}
}