{
  "type": "Feature",
  "properties": {
    "gn:admin1_code":"1",
    "gn:asciiname":"Muidumbe",
    "gn:country_code":"MZ",
    "gn:dem":597,
    "gn:feature_class":"P",
    "gn:feature_code":"PPL",
    "gn:name":"Muidumbe",
    "gn:population":0,
    "gn:timezone":"Africa/Maputo",
    "iso:country":"MZ",
    "wof:name":"Muidumbe",
    "wof:placetype":"locality"
},
  "geometry": {"coordinates":[39.82139,-11.82361],"type":"Point"}
}