{
  "type": "Feature",
  "properties": {
    "gn:admin1_code":"2.0",
    "gn:asciiname":"Papeni",
    "gn:country_code":"MZ",
    "gn:dem":126,
    "gn:feature_class":"P",
    "gn:feature_code":"PPL",
    "gn:name":"Papeni",
    "gn:population":0,
    "gn:timezone":"Africa/Maputo",
    "iso:country":"MZ",
    "wof:name":"Papeni",
    "wof:placetype":"locality"
},
  "geometry": {"coordinates":[32.07778,-23.02806],"type":"Point"}
}