{
  "type": "Feature",
  "properties": {
    "gn:admin1_code":"1",
    "gn:asciiname":"Nacuchupa",
    "gn:country_code":"MZ",
    "gn:dem":178,
    "gn:feature_class":"P",
    "gn:feature_code":"PPL",
    "gn:name":"Nacuchupa",
    "gn:population":0,
    "gn:timezone":"Africa/Maputo",
    "iso:country":"MZ",
    "wof:name":"Nacuchupa",
    "wof:placetype":"locality"
},
  "geometry": {"coordinates":[40.05917,-12.67889],"type":"Point"}
}