{
  "type": "Feature",
  "properties": {
    "gn:admin1_code":"8",
    "gn:asciiname":"Cachombo",
    "gn:cc2":"MZ",
    "gn:country_code":"MZ",
    "gn:dem":983,
    "gn:feature_class":"P",
    "gn:feature_code":"PPL",
    "gn:name":"Cachombo",
    "gn:population":0,
    "gn:timezone":"Africa/Maputo",
    "iso:country":"MZ",
    "name:und_x_variant":[
        "Cachomba",
        "Cachombo"
    ],
    "wof:name":"Cachombo",
    "wof:placetype":"locality"
},
  "geometry": {"coordinates":[31.82056,-15.05667],"type":"Point"}
}