{
  "type": "Feature",
  "properties": {
    "gn:admin1_code":"1",
    "gn:asciiname":"Atoto",
    "gn:country_code":"MZ",
    "gn:dem":343,
    "gn:feature_class":"P",
    "gn:feature_code":"PPL",
    "gn:name":"At\u00f3to",
    "gn:population":0,
    "gn:timezone":"Africa/Maputo",
    "iso:country":"MZ",
    "name:und_x_variant":[
        "At\u00f3to"
    ],
    "wof:name":"Atoto",
    "wof:placetype":"locality"
},
  "geometry": {"coordinates":[39.86778,-12.88444],"type":"Point"}
}