{
  "type": "Feature",
  "properties": {
    "gn:admin1_code":"1",
    "gn:asciiname":"Lae",
    "gn:country_code":"MZ",
    "gn:dem":97,
    "gn:feature_class":"P",
    "gn:feature_code":"PPL",
    "gn:name":"Lae",
    "gn:population":0,
    "gn:timezone":"Africa/Maputo",
    "iso:country":"MZ",
    "name:cat_x_preferred":[
        "Lae"
    ],
    "name:ces_x_preferred":[
        "Lae"
    ],
    "name:deu_x_preferred":[
        "Lae"
    ],
    "name:epo_x_preferred":[
        "Lae"
    ],
    "name:est_x_preferred":[
        "Lae"
    ],
    "name:eus_x_preferred":[
        "Lae"
    ],
    "name:fas_x_preferred":[
        "\u0644\u0627\u0626\u0647"
    ],
    "name:fin_x_preferred":[
        "Lae"
    ],
    "name:fra_x_preferred":[
        "Lae"
    ],
    "name:glg_x_preferred":[
        "Lae"
    ],
    "name:heb_x_preferred":[
        "\u05dc\u05d0\u05d4"
    ],
    "name:hif_x_preferred":[
        "Lae"
    ],
    "name:ind_x_preferred":[
        "Lae"
    ],
    "name:ita_x_preferred":[
        "Lae"
    ],
    "name:kir_x_preferred":[
        "\u041b\u0430\u044d \u0448\u0430\u0430\u0440\u044b"
    ],
    "name:lit_x_preferred":[
        "La\u0117"
    ],
    "name:nld_x_preferred":[
        "Lae"
    ],
    "name:nor_x_preferred":[
        "Lae"
    ],
    "name:pol_x_preferred":[
        "Lae"
    ],
    "name:por_x_preferred":[
        "Lae"
    ],
    "name:rus_x_preferred":[
        "\u041b\u0430\u044d"
    ],
    "name:slk_x_preferred":[
        "Lae"
    ],
    "name:spa_x_preferred":[
        "Lae"
    ],
    "name:swe_x_preferred":[
        "Lae"
    ],
    "name:tpi_x_preferred":[
        "Lae"
    ],
    "name:ukr_x_preferred":[
        "\u041b\u0430\u0435"
    ],
    "name:urd_x_preferred":[
        "\u0644\u0627\u0626\u06d2"
    ],
    "name:zho_x_preferred":[
        "\u83b1\u57ce"
    ],
    "wof:name":"Lae",
    "wof:placetype":"locality"
},
  "geometry": {"coordinates":[40.11556,-11.09722],"type":"Point"}
}