{
  "type": "Feature",
  "properties": {
    "gn:admin1_code":"5",
    "gn:asciiname":"Chucuane",
    "gn:country_code":"MZ",
    "gn:dem":87,
    "gn:feature_class":"P",
    "gn:feature_code":"PPL",
    "gn:name":"Chucuane",
    "gn:population":0,
    "gn:timezone":"Africa/Maputo",
    "iso:country":"MZ",
    "wof:name":"Chucuane",
    "wof:placetype":"locality"
},
  "geometry": {"coordinates":[33.79583,-20.08028],"type":"Point"}
}