{
  "type": "Feature",
  "properties": {
    "gn:admin1_code":"3.0",
    "gn:asciiname":"V. Chavanguana",
    "gn:country_code":"MZ",
    "gn:dem":47,
    "gn:feature_class":"P",
    "gn:feature_code":"PPL",
    "gn:name":"V. Chavanguana",
    "gn:population":0,
    "gn:timezone":"Africa/Maputo",
    "iso:country":"MZ",
    "wof:name":"V. Chavanguana",
    "wof:placetype":"locality"
},
  "geometry": {"coordinates":[35.10055999999999,-24.00417],"type":"Point"}
}