{
  "type": "Feature",
  "properties": {
    "gn:admin1_code":"1",
    "gn:asciiname":"Muidine",
    "gn:country_code":"MZ",
    "gn:dem":44,
    "gn:feature_class":"P",
    "gn:feature_code":"PPL",
    "gn:name":"Muidine",
    "gn:population":0,
    "gn:timezone":"Africa/Maputo",
    "iso:country":"MZ",
    "wof:name":"Muidine",
    "wof:placetype":"locality"
},
  "geometry": {"coordinates":[39.84944,-10.87972],"type":"Point"}
}