{
  "type": "Feature",
  "properties": {
    "gn:admin1_code":"0",
    "gn:asciiname":"Nachando",
    "gn:country_code":"MZ",
    "gn:dem":545,
    "gn:feature_class":"P",
    "gn:feature_code":"PPL",
    "gn:name":"Nachando",
    "gn:population":0,
    "gn:timezone":"Africa/Maputo",
    "iso:country":"MZ",
    "wof:name":"Nachando",
    "wof:placetype":"locality"
},
  "geometry": {"coordinates":[36.51667,-12.91667],"type":"Point"}
}