{
  "type": "Feature",
  "properties": {
    "gn:admin1_code":"6",
    "gn:asciiname":"Capulo",
    "gn:country_code":"MZ",
    "gn:dem":201,
    "gn:feature_class":"P",
    "gn:feature_code":"PPL",
    "gn:name":"C\u00e1pulo",
    "gn:population":0,
    "gn:timezone":"Africa/Maputo",
    "iso:country":"MZ",
    "wof:name":"Capulo",
    "wof:placetype":"locality"
},
  "geometry": {"coordinates":[40.36417,-13.99222],"type":"Point"}
}