{
  "type": "Feature",
  "properties": {
    "gn:admin1_code":"9",
    "gn:asciiname":"Jacinto",
    "gn:country_code":"MZ",
    "gn:dem":5,
    "gn:feature_class":"P",
    "gn:feature_code":"PPL",
    "gn:name":"Jacinto",
    "gn:population":0,
    "gn:timezone":"Africa/Maputo",
    "iso:country":"MZ",
    "wof:name":"Jacinto",
    "wof:placetype":"locality"
},
  "geometry": {"coordinates":[36.6525,-18.28389],"type":"Point"}
}