{
  "type": "Feature",
  "properties": {
    "gn:admin1_code":"0",
    "gn:asciiname":"Jana",
    "gn:country_code":"MZ",
    "gn:dem":8,
    "gn:feature_class":"P",
    "gn:feature_code":"PPL",
    "gn:name":"Jana",
    "gn:population":0,
    "gn:timezone":"Africa/Maputo",
    "iso:country":"MZ",
    "name:ceb_x_preferred":[
        "Jana"
    ],
    "name:ces_x_preferred":[
        "Jana"
    ],
    "name:deu_x_preferred":[
        "Jana"
    ],
    "name:fin_x_preferred":[
        "Jana"
    ],
    "name:ita_x_preferred":[
        "Jana"
    ],
    "name:nld_x_preferred":[
        "Jana"
    ],
    "name:nor_x_preferred":[
        "Jana"
    ],
    "name:pol_x_preferred":[
        "Jana"
    ],
    "name:por_x_preferred":[
        "Jana"
    ],
    "name:slk_x_preferred":[
        "Jana"
    ],
    "name:srp_x_preferred":[
        "\u0408\u0430\u043d\u0430"
    ],
    "name:swe_x_preferred":[
        "Jana"
    ],
    "wof:name":"Jana",
    "wof:placetype":"locality"
},
  "geometry": {"coordinates":[40.56667,-15.11667],"type":"Point"}
}