{
  "type": "Feature",
  "properties": {
    "gn:admin1_code":"2.0",
    "gn:asciiname":"Ualangane",
    "gn:country_code":"MZ",
    "gn:dem":77,
    "gn:feature_class":"P",
    "gn:feature_code":"PPL",
    "gn:name":"Ualangane",
    "gn:population":0,
    "gn:timezone":"Africa/Maputo",
    "iso:country":"MZ",
    "wof:name":"Ualangane",
    "wof:placetype":"locality"
},
  "geometry": {"coordinates":[33.73305999999999,-24.76167],"type":"Point"}
}