{
  "type": "Feature",
  "properties": {
    "gn:admin1_code":"1.0",
    "gn:asciiname":"Purrumula",
    "gn:country_code":"MZ",
    "gn:dem":317,
    "gn:feature_class":"P",
    "gn:feature_code":"PPL",
    "gn:name":"Purrumula",
    "gn:population":0,
    "gn:timezone":"Africa/Maputo",
    "iso:country":"MZ",
    "wof:name":"Purrumula",
    "wof:placetype":"locality"
},
  "geometry": {"coordinates":[39.34111,-13.66861],"type":"Point"}
}