{
  "type": "Feature",
  "properties": {
    "gn:admin1_code":"2.0",
    "gn:asciiname":"Guilaze",
    "gn:country_code":"MZ",
    "gn:dem":80,
    "gn:feature_class":"P",
    "gn:feature_code":"PPL",
    "gn:name":"Guilaze",
    "gn:population":0,
    "gn:timezone":"Africa/Maputo",
    "iso:country":"MZ",
    "wof:name":"Guilaze",
    "wof:placetype":"locality"
},
  "geometry": {"coordinates":[33.32444,-22.76944],"type":"Point"}
}