{
  "type": "Feature",
  "properties": {
    "gn:admin1_code":"9",
    "gn:asciiname":"Mparrane",
    "gn:country_code":"MZ",
    "gn:dem":710,
    "gn:feature_class":"P",
    "gn:feature_code":"PPL",
    "gn:name":"Mp\u00e1rrane",
    "gn:population":0,
    "gn:timezone":"Africa/Maputo",
    "iso:country":"MZ",
    "wof:name":"Mparrane",
    "wof:placetype":"locality"
},
  "geometry": {"coordinates":[36.76528,-15.06111],"type":"Point"}
}