{
  "type": "Feature",
  "properties": {
    "gn:admin1_code":"6",
    "gn:asciiname":"Massuti",
    "gn:cc2":"MZ",
    "gn:country_code":"MZ",
    "gn:dem":268,
    "gn:feature_class":"P",
    "gn:feature_code":"PPL",
    "gn:name":"Massuti",
    "gn:population":0,
    "gn:timezone":"Africa/Maputo",
    "iso:country":"MZ",
    "name:und_x_variant":[
        "Macutu",
        "Macuto",
        "Massuti"
    ],
    "wof:name":"Massuti",
    "wof:placetype":"locality"
},
  "geometry": {"coordinates":[38.87139000000001,-15.79139],"type":"Point"}
}