{
  "type": "Feature",
  "properties": {
    "gn:admin1_code":"3",
    "gn:asciiname":"Lambo",
    "gn:country_code":"MZ",
    "gn:dem":180,
    "gn:feature_class":"P",
    "gn:feature_code":"PPL",
    "gn:name":"Lambo",
    "gn:population":0,
    "gn:timezone":"Africa/Maputo",
    "iso:country":"MZ",
    "name:ceb_x_preferred":[
        "Lambo"
    ],
    "name:rus_x_preferred":[
        "\u041b\u0430\u043c\u0431\u043e"
    ],
    "name:spa_x_preferred":[
        "Lambo"
    ],
    "name:swe_x_preferred":[
        "Lambo"
    ],
    "wof:name":"Lambo",
    "wof:placetype":"locality"
},
  "geometry": {"coordinates":[33.88222,-21.83167000000001],"type":"Point"}
}