{
  "type": "Feature",
  "properties": {
    "gn:admin1_code":"8.0",
    "gn:asciiname":"Tumbaranhuche",
    "gn:country_code":"MZ",
    "gn:dem":339,
    "gn:feature_class":"P",
    "gn:feature_code":"PPL",
    "gn:name":"Tumbaranhuche",
    "gn:population":0,
    "gn:timezone":"Africa/Maputo",
    "iso:country":"MZ",
    "wof:name":"Tumbaranhuche",
    "wof:placetype":"locality"
},
  "geometry": {"coordinates":[34.11139,-16.15306],"type":"Point"}
}