{
  "type": "Feature",
  "properties": {
    "gn:admin1_code":"1",
    "gn:asciiname":"Chamadi",
    "gn:country_code":"MZ",
    "gn:dem":869,
    "gn:feature_class":"P",
    "gn:feature_code":"PPL",
    "gn:name":"Chamadi",
    "gn:population":0,
    "gn:timezone":"Africa/Maputo",
    "iso:country":"MZ",
    "wof:name":"Chamadi",
    "wof:placetype":"locality"
},
  "geometry": {"coordinates":[39.34333,-11.44361],"type":"Point"}
}