{
  "type": "Feature",
  "properties": {
    "gn:admin1_code":"1",
    "gn:asciiname":"Regulo Natabua",
    "gn:country_code":"MZ",
    "gn:dem":256,
    "gn:feature_class":"P",
    "gn:feature_code":"PPL",
    "gn:name":"R\u00e9gulo Nat\u00e1bua",
    "gn:population":0,
    "gn:timezone":"Africa/Maputo",
    "iso:country":"MZ",
    "wof:name":"Regulo Natabua",
    "wof:placetype":"locality"
},
  "geometry": {"coordinates":[39.70444000000001,-13.64972],"type":"Point"}
}