{
  "type": "Feature",
  "properties": {
    "gn:admin1_code":"1",
    "gn:asciiname":"Lutambo",
    "gn:country_code":"MZ",
    "gn:dem":284,
    "gn:feature_class":"P",
    "gn:feature_code":"PPL",
    "gn:name":"Lutambo",
    "gn:population":0,
    "gn:timezone":"Africa/Maputo",
    "iso:country":"MZ",
    "wof:name":"Lutambo",
    "wof:placetype":"locality"
},
  "geometry": {"coordinates":[39.93917,-11.44667],"type":"Point"}
}