{
  "type": "Feature",
  "properties": {
    "gn:admin1_code":"3.0",
    "gn:asciiname":"Souquisse",
    "gn:country_code":"MZ",
    "gn:dem":114,
    "gn:feature_class":"P",
    "gn:feature_code":"PPL",
    "gn:name":"Souquisse",
    "gn:population":0,
    "gn:timezone":"Africa/Maputo",
    "iso:country":"MZ",
    "wof:name":"Souquisse",
    "wof:placetype":"locality"
},
  "geometry": {"coordinates":[34.74417,-21.86639],"type":"Point"}
}