{
  "type": "Feature",
  "properties": {
    "gn:admin1_code":"6",
    "gn:asciiname":"Muialene",
    "gn:country_code":"MZ",
    "gn:dem":342,
    "gn:feature_class":"P",
    "gn:feature_code":"PPL",
    "gn:name":"Muialene",
    "gn:population":0,
    "gn:timezone":"Africa/Maputo",
    "iso:country":"MZ",
    "wof:name":"Muialene",
    "wof:placetype":"locality"
},
  "geometry": {"coordinates":[39.73139000000001,-14.28806],"type":"Point"}
}