{
  "type": "Feature",
  "properties": {
    "gn:admin1_code":"3.0",
    "gn:asciiname":"Finisse",
    "gn:country_code":"MZ",
    "gn:dem":112,
    "gn:feature_class":"P",
    "gn:feature_code":"PPL",
    "gn:name":"Finisse",
    "gn:population":0,
    "gn:timezone":"Africa/Maputo",
    "iso:country":"MZ",
    "wof:name":"Finisse",
    "wof:placetype":"locality"
},
  "geometry": {"coordinates":[34.60528,-23.21861],"type":"Point"}
}