{
  "type": "Feature",
  "properties": {
    "gn:admin1_code":"0",
    "gn:asciiname":"Javela",
    "gn:country_code":"MZ",
    "gn:dem":33,
    "gn:feature_class":"P",
    "gn:feature_code":"PPL",
    "gn:name":"Javela",
    "gn:population":0,
    "gn:timezone":"Africa/Maputo",
    "iso:country":"MZ",
    "wof:name":"Javela",
    "wof:placetype":"locality"
},
  "geometry": {"coordinates":[33.06667,-24.53333],"type":"Point"}
}