{
  "type": "Feature",
  "properties": {
    "gn:admin1_code":"9.0",
    "gn:asciiname":"Acampamento Sena Sugar",
    "gn:country_code":"MZ",
    "gn:dem":243,
    "gn:feature_class":"P",
    "gn:feature_code":"PPL",
    "gn:name":"Acampamento Sena Sugar",
    "gn:population":0,
    "gn:timezone":"Africa/Maputo",
    "iso:country":"MZ",
    "wof:name":"Acampamento Sena Sugar",
    "wof:placetype":"locality"
},
  "geometry": {"coordinates":[37.53833,-16.42611],"type":"Point"}
}