{
  "type": "Feature",
  "properties": {
    "gn:admin1_code":"4.0",
    "gn:asciiname":"Juliao",
    "gn:country_code":"MZ",
    "gn:dem":112,
    "gn:feature_class":"P",
    "gn:feature_code":"PPL",
    "gn:name":"Juli\u00e3o",
    "gn:population":0,
    "gn:timezone":"Africa/Maputo",
    "iso:country":"MZ",
    "wof:name":"Juliao",
    "wof:placetype":"locality"
},
  "geometry": {"coordinates":[32.38083,-24.54806],"type":"Point"}
}