{
  "type": "Feature",
  "properties": {
    "gn:admin1_code":"9",
    "gn:asciiname":"Chefe Namigo",
    "gn:cc2":"MZ",
    "gn:country_code":"MZ",
    "gn:dem":256,
    "gn:feature_class":"P",
    "gn:feature_code":"PPL",
    "gn:name":"Chefe Namigo",
    "gn:population":0,
    "gn:timezone":"Africa/Maputo",
    "iso:country":"MZ",
    "name:und_x_variant":[
        "Namigo",
        "Chefe Namigo"
    ],
    "wof:name":"Chefe Namigo",
    "wof:placetype":"locality"
},
  "geometry": {"coordinates":[38.17444,-16.06833],"type":"Point"}
}