{
  "type": "Feature",
  "properties": {
    "gn:admin1_code":"4",
    "gn:asciiname":"Machova",
    "gn:country_code":"MZ",
    "gn:dem":37,
    "gn:feature_class":"P",
    "gn:feature_code":"PPL",
    "gn:name":"Machova",
    "gn:population":0,
    "gn:timezone":"Africa/Maputo",
    "iso:country":"MZ",
    "wof:name":"Machova",
    "wof:placetype":"locality"
},
  "geometry": {"coordinates":[32.63056,-26.41167],"type":"Point"}
}