{
  "type": "Feature",
  "properties": {
    "gn:admin1_code":"6",
    "gn:asciiname":"Chefe Gimo",
    "gn:country_code":"MZ",
    "gn:dem":91,
    "gn:feature_class":"P",
    "gn:feature_code":"PPL",
    "gn:name":"Chefe Gimo",
    "gn:population":0,
    "gn:timezone":"Africa/Maputo",
    "iso:country":"MZ",
    "wof:name":"Chefe Gimo",
    "wof:placetype":"locality"
},
  "geometry": {"coordinates":[39.44694000000001,-16.02333],"type":"Point"}
}