{
  "type": "Feature",
  "properties": {
    "gn:admin1_code":"1",
    "gn:asciiname":"Chefe Namuecue",
    "gn:country_code":"MZ",
    "gn:dem":316,
    "gn:feature_class":"P",
    "gn:feature_code":"PPL",
    "gn:name":"Chefe Namu\u00e9cu\u00e8",
    "gn:population":0,
    "gn:timezone":"Africa/Maputo",
    "iso:country":"MZ",
    "wof:name":"Chefe Namuecue",
    "wof:placetype":"locality"
},
  "geometry": {"coordinates":[39.34889,-13.75694],"type":"Point"}
}