{
  "type": "Feature",
  "properties": {
    "gn:admin1_code":"7",
    "gn:asciiname":"Mussoma",
    "gn:cc2":"MZ",
    "gn:country_code":"MZ",
    "gn:dem":505,
    "gn:feature_class":"P",
    "gn:feature_code":"PPL",
    "gn:name":"Mussoma",
    "gn:population":0,
    "gn:timezone":"Africa/Maputo",
    "iso:country":"MZ",
    "name:und_x_variant":[
        "M\u2019soma",
        "Mussoma"
    ],
    "wof:name":"Mussoma",
    "wof:placetype":"locality"
},
  "geometry": {"coordinates":[37.69361,-12.84028],"type":"Point"}
}