{
  "type": "Feature",
  "properties": {
    "gn:admin1_code":"8.0",
    "gn:asciiname":"Tambo",
    "gn:country_code":"MZ",
    "gn:dem":358,
    "gn:feature_class":"P",
    "gn:feature_code":"PPL",
    "gn:name":"Tambo",
    "gn:population":0,
    "gn:timezone":"Africa/Maputo",
    "iso:country":"MZ",
    "wof:name":"Tambo",
    "wof:placetype":"locality"
},
  "geometry": {"coordinates":[33.30917,-16.08083],"type":"Point"}
}