{
  "type": "Feature",
  "properties": {
    "gn:admin1_code":"9.0",
    "gn:asciiname":"Chefe Ligama",
    "gn:country_code":"MZ",
    "gn:dem":396,
    "gn:feature_class":"P",
    "gn:feature_code":"PPL",
    "gn:name":"Chefe Ligama",
    "gn:population":0,
    "gn:timezone":"Africa/Maputo",
    "iso:country":"MZ",
    "wof:name":"Chefe Ligama",
    "wof:placetype":"locality"
},
  "geometry": {"coordinates":[37.19694000000001,-16.12389],"type":"Point"}
}