{
  "type": "Feature",
  "properties": {
    "gn:admin1_code":"8",
    "gn:asciiname":"Magasso",
    "gn:country_code":"MZ",
    "gn:dem":311,
    "gn:feature_class":"P",
    "gn:feature_code":"PPL",
    "gn:name":"Magasso",
    "gn:population":0,
    "gn:timezone":"Africa/Maputo",
    "iso:country":"MZ",
    "wof:name":"Magasso",
    "wof:placetype":"locality"
},
  "geometry": {"coordinates":[33.62389,-16.34444],"type":"Point"}
}