{
  "type": "Feature",
  "properties": {
    "gn:admin1_code":"0",
    "gn:asciiname":"Cambola",
    "gn:cc2":"MZ",
    "gn:country_code":"MZ",
    "gn:dem":45,
    "gn:feature_class":"P",
    "gn:feature_code":"PPL",
    "gn:name":"Cambola",
    "gn:population":0,
    "gn:timezone":"Africa/Maputo",
    "iso:country":"MZ",
    "name:und_x_variant":[
        "Cambota",
        "Cambola"
    ],
    "wof:name":"Cambola",
    "wof:placetype":"locality"
},
  "geometry": {"coordinates":[35.16667,-17.28333],"type":"Point"}
}