{
  "type": "Feature",
  "properties": {
    "gn:admin1_code":"1",
    "gn:asciiname":"Krimisi",
    "gn:country_code":"MZ",
    "gn:dem":17,
    "gn:feature_class":"P",
    "gn:feature_code":"PPL",
    "gn:name":"Krimisi",
    "gn:population":0,
    "gn:timezone":"Africa/Maputo",
    "iso:country":"MZ",
    "wof:name":"Krimisi",
    "wof:placetype":"locality"
},
  "geometry": {"coordinates":[40.47444,-12.17667],"type":"Point"}
}