{
  "type": "Feature",
  "properties": {
    "gn:admin1_code":"9.0",
    "gn:asciiname":"Tapiua",
    "gn:country_code":"MZ",
    "gn:dem":510,
    "gn:feature_class":"P",
    "gn:feature_code":"PPL",
    "gn:name":"T\u00e1piua",
    "gn:population":0,
    "gn:timezone":"Africa/Maputo",
    "iso:country":"MZ",
    "wof:name":"Tapiua",
    "wof:placetype":"locality"
},
  "geometry": {"coordinates":[37.74833,-15.58278],"type":"Point"}
}