{
  "type": "Feature",
  "properties": {
    "gn:admin1_code":"10",
    "gn:asciiname":"Meque",
    "gn:country_code":"MZ",
    "gn:dem":591,
    "gn:feature_class":"P",
    "gn:feature_code":"PPL",
    "gn:name":"Meque",
    "gn:population":0,
    "gn:timezone":"Africa/Maputo",
    "iso:country":"MZ",
    "name:por_x_preferred":[
        "Meque"
    ],
    "wof:name":"Meque",
    "wof:placetype":"locality"
},
  "geometry": {"coordinates":[32.64917,-20.75806],"type":"Point"}
}