{
  "type": "Feature",
  "properties": {
    "gn:admin1_code":"0",
    "gn:asciiname":"Ginga",
    "gn:country_code":"MZ",
    "gn:dem":7,
    "gn:feature_class":"P",
    "gn:feature_code":"PPL",
    "gn:name":"Ginga",
    "gn:population":0,
    "gn:timezone":"Africa/Maputo",
    "iso:country":"MZ",
    "name:ceb_x_preferred":[
        "Ginga"
    ],
    "name:deu_x_preferred":[
        "Ginga"
    ],
    "name:glg_x_preferred":[
        "Ginga"
    ],
    "name:por_x_preferred":[
        "Ginga"
    ],
    "name:spa_x_preferred":[
        "Ginga"
    ],
    "name:swe_x_preferred":[
        "Ginga"
    ],
    "wof:name":"Ginga",
    "wof:placetype":"locality"
},
  "geometry": {"coordinates":[35.68333,-18.83333],"type":"Point"}
}