{
  "type": "Feature",
  "properties": {
    "gn:admin1_code":"9",
    "gn:asciiname":"Mulaquera",
    "gn:country_code":"MZ",
    "gn:dem":695,
    "gn:feature_class":"P",
    "gn:feature_code":"PPL",
    "gn:name":"Mulaqu\u00e9ra",
    "gn:population":0,
    "gn:timezone":"Africa/Maputo",
    "iso:country":"MZ",
    "wof:name":"Mulaquera",
    "wof:placetype":"locality"
},
  "geometry": {"coordinates":[36.03917,-15.51028],"type":"Point"}
}