{
  "type": "Feature",
  "properties": {
    "gn:admin1_code":"2.0",
    "gn:asciiname":"Uatxe",
    "gn:country_code":"MZ",
    "gn:dem":137,
    "gn:feature_class":"P",
    "gn:feature_code":"PPL",
    "gn:name":"Uatxe",
    "gn:population":0,
    "gn:timezone":"Africa/Maputo",
    "iso:country":"MZ",
    "wof:name":"Uatxe",
    "wof:placetype":"locality"
},
  "geometry": {"coordinates":[32.33694000000001,-24.21861],"type":"Point"}
}