{
  "type": "Feature",
  "properties": {
    "gn:admin1_code":"3",
    "gn:asciiname":"Alfinete",
    "gn:country_code":"MZ",
    "gn:dem":76,
    "gn:feature_class":"P",
    "gn:feature_code":"PPL",
    "gn:name":"Alfinete",
    "gn:population":0,
    "gn:timezone":"Africa/Maputo",
    "iso:country":"MZ",
    "name:por_x_preferred":[
        "Alfinete"
    ],
    "wof:name":"Alfinete",
    "wof:placetype":"locality"
},
  "geometry": {"coordinates":[34.83278,-21.52389],"type":"Point"}
}