{
  "type": "Feature",
  "properties": {
    "gn:admin1_code":"10.0",
    "gn:asciiname":"Simbe",
    "gn:country_code":"MZ",
    "gn:dem":427,
    "gn:feature_class":"P",
    "gn:feature_code":"PPL",
    "gn:name":"Simbe",
    "gn:population":0,
    "gn:timezone":"Africa/Maputo",
    "iso:country":"MZ",
    "wof:name":"Simbe",
    "wof:placetype":"locality"
},
  "geometry": {"coordinates":[33.73833,-17.01389],"type":"Point"}
}