{
  "type": "Feature",
  "properties": {
    "gn:admin1_code":"9.0",
    "gn:asciiname":"Chefe Murruba",
    "gn:country_code":"MZ",
    "gn:dem":10,
    "gn:feature_class":"P",
    "gn:feature_code":"PPL",
    "gn:name":"Chefe Murruba",
    "gn:population":0,
    "gn:timezone":"Africa/Maputo",
    "iso:country":"MZ",
    "wof:name":"Chefe Murruba",
    "wof:placetype":"locality"
},
  "geometry": {"coordinates":[38.89,-16.93722],"type":"Point"}
}