{
  "type": "Feature",
  "properties": {
    "gn:admin1_code":"4",
    "gn:asciiname":"Loguaja",
    "gn:cc2":"MZ",
    "gn:country_code":"MZ",
    "gn:dem":86,
    "gn:feature_class":"P",
    "gn:feature_code":"PPL",
    "gn:name":"Loguaja",
    "gn:population":0,
    "gn:timezone":"Africa/Maputo",
    "iso:country":"MZ",
    "name:und_x_variant":[
        "M\u2019guaja",
        "Loguaja"
    ],
    "wof:name":"Loguaja",
    "wof:placetype":"locality"
},
  "geometry": {"coordinates":[32.36556,-25.40417],"type":"Point"}
}