{
  "type": "Feature",
  "properties": {
    "gn:admin1_code":"6",
    "gn:asciiname":"Capataz Devia",
    "gn:country_code":"MZ",
    "gn:dem":700,
    "gn:feature_class":"P",
    "gn:feature_code":"PPL",
    "gn:name":"Capataz Devia",
    "gn:population":0,
    "gn:timezone":"Africa/Maputo",
    "iso:country":"MZ",
    "wof:name":"Capataz Devia",
    "wof:placetype":"locality"
},
  "geometry": {"coordinates":[37.76778,-15.0025],"type":"Point"}
}