{
  "type": "Feature",
  "properties": {
    "gn:admin1_code":"7.0",
    "gn:asciiname":"Totela",
    "gn:country_code":"MZ",
    "gn:dem":1145,
    "gn:feature_class":"P",
    "gn:feature_code":"PPL",
    "gn:name":"Totela",
    "gn:population":0,
    "gn:timezone":"Africa/Maputo",
    "iso:country":"MZ",
    "wof:name":"Totela",
    "wof:placetype":"locality"
},
  "geometry": {"coordinates":[35.35778,-13.12444],"type":"Point"}
}