{
  "type": "Feature",
  "properties": {
    "gn:admin1_code":"3",
    "gn:asciiname":"Muchuacane",
    "gn:country_code":"MZ",
    "gn:dem":181,
    "gn:feature_class":"P",
    "gn:feature_code":"PPL",
    "gn:name":"Muchuacane",
    "gn:population":0,
    "gn:timezone":"Africa/Maputo",
    "iso:country":"MZ",
    "wof:name":"Muchuacane",
    "wof:placetype":"locality"
},
  "geometry": {"coordinates":[34.385,-21.80361],"type":"Point"}
}