{
  "type": "Feature",
  "properties": {
    "gn:admin1_code":"8.0",
    "gn:asciiname":"Rupia",
    "gn:country_code":"MZ",
    "gn:dem":248,
    "gn:feature_class":"P",
    "gn:feature_code":"PPL",
    "gn:name":"Rupia",
    "gn:population":0,
    "gn:timezone":"Africa/Maputo",
    "iso:country":"MZ",
    "wof:name":"Rupia",
    "wof:placetype":"locality"
},
  "geometry": {"coordinates":[33.10917,-15.78889],"type":"Point"}
}