{
  "type": "Feature",
  "properties": {
    "gn:admin1_code":"6",
    "gn:asciiname":"Mirape",
    "gn:country_code":"MZ",
    "gn:dem":199,
    "gn:feature_class":"P",
    "gn:feature_code":"PPL",
    "gn:name":"Mirape",
    "gn:population":0,
    "gn:timezone":"Africa/Maputo",
    "iso:country":"MZ",
    "wof:name":"Mirape",
    "wof:placetype":"locality"
},
  "geometry": {"coordinates":[39.98833,-15.13972],"type":"Point"}
}