{
  "type": "Feature",
  "properties": {
    "gn:admin1_code":"2",
    "gn:asciiname":"Chefe Papate",
    "gn:cc2":"MZ",
    "gn:country_code":"MZ",
    "gn:dem":26,
    "gn:feature_class":"P",
    "gn:feature_code":"PPL",
    "gn:name":"Chefe Papate",
    "gn:population":0,
    "gn:timezone":"Africa/Maputo",
    "iso:country":"MZ",
    "name:und_x_variant":[
        "Papate",
        "Chefe Papate"
    ],
    "wof:name":"Chefe Papate",
    "wof:placetype":"locality"
},
  "geometry": {"coordinates":[33.17083,-24.58333],"type":"Point"}
}