{
  "type": "Feature",
  "properties": {
    "gn:admin1_code":"1",
    "gn:asciiname":"Assini",
    "gn:country_code":"MZ",
    "gn:dem":217,
    "gn:feature_class":"P",
    "gn:feature_code":"PPL",
    "gn:name":"Assini",
    "gn:population":0,
    "gn:timezone":"Africa/Maputo",
    "iso:country":"MZ",
    "name:deu_x_preferred":[
        "Assini"
    ],
    "wof:name":"Assini",
    "wof:placetype":"locality"
},
  "geometry": {"coordinates":[39.95139,-12.43056],"type":"Point"}
}