{
  "type": "Feature",
  "properties": {
    "gn:admin1_code":"9",
    "gn:asciiname":"Passura",
    "gn:country_code":"MZ",
    "gn:dem":96,
    "gn:feature_class":"P",
    "gn:feature_code":"PPL",
    "gn:name":"Passura",
    "gn:population":0,
    "gn:timezone":"Africa/Maputo",
    "iso:country":"MZ",
    "wof:name":"Passura",
    "wof:placetype":"locality"
},
  "geometry": {"coordinates":[36.03861,-17.51556],"type":"Point"}
}