{
  "type": "Feature",
  "properties": {
    "gn:admin1_code":"6",
    "gn:asciiname":"Muiconele",
    "gn:country_code":"MZ",
    "gn:dem":135,
    "gn:feature_class":"P",
    "gn:feature_code":"PPL",
    "gn:name":"Mu\u00efconele",
    "gn:population":0,
    "gn:timezone":"Africa/Maputo",
    "iso:country":"MZ",
    "wof:name":"Muiconele",
    "wof:placetype":"locality"
},
  "geometry": {"coordinates":[39.16667,-15.88778],"type":"Point"}
}