{
  "type": "Feature",
  "properties": {
    "gn:admin1_code":"7",
    "gn:asciiname":"Nocorroco",
    "gn:country_code":"MZ",
    "gn:dem":471,
    "gn:feature_class":"P",
    "gn:feature_code":"PPL",
    "gn:name":"Nocorr\u00f4co",
    "gn:population":0,
    "gn:timezone":"Africa/Maputo",
    "iso:country":"MZ",
    "wof:name":"Nocorroco",
    "wof:placetype":"locality"
},
  "geometry": {"coordinates":[37.91306,-13.94361],"type":"Point"}
}