{
  "type": "Feature",
  "properties": {
    "gn:admin1_code":"9",
    "gn:asciiname":"Maguro",
    "gn:country_code":"MZ",
    "gn:dem":549,
    "gn:feature_class":"P",
    "gn:feature_code":"PPL",
    "gn:name":"Maguro",
    "gn:population":0,
    "gn:timezone":"Africa/Maputo",
    "iso:country":"MZ",
    "wof:name":"Maguro",
    "wof:placetype":"locality"
},
  "geometry": {"coordinates":[37.36861,-15.74972],"type":"Point"}
}