{
  "type": "Feature",
  "properties": {
    "gn:admin1_code":"5",
    "gn:asciiname":"Peupo",
    "gn:country_code":"MZ",
    "gn:dem":20,
    "gn:feature_class":"P",
    "gn:feature_code":"PPL",
    "gn:name":"Peupo",
    "gn:population":0,
    "gn:timezone":"Africa/Maputo",
    "iso:country":"MZ",
    "wof:name":"Peupo",
    "wof:placetype":"locality"
},
  "geometry": {"coordinates":[34.45472,-19.18583],"type":"Point"}
}