{
  "type": "Feature",
  "properties": {
    "gn:admin1_code":"10",
    "gn:asciiname":"Guilaze",
    "gn:country_code":"MZ",
    "gn:dem":141,
    "gn:feature_class":"P",
    "gn:feature_code":"PPL",
    "gn:name":"Guilaze",
    "gn:population":0,
    "gn:timezone":"Africa/Maputo",
    "iso:country":"MZ",
    "wof:name":"Guilaze",
    "wof:placetype":"locality"
},
  "geometry": {"coordinates":[33.44333,-19.99222],"type":"Point"}
}