{
  "type": "Feature",
  "properties": {
    "gn:admin1_code":"5",
    "gn:asciiname":"Chirara",
    "gn:country_code":"MZ",
    "gn:dem":104,
    "gn:feature_class":"P",
    "gn:feature_code":"PPL",
    "gn:name":"Chirara",
    "gn:population":0,
    "gn:timezone":"Africa/Maputo",
    "iso:country":"MZ",
    "wof:name":"Chirara",
    "wof:placetype":"locality"
},
  "geometry": {"coordinates":[33.70139,-20.24972],"type":"Point"}
}