{
  "type": "Feature",
  "properties": {
    "gn:admin1_code":"9",
    "gn:asciiname":"Assumane",
    "gn:country_code":"MZ",
    "gn:dem":9,
    "gn:feature_class":"P",
    "gn:feature_code":"PPL",
    "gn:name":"Assumane",
    "gn:population":0,
    "gn:timezone":"Africa/Maputo",
    "iso:country":"MZ",
    "wof:name":"Assumane",
    "wof:placetype":"locality"
},
  "geometry": {"coordinates":[37.69667000000001,-17.26667],"type":"Point"}
}