{
  "type": "Feature",
  "properties": {
    "gn:admin1_code":"3",
    "gn:asciiname":"Mazambane",
    "gn:cc2":"MZ",
    "gn:country_code":"MZ",
    "gn:dem":165,
    "gn:feature_class":"P",
    "gn:feature_code":"PPL",
    "gn:name":"Mazambane",
    "gn:population":0,
    "gn:timezone":"Africa/Maputo",
    "iso:country":"MZ",
    "name:und_x_variant":[
        "Mazombane",
        "Mazambane"
    ],
    "wof:name":"Mazambane",
    "wof:placetype":"locality"
},
  "geometry": {"coordinates":[34.60556,-22.21944],"type":"Point"}
}