{
  "type": "Feature",
  "properties": {
    "gn:admin1_code":"7",
    "gn:asciiname":"Ibraimo",
    "gn:country_code":"MZ",
    "gn:dem":329,
    "gn:feature_class":"P",
    "gn:feature_code":"PPL",
    "gn:name":"Ibraimo",
    "gn:population":0,
    "gn:timezone":"Africa/Maputo",
    "iso:country":"MZ",
    "wof:name":"Ibraimo",
    "wof:placetype":"locality"
},
  "geometry": {"coordinates":[37.75972,-12.14472],"type":"Point"}
}