{
  "type": "Feature",
  "properties": {
    "gn:admin1_code":"0",
    "gn:asciiname":"Mecuta",
    "gn:country_code":"MZ",
    "gn:dem":16,
    "gn:feature_class":"P",
    "gn:feature_code":"PPL",
    "gn:name":"Mecuta",
    "gn:population":0,
    "gn:timezone":"Africa/Maputo",
    "iso:country":"MZ",
    "wof:name":"Mecuta",
    "wof:placetype":"locality"
},
  "geometry": {"coordinates":[40.55,-14.21667],"type":"Point"}
}