{
  "type": "Feature",
  "properties": {
    "gn:admin1_code":"7",
    "gn:asciiname":"Nampande",
    "gn:cc2":"MZ",
    "gn:country_code":"MZ",
    "gn:dem":996,
    "gn:feature_class":"P",
    "gn:feature_code":"PPL",
    "gn:name":"Nampande",
    "gn:population":0,
    "gn:timezone":"Africa/Maputo",
    "iso:country":"MZ",
    "name:und_x_variant":[
        "Nampanda",
        "Nampande"
    ],
    "wof:name":"Nampande",
    "wof:placetype":"locality"
},
  "geometry": {"coordinates":[35.36639,-12.79444],"type":"Point"}
}