{
  "type": "Feature",
  "properties": {
    "gn:admin1_code":"5",
    "gn:asciiname":"Gire",
    "gn:country_code":"MZ",
    "gn:dem":225,
    "gn:feature_class":"P",
    "gn:feature_code":"PPL",
    "gn:name":"Gire",
    "gn:population":0,
    "gn:timezone":"Africa/Maputo",
    "iso:country":"MZ",
    "wof:name":"Gire",
    "wof:placetype":"locality"
},
  "geometry": {"coordinates":[34.12056,-18.88417],"type":"Point"}
}