{
  "type": "Feature",
  "properties": {
    "gn:admin1_code":"7",
    "gn:asciiname":"Cuitambe",
    "gn:country_code":"MZ",
    "gn:dem":1306,
    "gn:feature_class":"P",
    "gn:feature_code":"PPL",
    "gn:name":"Cuitambe",
    "gn:population":0,
    "gn:timezone":"Africa/Maputo",
    "iso:country":"MZ",
    "wof:name":"Cuitambe",
    "wof:placetype":"locality"
},
  "geometry": {"coordinates":[35.29833,-13.90639],"type":"Point"}
}