{
  "type": "Feature",
  "properties": {
    "gn:admin1_code":"9.0",
    "gn:asciiname":"Techera",
    "gn:country_code":"MZ",
    "gn:dem":259,
    "gn:feature_class":"P",
    "gn:feature_code":"PPL",
    "gn:name":"Techera",
    "gn:population":0,
    "gn:timezone":"Africa/Maputo",
    "iso:country":"MZ",
    "wof:name":"Techera",
    "wof:placetype":"locality"
},
  "geometry": {"coordinates":[37.85889,-16.13583],"type":"Point"}
}