{
  "type": "Feature",
  "properties": {
    "gn:admin1_code":"1",
    "gn:asciiname":"Mueda",
    "gn:country_code":"MZ",
    "gn:dem":264,
    "gn:feature_class":"P",
    "gn:feature_code":"PPL",
    "gn:name":"Mueda",
    "gn:population":0,
    "gn:timezone":"Africa/Maputo",
    "iso:country":"MZ",
    "wof:name":"Mueda",
    "wof:placetype":"locality"
},
  "geometry": {"coordinates":[40.16111,-12.24611],"type":"Point"}
}