{
  "type": "Feature",
  "properties": {
    "gn:admin1_code":"6",
    "gn:asciiname":"Uchia",
    "gn:country_code":"MZ",
    "gn:dem":389,
    "gn:feature_class":"P",
    "gn:feature_code":"PPL",
    "gn:name":"Uchia",
    "gn:population":0,
    "gn:timezone":"Africa/Maputo",
    "iso:country":"MZ",
    "wof:name":"Uchia",
    "wof:placetype":"locality"
},
  "geometry": {"coordinates":[39.36556,-14.26694],"type":"Point"}
}