{
  "type": "Feature",
  "properties": {
    "gn:admin1_code":"4",
    "gn:asciiname":"Peto",
    "gn:country_code":"MZ",
    "gn:dem":30,
    "gn:feature_class":"P",
    "gn:feature_code":"PPL",
    "gn:name":"Peto",
    "gn:population":0,
    "gn:timezone":"Africa/Maputo",
    "iso:country":"MZ",
    "name:ben_x_preferred":[
        "\u09aa\u09c7\u099f\u09cb"
    ],
    "name:cat_x_preferred":[
        "Peto"
    ],
    "name:ceb_x_preferred":[
        "Peto"
    ],
    "name:deu_x_preferred":[
        "Peto"
    ],
    "name:ell_x_preferred":[
        "\u03a0\u03ad\u03c4\u03bf"
    ],
    "name:fas_x_preferred":[
        "\u067e\u062a\u0648"
    ],
    "name:fin_x_preferred":[
        "Peto"
    ],
    "name:fra_x_preferred":[
        "Peto"
    ],
    "name:heb_x_preferred":[
        "\u05e4\u05d8\u05d5"
    ],
    "name:hin_x_preferred":[
        "\u092a\u0947\u091f\u094b"
    ],
    "name:hun_x_preferred":[
        "Peto"
    ],
    "name:ind_x_preferred":[
        "Peto"
    ],
    "name:jpn_x_preferred":[
        "\u30da\u30c8"
    ],
    "name:kor_x_preferred":[
        "\ud398\ud1a0"
    ],
    "name:pol_x_preferred":[
        "Peto"
    ],
    "name:rus_x_preferred":[
        "\u041f\u0435\u0442\u043e"
    ],
    "name:spa_x_preferred":[
        "Peto"
    ],
    "name:srp_x_preferred":[
        "\u041f\u0435\u0442\u043e"
    ],
    "name:swe_x_preferred":[
        "Peto"
    ],
    "name:tur_x_preferred":[
        "Peto"
    ],
    "name:ukr_x_preferred":[
        "\u041f\u0435\u0442\u043e"
    ],
    "name:urd_x_preferred":[
        "\u067e\u06cc\u0679\u0648"
    ],
    "name:vie_x_preferred":[
        "Peto"
    ],
    "name:zho_cn_x_preferred":[
        "\u4f69\u6258"
    ],
    "name:zho_tw_x_preferred":[
        "\u4f69\u6258"
    ],
    "wof:name":"Peto",
    "wof:placetype":"locality"
},
  "geometry": {"coordinates":[32.84917,-26.83306],"type":"Point"}
}