{
  "type": "Feature",
  "properties": {
    "gn:admin1_code":"4",
    "gn:asciiname":"Peto",
    "gn:country_code":"MZ",
    "gn:dem":30,
    "gn:feature_class":"P",
    "gn:feature_code":"PPL",
    "gn:name":"Peto",
    "gn:population":0,
    "gn:timezone":"Africa/Maputo",
    "iso:country":"MZ",
    "name:cat_x_preferred":[
        "Peto"
    ],
    "name:ceb_x_preferred":[
        "Peto"
    ],
    "name:deu_x_preferred":[
        "Peto"
    ],
    "name:fin_x_preferred":[
        "Peto"
    ],
    "name:fra_x_preferred":[
        "Peto"
    ],
    "name:pol_x_preferred":[
        "Peto"
    ],
    "name:rus_x_preferred":[
        "\u041f\u0435\u0442\u043e"
    ],
    "name:spa_x_preferred":[
        "Peto"
    ],
    "name:srp_x_preferred":[
        "\u041f\u0435\u0442\u043e"
    ],
    "name:swe_x_preferred":[
        "Peto"
    ],
    "wof:name":"Peto",
    "wof:placetype":"locality"
},
  "geometry": {"coordinates":[32.84917,-26.83306],"type":"Point"}
}