{
  "type": "Feature",
  "properties": {
    "gn:admin1_code":"4",
    "gn:asciiname":"Peto",
    "gn:country_code":"MZ",
    "gn:dem":30,
    "gn:feature_class":"P",
    "gn:feature_code":"PPL",
    "gn:name":"Peto",
    "gn:population":0,
    "gn:timezone":"Africa/Maputo",
    "iso:country":"MZ",
    "wof:name":"Peto",
    "wof:placetype":"locality"
},
  "geometry": {"coordinates":[32.84917,-26.83306],"type":"Point"}
}