{
  "type": "Feature",
  "properties": {
    "gn:admin1_code":"10",
    "gn:asciiname":"Jacuinje",
    "gn:country_code":"MZ",
    "gn:dem":613,
    "gn:feature_class":"P",
    "gn:feature_code":"PPL",
    "gn:name":"Jacuinje",
    "gn:population":0,
    "gn:timezone":"Africa/Maputo",
    "iso:country":"MZ",
    "wof:name":"Jacuinje",
    "wof:placetype":"locality"
},
  "geometry": {"coordinates":[33.41639,-19.28861],"type":"Point"}
}