{
  "type": "Feature",
  "properties": {
    "gn:admin1_code":"6",
    "gn:asciiname":"Merrogosa",
    "gn:country_code":"MZ",
    "gn:dem":66,
    "gn:feature_class":"P",
    "gn:feature_code":"PPL",
    "gn:name":"Merrogosa",
    "gn:population":0,
    "gn:timezone":"Africa/Maputo",
    "iso:country":"MZ",
    "wof:name":"Merrogosa",
    "wof:placetype":"locality"
},
  "geometry": {"coordinates":[40.47833,-13.93306],"type":"Point"}
}