{
  "type": "Feature",
  "properties": {
    "gn:admin1_code":"6.0",
    "gn:asciiname":"Alberto",
    "gn:country_code":"MZ",
    "gn:dem":79,
    "gn:feature_class":"P",
    "gn:feature_code":"PPL",
    "gn:name":"Alberto",
    "gn:population":0,
    "gn:timezone":"Africa/Maputo",
    "iso:country":"MZ",
    "name:bre_x_preferred":[
        "Alberto"
    ],
    "name:deu_x_preferred":[
        "Alberto"
    ],
    "name:fra_x_preferred":[
        "Alberto"
    ],
    "name:ita_x_preferred":[
        "Alberto"
    ],
    "name:kor_x_preferred":[
        "\uc54c\ubca0\ub974\ud1a0"
    ],
    "name:nld_x_preferred":[
        "Alberto"
    ],
    "name:por_x_preferred":[
        "Alberto"
    ],
    "name:rus_x_preferred":[
        "\u0410\u043b\u044c\u0431\u0435\u0440\u0442\u043e"
    ],
    "name:spa_x_preferred":[
        "Alberto"
    ],
    "wof:name":"Alberto",
    "wof:placetype":"locality"
},
  "geometry": {"coordinates":[39.15972,-16.27277999999999],"type":"Point"}
}