{
  "type": "Feature",
  "properties": {
    "gn:admin1_code":"3.0",
    "gn:asciiname":"Iobela",
    "gn:country_code":"MZ",
    "gn:dem":29,
    "gn:feature_class":"P",
    "gn:feature_code":"PPL",
    "gn:name":"Iobela",
    "gn:population":0,
    "gn:timezone":"Africa/Maputo",
    "iso:country":"MZ",
    "wof:name":"Iobela",
    "wof:placetype":"locality"
},
  "geometry": {"coordinates":[35.14472,-22.08222],"type":"Point"}
}