{
  "type": "Feature",
  "properties": {
    "gn:admin1_code":"3.0",
    "gn:asciiname":"Valente Pumele",
    "gn:country_code":"MZ",
    "gn:dem":37,
    "gn:feature_class":"P",
    "gn:feature_code":"PPL",
    "gn:name":"Valente Pumele",
    "gn:population":0,
    "gn:timezone":"Africa/Maputo",
    "iso:country":"MZ",
    "wof:name":"Valente Pumele",
    "wof:placetype":"locality"
},
  "geometry": {"coordinates":[34.22861,-24.34472],"type":"Point"}
}