{
  "type": "Feature",
  "properties": {
    "gn:admin1_code":"8",
    "gn:asciiname":"Chuaula",
    "gn:country_code":"MZ",
    "gn:dem":392,
    "gn:feature_class":"P",
    "gn:feature_code":"PPL",
    "gn:name":"Chua\u00fala",
    "gn:population":0,
    "gn:timezone":"Africa/Maputo",
    "iso:country":"MZ",
    "wof:name":"Chuaula",
    "wof:placetype":"locality"
},
  "geometry": {"coordinates":[32.90472,-15.50222],"type":"Point"}
}