{
  "type": "Feature",
  "properties": {
    "iso:country":"MZ",
    "qs:gn_country":"MZ",
    "qs:gn_fcode":"PPL",
    "qs:gn_pop":0,
    "qs:name":"Catembe",
    "qs:name_adm0":"Mo\u00e7ambique",
    "qs:name_adm1":"Maputo",
    "qs:photos":70,
    "qs:photos_1k":14,
    "qs:photos_9k":1,
    "qs:photos_9r":2,
    "qs:photos_all":70,
    "qs:photos_sr":2,
    "qs:placetype":"Town",
    "qs:pop_sr":"0",
    "qs:woe_adm0":23424902,
    "wof:name":"Catembe",
    "wof:placetype":"locality"
},
  "geometry": {"coordinates":[32.55738,-26.00295],"type":"Point"}
}