{
  "type": "Feature",
  "properties": {
    "gn:admin1_code":"6",
    "gn:asciiname":"Leite Faria",
    "gn:country_code":"MZ",
    "gn:dem":614,
    "gn:feature_class":"P",
    "gn:feature_code":"PPL",
    "gn:name":"Leite Faria",
    "gn:population":0,
    "gn:timezone":"Africa/Maputo",
    "iso:country":"MZ",
    "wof:name":"Leite Faria",
    "wof:placetype":"locality"
},
  "geometry": {"coordinates":[37.98583,-14.92083],"type":"Point"}
}