{
  "type": "Feature",
  "properties": {
    "gn:admin1_code":"2.0",
    "gn:asciiname":"Judas",
    "gn:country_code":"MZ",
    "gn:dem":155,
    "gn:feature_class":"P",
    "gn:feature_code":"PPL",
    "gn:name":"Judas",
    "gn:population":0,
    "gn:timezone":"Africa/Maputo",
    "iso:country":"MZ",
    "wof:name":"Judas",
    "wof:placetype":"locality"
},
  "geometry": {"coordinates":[32.50472,-23.13528],"type":"Point"}
}