{
  "type": "Feature",
  "properties": {
    "gn:admin1_code":"8.0",
    "gn:asciiname":"Marques",
    "gn:country_code":"MZ",
    "gn:dem":32,
    "gn:feature_class":"P",
    "gn:feature_code":"PPL",
    "gn:name":"Marques",
    "gn:population":0,
    "gn:timezone":"Africa/Maputo",
    "iso:country":"MZ",
    "name:deu_x_preferred":[
        "Marques"
    ],
    "name:epo_x_preferred":[
        "Marques"
    ],
    "name:fra_x_preferred":[
        "Marques"
    ],
    "name:ita_x_preferred":[
        "Marques"
    ],
    "name:por_x_preferred":[
        "Marques"
    ],
    "name:rus_x_preferred":[
        "\u041c\u0430\u0440\u043a\u0435\u0448"
    ],
    "name:swe_x_preferred":[
        "Marques"
    ],
    "wof:name":"Marques",
    "wof:placetype":"locality"
},
  "geometry": {"coordinates":[35.285,-17.43667],"type":"Point"}
}