{
  "type": "Feature",
  "properties": {
    "gn:admin1_code":"6",
    "gn:asciiname":"Chefe Mussassuade",
    "gn:country_code":"MZ",
    "gn:dem":19,
    "gn:feature_class":"P",
    "gn:feature_code":"PPL",
    "gn:name":"Chefe Mussassuade",
    "gn:population":0,
    "gn:timezone":"Africa/Maputo",
    "iso:country":"MZ",
    "wof:name":"Chefe Mussassuade",
    "wof:placetype":"locality"
},
  "geometry": {"coordinates":[39.94,-16.03139],"type":"Point"}
}