{
  "type": "Feature",
  "properties": {
    "gn:admin1_code":"1",
    "gn:asciiname":"Corango",
    "gn:country_code":"MZ",
    "gn:dem":406,
    "gn:feature_class":"P",
    "gn:feature_code":"PPL",
    "gn:name":"Corango",
    "gn:population":0,
    "gn:timezone":"Africa/Maputo",
    "iso:country":"MZ",
    "wof:name":"Corango",
    "wof:placetype":"locality"
},
  "geometry": {"coordinates":[39.1875,-12.95528],"type":"Point"}
}