{
  "type": "Feature",
  "properties": {
    "gn:admin1_code":"7",
    "gn:asciiname":"Venhua",
    "gn:country_code":"MZ",
    "gn:dem":478,
    "gn:feature_class":"P",
    "gn:feature_code":"PPL",
    "gn:name":"Venhua",
    "gn:population":0,
    "gn:timezone":"Africa/Maputo",
    "iso:country":"MZ",
    "wof:name":"Venhua",
    "wof:placetype":"locality"
},
  "geometry": {"coordinates":[37.96389,-14.06056],"type":"Point"}
}