{
  "type": "Feature",
  "properties": {
    "gn:admin1_code":"3.0",
    "gn:asciiname":"Machachovane",
    "gn:country_code":"MZ",
    "gn:dem":100,
    "gn:feature_class":"P",
    "gn:feature_code":"PPL",
    "gn:name":"Machachovane",
    "gn:population":0,
    "gn:timezone":"Africa/Maputo",
    "iso:country":"MZ",
    "wof:name":"Machachovane",
    "wof:placetype":"locality"
},
  "geometry": {"coordinates":[34.68556,-21.34778],"type":"Point"}
}