{
  "type": "Feature",
  "properties": {
    "gn:admin1_code":"1",
    "gn:asciiname":"Cumuumba",
    "gn:country_code":"MZ",
    "gn:dem":211,
    "gn:feature_class":"P",
    "gn:feature_code":"PPL",
    "gn:name":"Cumuumba",
    "gn:population":0,
    "gn:timezone":"Africa/Maputo",
    "iso:country":"MZ",
    "wof:name":"Cumuumba",
    "wof:placetype":"locality"
},
  "geometry": {"coordinates":[39.01861,-11.31778],"type":"Point"}
}