{
  "type": "Feature",
  "properties": {
    "gn:admin1_code":"3.0",
    "gn:asciiname":"Tsotsumane",
    "gn:country_code":"MZ",
    "gn:dem":65,
    "gn:feature_class":"P",
    "gn:feature_code":"PPL",
    "gn:name":"Tsotsumane",
    "gn:population":0,
    "gn:timezone":"Africa/Maputo",
    "iso:country":"MZ",
    "wof:name":"Tsotsumane",
    "wof:placetype":"locality"
},
  "geometry": {"coordinates":[34.79778,-21.30972],"type":"Point"}
}