{
  "type": "Feature",
  "properties": {
    "gn:admin1_code":"0",
    "gn:asciiname":"Goche",
    "gn:country_code":"MZ",
    "gn:dem":3,
    "gn:feature_class":"P",
    "gn:feature_code":"PPL",
    "gn:name":"Goche",
    "gn:population":0,
    "gn:timezone":"Africa/Maputo",
    "iso:country":"MZ",
    "wof:name":"Goche",
    "wof:placetype":"locality"
},
  "geometry": {"coordinates":[36.13333,-18.76667],"type":"Point"}
}