{
  "type": "Feature",
  "properties": {
    "gn:admin1_code":"1",
    "gn:asciiname":"Acutipuane",
    "gn:country_code":"MZ",
    "gn:dem":126,
    "gn:feature_class":"P",
    "gn:feature_code":"PPL",
    "gn:name":"Acutipuane",
    "gn:population":0,
    "gn:timezone":"Africa/Maputo",
    "iso:country":"MZ",
    "wof:name":"Acutipuane",
    "wof:placetype":"locality"
},
  "geometry": {"coordinates":[39.77278,-12.07806],"type":"Point"}
}