{
  "type": "Feature",
  "properties": {
    "gn:admin1_code":"1",
    "gn:asciiname":"Asse",
    "gn:country_code":"MZ",
    "gn:dem":338,
    "gn:feature_class":"P",
    "gn:feature_code":"PPL",
    "gn:name":"Asse",
    "gn:population":0,
    "gn:timezone":"Africa/Maputo",
    "iso:country":"MZ",
    "wof:name":"Asse",
    "wof:placetype":"locality"
},
  "geometry": {"coordinates":[38.87722,-14.01639],"type":"Point"}
}