{
  "type": "Feature",
  "properties": {
    "gn:admin1_code":"1.0",
    "gn:asciiname":"Chefe Chinande",
    "gn:cc2":"MZ",
    "gn:country_code":"MZ",
    "gn:dem":417,
    "gn:feature_class":"P",
    "gn:feature_code":"PPL",
    "gn:name":"Chefe Chinande",
    "gn:population":0,
    "gn:timezone":"Africa/Maputo",
    "iso:country":"MZ",
    "name:und_x_variant":[
        "Quinhante",
        "Chefe Chinande"
    ],
    "wof:name":"Chefe Chinande",
    "wof:placetype":"locality"
},
  "geometry": {"coordinates":[39.53222,-13.01056],"type":"Point"}
}