{
  "type": "Feature",
  "properties": {
    "gn:admin1_code":"9",
    "gn:asciiname":"Bobo",
    "gn:country_code":"MZ",
    "gn:dem":95,
    "gn:feature_class":"P",
    "gn:feature_code":"PPL",
    "gn:name":"Bobo",
    "gn:population":0,
    "gn:timezone":"Africa/Maputo",
    "iso:country":"MZ",
    "wof:name":"Bobo",
    "wof:placetype":"locality"
},
  "geometry": {"coordinates":[36.84361,-17.24639],"type":"Point"}
}