{
  "type": "Feature",
  "properties": {
    "gn:admin1_code":"7",
    "gn:asciiname":"Carrau",
    "gn:country_code":"MZ",
    "gn:dem":556,
    "gn:feature_class":"P",
    "gn:feature_code":"PPL",
    "gn:name":"Carrau",
    "gn:population":0,
    "gn:timezone":"Africa/Maputo",
    "iso:country":"MZ",
    "wof:name":"Carrau",
    "wof:placetype":"locality"
},
  "geometry": {"coordinates":[36.765,-14.72833],"type":"Point"}
}