{
  "type": "Feature",
  "properties": {
    "gn:admin1_code":"7",
    "gn:asciiname":"Lopes",
    "gn:country_code":"MZ",
    "gn:dem":1175,
    "gn:feature_class":"P",
    "gn:feature_code":"PPL",
    "gn:name":"Lopes",
    "gn:population":0,
    "gn:timezone":"Africa/Maputo",
    "iso:country":"MZ",
    "wof:name":"Lopes",
    "wof:placetype":"locality"
},
  "geometry": {"coordinates":[35.25028,-13.63639],"type":"Point"}
}