{
  "type": "Feature",
  "properties": {
    "gn:admin1_code":"6",
    "gn:asciiname":"Licuangua",
    "gn:country_code":"MZ",
    "gn:dem":893,
    "gn:feature_class":"P",
    "gn:feature_code":"PPL",
    "gn:name":"Licu\u00e2ngua",
    "gn:population":0,
    "gn:timezone":"Africa/Maputo",
    "iso:country":"MZ",
    "wof:name":"Licuangua",
    "wof:placetype":"locality"
},
  "geometry": {"coordinates":[37.25694,-15.07778],"type":"Point"}
}