{
  "type": "Feature",
  "properties": {
    "gn:admin1_code":"3",
    "gn:asciiname":"Barane",
    "gn:country_code":"MZ",
    "gn:dem":31,
    "gn:feature_class":"P",
    "gn:feature_code":"PPL",
    "gn:name":"Barane",
    "gn:population":0,
    "gn:timezone":"Africa/Maputo",
    "iso:country":"MZ",
    "wof:name":"Barane",
    "wof:placetype":"locality"
},
  "geometry": {"coordinates":[35.29583,-23.79389],"type":"Point"}
}