{
  "type": "Feature",
  "properties": {
    "gn:admin1_code":"6",
    "gn:asciiname":"Geba",
    "gn:cc2":"MZ",
    "gn:country_code":"MZ",
    "gn:dem":10,
    "gn:feature_class":"P",
    "gn:feature_code":"PPL",
    "gn:name":"Geba",
    "gn:population":0,
    "gn:timezone":"Africa/Maputo",
    "iso:country":"MZ",
    "name:und_x_variant":[
        "Ceba",
        "Gebo",
        "Geba"
    ],
    "wof:name":"Geba",
    "wof:placetype":"locality"
},
  "geometry": {"coordinates":[40.62083,-14.325],"type":"Point"}
}