{
  "type": "Feature",
  "properties": {
    "gn:admin1_code":"3.0",
    "gn:asciiname":"Chefe Rumbatsatsa",
    "gn:cc2":"MZ",
    "gn:country_code":"MZ",
    "gn:dem":74,
    "gn:feature_class":"P",
    "gn:feature_code":"PPL",
    "gn:name":"Chefe Rumbatsatsa",
    "gn:population":0,
    "gn:timezone":"Africa/Maputo",
    "iso:country":"MZ",
    "name:und_x_variant":[
        "Rumba\u00e7a\u00e7a",
        "Chefe Rumbatsatsa"
    ],
    "wof:name":"Chefe Rumbatsatsa",
    "wof:placetype":"locality"
},
  "geometry": {"coordinates":[34.90028,-21.81472],"type":"Point"}
}