{
  "type": "Feature",
  "properties": {
    "gn:admin1_code":"3.0",
    "gn:asciiname":"Laita",
    "gn:country_code":"MZ",
    "gn:dem":101,
    "gn:feature_class":"P",
    "gn:feature_code":"PPL",
    "gn:name":"La\u00edta",
    "gn:population":0,
    "gn:timezone":"Africa/Maputo",
    "iso:country":"MZ",
    "wof:name":"Laita",
    "wof:placetype":"locality"
},
  "geometry": {"coordinates":[35.39333,-22.81694],"type":"Point"}
}