{
  "type": "Feature",
  "properties": {
    "gn:admin1_code":"1",
    "gn:asciiname":"Cabo Bacar",
    "gn:country_code":"MZ",
    "gn:dem":427,
    "gn:feature_class":"P",
    "gn:feature_code":"PPL",
    "gn:name":"Cabo Bacar",
    "gn:population":0,
    "gn:timezone":"Africa/Maputo",
    "iso:country":"MZ",
    "wof:name":"Cabo Bacar",
    "wof:placetype":"locality"
},
  "geometry": {"coordinates":[39.11778,-13.475],"type":"Point"}
}