{
  "type": "Feature",
  "properties": {
    "gn:admin1_code":"6",
    "gn:asciiname":"Inveia",
    "gn:country_code":"MZ",
    "gn:dem":327,
    "gn:feature_class":"P",
    "gn:feature_code":"PPL",
    "gn:name":"Inveia",
    "gn:population":0,
    "gn:timezone":"Africa/Maputo",
    "iso:country":"MZ",
    "wof:name":"Inveia",
    "wof:placetype":"locality"
},
  "geometry": {"coordinates":[38.67806,-15.65528],"type":"Point"}
}