{
  "type": "Feature",
  "properties": {
    "gn:admin1_code":"1",
    "gn:asciiname":"Jancau",
    "gn:country_code":"MZ",
    "gn:dem":468,
    "gn:feature_class":"P",
    "gn:feature_code":"PPL",
    "gn:name":"Jancau",
    "gn:population":0,
    "gn:timezone":"Africa/Maputo",
    "iso:country":"MZ",
    "wof:name":"Jancau",
    "wof:placetype":"locality"
},
  "geometry": {"coordinates":[38.62556,-13.75278],"type":"Point"}
}