{
  "type": "Feature",
  "properties": {
    "gn:admin1_code":"10",
    "gn:asciiname":"Gimo",
    "gn:country_code":"MZ",
    "gn:dem":86,
    "gn:feature_class":"P",
    "gn:feature_code":"PPL",
    "gn:name":"Gimo",
    "gn:population":0,
    "gn:timezone":"Africa/Maputo",
    "iso:country":"MZ",
    "wof:name":"Gimo",
    "wof:placetype":"locality"
},
  "geometry": {"coordinates":[33.91444,-21.1225],"type":"Point"}
}