{
  "type": "Feature",
  "properties": {
    "gn:admin1_code":"9.0",
    "gn:asciiname":"Raimundo",
    "gn:country_code":"MZ",
    "gn:dem":92,
    "gn:feature_class":"P",
    "gn:feature_code":"PPL",
    "gn:name":"Raimundo",
    "gn:population":0,
    "gn:timezone":"Africa/Maputo",
    "iso:country":"MZ",
    "name:ceb_x_preferred":[
        "Raimundo"
    ],
    "name:jpn_x_preferred":[
        "\u30e9\u30a4\u30e0\u30f3\u30c9"
    ],
    "name:por_x_preferred":[
        "Raimundo"
    ],
    "name:swe_x_preferred":[
        "Raimundo"
    ],
    "wof:name":"Raimundo",
    "wof:placetype":"locality"
},
  "geometry": {"coordinates":[38.30583,-16.845],"type":"Point"}
}