{
  "type": "Feature",
  "properties": {
    "gn:admin1_code":"9.0",
    "gn:asciiname":"Raimundo",
    "gn:country_code":"MZ",
    "gn:dem":92,
    "gn:feature_class":"P",
    "gn:feature_code":"PPL",
    "gn:name":"Raimundo",
    "gn:population":0,
    "gn:timezone":"Africa/Maputo",
    "iso:country":"MZ",
    "wof:name":"Raimundo",
    "wof:placetype":"locality"
},
  "geometry": {"coordinates":[38.30583,-16.845],"type":"Point"}
}