{
  "type": "Feature",
  "properties": {
    "gn:admin1_code":"1",
    "gn:asciiname":"Chefe Oscar",
    "gn:country_code":"MZ",
    "gn:dem":90,
    "gn:feature_class":"P",
    "gn:feature_code":"PPL",
    "gn:name":"Chefe Oscar",
    "gn:population":0,
    "gn:timezone":"Africa/Maputo",
    "iso:country":"MZ",
    "wof:name":"Chefe Oscar",
    "wof:placetype":"locality"
},
  "geometry": {"coordinates":[40.385,-13.06722],"type":"Point"}
}