{
  "type": "Feature",
  "properties": {
    "gn:admin1_code":"10",
    "gn:asciiname":"Mereque",
    "gn:country_code":"MZ",
    "gn:dem":533,
    "gn:feature_class":"P",
    "gn:feature_code":"PPL",
    "gn:name":"Mereque",
    "gn:population":0,
    "gn:timezone":"Africa/Maputo",
    "iso:country":"MZ",
    "wof:name":"Mereque",
    "wof:placetype":"locality"
},
  "geometry": {"coordinates":[33.31583,-19.56167],"type":"Point"}
}