{
  "type": "Feature",
  "properties": {
    "gn:admin1_code":"10.0",
    "gn:asciiname":"Mavia",
    "gn:country_code":"MZ",
    "gn:dem":233,
    "gn:feature_class":"P",
    "gn:feature_code":"PPL",
    "gn:name":"Mavia",
    "gn:population":0,
    "gn:timezone":"Africa/Maputo",
    "iso:country":"MZ",
    "wof:name":"Mavia",
    "wof:placetype":"locality"
},
  "geometry": {"coordinates":[33.66222,-20.69111],"type":"Point"}
}