{
  "type": "Feature",
  "properties": {
    "gn:admin1_code":"10",
    "gn:asciiname":"Chacutacuta",
    "gn:country_code":"MZ",
    "gn:dem":378,
    "gn:feature_class":"P",
    "gn:feature_code":"PPL",
    "gn:name":"Chacutacuta",
    "gn:population":0,
    "gn:timezone":"Africa/Maputo",
    "iso:country":"MZ",
    "wof:name":"Chacutacuta",
    "wof:placetype":"locality"
},
  "geometry": {"coordinates":[33.85306,-18.855],"type":"Point"}
}