{
  "type": "Feature",
  "properties": {
    "gn:admin1_code":"3",
    "gn:asciiname":"Chefe Matanato",
    "gn:cc2":"MZ",
    "gn:country_code":"MZ",
    "gn:dem":82,
    "gn:feature_class":"P",
    "gn:feature_code":"PPL",
    "gn:name":"Chefe Matanato",
    "gn:population":0,
    "gn:timezone":"Africa/Maputo",
    "iso:country":"MZ",
    "name:und_x_variant":[
        "Matanato",
        "Chefe Matanato"
    ],
    "wof:name":"Chefe Matanato",
    "wof:placetype":"locality"
},
  "geometry": {"coordinates":[34.46333,-24.68556],"type":"Point"}
}