{
  "type": "Feature",
  "properties": {
    "gn:admin1_code":"9",
    "gn:asciiname":"Murrotua",
    "gn:country_code":"MZ",
    "gn:dem":97,
    "gn:feature_class":"P",
    "gn:feature_code":"PPL",
    "gn:name":"Murrotua",
    "gn:population":0,
    "gn:timezone":"Africa/Maputo",
    "iso:country":"MZ",
    "wof:name":"Murrotua",
    "wof:placetype":"locality"
},
  "geometry": {"coordinates":[37.74028,-16.93667],"type":"Point"}
}