{
  "type": "Feature",
  "properties": {
    "gn:admin1_code":"2",
    "gn:asciiname":"Galaze",
    "gn:country_code":"MZ",
    "gn:dem":15,
    "gn:feature_class":"P",
    "gn:feature_code":"PPL",
    "gn:name":"Galaze",
    "gn:population":0,
    "gn:timezone":"Africa/Maputo",
    "iso:country":"MZ",
    "wof:name":"Galaze",
    "wof:placetype":"locality"
},
  "geometry": {"coordinates":[33.01639,-25.12861],"type":"Point"}
}