{
  "type": "Feature",
  "properties": {
    "gn:admin1_code":"3.0",
    "gn:asciiname":"Chefe Conzo",
    "gn:country_code":"MZ",
    "gn:dem":62,
    "gn:feature_class":"P",
    "gn:feature_code":"PPL",
    "gn:name":"Chefe Conzo",
    "gn:population":0,
    "gn:timezone":"Africa/Maputo",
    "iso:country":"MZ",
    "wof:name":"Chefe Conzo",
    "wof:placetype":"locality"
},
  "geometry": {"coordinates":[35.19778,-24.33222],"type":"Point"}
}