{
  "type": "Feature",
  "properties": {
    "gn:admin1_code":"6.0",
    "gn:asciiname":"Sangoge",
    "gn:cc2":"MZ",
    "gn:country_code":"MZ",
    "gn:dem":44,
    "gn:feature_class":"P",
    "gn:feature_code":"PPL",
    "gn:name":"Sangoge",
    "gn:population":0,
    "gn:timezone":"Africa/Maputo",
    "iso:country":"MZ",
    "name:und_x_variant":[
        "Sangage",
        "Sangoge"
    ],
    "wof:name":"Sangoge",
    "wof:placetype":"locality"
},
  "geometry": {"coordinates":[40.10472,-15.94583],"type":"Point"}
}