{
  "type": "Feature",
  "properties": {
    "gn:admin1_code":"3.0",
    "gn:asciiname":"Laquico",
    "gn:country_code":"MZ",
    "gn:dem":131,
    "gn:feature_class":"P",
    "gn:feature_code":"PPL",
    "gn:name":"Laqui\u00e7o",
    "gn:population":0,
    "gn:timezone":"Africa/Maputo",
    "iso:country":"MZ",
    "wof:name":"Laquico",
    "wof:placetype":"locality"
},
  "geometry": {"coordinates":[34.82694,-22.33139],"type":"Point"}
}