{
  "type": "Feature",
  "properties": {
    "gn:admin1_code":"6",
    "gn:asciiname":"Cabo Bomba",
    "gn:country_code":"MZ",
    "gn:dem":472,
    "gn:feature_class":"P",
    "gn:feature_code":"PPL",
    "gn:name":"Cabo Bomba",
    "gn:population":0,
    "gn:timezone":"Africa/Maputo",
    "iso:country":"MZ",
    "wof:name":"Cabo Bomba",
    "wof:placetype":"locality"
},
  "geometry": {"coordinates":[39.00889,-14.87611],"type":"Point"}
}