{
  "type": "Feature",
  "properties": {
    "gn:admin1_code":"7",
    "gn:asciiname":"Micunde",
    "gn:country_code":"MZ",
    "gn:dem":297,
    "gn:feature_class":"P",
    "gn:feature_code":"PPL",
    "gn:name":"Micunde",
    "gn:population":0,
    "gn:timezone":"Africa/Maputo",
    "iso:country":"MZ",
    "wof:name":"Micunde",
    "wof:placetype":"locality"
},
  "geometry": {"coordinates":[37.77139,-12.28111],"type":"Point"}
}