{
  "type": "Feature",
  "properties": {
    "gn:admin1_code":"3",
    "gn:asciiname":"Cabo Mazucane",
    "gn:cc2":"MZ",
    "gn:country_code":"MZ",
    "gn:dem":81,
    "gn:feature_class":"P",
    "gn:feature_code":"PPL",
    "gn:name":"Cabo Mazucane",
    "gn:population":0,
    "gn:timezone":"Africa/Maputo",
    "iso:country":"MZ",
    "name:und_x_variant":[
        "Mazaucane",
        "Cabo Mazucane"
    ],
    "wof:name":"Cabo Mazucane",
    "wof:placetype":"locality"
},
  "geometry": {"coordinates":[34.64,-24.09611],"type":"Point"}
}