{
  "type": "Feature",
  "properties": {
    "gn:admin1_code":"5",
    "gn:asciiname":"Nhabesse",
    "gn:country_code":"MZ",
    "gn:dem":196,
    "gn:feature_class":"P",
    "gn:feature_code":"PPL",
    "gn:name":"Nhabesse",
    "gn:population":0,
    "gn:timezone":"Africa/Maputo",
    "iso:country":"MZ",
    "wof:name":"Nhabesse",
    "wof:placetype":"locality"
},
  "geometry": {"coordinates":[33.94778,-20.08639],"type":"Point"}
}