{
  "type": "Feature",
  "properties": {
    "gn:admin1_code":"3",
    "gn:asciiname":"Manhelacule",
    "gn:country_code":"MZ",
    "gn:dem":52,
    "gn:feature_class":"P",
    "gn:feature_code":"PPL",
    "gn:name":"Manhelacule",
    "gn:population":0,
    "gn:timezone":"Africa/Maputo",
    "iso:country":"MZ",
    "wof:name":"Manhelacule",
    "wof:placetype":"locality"
},
  "geometry": {"coordinates":[34.77611,-21.26333],"type":"Point"}
}