{
  "type": "Feature",
  "properties": {
    "gn:admin1_code":"9",
    "gn:asciiname":"Conane",
    "gn:country_code":"MZ",
    "gn:dem":741,
    "gn:feature_class":"P",
    "gn:feature_code":"PPL",
    "gn:name":"Conane",
    "gn:population":0,
    "gn:timezone":"Africa/Maputo",
    "iso:country":"MZ",
    "wof:name":"Conane",
    "wof:placetype":"locality"
},
  "geometry": {"coordinates":[37.67556,-15.34528],"type":"Point"}
}