{
  "type": "Feature",
  "properties": {
    "gn:admin1_code":"3.0",
    "gn:asciiname":"Manuel",
    "gn:country_code":"MZ",
    "gn:dem":150,
    "gn:feature_class":"P",
    "gn:feature_code":"PPL",
    "gn:name":"Manuel",
    "gn:population":0,
    "gn:timezone":"Africa/Maputo",
    "iso:country":"MZ",
    "wof:name":"Manuel",
    "wof:placetype":"locality"
},
  "geometry": {"coordinates":[34.49194,-21.77056],"type":"Point"}
}