{
  "type": "Feature",
  "properties": {
    "gn:admin1_code":"0",
    "gn:asciiname":"Nhamatamanga",
    "gn:country_code":"MZ",
    "gn:dem":6,
    "gn:feature_class":"P",
    "gn:feature_code":"PPL",
    "gn:name":"Nhamatamanga",
    "gn:population":0,
    "gn:timezone":"Africa/Maputo",
    "iso:country":"MZ",
    "wof:name":"Nhamatamanga",
    "wof:placetype":"locality"
},
  "geometry": {"coordinates":[36.51667,-18.45],"type":"Point"}
}