{
  "type": "Feature",
  "properties": {
    "gn:admin1_code":"7.0",
    "gn:asciiname":"Salange",
    "gn:country_code":"MZ",
    "gn:dem":1159,
    "gn:feature_class":"P",
    "gn:feature_code":"PPL",
    "gn:name":"Salange",
    "gn:population":0,
    "gn:timezone":"Africa/Maputo",
    "iso:country":"MZ",
    "wof:name":"Salange",
    "wof:placetype":"locality"
},
  "geometry": {"coordinates":[35.53639000000001,-13.20306],"type":"Point"}
}