{
  "type": "Feature",
  "properties": {
    "gn:admin1_code":"7",
    "gn:asciiname":"Chefe Nipurro",
    "gn:country_code":"MZ",
    "gn:dem":671,
    "gn:feature_class":"P",
    "gn:feature_code":"PPL",
    "gn:name":"Chefe Nipurro",
    "gn:population":0,
    "gn:timezone":"Africa/Maputo",
    "iso:country":"MZ",
    "wof:name":"Chefe Nipurro",
    "wof:placetype":"locality"
},
  "geometry": {"coordinates":[36.30056,-14.48444],"type":"Point"}
}