{
  "type": "Feature",
  "properties": {
    "iso:country":"MZ",
    "name:ceb_x_preferred":[
        "Vilanculos"
    ],
    "name:deu_x_preferred":[
        "Flughafen Vilankulo"
    ],
    "name:eng_x_preferred":[
        "Vilankulo Airport"
    ],
    "name:fas_x_preferred":[
        "\u0641\u0631\u0648\u062f\u06af\u0627\u0647 \u0648\u06cc\u0644\u0646\u06a9\u0648\u0644\u0648"
    ],
    "name:jpn_x_preferred":[
        "\u30f4\u30a3\u30e9\u30f3\u30af\u30ed\u30b9"
    ],
    "name:msa_x_preferred":[
        "Lapangan Terbang Vilankulo"
    ],
    "name:pol_x_preferred":[
        "Port lotniczy Vilankulo"
    ],
    "name:ron_x_preferred":[
        "Aeroportul Vilankulo"
    ],
    "name:tgk_x_preferred":[
        "\u0424\u0443\u0440\u0443\u0434\u0433\u043e\u04b3\u0438 \u0432\u0438\u043b\u043d\u043a\u0443\u043b\u0443"
    ],
    "name:zho_x_preferred":[
        "\u7dad\u862d\u5eab\u6d1b\u6a5f\u5834"
    ],
    "oa:elevation_ft":"46",
    "oa:type":"medium_airport",
    "wd:wordcount":122,
    "woe:hierarchy":{
        "country_id":23424902,
        "planet_id":1,
        "state_id":2346313
    },
    "wof:name":"Vilanculos Airport",
    "wof:placetype":"campus"
},
  "geometry": {"coordinates":[35.313297222222,-22.018430555556],"type":"Point"}
}