{
  "type": "Feature",
  "properties": {
    "iso:country":"MZ",
    "name:fas_x_preferred":[
        "\u0641\u0631\u0648\u062f\u06af\u0627\u0647 \u0648\u06cc\u0644\u0646\u06a9\u0648\u0644\u0648"
    ],
    "name:pol_x_preferred":[
        "Port lotniczy Vilankulo"
    ],
    "name:tgk_x_preferred":[
        "\u0424\u0443\u0440\u0443\u0434\u0433\u043e\u04b3\u0438 \u0432\u0438\u043b\u043d\u043a\u0443\u043b\u0443"
    ],
    "oa:elevation_ft":"46",
    "oa:type":"medium_airport",
    "wd:wordcount":122,
    "woe:hierarchy":{
        "country_id":23424902,
        "planet_id":1,
        "state_id":2346313
    },
    "wof:name":"Vilanculos Airport",
    "wof:placetype":"campus"
},
  "geometry": {"coordinates":[35.313297222222,-22.018430555556],"type":"Point"}
}