{
  "type": "Feature",
  "properties": {
    "gn:admin1_code":"0",
    "gn:asciiname":"Goi",
    "gn:country_code":"MZ",
    "gn:dem":185,
    "gn:feature_class":"P",
    "gn:feature_code":"PPL",
    "gn:name":"Goi",
    "gn:population":0,
    "gn:timezone":"Africa/Maputo",
    "iso:country":"MZ",
    "wof:name":"Goi",
    "wof:placetype":"locality"
},
  "geometry": {"coordinates":[34.76667,-17.43333],"type":"Point"}
}