{
  "type": "Feature",
  "properties": {
    "gn:admin1_code":"3.0",
    "gn:asciiname":"Chinongole",
    "gn:country_code":"MZ",
    "gn:dem":174,
    "gn:feature_class":"P",
    "gn:feature_code":"PPL",
    "gn:name":"Chinongole",
    "gn:population":0,
    "gn:timezone":"Africa/Maputo",
    "iso:country":"MZ",
    "wof:name":"Chinongole",
    "wof:placetype":"locality"
},
  "geometry": {"coordinates":[34.58694000000001,-22.09278],"type":"Point"}
}