{
  "type": "Feature",
  "properties": {
    "gn:admin1_code":"3.0",
    "gn:asciiname":"Checoluane",
    "gn:country_code":"MZ",
    "gn:dem":113,
    "gn:feature_class":"P",
    "gn:feature_code":"PPL",
    "gn:name":"Checoluane",
    "gn:population":0,
    "gn:timezone":"Africa/Maputo",
    "iso:country":"MZ",
    "wof:name":"Checoluane",
    "wof:placetype":"locality"
},
  "geometry": {"coordinates":[34.33917,-23.60556],"type":"Point"}
}