{
  "type": "Feature",
  "properties": {
    "gn:admin1_code":"10.0",
    "gn:asciiname":"Mavonde",
    "gn:country_code":"MZ",
    "gn:dem":594,
    "gn:feature_class":"P",
    "gn:feature_code":"PPL",
    "gn:name":"Mavonde",
    "gn:population":0,
    "gn:timezone":"Africa/Maputo",
    "iso:country":"MZ",
    "wof:name":"Mavonde",
    "wof:placetype":"locality"
},
  "geometry": {"coordinates":[33.03551,-18.53848],"type":"Point"}
}