{
  "type": "Feature",
  "properties": {
    "gn:admin1_code":"3",
    "gn:asciiname":"Macauzo",
    "gn:country_code":"MZ",
    "gn:dem":196,
    "gn:feature_class":"P",
    "gn:feature_code":"PPL",
    "gn:name":"Macauzo",
    "gn:population":0,
    "gn:timezone":"Africa/Maputo",
    "iso:country":"MZ",
    "wof:name":"Macauzo",
    "wof:placetype":"locality"
},
  "geometry": {"coordinates":[34.33806,-21.90306],"type":"Point"}
}