{
  "type": "Feature",
  "properties": {
    "gn:admin1_code":"8",
    "gn:asciiname":"Muende",
    "gn:country_code":"MZ",
    "gn:dem":723,
    "gn:feature_class":"P",
    "gn:feature_code":"PPL",
    "gn:name":"Muende",
    "gn:population":0,
    "gn:timezone":"Africa/Maputo",
    "iso:country":"MZ",
    "wof:name":"Muende",
    "wof:placetype":"locality"
},
  "geometry": {"coordinates":[33.02361,-14.39889],"type":"Point"}
}