{
  "type": "Feature",
  "properties": {
    "gn:admin1_code":"1",
    "gn:asciiname":"Metania",
    "gn:country_code":"MZ",
    "gn:dem":320,
    "gn:feature_class":"P",
    "gn:feature_code":"PPL",
    "gn:name":"Metania",
    "gn:population":0,
    "gn:timezone":"Africa/Maputo",
    "iso:country":"MZ",
    "wof:name":"Metania",
    "wof:placetype":"locality"
},
  "geometry": {"coordinates":[39.80639,-13.38528],"type":"Point"}
}