{
  "type": "Feature",
  "properties": {
    "gn:admin1_code":"6",
    "gn:asciiname":"Namaneque",
    "gn:country_code":"MZ",
    "gn:dem":358,
    "gn:feature_class":"P",
    "gn:feature_code":"PPL",
    "gn:name":"Naman\u00e9que",
    "gn:population":0,
    "gn:timezone":"Africa/Maputo",
    "iso:country":"MZ",
    "wof:name":"Namaneque",
    "wof:placetype":"locality"
},
  "geometry": {"coordinates":[38.3875,-14.37722],"type":"Point"}
}