{
  "type": "Feature",
  "properties": {
    "gn:admin1_code":"8",
    "gn:asciiname":"Metengomodzi",
    "gn:cc2":"MZ",
    "gn:country_code":"MZ",
    "gn:dem":1210,
    "gn:feature_class":"P",
    "gn:feature_code":"PPL",
    "gn:name":"Metengomodzi",
    "gn:population":0,
    "gn:timezone":"Africa/Maputo",
    "iso:country":"MZ",
    "name:und_x_variant":[
        "M\u2019Tengo-Ua-Modsi",
        "Metengo-u\u00e1-M\u00f3dzi",
        "Metengomodzi"
    ],
    "wof:name":"Metengomodzi",
    "wof:placetype":"locality"
},
  "geometry": {"coordinates":[34.1875,-14.54444],"type":"Point"}
}