{
  "type": "Feature",
  "properties": {
    "gn:admin1_code":"4.0",
    "gn:asciiname":"Queija",
    "gn:country_code":"MZ",
    "gn:dem":210,
    "gn:feature_class":"P",
    "gn:feature_code":"PPL",
    "gn:name":"Queija",
    "gn:population":0,
    "gn:timezone":"Africa/Maputo",
    "iso:country":"MZ",
    "wof:name":"Queija",
    "wof:placetype":"locality"
},
  "geometry": {"coordinates":[32.10889,-25.69806],"type":"Point"}
}