{
  "type": "Feature",
  "properties": {
    "gn:admin1_code":"7",
    "gn:asciiname":"Limbangoe",
    "gn:cc2":"MZ",
    "gn:country_code":"MZ",
    "gn:dem":998,
    "gn:feature_class":"P",
    "gn:feature_code":"PPL",
    "gn:name":"Limbangoe",
    "gn:population":0,
    "gn:timezone":"Africa/Maputo",
    "iso:country":"MZ",
    "name:und_x_variant":[
        "Limbongoe",
        "Limbangoe"
    ],
    "wof:name":"Limbangoe",
    "wof:placetype":"locality"
},
  "geometry": {"coordinates":[35.62611,-12.74944],"type":"Point"}
}