{
  "type": "Feature",
  "properties": {
    "gn:admin1_code":"10",
    "gn:asciiname":"Machese",
    "gn:country_code":"MZ",
    "gn:dem":140,
    "gn:feature_class":"P",
    "gn:feature_code":"PPL",
    "gn:name":"Machese",
    "gn:population":0,
    "gn:timezone":"Africa/Maputo",
    "iso:country":"MZ",
    "wof:name":"Machese",
    "wof:placetype":"locality"
},
  "geometry": {"coordinates":[33.48639,-19.95056],"type":"Point"}
}