{
  "type": "Feature",
  "properties": {
    "gn:admin1_code":"3",
    "gn:asciiname":"Chicoche",
    "gn:country_code":"MZ",
    "gn:dem":115,
    "gn:feature_class":"P",
    "gn:feature_code":"PPL",
    "gn:name":"Chicoche",
    "gn:population":0,
    "gn:timezone":"Africa/Maputo",
    "iso:country":"MZ",
    "wof:name":"Chicoche",
    "wof:placetype":"locality"
},
  "geometry": {"coordinates":[34.64528,-23.13694],"type":"Point"}
}