{
  "type": "Feature",
  "properties": {
    "gn:admin1_code":"3",
    "gn:asciiname":"Tafula Xidolo",
    "gn:cc2":"MZ",
    "gn:country_code":"MZ",
    "gn:dem":56,
    "gn:feature_class":"P",
    "gn:feature_code":"PPL",
    "gn:name":"Tafula Xidolo",
    "gn:population":0,
    "gn:timezone":"Africa/Maputo",
    "iso:country":"MZ",
    "name:und_x_variant":[
        "Penicelo",
        "Tafula Xidolo"
    ],
    "wof:name":"Tafula Xidolo",
    "wof:placetype":"locality"
},
  "geometry": {"coordinates":[34.73972,-24.64667],"type":"Point"}
}