{
  "type": "Feature",
  "properties": {
    "gn:admin1_code":"6",
    "gn:asciiname":"Nameca",
    "gn:country_code":"MZ",
    "gn:dem":311,
    "gn:feature_class":"P",
    "gn:feature_code":"PPL",
    "gn:name":"Nameca",
    "gn:population":0,
    "gn:timezone":"Africa/Maputo",
    "iso:country":"MZ",
    "wof:name":"Nameca",
    "wof:placetype":"locality"
},
  "geometry": {"coordinates":[39.63889,-15.08111],"type":"Point"}
}