{
  "type": "Feature",
  "properties": {
    "gn:admin1_code":"6",
    "gn:asciiname":"Chefe Umalauato",
    "gn:country_code":"MZ",
    "gn:dem":289,
    "gn:feature_class":"P",
    "gn:feature_code":"PPL",
    "gn:name":"Chefe Umalauato",
    "gn:population":0,
    "gn:timezone":"Africa/Maputo",
    "iso:country":"MZ",
    "wof:name":"Chefe Umalauato",
    "wof:placetype":"locality"
},
  "geometry": {"coordinates":[39.40306,-13.92889],"type":"Point"}
}