{
  "type": "Feature",
  "properties": {
    "gn:admin1_code":"6",
    "gn:asciiname":"Maatxe",
    "gn:country_code":"MZ",
    "gn:dem":459,
    "gn:feature_class":"P",
    "gn:feature_code":"PPL",
    "gn:name":"Ma\u00e1txe",
    "gn:population":0,
    "gn:timezone":"Africa/Maputo",
    "iso:country":"MZ",
    "wof:name":"Maatxe",
    "wof:placetype":"locality"
},
  "geometry": {"coordinates":[37.88778,-14.49056],"type":"Point"}
}