{
  "type": "Feature",
  "properties": {
    "gn:admin1_code":"7",
    "gn:asciiname":"Chefe Meporiua",
    "gn:country_code":"MZ",
    "gn:dem":664,
    "gn:feature_class":"P",
    "gn:feature_code":"PPL",
    "gn:name":"Chefe Meporiua",
    "gn:population":0,
    "gn:timezone":"Africa/Maputo",
    "iso:country":"MZ",
    "wof:name":"Chefe Meporiua",
    "wof:placetype":"locality"
},
  "geometry": {"coordinates":[35.93889,-14.14028],"type":"Point"}
}