{
  "type": "Feature",
  "properties": {
    "gn:admin1_code":"1",
    "gn:asciiname":"Changana",
    "gn:country_code":"MZ",
    "gn:dem":94,
    "gn:feature_class":"P",
    "gn:feature_code":"PPL",
    "gn:name":"Changana",
    "gn:population":0,
    "gn:timezone":"Africa/Maputo",
    "iso:country":"MZ",
    "wof:name":"Changana",
    "wof:placetype":"locality"
},
  "geometry": {"coordinates":[40.22194,-11.43944],"type":"Point"}
}