{
  "type": "Feature",
  "properties": {
    "gn:admin1_code":"2.0",
    "gn:asciiname":"Combo",
    "gn:country_code":"MZ",
    "gn:dem":54,
    "gn:feature_class":"P",
    "gn:feature_code":"PPL",
    "gn:name":"Combo",
    "gn:population":0,
    "gn:timezone":"Africa/Maputo",
    "iso:country":"MZ",
    "name:ceb_x_preferred":[
        "Combo"
    ],
    "name:ces_x_preferred":[
        "Combo"
    ],
    "name:deu_x_preferred":[
        "Combo"
    ],
    "name:fra_x_preferred":[
        "Combo"
    ],
    "name:ita_x_preferred":[
        "Combo"
    ],
    "name:jpn_x_preferred":[
        "\u30b3\u30f3\u30dc"
    ],
    "name:nld_x_preferred":[
        "Combo"
    ],
    "name:spa_x_preferred":[
        "Combo"
    ],
    "name:swe_x_preferred":[
        "Combo"
    ],
    "name:zho_x_preferred":[
        "Combo"
    ],
    "wof:name":"Combo",
    "wof:placetype":"locality"
},
  "geometry": {"coordinates":[33.45361,-23.90556],"type":"Point"}
}