{
  "type": "Feature",
  "properties": {
    "gn:admin1_code":"5",
    "gn:asciiname":"Botera",
    "gn:country_code":"MZ",
    "gn:dem":74,
    "gn:feature_class":"P",
    "gn:feature_code":"PPL",
    "gn:name":"Botera",
    "gn:population":0,
    "gn:timezone":"Africa/Maputo",
    "iso:country":"MZ",
    "wof:name":"Botera",
    "wof:placetype":"locality"
},
  "geometry": {"coordinates":[34.31333,-20.17806],"type":"Point"}
}