{
  "type": "Feature",
  "properties": {
    "gn:admin1_code":"6",
    "gn:asciiname":"Mivia",
    "gn:cc2":"MZ",
    "gn:country_code":"MZ",
    "gn:dem":534,
    "gn:feature_class":"P",
    "gn:feature_code":"PPL",
    "gn:name":"Mivia",
    "gn:population":0,
    "gn:timezone":"Africa/Maputo",
    "iso:country":"MZ",
    "name:und_x_variant":[
        "Mevia",
        "Mivia"
    ],
    "wof:name":"Mivia",
    "wof:placetype":"locality"
},
  "geometry": {"coordinates":[38.97667,-14.83611],"type":"Point"}
}