{
  "type": "Feature",
  "properties": {
    "gn:admin1_code":"1",
    "gn:asciiname":"Calomba",
    "gn:country_code":"MZ",
    "gn:dem":114,
    "gn:feature_class":"P",
    "gn:feature_code":"PPL",
    "gn:name":"Calomba",
    "gn:population":0,
    "gn:timezone":"Africa/Maputo",
    "iso:country":"MZ",
    "wof:name":"Calomba",
    "wof:placetype":"locality"
},
  "geometry": {"coordinates":[40.29861,-10.69111],"type":"Point"}
}