{
  "type": "Feature",
  "properties": {
    "gn:admin1_code":"10.0",
    "gn:asciiname":"Semente",
    "gn:country_code":"MZ",
    "gn:dem":602,
    "gn:feature_class":"P",
    "gn:feature_code":"PPL",
    "gn:name":"Semente",
    "gn:population":0,
    "gn:timezone":"Africa/Maputo",
    "iso:country":"MZ",
    "wof:name":"Semente",
    "wof:placetype":"locality"
},
  "geometry": {"coordinates":[33.08889,-18.63861],"type":"Point"}
}