{
  "type": "Feature",
  "properties": {
    "gn:admin1_code":"5",
    "gn:asciiname":"Malozinene",
    "gn:country_code":"MZ",
    "gn:dem":269,
    "gn:feature_class":"P",
    "gn:feature_code":"PPL",
    "gn:name":"Malozinene",
    "gn:population":0,
    "gn:timezone":"Africa/Maputo",
    "iso:country":"MZ",
    "wof:name":"Malozinene",
    "wof:placetype":"locality"
},
  "geometry": {"coordinates":[33.88528,-20.21306],"type":"Point"}
}