{
  "type": "Feature",
  "properties": {
    "gn:admin1_code":"4.0",
    "gn:asciiname":"Chicutso",
    "gn:country_code":"MZ",
    "gn:dem":81,
    "gn:feature_class":"P",
    "gn:feature_code":"PPL",
    "gn:name":"Chicutso",
    "gn:population":0,
    "gn:timezone":"Africa/Maputo",
    "iso:country":"MZ",
    "wof:name":"Chicutso",
    "wof:placetype":"locality"
},
  "geometry": {"coordinates":[32.51667,-24.48556],"type":"Point"}
}