{
  "type": "Feature",
  "properties": {
    "gn:admin1_code":"4",
    "gn:asciiname":"Lingamo",
    "gn:country_code":"MZ",
    "gn:dem":21,
    "gn:feature_class":"P",
    "gn:feature_code":"PPL",
    "gn:name":"Lingamo",
    "gn:population":0,
    "gn:timezone":"Africa/Maputo",
    "iso:country":"MZ",
    "wof:name":"Lingamo",
    "wof:placetype":"locality"
},
  "geometry": {"coordinates":[32.47417,-25.96222],"type":"Point"}
}