{
  "type": "Feature",
  "properties": {
    "gn:admin1_code":"2.0",
    "gn:asciiname":"Jossefa",
    "gn:country_code":"MZ",
    "gn:dem":52,
    "gn:feature_class":"P",
    "gn:feature_code":"PPL",
    "gn:name":"Jossefa",
    "gn:population":0,
    "gn:timezone":"Africa/Maputo",
    "iso:country":"MZ",
    "wof:name":"Jossefa",
    "wof:placetype":"locality"
},
  "geometry": {"coordinates":[33.86611,-23.49778],"type":"Point"}
}