{
  "type": "Feature",
  "properties": {
    "gn:admin1_code":"5",
    "gn:asciiname":"Chupanga",
    "gn:cc2":"MZ",
    "gn:country_code":"MZ",
    "gn:dem":39,
    "gn:feature_class":"P",
    "gn:feature_code":"PPL",
    "gn:name":"Chupanga",
    "gn:population":0,
    "gn:timezone":"Africa/Maputo",
    "iso:country":"MZ",
    "name:und_x_variant":[
        "Lacerd\u00f3nia",
        "Chupanga"
    ],
    "wof:name":"Chupanga",
    "wof:placetype":"locality"
},
  "geometry": {"coordinates":[35.56417000000001,-18.02111],"type":"Point"}
}