{
  "type": "Feature",
  "properties": {
    "gn:admin1_code":"6",
    "gn:asciiname":"Matibane",
    "gn:cc2":"MZ",
    "gn:country_code":"MZ",
    "gn:dem":12,
    "gn:feature_class":"P",
    "gn:feature_code":"PPL",
    "gn:name":"Matibane",
    "gn:population":0,
    "gn:timezone":"Africa/Maputo",
    "iso:country":"MZ",
    "name:und_x_variant":[
        "Chicoma",
        "Matibane"
    ],
    "wof:name":"Matibane",
    "wof:placetype":"locality"
},
  "geometry": {"coordinates":[40.7625,-14.86111],"type":"Point"}
}