{
  "type": "Feature",
  "properties": {
    "gn:admin1_code":"6.0",
    "gn:asciiname":"Gracio",
    "gn:country_code":"MZ",
    "gn:dem":432,
    "gn:feature_class":"P",
    "gn:feature_code":"PPL",
    "gn:name":"Gracio",
    "gn:population":0,
    "gn:timezone":"Africa/Maputo",
    "iso:country":"MZ",
    "wof:name":"Gracio",
    "wof:placetype":"locality"
},
  "geometry": {"coordinates":[39.39389,-14.42583],"type":"Point"}
}