{
  "type": "Feature",
  "properties": {
    "gn:admin1_code":"0",
    "gn:asciiname":"Joao",
    "gn:country_code":"MZ",
    "gn:dem":15,
    "gn:feature_class":"P",
    "gn:feature_code":"PPL",
    "gn:name":"Jo\u00e3o",
    "gn:population":0,
    "gn:timezone":"Africa/Maputo",
    "iso:country":"MZ",
    "wof:name":"Joao",
    "wof:placetype":"locality"
},
  "geometry": {"coordinates":[32.95,-25.13333],"type":"Point"}
}