{
  "type": "Feature",
  "properties": {
    "gn:admin1_code":"8.0",
    "gn:asciiname":"Sinsuema",
    "gn:country_code":"MZ",
    "gn:dem":968,
    "gn:feature_class":"P",
    "gn:feature_code":"PPL",
    "gn:name":"Sinsuema",
    "gn:population":0,
    "gn:timezone":"Africa/Maputo",
    "iso:country":"MZ",
    "wof:name":"Sinsuema",
    "wof:placetype":"locality"
},
  "geometry": {"coordinates":[31.91861,-14.77972],"type":"Point"}
}