{
  "type": "Feature",
  "properties": {
    "gn:admin1_code":"6",
    "gn:asciiname":"Chefe Puarro",
    "gn:country_code":"MZ",
    "gn:dem":156,
    "gn:feature_class":"P",
    "gn:feature_code":"PPL",
    "gn:name":"Chefe Puarro",
    "gn:population":0,
    "gn:timezone":"Africa/Maputo",
    "iso:country":"MZ",
    "wof:name":"Chefe Puarro",
    "wof:placetype":"locality"
},
  "geometry": {"coordinates":[39.18667,-16.10167],"type":"Point"}
}