{
  "type": "Feature",
  "properties": {
    "gn:admin1_code":"5",
    "gn:asciiname":"Mapounce",
    "gn:cc2":"MZ",
    "gn:country_code":"MZ",
    "gn:dem":78,
    "gn:feature_class":"P",
    "gn:feature_code":"PPL",
    "gn:name":"Mapounce",
    "gn:population":0,
    "gn:timezone":"Africa/Maputo",
    "iso:country":"MZ",
    "name:und_x_variant":[
        "Mapouce",
        "Mapounce"
    ],
    "wof:name":"Mapounce",
    "wof:placetype":"locality"
},
  "geometry": {"coordinates":[34.09889,-21.25889],"type":"Point"}
}