{
  "type": "Feature",
  "properties": {
    "gn:admin1_code":"2",
    "gn:asciiname":"Muzamane",
    "gn:country_code":"MZ",
    "gn:dem":297,
    "gn:feature_class":"P",
    "gn:feature_code":"PPL",
    "gn:name":"Muzamane",
    "gn:population":0,
    "gn:timezone":"Africa/Maputo",
    "iso:country":"MZ",
    "wof:name":"Muzamane",
    "wof:placetype":"locality"
},
  "geometry": {"coordinates":[32.36111,-21.59111],"type":"Point"}
}