{
  "type": "Feature",
  "properties": {
    "gn:admin1_code":"2.0",
    "gn:asciiname":"Jambo",
    "gn:country_code":"MZ",
    "gn:dem":97,
    "gn:feature_class":"P",
    "gn:feature_code":"PPL",
    "gn:name":"Jambo",
    "gn:population":0,
    "gn:timezone":"Africa/Maputo",
    "iso:country":"MZ",
    "wof:name":"Jambo",
    "wof:placetype":"locality"
},
  "geometry": {"coordinates":[32.86111,-23.55],"type":"Point"}
}