{
  "type": "Feature",
  "properties": {
    "gn:admin1_code":"3",
    "gn:asciiname":"Bando Taimo",
    "gn:cc2":"MZ",
    "gn:country_code":"MZ",
    "gn:dem":33,
    "gn:feature_class":"P",
    "gn:feature_code":"PPL",
    "gn:name":"Bando Taimo",
    "gn:population":0,
    "gn:timezone":"Africa/Maputo",
    "iso:country":"MZ",
    "name:und_x_variant":[
        "Namburete",
        "Bando Taimo"
    ],
    "wof:name":"Bando Taimo",
    "wof:placetype":"locality"
},
  "geometry": {"coordinates":[35.37333,-24.22278],"type":"Point"}
}