{
  "type": "Feature",
  "properties": {
    "gn:admin1_code":"6.0",
    "gn:asciiname":"Regulo Muamuia",
    "gn:country_code":"MZ",
    "gn:dem":67,
    "gn:feature_class":"P",
    "gn:feature_code":"PPL",
    "gn:name":"R\u00e9gulo Muamuia",
    "gn:population":0,
    "gn:timezone":"Africa/Maputo",
    "iso:country":"MZ",
    "wof:name":"Regulo Muamuia",
    "wof:placetype":"locality"
},
  "geometry": {"coordinates":[39.03333,-16.40583],"type":"Point"}
}