{
  "type": "Feature",
  "properties": {
    "gn:admin1_code":"0",
    "gn:asciiname":"Antigo Posto de Mandimba",
    "gn:country_code":"MZ",
    "gn:dem":741,
    "gn:feature_class":"P",
    "gn:feature_code":"PPL",
    "gn:name":"Antigo P\u00f4sto de Mandimba",
    "gn:population":0,
    "gn:timezone":"Africa/Maputo",
    "iso:country":"MZ",
    "wof:name":"Antigo Posto de Mandimba",
    "wof:placetype":"locality"
},
  "geometry": {"coordinates":[35.65,-14.36667],"type":"Point"}
}