{
  "type": "Feature",
  "properties": {
    "gn:admin1_code":"1",
    "gn:asciiname":"Chefe Nhebo",
    "gn:country_code":"MZ",
    "gn:dem":311,
    "gn:feature_class":"P",
    "gn:feature_code":"PPL",
    "gn:name":"Chefe Nhebo",
    "gn:population":0,
    "gn:timezone":"Africa/Maputo",
    "iso:country":"MZ",
    "wof:name":"Chefe Nhebo",
    "wof:placetype":"locality"
},
  "geometry": {"coordinates":[39.19389,-13.86861],"type":"Point"}
}