{
  "type": "Feature",
  "properties": {
    "gn:admin1_code":"3",
    "gn:asciiname":"Mazive",
    "gn:country_code":"MZ",
    "gn:dem":119,
    "gn:feature_class":"P",
    "gn:feature_code":"PPL",
    "gn:name":"Mazive",
    "gn:population":0,
    "gn:timezone":"Africa/Maputo",
    "iso:country":"MZ",
    "wof:name":"Mazive",
    "wof:placetype":"locality"
},
  "geometry": {"coordinates":[34.3425,-22.96361],"type":"Point"}
}