{
  "type": "Feature",
  "properties": {
    "gn:admin1_code":"6",
    "gn:asciiname":"Colulo",
    "gn:country_code":"MZ",
    "gn:dem":183,
    "gn:feature_class":"P",
    "gn:feature_code":"PPL",
    "gn:name":"Colulo",
    "gn:population":0,
    "gn:timezone":"Africa/Maputo",
    "iso:country":"MZ",
    "wof:name":"Colulo",
    "wof:placetype":"locality"
},
  "geometry": {"coordinates":[39.79417,-15.20778],"type":"Point"}
}