{
  "type": "Feature",
  "properties": {
    "gn:admin1_code":"9",
    "gn:asciiname":"Namiua",
    "gn:country_code":"MZ",
    "gn:dem":8,
    "gn:feature_class":"P",
    "gn:feature_code":"PPL",
    "gn:name":"Namiua",
    "gn:population":0,
    "gn:timezone":"Africa/Maputo",
    "iso:country":"MZ",
    "wof:name":"Namiua",
    "wof:placetype":"locality"
},
  "geometry": {"coordinates":[37.36167,-17.55694],"type":"Point"}
}