{
  "type": "Feature",
  "properties": {
    "gn:admin1_code":"0",
    "gn:asciiname":"Daimane",
    "gn:country_code":"MZ",
    "gn:dem":169,
    "gn:feature_class":"P",
    "gn:feature_code":"PPL",
    "gn:name":"Daimane",
    "gn:population":0,
    "gn:timezone":"Africa/Maputo",
    "iso:country":"MZ",
    "wof:name":"Daimane",
    "wof:placetype":"locality"
},
  "geometry": {"coordinates":[32.06667,-25.26667],"type":"Point"}
}