{
  "type": "Feature",
  "properties": {
    "gn:admin1_code":"6",
    "gn:asciiname":"Erepa",
    "gn:country_code":"MZ",
    "gn:dem":1,
    "gn:feature_class":"P",
    "gn:feature_code":"PPL",
    "gn:name":"Erepa",
    "gn:population":0,
    "gn:timezone":"Africa/Maputo",
    "iso:country":"MZ",
    "wof:name":"Erepa",
    "wof:placetype":"locality"
},
  "geometry": {"coordinates":[40.82222,-14.80222],"type":"Point"}
}