{
  "type": "Feature",
  "properties": {
    "gn:admin1_code":"9.0",
    "gn:asciiname":"Namualiua",
    "gn:country_code":"MZ",
    "gn:dem":73,
    "gn:feature_class":"P",
    "gn:feature_code":"PPL",
    "gn:name":"Namualiua",
    "gn:population":0,
    "gn:timezone":"Africa/Maputo",
    "iso:country":"MZ",
    "wof:name":"Namualiua",
    "wof:placetype":"locality"
},
  "geometry": {"coordinates":[38.32056,-16.89806],"type":"Point"}
}