{
  "type": "Feature",
  "properties": {
    "gn:admin1_code":"4",
    "gn:asciiname":"Machubo",
    "gn:country_code":"MZ",
    "gn:dem":18,
    "gn:feature_class":"P",
    "gn:feature_code":"PPL",
    "gn:name":"Machubo",
    "gn:population":0,
    "gn:timezone":"Africa/Maputo",
    "iso:country":"MZ",
    "wof:name":"Machubo",
    "wof:placetype":"locality"
},
  "geometry": {"coordinates":[32.93472,-25.49],"type":"Point"}
}