{
  "type": "Feature",
  "properties": {
    "gn:admin1_code":"9.0",
    "gn:asciiname":"Macuo",
    "gn:country_code":"MZ",
    "gn:dem":234,
    "gn:feature_class":"P",
    "gn:feature_code":"PPL",
    "gn:name":"Macuo",
    "gn:population":0,
    "gn:timezone":"Africa/Maputo",
    "iso:country":"MZ",
    "wof:name":"Macuo",
    "wof:placetype":"locality"
},
  "geometry": {"coordinates":[37.77444000000001,-16.37944],"type":"Point"}
}