{
  "type": "Feature",
  "properties": {
    "gn:admin1_code":"1",
    "gn:asciiname":"Chitamire",
    "gn:country_code":"MZ",
    "gn:dem":169,
    "gn:feature_class":"P",
    "gn:feature_code":"PPL",
    "gn:name":"Chitamire",
    "gn:population":0,
    "gn:timezone":"Africa/Maputo",
    "iso:country":"MZ",
    "wof:name":"Chitamire",
    "wof:placetype":"locality"
},
  "geometry": {"coordinates":[38.42639000000001,-11.57139],"type":"Point"}
}