{
  "type": "Feature",
  "properties": {
    "gn:admin1_code":"7",
    "gn:asciiname":"Muanlati",
    "gn:country_code":"MZ",
    "gn:dem":405,
    "gn:feature_class":"P",
    "gn:feature_code":"PPL",
    "gn:name":"Muanlati",
    "gn:population":0,
    "gn:timezone":"Africa/Maputo",
    "iso:country":"MZ",
    "wof:name":"Muanlati",
    "wof:placetype":"locality"
},
  "geometry": {"coordinates":[38.13889,-14.13722],"type":"Point"}
}