{
  "type": "Feature",
  "properties": {
    "gn:admin1_code":"0",
    "gn:asciiname":"Ingerenga",
    "gn:country_code":"MZ",
    "gn:dem":522,
    "gn:feature_class":"P",
    "gn:feature_code":"PPL",
    "gn:name":"Ingerenga",
    "gn:population":0,
    "gn:timezone":"Africa/Maputo",
    "iso:country":"MZ",
    "wof:name":"Ingerenga",
    "wof:placetype":"locality"
},
  "geometry": {"coordinates":[39.03333,-12.96667],"type":"Point"}
}