{
  "type": "Feature",
  "properties": {
    "gn:admin1_code":"10",
    "gn:asciiname":"Chipanga",
    "gn:country_code":"MZ",
    "gn:dem":621,
    "gn:feature_class":"P",
    "gn:feature_code":"PPL",
    "gn:name":"Chipanga",
    "gn:population":0,
    "gn:timezone":"Africa/Maputo",
    "iso:country":"MZ",
    "name:ita_x_preferred":[
        "Chipanga"
    ],
    "name:por_x_preferred":[
        "Chipanga"
    ],
    "name:swa_x_preferred":[
        "Chipanga"
    ],
    "wof:name":"Chipanga",
    "wof:placetype":"locality"
},
  "geometry": {"coordinates":[32.94389,-20.24],"type":"Point"}
}