{
  "type": "Feature",
  "properties": {
    "gn:admin1_code":"7",
    "gn:asciiname":"Aquida",
    "gn:country_code":"MZ",
    "gn:dem":576,
    "gn:feature_class":"P",
    "gn:feature_code":"PPL",
    "gn:name":"Aquida",
    "gn:population":0,
    "gn:timezone":"Africa/Maputo",
    "iso:country":"MZ",
    "wof:name":"Aquida",
    "wof:placetype":"locality"
},
  "geometry": {"coordinates":[36.63583,-13.14306],"type":"Point"}
}