{
  "type": "Feature",
  "properties": {
    "gn:admin1_code":"6",
    "gn:asciiname":"Ancorora",
    "gn:country_code":"MZ",
    "gn:dem":372,
    "gn:feature_class":"P",
    "gn:feature_code":"PPL",
    "gn:name":"Ancorora",
    "gn:population":0,
    "gn:timezone":"Africa/Maputo",
    "iso:country":"MZ",
    "wof:name":"Ancorora",
    "wof:placetype":"locality"
},
  "geometry": {"coordinates":[39.43278,-14.11222],"type":"Point"}
}