{
  "type": "Feature",
  "properties": {
    "gn:admin1_code":"4",
    "gn:asciiname":"Gueleguele",
    "gn:cc2":"MZ",
    "gn:country_code":"MZ",
    "gn:dem":84,
    "gn:feature_class":"P",
    "gn:feature_code":"PPL",
    "gn:name":"Gueleguele",
    "gn:population":0,
    "gn:timezone":"Africa/Maputo",
    "iso:country":"MZ",
    "name:und_x_variant":[
        "Chibanguane",
        "Gueleguele"
    ],
    "wof:name":"Gueleguele",
    "wof:placetype":"locality"
},
  "geometry": {"coordinates":[32.48333,-24.72306],"type":"Point"}
}