{
  "type": "Feature",
  "properties": {
    "gn:admin1_code":"3",
    "gn:asciiname":"Cabo Chiambo",
    "gn:cc2":"MZ",
    "gn:country_code":"MZ",
    "gn:dem":91,
    "gn:feature_class":"P",
    "gn:feature_code":"PPL",
    "gn:name":"Cabo Chiambo",
    "gn:population":0,
    "gn:timezone":"Africa/Maputo",
    "iso:country":"MZ",
    "name:und_x_variant":[
        "Chiambo",
        "Cabo Chiambo"
    ],
    "wof:name":"Cabo Chiambo",
    "wof:placetype":"locality"
},
  "geometry": {"coordinates":[35.03861,-24.10944],"type":"Point"}
}