{
  "type": "Feature",
  "properties": {
    "gn:admin1_code":"3",
    "gn:asciiname":"Murtalha",
    "gn:country_code":"MZ",
    "gn:dem":35,
    "gn:feature_class":"P",
    "gn:feature_code":"PPL",
    "gn:name":"Murtalha",
    "gn:population":0,
    "gn:timezone":"Africa/Maputo",
    "iso:country":"MZ",
    "wof:name":"Murtalha",
    "wof:placetype":"locality"
},
  "geometry": {"coordinates":[35.44361,-21.66278],"type":"Point"}
}