{
  "type": "Feature",
  "properties": {
    "gn:admin1_code":"1",
    "gn:asciiname":"Muaja",
    "gn:country_code":"MZ",
    "gn:dem":426,
    "gn:feature_class":"P",
    "gn:feature_code":"PPL",
    "gn:name":"Muaja",
    "gn:population":0,
    "gn:timezone":"Africa/Maputo",
    "iso:country":"MZ",
    "wof:name":"Muaja",
    "wof:placetype":"locality"
},
  "geometry": {"coordinates":[39.47,-12.99139],"type":"Point"}
}