{
  "type": "Feature",
  "properties": {
    "gn:admin1_code":"2.0",
    "gn:asciiname":"Coxoane",
    "gn:country_code":"MZ",
    "gn:dem":100,
    "gn:feature_class":"P",
    "gn:feature_code":"PPL",
    "gn:name":"Coxoane",
    "gn:population":0,
    "gn:timezone":"Africa/Maputo",
    "iso:country":"MZ",
    "wof:name":"Coxoane",
    "wof:placetype":"locality"
},
  "geometry": {"coordinates":[32.7825,-22.5325],"type":"Point"}
}