{
  "type": "Feature",
  "properties": {
    "gn:admin1_code":"2",
    "gn:asciiname":"Macua",
    "gn:country_code":"MZ",
    "gn:dem":92,
    "gn:feature_class":"P",
    "gn:feature_code":"PPL",
    "gn:name":"Macua",
    "gn:population":0,
    "gn:timezone":"Africa/Maputo",
    "iso:country":"MZ",
    "wof:name":"Macua",
    "wof:placetype":"locality"
},
  "geometry": {"coordinates":[32.41556,-23.46],"type":"Point"}
}