{
  "type": "Feature",
  "properties": {
    "gn:admin1_code":"9.0",
    "gn:asciiname":"Abudo",
    "gn:country_code":"MZ",
    "gn:dem":33,
    "gn:feature_class":"P",
    "gn:feature_code":"PPL",
    "gn:name":"Abudo",
    "gn:population":0,
    "gn:timezone":"Africa/Maputo",
    "iso:country":"MZ",
    "wof:name":"Abudo",
    "wof:placetype":"locality"
},
  "geometry": {"coordinates":[38.62889000000001,-16.88083],"type":"Point"}
}