{
  "type": "Feature",
  "properties": {
    "gn:admin1_code":"6",
    "gn:asciiname":"Luis",
    "gn:country_code":"MZ",
    "gn:dem":273,
    "gn:feature_class":"P",
    "gn:feature_code":"PPL",
    "gn:name":"Lu\u00eds",
    "gn:population":0,
    "gn:timezone":"Africa/Maputo",
    "iso:country":"MZ",
    "name:bre_x_preferred":[
        "Luis"
    ],
    "name:deu_x_preferred":[
        "Luis"
    ],
    "name:eml_x_preferred":[
        "L\u00fc\u00ecg'"
    ],
    "name:glg_x_preferred":[
        "Lois"
    ],
    "name:hye_x_preferred":[
        "\u053c\u0578\u0582\u056b\u057d"
    ],
    "name:lmo_x_preferred":[
        "Luis"
    ],
    "name:nld_x_preferred":[
        "Luis"
    ],
    "name:nor_x_preferred":[
        "Luis"
    ],
    "name:spa_x_preferred":[
        "Luis"
    ],
    "name:srp_x_preferred":[
        "\u0409\u0443\u0434\u0435\u0432\u0438\u0442"
    ],
    "name:ukr_x_preferred":[
        "\u041b\u0443\u0457\u0448"
    ],
    "wof:name":"Luis",
    "wof:placetype":"locality"
},
  "geometry": {"coordinates":[39.47944,-15.3225],"type":"Point"}
}