{
  "type": "Feature",
  "properties": {
    "gn:admin1_code":"9.0",
    "gn:asciiname":"Chefe Patela",
    "gn:country_code":"MZ",
    "gn:dem":174,
    "gn:feature_class":"P",
    "gn:feature_code":"PPL",
    "gn:name":"Chefe Patela",
    "gn:population":0,
    "gn:timezone":"Africa/Maputo",
    "iso:country":"MZ",
    "wof:name":"Chefe Patela",
    "wof:placetype":"locality"
},
  "geometry": {"coordinates":[37.35306,-16.71611],"type":"Point"}
}