{
  "type": "Feature",
  "properties": {
    "gn:admin1_code":"8",
    "gn:asciiname":"Massimbe",
    "gn:country_code":"MZ",
    "gn:dem":362,
    "gn:feature_class":"P",
    "gn:feature_code":"PPL",
    "gn:name":"Massimbe",
    "gn:population":0,
    "gn:timezone":"Africa/Maputo",
    "iso:country":"MZ",
    "wof:name":"Massimbe",
    "wof:placetype":"locality"
},
  "geometry": {"coordinates":[33.18389000000001,-16.10611],"type":"Point"}
}