{
  "type": "Feature",
  "properties": {
    "gn:admin1_code":"2.0",
    "gn:asciiname":"Armazem",
    "gn:country_code":"MZ",
    "gn:dem":67,
    "gn:feature_class":"P",
    "gn:feature_code":"PPL",
    "gn:name":"Armaz\u00e9m",
    "gn:population":0,
    "gn:timezone":"Africa/Maputo",
    "iso:country":"MZ",
    "wof:name":"Armazem",
    "wof:placetype":"locality"
},
  "geometry": {"coordinates":[33.99222,-24.67417],"type":"Point"}
}