{
  "type": "Feature",
  "properties": {
    "gn:admin1_code":"6",
    "gn:asciiname":"Namacazimba",
    "gn:country_code":"MZ",
    "gn:dem":16,
    "gn:feature_class":"P",
    "gn:feature_code":"PPL",
    "gn:name":"Namacazimba",
    "gn:population":0,
    "gn:timezone":"Africa/Maputo",
    "iso:country":"MZ",
    "wof:name":"Namacazimba",
    "wof:placetype":"locality"
},
  "geometry": {"coordinates":[40.75889,-14.62806],"type":"Point"}
}