{
  "type": "Feature",
  "properties": {
    "gn:admin1_code":"6",
    "gn:asciiname":"Nacapa",
    "gn:country_code":"MZ",
    "gn:dem":414,
    "gn:feature_class":"P",
    "gn:feature_code":"PPL",
    "gn:name":"Nacapa",
    "gn:population":0,
    "gn:timezone":"Africa/Maputo",
    "iso:country":"MZ",
    "wof:name":"Nacapa",
    "wof:placetype":"locality"
},
  "geometry": {"coordinates":[38.38167,-14.42556],"type":"Point"}
}