{
  "type": "Feature",
  "properties": {
    "gn:admin1_code":"0",
    "gn:asciiname":"Musseca",
    "gn:country_code":"MZ",
    "gn:dem":362,
    "gn:feature_class":"P",
    "gn:feature_code":"PPL",
    "gn:name":"Muss\u00e9ca",
    "gn:population":0,
    "gn:timezone":"Africa/Maputo",
    "iso:country":"MZ",
    "name:por_x_preferred":[
        "Muss\u00e9ca"
    ],
    "wof:name":"Musseca",
    "wof:placetype":"locality"
},
  "geometry": {"coordinates":[30.98333,-16.05],"type":"Point"}
}