{
  "type": "Feature",
  "properties": {
    "gn:admin1_code":"2.0",
    "gn:asciiname":"Cacha",
    "gn:country_code":"MZ",
    "gn:dem":105,
    "gn:feature_class":"P",
    "gn:feature_code":"PPL",
    "gn:name":"Cacha",
    "gn:population":0,
    "gn:timezone":"Africa/Maputo",
    "iso:country":"MZ",
    "name:que_x_preferred":[
        "Kacha"
    ],
    "name:spa_x_preferred":[
        "Cacha"
    ],
    "wof:name":"Cacha",
    "wof:placetype":"locality"
},
  "geometry": {"coordinates":[33.36444,-22.35667],"type":"Point"}
}