{
  "type": "Feature",
  "properties": {
    "gn:admin1_code":"9",
    "gn:asciiname":"Nhafuba",
    "gn:country_code":"MZ",
    "gn:dem":92,
    "gn:feature_class":"P",
    "gn:feature_code":"PPL",
    "gn:name":"Nhafuba",
    "gn:population":0,
    "gn:timezone":"Africa/Maputo",
    "iso:country":"MZ",
    "wof:name":"Nhafuba",
    "wof:placetype":"locality"
},
  "geometry": {"coordinates":[37.32861,-17.21194],"type":"Point"}
}