{
  "type": "Feature",
  "properties": {
    "gn:admin1_code":"9",
    "gn:asciiname":"Mabua",
    "gn:country_code":"MZ",
    "gn:dem":241,
    "gn:feature_class":"P",
    "gn:feature_code":"PPL",
    "gn:name":"Mabua",
    "gn:population":0,
    "gn:timezone":"Africa/Maputo",
    "iso:country":"MZ",
    "wof:name":"Mabua",
    "wof:placetype":"locality"
},
  "geometry": {"coordinates":[36.42083,-16.98333],"type":"Point"}
}