{
  "type": "Feature",
  "properties": {
    "gn:admin1_code":"9",
    "gn:asciiname":"Verria",
    "gn:country_code":"MZ",
    "gn:dem":621,
    "gn:feature_class":"P",
    "gn:feature_code":"PPL",
    "gn:name":"Verria",
    "gn:population":0,
    "gn:timezone":"Africa/Maputo",
    "iso:country":"MZ",
    "wof:name":"Verria",
    "wof:placetype":"locality"
},
  "geometry": {"coordinates":[36.72417,-15.78306],"type":"Point"}
}