{
  "type": "Feature",
  "properties": {
    "gn:admin1_code":"4.0",
    "gn:asciiname":"Chichique",
    "gn:country_code":"MZ",
    "gn:dem":56,
    "gn:feature_class":"P",
    "gn:feature_code":"PPL",
    "gn:name":"Chichique",
    "gn:population":0,
    "gn:timezone":"Africa/Maputo",
    "iso:country":"MZ",
    "wof:name":"Chichique",
    "wof:placetype":"locality"
},
  "geometry": {"coordinates":[32.67055999999999,-24.49833],"type":"Point"}
}