{
  "type": "Feature",
  "properties": {
    "gn:admin1_code":"7",
    "gn:asciiname":"Lusiano",
    "gn:country_code":"MZ",
    "gn:dem":523,
    "gn:feature_class":"P",
    "gn:feature_code":"PPL",
    "gn:name":"Lusiano",
    "gn:population":0,
    "gn:timezone":"Africa/Maputo",
    "iso:country":"MZ",
    "wof:name":"Lusiano",
    "wof:placetype":"locality"
},
  "geometry": {"coordinates":[37.24583,-14.56],"type":"Point"}
}