{
  "type": "Feature",
  "properties": {
    "gn:admin1_code":"6.0",
    "gn:asciiname":"Cicome",
    "gn:country_code":"MZ",
    "gn:dem":52,
    "gn:feature_class":"P",
    "gn:feature_code":"PPL",
    "gn:name":"Cicome",
    "gn:population":0,
    "gn:timezone":"Africa/Maputo",
    "iso:country":"MZ",
    "wof:name":"Cicome",
    "wof:placetype":"locality"
},
  "geometry": {"coordinates":[39.08417,-16.47722000000001],"type":"Point"}
}