{
  "type": "Feature",
  "properties": {
    "gn:admin1_code":"1",
    "gn:asciiname":"Nhota",
    "gn:country_code":"MZ",
    "gn:dem":46,
    "gn:feature_class":"P",
    "gn:feature_code":"PPL",
    "gn:name":"Nhota",
    "gn:population":0,
    "gn:timezone":"Africa/Maputo",
    "iso:country":"MZ",
    "wof:name":"Nhota",
    "wof:placetype":"locality"
},
  "geometry": {"coordinates":[40.08361,-11.84972],"type":"Point"}
}