{
  "type": "Feature",
  "properties": {
    "gn:admin1_code":"2.0",
    "gn:asciiname":"Chicuambo",
    "gn:country_code":"MZ",
    "gn:dem":78,
    "gn:feature_class":"P",
    "gn:feature_code":"PPL",
    "gn:name":"Chicuambo",
    "gn:population":0,
    "gn:timezone":"Africa/Maputo",
    "iso:country":"MZ",
    "wof:name":"Chicuambo",
    "wof:placetype":"locality"
},
  "geometry": {"coordinates":[32.48944,-23.75167],"type":"Point"}
}