{
  "type": "Feature",
  "properties": {
    "gn:admin1_code":"0.0",
    "gn:asciiname":"Sempa",
    "gn:country_code":"MZ",
    "gn:dem":521,
    "gn:feature_class":"P",
    "gn:feature_code":"PPL",
    "gn:name":"Sempa",
    "gn:population":0,
    "gn:timezone":"Africa/Maputo",
    "iso:country":"MZ",
    "wof:name":"Sempa",
    "wof:placetype":"locality"
},
  "geometry": {"coordinates":[39.03333,-13.13333],"type":"Point"}
}