{
  "type": "Feature",
  "properties": {
    "gn:admin1_code":"6.0",
    "gn:asciiname":"Chefe Albino",
    "gn:country_code":"MZ",
    "gn:dem":165,
    "gn:feature_class":"P",
    "gn:feature_code":"PPL",
    "gn:name":"Chefe Albino",
    "gn:population":0,
    "gn:timezone":"Africa/Maputo",
    "iso:country":"MZ",
    "wof:name":"Chefe Albino",
    "wof:placetype":"locality"
},
  "geometry": {"coordinates":[39.08139,-16.13806],"type":"Point"}
}