{
  "type": "Feature",
  "properties": {
    "gn:admin1_code":"7",
    "gn:asciiname":"Loice",
    "gn:country_code":"MZ",
    "gn:dem":496,
    "gn:feature_class":"P",
    "gn:feature_code":"PPL",
    "gn:name":"Loice",
    "gn:population":0,
    "gn:timezone":"Africa/Maputo",
    "iso:country":"MZ",
    "wof:name":"Loice",
    "wof:placetype":"locality"
},
  "geometry": {"coordinates":[34.70611,-12.38722],"type":"Point"}
}