{
  "type": "Feature",
  "properties": {
    "gn:admin1_code":"3",
    "gn:asciiname":"Magueza",
    "gn:country_code":"MZ",
    "gn:dem":151,
    "gn:feature_class":"P",
    "gn:feature_code":"PPL",
    "gn:name":"Magueza",
    "gn:population":0,
    "gn:timezone":"Africa/Maputo",
    "iso:country":"MZ",
    "wof:name":"Magueza",
    "wof:placetype":"locality"
},
  "geometry": {"coordinates":[35.14833,-23.68],"type":"Point"}
}