{
  "type": "Feature",
  "properties": {
    "gn:admin1_code":"8",
    "gn:asciiname":"Chataza",
    "gn:country_code":"MZ",
    "gn:dem":201,
    "gn:feature_class":"P",
    "gn:feature_code":"PPL",
    "gn:name":"Chataza",
    "gn:population":0,
    "gn:timezone":"Africa/Maputo",
    "iso:country":"MZ",
    "wof:name":"Chataza",
    "wof:placetype":"locality"
},
  "geometry": {"coordinates":[33.45389,-16.47639],"type":"Point"}
}