{
  "type": "Feature",
  "properties": {
    "gn:admin1_code":"1",
    "gn:asciiname":"Muicaua",
    "gn:country_code":"MZ",
    "gn:dem":334,
    "gn:feature_class":"P",
    "gn:feature_code":"PPL",
    "gn:name":"Muicaua",
    "gn:population":0,
    "gn:timezone":"Africa/Maputo",
    "iso:country":"MZ",
    "wof:name":"Muicaua",
    "wof:placetype":"locality"
},
  "geometry": {"coordinates":[39.945,-12.16917],"type":"Point"}
}