{
  "type": "Feature",
  "properties": {
    "gn:admin1_code":"4",
    "gn:asciiname":"Mijubeque",
    "gn:country_code":"MZ",
    "gn:dem":102,
    "gn:feature_class":"P",
    "gn:feature_code":"PPL",
    "gn:name":"Mijubeque",
    "gn:population":0,
    "gn:timezone":"Africa/Maputo",
    "iso:country":"MZ",
    "wof:name":"Mijubeque",
    "wof:placetype":"locality"
},
  "geometry": {"coordinates":[32.38333,-25.63333],"type":"Point"}
}