{
  "type": "Feature",
  "properties": {
    "gn:admin1_code":"1.0",
    "gn:asciiname":"Ungunga",
    "gn:country_code":"MZ",
    "gn:dem":874,
    "gn:feature_class":"P",
    "gn:feature_code":"PPL",
    "gn:name":"Ungunga",
    "gn:population":0,
    "gn:timezone":"Africa/Maputo",
    "iso:country":"MZ",
    "wof:name":"Ungunga",
    "wof:placetype":"locality"
},
  "geometry": {"coordinates":[39.54306,-11.5975],"type":"Point"}
}