{
  "type": "Feature",
  "properties": {
    "gn:admin1_code":"8",
    "gn:asciiname":"Aldeia Necungas",
    "gn:country_code":"MZ",
    "gn:dem":310,
    "gn:feature_class":"P",
    "gn:feature_code":"PPL",
    "gn:name":"Aldeia Necungas",
    "gn:population":0,
    "gn:timezone":"Africa/Maputo",
    "iso:country":"MZ",
    "wof:name":"Aldeia Necungas",
    "wof:placetype":"locality"
},
  "geometry": {"coordinates":[34.27472,-16.17694],"type":"Point"}
}