{
  "type": "Feature",
  "properties": {
    "gn:admin1_code":"0",
    "gn:asciiname":"Muchaque",
    "gn:country_code":"MZ",
    "gn:dem":2,
    "gn:feature_class":"P",
    "gn:feature_code":"PPL",
    "gn:name":"Muchaque",
    "gn:population":0,
    "gn:timezone":"Africa/Maputo",
    "iso:country":"MZ",
    "wof:name":"Muchaque",
    "wof:placetype":"locality"
},
  "geometry": {"coordinates":[33.58333,-25.13333],"type":"Point"}
}