{
  "type": "Feature",
  "properties": {
    "gn:admin1_code":"7",
    "gn:asciiname":"Nhunga",
    "gn:country_code":"MZ",
    "gn:dem":676,
    "gn:feature_class":"P",
    "gn:feature_code":"PPL",
    "gn:name":"Nhunga",
    "gn:population":0,
    "gn:timezone":"Africa/Maputo",
    "iso:country":"MZ",
    "wof:name":"Nhunga",
    "wof:placetype":"locality"
},
  "geometry": {"coordinates":[36.66111,-13.44333],"type":"Point"}
}