{
  "type": "Feature",
  "properties": {
    "gn:admin1_code":"2.0",
    "gn:asciiname":"Bubuio",
    "gn:country_code":"MZ",
    "gn:dem":58,
    "gn:feature_class":"P",
    "gn:feature_code":"PPL",
    "gn:name":"Bubuio",
    "gn:population":0,
    "gn:timezone":"Africa/Maputo",
    "iso:country":"MZ",
    "wof:name":"Bubuio",
    "wof:placetype":"locality"
},
  "geometry": {"coordinates":[33.37667,-23.8625],"type":"Point"}
}