{
  "type": "Feature",
  "properties": {
    "gn:admin1_code":"9.0",
    "gn:asciiname":"Marrare",
    "gn:country_code":"MZ",
    "gn:dem":5,
    "gn:feature_class":"P",
    "gn:feature_code":"PPL",
    "gn:name":"Marrare",
    "gn:population":0,
    "gn:timezone":"Africa/Maputo",
    "iso:country":"MZ",
    "wof:name":"Marrare",
    "wof:placetype":"locality"
},
  "geometry": {"coordinates":[37.61806,-17.49889],"type":"Point"}
}