{
  "type": "Feature",
  "properties": {
    "gn:admin1_code":"9",
    "gn:asciiname":"Inhamiara",
    "gn:country_code":"MZ",
    "gn:dem":6,
    "gn:feature_class":"P",
    "gn:feature_code":"PPL",
    "gn:name":"Inhamiara",
    "gn:population":0,
    "gn:timezone":"Africa/Maputo",
    "iso:country":"MZ",
    "wof:name":"Inhamiara",
    "wof:placetype":"locality"
},
  "geometry": {"coordinates":[36.52472,-18.5175],"type":"Point"}
}