{
  "type": "Feature",
  "properties": {
    "gn:admin1_code":"8",
    "gn:asciiname":"Aldeia Gimica",
    "gn:country_code":"MZ",
    "gn:dem":513,
    "gn:feature_class":"P",
    "gn:feature_code":"PPL",
    "gn:name":"Aldeia Gimica",
    "gn:population":0,
    "gn:timezone":"Africa/Maputo",
    "iso:country":"MZ",
    "wof:name":"Aldeia Gimica",
    "wof:placetype":"locality"
},
  "geometry": {"coordinates":[33.16028,-15.52056],"type":"Point"}
}