{
  "type": "Feature",
  "properties": {
    "gn:admin1_code":"1",
    "gn:asciiname":"Muali",
    "gn:country_code":"MZ",
    "gn:dem":424,
    "gn:feature_class":"P",
    "gn:feature_code":"PPL",
    "gn:name":"Mu\u00e1li",
    "gn:population":0,
    "gn:timezone":"Africa/Maputo",
    "iso:country":"MZ",
    "wof:name":"Muali",
    "wof:placetype":"locality"
},
  "geometry": {"coordinates":[38.87778,-13.62194],"type":"Point"}
}