{
  "type": "Feature",
  "properties": {
    "gn:admin1_code":"5",
    "gn:asciiname":"Mangomonhe",
    "gn:country_code":"MZ",
    "gn:dem":153,
    "gn:feature_class":"P",
    "gn:feature_code":"PPL",
    "gn:name":"Mangomonhe",
    "gn:population":0,
    "gn:timezone":"Africa/Maputo",
    "iso:country":"MZ",
    "wof:name":"Mangomonhe",
    "wof:placetype":"locality"
},
  "geometry": {"coordinates":[34.03805999999999,-20.37361],"type":"Point"}
}