{
  "type": "Feature",
  "properties": {
    "gn:admin1_code":"6",
    "gn:asciiname":"Murengulo",
    "gn:country_code":"MZ",
    "gn:dem":5,
    "gn:feature_class":"P",
    "gn:feature_code":"PPL",
    "gn:name":"Murengulo",
    "gn:population":0,
    "gn:timezone":"Africa/Maputo",
    "iso:country":"MZ",
    "wof:name":"Murengulo",
    "wof:placetype":"locality"
},
  "geometry": {"coordinates":[40.725,-14.98833],"type":"Point"}
}