{
  "type": "Feature",
  "properties": {
    "gn:admin1_code":"3.0",
    "gn:asciiname":"Laissane Muanzule",
    "gn:country_code":"MZ",
    "gn:dem":66,
    "gn:feature_class":"P",
    "gn:feature_code":"PPL",
    "gn:name":"La\u00edssane Muanzule",
    "gn:population":0,
    "gn:timezone":"Africa/Maputo",
    "iso:country":"MZ",
    "wof:name":"Laissane Muanzule",
    "wof:placetype":"locality"
},
  "geometry": {"coordinates":[34.06,-24.29472],"type":"Point"}
}