{
  "type": "Feature",
  "properties": {
    "gn:admin1_code":"10",
    "gn:asciiname":"Nadingo",
    "gn:country_code":"MZ",
    "gn:dem":503,
    "gn:feature_class":"P",
    "gn:feature_code":"PPL",
    "gn:name":"Nadingo",
    "gn:population":0,
    "gn:timezone":"Africa/Maputo",
    "iso:country":"MZ",
    "wof:name":"Nadingo",
    "wof:placetype":"locality"
},
  "geometry": {"coordinates":[33.33556,-19.65444],"type":"Point"}
}