{
  "type": "Feature",
  "properties": {
    "gn:admin1_code":"7",
    "gn:asciiname":"Macalonge",
    "gn:cc2":"MZ",
    "gn:country_code":"MZ",
    "gn:dem":944,
    "gn:feature_class":"P",
    "gn:feature_code":"PPL",
    "gn:name":"Macalonge",
    "gn:population":0,
    "gn:timezone":"Africa/Maputo",
    "iso:country":"MZ",
    "name:und_x_variant":[
        "Mecaloje",
        "Macaloje",
        "Sanga",
        "Macaloge",
        "Macaloze",
        "Macalonge"
    ],
    "wof:name":"Macalonge",
    "wof:placetype":"locality"
},
  "geometry": {"coordinates":[35.42778,-12.49972],"type":"Point"}
}