{
  "type": "Feature",
  "properties": {
    "gn:admin1_code":"8",
    "gn:asciiname":"Chissambo",
    "gn:cc2":"MZ",
    "gn:country_code":"MZ",
    "gn:dem":575,
    "gn:feature_class":"P",
    "gn:feature_code":"PPL",
    "gn:name":"Chissambo",
    "gn:population":0,
    "gn:timezone":"Africa/Maputo",
    "iso:country":"MZ",
    "name:und_x_variant":[
        "Chissamba",
        "Chissambo"
    ],
    "wof:name":"Chissambo",
    "wof:placetype":"locality"
},
  "geometry": {"coordinates":[32.9875,-14.77694],"type":"Point"}
}