{
  "type": "Feature",
  "properties": {
    "gn:admin1_code":"7",
    "gn:asciiname":"Mcorrona",
    "gn:country_code":"MZ",
    "gn:dem":473,
    "gn:feature_class":"P",
    "gn:feature_code":"PPL",
    "gn:name":"Mcorrona",
    "gn:population":0,
    "gn:timezone":"Africa/Maputo",
    "iso:country":"MZ",
    "wof:name":"Mcorrona",
    "wof:placetype":"locality"
},
  "geometry": {"coordinates":[37.49028,-14.37222],"type":"Point"}
}