{
  "type": "Feature",
  "properties": {
    "gn:admin1_code":"1",
    "gn:asciiname":"Chipande",
    "gn:country_code":"MZ",
    "gn:dem":702,
    "gn:feature_class":"P",
    "gn:feature_code":"PPL",
    "gn:name":"Chipande",
    "gn:population":0,
    "gn:timezone":"Africa/Maputo",
    "iso:country":"MZ",
    "wof:name":"Chipande",
    "wof:placetype":"locality"
},
  "geometry": {"coordinates":[39.63167,-11.62417],"type":"Point"}
}