{
  "type": "Feature",
  "properties": {
    "gn:admin1_code":"2",
    "gn:asciiname":"Magondene",
    "gn:cc2":"MZ",
    "gn:country_code":"MZ",
    "gn:dem":63,
    "gn:feature_class":"P",
    "gn:feature_code":"PPL",
    "gn:name":"Magondene",
    "gn:population":0,
    "gn:timezone":"Africa/Maputo",
    "iso:country":"MZ",
    "name:und_x_variant":[
        "Magandene",
        "Magondene"
    ],
    "wof:name":"Magondene",
    "wof:placetype":"locality"
},
  "geometry": {"coordinates":[33.36667,-23.73278],"type":"Point"}
}