{
  "type": "Feature",
  "properties": {
    "gn:admin1_code":"6",
    "gn:asciiname":"Abudala",
    "gn:country_code":"MZ",
    "gn:dem":224,
    "gn:feature_class":"P",
    "gn:feature_code":"PPL",
    "gn:name":"Abudala",
    "gn:population":0,
    "gn:timezone":"Africa/Maputo",
    "iso:country":"MZ",
    "wof:name":"Abudala",
    "wof:placetype":"locality"
},
  "geometry": {"coordinates":[39.22278,-15.43972],"type":"Point"}
}