{
  "type": "Feature",
  "properties": {
    "gn:admin1_code":"2.0",
    "gn:asciiname":"Tengalene",
    "gn:country_code":"MZ",
    "gn:dem":37,
    "gn:feature_class":"P",
    "gn:feature_code":"PPL",
    "gn:name":"Tengalene",
    "gn:population":0,
    "gn:timezone":"Africa/Maputo",
    "iso:country":"MZ",
    "wof:name":"Tengalene",
    "wof:placetype":"locality"
},
  "geometry": {"coordinates":[33.24139,-25.06306],"type":"Point"}
}