{
  "type": "Feature",
  "properties": {
    "gn:admin1_code":"3",
    "gn:asciiname":"Magumo",
    "gn:country_code":"MZ",
    "gn:dem":130,
    "gn:feature_class":"P",
    "gn:feature_code":"PPL",
    "gn:name":"Magumo",
    "gn:population":0,
    "gn:timezone":"Africa/Maputo",
    "iso:country":"MZ",
    "wof:name":"Magumo",
    "wof:placetype":"locality"
},
  "geometry": {"coordinates":[33.41778,-22.15083],"type":"Point"}
}