{
  "type": "Feature",
  "properties": {
    "gn:admin1_code":"3.0",
    "gn:asciiname":"Calbe Lazaro",
    "gn:country_code":"MZ",
    "gn:dem":85,
    "gn:feature_class":"P",
    "gn:feature_code":"PPL",
    "gn:name":"Calbe L\u00e1zaro",
    "gn:population":0,
    "gn:timezone":"Africa/Maputo",
    "iso:country":"MZ",
    "wof:name":"Calbe Lazaro",
    "wof:placetype":"locality"
},
  "geometry": {"coordinates":[34.89861,-24.34972],"type":"Point"}
}