{
  "type": "Feature",
  "properties": {
    "gn:admin1_code":"3.0",
    "gn:asciiname":"Chico",
    "gn:country_code":"MZ",
    "gn:dem":138,
    "gn:feature_class":"P",
    "gn:feature_code":"PPL",
    "gn:name":"Chico",
    "gn:population":0,
    "gn:timezone":"Africa/Maputo",
    "iso:country":"MZ",
    "wof:name":"Chico",
    "wof:placetype":"locality"
},
  "geometry": {"coordinates":[34.77972,-23.8575],"type":"Point"}
}