{
  "type": "Feature",
  "properties": {
    "gn:admin1_code":"6.0",
    "gn:asciiname":"Puruma",
    "gn:country_code":"MZ",
    "gn:dem":263,
    "gn:feature_class":"P",
    "gn:feature_code":"PPL",
    "gn:name":"Puruma",
    "gn:population":0,
    "gn:timezone":"Africa/Maputo",
    "iso:country":"MZ",
    "wof:name":"Puruma",
    "wof:placetype":"locality"
},
  "geometry": {"coordinates":[40.095,-14.54667],"type":"Point"}
}