{
  "type": "Feature",
  "properties": {
    "gn:admin1_code":"9",
    "gn:asciiname":"Cardoso",
    "gn:country_code":"MZ",
    "gn:dem":63,
    "gn:feature_class":"P",
    "gn:feature_code":"PPL",
    "gn:name":"Cardoso",
    "gn:population":0,
    "gn:timezone":"Africa/Maputo",
    "iso:country":"MZ",
    "name:ceb_x_preferred":[
        "Cardoso"
    ],
    "name:deu_x_preferred":[
        "Cardoso"
    ],
    "name:fra_x_preferred":[
        "Cardoso"
    ],
    "name:heb_x_preferred":[
        "\u05e7\u05e8\u05d3\u05d5\u05e1\u05d5"
    ],
    "name:ita_x_preferred":[
        "Cardoso"
    ],
    "name:jpn_x_preferred":[
        "\u30ab\u30eb\u30c9\u30fc\u30be"
    ],
    "name:nld_x_preferred":[
        "Cardoso"
    ],
    "name:rus_x_preferred":[
        "\u041a\u0430\u0440\u0434\u043e\u0437\u0443"
    ],
    "name:swe_x_preferred":[
        "Cardoso"
    ],
    "wof:name":"Cardoso",
    "wof:placetype":"locality"
},
  "geometry": {"coordinates":[35.78639000000001,-17.80611],"type":"Point"}
}