{
  "type": "Feature",
  "properties": {
    "gn:admin1_code":"9",
    "gn:asciiname":"Namanjavira",
    "gn:country_code":"MZ",
    "gn:dem":330,
    "gn:feature_class":"P",
    "gn:feature_code":"PPL",
    "gn:name":"Namanjavira",
    "gn:population":0,
    "gn:timezone":"Africa/Maputo",
    "iso:country":"MZ",
    "wof:name":"Namanjavira",
    "wof:placetype":"locality"
},
  "geometry": {"coordinates":[36.57556,-16.7975],"type":"Point"}
}