{
  "type": "Feature",
  "properties": {
    "gn:admin1_code":"10",
    "gn:asciiname":"Mteme",
    "gn:country_code":"MZ",
    "gn:dem":428,
    "gn:feature_class":"P",
    "gn:feature_code":"PPL",
    "gn:name":"Mteme",
    "gn:population":0,
    "gn:timezone":"Africa/Maputo",
    "iso:country":"MZ",
    "wof:name":"Mteme",
    "wof:placetype":"locality"
},
  "geometry": {"coordinates":[33.92917,-17.26],"type":"Point"}
}