{
  "type": "Feature",
  "properties": {
    "gn:admin1_code":"1.0",
    "gn:asciiname":"Tepere",
    "gn:country_code":"MZ",
    "gn:dem":377,
    "gn:feature_class":"P",
    "gn:feature_code":"PPL",
    "gn:name":"Tepere",
    "gn:population":0,
    "gn:timezone":"Africa/Maputo",
    "iso:country":"MZ",
    "wof:name":"Tepere",
    "wof:placetype":"locality"
},
  "geometry": {"coordinates":[38.80972,-13.96333],"type":"Point"}
}