{
  "type": "Feature",
  "properties": {
    "gn:admin1_code":"10.0",
    "gn:asciiname":"Samboco",
    "gn:country_code":"MZ",
    "gn:dem":210,
    "gn:feature_class":"P",
    "gn:feature_code":"PPL",
    "gn:name":"Samboco",
    "gn:population":0,
    "gn:timezone":"Africa/Maputo",
    "iso:country":"MZ",
    "wof:name":"Samboco",
    "wof:placetype":"locality"
},
  "geometry": {"coordinates":[33.52833,-20.90222],"type":"Point"}
}