{
  "type": "Feature",
  "properties": {
    "gn:admin1_code":"9.0",
    "gn:asciiname":"Tapua",
    "gn:country_code":"MZ",
    "gn:dem":214,
    "gn:feature_class":"P",
    "gn:feature_code":"PPL",
    "gn:name":"Tapua",
    "gn:population":0,
    "gn:timezone":"Africa/Maputo",
    "iso:country":"MZ",
    "wof:name":"Tapua",
    "wof:placetype":"locality"
},
  "geometry": {"coordinates":[37.17306,-16.53972000000001],"type":"Point"}
}