{
  "type": "Feature",
  "properties": {
    "gn:admin1_code":"7",
    "gn:asciiname":"Mavago",
    "gn:cc2":"MZ",
    "gn:country_code":"MZ",
    "gn:dem":781,
    "gn:feature_class":"P",
    "gn:feature_code":"PPL",
    "gn:name":"Mavago",
    "gn:population":0,
    "gn:timezone":"Africa/Maputo",
    "iso:country":"MZ",
    "name:und_x_variant":[
        "Valadim",
        "Mavabo",
        "Mavago"
    ],
    "wof:name":"Mavago",
    "wof:placetype":"locality"
},
  "geometry": {"coordinates":[36.18361,-12.48417],"type":"Point"}
}