{
  "type": "Feature",
  "properties": {
    "gn:admin1_code":"7",
    "gn:asciiname":"Chingomo",
    "gn:cc2":"MZ",
    "gn:country_code":"MZ",
    "gn:dem":1128,
    "gn:feature_class":"P",
    "gn:feature_code":"PPL",
    "gn:name":"Chingomo",
    "gn:population":0,
    "gn:timezone":"Africa/Maputo",
    "iso:country":"MZ",
    "name:und_x_variant":[
        "Chingoma",
        "Chingomo"
    ],
    "wof:name":"Chingomo",
    "wof:placetype":"locality"
},
  "geometry": {"coordinates":[35.09472,-12.67833],"type":"Point"}
}