{
  "type": "Feature",
  "properties": {
    "gn:admin1_code":"8",
    "gn:asciiname":"Aldeia Nachinanga",
    "gn:cc2":"MZ",
    "gn:country_code":"MZ",
    "gn:dem":248,
    "gn:feature_class":"P",
    "gn:feature_code":"PPL",
    "gn:name":"Aldeia Nachinanga",
    "gn:population":0,
    "gn:timezone":"Africa/Maputo",
    "iso:country":"MZ",
    "name:und_x_variant":[
        "Chinanga",
        "Aldeia Nachinanga"
    ],
    "wof:name":"Aldeia Nachinanga",
    "wof:placetype":"locality"
},
  "geometry": {"coordinates":[33.06278,-16.70194],"type":"Point"}
}