{
  "type": "Feature",
  "properties": {
    "gn:admin1_code":"3",
    "gn:asciiname":"Chibimbirre",
    "gn:country_code":"MZ",
    "gn:dem":72,
    "gn:feature_class":"P",
    "gn:feature_code":"PPL",
    "gn:name":"Chibimbirre",
    "gn:population":0,
    "gn:timezone":"Africa/Maputo",
    "iso:country":"MZ",
    "wof:name":"Chibimbirre",
    "wof:placetype":"locality"
},
  "geometry": {"coordinates":[34.34194,-24.71944],"type":"Point"}
}