{
  "type": "Feature",
  "properties": {
    "gn:admin1_code":"4",
    "gn:asciiname":"Malate",
    "gn:country_code":"MZ",
    "gn:dem":111,
    "gn:feature_class":"P",
    "gn:feature_code":"PPL",
    "gn:name":"Malate",
    "gn:population":0,
    "gn:timezone":"Africa/Maputo",
    "iso:country":"MZ",
    "wof:name":"Malate",
    "wof:placetype":"locality"
},
  "geometry": {"coordinates":[32.16667,-25.83056],"type":"Point"}
}