{
  "type": "Feature",
  "properties": {
    "gn:admin1_code":"7.0",
    "gn:asciiname":"Chefe Chiposse",
    "gn:cc2":"MZ",
    "gn:country_code":"MZ",
    "gn:dem":689,
    "gn:feature_class":"P",
    "gn:feature_code":"PPL",
    "gn:name":"Chefe Chiposse",
    "gn:population":0,
    "gn:timezone":"Africa/Maputo",
    "iso:country":"MZ",
    "name:und_x_variant":[
        "S\u00e9ra",
        "Chefe Chiposse"
    ],
    "wof:name":"Chefe Chiposse",
    "wof:placetype":"locality"
},
  "geometry": {"coordinates":[35.96639000000001,-15.025],"type":"Point"}
}