{
  "type": "Feature",
  "properties": {
    "gn:admin1_code":"9",
    "gn:asciiname":"Tome",
    "gn:country_code":"MZ",
    "gn:dem":160,
    "gn:feature_class":"P",
    "gn:feature_code":"PPL",
    "gn:name":"Tom\u00e9",
    "gn:population":0,
    "gn:timezone":"Africa/Maputo",
    "iso:country":"MZ",
    "name:ceb_x_preferred":[
        "Tome"
    ],
    "name:deu_x_preferred":[
        "Tome"
    ],
    "name:fra_x_preferred":[
        "Tome"
    ],
    "name:nld_x_preferred":[
        "Tome"
    ],
    "name:swe_x_preferred":[
        "Tome"
    ],
    "wof:name":"Tome",
    "wof:placetype":"locality"
},
  "geometry": {"coordinates":[37.08861,-16.75222],"type":"Point"}
}