{
  "type": "Feature",
  "properties": {
    "gn:admin1_code":"1",
    "gn:asciiname":"Nicoco",
    "gn:country_code":"MZ",
    "gn:dem":257,
    "gn:feature_class":"P",
    "gn:feature_code":"PPL",
    "gn:name":"Nicoco",
    "gn:population":0,
    "gn:timezone":"Africa/Maputo",
    "iso:country":"MZ",
    "wof:name":"Nicoco",
    "wof:placetype":"locality"
},
  "geometry": {"coordinates":[39.39944000000001,-12.05722],"type":"Point"}
}