{
  "type": "Feature",
  "properties": {
    "gn:admin1_code":"3",
    "gn:asciiname":"Chiuane",
    "gn:country_code":"MZ",
    "gn:dem":111,
    "gn:feature_class":"P",
    "gn:feature_code":"PPL",
    "gn:name":"Chiuane",
    "gn:population":0,
    "gn:timezone":"Africa/Maputo",
    "iso:country":"MZ",
    "wof:name":"Chiuane",
    "wof:placetype":"locality"
},
  "geometry": {"coordinates":[33.32056,-21.50722],"type":"Point"}
}