{
  "type": "Feature",
  "properties": {
    "gn:admin1_code":"7",
    "gn:asciiname":"Liponda",
    "gn:country_code":"MZ",
    "gn:dem":493,
    "gn:feature_class":"P",
    "gn:feature_code":"PPL",
    "gn:name":"Liponda",
    "gn:population":0,
    "gn:timezone":"Africa/Maputo",
    "iso:country":"MZ",
    "wof:name":"Liponda",
    "wof:placetype":"locality"
},
  "geometry": {"coordinates":[34.7575,-12.55694],"type":"Point"}
}