{
  "type": "Feature",
  "properties": {
    "gn:admin1_code":"5.0",
    "gn:asciiname":"Santa Fe",
    "gn:country_code":"MZ",
    "gn:dem":342,
    "gn:feature_class":"P",
    "gn:feature_code":"PPL",
    "gn:name":"Santa Fe",
    "gn:population":0,
    "gn:timezone":"Africa/Maputo",
    "iso:country":"MZ",
    "wof:name":"Santa Fe",
    "wof:placetype":"locality"
},
  "geometry": {"coordinates":[34.98944,-18.46722],"type":"Point"}
}