{
  "type": "Feature",
  "properties": {
    "gn:admin1_code":"6",
    "gn:asciiname":"Malico",
    "gn:country_code":"MZ",
    "gn:dem":644,
    "gn:feature_class":"P",
    "gn:feature_code":"PPL",
    "gn:name":"Malico",
    "gn:population":0,
    "gn:timezone":"Africa/Maputo",
    "iso:country":"MZ",
    "wof:name":"Malico",
    "wof:placetype":"locality"
},
  "geometry": {"coordinates":[38.30278,-15.10806],"type":"Point"}
}