{
  "type": "Feature",
  "properties": {
    "gn:admin1_code":"5",
    "gn:asciiname":"Nova Maceira",
    "gn:country_code":"MZ",
    "gn:dem":47,
    "gn:feature_class":"P",
    "gn:feature_code":"PPL",
    "gn:name":"Nova Maceira",
    "gn:population":0,
    "gn:timezone":"Africa/Maputo",
    "iso:country":"MZ",
    "wof:name":"Nova Maceira",
    "wof:placetype":"locality"
},
  "geometry": {"coordinates":[34.75278,-19.64528],"type":"Point"}
}