{
  "type": "Feature",
  "properties": {
    "gn:admin1_code":"6",
    "gn:asciiname":"Regulo Naueia",
    "gn:country_code":"MZ",
    "gn:dem":101,
    "gn:feature_class":"P",
    "gn:feature_code":"PPL",
    "gn:name":"R\u00e9gulo Naueia",
    "gn:population":0,
    "gn:timezone":"Africa/Maputo",
    "iso:country":"MZ",
    "wof:name":"Regulo Naueia",
    "wof:placetype":"locality"
},
  "geometry": {"coordinates":[39.76139000000001,-16.02361],"type":"Point"}
}