{
  "type": "Feature",
  "properties": {
    "gn:admin1_code":"8",
    "gn:asciiname":"Mitemangawa",
    "gn:country_code":"MZ",
    "gn:dem":204,
    "gn:feature_class":"P",
    "gn:feature_code":"PPL",
    "gn:name":"Mitemangawa",
    "gn:population":0,
    "gn:timezone":"Africa/Maputo",
    "iso:country":"MZ",
    "wof:name":"Mitemangawa",
    "wof:placetype":"locality"
},
  "geometry": {"coordinates":[33.18639,-16.61028],"type":"Point"}
}