{
  "type": "Feature",
  "properties": {
    "gn:admin1_code":"7",
    "gn:asciiname":"Cocola",
    "gn:country_code":"MZ",
    "gn:dem":565,
    "gn:feature_class":"P",
    "gn:feature_code":"PPL",
    "gn:name":"C\u00f3c\u00f3la",
    "gn:population":0,
    "gn:timezone":"Africa/Maputo",
    "iso:country":"MZ",
    "wof:name":"Cocola",
    "wof:placetype":"locality"
},
  "geometry": {"coordinates":[37.00111,-14.57056],"type":"Point"}
}