{
  "type": "Feature",
  "properties": {
    "gn:admin1_code":"10",
    "gn:asciiname":"Josefa",
    "gn:country_code":"MZ",
    "gn:dem":200,
    "gn:feature_class":"P",
    "gn:feature_code":"PPL",
    "gn:name":"Josefa",
    "gn:population":0,
    "gn:timezone":"Africa/Maputo",
    "iso:country":"MZ",
    "name:ita_x_preferred":[
        "Josefa"
    ],
    "name:spa_x_preferred":[
        "Josefa"
    ],
    "wof:name":"Josefa",
    "wof:placetype":"locality"
},
  "geometry": {"coordinates":[32.68056,-21.21639],"type":"Point"}
}