{
  "type": "Feature",
  "properties": {
    "gn:admin1_code":"7",
    "gn:asciiname":"Munlala",
    "gn:cc2":"MZ",
    "gn:country_code":"MZ",
    "gn:dem":649,
    "gn:feature_class":"P",
    "gn:feature_code":"PPL",
    "gn:name":"Munlala",
    "gn:population":0,
    "gn:timezone":"Africa/Maputo",
    "iso:country":"MZ",
    "name:und_x_variant":[
        "Munt\u00e3la",
        "Munlala"
    ],
    "wof:name":"Munlala",
    "wof:placetype":"locality"
},
  "geometry": {"coordinates":[37.66389,-13.28722],"type":"Point"}
}