{
  "type": "Feature",
  "properties": {
    "gn:admin1_code":"0",
    "gn:asciiname":"Jamal",
    "gn:country_code":"MZ",
    "gn:dem":87,
    "gn:feature_class":"P",
    "gn:feature_code":"PPL",
    "gn:name":"Jamal",
    "gn:population":0,
    "gn:timezone":"Africa/Maputo",
    "iso:country":"MZ",
    "wof:name":"Jamal",
    "wof:placetype":"locality"
},
  "geometry": {"coordinates":[40.66667,-14.61667],"type":"Point"}
}