{
  "type": "Feature",
  "properties": {
    "gn:admin1_code":"3.0",
    "gn:asciiname":"Met. Livre",
    "gn:country_code":"MZ",
    "gn:dem":90,
    "gn:feature_class":"P",
    "gn:feature_code":"PPL",
    "gn:name":"Met. Livre",
    "gn:population":0,
    "gn:timezone":"Africa/Maputo",
    "iso:country":"MZ",
    "wof:name":"Met. Livre",
    "wof:placetype":"locality"
},
  "geometry": {"coordinates":[35.1775,-24.23972],"type":"Point"}
}