{
  "type": "Feature",
  "properties": {
    "gn:admin1_code":"9",
    "gn:asciiname":"Ossufo",
    "gn:country_code":"MZ",
    "gn:dem":45,
    "gn:feature_class":"P",
    "gn:feature_code":"PPL",
    "gn:name":"Ossufo",
    "gn:population":0,
    "gn:timezone":"Africa/Maputo",
    "iso:country":"MZ",
    "wof:name":"Ossufo",
    "wof:placetype":"locality"
},
  "geometry": {"coordinates":[38.98417,-16.70667000000001],"type":"Point"}
}