{
  "type": "Feature",
  "properties": {
    "gn:admin1_code":"9",
    "gn:asciiname":"Chefe Namalumbe",
    "gn:country_code":"MZ",
    "gn:dem":684,
    "gn:feature_class":"P",
    "gn:feature_code":"PPL",
    "gn:name":"Chefe Namalumbe",
    "gn:population":0,
    "gn:timezone":"Africa/Maputo",
    "iso:country":"MZ",
    "wof:name":"Chefe Namalumbe",
    "wof:placetype":"locality"
},
  "geometry": {"coordinates":[36.01028,-15.58667],"type":"Point"}
}