{
  "type": "Feature",
  "properties": {
    "gn:admin1_code":"0",
    "gn:asciiname":"Cantoneiro",
    "gn:country_code":"MZ",
    "gn:dem":19,
    "gn:feature_class":"P",
    "gn:feature_code":"PPL",
    "gn:name":"Cantoneiro",
    "gn:population":0,
    "gn:timezone":"Africa/Maputo",
    "iso:country":"MZ",
    "wof:name":"Cantoneiro",
    "wof:placetype":"locality"
},
  "geometry": {"coordinates":[39.35,-16.48333],"type":"Point"}
}