{
  "type": "Feature",
  "properties": {
    "gn:admin1_code":"9",
    "gn:asciiname":"Mucopoa",
    "gn:country_code":"MZ",
    "gn:dem":722,
    "gn:feature_class":"P",
    "gn:feature_code":"PPL",
    "gn:name":"Mucopoa",
    "gn:population":0,
    "gn:timezone":"Africa/Maputo",
    "iso:country":"MZ",
    "wof:name":"Mucopoa",
    "wof:placetype":"locality"
},
  "geometry": {"coordinates":[37.20722,-15.07417],"type":"Point"}
}