{
  "type": "Feature",
  "properties": {
    "gn:admin1_code":"1",
    "gn:asciiname":"Nicole",
    "gn:country_code":"MZ",
    "gn:dem":580,
    "gn:feature_class":"P",
    "gn:feature_code":"PPL",
    "gn:name":"Nicole",
    "gn:population":0,
    "gn:timezone":"Africa/Maputo",
    "iso:country":"MZ",
    "wof:name":"Nicole",
    "wof:placetype":"locality"
},
  "geometry": {"coordinates":[38.57306,-13.44861],"type":"Point"}
}