{
  "type": "Feature",
  "properties": {
    "gn:admin1_code":"6.0",
    "gn:asciiname":"Adibo",
    "gn:country_code":"MZ",
    "gn:dem":38,
    "gn:feature_class":"P",
    "gn:feature_code":"PPL",
    "gn:name":"Adibo",
    "gn:population":0,
    "gn:timezone":"Africa/Maputo",
    "iso:country":"MZ",
    "wof:name":"Adibo",
    "wof:placetype":"locality"
},
  "geometry": {"coordinates":[39.5625,-16.42972],"type":"Point"}
}