{
  "type": "Feature",
  "properties": {
    "gn:admin1_code":"2",
    "gn:asciiname":"Chefe Mafele",
    "gn:cc2":"MZ",
    "gn:country_code":"MZ",
    "gn:dem":64,
    "gn:feature_class":"P",
    "gn:feature_code":"PPL",
    "gn:name":"Chefe Mafele",
    "gn:population":0,
    "gn:timezone":"Africa/Maputo",
    "iso:country":"MZ",
    "name:und_x_variant":[
        "Chibaganhane",
        "Chefe Mafele"
    ],
    "wof:name":"Chefe Mafele",
    "wof:placetype":"locality"
},
  "geometry": {"coordinates":[34.15778,-24.89333],"type":"Point"}
}