{
  "type": "Feature",
  "properties": {
    "gn:admin1_code":"2.0",
    "gn:asciiname":"Chicomelane",
    "gn:country_code":"MZ",
    "gn:dem":49,
    "gn:feature_class":"P",
    "gn:feature_code":"PPL",
    "gn:name":"Chicomelane",
    "gn:population":0,
    "gn:timezone":"Africa/Maputo",
    "iso:country":"MZ",
    "wof:name":"Chicomelane",
    "wof:placetype":"locality"
},
  "geometry": {"coordinates":[33.32917,-24.10306],"type":"Point"}
}