{
  "type": "Feature",
  "properties": {
    "gn:admin1_code":"6",
    "gn:asciiname":"Abudo",
    "gn:country_code":"MZ",
    "gn:dem":64,
    "gn:feature_class":"P",
    "gn:feature_code":"PPL",
    "gn:name":"Abudo",
    "gn:population":0,
    "gn:timezone":"Africa/Maputo",
    "iso:country":"MZ",
    "wof:name":"Abudo",
    "wof:placetype":"locality"
},
  "geometry": {"coordinates":[40.58194,-14.83833],"type":"Point"}
}