{
  "type": "Feature",
  "properties": {
    "gn:admin1_code":"7.0",
    "gn:asciiname":"Chefe Naissima",
    "gn:cc2":"MZ",
    "gn:country_code":"MZ",
    "gn:dem":666,
    "gn:feature_class":"P",
    "gn:feature_code":"PPL",
    "gn:name":"Chefe Naissima",
    "gn:population":0,
    "gn:timezone":"Africa/Maputo",
    "iso:country":"MZ",
    "name:und_x_variant":[
        "Sicima",
        "Chefe Naissima"
    ],
    "wof:name":"Chefe Naissima",
    "wof:placetype":"locality"
},
  "geometry": {"coordinates":[35.98528,-15.27917],"type":"Point"}
}