{
  "type": "Feature",
  "properties": {
    "gn:admin1_code":"3.0",
    "gn:asciiname":"G. Nhalicale",
    "gn:country_code":"MZ",
    "gn:dem":114,
    "gn:feature_class":"P",
    "gn:feature_code":"PPL",
    "gn:name":"G. Nhalicale",
    "gn:population":0,
    "gn:timezone":"Africa/Maputo",
    "iso:country":"MZ",
    "wof:name":"G. Nhalicale",
    "wof:placetype":"locality"
},
  "geometry": {"coordinates":[34.59444000000001,-24.74139],"type":"Point"}
}