{
  "type": "Feature",
  "properties": {
    "gn:admin1_code":"7.0",
    "gn:asciiname":"Selimo",
    "gn:country_code":"MZ",
    "gn:dem":463,
    "gn:feature_class":"P",
    "gn:feature_code":"PPL",
    "gn:name":"Selimo",
    "gn:population":0,
    "gn:timezone":"Africa/Maputo",
    "iso:country":"MZ",
    "wof:name":"Selimo",
    "wof:placetype":"locality"
},
  "geometry": {"coordinates":[37.82861,-12.92333],"type":"Point"}
}