{
  "type": "Feature",
  "properties": {
    "gn:admin1_code":"4.0",
    "gn:asciiname":"Sonte",
    "gn:country_code":"MZ",
    "gn:dem":106,
    "gn:feature_class":"P",
    "gn:feature_code":"PPL",
    "gn:name":"Sonte",
    "gn:population":0,
    "gn:timezone":"Africa/Maputo",
    "iso:country":"MZ",
    "wof:name":"Sonte",
    "wof:placetype":"locality"
},
  "geometry": {"coordinates":[32.34361,-25.77917],"type":"Point"}
}