{
  "type": "Feature",
  "properties": {
    "gn:admin1_code":"6",
    "gn:asciiname":"Anatule",
    "gn:country_code":"MZ",
    "gn:dem":635,
    "gn:feature_class":"P",
    "gn:feature_code":"PPL",
    "gn:name":"Anatule",
    "gn:population":0,
    "gn:timezone":"Africa/Maputo",
    "iso:country":"MZ",
    "wof:name":"Anatule",
    "wof:placetype":"locality"
},
  "geometry": {"coordinates":[38.25722,-15.17083],"type":"Point"}
}