{
  "type": "Feature",
  "properties": {
    "gn:admin1_code":"7",
    "gn:asciiname":"Djerace",
    "gn:country_code":"MZ",
    "gn:dem":524,
    "gn:feature_class":"P",
    "gn:feature_code":"PPL",
    "gn:name":"Djerace",
    "gn:population":0,
    "gn:timezone":"Africa/Maputo",
    "iso:country":"MZ",
    "wof:name":"Djerace",
    "wof:placetype":"locality"
},
  "geometry": {"coordinates":[37.28556,-14.1775],"type":"Point"}
}