{
  "type": "Feature",
  "properties": {
    "gn:admin1_code":"6",
    "gn:asciiname":"Milhana",
    "gn:country_code":"MZ",
    "gn:dem":331,
    "gn:feature_class":"P",
    "gn:feature_code":"PPL",
    "gn:name":"Milhana",
    "gn:population":0,
    "gn:timezone":"Africa/Maputo",
    "iso:country":"MZ",
    "wof:name":"Milhana",
    "wof:placetype":"locality"
},
  "geometry": {"coordinates":[39.18722,-14.15694],"type":"Point"}
}