{
  "type": "Feature",
  "properties": {
    "gn:admin1_code":"3",
    "gn:asciiname":"Balane",
    "gn:country_code":"MZ",
    "gn:dem":122,
    "gn:feature_class":"P",
    "gn:feature_code":"PPL",
    "gn:name":"Balane",
    "gn:population":0,
    "gn:timezone":"Africa/Maputo",
    "iso:country":"MZ",
    "wof:name":"Balane",
    "wof:placetype":"locality"
},
  "geometry": {"coordinates":[33.87778,-22.39556],"type":"Point"}
}