{
  "type": "Feature",
  "properties": {
    "gn:admin1_code":"10.0",
    "gn:asciiname":"Saize",
    "gn:country_code":"MZ",
    "gn:dem":538,
    "gn:feature_class":"P",
    "gn:feature_code":"PPL",
    "gn:name":"Saize",
    "gn:population":0,
    "gn:timezone":"Africa/Maputo",
    "iso:country":"MZ",
    "name:por_x_preferred":[
        "Saize"
    ],
    "wof:name":"Saize",
    "wof:placetype":"locality"
},
  "geometry": {"coordinates":[32.61861,-20.6925],"type":"Point"}
}