{
  "type": "Feature",
  "properties": {
    "gn:admin1_code":"2.0",
    "gn:asciiname":"Tovocane",
    "gn:country_code":"MZ",
    "gn:dem":81,
    "gn:feature_class":"P",
    "gn:feature_code":"PPL",
    "gn:name":"Tovocane",
    "gn:population":0,
    "gn:timezone":"Africa/Maputo",
    "iso:country":"MZ",
    "wof:name":"Tovocane",
    "wof:placetype":"locality"
},
  "geometry": {"coordinates":[32.47944,-23.72639],"type":"Point"}
}