{
  "type": "Feature",
  "properties": {
    "gn:admin1_code":"1.0",
    "gn:asciiname":"Vaossa",
    "gn:country_code":"MZ",
    "gn:dem":460,
    "gn:feature_class":"P",
    "gn:feature_code":"PPL",
    "gn:name":"Vaossa",
    "gn:population":0,
    "gn:timezone":"Africa/Maputo",
    "iso:country":"MZ",
    "wof:name":"Vaossa",
    "wof:placetype":"locality"
},
  "geometry": {"coordinates":[39.42944,-13.31444],"type":"Point"}
}