{
  "type": "Feature",
  "properties": {
    "gn:admin1_code":"0",
    "gn:asciiname":"Mudivela",
    "gn:country_code":"MZ",
    "gn:dem":508,
    "gn:feature_class":"P",
    "gn:feature_code":"PPL",
    "gn:name":"Mudivela",
    "gn:population":0,
    "gn:timezone":"Africa/Maputo",
    "iso:country":"MZ",
    "wof:name":"Mudivela",
    "wof:placetype":"locality"
},
  "geometry": {"coordinates":[31.96667,-25.86667000000001],"type":"Point"}
}