{
  "type": "Feature",
  "properties": {
    "gn:admin1_code":"9.0",
    "gn:asciiname":"Tatamula",
    "gn:country_code":"MZ",
    "gn:dem":641,
    "gn:feature_class":"P",
    "gn:feature_code":"PPL",
    "gn:name":"Tat\u00e2mula",
    "gn:population":0,
    "gn:timezone":"Africa/Maputo",
    "iso:country":"MZ",
    "wof:name":"Tatamula",
    "wof:placetype":"locality"
},
  "geometry": {"coordinates":[36.4175,-15.87806],"type":"Point"}
}