{
  "type": "Feature",
  "properties": {
    "gn:admin1_code":"1",
    "gn:asciiname":"Trepte",
    "gn:country_code":"MZ",
    "gn:dem":333,
    "gn:feature_class":"P",
    "gn:feature_code":"PPL",
    "gn:name":"Trepte",
    "gn:population":0,
    "gn:timezone":"Africa/Maputo",
    "iso:country":"MZ",
    "wof:name":"Trepte",
    "wof:placetype":"locality"
},
  "geometry": {"coordinates":[39.91611,-12.93806],"type":"Point"}
}