{
  "type": "Feature",
  "properties": {
    "gn:admin1_code":"2",
    "gn:asciiname":"Djoco",
    "gn:country_code":"MZ",
    "gn:dem":7,
    "gn:feature_class":"P",
    "gn:feature_code":"PPL",
    "gn:name":"Djoco",
    "gn:population":0,
    "gn:timezone":"Africa/Maputo",
    "iso:country":"MZ",
    "wof:name":"Djoco",
    "wof:placetype":"locality"
},
  "geometry": {"coordinates":[33.44611,-25.07389],"type":"Point"}
}