{
  "type": "Feature",
  "properties": {
    "gn:admin1_code":"7",
    "gn:asciiname":"Nicuo",
    "gn:cc2":"MZ",
    "gn:country_code":"MZ",
    "gn:dem":363,
    "gn:feature_class":"P",
    "gn:feature_code":"PPL",
    "gn:name":"Nicuo",
    "gn:population":0,
    "gn:timezone":"Africa/Maputo",
    "iso:country":"MZ",
    "name:und_x_variant":[
        "Nicua",
        "Nicuo"
    ],
    "wof:name":"Nicuo",
    "wof:placetype":"locality"
},
  "geometry": {"coordinates":[37.445,-12.6275],"type":"Point"}
}