{
  "type": "Feature",
  "properties": {
    "gn:admin1_code":"4.0",
    "gn:asciiname":"Tchozene",
    "gn:country_code":"MZ",
    "gn:dem":191,
    "gn:feature_class":"P",
    "gn:feature_code":"PPL",
    "gn:name":"Tchozene",
    "gn:population":0,
    "gn:timezone":"Africa/Maputo",
    "iso:country":"MZ",
    "wof:name":"Tchozene",
    "wof:placetype":"locality"
},
  "geometry": {"coordinates":[32.055,-25.40972],"type":"Point"}
}