{
  "type": "Feature",
  "properties": {
    "gn:admin1_code":"4.0",
    "gn:asciiname":"Zacue",
    "gn:country_code":"MZ",
    "gn:dem":153,
    "gn:feature_class":"P",
    "gn:feature_code":"PPL",
    "gn:name":"Zacu\u00e9",
    "gn:population":0,
    "gn:timezone":"Africa/Maputo",
    "iso:country":"MZ",
    "wof:name":"Zacue",
    "wof:placetype":"locality"
},
  "geometry": {"coordinates":[32.07,-24.44],"type":"Point"}
}