{
  "type": "Feature",
  "properties": {
    "gn:admin1_code":"9.0",
    "gn:asciiname":"Ossifo",
    "gn:country_code":"MZ",
    "gn:dem":72,
    "gn:feature_class":"P",
    "gn:feature_code":"PPL",
    "gn:name":"Ossifo",
    "gn:population":0,
    "gn:timezone":"Africa/Maputo",
    "iso:country":"MZ",
    "wof:name":"Ossifo",
    "wof:placetype":"locality"
},
  "geometry": {"coordinates":[38.39194000000001,-16.93139],"type":"Point"}
}