{
  "type": "Feature",
  "properties": {
    "gn:admin1_code":"8",
    "gn:asciiname":"Canguro",
    "gn:country_code":"MZ",
    "gn:dem":586,
    "gn:feature_class":"P",
    "gn:feature_code":"PPL",
    "gn:name":"Canguro",
    "gn:population":0,
    "gn:timezone":"Africa/Maputo",
    "iso:country":"MZ",
    "wof:name":"Canguro",
    "wof:placetype":"locality"
},
  "geometry": {"coordinates":[32.98,-14.81444],"type":"Point"}
}