{
  "type": "Feature",
  "properties": {
    "gn:admin1_code":"7",
    "gn:asciiname":"Machemba",
    "gn:country_code":"MZ",
    "gn:dem":856,
    "gn:feature_class":"P",
    "gn:feature_code":"PPL",
    "gn:name":"Machemba",
    "gn:population":0,
    "gn:timezone":"Africa/Maputo",
    "iso:country":"MZ",
    "wof:name":"Machemba",
    "wof:placetype":"locality"
},
  "geometry": {"coordinates":[35.78944,-13.22639],"type":"Point"}
}