{
  "type": "Feature",
  "properties": {
    "gn:admin1_code":"0.0",
    "gn:asciiname":"Tchifuxira",
    "gn:country_code":"MZ",
    "gn:dem":725,
    "gn:feature_class":"P",
    "gn:feature_code":"PPL",
    "gn:name":"Tchifuxira",
    "gn:population":0,
    "gn:timezone":"Africa/Maputo",
    "iso:country":"MZ",
    "wof:name":"Tchifuxira",
    "wof:placetype":"locality"
},
  "geometry": {"coordinates":[31.13333,-15.36667],"type":"Point"}
}