{
  "type": "Feature",
  "properties": {
    "gn:admin1_code":"5",
    "gn:asciiname":"Boeza",
    "gn:country_code":"MZ",
    "gn:dem":73,
    "gn:feature_class":"P",
    "gn:feature_code":"PPL",
    "gn:name":"Boeza",
    "gn:population":0,
    "gn:timezone":"Africa/Maputo",
    "iso:country":"MZ",
    "wof:name":"Boeza",
    "wof:placetype":"locality"
},
  "geometry": {"coordinates":[35.02833,-17.65889],"type":"Point"}
}