{
  "type": "Feature",
  "properties": {
    "gn:admin1_code":"3.0",
    "gn:asciiname":"Sabino",
    "gn:country_code":"MZ",
    "gn:dem":130,
    "gn:feature_class":"P",
    "gn:feature_code":"PPL",
    "gn:name":"Sabino",
    "gn:population":0,
    "gn:timezone":"Africa/Maputo",
    "iso:country":"MZ",
    "name:bpy_x_preferred":[
        "\u09b8\u09be\u09ac\u09bf\u09a8\u09cb"
    ],
    "name:ceb_x_preferred":[
        "Sabino"
    ],
    "name:epo_x_preferred":[
        "Sabino"
    ],
    "name:eus_x_preferred":[
        "Sabino"
    ],
    "name:fra_x_preferred":[
        "Sabino"
    ],
    "name:ita_x_preferred":[
        "Sabino"
    ],
    "name:kaz_x_preferred":[
        "\u0421\u0430\u0431\u0438\u043d\u0443"
    ],
    "name:mlg_x_preferred":[
        "Sabino"
    ],
    "name:nld_x_preferred":[
        "Sabino"
    ],
    "name:nor_x_preferred":[
        "Sabino"
    ],
    "name:pol_x_preferred":[
        "Sabino"
    ],
    "name:por_x_preferred":[
        "Sabino"
    ],
    "name:ron_x_preferred":[
        "Sabino"
    ],
    "name:rus_x_preferred":[
        "\u0421\u0430\u0431\u0438\u043d\u0443"
    ],
    "name:spa_x_preferred":[
        "Sabino"
    ],
    "name:vie_x_preferred":[
        "Sabino"
    ],
    "name:vol_x_preferred":[
        "Sabino"
    ],
    "name:war_x_preferred":[
        "Sabino"
    ],
    "name:zho_x_preferred":[
        "\u8428\u6bd4\u52aa"
    ],
    "wof:name":"Sabino",
    "wof:placetype":"locality"
},
  "geometry": {"coordinates":[34.37860999999999,-22.68806],"type":"Point"}
}