{
  "type": "Feature",
  "properties": {
    "gn:admin1_code":"3.0",
    "gn:asciiname":"Sabino",
    "gn:country_code":"MZ",
    "gn:dem":130,
    "gn:feature_class":"P",
    "gn:feature_code":"PPL",
    "gn:name":"Sabino",
    "gn:population":0,
    "gn:timezone":"Africa/Maputo",
    "iso:country":"MZ",
    "wof:name":"Sabino",
    "wof:placetype":"locality"
},
  "geometry": {"coordinates":[34.37860999999999,-22.68806],"type":"Point"}
}