{
  "type": "Feature",
  "properties": {
    "gn:admin1_code":"3",
    "gn:asciiname":"Chefe Mavolule",
    "gn:cc2":"MZ",
    "gn:country_code":"MZ",
    "gn:dem":53,
    "gn:feature_class":"P",
    "gn:feature_code":"PPL",
    "gn:name":"Chefe Mavolule",
    "gn:population":0,
    "gn:timezone":"Africa/Maputo",
    "iso:country":"MZ",
    "name:und_x_variant":[
        "Mavoulula",
        "Chefe Mavolule"
    ],
    "wof:name":"Chefe Mavolule",
    "wof:placetype":"locality"
},
  "geometry": {"coordinates":[34.4175,-24.66194],"type":"Point"}
}