{
  "type": "Feature",
  "properties": {
    "gn:admin1_code":"3",
    "gn:asciiname":"Ingomanhane",
    "gn:country_code":"MZ",
    "gn:dem":116,
    "gn:feature_class":"P",
    "gn:feature_code":"PPL",
    "gn:name":"Ingomanhane",
    "gn:population":0,
    "gn:timezone":"Africa/Maputo",
    "iso:country":"MZ",
    "wof:name":"Ingomanhane",
    "wof:placetype":"locality"
},
  "geometry": {"coordinates":[33.88556,-22.46056],"type":"Point"}
}