{
  "type": "Feature",
  "properties": {
    "gn:admin1_code":"6",
    "gn:asciiname":"Matanla",
    "gn:country_code":"MZ",
    "gn:dem":75,
    "gn:feature_class":"P",
    "gn:feature_code":"PPL",
    "gn:name":"Matanla",
    "gn:population":0,
    "gn:timezone":"Africa/Maputo",
    "iso:country":"MZ",
    "wof:name":"Matanla",
    "wof:placetype":"locality"
},
  "geometry": {"coordinates":[40.56917,-14.51583],"type":"Point"}
}