{
  "type": "Feature",
  "properties": {
    "gn:admin1_code":"1",
    "gn:asciiname":"Galudo",
    "gn:cc2":"MZ",
    "gn:country_code":"MZ",
    "gn:dem":40,
    "gn:feature_class":"P",
    "gn:feature_code":"PPL",
    "gn:name":"Galudo",
    "gn:population":0,
    "gn:timezone":"Africa/Maputo",
    "iso:country":"MZ",
    "name:und_x_variant":[
        "Goludo",
        "Galudo"
    ],
    "wof:name":"Galudo",
    "wof:placetype":"locality"
},
  "geometry": {"coordinates":[40.47694,-12.12583],"type":"Point"}
}