{
  "type": "Feature",
  "properties": {
    "gn:admin1_code":"6",
    "gn:asciiname":"Muepurra",
    "gn:country_code":"MZ",
    "gn:dem":303,
    "gn:feature_class":"P",
    "gn:feature_code":"PPL",
    "gn:name":"Muepurra",
    "gn:population":0,
    "gn:timezone":"Africa/Maputo",
    "iso:country":"MZ",
    "wof:name":"Muepurra",
    "wof:placetype":"locality"
},
  "geometry": {"coordinates":[39.51806,-14.88833],"type":"Point"}
}