{
  "type": "Feature",
  "properties": {
    "gn:admin1_code":"10",
    "gn:asciiname":"Galanguene",
    "gn:country_code":"MZ",
    "gn:dem":225,
    "gn:feature_class":"P",
    "gn:feature_code":"PPL",
    "gn:name":"Galanguene",
    "gn:population":0,
    "gn:timezone":"Africa/Maputo",
    "iso:country":"MZ",
    "wof:name":"Galanguene",
    "wof:placetype":"locality"
},
  "geometry": {"coordinates":[33.33472,-16.73028],"type":"Point"}
}