{
  "type": "Feature",
  "properties": {
    "gn:admin1_code":"4",
    "gn:asciiname":"Chulamate",
    "gn:cc2":"MZ",
    "gn:country_code":"MZ",
    "gn:dem":19,
    "gn:feature_class":"P",
    "gn:feature_code":"PPL",
    "gn:name":"Chulamate",
    "gn:population":0,
    "gn:timezone":"Africa/Maputo",
    "iso:country":"MZ",
    "name:und_x_variant":[
        "Chulamati",
        "Chulamate"
    ],
    "wof:name":"Chulamate",
    "wof:placetype":"locality"
},
  "geometry": {"coordinates":[32.79917,-25.1175],"type":"Point"}
}