{
  "type": "Feature",
  "properties": {
    "gn:admin1_code":"1",
    "gn:asciiname":"Changa",
    "gn:country_code":"MZ",
    "gn:dem":115,
    "gn:feature_class":"P",
    "gn:feature_code":"PPL",
    "gn:name":"Changa",
    "gn:population":0,
    "gn:timezone":"Africa/Maputo",
    "iso:country":"MZ",
    "name:ceb_x_preferred":[
        "Changa"
    ],
    "name:swe_x_preferred":[
        "Changa"
    ],
    "wof:name":"Changa",
    "wof:placetype":"locality"
},
  "geometry": {"coordinates":[40.52611,-13.08833],"type":"Point"}
}