{
  "type": "Feature",
  "properties": {
    "gn:admin1_code":"4",
    "gn:asciiname":"Nossa Senhora das Merces",
    "gn:country_code":"MZ",
    "gn:dem":40,
    "gn:feature_class":"P",
    "gn:feature_code":"PPL",
    "gn:name":"Nossa Senhora das Merces",
    "gn:population":0,
    "gn:timezone":"Africa/Maputo",
    "iso:country":"MZ",
    "wof:name":"Nossa Senhora das Merces",
    "wof:placetype":"locality"
},
  "geometry": {"coordinates":[32.54278,-26.00389],"type":"Point"}
}