{
  "type": "Feature",
  "properties": {
    "gn:admin1_code":"2",
    "gn:asciiname":"Armazem",
    "gn:cc2":"MZ",
    "gn:country_code":"MZ",
    "gn:dem":50,
    "gn:feature_class":"P",
    "gn:feature_code":"PPL",
    "gn:name":"Armaz\u00e9m",
    "gn:population":0,
    "gn:timezone":"Africa/Maputo",
    "iso:country":"MZ",
    "name:und_x_variant":[
        "Dinga",
        "Armaz\u00e9m"
    ],
    "wof:name":"Armazem",
    "wof:placetype":"locality"
},
  "geometry": {"coordinates":[33.27694,-24.14528],"type":"Point"}
}