{
  "type": "Feature",
  "properties": {
    "gn:admin1_code":"5",
    "gn:asciiname":"Gamenga",
    "gn:country_code":"MZ",
    "gn:dem":30,
    "gn:feature_class":"P",
    "gn:feature_code":"PPL",
    "gn:name":"Gamenga",
    "gn:population":0,
    "gn:timezone":"Africa/Maputo",
    "iso:country":"MZ",
    "wof:name":"Gamenga",
    "wof:placetype":"locality"
},
  "geometry": {"coordinates":[35.28111,-17.73361000000001],"type":"Point"}
}