{
  "type": "Feature",
  "properties": {
    "gn:admin1_code":"3.0",
    "gn:asciiname":"M. Nhabombe",
    "gn:country_code":"MZ",
    "gn:dem":64,
    "gn:feature_class":"P",
    "gn:feature_code":"PPL",
    "gn:name":"M. Nhabombe",
    "gn:population":0,
    "gn:timezone":"Africa/Maputo",
    "iso:country":"MZ",
    "wof:name":"M. Nhabombe",
    "wof:placetype":"locality"
},
  "geometry": {"coordinates":[34.91417,-24.42722],"type":"Point"}
}