{
  "type": "Feature",
  "properties": {
    "gn:admin1_code":"9",
    "gn:asciiname":"Camuana",
    "gn:country_code":"MZ",
    "gn:dem":68,
    "gn:feature_class":"P",
    "gn:feature_code":"PPL",
    "gn:name":"Camuana",
    "gn:population":0,
    "gn:timezone":"Africa/Maputo",
    "iso:country":"MZ",
    "wof:name":"Camuana",
    "wof:placetype":"locality"
},
  "geometry": {"coordinates":[38.32917,-16.88139],"type":"Point"}
}