{
  "type": "Feature",
  "properties": {
    "gn:admin1_code":"5",
    "gn:asciiname":"Nhanguaze",
    "gn:country_code":"MZ",
    "gn:dem":46,
    "gn:feature_class":"P",
    "gn:feature_code":"PPL",
    "gn:name":"Nhanguaze",
    "gn:population":0,
    "gn:timezone":"Africa/Maputo",
    "iso:country":"MZ",
    "wof:name":"Nhanguaze",
    "wof:placetype":"locality"
},
  "geometry": {"coordinates":[34.65806,-18.58583],"type":"Point"}
}