{
  "type": "Feature",
  "properties": {
    "gn:admin1_code":"2.0",
    "gn:asciiname":"Uiliamo",
    "gn:country_code":"MZ",
    "gn:dem":174,
    "gn:feature_class":"P",
    "gn:feature_code":"PPL",
    "gn:name":"Uiliamo",
    "gn:population":0,
    "gn:timezone":"Africa/Maputo",
    "iso:country":"MZ",
    "wof:name":"Uiliamo",
    "wof:placetype":"locality"
},
  "geometry": {"coordinates":[31.79278,-22.65917],"type":"Point"}
}