{
  "type": "Feature",
  "properties": {
    "gn:admin1_code":"1",
    "gn:asciiname":"Chefe Muela",
    "gn:country_code":"MZ",
    "gn:dem":265,
    "gn:feature_class":"P",
    "gn:feature_code":"PPL",
    "gn:name":"Chefe Muela",
    "gn:population":0,
    "gn:timezone":"Africa/Maputo",
    "iso:country":"MZ",
    "wof:name":"Chefe Muela",
    "wof:placetype":"locality"
},
  "geometry": {"coordinates":[39.85583,-13.45],"type":"Point"}
}