{
  "type": "Feature",
  "properties": {
    "gn:admin1_code":"7",
    "gn:asciiname":"Amalia",
    "gn:country_code":"MZ",
    "gn:dem":567,
    "gn:feature_class":"P",
    "gn:feature_code":"PPL",
    "gn:name":"Am\u00e1lia",
    "gn:population":0,
    "gn:timezone":"Africa/Maputo",
    "iso:country":"MZ",
    "wof:name":"Amalia",
    "wof:placetype":"locality"
},
  "geometry": {"coordinates":[36.77556,-14.44722],"type":"Point"}
}