{
  "type": "Feature",
  "properties": {
    "gn:admin1_code":"7",
    "gn:asciiname":"Amalia",
    "gn:country_code":"MZ",
    "gn:dem":567,
    "gn:feature_class":"P",
    "gn:feature_code":"PPL",
    "gn:name":"Am\u00e1lia",
    "gn:population":0,
    "gn:timezone":"Africa/Maputo",
    "iso:country":"MZ",
    "name:bre_x_preferred":[
        "Amalia"
    ],
    "name:fra_x_preferred":[
        "Amalia"
    ],
    "name:ita_x_preferred":[
        "Amalia"
    ],
    "name:jpn_x_preferred":[
        "\u30a2\u30de\u30ea\u30a2"
    ],
    "name:kor_x_preferred":[
        "\uc544\ub9d0\ub9ac\uc544"
    ],
    "name:nld_x_preferred":[
        "Amalia"
    ],
    "name:por_x_preferred":[
        "Am\u00e1lia"
    ],
    "name:ron_x_preferred":[
        "Amalia"
    ],
    "name:rus_x_preferred":[
        "\u0410\u043c\u0430\u043b\u0438\u044f"
    ],
    "name:spa_x_preferred":[
        "Amalia"
    ],
    "wof:name":"Amalia",
    "wof:placetype":"locality"
},
  "geometry": {"coordinates":[36.77556,-14.44722],"type":"Point"}
}