{
  "type": "Feature",
  "properties": {
    "gn:admin1_code":"8",
    "gn:asciiname":"Aldeia Saymica",
    "gn:country_code":"MZ",
    "gn:dem":428,
    "gn:feature_class":"P",
    "gn:feature_code":"PPL",
    "gn:name":"Aldeia Saymica",
    "gn:population":0,
    "gn:timezone":"Africa/Maputo",
    "iso:country":"MZ",
    "wof:name":"Aldeia Saymica",
    "wof:placetype":"locality"
},
  "geometry": {"coordinates":[33.44889000000001,-15.42139],"type":"Point"}
}