{
  "type": "Feature",
  "properties": {
    "gn:admin1_code":"2",
    "gn:asciiname":"Dane",
    "gn:country_code":"MZ",
    "gn:dem":65,
    "gn:feature_class":"P",
    "gn:feature_code":"PPL",
    "gn:name":"Dane",
    "gn:population":0,
    "gn:timezone":"Africa/Maputo",
    "iso:country":"MZ",
    "name:bos_x_preferred":[
        "Dane"
    ],
    "name:ceb_x_preferred":[
        "Dane"
    ],
    "name:ces_x_preferred":[
        "Dane"
    ],
    "name:deu_x_preferred":[
        "Dane"
    ],
    "name:fas_x_preferred":[
        "\u062f\u06cc\u0646"
    ],
    "name:fra_x_preferred":[
        "Dane"
    ],
    "name:hrv_x_preferred":[
        "Dane"
    ],
    "name:hun_x_preferred":[
        "Dane"
    ],
    "name:ita_x_preferred":[
        "Dane"
    ],
    "name:jpn_x_preferred":[
        "\u30c7\u30fc\u30f3"
    ],
    "name:nld_x_preferred":[
        "Dane"
    ],
    "name:nor_x_preferred":[
        "Dane"
    ],
    "name:pol_x_preferred":[
        "Dane"
    ],
    "name:por_x_preferred":[
        "Dane"
    ],
    "name:rus_x_preferred":[
        "\u0414\u0435\u0439\u043d"
    ],
    "name:sco_x_preferred":[
        "Dane"
    ],
    "name:slv_x_preferred":[
        "Dane"
    ],
    "name:srp_x_preferred":[
        "\u0414\u0435\u0458\u043d"
    ],
    "name:swe_x_preferred":[
        "Dane"
    ],
    "name:ukr_x_preferred":[
        "\u0414\u0435\u0439\u043d"
    ],
    "wof:name":"Dane",
    "wof:placetype":"locality"
},
  "geometry": {"coordinates":[33.23028,-25.015],"type":"Point"}
}