{
  "type": "Feature",
  "properties": {
    "gn:admin1_code":"3",
    "gn:asciiname":"Camacho",
    "gn:country_code":"MZ",
    "gn:dem":28,
    "gn:feature_class":"P",
    "gn:feature_code":"PPL",
    "gn:name":"Camacho",
    "gn:population":0,
    "gn:timezone":"Africa/Maputo",
    "iso:country":"MZ",
    "wof:name":"Camacho",
    "wof:placetype":"locality"
},
  "geometry": {"coordinates":[35.20417,-22.05972],"type":"Point"}
}