{
  "type": "Feature",
  "properties": {
    "gn:admin1_code":"6.0",
    "gn:asciiname":"Ranci",
    "gn:country_code":"MZ",
    "gn:dem":281,
    "gn:feature_class":"P",
    "gn:feature_code":"PPL",
    "gn:name":"Ranci",
    "gn:population":0,
    "gn:timezone":"Africa/Maputo",
    "iso:country":"MZ",
    "wof:name":"Ranci",
    "wof:placetype":"locality"
},
  "geometry": {"coordinates":[38.88528,-15.79861],"type":"Point"}
}