{
  "type": "Feature",
  "properties": {
    "gn:admin1_code":"8",
    "gn:asciiname":"Chissinga",
    "gn:country_code":"MZ",
    "gn:dem":441,
    "gn:feature_class":"P",
    "gn:feature_code":"PPL",
    "gn:name":"Chissinga",
    "gn:population":0,
    "gn:timezone":"Africa/Maputo",
    "iso:country":"MZ",
    "wof:name":"Chissinga",
    "wof:placetype":"locality"
},
  "geometry": {"coordinates":[32.10028,-15.4575],"type":"Point"}
}