{
  "type": "Feature",
  "properties": {
    "gn:admin1_code":"9",
    "gn:asciiname":"Nampilane",
    "gn:country_code":"MZ",
    "gn:dem":19,
    "gn:feature_class":"P",
    "gn:feature_code":"PPL",
    "gn:name":"Nampilane",
    "gn:population":0,
    "gn:timezone":"Africa/Maputo",
    "iso:country":"MZ",
    "wof:name":"Nampilane",
    "wof:placetype":"locality"
},
  "geometry": {"coordinates":[37.38306,-17.42389],"type":"Point"}
}