{
  "type": "Feature",
  "properties": {
    "gn:admin1_code":"10",
    "gn:asciiname":"Nhamatanga",
    "gn:country_code":"MZ",
    "gn:dem":505,
    "gn:feature_class":"P",
    "gn:feature_code":"PPL",
    "gn:name":"Nhamatanga",
    "gn:population":0,
    "gn:timezone":"Africa/Maputo",
    "iso:country":"MZ",
    "wof:name":"Nhamatanga",
    "wof:placetype":"locality"
},
  "geometry": {"coordinates":[33.73528,-19.10222000000001],"type":"Point"}
}