{
  "type": "Feature",
  "properties": {
    "gn:admin1_code":"6",
    "gn:asciiname":"Cero",
    "gn:country_code":"MZ",
    "gn:dem":439,
    "gn:feature_class":"P",
    "gn:feature_code":"PPL",
    "gn:name":"C\u00e9ro",
    "gn:population":0,
    "gn:timezone":"Africa/Maputo",
    "iso:country":"MZ",
    "wof:name":"Cero",
    "wof:placetype":"locality"
},
  "geometry": {"coordinates":[38.66194,-15.45028],"type":"Point"}
}