{
  "type": "Feature",
  "properties": {
    "gn:admin1_code":"9",
    "gn:asciiname":"Samori",
    "gn:cc2":"MZ",
    "gn:country_code":"MZ",
    "gn:dem":82,
    "gn:feature_class":"P",
    "gn:feature_code":"PPL",
    "gn:name":"Samori",
    "gn:population":0,
    "gn:timezone":"Africa/Maputo",
    "iso:country":"MZ",
    "name:und_x_variant":[
        "Chaubire",
        "Samori"
    ],
    "wof:name":"Samori",
    "wof:placetype":"locality"
},
  "geometry": {"coordinates":[38.07861,-17.00278],"type":"Point"}
}