{
  "type": "Feature",
  "properties": {
    "gn:admin1_code":"8",
    "gn:asciiname":"Dzunsa",
    "gn:country_code":"MZ",
    "gn:dem":909,
    "gn:feature_class":"P",
    "gn:feature_code":"PPL",
    "gn:name":"Dzunsa",
    "gn:population":0,
    "gn:timezone":"Africa/Maputo",
    "iso:country":"MZ",
    "wof:name":"Dzunsa",
    "wof:placetype":"locality"
},
  "geometry": {"coordinates":[32.71917,-15.67389],"type":"Point"}
}