{
  "type": "Feature",
  "properties": {
    "gn:admin1_code":"3.0",
    "gn:asciiname":"Chefe Massace",
    "gn:country_code":"MZ",
    "gn:dem":74,
    "gn:feature_class":"P",
    "gn:feature_code":"PPL",
    "gn:name":"Chefe Massace",
    "gn:population":0,
    "gn:timezone":"Africa/Maputo",
    "iso:country":"MZ",
    "wof:name":"Chefe Massace",
    "wof:placetype":"locality"
},
  "geometry": {"coordinates":[35.21972,-22.83361],"type":"Point"}
}