{
  "type": "Feature",
  "properties": {
    "gn:admin1_code":"7",
    "gn:asciiname":"Malavata",
    "gn:cc2":"MZ",
    "gn:country_code":"MZ",
    "gn:dem":621,
    "gn:feature_class":"P",
    "gn:feature_code":"PPL",
    "gn:name":"Malavata",
    "gn:population":0,
    "gn:timezone":"Africa/Maputo",
    "iso:country":"MZ",
    "name:und_x_variant":[
        "Malivata",
        "Malavata"
    ],
    "wof:name":"Malavata",
    "wof:placetype":"locality"
},
  "geometry": {"coordinates":[36.15833,-13.77889],"type":"Point"}
}