{
  "type": "Feature",
  "properties": {
    "gn:admin1_code":"1",
    "gn:asciiname":"Chimpue",
    "gn:country_code":"MZ",
    "gn:dem":493,
    "gn:feature_class":"P",
    "gn:feature_code":"PPL",
    "gn:name":"Chimpue",
    "gn:population":0,
    "gn:timezone":"Africa/Maputo",
    "iso:country":"MZ",
    "wof:name":"Chimpue",
    "wof:placetype":"locality"
},
  "geometry": {"coordinates":[39.13833,-13.41139],"type":"Point"}
}