{
  "type": "Feature",
  "properties": {
    "gn:admin1_code":"9",
    "gn:asciiname":"Muhoco",
    "gn:cc2":"MZ",
    "gn:country_code":"MZ",
    "gn:dem":303,
    "gn:feature_class":"P",
    "gn:feature_code":"PPL",
    "gn:name":"Muh\u00f3co",
    "gn:population":0,
    "gn:timezone":"Africa/Maputo",
    "iso:country":"MZ",
    "name:und_x_variant":[
        "Moh\u00f3co",
        "Muh\u00f3co"
    ],
    "wof:name":"Muhoco",
    "wof:placetype":"locality"
},
  "geometry": {"coordinates":[38.56694,-15.95056],"type":"Point"}
}