{
  "type": "Feature",
  "properties": {
    "gn:admin1_code":"6",
    "gn:asciiname":"Muacua",
    "gn:country_code":"MZ",
    "gn:dem":689,
    "gn:feature_class":"P",
    "gn:feature_code":"PPL",
    "gn:name":"Mu\u00e0cua",
    "gn:population":0,
    "gn:timezone":"Africa/Maputo",
    "iso:country":"MZ",
    "wof:name":"Muacua",
    "wof:placetype":"locality"
},
  "geometry": {"coordinates":[37.77333,-14.98417],"type":"Point"}
}