{
  "type": "Feature",
  "properties": {
    "gn:admin1_code":"2",
    "gn:asciiname":"Chefe Mateus",
    "gn:cc2":"MZ",
    "gn:country_code":"MZ",
    "gn:dem":82,
    "gn:feature_class":"P",
    "gn:feature_code":"PPL",
    "gn:name":"Chefe Mateus",
    "gn:population":0,
    "gn:timezone":"Africa/Maputo",
    "iso:country":"MZ",
    "name:und_x_variant":[
        "Mateus",
        "Chefe Mateus"
    ],
    "wof:name":"Chefe Mateus",
    "wof:placetype":"locality"
},
  "geometry": {"coordinates":[34.1475,-24.56472],"type":"Point"}
}