{
  "type": "Feature",
  "properties": {
    "gn:admin1_code":"3.0",
    "gn:asciiname":"Penicela",
    "gn:country_code":"MZ",
    "gn:dem":53,
    "gn:feature_class":"P",
    "gn:feature_code":"PPL",
    "gn:name":"Penicela",
    "gn:population":0,
    "gn:timezone":"Africa/Maputo",
    "iso:country":"MZ",
    "wof:name":"Penicela",
    "wof:placetype":"locality"
},
  "geometry": {"coordinates":[35.255,-22.43472],"type":"Point"}
}