{
  "type": "Feature",
  "properties": {
    "gn:admin1_code":"2.0",
    "gn:asciiname":"U. Chipondo",
    "gn:country_code":"MZ",
    "gn:dem":34,
    "gn:feature_class":"P",
    "gn:feature_code":"PPL",
    "gn:name":"U. Chipondo",
    "gn:population":0,
    "gn:timezone":"Africa/Maputo",
    "iso:country":"MZ",
    "wof:name":"U. Chipondo",
    "wof:placetype":"locality"
},
  "geometry": {"coordinates":[34.06361,-24.47667],"type":"Point"}
}