{
  "type": "Feature",
  "properties": {
    "gn:admin1_code":"9.0",
    "gn:asciiname":"Massoe",
    "gn:cc2":"MZ",
    "gn:country_code":"MZ",
    "gn:dem":282,
    "gn:feature_class":"P",
    "gn:feature_code":"PPL",
    "gn:name":"Massoe",
    "gn:population":0,
    "gn:timezone":"Africa/Maputo",
    "iso:country":"MZ",
    "name:und_x_variant":[
        "Sagu\u00e1ti",
        "Massoe"
    ],
    "wof:name":"Massoe",
    "wof:placetype":"locality"
},
  "geometry": {"coordinates":[37.73361,-16.36528],"type":"Point"}
}