{
  "type": "Feature",
  "properties": {
    "gn:admin1_code":"4.0",
    "gn:asciiname":"Ichique",
    "gn:cc2":"MZ",
    "gn:country_code":"MZ",
    "gn:dem":60,
    "gn:feature_class":"P",
    "gn:feature_code":"PPL",
    "gn:name":"Ichique",
    "gn:population":0,
    "gn:timezone":"Africa/Maputo",
    "iso:country":"MZ",
    "name:und_x_variant":[
        "Tchique",
        "Ichique"
    ],
    "wof:name":"Ichique",
    "wof:placetype":"locality"
},
  "geometry": {"coordinates":[32.26361,-25.33417],"type":"Point"}
}