{
  "type": "Feature",
  "properties": {
    "gn:admin1_code":"6",
    "gn:asciiname":"Reice",
    "gn:country_code":"MZ",
    "gn:dem":116,
    "gn:feature_class":"P",
    "gn:feature_code":"PPL",
    "gn:name":"Reice",
    "gn:population":0,
    "gn:timezone":"Africa/Maputo",
    "iso:country":"MZ",
    "wof:name":"Reice",
    "wof:placetype":"locality"
},
  "geometry": {"coordinates":[40.2225,-14.98528],"type":"Point"}
}