{
  "type": "Feature",
  "properties": {
    "gn:admin1_code":"2",
    "gn:asciiname":"Chefe Massochua",
    "gn:cc2":"MZ",
    "gn:country_code":"MZ",
    "gn:dem":11,
    "gn:feature_class":"P",
    "gn:feature_code":"PPL",
    "gn:name":"Chefe Massochua",
    "gn:population":0,
    "gn:timezone":"Africa/Maputo",
    "iso:country":"MZ",
    "name:und_x_variant":[
        "Lubanhane",
        "Chefe Massochua"
    ],
    "wof:name":"Chefe Massochua",
    "wof:placetype":"locality"
},
  "geometry": {"coordinates":[33.45639,-24.82833],"type":"Point"}
}