{
  "type": "Feature",
  "properties": {
    "gn:admin1_code":"3",
    "gn:asciiname":"Cobime",
    "gn:country_code":"MZ",
    "gn:dem":161,
    "gn:feature_class":"P",
    "gn:feature_code":"PPL",
    "gn:name":"Cobime",
    "gn:population":0,
    "gn:timezone":"Africa/Maputo",
    "iso:country":"MZ",
    "wof:name":"Cobime",
    "wof:placetype":"locality"
},
  "geometry": {"coordinates":[34.43778,-21.74972],"type":"Point"}
}