{
  "type": "Feature",
  "properties": {
    "gn:admin1_code":"6",
    "gn:asciiname":"Muiquita",
    "gn:country_code":"MZ",
    "gn:dem":538,
    "gn:feature_class":"P",
    "gn:feature_code":"PPL",
    "gn:name":"Mu\u00edquita",
    "gn:population":0,
    "gn:timezone":"Africa/Maputo",
    "iso:country":"MZ",
    "wof:name":"Muiquita",
    "wof:placetype":"locality"
},
  "geometry": {"coordinates":[38.15167,-14.79083],"type":"Point"}
}