{
  "type": "Feature",
  "properties": {
    "gn:admin1_code":"5",
    "gn:asciiname":"Gomondo",
    "gn:cc2":"MZ",
    "gn:country_code":"MZ",
    "gn:dem":159,
    "gn:feature_class":"P",
    "gn:feature_code":"PPL",
    "gn:name":"Gomondo",
    "gn:population":0,
    "gn:timezone":"Africa/Maputo",
    "iso:country":"MZ",
    "name:und_x_variant":[
        "Gomando",
        "Gomondo"
    ],
    "wof:name":"Gomondo",
    "wof:placetype":"locality"
},
  "geometry": {"coordinates":[33.84361,-20.59806],"type":"Point"}
}