{
  "type": "Feature",
  "properties": {
    "gn:admin1_code":"1",
    "gn:asciiname":"Magombo",
    "gn:country_code":"MZ",
    "gn:dem":139,
    "gn:feature_class":"P",
    "gn:feature_code":"PPL",
    "gn:name":"Magombo",
    "gn:population":0,
    "gn:timezone":"Africa/Maputo",
    "iso:country":"MZ",
    "wof:name":"Magombo",
    "wof:placetype":"locality"
},
  "geometry": {"coordinates":[39.99694,-11.09694],"type":"Point"}
}