{
  "type": "Feature",
  "properties": {
    "gn:admin1_code":"3.0",
    "gn:asciiname":"Sarmento",
    "gn:country_code":"MZ",
    "gn:dem":200,
    "gn:feature_class":"P",
    "gn:feature_code":"PPL",
    "gn:name":"Sarmento",
    "gn:population":0,
    "gn:timezone":"Africa/Maputo",
    "iso:country":"MZ",
    "wof:name":"Sarmento",
    "wof:placetype":"locality"
},
  "geometry": {"coordinates":[34.30083,-21.91111],"type":"Point"}
}