{
  "type": "Feature",
  "properties": {
    "gn:admin1_code":"8",
    "gn:asciiname":"Chauruca",
    "gn:country_code":"MZ",
    "gn:dem":1348,
    "gn:feature_class":"P",
    "gn:feature_code":"PPL",
    "gn:name":"Chauruca",
    "gn:population":0,
    "gn:timezone":"Africa/Maputo",
    "iso:country":"MZ",
    "wof:name":"Chauruca",
    "wof:placetype":"locality"
},
  "geometry": {"coordinates":[34.23639,-14.49722],"type":"Point"}
}