{
  "type": "Feature",
  "properties": {
    "gn:admin1_code":"6.0",
    "gn:asciiname":"Anigo",
    "gn:cc2":"MZ",
    "gn:country_code":"MZ",
    "gn:dem":107,
    "gn:feature_class":"P",
    "gn:feature_code":"PPL",
    "gn:name":"Anigo",
    "gn:population":0,
    "gn:timezone":"Africa/Maputo",
    "iso:country":"MZ",
    "name:und_x_variant":[
        "Uarrema",
        "Anigo"
    ],
    "wof:name":"Anigo",
    "wof:placetype":"locality"
},
  "geometry": {"coordinates":[39.485,-15.97722],"type":"Point"}
}