{
  "type": "Feature",
  "properties": {
    "gn:admin1_code":"8",
    "gn:asciiname":"Calissongole",
    "gn:country_code":"MZ",
    "gn:dem":1280,
    "gn:feature_class":"P",
    "gn:feature_code":"PPL",
    "gn:name":"Calissongole",
    "gn:population":0,
    "gn:timezone":"Africa/Maputo",
    "iso:country":"MZ",
    "wof:name":"Calissongole",
    "wof:placetype":"locality"
},
  "geometry": {"coordinates":[34.13139,-14.56056],"type":"Point"}
}