{
  "type": "Feature",
  "properties": {
    "gn:admin1_code":"3.0",
    "gn:asciiname":"R. Nhapossa",
    "gn:country_code":"MZ",
    "gn:dem":45,
    "gn:feature_class":"P",
    "gn:feature_code":"PPL",
    "gn:name":"R. Nhapossa",
    "gn:population":0,
    "gn:timezone":"Africa/Maputo",
    "iso:country":"MZ",
    "wof:name":"R. Nhapossa",
    "wof:placetype":"locality"
},
  "geometry": {"coordinates":[35.40861,-24.10361],"type":"Point"}
}