{
  "type": "Feature",
  "properties": {
    "gn:admin1_code":"6",
    "gn:asciiname":"Mira",
    "gn:country_code":"MZ",
    "gn:dem":148,
    "gn:feature_class":"P",
    "gn:feature_code":"PPL",
    "gn:name":"Mira",
    "gn:population":0,
    "gn:timezone":"Africa/Maputo",
    "iso:country":"MZ",
    "name:afr_x_preferred":[
        "Mira"
    ],
    "name:als_x_preferred":[
        "Mira"
    ],
    "name:ara_x_preferred":[
        "\u0645\u064a\u0631\u0627"
    ],
    "name:ast_x_preferred":[
        "Mira"
    ],
    "name:bel_x_preferred":[
        "\u041c\u0456\u0440\u0430"
    ],
    "name:bos_x_preferred":[
        "Omicron Ceti"
    ],
    "name:bul_x_preferred":[
        "\u041c\u0438\u0440\u0430"
    ],
    "name:cat_x_preferred":[
        "Mira"
    ],
    "name:ces_x_preferred":[
        "Mira"
    ],
    "name:ckb_x_preferred":[
        "\u0626\u06d5\u0633\u062a\u06ce\u0631\u06d5\u06cc \u0645\u06cc\u0631\u0627"
    ],
    "name:dan_x_preferred":[
        "Mira"
    ],
    "name:deu_x_preferred":[
        "Mira"
    ],
    "name:ell_x_preferred":[
        "\u039c\u03af\u03c1\u03b1"
    ],
    "name:epo_x_preferred":[
        "Omikron Baleno"
    ],
    "name:est_x_preferred":[
        "Mira"
    ],
    "name:fas_x_preferred":[
        "\u0634\u06af\u0641\u062a\u200c\u0627\u062e\u062a\u0631"
    ],
    "name:fin_x_preferred":[
        "Mira"
    ],
    "name:fra_x_preferred":[
        "Mira"
    ],
    "name:gle_x_preferred":[
        "Mira"
    ],
    "name:heb_x_preferred":[
        "\u05de\u05d9\u05e8\u05d4"
    ],
    "name:hun_x_preferred":[
        "Mira"
    ],
    "name:hye_x_preferred":[
        "\u0544\u056b\u0580\u0561"
    ],
    "name:ind_x_preferred":[
        "Mira"
    ],
    "name:ita_x_preferred":[
        "Mira"
    ],
    "name:jpn_x_preferred":[
        "\u30df\u30e9"
    ],
    "name:kat_x_preferred":[
        "\u10db\u10d8\u10e0\u10d0"
    ],
    "name:kor_x_preferred":[
        "\ubbf8\ub77c"
    ],
    "name:ltz_x_preferred":[
        "Mira"
    ],
    "name:mal_x_preferred":[
        "\u0d2e\u0d48\u0d31\u0d46"
    ],
    "name:nds_x_preferred":[
        "Mira"
    ],
    "name:nld_x_preferred":[
        "Mira"
    ],
    "name:nno_x_preferred":[
        "Mira"
    ],
    "name:nor_x_preferred":[
        "Mira"
    ],
    "name:pol_x_preferred":[
        "Mira Ceti"
    ],
    "name:por_x_preferred":[
        "Mira"
    ],
    "name:ron_x_preferred":[
        "Mira"
    ],
    "name:rus_x_preferred":[
        "\u041c\u0438\u0440\u0430"
    ],
    "name:sco_x_preferred":[
        "Mira"
    ],
    "name:slk_x_preferred":[
        "Mira"
    ],
    "name:slv_x_preferred":[
        "Mira"
    ],
    "name:spa_x_preferred":[
        "Mira"
    ],
    "name:srp_x_preferred":[
        "\u041c\u0438\u0440\u0430"
    ],
    "name:swe_x_preferred":[
        "Mira"
    ],
    "name:tha_x_preferred":[
        "\u0e14\u0e32\u0e27\u0e44\u0e21\u0e23\u0e32"
    ],
    "name:tur_x_preferred":[
        "Mira"
    ],
    "name:tur_x_variant":[
        "Mira Ceti"
    ],
    "name:ukr_x_preferred":[
        "\u041c\u0456\u0440\u0430"
    ],
    "name:urd_x_preferred":[
        "\u0645\u06cc\u0631\u0627"
    ],
    "name:uzb_x_preferred":[
        "Mira"
    ],
    "name:vie_x_preferred":[
        "S\u00f4ng Mira"
    ],
    "name:vie_x_variant":[
        "Mira"
    ],
    "name:war_x_preferred":[
        "Mira"
    ],
    "name:zho_x_preferred":[
        "\u520d\u85c1\u589e\u4e8c"
    ],
    "wof:name":"Mira",
    "wof:placetype":"locality"
},
  "geometry": {"coordinates":[39.57056,-15.89111],"type":"Point"}
}