{
  "type": "Feature",
  "properties": {
    "gn:admin1_code":"6",
    "gn:asciiname":"Rainha",
    "gn:country_code":"MZ",
    "gn:dem":113,
    "gn:feature_class":"P",
    "gn:feature_code":"PPL",
    "gn:name":"Rainha",
    "gn:population":0,
    "gn:timezone":"Africa/Maputo",
    "iso:country":"MZ",
    "wof:name":"Rainha",
    "wof:placetype":"locality"
},
  "geometry": {"coordinates":[39.69667000000001,-15.82472],"type":"Point"}
}