{
  "type": "Feature",
  "properties": {
    "gn:admin1_code":"0",
    "gn:asciiname":"Espoleta",
    "gn:country_code":"MZ",
    "gn:dem":827,
    "gn:feature_class":"P",
    "gn:feature_code":"PPL",
    "gn:name":"Espoleta",
    "gn:population":0,
    "gn:timezone":"Africa/Maputo",
    "iso:country":"MZ",
    "wof:name":"Espoleta",
    "wof:placetype":"locality"
},
  "geometry": {"coordinates":[31.43333,-15.05],"type":"Point"}
}