{
  "type": "Feature",
  "properties": {
    "gn:admin1_code":"0.0",
    "gn:asciiname":"Xivato",
    "gn:country_code":"MZ",
    "gn:dem":4,
    "gn:feature_class":"P",
    "gn:feature_code":"PPL",
    "gn:name":"Xivato",
    "gn:population":0,
    "gn:timezone":"Africa/Maputo",
    "iso:country":"MZ",
    "wof:name":"Xivato",
    "wof:placetype":"locality"
},
  "geometry": {"coordinates":[40.78333,-14.41667],"type":"Point"}
}