{
  "type": "Feature",
  "properties": {
    "gn:admin1_code":"1.0",
    "gn:asciiname":"Tupula",
    "gn:country_code":"MZ",
    "gn:dem":558,
    "gn:feature_class":"P",
    "gn:feature_code":"PPL",
    "gn:name":"Tupula",
    "gn:population":0,
    "gn:timezone":"Africa/Maputo",
    "iso:country":"MZ",
    "wof:name":"Tupula",
    "wof:placetype":"locality"
},
  "geometry": {"coordinates":[38.68972,-13.2825],"type":"Point"}
}