{
  "type": "Feature",
  "properties": {
    "gn:admin1_code":"9.0",
    "gn:asciiname":"Chefe Chicapa",
    "gn:cc2":"MZ",
    "gn:country_code":"MZ",
    "gn:dem":649,
    "gn:feature_class":"P",
    "gn:feature_code":"PPL",
    "gn:name":"Chefe Chicapa",
    "gn:population":0,
    "gn:timezone":"Africa/Maputo",
    "iso:country":"MZ",
    "name:und_x_variant":[
        "Pol\u00f3ssa",
        "Chefe Chicapa"
    ],
    "wof:name":"Chefe Chicapa",
    "wof:placetype":"locality"
},
  "geometry": {"coordinates":[35.90222,-15.60778],"type":"Point"}
}