{
  "type": "Feature",
  "properties": {
    "gn:admin1_code":"8.0",
    "gn:asciiname":"Umevere",
    "gn:country_code":"MZ",
    "gn:dem":908,
    "gn:feature_class":"P",
    "gn:feature_code":"PPL",
    "gn:name":"Umevere",
    "gn:population":0,
    "gn:timezone":"Africa/Maputo",
    "iso:country":"MZ",
    "wof:name":"Umevere",
    "wof:placetype":"locality"
},
  "geometry": {"coordinates":[31.63083,-15.21139],"type":"Point"}
}