{
  "type": "Feature",
  "properties": {
    "gn:admin1_code":"10.0",
    "gn:asciiname":"Vaissa",
    "gn:country_code":"MZ",
    "gn:dem":323,
    "gn:feature_class":"P",
    "gn:feature_code":"PPL",
    "gn:name":"Vaissa",
    "gn:population":0,
    "gn:timezone":"Africa/Maputo",
    "iso:country":"MZ",
    "name:por_x_preferred":[
        "Vaissa"
    ],
    "wof:name":"Vaissa",
    "wof:placetype":"locality"
},
  "geometry": {"coordinates":[32.81667,-20.81],"type":"Point"}
}