{
  "type": "Feature",
  "properties": {
    "gn:admin1_code":"9",
    "gn:asciiname":"Morrumbala",
    "gn:cc2":"MZ",
    "gn:country_code":"MZ",
    "gn:dem":412,
    "gn:feature_class":"P",
    "gn:feature_code":"PPL",
    "gn:name":"Morrumbala",
    "gn:population":0,
    "gn:timezone":"Africa/Maputo",
    "iso:country":"MZ",
    "name:und_x_variant":[
        "Marrumbala",
        "Murrumbala",
        "Morrumbala"
    ],
    "wof:name":"Morrumbala",
    "wof:placetype":"locality"
},
  "geometry": {"coordinates":[35.58417,-17.32694],"type":"Point"}
}