{
  "type": "Feature",
  "properties": {
    "gn:admin1_code":"1",
    "gn:asciiname":"Macule",
    "gn:country_code":"MZ",
    "gn:dem":439,
    "gn:feature_class":"P",
    "gn:feature_code":"PPL",
    "gn:name":"Macule",
    "gn:population":0,
    "gn:timezone":"Africa/Maputo",
    "iso:country":"MZ",
    "wof:name":"Macule",
    "wof:placetype":"locality"
},
  "geometry": {"coordinates":[38.77611,-13.73111],"type":"Point"}
}