{
  "type": "Feature",
  "properties": {
    "gn:admin1_code":"0",
    "gn:asciiname":"M'taia",
    "gn:country_code":"MZ",
    "gn:dem":1454,
    "gn:feature_class":"P",
    "gn:feature_code":"PPL",
    "gn:name":"M\u2019t\u00e1ia",
    "gn:population":0,
    "gn:timezone":"Africa/Maputo",
    "iso:country":"MZ",
    "wof:name":"M'taia",
    "wof:placetype":"locality"
},
  "geometry": {"coordinates":[34.46667,-14.53333],"type":"Point"}
}