{
  "type": "Feature",
  "properties": {
    "gn:admin1_code":"10",
    "gn:asciiname":"Gurupira",
    "gn:country_code":"MZ",
    "gn:dem":652,
    "gn:feature_class":"P",
    "gn:feature_code":"PPL",
    "gn:name":"Gurupira",
    "gn:population":0,
    "gn:timezone":"Africa/Maputo",
    "iso:country":"MZ",
    "wof:name":"Gurupira",
    "wof:placetype":"locality"
},
  "geometry": {"coordinates":[33.48694,-19.28611],"type":"Point"}
}