{
  "type": "Feature",
  "properties": {
    "gn:admin1_code":"6",
    "gn:asciiname":"Malepua",
    "gn:country_code":"MZ",
    "gn:dem":37,
    "gn:feature_class":"P",
    "gn:feature_code":"PPL",
    "gn:name":"Malepua",
    "gn:population":0,
    "gn:timezone":"Africa/Maputo",
    "iso:country":"MZ",
    "wof:name":"Malepua",
    "wof:placetype":"locality"
},
  "geometry": {"coordinates":[39.68556,-16.31778],"type":"Point"}
}