{
  "type": "Feature",
  "properties": {
    "gn:admin1_code":"5.0",
    "gn:asciiname":"Razao",
    "gn:country_code":"MZ",
    "gn:dem":238,
    "gn:feature_class":"P",
    "gn:feature_code":"PPL",
    "gn:name":"Raz\u00e3o",
    "gn:population":0,
    "gn:timezone":"Africa/Maputo",
    "iso:country":"MZ",
    "wof:name":"Razao",
    "wof:placetype":"locality"
},
  "geometry": {"coordinates":[33.65306,-20.45556],"type":"Point"}
}