{
  "type": "Feature",
  "properties": {
    "gn:admin1_code":"7",
    "gn:asciiname":"Chuonga",
    "gn:country_code":"MZ",
    "gn:dem":1207,
    "gn:feature_class":"P",
    "gn:feature_code":"PPL",
    "gn:name":"Chuonga",
    "gn:population":0,
    "gn:timezone":"Africa/Maputo",
    "iso:country":"MZ",
    "wof:name":"Chuonga",
    "wof:placetype":"locality"
},
  "geometry": {"coordinates":[35.3125,-13.91917],"type":"Point"}
}