{
  "type": "Feature",
  "properties": {
    "gn:admin1_code":"0.0",
    "gn:asciiname":"Ripaue",
    "gn:country_code":"MZ",
    "gn:dem":-9999,
    "gn:feature_class":"P",
    "gn:feature_code":"PPL",
    "gn:name":"Ripau\u00e9",
    "gn:population":0,
    "gn:timezone":"Africa/Maputo",
    "iso:country":"MZ",
    "wof:name":"Ripaue",
    "wof:placetype":"locality"
},
  "geometry": {"coordinates":[40.66667,-14.51667],"type":"Point"}
}