{
  "type": "Feature",
  "properties": {
    "gn:admin1_code":"8",
    "gn:asciiname":"Catedenguere",
    "gn:country_code":"MZ",
    "gn:dem":312,
    "gn:feature_class":"P",
    "gn:feature_code":"PPL",
    "gn:name":"Catedenguere",
    "gn:population":0,
    "gn:timezone":"Africa/Maputo",
    "iso:country":"MZ",
    "wof:name":"Catedenguere",
    "wof:placetype":"locality"
},
  "geometry": {"coordinates":[33.15639,-16.19861],"type":"Point"}
}