{
  "type": "Feature",
  "properties": {
    "gn:admin1_code":"3",
    "gn:asciiname":"Cumbe",
    "gn:country_code":"MZ",
    "gn:dem":124,
    "gn:feature_class":"P",
    "gn:feature_code":"PPL",
    "gn:name":"Cumbe",
    "gn:population":0,
    "gn:timezone":"Africa/Maputo",
    "iso:country":"MZ",
    "name:bpy_x_preferred":[
        "\u0995\u09c1\u09ae\u09ac\u09c7"
    ],
    "name:ceb_x_preferred":[
        "Cumbe"
    ],
    "name:epo_x_preferred":[
        "Cumbe"
    ],
    "name:eus_x_preferred":[
        "Cumbe"
    ],
    "name:fra_x_preferred":[
        "Cumbe"
    ],
    "name:ita_x_preferred":[
        "Cumbe"
    ],
    "name:nld_x_preferred":[
        "Cumbe"
    ],
    "name:nor_x_preferred":[
        "Cumbe"
    ],
    "name:por_x_preferred":[
        "Cumbe"
    ],
    "name:ron_x_preferred":[
        "Cumbe"
    ],
    "name:rus_x_preferred":[
        "\u041a\u0443\u043c\u0431\u0438"
    ],
    "name:spa_x_preferred":[
        "Cumbe"
    ],
    "name:swe_x_preferred":[
        "Cumbe"
    ],
    "name:vie_x_preferred":[
        "Cumbe"
    ],
    "name:vol_x_preferred":[
        "Cumbe"
    ],
    "name:war_x_preferred":[
        "Cumbe"
    ],
    "wof:name":"Cumbe",
    "wof:placetype":"locality"
},
  "geometry": {"coordinates":[34.13556,-22.51028],"type":"Point"}
}