{
  "type": "Feature",
  "properties": {
    "gn:admin1_code":"6",
    "gn:asciiname":"Muanuno",
    "gn:country_code":"MZ",
    "gn:dem":317,
    "gn:feature_class":"P",
    "gn:feature_code":"PPL",
    "gn:name":"Muanuno",
    "gn:population":0,
    "gn:timezone":"Africa/Maputo",
    "iso:country":"MZ",
    "wof:name":"Muanuno",
    "wof:placetype":"locality"
},
  "geometry": {"coordinates":[39.48694,-14.97694],"type":"Point"}
}