{
  "type": "Feature",
  "properties": {
    "gn:admin1_code":"5.0",
    "gn:asciiname":"Pedro",
    "gn:country_code":"MZ",
    "gn:dem":24,
    "gn:feature_class":"P",
    "gn:feature_code":"PPL",
    "gn:name":"Pedro",
    "gn:population":0,
    "gn:timezone":"Africa/Maputo",
    "iso:country":"MZ",
    "wof:name":"Pedro",
    "wof:placetype":"locality"
},
  "geometry": {"coordinates":[34.31778,-19.32167],"type":"Point"}
}