{
  "type": "Feature",
  "properties": {
    "gn:admin1_code":"8",
    "gn:asciiname":"Tamwariri",
    "gn:country_code":"MZ",
    "gn:dem":468,
    "gn:feature_class":"P",
    "gn:feature_code":"PPL",
    "gn:name":"Tamwariri",
    "gn:population":0,
    "gn:timezone":"Africa/Maputo",
    "iso:country":"MZ",
    "wof:name":"Tamwariri",
    "wof:placetype":"locality"
},
  "geometry": {"coordinates":[33.34417,-15.64833],"type":"Point"}
}