{
  "type": "Feature",
  "properties": {
    "gn:admin1_code":"8",
    "gn:asciiname":"Cachere",
    "gn:country_code":"MZ",
    "gn:dem":558,
    "gn:feature_class":"P",
    "gn:feature_code":"PPL",
    "gn:name":"Cachere",
    "gn:population":0,
    "gn:timezone":"Africa/Maputo",
    "iso:country":"MZ",
    "wof:name":"Cachere",
    "wof:placetype":"locality"
},
  "geometry": {"coordinates":[33.13306,-15.37278],"type":"Point"}
}