{
  "type": "Feature",
  "properties": {
    "gn:admin1_code":"3",
    "gn:asciiname":"Laicha",
    "gn:country_code":"MZ",
    "gn:dem":147,
    "gn:feature_class":"P",
    "gn:feature_code":"PPL",
    "gn:name":"Laicha",
    "gn:population":0,
    "gn:timezone":"Africa/Maputo",
    "iso:country":"MZ",
    "wof:name":"Laicha",
    "wof:placetype":"locality"
},
  "geometry": {"coordinates":[34.22056,-21.80889],"type":"Point"}
}