{
  "type": "Feature",
  "properties": {
    "gn:admin1_code":"6",
    "gn:asciiname":"Purrurua",
    "gn:country_code":"MZ",
    "gn:dem":155,
    "gn:feature_class":"P",
    "gn:feature_code":"PPL",
    "gn:name":"Purrurua",
    "gn:population":0,
    "gn:timezone":"Africa/Maputo",
    "iso:country":"MZ",
    "wof:name":"Purrurua",
    "wof:placetype":"locality"
},
  "geometry": {"coordinates":[40.37083,-14.22167],"type":"Point"}
}