{
  "type": "Feature",
  "properties": {
    "gn:admin1_code":"3.0",
    "gn:asciiname":"Muluguiane",
    "gn:country_code":"MZ",
    "gn:dem":127,
    "gn:feature_class":"P",
    "gn:feature_code":"PPL",
    "gn:name":"Muluguiane",
    "gn:population":0,
    "gn:timezone":"Africa/Maputo",
    "iso:country":"MZ",
    "wof:name":"Muluguiane",
    "wof:placetype":"locality"
},
  "geometry": {"coordinates":[34.85611,-22.6375],"type":"Point"}
}