{
  "type": "Feature",
  "properties": {
    "gn:admin1_code":"0",
    "gn:asciiname":"Medima",
    "gn:country_code":"MZ",
    "gn:dem":-9999,
    "gn:feature_class":"P",
    "gn:feature_code":"PPL",
    "gn:name":"Medima",
    "gn:population":0,
    "gn:timezone":"Africa/Maputo",
    "iso:country":"MZ",
    "wof:name":"Medima",
    "wof:placetype":"locality"
},
  "geometry": {"coordinates":[40.76667,-14.98333],"type":"Point"}
}