{
  "type": "Feature",
  "properties": {
    "gn:admin1_code":"8",
    "gn:asciiname":"Aldeia Chiputu",
    "gn:cc2":"MZ",
    "gn:country_code":"MZ",
    "gn:dem":454,
    "gn:feature_class":"P",
    "gn:feature_code":"PPL",
    "gn:name":"Aldeia Chiputu",
    "gn:population":0,
    "gn:timezone":"Africa/Maputo",
    "iso:country":"MZ",
    "name:und_x_variant":[
        "Chipute",
        "Mazendira",
        "Chip\u00fati",
        "Aldeia Chiputu"
    ],
    "wof:name":"Aldeia Chiputu",
    "wof:placetype":"locality"
},
  "geometry": {"coordinates":[32.64722,-15.43611],"type":"Point"}
}