{
  "type": "Feature",
  "properties": {
    "gn:admin1_code":"1",
    "gn:asciiname":"Chapa",
    "gn:country_code":"MZ",
    "gn:dem":367,
    "gn:feature_class":"P",
    "gn:feature_code":"PPL",
    "gn:name":"Chapa",
    "gn:population":0,
    "gn:timezone":"Africa/Maputo",
    "iso:country":"MZ",
    "wof:name":"Chapa",
    "wof:placetype":"locality"
},
  "geometry": {"coordinates":[39.30778,-11.88917],"type":"Point"}
}