{
  "type": "Feature",
  "properties": {
    "gn:admin1_code":"8",
    "gn:asciiname":"Cambui",
    "gn:country_code":"MZ",
    "gn:dem":323,
    "gn:feature_class":"P",
    "gn:feature_code":"PPL",
    "gn:name":"Cambui",
    "gn:population":0,
    "gn:timezone":"Africa/Maputo",
    "iso:country":"MZ",
    "wof:name":"Cambui",
    "wof:placetype":"locality"
},
  "geometry": {"coordinates":[33.79222,-15.6575],"type":"Point"}
}