{
  "type": "Feature",
  "properties": {
    "gn:admin1_code":"8.0",
    "gn:asciiname":"Unhamaula",
    "gn:country_code":"MZ",
    "gn:dem":484,
    "gn:feature_class":"P",
    "gn:feature_code":"PPL",
    "gn:name":"Unhama\u00fala",
    "gn:population":0,
    "gn:timezone":"Africa/Maputo",
    "iso:country":"MZ",
    "wof:name":"Unhamaula",
    "wof:placetype":"locality"
},
  "geometry": {"coordinates":[32.62611,-15.20306],"type":"Point"}
}