{
  "type": "Feature",
  "properties": {
    "gn:admin1_code":"2",
    "gn:asciiname":"Manjague",
    "gn:country_code":"MZ",
    "gn:dem":31,
    "gn:feature_class":"P",
    "gn:feature_code":"PPL",
    "gn:name":"Manjague",
    "gn:population":0,
    "gn:timezone":"Africa/Maputo",
    "iso:country":"MZ",
    "wof:name":"Manjague",
    "wof:placetype":"locality"
},
  "geometry": {"coordinates":[33.125,-24.77167],"type":"Point"}
}