{
  "type": "Feature",
  "properties": {
    "gn:admin1_code":"3",
    "gn:asciiname":"Fouquisse",
    "gn:country_code":"MZ",
    "gn:dem":87,
    "gn:feature_class":"P",
    "gn:feature_code":"PPL",
    "gn:name":"Fouquisse",
    "gn:population":0,
    "gn:timezone":"Africa/Maputo",
    "iso:country":"MZ",
    "wof:name":"Fouquisse",
    "wof:placetype":"locality"
},
  "geometry": {"coordinates":[34.19278,-21.34917],"type":"Point"}
}