{
  "type": "Feature",
  "properties": {
    "gn:admin1_code":"7",
    "gn:asciiname":"Bilange",
    "gn:country_code":"MZ",
    "gn:dem":576,
    "gn:feature_class":"P",
    "gn:feature_code":"PPL",
    "gn:name":"Bilange",
    "gn:population":0,
    "gn:timezone":"Africa/Maputo",
    "iso:country":"MZ",
    "wof:name":"Bilange",
    "wof:placetype":"locality"
},
  "geometry": {"coordinates":[34.92861,-13.39833],"type":"Point"}
}