{
  "type": "Feature",
  "properties": {
    "gn:admin1_code":"4",
    "gn:asciiname":"Velgueiro",
    "gn:country_code":"MZ",
    "gn:dem":25,
    "gn:feature_class":"P",
    "gn:feature_code":"PPL",
    "gn:name":"Velgueiro",
    "gn:population":0,
    "gn:timezone":"Africa/Maputo",
    "iso:country":"MZ",
    "wof:name":"Velgueiro",
    "wof:placetype":"locality"
},
  "geometry": {"coordinates":[32.285,-26.00278],"type":"Point"}
}