{
  "type": "Feature",
  "properties": {
    "gn:admin1_code":"4.0",
    "gn:asciiname":"Paipai",
    "gn:country_code":"MZ",
    "gn:dem":71,
    "gn:feature_class":"P",
    "gn:feature_code":"PPL",
    "gn:name":"Paipai",
    "gn:population":0,
    "gn:timezone":"Africa/Maputo",
    "iso:country":"MZ",
    "name:cat_x_preferred":[
        "Paipais"
    ],
    "name:hrv_x_preferred":[
        "Akwa\u2019ala Indijanci"
    ],
    "name:rus_x_preferred":[
        "\u041f\u0430\u0439\u043f\u0430\u0439"
    ],
    "name:spa_x_preferred":[
        "Paipai"
    ],
    "wof:name":"Paipai",
    "wof:placetype":"locality"
},
  "geometry": {"coordinates":[32.60528,-24.56861],"type":"Point"}
}