{
  "type": "Feature",
  "properties": {
    "gn:admin1_code":"1",
    "gn:asciiname":"Xitachi",
    "gn:country_code":"MZ",
    "gn:dem":39,
    "gn:feature_class":"P",
    "gn:feature_code":"PPL",
    "gn:name":"Xitachi",
    "gn:population":0,
    "gn:timezone":"Africa/Maputo",
    "iso:country":"MZ",
    "wof:name":"Xitachi",
    "wof:placetype":"locality"
},
  "geometry": {"coordinates":[40.08889,-11.82833],"type":"Point"}
}