{
  "type": "Feature",
  "properties": {
    "gn:admin1_code":"10.0",
    "gn:asciiname":"Rore",
    "gn:country_code":"MZ",
    "gn:dem":670,
    "gn:feature_class":"P",
    "gn:feature_code":"PPL",
    "gn:name":"Ror\u00ea",
    "gn:population":0,
    "gn:timezone":"Africa/Maputo",
    "iso:country":"MZ",
    "name:ceb_x_preferred":[
        "Rore"
    ],
    "name:nno_x_preferred":[
        "Rore"
    ],
    "name:nor_x_preferred":[
        "Rore"
    ],
    "wof:name":"Rore",
    "wof:placetype":"locality"
},
  "geometry": {"coordinates":[33.16861,-18.80111],"type":"Point"}
}