{
  "type": "Feature",
  "properties": {
    "gn:admin1_code":"3.0",
    "gn:asciiname":"Jeremias",
    "gn:country_code":"MZ",
    "gn:dem":148,
    "gn:feature_class":"P",
    "gn:feature_code":"PPL",
    "gn:name":"Jeremias",
    "gn:population":0,
    "gn:timezone":"Africa/Maputo",
    "iso:country":"MZ",
    "wof:name":"Jeremias",
    "wof:placetype":"locality"
},
  "geometry": {"coordinates":[34.92778,-23.53222],"type":"Point"}
}