{
  "type": "Feature",
  "properties": {
    "gn:admin1_code":"9",
    "gn:asciiname":"Berua",
    "gn:country_code":"MZ",
    "gn:dem":353,
    "gn:feature_class":"P",
    "gn:feature_code":"PPL",
    "gn:name":"Berua",
    "gn:population":0,
    "gn:timezone":"Africa/Maputo",
    "iso:country":"MZ",
    "wof:name":"Berua",
    "wof:placetype":"locality"
},
  "geometry": {"coordinates":[35.30389,-16.29639],"type":"Point"}
}