{
  "type": "Feature",
  "properties": {
    "gn:admin1_code":"4.0",
    "gn:asciiname":"Combate de Magul",
    "gn:cc2":"MZ",
    "gn:country_code":"MZ",
    "gn:dem":15,
    "gn:feature_class":"P",
    "gn:feature_code":"PPL",
    "gn:name":"Combate de Magul",
    "gn:population":0,
    "gn:timezone":"Africa/Maputo",
    "iso:country":"MZ",
    "name:und_x_variant":[
        "Magul",
        "Combate de Magul"
    ],
    "wof:name":"Combate de Magul",
    "wof:placetype":"locality"
},
  "geometry": {"coordinates":[32.99,-25.065],"type":"Point"}
}