{
  "type": "Feature",
  "properties": {
    "gn:admin1_code":"2",
    "gn:asciiname":"Bagia",
    "gn:cc2":"MZ",
    "gn:country_code":"MZ",
    "gn:dem":52,
    "gn:feature_class":"P",
    "gn:feature_code":"PPL",
    "gn:name":"Bagia",
    "gn:population":0,
    "gn:timezone":"Africa/Maputo",
    "iso:country":"MZ",
    "name:und_x_variant":[
        "Bai\u00e9",
        "Bagia"
    ],
    "wof:name":"Bagia",
    "wof:placetype":"locality"
},
  "geometry": {"coordinates":[33.49472,-23.85167],"type":"Point"}
}