{
  "type": "Feature",
  "properties": {
    "gn:admin1_code":"7",
    "gn:asciiname":"Chefe Chicuato",
    "gn:country_code":"MZ",
    "gn:dem":655,
    "gn:feature_class":"P",
    "gn:feature_code":"PPL",
    "gn:name":"Chefe Chicuato",
    "gn:population":0,
    "gn:timezone":"Africa/Maputo",
    "iso:country":"MZ",
    "wof:name":"Chefe Chicuato",
    "wof:placetype":"locality"
},
  "geometry": {"coordinates":[35.9025,-15.16861],"type":"Point"}
}