{
  "type": "Feature",
  "properties": {
    "gn:admin1_code":"10",
    "gn:asciiname":"Machananja",
    "gn:country_code":"MZ",
    "gn:dem":625,
    "gn:feature_class":"P",
    "gn:feature_code":"PPL",
    "gn:name":"Machananja",
    "gn:population":0,
    "gn:timezone":"Africa/Maputo",
    "iso:country":"MZ",
    "wof:name":"Machananja",
    "wof:placetype":"locality"
},
  "geometry": {"coordinates":[33.05056,-19.03167],"type":"Point"}
}