{
  "type": "Feature",
  "properties": {
    "gn:admin1_code":"0.0",
    "gn:asciiname":"Sefane",
    "gn:country_code":"MZ",
    "gn:dem":160,
    "gn:feature_class":"P",
    "gn:feature_code":"PPL",
    "gn:name":"Sefane",
    "gn:population":0,
    "gn:timezone":"Africa/Maputo",
    "iso:country":"MZ",
    "wof:name":"Sefane",
    "wof:placetype":"locality"
},
  "geometry": {"coordinates":[34.43333,-21.88333],"type":"Point"}
}