{
  "type": "Feature",
  "properties": {
    "gn:admin1_code":"6",
    "gn:asciiname":"Canroea",
    "gn:country_code":"MZ",
    "gn:dem":187,
    "gn:feature_class":"P",
    "gn:feature_code":"PPL",
    "gn:name":"Canr\u00f4ea",
    "gn:population":0,
    "gn:timezone":"Africa/Maputo",
    "iso:country":"MZ",
    "wof:name":"Canroea",
    "wof:placetype":"locality"
},
  "geometry": {"coordinates":[39.95028,-15.12306],"type":"Point"}
}