{
  "type": "Feature",
  "properties": {
    "gn:admin1_code":"3.0",
    "gn:asciiname":"Paulino",
    "gn:country_code":"MZ",
    "gn:dem":128,
    "gn:feature_class":"P",
    "gn:feature_code":"PPL",
    "gn:name":"Paulino",
    "gn:population":0,
    "gn:timezone":"Africa/Maputo",
    "iso:country":"MZ",
    "name:deu_x_preferred":[
        "Paulino"
    ],
    "wof:name":"Paulino",
    "wof:placetype":"locality"
},
  "geometry": {"coordinates":[34.76667,-22.42944],"type":"Point"}
}