{
  "type": "Feature",
  "properties": {
    "gn:admin1_code":"0",
    "gn:asciiname":"Muganquite",
    "gn:country_code":"MZ",
    "gn:dem":506,
    "gn:feature_class":"P",
    "gn:feature_code":"PPL",
    "gn:name":"Muganquite",
    "gn:population":0,
    "gn:timezone":"Africa/Maputo",
    "iso:country":"MZ",
    "wof:name":"Muganquite",
    "wof:placetype":"locality"
},
  "geometry": {"coordinates":[39.08333,-13.11667],"type":"Point"}
}