{
  "type": "Feature",
  "properties": {
    "gn:admin1_code":"1",
    "gn:asciiname":"Melola",
    "gn:country_code":"MZ",
    "gn:dem":605,
    "gn:feature_class":"P",
    "gn:feature_code":"PPL",
    "gn:name":"Melola",
    "gn:population":0,
    "gn:timezone":"Africa/Maputo",
    "iso:country":"MZ",
    "wof:name":"Melola",
    "wof:placetype":"locality"
},
  "geometry": {"coordinates":[38.49889,-13.41],"type":"Point"}
}