{
  "type": "Feature",
  "properties": {
    "gn:admin1_code":"10",
    "gn:asciiname":"Bobo",
    "gn:country_code":"MZ",
    "gn:dem":120,
    "gn:feature_class":"P",
    "gn:feature_code":"PPL",
    "gn:name":"B\u00f4bo",
    "gn:population":0,
    "gn:timezone":"Africa/Maputo",
    "iso:country":"MZ",
    "name:ceb_x_preferred":[
        "Bobo"
    ],
    "name:deu_x_preferred":[
        "Bobo"
    ],
    "name:fin_x_preferred":[
        "Bobo"
    ],
    "name:fra_x_preferred":[
        "Bobo"
    ],
    "name:hun_x_preferred":[
        "Bobo"
    ],
    "name:ita_x_preferred":[
        "Bobo"
    ],
    "name:nld_x_preferred":[
        "Bobo"
    ],
    "name:pol_x_preferred":[
        "Bobo"
    ],
    "name:por_x_preferred":[
        "Bobo"
    ],
    "name:rus_x_preferred":[
        "\u0411\u043e\u0431\u043e"
    ],
    "name:spa_x_preferred":[
        "Bobo"
    ],
    "name:zho_x_preferred":[
        "Bobo"
    ],
    "wof:name":"Bobo",
    "wof:placetype":"locality"
},
  "geometry": {"coordinates":[33.84944,-16.47528],"type":"Point"}
}