{
  "type": "Feature",
  "properties": {
    "gn:admin1_code":"10",
    "gn:asciiname":"Bobo",
    "gn:country_code":"MZ",
    "gn:dem":120,
    "gn:feature_class":"P",
    "gn:feature_code":"PPL",
    "gn:name":"B\u00f4bo",
    "gn:population":0,
    "gn:timezone":"Africa/Maputo",
    "iso:country":"MZ",
    "wof:name":"Bobo",
    "wof:placetype":"locality"
},
  "geometry": {"coordinates":[33.84944,-16.47528],"type":"Point"}
}