{
  "type": "Feature",
  "properties": {
    "gn:admin1_code":"0",
    "gn:asciiname":"Dick",
    "gn:country_code":"MZ",
    "gn:dem":182,
    "gn:feature_class":"P",
    "gn:feature_code":"PPL",
    "gn:name":"Dick",
    "gn:population":0,
    "gn:timezone":"Africa/Maputo",
    "iso:country":"MZ",
    "wof:name":"Dick",
    "wof:placetype":"locality"
},
  "geometry": {"coordinates":[33.51667,-19.78333],"type":"Point"}
}