{
  "type": "Feature",
  "properties": {
    "gn:admin1_code":"0",
    "gn:asciiname":"Dick",
    "gn:country_code":"MZ",
    "gn:dem":182,
    "gn:feature_class":"P",
    "gn:feature_code":"PPL",
    "gn:name":"Dick",
    "gn:population":0,
    "gn:timezone":"Africa/Maputo",
    "iso:country":"MZ",
    "name:ceb_x_preferred":[
        "Dick"
    ],
    "name:ces_x_preferred":[
        "Dick"
    ],
    "name:deu_x_preferred":[
        "Dick"
    ],
    "name:epo_x_preferred":[
        "Dick"
    ],
    "name:fin_x_preferred":[
        "Dick"
    ],
    "name:fra_x_preferred":[
        "Dick"
    ],
    "name:heb_x_preferred":[
        "\u05d3\u05d9\u05e7"
    ],
    "name:ita_x_preferred":[
        "Dick"
    ],
    "name:jpn_x_preferred":[
        "\u30c7\u30a3\u30c3\u30af"
    ],
    "name:nor_x_preferred":[
        "Dick"
    ],
    "name:pol_x_preferred":[
        "Dick"
    ],
    "name:rus_x_preferred":[
        "\u0414\u0438\u043a"
    ],
    "name:swe_x_preferred":[
        "Dick"
    ],
    "name:ukr_x_preferred":[
        "\u0414\u0456\u043a"
    ],
    "wof:name":"Dick",
    "wof:placetype":"locality"
},
  "geometry": {"coordinates":[33.51667,-19.78333],"type":"Point"}
}