{
  "type": "Feature",
  "properties": {
    "gn:admin1_code":"3.0",
    "gn:asciiname":"Mapetule Picanisso",
    "gn:country_code":"MZ",
    "gn:dem":49,
    "gn:feature_class":"P",
    "gn:feature_code":"PPL",
    "gn:name":"Mapetule Picanisso",
    "gn:population":0,
    "gn:timezone":"Africa/Maputo",
    "iso:country":"MZ",
    "wof:name":"Mapetule Picanisso",
    "wof:placetype":"locality"
},
  "geometry": {"coordinates":[34.37417,-24.39167],"type":"Point"}
}