{
  "type": "Feature",
  "properties": {
    "gn:admin1_code":"10",
    "gn:asciiname":"Mabalane",
    "gn:country_code":"MZ",
    "gn:dem":267,
    "gn:feature_class":"P",
    "gn:feature_code":"PPL",
    "gn:name":"Mabalane",
    "gn:population":0,
    "gn:timezone":"Africa/Maputo",
    "iso:country":"MZ",
    "name:por_x_preferred":[
        "Mabalane"
    ],
    "name:zho_x_preferred":[
        "\u99ac\u5df4\u62c9\u5167"
    ],
    "wof:name":"Mabalane",
    "wof:placetype":"locality"
},
  "geometry": {"coordinates":[33.40778,-20.77806],"type":"Point"}
}