{
  "type": "Feature",
  "properties": {
    "gn:admin1_code":"6",
    "gn:asciiname":"Lavie",
    "gn:country_code":"MZ",
    "gn:dem":173,
    "gn:feature_class":"P",
    "gn:feature_code":"PPL",
    "gn:name":"Lavie",
    "gn:population":0,
    "gn:timezone":"Africa/Maputo",
    "iso:country":"MZ",
    "name:ces_x_preferred":[
        "Lavie"
    ],
    "name:deu_x_preferred":[
        "Lavie"
    ],
    "wof:name":"Lavie",
    "wof:placetype":"locality"
},
  "geometry": {"coordinates":[40.11194,-15.15667],"type":"Point"}
}