{
  "type": "Feature",
  "properties": {
    "gn:admin1_code":"10",
    "gn:asciiname":"Canaco",
    "gn:country_code":"MZ",
    "gn:dem":176,
    "gn:feature_class":"P",
    "gn:feature_code":"PPL",
    "gn:name":"Canaco",
    "gn:population":0,
    "gn:timezone":"Africa/Maputo",
    "iso:country":"MZ",
    "wof:name":"Canaco",
    "wof:placetype":"locality"
},
  "geometry": {"coordinates":[33.31944,-20.08861],"type":"Point"}
}