{
  "type": "Feature",
  "properties": {
    "gn:admin1_code":"6",
    "gn:asciiname":"Mepaio",
    "gn:cc2":"MZ",
    "gn:country_code":"MZ",
    "gn:dem":281,
    "gn:feature_class":"P",
    "gn:feature_code":"PPL",
    "gn:name":"Mepaio",
    "gn:population":0,
    "gn:timezone":"Africa/Maputo",
    "iso:country":"MZ",
    "name:und_x_variant":[
        "Mapaio",
        "Mepaio"
    ],
    "wof:name":"Mepaio",
    "wof:placetype":"locality"
},
  "geometry": {"coordinates":[40.01389,-14.47667],"type":"Point"}
}