{
  "type": "Feature",
  "properties": {
    "gn:admin1_code":"3",
    "gn:asciiname":"Ecangala",
    "gn:country_code":"MZ",
    "gn:dem":158,
    "gn:feature_class":"P",
    "gn:feature_code":"PPL",
    "gn:name":"Ecangala",
    "gn:population":0,
    "gn:timezone":"Africa/Maputo",
    "iso:country":"MZ",
    "wof:name":"Ecangala",
    "wof:placetype":"locality"
},
  "geometry": {"coordinates":[34.13861,-21.82083],"type":"Point"}
}