{
  "type": "Feature",
  "properties": {
    "gn:admin1_code":"7",
    "gn:asciiname":"Buane",
    "gn:country_code":"MZ",
    "gn:dem":1046,
    "gn:feature_class":"P",
    "gn:feature_code":"PPL",
    "gn:name":"Buane",
    "gn:population":0,
    "gn:timezone":"Africa/Maputo",
    "iso:country":"MZ",
    "wof:name":"Buane",
    "wof:placetype":"locality"
},
  "geometry": {"coordinates":[35.42694,-13.80944],"type":"Point"}
}