{
  "type": "Feature",
  "properties": {
    "gn:admin1_code":"4",
    "gn:asciiname":"Machavite",
    "gn:country_code":"MZ",
    "gn:dem":36,
    "gn:feature_class":"P",
    "gn:feature_code":"PPL",
    "gn:name":"Machavite",
    "gn:population":0,
    "gn:timezone":"Africa/Maputo",
    "iso:country":"MZ",
    "wof:name":"Machavite",
    "wof:placetype":"locality"
},
  "geometry": {"coordinates":[32.30889000000001,-26.6525],"type":"Point"}
}