{
  "type": "Feature",
  "properties": {
    "gn:admin1_code":"2",
    "gn:asciiname":"Fucua",
    "gn:country_code":"MZ",
    "gn:dem":27,
    "gn:feature_class":"P",
    "gn:feature_code":"PPL",
    "gn:name":"Fucua",
    "gn:population":0,
    "gn:timezone":"Africa/Maputo",
    "iso:country":"MZ",
    "wof:name":"Fucua",
    "wof:placetype":"locality"
},
  "geometry": {"coordinates":[33.16194,-24.61167],"type":"Point"}
}