{
  "type": "Feature",
  "properties": {
    "gn:admin1_code":"7",
    "gn:asciiname":"Mutaparata",
    "gn:cc2":"MZ",
    "gn:country_code":"MZ",
    "gn:dem":518,
    "gn:feature_class":"P",
    "gn:feature_code":"PPL",
    "gn:name":"Mutaparata",
    "gn:population":0,
    "gn:timezone":"Africa/Maputo",
    "iso:country":"MZ",
    "name:und_x_variant":[
        "Mutaprata",
        "Mutaparata"
    ],
    "wof:name":"Mutaparata",
    "wof:placetype":"locality"
},
  "geometry": {"coordinates":[37.75806,-12.98167],"type":"Point"}
}