{
  "type": "Feature",
  "properties": {
    "gn:admin1_code":"6",
    "gn:asciiname":"Pedra",
    "gn:country_code":"MZ",
    "gn:dem":120,
    "gn:feature_class":"P",
    "gn:feature_code":"PPL",
    "gn:name":"Pedra",
    "gn:population":0,
    "gn:timezone":"Africa/Maputo",
    "iso:country":"MZ",
    "wof:name":"Pedra",
    "wof:placetype":"locality"
},
  "geometry": {"coordinates":[39.92278,-15.55639],"type":"Point"}
}