{
  "type": "Feature",
  "properties": {
    "gn:admin1_code":"8",
    "gn:asciiname":"Sungunudzi",
    "gn:country_code":"MZ",
    "gn:dem":847,
    "gn:feature_class":"P",
    "gn:feature_code":"PPL",
    "gn:name":"Sungunudzi",
    "gn:population":0,
    "gn:timezone":"Africa/Maputo",
    "iso:country":"MZ",
    "wof:name":"Sungunudzi",
    "wof:placetype":"locality"
},
  "geometry": {"coordinates":[31.88139,-15.19361],"type":"Point"}
}