{
  "type": "Feature",
  "properties": {
    "gn:admin1_code":"9",
    "gn:asciiname":"Cucurreia",
    "gn:country_code":"MZ",
    "gn:dem":613,
    "gn:feature_class":"P",
    "gn:feature_code":"PPL",
    "gn:name":"Cucurreia",
    "gn:population":0,
    "gn:timezone":"Africa/Maputo",
    "iso:country":"MZ",
    "wof:name":"Cucurreia",
    "wof:placetype":"locality"
},
  "geometry": {"coordinates":[37.73444,-15.47333],"type":"Point"}
}