{
  "type": "Feature",
  "properties": {
    "gn:admin1_code":"5",
    "gn:asciiname":"Jacopo",
    "gn:country_code":"MZ",
    "gn:dem":132,
    "gn:feature_class":"P",
    "gn:feature_code":"PPL",
    "gn:name":"Jacopo",
    "gn:population":0,
    "gn:timezone":"Africa/Maputo",
    "iso:country":"MZ",
    "name:deu_x_preferred":[
        "Jacopo"
    ],
    "name:ita_x_preferred":[
        "Jacopo"
    ],
    "name:jpn_x_preferred":[
        "\u30e4\u30b3\u30dd"
    ],
    "name:rus_x_preferred":[
        "\u042f\u043a\u043e\u043f\u043e"
    ],
    "wof:name":"Jacopo",
    "wof:placetype":"locality"
},
  "geometry": {"coordinates":[33.64028,-19.94472],"type":"Point"}
}