{
  "type": "Feature",
  "properties": {
    "gn:admin1_code":"6.0",
    "gn:asciiname":"Niuea",
    "gn:country_code":"MZ",
    "gn:dem":40,
    "gn:feature_class":"P",
    "gn:feature_code":"PPL",
    "gn:name":"Niuea",
    "gn:population":0,
    "gn:timezone":"Africa/Maputo",
    "iso:country":"MZ",
    "wof:name":"Niuea",
    "wof:placetype":"locality"
},
  "geometry": {"coordinates":[39.09778,-16.73389],"type":"Point"}
}