{
  "type": "Feature",
  "properties": {
    "gn:admin1_code":"2",
    "gn:asciiname":"Chibuco",
    "gn:country_code":"MZ",
    "gn:dem":41,
    "gn:feature_class":"P",
    "gn:feature_code":"PPL",
    "gn:name":"Chibuco",
    "gn:population":0,
    "gn:timezone":"Africa/Maputo",
    "iso:country":"MZ",
    "wof:name":"Chibuco",
    "wof:placetype":"locality"
},
  "geometry": {"coordinates":[32.99667,-24.98778],"type":"Point"}
}