{
  "type": "Feature",
  "properties": {
    "gn:admin1_code":"9.0",
    "gn:asciiname":"Chefe Vitua",
    "gn:country_code":"MZ",
    "gn:dem":296,
    "gn:feature_class":"P",
    "gn:feature_code":"PPL",
    "gn:name":"Chefe Vitua",
    "gn:population":0,
    "gn:timezone":"Africa/Maputo",
    "iso:country":"MZ",
    "wof:name":"Chefe Vitua",
    "wof:placetype":"locality"
},
  "geometry": {"coordinates":[37.09556,-16.37694],"type":"Point"}
}