{
  "type": "Feature",
  "properties": {
    "gn:admin1_code":"6",
    "gn:asciiname":"Metariua",
    "gn:country_code":"MZ",
    "gn:dem":640,
    "gn:feature_class":"P",
    "gn:feature_code":"PPL",
    "gn:name":"Metariua",
    "gn:population":0,
    "gn:timezone":"Africa/Maputo",
    "iso:country":"MZ",
    "wof:name":"Metariua",
    "wof:placetype":"locality"
},
  "geometry": {"coordinates":[38.03306,-15.13694],"type":"Point"}
}