{
  "type": "Feature",
  "properties": {
    "gn:admin1_code":"6.0",
    "gn:asciiname":"Tipene",
    "gn:country_code":"MZ",
    "gn:dem":204,
    "gn:feature_class":"P",
    "gn:feature_code":"PPL",
    "gn:name":"Tipene",
    "gn:population":0,
    "gn:timezone":"Africa/Maputo",
    "iso:country":"MZ",
    "wof:name":"Tipene",
    "wof:placetype":"locality"
},
  "geometry": {"coordinates":[40.30333,-14.58194],"type":"Point"}
}