{
  "type": "Feature",
  "properties": {
    "gn:admin1_code":"7",
    "gn:asciiname":"Aldeia Mbulise",
    "gn:country_code":"MZ",
    "gn:dem":900,
    "gn:feature_class":"P",
    "gn:feature_code":"PPL",
    "gn:name":"Aldeia Mbulise",
    "gn:population":0,
    "gn:timezone":"Africa/Maputo",
    "iso:country":"MZ",
    "wof:name":"Aldeia Mbulise",
    "wof:placetype":"locality"
},
  "geometry": {"coordinates":[35.44611,-12.52278],"type":"Point"}
}