{
  "type": "Feature",
  "properties": {
    "gn:admin1_code":"6",
    "gn:asciiname":"Murriaco",
    "gn:country_code":"MZ",
    "gn:dem":7,
    "gn:feature_class":"P",
    "gn:feature_code":"PPL",
    "gn:name":"Murriaco",
    "gn:population":0,
    "gn:timezone":"Africa/Maputo",
    "iso:country":"MZ",
    "wof:name":"Murriaco",
    "wof:placetype":"locality"
},
  "geometry": {"coordinates":[40.61833,-14.51417],"type":"Point"}
}