{
  "type": "Feature",
  "properties": {
    "gn:admin1_code":"7",
    "gn:asciiname":"Mepeima",
    "gn:cc2":"MZ",
    "gn:country_code":"MZ",
    "gn:dem":607,
    "gn:feature_class":"P",
    "gn:feature_code":"PPL",
    "gn:name":"Mepeima",
    "gn:population":0,
    "gn:timezone":"Africa/Maputo",
    "iso:country":"MZ",
    "name:und_x_variant":[
        "Mepejiua",
        "Mepeima"
    ],
    "wof:name":"Mepeima",
    "wof:placetype":"locality"
},
  "geometry": {"coordinates":[36.48083,-13.1625],"type":"Point"}
}