{
  "type": "Feature",
  "properties": {
    "gn:admin1_code":"8",
    "gn:asciiname":"Macundo",
    "gn:country_code":"MZ",
    "gn:dem":368,
    "gn:feature_class":"P",
    "gn:feature_code":"PPL",
    "gn:name":"Macundo",
    "gn:population":0,
    "gn:timezone":"Africa/Maputo",
    "iso:country":"MZ",
    "wof:name":"Macundo",
    "wof:placetype":"locality"
},
  "geometry": {"coordinates":[30.47222,-15.95056],"type":"Point"}
}