{
  "type": "Feature",
  "properties": {
    "gn:admin1_code":"1",
    "gn:asciiname":"Conamo",
    "gn:country_code":"MZ",
    "gn:dem":104,
    "gn:feature_class":"P",
    "gn:feature_code":"PPL",
    "gn:name":"Conamo",
    "gn:population":0,
    "gn:timezone":"Africa/Maputo",
    "iso:country":"MZ",
    "wof:name":"Conamo",
    "wof:placetype":"locality"
},
  "geometry": {"coordinates":[40.53444,-13.02194],"type":"Point"}
}