{
  "type": "Feature",
  "properties": {
    "gn:admin1_code":"3.0",
    "gn:asciiname":"Julia",
    "gn:country_code":"MZ",
    "gn:dem":71,
    "gn:feature_class":"P",
    "gn:feature_code":"PPL",
    "gn:name":"J\u00falia",
    "gn:population":0,
    "gn:timezone":"Africa/Maputo",
    "iso:country":"MZ",
    "name:deu_x_preferred":[
        "Julia"
    ],
    "name:est_x_preferred":[
        "Julia"
    ],
    "name:fin_x_preferred":[
        "Julia"
    ],
    "name:lat_x_preferred":[
        "Julia"
    ],
    "name:nld_x_preferred":[
        "Julia"
    ],
    "name:nor_x_preferred":[
        "Julia"
    ],
    "name:pol_x_preferred":[
        "Julia"
    ],
    "name:slv_x_preferred":[
        "Julia"
    ],
    "name:spa_x_preferred":[
        "Julia"
    ],
    "name:swe_x_preferred":[
        "Julia"
    ],
    "wof:name":"Julia",
    "wof:placetype":"locality"
},
  "geometry": {"coordinates":[35.31333,-23.16944],"type":"Point"}
}