{
  "type": "Feature",
  "properties": {
    "gn:admin1_code":"0",
    "gn:asciiname":"Mecararandengo",
    "gn:country_code":"MZ",
    "gn:dem":666,
    "gn:feature_class":"P",
    "gn:feature_code":"PPL",
    "gn:name":"Mecararandengo",
    "gn:population":0,
    "gn:timezone":"Africa/Maputo",
    "iso:country":"MZ",
    "wof:name":"Mecararandengo",
    "wof:placetype":"locality"
},
  "geometry": {"coordinates":[32.88333,-19.18333],"type":"Point"}
}