{
  "type": "Feature",
  "properties": {
    "gn:admin1_code":"6",
    "gn:asciiname":"Ropane",
    "gn:country_code":"MZ",
    "gn:dem":385,
    "gn:feature_class":"P",
    "gn:feature_code":"PPL",
    "gn:name":"Ropane",
    "gn:population":0,
    "gn:timezone":"Africa/Maputo",
    "iso:country":"MZ",
    "wof:name":"Ropane",
    "wof:placetype":"locality"
},
  "geometry": {"coordinates":[39.76139000000001,-14.56472],"type":"Point"}
}