{
  "type": "Feature",
  "properties": {
    "gn:admin1_code":"1",
    "gn:asciiname":"Buanato",
    "gn:country_code":"MZ",
    "gn:dem":508,
    "gn:feature_class":"P",
    "gn:feature_code":"PPL",
    "gn:name":"Buanato",
    "gn:population":0,
    "gn:timezone":"Africa/Maputo",
    "iso:country":"MZ",
    "wof:name":"Buanato",
    "wof:placetype":"locality"
},
  "geometry": {"coordinates":[38.96806,-13.15639],"type":"Point"}
}