{
  "type": "Feature",
  "properties": {
    "gn:admin1_code":"6",
    "gn:asciiname":"Napuete",
    "gn:country_code":"MZ",
    "gn:dem":343,
    "gn:feature_class":"P",
    "gn:feature_code":"PPL",
    "gn:name":"Napuete",
    "gn:population":0,
    "gn:timezone":"Africa/Maputo",
    "iso:country":"MZ",
    "wof:name":"Napuete",
    "wof:placetype":"locality"
},
  "geometry": {"coordinates":[39.93917,-13.76861],"type":"Point"}
}