{
  "type": "Feature",
  "properties": {
    "gn:admin1_code":"2",
    "gn:asciiname":"Congoto",
    "gn:country_code":"MZ",
    "gn:dem":59,
    "gn:feature_class":"P",
    "gn:feature_code":"PPL",
    "gn:name":"Congoto",
    "gn:population":0,
    "gn:timezone":"Africa/Maputo",
    "iso:country":"MZ",
    "wof:name":"Congoto",
    "wof:placetype":"locality"
},
  "geometry": {"coordinates":[33.38833,-24.91972],"type":"Point"}
}