{
  "type": "Feature",
  "properties": {
    "gn:admin1_code":"3.0",
    "gn:asciiname":"Ernesto",
    "gn:country_code":"MZ",
    "gn:dem":120,
    "gn:feature_class":"P",
    "gn:feature_code":"PPL",
    "gn:name":"Ernesto",
    "gn:population":0,
    "gn:timezone":"Africa/Maputo",
    "iso:country":"MZ",
    "name:bre_x_preferred":[
        "Ernesto"
    ],
    "name:deu_x_preferred":[
        "Ernesto"
    ],
    "name:fra_x_preferred":[
        "Ernesto"
    ],
    "name:ita_x_preferred":[
        "Ernesto"
    ],
    "name:spa_x_preferred":[
        "Ernesto"
    ],
    "wof:name":"Ernesto",
    "wof:placetype":"locality"
},
  "geometry": {"coordinates":[34.58667,-23.11722],"type":"Point"}
}