{
  "type": "Feature",
  "properties": {
    "gn:admin1_code":"9",
    "gn:asciiname":"Carpinteiro",
    "gn:country_code":"MZ",
    "gn:dem":326,
    "gn:feature_class":"P",
    "gn:feature_code":"PPL",
    "gn:name":"Carpinteiro",
    "gn:population":0,
    "gn:timezone":"Africa/Maputo",
    "iso:country":"MZ",
    "wof:name":"Carpinteiro",
    "wof:placetype":"locality"
},
  "geometry": {"coordinates":[38.085,-16.05583],"type":"Point"}
}