{
  "type": "Feature",
  "properties": {
    "gn:admin1_code":"10",
    "gn:asciiname":"Muiose",
    "gn:country_code":"MZ",
    "gn:dem":141,
    "gn:feature_class":"P",
    "gn:feature_code":"PPL",
    "gn:name":"Muiose",
    "gn:population":0,
    "gn:timezone":"Africa/Maputo",
    "iso:country":"MZ",
    "wof:name":"Muiose",
    "wof:placetype":"locality"
},
  "geometry": {"coordinates":[33.26806,-20.33833],"type":"Point"}
}