{
  "type": "Feature",
  "properties": {
    "gn:admin1_code":"4.0",
    "gn:asciiname":"Seandie",
    "gn:cc2":"MZ",
    "gn:country_code":"MZ",
    "gn:dem":47,
    "gn:feature_class":"P",
    "gn:feature_code":"PPL",
    "gn:name":"Seandie",
    "gn:population":0,
    "gn:timezone":"Africa/Maputo",
    "iso:country":"MZ",
    "name:und_x_variant":[
        "Scandie",
        "Seandie"
    ],
    "wof:name":"Seandie",
    "wof:placetype":"locality"
},
  "geometry": {"coordinates":[32.19806,-26.12917],"type":"Point"}
}