{
  "type": "Feature",
  "properties": {
    "gn:admin1_code":"3.0",
    "gn:asciiname":"Capataz",
    "gn:country_code":"MZ",
    "gn:dem":84,
    "gn:feature_class":"P",
    "gn:feature_code":"PPL",
    "gn:name":"Capataz",
    "gn:population":0,
    "gn:timezone":"Africa/Maputo",
    "iso:country":"MZ",
    "wof:name":"Capataz",
    "wof:placetype":"locality"
},
  "geometry": {"coordinates":[35.15806,-22.76667],"type":"Point"}
}