{
  "type": "Feature",
  "properties": {
    "gn:admin1_code":"2.0",
    "gn:asciiname":"Serracao Velha",
    "gn:country_code":"MZ",
    "gn:dem":80,
    "gn:feature_class":"P",
    "gn:feature_code":"PPL",
    "gn:name":"Serra\u00e7\u00e3o Velha",
    "gn:population":0,
    "gn:timezone":"Africa/Maputo",
    "iso:country":"MZ",
    "wof:name":"Serracao Velha",
    "wof:placetype":"locality"
},
  "geometry": {"coordinates":[33.06861,-23.53722],"type":"Point"}
}