{
  "type": "Feature",
  "properties": {
    "gn:admin1_code":"3",
    "gn:asciiname":"Baula",
    "gn:country_code":"MZ",
    "gn:dem":184,
    "gn:feature_class":"P",
    "gn:feature_code":"PPL",
    "gn:name":"Baula",
    "gn:population":0,
    "gn:timezone":"Africa/Maputo",
    "iso:country":"MZ",
    "name:ceb_x_preferred":[
        "Baula"
    ],
    "name:deu_x_preferred":[
        "Baula"
    ],
    "name:epo_x_preferred":[
        "Baula"
    ],
    "name:isl_x_preferred":[
        "Baula"
    ],
    "name:kor_x_preferred":[
        "\ubd48\uc77c\ub77c \uc0b0"
    ],
    "name:nld_x_preferred":[
        "Baula"
    ],
    "name:nno_x_preferred":[
        "Baula"
    ],
    "name:nor_x_preferred":[
        "Baula"
    ],
    "name:pnb_x_preferred":[
        "\u0628\u0648\u0644\u0627"
    ],
    "name:pol_x_preferred":[
        "Baula"
    ],
    "name:rus_x_preferred":[
        "\u0411\u0451\u0439\u043b\u0430"
    ],
    "name:swe_x_preferred":[
        "Baula"
    ],
    "wof:name":"Baula",
    "wof:placetype":"locality"
},
  "geometry": {"coordinates":[34.20194,-21.98389],"type":"Point"}
}