{
  "type": "Feature",
  "properties": {
    "gn:admin1_code":"7",
    "gn:asciiname":"Mepua",
    "gn:cc2":"MZ",
    "gn:country_code":"MZ",
    "gn:dem":657,
    "gn:feature_class":"P",
    "gn:feature_code":"PPL",
    "gn:name":"Mepua",
    "gn:population":0,
    "gn:timezone":"Africa/Maputo",
    "iso:country":"MZ",
    "name:und_x_variant":[
        "Mepuaa",
        "Mepua"
    ],
    "wof:name":"Mepua",
    "wof:placetype":"locality"
},
  "geometry": {"coordinates":[36.60556,-13.43667],"type":"Point"}
}