{
  "type": "Feature",
  "properties": {
    "gn:admin1_code":"8",
    "gn:asciiname":"Muze",
    "gn:country_code":"MZ",
    "gn:dem":873,
    "gn:feature_class":"P",
    "gn:feature_code":"PPL",
    "gn:name":"Muze",
    "gn:population":0,
    "gn:timezone":"Africa/Maputo",
    "iso:country":"MZ",
    "wof:name":"Muze",
    "wof:placetype":"locality"
},
  "geometry": {"coordinates":[31.23944,-15.00806],"type":"Point"}
}