{
  "type": "Feature",
  "properties": {
    "gn:admin1_code":"3",
    "gn:asciiname":"Changaveza",
    "gn:country_code":"MZ",
    "gn:dem":113,
    "gn:feature_class":"P",
    "gn:feature_code":"PPL",
    "gn:name":"Changaveza",
    "gn:population":0,
    "gn:timezone":"Africa/Maputo",
    "iso:country":"MZ",
    "wof:name":"Changaveza",
    "wof:placetype":"locality"
},
  "geometry": {"coordinates":[34.445,-21.52222],"type":"Point"}
}