{
  "type": "Feature",
  "properties": {
    "gn:admin1_code":"9",
    "gn:asciiname":"Errema",
    "gn:country_code":"MZ",
    "gn:dem":499,
    "gn:feature_class":"P",
    "gn:feature_code":"PPL",
    "gn:name":"Err\u00eama",
    "gn:population":0,
    "gn:timezone":"Africa/Maputo",
    "iso:country":"MZ",
    "wof:name":"Errema",
    "wof:placetype":"locality"
},
  "geometry": {"coordinates":[37.28583,-15.81028],"type":"Point"}
}