{
  "type": "Feature",
  "properties": {
    "gn:admin1_code":"6.0",
    "gn:asciiname":"Xitove",
    "gn:country_code":"MZ",
    "gn:dem":182,
    "gn:feature_class":"P",
    "gn:feature_code":"PPL",
    "gn:name":"Xitove",
    "gn:population":0,
    "gn:timezone":"Africa/Maputo",
    "iso:country":"MZ",
    "wof:name":"Xitove",
    "wof:placetype":"locality"
},
  "geometry": {"coordinates":[39.94611,-15.20361],"type":"Point"}
}