{
  "type": "Feature",
  "properties": {
    "gn:admin1_code":"0",
    "gn:asciiname":"Chibombo",
    "gn:country_code":"MZ",
    "gn:dem":121,
    "gn:feature_class":"P",
    "gn:feature_code":"PPL",
    "gn:name":"Chibombo",
    "gn:population":0,
    "gn:timezone":"Africa/Maputo",
    "iso:country":"MZ",
    "name:ceb_x_preferred":[
        "Chibombo"
    ],
    "name:deu_x_preferred":[
        "Chibombo"
    ],
    "name:ita_x_preferred":[
        "Chibombo"
    ],
    "name:lit_x_preferred":[
        "\u010cibombas"
    ],
    "name:mrj_x_preferred":[
        "\u0427\u0438\u0431\u043e\u043c\u0431\u043e"
    ],
    "name:pol_x_preferred":[
        "Chibombo"
    ],
    "name:por_x_preferred":[
        "Chibombo"
    ],
    "name:ron_x_preferred":[
        "Chibombo"
    ],
    "name:zho_x_preferred":[
        "\u5947\u90a6\u535a"
    ],
    "wof:name":"Chibombo",
    "wof:placetype":"locality"
},
  "geometry": {"coordinates":[32.13333,-25.36667000000001],"type":"Point"}
}