{
  "type": "Feature",
  "properties": {
    "gn:admin1_code":"0",
    "gn:asciiname":"Chibombo",
    "gn:country_code":"MZ",
    "gn:dem":121,
    "gn:feature_class":"P",
    "gn:feature_code":"PPL",
    "gn:name":"Chibombo",
    "gn:population":0,
    "gn:timezone":"Africa/Maputo",
    "iso:country":"MZ",
    "wof:name":"Chibombo",
    "wof:placetype":"locality"
},
  "geometry": {"coordinates":[32.13333,-25.36667000000001],"type":"Point"}
}