{
  "type": "Feature",
  "properties": {
    "gn:admin1_code":"4.0",
    "gn:asciiname":"Francisco",
    "gn:country_code":"MZ",
    "gn:dem":38,
    "gn:feature_class":"P",
    "gn:feature_code":"PPL",
    "gn:name":"Francisco",
    "gn:population":0,
    "gn:timezone":"Africa/Maputo",
    "iso:country":"MZ",
    "wof:name":"Francisco",
    "wof:placetype":"locality"
},
  "geometry": {"coordinates":[32.79,-24.73222],"type":"Point"}
}