{
  "type": "Feature",
  "properties": {
    "gn:admin1_code":"3.0",
    "gn:asciiname":"Serracao Mecanica",
    "gn:country_code":"MZ",
    "gn:dem":116,
    "gn:feature_class":"P",
    "gn:feature_code":"PPL",
    "gn:name":"Serra\u00e7\u00e3o Mec\u00e3nica",
    "gn:population":0,
    "gn:timezone":"Africa/Maputo",
    "iso:country":"MZ",
    "wof:name":"Serracao Mecanica",
    "wof:placetype":"locality"
},
  "geometry": {"coordinates":[34.50306,-23.94972000000001],"type":"Point"}
}