{
  "type": "Feature",
  "properties": {
    "gn:admin1_code":"0",
    "gn:asciiname":"Chilangue",
    "gn:cc2":"MZ",
    "gn:country_code":"MZ",
    "gn:dem":727,
    "gn:feature_class":"P",
    "gn:feature_code":"PPL",
    "gn:name":"Chilangue",
    "gn:population":0,
    "gn:timezone":"Africa/Maputo",
    "iso:country":"MZ",
    "name:und_x_variant":[
        "Chilange",
        "Chilangue"
    ],
    "wof:name":"Chilangue",
    "wof:placetype":"locality"
},
  "geometry": {"coordinates":[35.68333,-14.41667],"type":"Point"}
}