{
  "type": "Feature",
  "properties": {
    "gn:admin1_code":"9",
    "gn:asciiname":"Chefe Naquereia",
    "gn:country_code":"MZ",
    "gn:dem":801,
    "gn:feature_class":"P",
    "gn:feature_code":"PPL",
    "gn:name":"Chefe Naquereia",
    "gn:population":0,
    "gn:timezone":"Africa/Maputo",
    "iso:country":"MZ",
    "wof:name":"Chefe Naquereia",
    "wof:placetype":"locality"
},
  "geometry": {"coordinates":[36.42528,-15.60583],"type":"Point"}
}