{
  "type": "Feature",
  "properties": {
    "gn:admin1_code":"7",
    "gn:asciiname":"Metoto",
    "gn:country_code":"MZ",
    "gn:dem":1379,
    "gn:feature_class":"P",
    "gn:feature_code":"PPL",
    "gn:name":"Met\u00f4to",
    "gn:population":0,
    "gn:timezone":"Africa/Maputo",
    "iso:country":"MZ",
    "wof:name":"Metoto",
    "wof:placetype":"locality"
},
  "geometry": {"coordinates":[35.30110999999999,-13.34861],"type":"Point"}
}