{
  "type": "Feature",
  "properties": {
    "gn:admin1_code":"10.0",
    "gn:asciiname":"Vicente",
    "gn:country_code":"MZ",
    "gn:dem":277,
    "gn:feature_class":"P",
    "gn:feature_code":"PPL",
    "gn:name":"Vicente",
    "gn:population":0,
    "gn:timezone":"Africa/Maputo",
    "iso:country":"MZ",
    "wof:name":"Vicente",
    "wof:placetype":"locality"
},
  "geometry": {"coordinates":[33.95361,-19.12444],"type":"Point"}
}