{
  "type": "Feature",
  "properties": {
    "gn:admin1_code":"6",
    "gn:asciiname":"Cabo Joao",
    "gn:country_code":"MZ",
    "gn:dem":182,
    "gn:feature_class":"P",
    "gn:feature_code":"PPL",
    "gn:name":"Cabo Jo\u00e3o",
    "gn:population":0,
    "gn:timezone":"Africa/Maputo",
    "iso:country":"MZ",
    "wof:name":"Cabo Joao",
    "wof:placetype":"locality"
},
  "geometry": {"coordinates":[40.36333,-13.55667],"type":"Point"}
}