{
  "type": "Feature",
  "properties": {
    "gn:admin1_code":"3.0",
    "gn:asciiname":"Saite",
    "gn:country_code":"MZ",
    "gn:dem":89,
    "gn:feature_class":"P",
    "gn:feature_code":"PPL",
    "gn:name":"Saite",
    "gn:population":0,
    "gn:timezone":"Africa/Maputo",
    "iso:country":"MZ",
    "wof:name":"Saite",
    "wof:placetype":"locality"
},
  "geometry": {"coordinates":[33.97056,-21.35139],"type":"Point"}
}