{
  "type": "Feature",
  "properties": {
    "gn:admin1_code":"7",
    "gn:asciiname":"Teixeira",
    "gn:country_code":"MZ",
    "gn:dem":611,
    "gn:feature_class":"P",
    "gn:feature_code":"PPL",
    "gn:name":"Teixeira",
    "gn:population":0,
    "gn:timezone":"Africa/Maputo",
    "iso:country":"MZ",
    "wof:name":"Teixeira",
    "wof:placetype":"locality"
},
  "geometry": {"coordinates":[36.59639,-14.52583],"type":"Point"}
}