{
  "type": "Feature",
  "properties": {
    "gn:admin1_code":"5",
    "gn:asciiname":"Cazasse",
    "gn:country_code":"MZ",
    "gn:dem":104,
    "gn:feature_class":"P",
    "gn:feature_code":"PPL",
    "gn:name":"Cazasse",
    "gn:population":0,
    "gn:timezone":"Africa/Maputo",
    "iso:country":"MZ",
    "wof:name":"Cazasse",
    "wof:placetype":"locality"
},
  "geometry": {"coordinates":[34.17278,-19.07111],"type":"Point"}
}