{
  "type": "Feature",
  "properties": {
    "gn:admin1_code":"9",
    "gn:asciiname":"Mafumare",
    "gn:country_code":"MZ",
    "gn:dem":40,
    "gn:feature_class":"P",
    "gn:feature_code":"PPL",
    "gn:name":"Mafumare",
    "gn:population":0,
    "gn:timezone":"Africa/Maputo",
    "iso:country":"MZ",
    "wof:name":"Mafumare",
    "wof:placetype":"locality"
},
  "geometry": {"coordinates":[37.51389,-17.28556],"type":"Point"}
}