{
  "type": "Feature",
  "properties": {
    "gn:admin1_code":"6",
    "gn:asciiname":"Nantala",
    "gn:country_code":"MZ",
    "gn:dem":280,
    "gn:feature_class":"P",
    "gn:feature_code":"PPL",
    "gn:name":"Nantala",
    "gn:population":0,
    "gn:timezone":"Africa/Maputo",
    "iso:country":"MZ",
    "wof:name":"Nantala",
    "wof:placetype":"locality"
},
  "geometry": {"coordinates":[39.69361,-15.12444],"type":"Point"}
}