{
  "type": "Feature",
  "properties": {
    "gn:admin1_code":"3",
    "gn:asciiname":"Homoine",
    "gn:cc2":"MZ",
    "gn:country_code":"MZ",
    "gn:dem":114,
    "gn:feature_class":"P",
    "gn:feature_code":"PPL",
    "gn:name":"Homo\u00edne",
    "gn:population":0,
    "gn:timezone":"Africa/Maputo",
    "iso:country":"MZ",
    "name:und_x_variant":[
        "Manhica",
        "Homo\u00edne"
    ],
    "wof:name":"Homoine",
    "wof:placetype":"locality"
},
  "geometry": {"coordinates":[35.15139,-23.88444],"type":"Point"}
}