{
  "type": "Feature",
  "properties": {
    "gn:admin1_code":"0",
    "gn:asciiname":"Chevanze",
    "gn:country_code":"MZ",
    "gn:dem":96,
    "gn:feature_class":"P",
    "gn:feature_code":"PPL",
    "gn:name":"Chevanze",
    "gn:population":0,
    "gn:timezone":"Africa/Maputo",
    "iso:country":"MZ",
    "wof:name":"Chevanze",
    "wof:placetype":"locality"
},
  "geometry": {"coordinates":[34.46667,-21.21667],"type":"Point"}
}