{
  "type": "Feature",
  "properties": {
    "gn:admin1_code":"8",
    "gn:asciiname":"Chowalo",
    "gn:country_code":"MZ",
    "gn:dem":375,
    "gn:feature_class":"P",
    "gn:feature_code":"PPL",
    "gn:name":"Chowalo",
    "gn:population":0,
    "gn:timezone":"Africa/Maputo",
    "iso:country":"MZ",
    "wof:name":"Chowalo",
    "wof:placetype":"locality"
},
  "geometry": {"coordinates":[30.27944,-15.09806],"type":"Point"}
}