{
  "type": "Feature",
  "properties": {
    "gn:admin1_code":"9",
    "gn:asciiname":"Mutange",
    "gn:cc2":"MZ",
    "gn:country_code":"MZ",
    "gn:dem":16,
    "gn:feature_class":"P",
    "gn:feature_code":"PPL",
    "gn:name":"Mutange",
    "gn:population":0,
    "gn:timezone":"Africa/Maputo",
    "iso:country":"MZ",
    "name:und_x_variant":[
        "Mutanje",
        "Mutange"
    ],
    "wof:name":"Mutange",
    "wof:placetype":"locality"
},
  "geometry": {"coordinates":[36.92611,-17.57139],"type":"Point"}
}