{
  "type": "Feature",
  "properties": {
    "gn:admin1_code":"5",
    "gn:asciiname":"Bungano",
    "gn:country_code":"MZ",
    "gn:dem":147,
    "gn:feature_class":"P",
    "gn:feature_code":"PPL",
    "gn:name":"Bungano",
    "gn:population":0,
    "gn:timezone":"Africa/Maputo",
    "iso:country":"MZ",
    "wof:name":"Bungano",
    "wof:placetype":"locality"
},
  "geometry": {"coordinates":[33.48611,-20.01194],"type":"Point"}
}