{
  "type": "Feature",
  "properties": {
    "gn:admin1_code":"6",
    "gn:asciiname":"Mulata",
    "gn:country_code":"MZ",
    "gn:dem":399,
    "gn:feature_class":"P",
    "gn:feature_code":"PPL",
    "gn:name":"Mulata",
    "gn:population":0,
    "gn:timezone":"Africa/Maputo",
    "iso:country":"MZ",
    "wof:name":"Mulata",
    "wof:placetype":"locality"
},
  "geometry": {"coordinates":[38.26889,-14.43083],"type":"Point"}
}