{
  "type": "Feature",
  "properties": {
    "gn:admin1_code":"6",
    "gn:asciiname":"Napala",
    "gn:country_code":"MZ",
    "gn:dem":73,
    "gn:feature_class":"P",
    "gn:feature_code":"PPL",
    "gn:name":"Napala",
    "gn:population":0,
    "gn:timezone":"Africa/Maputo",
    "iso:country":"MZ",
    "wof:name":"Napala",
    "wof:placetype":"locality"
},
  "geometry": {"coordinates":[39.15139,-16.56472],"type":"Point"}
}