{
  "type": "Feature",
  "properties": {
    "gn:admin1_code":"10.0",
    "gn:asciiname":"Usa",
    "gn:country_code":"MZ",
    "gn:dem":254,
    "gn:feature_class":"P",
    "gn:feature_code":"PPL",
    "gn:name":"Usa",
    "gn:population":0,
    "gn:timezone":"Africa/Maputo",
    "iso:country":"MZ",
    "name:ara_x_preferred":[
        "\u0623\u0648\u0633\u0627"
    ],
    "name:ben_x_preferred":[
        "\u0987\u0989\u09b8\u09be"
    ],
    "name:ell_x_preferred":[
        "\u039f\u03cd\u03b6\u03b1"
    ],
    "name:heb_x_preferred":[
        "\u05d0\u05d5\u05bc\u05e1\u05d4"
    ],
    "name:hin_x_preferred":[
        "\u0909\u0938\u093e "
    ],
    "name:ind_x_preferred":[
        "Usa"
    ],
    "name:kor_x_preferred":[
        "\uc6b0\uc0ac"
    ],
    "name:por_x_preferred":[
        "Usa"
    ],
    "name:swe_x_preferred":[
        "Usa"
    ],
    "name:urd_x_preferred":[
        "\u0627\u0648\u0633\u0627"
    ],
    "name:vie_x_preferred":[
        "S\u00f4ng Usa"
    ],
    "wof:name":"Usa",
    "wof:placetype":"locality"
},
  "geometry": {"coordinates":[33.18861,-21.06528],"type":"Point"}
}