{
  "type": "Feature",
  "properties": {
    "gn:admin1_code":"10.0",
    "gn:asciiname":"Usa",
    "gn:country_code":"MZ",
    "gn:dem":254,
    "gn:feature_class":"P",
    "gn:feature_code":"PPL",
    "gn:name":"Usa",
    "gn:population":0,
    "gn:timezone":"Africa/Maputo",
    "iso:country":"MZ",
    "wof:name":"Usa",
    "wof:placetype":"locality"
},
  "geometry": {"coordinates":[33.18861,-21.06528],"type":"Point"}
}