{
  "type": "Feature",
  "properties": {
    "gn:admin1_code":"3",
    "gn:asciiname":"Regedor Guamba Pequeno",
    "gn:cc2":"MZ",
    "gn:country_code":"MZ",
    "gn:dem":68,
    "gn:feature_class":"P",
    "gn:feature_code":"PPL",
    "gn:name":"Regedor Guamba Pequeno",
    "gn:population":0,
    "gn:timezone":"Africa/Maputo",
    "iso:country":"MZ",
    "name:und_x_variant":[
        "Guamba Pequeno",
        "Regedor Guamba Pequeno"
    ],
    "wof:name":"Regedor Guamba Pequeno",
    "wof:placetype":"locality"
},
  "geometry": {"coordinates":[34.65333,-24.47694],"type":"Point"}
}