{
  "type": "Feature",
  "properties": {
    "gn:admin1_code":"5",
    "gn:asciiname":"Damiao",
    "gn:country_code":"MZ",
    "gn:dem":3,
    "gn:feature_class":"P",
    "gn:feature_code":"PPL",
    "gn:name":"Dami\u00e3o",
    "gn:population":0,
    "gn:timezone":"Africa/Maputo",
    "iso:country":"MZ",
    "wof:name":"Damiao",
    "wof:placetype":"locality"
},
  "geometry": {"coordinates":[34.95889,-19.78056],"type":"Point"}
}