{
  "type": "Feature",
  "properties": {
    "gn:admin1_code":"6",
    "gn:asciiname":"Chapala",
    "gn:country_code":"MZ",
    "gn:dem":56,
    "gn:feature_class":"P",
    "gn:feature_code":"PPL",
    "gn:name":"Chapala",
    "gn:population":0,
    "gn:timezone":"Africa/Maputo",
    "iso:country":"MZ",
    "name:ceb_x_preferred":[
        "Chapala"
    ],
    "name:rus_x_preferred":[
        "\u0427\u0430\u043f\u0430\u043b\u0430"
    ],
    "name:spa_x_preferred":[
        "Chapala"
    ],
    "name:swe_x_preferred":[
        "Chapala"
    ],
    "wof:name":"Chapala",
    "wof:placetype":"locality"
},
  "geometry": {"coordinates":[40.74222,-14.82111],"type":"Point"}
}