{
  "type": "Feature",
  "properties": {
    "gn:admin1_code":"6",
    "gn:asciiname":"Laca",
    "gn:country_code":"MZ",
    "gn:dem":464,
    "gn:feature_class":"P",
    "gn:feature_code":"PPL",
    "gn:name":"Laca",
    "gn:population":0,
    "gn:timezone":"Africa/Maputo",
    "iso:country":"MZ",
    "wof:name":"Laca",
    "wof:placetype":"locality"
},
  "geometry": {"coordinates":[38.66583,-15.39361],"type":"Point"}
}