{
  "type": "Feature",
  "properties": {
    "gn:admin1_code":"7",
    "gn:asciiname":"Marruanha",
    "gn:country_code":"MZ",
    "gn:dem":515,
    "gn:feature_class":"P",
    "gn:feature_code":"PPL",
    "gn:name":"Marruanha",
    "gn:population":0,
    "gn:timezone":"Africa/Maputo",
    "iso:country":"MZ",
    "wof:name":"Marruanha",
    "wof:placetype":"locality"
},
  "geometry": {"coordinates":[37.25333,-14.28389],"type":"Point"}
}