{
  "type": "Feature",
  "properties": {
    "gn:admin1_code":"4",
    "gn:asciiname":"C. Ribejene",
    "gn:country_code":"MZ",
    "gn:dem":41,
    "gn:feature_class":"P",
    "gn:feature_code":"PPL",
    "gn:name":"C. Ribejene",
    "gn:population":0,
    "gn:timezone":"Africa/Maputo",
    "iso:country":"MZ",
    "wof:name":"C. Ribejene",
    "wof:placetype":"locality"
},
  "geometry": {"coordinates":[32.73167,-25.33694],"type":"Point"}
}