{
  "type": "Feature",
  "properties": {
    "gn:admin1_code":"6",
    "gn:asciiname":"Coloele",
    "gn:country_code":"MZ",
    "gn:dem":536,
    "gn:feature_class":"P",
    "gn:feature_code":"PPL",
    "gn:name":"C\u00f3l\u00f3ele",
    "gn:population":0,
    "gn:timezone":"Africa/Maputo",
    "iso:country":"MZ",
    "wof:name":"Coloele",
    "wof:placetype":"locality"
},
  "geometry": {"coordinates":[37.42722,-14.69472],"type":"Point"}
}