{
  "type": "Feature",
  "properties": {
    "gn:admin1_code":"2",
    "gn:asciiname":"Josefe",
    "gn:country_code":"MZ",
    "gn:dem":103,
    "gn:feature_class":"P",
    "gn:feature_code":"PPL",
    "gn:name":"Josefe",
    "gn:population":0,
    "gn:timezone":"Africa/Maputo",
    "iso:country":"MZ",
    "wof:name":"Josefe",
    "wof:placetype":"locality"
},
  "geometry": {"coordinates":[32.86944,-23.46556],"type":"Point"}
}