{
  "type": "Feature",
  "properties": {
    "gn:admin1_code":"1",
    "gn:asciiname":"Capunja",
    "gn:country_code":"MZ",
    "gn:dem":626,
    "gn:feature_class":"P",
    "gn:feature_code":"PPL",
    "gn:name":"Capunja",
    "gn:population":0,
    "gn:timezone":"Africa/Maputo",
    "iso:country":"MZ",
    "wof:name":"Capunja",
    "wof:placetype":"locality"
},
  "geometry": {"coordinates":[39.30806,-11.40194],"type":"Point"}
}