{
  "type": "Feature",
  "properties": {
    "gn:admin1_code":"3",
    "gn:asciiname":"Issai",
    "gn:cc2":"MZ",
    "gn:country_code":"MZ",
    "gn:dem":42,
    "gn:feature_class":"P",
    "gn:feature_code":"PPL",
    "gn:name":"Issai",
    "gn:population":0,
    "gn:timezone":"Africa/Maputo",
    "iso:country":"MZ",
    "name:und_x_variant":[
        "Machengue",
        "Issai"
    ],
    "wof:name":"Issai",
    "wof:placetype":"locality"
},
  "geometry": {"coordinates":[35.1025,-22.13861],"type":"Point"}
}