{
  "type": "Feature",
  "properties": {
    "gn:admin1_code":"9.0",
    "gn:asciiname":"Regulo Motineia",
    "gn:country_code":"MZ",
    "gn:dem":319,
    "gn:feature_class":"P",
    "gn:feature_code":"PPL",
    "gn:name":"R\u00e9gulo Motineia",
    "gn:population":0,
    "gn:timezone":"Africa/Maputo",
    "iso:country":"MZ",
    "wof:name":"Regulo Motineia",
    "wof:placetype":"locality"
},
  "geometry": {"coordinates":[37.22917,-16.275],"type":"Point"}
}