{
  "type": "Feature",
  "properties": {
    "gn:admin1_code":"10.0",
    "gn:asciiname":"Matsinho",
    "gn:country_code":"MZ",
    "gn:dem":696,
    "gn:feature_class":"P",
    "gn:feature_code":"PPL",
    "gn:name":"Matsinho",
    "gn:population":0,
    "gn:timezone":"Africa/Maputo",
    "iso:country":"MZ",
    "wof:name":"Matsinho",
    "wof:placetype":"locality"
},
  "geometry": {"coordinates":[33.42722,-19.02389],"type":"Point"}
}