{
  "type": "Feature",
  "properties": {
    "gn:admin1_code":"7",
    "gn:asciiname":"Malique",
    "gn:country_code":"MZ",
    "gn:dem":618,
    "gn:feature_class":"P",
    "gn:feature_code":"PPL",
    "gn:name":"Malique",
    "gn:population":0,
    "gn:timezone":"Africa/Maputo",
    "iso:country":"MZ",
    "wof:name":"Malique",
    "wof:placetype":"locality"
},
  "geometry": {"coordinates":[37.7175,-13.39],"type":"Point"}
}