{
  "type": "Feature",
  "properties": {
    "gn:admin1_code":"9",
    "gn:asciiname":"Namurravua",
    "gn:country_code":"MZ",
    "gn:dem":8,
    "gn:feature_class":"P",
    "gn:feature_code":"PPL",
    "gn:name":"Namurravua",
    "gn:population":0,
    "gn:timezone":"Africa/Maputo",
    "iso:country":"MZ",
    "wof:name":"Namurravua",
    "wof:placetype":"locality"
},
  "geometry": {"coordinates":[37.59611,-17.52444],"type":"Point"}
}