{
  "type": "Feature",
  "properties": {
    "gn:admin1_code":"1",
    "gn:asciiname":"Humo Uncuba",
    "gn:country_code":"MZ",
    "gn:dem":403,
    "gn:feature_class":"P",
    "gn:feature_code":"PPL",
    "gn:name":"Humo Uncuba",
    "gn:population":0,
    "gn:timezone":"Africa/Maputo",
    "iso:country":"MZ",
    "wof:name":"Humo Uncuba",
    "wof:placetype":"locality"
},
  "geometry": {"coordinates":[38.79528,-13.88778],"type":"Point"}
}