{
  "type": "Feature",
  "properties": {
    "gn:admin1_code":"6",
    "gn:asciiname":"Malieque",
    "gn:country_code":"MZ",
    "gn:dem":268,
    "gn:feature_class":"P",
    "gn:feature_code":"PPL",
    "gn:name":"Malieque",
    "gn:population":0,
    "gn:timezone":"Africa/Maputo",
    "iso:country":"MZ",
    "wof:name":"Malieque",
    "wof:placetype":"locality"
},
  "geometry": {"coordinates":[39.58083,-15.35667],"type":"Point"}
}