{
  "type": "Feature",
  "properties": {
    "gn:admin1_code":"4.0",
    "gn:asciiname":"Chiburre",
    "gn:country_code":"MZ",
    "gn:dem":100,
    "gn:feature_class":"P",
    "gn:feature_code":"PPL",
    "gn:name":"Chiburre",
    "gn:population":0,
    "gn:timezone":"Africa/Maputo",
    "iso:country":"MZ",
    "wof:name":"Chiburre",
    "wof:placetype":"locality"
},
  "geometry": {"coordinates":[32.44556,-24.73806],"type":"Point"}
}