{
  "type": "Feature",
  "properties": {
    "gn:admin1_code":"7",
    "gn:asciiname":"Namacambale",
    "gn:country_code":"MZ",
    "gn:dem":481,
    "gn:feature_class":"P",
    "gn:feature_code":"PPL",
    "gn:name":"Namacambale",
    "gn:population":0,
    "gn:timezone":"Africa/Maputo",
    "iso:country":"MZ",
    "wof:name":"Namacambale",
    "wof:placetype":"locality"
},
  "geometry": {"coordinates":[36.76417,-12.67583],"type":"Point"}
}