{
  "type": "Feature",
  "properties": {
    "gn:admin1_code":"6.0",
    "gn:asciiname":"Uache",
    "gn:country_code":"MZ",
    "gn:dem":614,
    "gn:feature_class":"P",
    "gn:feature_code":"PPL",
    "gn:name":"U\u00e0che",
    "gn:population":0,
    "gn:timezone":"Africa/Maputo",
    "iso:country":"MZ",
    "wof:name":"Uache",
    "wof:placetype":"locality"
},
  "geometry": {"coordinates":[38.09833,-14.97528],"type":"Point"}
}