{
  "type": "Feature",
  "properties": {
    "gn:admin1_code":"10",
    "gn:asciiname":"Buca",
    "gn:country_code":"MZ",
    "gn:dem":135,
    "gn:feature_class":"P",
    "gn:feature_code":"PPL",
    "gn:name":"Buca",
    "gn:population":0,
    "gn:timezone":"Africa/Maputo",
    "iso:country":"MZ",
    "wof:name":"Buca",
    "wof:placetype":"locality"
},
  "geometry": {"coordinates":[33.14361,-21.47083],"type":"Point"}
}