{
  "type": "Feature",
  "properties": {
    "gn:admin1_code":"10",
    "gn:asciiname":"Buca",
    "gn:country_code":"MZ",
    "gn:dem":135,
    "gn:feature_class":"P",
    "gn:feature_code":"PPL",
    "gn:name":"Buca",
    "gn:population":0,
    "gn:timezone":"Africa/Maputo",
    "iso:country":"MZ",
    "name:aze_x_preferred":[
        "Buca"
    ],
    "name:ceb_x_preferred":[
        "Buca"
    ],
    "name:deu_x_preferred":[
        "Buca"
    ],
    "name:diq_x_preferred":[
        "Buca"
    ],
    "name:ell_x_preferred":[
        "\u0392\u03bf\u03c5\u03c4\u03b6\u03ac\u03c2"
    ],
    "name:epo_x_preferred":[
        "Buca"
    ],
    "name:fra_x_preferred":[
        "Buca"
    ],
    "name:mrj_x_preferred":[
        "\u0411\u0443\u0434\u0436\u0430"
    ],
    "name:msa_x_preferred":[
        "Buca"
    ],
    "name:nld_x_preferred":[
        "Buca"
    ],
    "name:nor_x_preferred":[
        "Buca"
    ],
    "name:swa_x_preferred":[
        "Buca"
    ],
    "name:tur_x_preferred":[
        "Buca"
    ],
    "name:urd_x_preferred":[
        "\u0628\u0648\u062c\u0627"
    ],
    "name:vie_x_preferred":[
        "Buca"
    ],
    "wof:name":"Buca",
    "wof:placetype":"locality"
},
  "geometry": {"coordinates":[33.14361,-21.47083],"type":"Point"}
}