{
  "type": "Feature",
  "properties": {
    "gn:admin1_code":"6",
    "gn:asciiname":"Menapo",
    "gn:country_code":"MZ",
    "gn:dem":61,
    "gn:feature_class":"P",
    "gn:feature_code":"PPL",
    "gn:name":"Menapo",
    "gn:population":0,
    "gn:timezone":"Africa/Maputo",
    "iso:country":"MZ",
    "wof:name":"Menapo",
    "wof:placetype":"locality"
},
  "geometry": {"coordinates":[39.15583,-16.66889],"type":"Point"}
}