{
  "type": "Feature",
  "properties": {
    "gn:admin1_code":"6.0",
    "gn:asciiname":"Ruhua",
    "gn:country_code":"MZ",
    "gn:dem":336,
    "gn:feature_class":"P",
    "gn:feature_code":"PPL",
    "gn:name":"Ruhua",
    "gn:population":0,
    "gn:timezone":"Africa/Maputo",
    "iso:country":"MZ",
    "wof:name":"Ruhua",
    "wof:placetype":"locality"
},
  "geometry": {"coordinates":[38.97139,-15.35056],"type":"Point"}
}