{
  "type": "Feature",
  "properties": {
    "gn:admin1_code":"0",
    "gn:asciiname":"Mucupura",
    "gn:country_code":"MZ",
    "gn:dem":677,
    "gn:feature_class":"P",
    "gn:feature_code":"PPL",
    "gn:name":"Mucupura",
    "gn:population":0,
    "gn:timezone":"Africa/Maputo",
    "iso:country":"MZ",
    "wof:name":"Mucupura",
    "wof:placetype":"locality"
},
  "geometry": {"coordinates":[32.88333,-19.15],"type":"Point"}
}