{
  "type": "Feature",
  "properties": {
    "gn:admin1_code":"5",
    "gn:asciiname":"Inhanvuvo",
    "gn:cc2":"MZ",
    "gn:country_code":"MZ",
    "gn:dem":161,
    "gn:feature_class":"P",
    "gn:feature_code":"PPL",
    "gn:name":"Inhanvuvo",
    "gn:population":0,
    "gn:timezone":"Africa/Maputo",
    "iso:country":"MZ",
    "name:und_x_variant":[
        "Inhainvuvo",
        "Inhanvuvo"
    ],
    "wof:name":"Inhanvuvo",
    "wof:placetype":"locality"
},
  "geometry": {"coordinates":[34.15667,-20.22194],"type":"Point"}
}