{
  "type": "Feature",
  "properties": {
    "gn:admin1_code":"3.0",
    "gn:asciiname":"Zangati",
    "gn:country_code":"MZ",
    "gn:dem":135,
    "gn:feature_class":"P",
    "gn:feature_code":"PPL",
    "gn:name":"Zangati",
    "gn:population":0,
    "gn:timezone":"Africa/Maputo",
    "iso:country":"MZ",
    "wof:name":"Zangati",
    "wof:placetype":"locality"
},
  "geometry": {"coordinates":[34.86806,-22.51083],"type":"Point"}
}