{
  "type": "Feature",
  "properties": {
    "gn:admin1_code":"10",
    "gn:asciiname":"Licau",
    "gn:country_code":"MZ",
    "gn:dem":245,
    "gn:feature_class":"P",
    "gn:feature_code":"PPL",
    "gn:name":"Licau",
    "gn:population":0,
    "gn:timezone":"Africa/Maputo",
    "iso:country":"MZ",
    "wof:name":"Licau",
    "wof:placetype":"locality"
},
  "geometry": {"coordinates":[33.48722,-20.69972000000001],"type":"Point"}
}