{
  "type": "Feature",
  "properties": {
    "gn:admin1_code":"10",
    "gn:asciiname":"Pezenga",
    "gn:country_code":"MZ",
    "gn:dem":472,
    "gn:feature_class":"P",
    "gn:feature_code":"PPL",
    "gn:name":"Pezenga",
    "gn:population":0,
    "gn:timezone":"Africa/Maputo",
    "iso:country":"MZ",
    "name:por_x_preferred":[
        "Pezenga"
    ],
    "wof:name":"Pezenga",
    "wof:placetype":"locality"
},
  "geometry": {"coordinates":[32.53751,-20.77504],"type":"Point"}
}