{
  "type": "Feature",
  "properties": {
    "gn:admin1_code":"2",
    "gn:asciiname":"Femiaco",
    "gn:country_code":"MZ",
    "gn:dem":106,
    "gn:feature_class":"P",
    "gn:feature_code":"PPL",
    "gn:name":"Femiaco",
    "gn:population":0,
    "gn:timezone":"Africa/Maputo",
    "iso:country":"MZ",
    "wof:name":"Femiaco",
    "wof:placetype":"locality"
},
  "geometry": {"coordinates":[33.32222,-22.36417],"type":"Point"}
}