{
  "type": "Feature",
  "properties": {
    "gn:admin1_code":"7",
    "gn:asciiname":"Peraculama",
    "gn:country_code":"MZ",
    "gn:dem":555,
    "gn:feature_class":"P",
    "gn:feature_code":"PPL",
    "gn:name":"Peraculama",
    "gn:population":0,
    "gn:timezone":"Africa/Maputo",
    "iso:country":"MZ",
    "wof:name":"Peraculama",
    "wof:placetype":"locality"
},
  "geometry": {"coordinates":[34.9675,-12.51333],"type":"Point"}
}