{
  "type": "Feature",
  "properties": {
    "gn:admin1_code":"10",
    "gn:asciiname":"Devi",
    "gn:country_code":"MZ",
    "gn:dem":267,
    "gn:feature_class":"P",
    "gn:feature_code":"PPL",
    "gn:name":"Devi",
    "gn:population":0,
    "gn:timezone":"Africa/Maputo",
    "iso:country":"MZ",
    "name:por_x_preferred":[
        "Devi"
    ],
    "wof:name":"Devi",
    "wof:placetype":"locality"
},
  "geometry": {"coordinates":[32.90067,-20.6467],"type":"Point"}
}