{
  "type": "Feature",
  "properties": {
    "gn:admin1_code":"10",
    "gn:asciiname":"Devi",
    "gn:country_code":"MZ",
    "gn:dem":267,
    "gn:feature_class":"P",
    "gn:feature_code":"PPL",
    "gn:name":"Devi",
    "gn:population":0,
    "gn:timezone":"Africa/Maputo",
    "iso:country":"MZ",
    "name:als_x_preferred":[
        "Devi"
    ],
    "name:ara_x_preferred":[
        "\u062f\u064a\u06a4\u064a"
    ],
    "name:ben_x_preferred":[
        "\u09a6\u09c7\u09ac\u09c0"
    ],
    "name:bih_x_preferred":[
        "\u0926\u0947\u0935\u0940"
    ],
    "name:bos_x_preferred":[
        "Devi"
    ],
    "name:cat_x_preferred":[
        "Devi"
    ],
    "name:ces_x_preferred":[
        "D\u00e9v\u00ed"
    ],
    "name:deu_x_preferred":[
        "Devi"
    ],
    "name:fas_x_preferred":[
        "\u062f\u0648\u06cc"
    ],
    "name:fin_x_preferred":[
        "Devi"
    ],
    "name:fra_x_preferred":[
        "Dev\u00ee"
    ],
    "name:hrv_x_preferred":[
        "Devi"
    ],
    "name:hun_x_preferred":[
        "D\u00e9vi"
    ],
    "name:ita_x_preferred":[
        "Devi"
    ],
    "name:jpn_x_preferred":[
        "\u30c7\u30fc\u30f4\u30a3\u30fc"
    ],
    "name:kan_x_preferred":[
        "\u0ca6\u0cc7\u0cb5\u0cbf"
    ],
    "name:kat_x_preferred":[
        "\u10d3\u10d4\u10d5\u10d8"
    ],
    "name:lit_x_preferred":[
        "Dev\u0117"
    ],
    "name:mal_x_preferred":[
        "\u0d26\u0d47\u0d35\u0d3f"
    ],
    "name:nep_x_preferred":[
        "\u0926\u0947\u0935\u0940"
    ],
    "name:nld_x_preferred":[
        "Devi"
    ],
    "name:nno_x_preferred":[
        "Devi"
    ],
    "name:nor_x_preferred":[
        "Devi"
    ],
    "name:pan_x_preferred":[
        "\u0a26\u0a47\u0a35\u0a40"
    ],
    "name:pol_x_preferred":[
        "Dewi"
    ],
    "name:por_x_preferred":[
        "Devi"
    ],
    "name:rus_x_preferred":[
        "\u0414\u0435\u0432\u0438"
    ],
    "name:san_x_preferred":[
        "\u0936\u0915\u094d\u0924\u093f\u0926\u0947\u0935\u0940"
    ],
    "name:sin_x_preferred":[
        "\u0daf\u0dda\u0dc0\u0dd3"
    ],
    "name:slv_x_preferred":[
        "Devi"
    ],
    "name:spa_x_preferred":[
        "Dev\u00ed"
    ],
    "name:swe_x_preferred":[
        "Devi"
    ],
    "name:tam_x_preferred":[
        "\u0ba4\u0bc7\u0bb5\u0bbf"
    ],
    "name:tha_x_preferred":[
        "\u0e40\u0e17\u0e27\u0e35\u0e43\u0e19\u0e28\u0e32\u0e2a\u0e19\u0e32\u0e2e\u0e34\u0e19\u0e14\u0e39"
    ],
    "name:tur_x_preferred":[
        "Devi"
    ],
    "name:ukr_x_preferred":[
        "\u0414\u0435\u0432\u0456"
    ],
    "name:urd_x_preferred":[
        "\u062f\u06cc\u0648\u06cc"
    ],
    "name:uzb_x_preferred":[
        "Devi"
    ],
    "wof:name":"Devi",
    "wof:placetype":"locality"
},
  "geometry": {"coordinates":[32.90067,-20.6467],"type":"Point"}
}