{
  "type": "Feature",
  "properties": {
    "gn:admin1_code":"3.0",
    "gn:asciiname":"S. Matsombe",
    "gn:country_code":"MZ",
    "gn:dem":34,
    "gn:feature_class":"P",
    "gn:feature_code":"PPL",
    "gn:name":"S. Matsombe",
    "gn:population":0,
    "gn:timezone":"Africa/Maputo",
    "iso:country":"MZ",
    "wof:name":"S. Matsombe",
    "wof:placetype":"locality"
},
  "geometry": {"coordinates":[34.21389,-24.35861],"type":"Point"}
}