{
  "type": "Feature",
  "properties": {
    "gn:admin1_code":"9",
    "gn:asciiname":"Alicene",
    "gn:country_code":"MZ",
    "gn:dem":253,
    "gn:feature_class":"P",
    "gn:feature_code":"PPL",
    "gn:name":"Alicene",
    "gn:population":0,
    "gn:timezone":"Africa/Maputo",
    "iso:country":"MZ",
    "wof:name":"Alicene",
    "wof:placetype":"locality"
},
  "geometry": {"coordinates":[36.63083,-16.96361],"type":"Point"}
}