{
  "type": "Feature",
  "properties": {
    "gn:admin1_code":"8",
    "gn:asciiname":"Mecussa",
    "gn:country_code":"MZ",
    "gn:dem":317,
    "gn:feature_class":"P",
    "gn:feature_code":"PPL",
    "gn:name":"Mecussa",
    "gn:population":0,
    "gn:timezone":"Africa/Maputo",
    "iso:country":"MZ",
    "wof:name":"Mecussa",
    "wof:placetype":"locality"
},
  "geometry": {"coordinates":[31.60472,-15.67306],"type":"Point"}
}