{
  "type": "Feature",
  "properties": {
    "gn:admin1_code":"10",
    "gn:asciiname":"Chicanga",
    "gn:country_code":"MZ",
    "gn:dem":515,
    "gn:feature_class":"P",
    "gn:feature_code":"PPL",
    "gn:name":"Chicanga",
    "gn:population":0,
    "gn:timezone":"Africa/Maputo",
    "iso:country":"MZ",
    "wof:name":"Chicanga",
    "wof:placetype":"locality"
},
  "geometry": {"coordinates":[33.57611,-19.2825],"type":"Point"}
}