{
  "type": "Feature",
  "properties": {
    "gn:admin1_code":"4",
    "gn:asciiname":"Chainhane",
    "gn:country_code":"MZ",
    "gn:dem":212,
    "gn:feature_class":"P",
    "gn:feature_code":"PPL",
    "gn:name":"Chainhane",
    "gn:population":0,
    "gn:timezone":"Africa/Maputo",
    "iso:country":"MZ",
    "wof:name":"Chainhane",
    "wof:placetype":"locality"
},
  "geometry": {"coordinates":[32.12583,-26.3925],"type":"Point"}
}