{
  "type": "Feature",
  "properties": {
    "gn:admin1_code":"5",
    "gn:asciiname":"Bandua",
    "gn:country_code":"MZ",
    "gn:dem":11,
    "gn:feature_class":"P",
    "gn:feature_code":"PPL",
    "gn:name":"Bandua",
    "gn:population":0,
    "gn:timezone":"Africa/Maputo",
    "iso:country":"MZ",
    "name:cat_x_preferred":[
        "Bandua"
    ],
    "name:deu_x_preferred":[
        "Bandua"
    ],
    "name:glg_x_preferred":[
        "Bandua"
    ],
    "name:por_x_preferred":[
        "Bandua"
    ],
    "name:zho_x_preferred":[
        "\u73ed\u8fbe"
    ],
    "wof:name":"Bandua",
    "wof:placetype":"locality"
},
  "geometry": {"coordinates":[34.45778,-19.985],"type":"Point"}
}