{
  "type": "Feature",
  "properties": {
    "gn:admin1_code":"7",
    "gn:asciiname":"Regulo Carronga",
    "gn:cc2":"MZ",
    "gn:country_code":"MZ",
    "gn:dem":638,
    "gn:feature_class":"P",
    "gn:feature_code":"PPL",
    "gn:name":"R\u00e9gulo Carronga",
    "gn:population":0,
    "gn:timezone":"Africa/Maputo",
    "iso:country":"MZ",
    "name:und_x_variant":[
        "Carronga",
        "Caronga",
        "R\u00e9gulo Carronga"
    ],
    "wof:name":"Regulo Carronga",
    "wof:placetype":"locality"
},
  "geometry": {"coordinates":[36.1625,-14.95139],"type":"Point"}
}