{
  "type": "Feature",
  "properties": {
    "gn:admin1_code":"6",
    "gn:asciiname":"Chaves",
    "gn:country_code":"MZ",
    "gn:dem":212,
    "gn:feature_class":"P",
    "gn:feature_code":"PPL",
    "gn:name":"Chaves",
    "gn:population":0,
    "gn:timezone":"Africa/Maputo",
    "iso:country":"MZ",
    "name:ara_x_preferred":[
        "\u0634\u0627\u0641\u064a\u0632"
    ],
    "name:bre_x_preferred":[
        "Chaves"
    ],
    "name:ceb_x_preferred":[
        "Chaves"
    ],
    "name:ces_x_preferred":[
        "Chaves"
    ],
    "name:deu_x_preferred":[
        "Chaves"
    ],
    "name:fra_x_preferred":[
        "Chaves"
    ],
    "name:glg_x_preferred":[
        "Chaves"
    ],
    "name:hrv_x_preferred":[
        "Chaves"
    ],
    "name:ita_x_preferred":[
        "Chaves"
    ],
    "name:kor_x_preferred":[
        "\ucc28\ubca0\uc2a4"
    ],
    "name:nld_x_preferred":[
        "Chaves"
    ],
    "name:por_x_preferred":[
        "Chaves"
    ],
    "name:rus_x_preferred":[
        "\u0428\u0430\u0432\u0435\u0441"
    ],
    "name:spa_x_preferred":[
        "Chaves"
    ],
    "name:swe_x_preferred":[
        "Chaves"
    ],
    "name:tur_x_preferred":[
        "Chaves"
    ],
    "name:vie_x_preferred":[
        "Chaves"
    ],
    "name:vol_x_preferred":[
        "Chaves"
    ],
    "wof:name":"Chaves",
    "wof:placetype":"locality"
},
  "geometry": {"coordinates":[40.23611,-14.17722],"type":"Point"}
}