{
  "type": "Feature",
  "properties": {
    "gn:admin1_code":"6",
    "gn:asciiname":"Chaves",
    "gn:country_code":"MZ",
    "gn:dem":212,
    "gn:feature_class":"P",
    "gn:feature_code":"PPL",
    "gn:name":"Chaves",
    "gn:population":0,
    "gn:timezone":"Africa/Maputo",
    "iso:country":"MZ",
    "wof:name":"Chaves",
    "wof:placetype":"locality"
},
  "geometry": {"coordinates":[40.23611,-14.17722],"type":"Point"}
}