{
  "type": "Feature",
  "properties": {
    "gn:admin1_code":"10",
    "gn:asciiname":"Ficha",
    "gn:country_code":"MZ",
    "gn:dem":748,
    "gn:feature_class":"P",
    "gn:feature_code":"PPL",
    "gn:name":"Ficha",
    "gn:population":0,
    "gn:timezone":"Africa/Maputo",
    "iso:country":"MZ",
    "wof:name":"Ficha",
    "wof:placetype":"locality"
},
  "geometry": {"coordinates":[33.40278,-17.70277999999999],"type":"Point"}
}