{
  "type": "Feature",
  "properties": {
    "gn:admin1_code":"3.0",
    "gn:asciiname":"Regulo Bambamba",
    "gn:country_code":"MZ",
    "gn:dem":58,
    "gn:feature_class":"P",
    "gn:feature_code":"PPL",
    "gn:name":"R\u00e9gulo Bambamba",
    "gn:population":0,
    "gn:timezone":"Africa/Maputo",
    "iso:country":"MZ",
    "wof:name":"Regulo Bambamba",
    "wof:placetype":"locality"
},
  "geometry": {"coordinates":[35.26139000000001,-24.10333],"type":"Point"}
}