{
  "type": "Feature",
  "properties": {
    "gn:admin1_code":"8",
    "gn:asciiname":"Luvuerere",
    "gn:country_code":"MZ",
    "gn:dem":921,
    "gn:feature_class":"P",
    "gn:feature_code":"PPL",
    "gn:name":"Luvuerere",
    "gn:population":0,
    "gn:timezone":"Africa/Maputo",
    "iso:country":"MZ",
    "wof:name":"Luvuerere",
    "wof:placetype":"locality"
},
  "geometry": {"coordinates":[31.51222000000001,-14.83361],"type":"Point"}
}