{
  "type": "Feature",
  "properties": {
    "gn:admin1_code":"1",
    "gn:asciiname":"Cassamo",
    "gn:country_code":"MZ",
    "gn:dem":364,
    "gn:feature_class":"P",
    "gn:feature_code":"PPL",
    "gn:name":"Cassamo",
    "gn:population":0,
    "gn:timezone":"Africa/Maputo",
    "iso:country":"MZ",
    "wof:name":"Cassamo",
    "wof:placetype":"locality"
},
  "geometry": {"coordinates":[39.99778,-12.24444],"type":"Point"}
}