{
  "type": "Feature",
  "properties": {
    "gn:admin1_code":"7",
    "gn:asciiname":"Mepunga",
    "gn:cc2":"MZ",
    "gn:country_code":"MZ",
    "gn:dem":656,
    "gn:feature_class":"P",
    "gn:feature_code":"PPL",
    "gn:name":"Mepunga",
    "gn:population":0,
    "gn:timezone":"Africa/Maputo",
    "iso:country":"MZ",
    "name:und_x_variant":[
        "Mpunga",
        "Mepunga"
    ],
    "wof:name":"Mepunga",
    "wof:placetype":"locality"
},
  "geometry": {"coordinates":[36.25694,-15.12528],"type":"Point"}
}