{
  "type": "Feature",
  "properties": {
    "gn:admin1_code":"1",
    "gn:asciiname":"Avaiaca",
    "gn:country_code":"MZ",
    "gn:dem":509,
    "gn:feature_class":"P",
    "gn:feature_code":"PPL",
    "gn:name":"Avaiaca",
    "gn:population":0,
    "gn:timezone":"Africa/Maputo",
    "iso:country":"MZ",
    "wof:name":"Avaiaca",
    "wof:placetype":"locality"
},
  "geometry": {"coordinates":[38.88417000000001,-12.95889],"type":"Point"}
}