{
  "type": "Feature",
  "properties": {
    "gn:admin1_code":"3.0",
    "gn:asciiname":"Cabo Chissidane",
    "gn:country_code":"MZ",
    "gn:dem":71,
    "gn:feature_class":"P",
    "gn:feature_code":"PPL",
    "gn:name":"Cabo Chissidane",
    "gn:population":0,
    "gn:timezone":"Africa/Maputo",
    "iso:country":"MZ",
    "wof:name":"Cabo Chissidane",
    "wof:placetype":"locality"
},
  "geometry": {"coordinates":[35.39306,-23.40694],"type":"Point"}
}