{
  "type": "Feature",
  "properties": {
    "gn:admin1_code":"6",
    "gn:asciiname":"Muaquima",
    "gn:country_code":"MZ",
    "gn:dem":276,
    "gn:feature_class":"P",
    "gn:feature_code":"PPL",
    "gn:name":"Muaquima",
    "gn:population":0,
    "gn:timezone":"Africa/Maputo",
    "iso:country":"MZ",
    "wof:name":"Muaquima",
    "wof:placetype":"locality"
},
  "geometry": {"coordinates":[39.18639,-13.97333],"type":"Point"}
}