{
  "type": "Feature",
  "properties": {
    "gn:admin1_code":"6",
    "gn:asciiname":"Juma",
    "gn:country_code":"MZ",
    "gn:dem":27,
    "gn:feature_class":"P",
    "gn:feature_code":"PPL",
    "gn:name":"Juma",
    "gn:population":0,
    "gn:timezone":"Africa/Maputo",
    "iso:country":"MZ",
    "name:ceb_x_preferred":[
        "Juma"
    ],
    "name:deu_x_preferred":[
        "Juma"
    ],
    "name:mal_x_preferred":[
        "\u0d1c\u0d41\u0d2e\u0d41\u0d05"
    ],
    "name:rus_x_preferred":[
        "\u0414\u0436\u0443\u043c\u0430"
    ],
    "name:swe_x_preferred":[
        "Juma"
    ],
    "name:ukr_x_preferred":[
        "\u0414\u0436\u0443\u043c\u0430"
    ],
    "name:uzb_x_preferred":[
        "Juma"
    ],
    "wof:name":"Juma",
    "wof:placetype":"locality"
},
  "geometry": {"coordinates":[40.49111,-14.17444],"type":"Point"}
}