{
  "type": "Feature",
  "properties": {
    "gn:admin1_code":"2.0",
    "gn:asciiname":"Mabizueni",
    "gn:country_code":"MZ",
    "gn:dem":249,
    "gn:feature_class":"P",
    "gn:feature_code":"PPL",
    "gn:name":"Mabizueni",
    "gn:population":0,
    "gn:timezone":"Africa/Maputo",
    "iso:country":"MZ",
    "wof:name":"Mabizueni",
    "wof:placetype":"locality"
},
  "geometry": {"coordinates":[31.595,-23.23417],"type":"Point"}
}