{
  "type": "Feature",
  "properties": {
    "gn:admin1_code":"2",
    "gn:asciiname":"Nideja",
    "gn:country_code":"MZ",
    "gn:dem":112,
    "gn:feature_class":"P",
    "gn:feature_code":"PPL",
    "gn:name":"Nideja",
    "gn:population":0,
    "gn:timezone":"Africa/Maputo",
    "iso:country":"MZ",
    "wof:name":"Nideja",
    "wof:placetype":"locality"
},
  "geometry": {"coordinates":[33.27944,-22.23972],"type":"Point"}
}