{
  "type": "Feature",
  "properties": {
    "gn:admin1_code":"1.0",
    "gn:asciiname":"Sicoto",
    "gn:country_code":"MZ",
    "gn:dem":344,
    "gn:feature_class":"P",
    "gn:feature_code":"PPL",
    "gn:name":"Sic\u00f4to",
    "gn:population":0,
    "gn:timezone":"Africa/Maputo",
    "iso:country":"MZ",
    "wof:name":"Sicoto",
    "wof:placetype":"locality"
},
  "geometry": {"coordinates":[39.47111,-12.75833],"type":"Point"}
}