{
  "type": "Feature",
  "properties": {
    "gn:admin1_code":"9",
    "gn:asciiname":"Pedro",
    "gn:country_code":"MZ",
    "gn:dem":176,
    "gn:feature_class":"P",
    "gn:feature_code":"PPL",
    "gn:name":"Pedro",
    "gn:population":0,
    "gn:timezone":"Africa/Maputo",
    "iso:country":"MZ",
    "name:ara_x_preferred":[
        "\u0628\u064a\u062f\u0631\u0648"
    ],
    "name:bre_x_preferred":[
        "Pedro"
    ],
    "name:dan_x_preferred":[
        "Pedro"
    ],
    "name:glg_x_preferred":[
        "Pedro"
    ],
    "name:heb_x_preferred":[
        "\u05e4\u05d3\u05e8\u05d5"
    ],
    "name:nah_x_preferred":[
        "Pedro"
    ],
    "name:nld_x_preferred":[
        "Pedro"
    ],
    "name:spa_x_preferred":[
        "Pedro"
    ],
    "name:ukr_x_preferred":[
        "\u041f\u0435\u0434\u0440\u043e"
    ],
    "wof:name":"Pedro",
    "wof:placetype":"locality"
},
  "geometry": {"coordinates":[36.18556,-17.10333],"type":"Point"}
}