{
  "type": "Feature",
  "properties": {
    "gn:admin1_code":"5",
    "gn:asciiname":"Inhangara",
    "gn:country_code":"MZ",
    "gn:dem":162,
    "gn:feature_class":"P",
    "gn:feature_code":"PPL",
    "gn:name":"Inhangara",
    "gn:population":0,
    "gn:timezone":"Africa/Maputo",
    "iso:country":"MZ",
    "wof:name":"Inhangara",
    "wof:placetype":"locality"
},
  "geometry": {"coordinates":[34.16694,-20.26556],"type":"Point"}
}