{
  "type": "Feature",
  "properties": {
    "gn:admin1_code":"1",
    "gn:asciiname":"Mussa",
    "gn:country_code":"MZ",
    "gn:dem":531,
    "gn:feature_class":"P",
    "gn:feature_code":"PPL",
    "gn:name":"Mussa",
    "gn:population":0,
    "gn:timezone":"Africa/Maputo",
    "iso:country":"MZ",
    "name:cat_x_preferred":[
        "Mussa"
    ],
    "name:ceb_x_preferred":[
        "Mussa"
    ],
    "name:deu_x_preferred":[
        "Mussa"
    ],
    "name:ita_x_preferred":[
        "Mussa"
    ],
    "name:swe_x_preferred":[
        "Mussa"
    ],
    "wof:name":"Mussa",
    "wof:placetype":"locality"
},
  "geometry": {"coordinates":[38.97278,-13.22639],"type":"Point"}
}