{
  "type": "Feature",
  "properties": {
    "gn:admin1_code":"6",
    "gn:asciiname":"Cabo Namirrupa",
    "gn:country_code":"MZ",
    "gn:dem":436,
    "gn:feature_class":"P",
    "gn:feature_code":"PPL",
    "gn:name":"Cabo Namirrupa",
    "gn:population":0,
    "gn:timezone":"Africa/Maputo",
    "iso:country":"MZ",
    "wof:name":"Cabo Namirrupa",
    "wof:placetype":"locality"
},
  "geometry": {"coordinates":[39.49444,-14.57139],"type":"Point"}
}