{
  "type": "Feature",
  "properties": {
    "gn:admin1_code":"10.0",
    "gn:asciiname":"Zimbire",
    "gn:country_code":"MZ",
    "gn:dem":191,
    "gn:feature_class":"P",
    "gn:feature_code":"PPL",
    "gn:name":"Zimbire",
    "gn:population":0,
    "gn:timezone":"Africa/Maputo",
    "iso:country":"MZ",
    "wof:name":"Zimbire",
    "wof:placetype":"locality"
},
  "geometry": {"coordinates":[33.59722,-20.85222000000001],"type":"Point"}
}