{
  "type": "Feature",
  "properties": {
    "gn:admin1_code":"9",
    "gn:asciiname":"Munembo",
    "gn:country_code":"MZ",
    "gn:dem":502,
    "gn:feature_class":"P",
    "gn:feature_code":"PPL",
    "gn:name":"Munembo",
    "gn:population":0,
    "gn:timezone":"Africa/Maputo",
    "iso:country":"MZ",
    "wof:name":"Munembo",
    "wof:placetype":"locality"
},
  "geometry": {"coordinates":[37.69139000000001,-15.77556],"type":"Point"}
}