{
  "type": "Feature",
  "properties": {
    "gn:admin1_code":"0",
    "gn:asciiname":"Chibite",
    "gn:country_code":"MZ",
    "gn:dem":81,
    "gn:feature_class":"P",
    "gn:feature_code":"PPL",
    "gn:name":"Chibite",
    "gn:population":0,
    "gn:timezone":"Africa/Maputo",
    "iso:country":"MZ",
    "wof:name":"Chibite",
    "wof:placetype":"locality"
},
  "geometry": {"coordinates":[32.25,-25.03333],"type":"Point"}
}