{
  "type": "Feature",
  "properties": {
    "gn:admin1_code":"3.0",
    "gn:asciiname":"Tinhebe",
    "gn:country_code":"MZ",
    "gn:dem":154,
    "gn:feature_class":"P",
    "gn:feature_code":"PPL",
    "gn:name":"Tinhebe",
    "gn:population":0,
    "gn:timezone":"Africa/Maputo",
    "iso:country":"MZ",
    "wof:name":"Tinhebe",
    "wof:placetype":"locality"
},
  "geometry": {"coordinates":[34.37194,-22.75444],"type":"Point"}
}