{
  "type": "Feature",
  "properties": {
    "gn:admin1_code":"7",
    "gn:asciiname":"Aldeia Ute",
    "gn:country_code":"MZ",
    "gn:dem":1117,
    "gn:feature_class":"P",
    "gn:feature_code":"PPL",
    "gn:name":"Aldeia Ute",
    "gn:population":0,
    "gn:timezone":"Africa/Maputo",
    "iso:country":"MZ",
    "wof:name":"Aldeia Ute",
    "wof:placetype":"locality"
},
  "geometry": {"coordinates":[35.39389,-13.43611],"type":"Point"}
}