{
  "type": "Feature",
  "properties": {
    "gn:admin1_code":"2",
    "gn:asciiname":"Chiqueto",
    "gn:country_code":"MZ",
    "gn:dem":136,
    "gn:feature_class":"P",
    "gn:feature_code":"PPL",
    "gn:name":"Chiqueto",
    "gn:population":0,
    "gn:timezone":"Africa/Maputo",
    "iso:country":"MZ",
    "wof:name":"Chiqueto",
    "wof:placetype":"locality"
},
  "geometry": {"coordinates":[32.7775,-21.48694],"type":"Point"}
}