{
  "type": "Feature",
  "properties": {
    "gn:admin1_code":"3",
    "gn:asciiname":"Fainda",
    "gn:country_code":"MZ",
    "gn:dem":155,
    "gn:feature_class":"P",
    "gn:feature_code":"PPL",
    "gn:name":"Fainda",
    "gn:population":0,
    "gn:timezone":"Africa/Maputo",
    "iso:country":"MZ",
    "wof:name":"Fainda",
    "wof:placetype":"locality"
},
  "geometry": {"coordinates":[34.42028,-21.92],"type":"Point"}
}