{
  "type": "Feature",
  "properties": {
    "gn:admin1_code":"10",
    "gn:asciiname":"Muchoioio",
    "gn:cc2":"MZ",
    "gn:country_code":"MZ",
    "gn:dem":152,
    "gn:feature_class":"P",
    "gn:feature_code":"PPL",
    "gn:name":"Muchoioio",
    "gn:population":0,
    "gn:timezone":"Africa/Maputo",
    "iso:country":"MZ",
    "name:und_x_variant":[
        "Muchoioto",
        "Muchoioio"
    ],
    "wof:name":"Muchoioio",
    "wof:placetype":"locality"
},
  "geometry": {"coordinates":[33.34472,-20.02222],"type":"Point"}
}