{
  "type": "Feature",
  "properties": {
    "gn:admin1_code":"9",
    "gn:asciiname":"Chefe Turromela",
    "gn:country_code":"MZ",
    "gn:dem":521,
    "gn:feature_class":"P",
    "gn:feature_code":"PPL",
    "gn:name":"Chefe Turromela",
    "gn:population":0,
    "gn:timezone":"Africa/Maputo",
    "iso:country":"MZ",
    "wof:name":"Chefe Turromela",
    "wof:placetype":"locality"
},
  "geometry": {"coordinates":[36.94194,-15.94444],"type":"Point"}
}