{
  "type": "Feature",
  "properties": {
    "gn:admin1_code":"6.0",
    "gn:asciiname":"Ussemane",
    "gn:country_code":"MZ",
    "gn:dem":24,
    "gn:feature_class":"P",
    "gn:feature_code":"PPL",
    "gn:name":"Ussemane",
    "gn:population":0,
    "gn:timezone":"Africa/Maputo",
    "iso:country":"MZ",
    "wof:name":"Ussemane",
    "wof:placetype":"locality"
},
  "geometry": {"coordinates":[40.63556,-15.01472],"type":"Point"}
}