{
  "type": "Feature",
  "properties": {
    "gn:admin1_code":"1",
    "gn:asciiname":"Guenda",
    "gn:country_code":"MZ",
    "gn:dem":128,
    "gn:feature_class":"P",
    "gn:feature_code":"PPL",
    "gn:name":"Guenda",
    "gn:population":0,
    "gn:timezone":"Africa/Maputo",
    "iso:country":"MZ",
    "wof:name":"Guenda",
    "wof:placetype":"locality"
},
  "geometry": {"coordinates":[40.02444000000001,-12.65083],"type":"Point"}
}