{
  "type": "Feature",
  "properties": {
    "gn:admin1_code":"6",
    "gn:asciiname":"Rupaliua",
    "gn:country_code":"MZ",
    "gn:dem":549,
    "gn:feature_class":"P",
    "gn:feature_code":"PPL",
    "gn:name":"Rupaliua",
    "gn:population":0,
    "gn:timezone":"Africa/Maputo",
    "iso:country":"MZ",
    "wof:name":"Rupaliua",
    "wof:placetype":"locality"
},
  "geometry": {"coordinates":[38.73722,-14.58361],"type":"Point"}
}