{
  "type": "Feature",
  "properties": {
    "gn:admin1_code":"0",
    "gn:asciiname":"Netete",
    "gn:country_code":"MZ",
    "gn:dem":176,
    "gn:feature_class":"P",
    "gn:feature_code":"PPL",
    "gn:name":"Netete",
    "gn:population":0,
    "gn:timezone":"Africa/Maputo",
    "iso:country":"MZ",
    "wof:name":"Netete",
    "wof:placetype":"locality"
},
  "geometry": {"coordinates":[39.43333,-15.76667],"type":"Point"}
}