{
  "type": "Feature",
  "properties": {
    "gn:admin1_code":"8",
    "gn:asciiname":"Mufa",
    "gn:country_code":"MZ",
    "gn:dem":131,
    "gn:feature_class":"P",
    "gn:feature_code":"PPL",
    "gn:name":"Mufa",
    "gn:population":0,
    "gn:timezone":"Africa/Maputo",
    "iso:country":"MZ",
    "wof:name":"Mufa",
    "wof:placetype":"locality"
},
  "geometry": {"coordinates":[33.45583,-16.07806],"type":"Point"}
}