{
  "type": "Feature",
  "properties": {
    "gn:admin1_code":"3.0",
    "gn:asciiname":"Velanjane",
    "gn:country_code":"MZ",
    "gn:dem":22,
    "gn:feature_class":"P",
    "gn:feature_code":"PPL",
    "gn:name":"Velanjane",
    "gn:population":0,
    "gn:timezone":"Africa/Maputo",
    "iso:country":"MZ",
    "wof:name":"Velanjane",
    "wof:placetype":"locality"
},
  "geometry": {"coordinates":[35.07806,-21.60417],"type":"Point"}
}