{
  "type": "Feature",
  "properties": {
    "gn:admin1_code":"1",
    "gn:asciiname":"Cocounho",
    "gn:country_code":"MZ",
    "gn:dem":279,
    "gn:feature_class":"P",
    "gn:feature_code":"PPL",
    "gn:name":"Cocounho",
    "gn:population":0,
    "gn:timezone":"Africa/Maputo",
    "iso:country":"MZ",
    "wof:name":"Cocounho",
    "wof:placetype":"locality"
},
  "geometry": {"coordinates":[39.67889,-13.55389],"type":"Point"}
}