{
  "type": "Feature",
  "properties": {
    "gn:admin1_code":"2",
    "gn:asciiname":"Guidione",
    "gn:country_code":"MZ",
    "gn:dem":76,
    "gn:feature_class":"P",
    "gn:feature_code":"PPL",
    "gn:name":"Guidione",
    "gn:population":0,
    "gn:timezone":"Africa/Maputo",
    "iso:country":"MZ",
    "wof:name":"Guidione",
    "wof:placetype":"locality"
},
  "geometry": {"coordinates":[33.1725,-24.90833],"type":"Point"}
}