{
  "type": "Feature",
  "properties": {
    "gn:admin1_code":"2",
    "gn:asciiname":"Maguava",
    "gn:country_code":"MZ",
    "gn:dem":10,
    "gn:feature_class":"P",
    "gn:feature_code":"PPL",
    "gn:name":"Maguava",
    "gn:population":0,
    "gn:timezone":"Africa/Maputo",
    "iso:country":"MZ",
    "wof:name":"Maguava",
    "wof:placetype":"locality"
},
  "geometry": {"coordinates":[33.49056,-24.70139],"type":"Point"}
}