{
  "type": "Feature",
  "properties": {
    "gn:admin1_code":"7",
    "gn:asciiname":"Lussanhando",
    "gn:country_code":"MZ",
    "gn:dem":1225,
    "gn:feature_class":"P",
    "gn:feature_code":"PPL",
    "gn:name":"Lussanhando",
    "gn:population":0,
    "gn:timezone":"Africa/Maputo",
    "iso:country":"MZ",
    "wof:name":"Lussanhando",
    "wof:placetype":"locality"
},
  "geometry": {"coordinates":[35.28277999999999,-13.18861],"type":"Point"}
}