{
  "type": "Feature",
  "properties": {
    "gn:admin1_code":"9",
    "gn:asciiname":"Mutala",
    "gn:country_code":"MZ",
    "gn:dem":517,
    "gn:feature_class":"P",
    "gn:feature_code":"PPL",
    "gn:name":"Mutala",
    "gn:population":0,
    "gn:timezone":"Africa/Maputo",
    "iso:country":"MZ",
    "wof:name":"Mutala",
    "wof:placetype":"locality"
},
  "geometry": {"coordinates":[37.85333,-15.91667],"type":"Point"}
}