{
  "type": "Feature",
  "properties": {
    "gn:admin1_code":"6.0",
    "gn:asciiname":"Vita",
    "gn:cc2":"MZ",
    "gn:country_code":"MZ",
    "gn:dem":200,
    "gn:feature_class":"P",
    "gn:feature_code":"PPL",
    "gn:name":"Vita",
    "gn:population":0,
    "gn:timezone":"Africa/Maputo",
    "iso:country":"MZ",
    "name:aze_x_preferred":[
        "Vita"
    ],
    "name:cat_x_preferred":[
        "Vita"
    ],
    "name:ceb_x_preferred":[
        "Vita"
    ],
    "name:deu_x_preferred":[
        "Vita"
    ],
    "name:ell_x_preferred":[
        "\u0396\u03c9\u03ae"
    ],
    "name:eus_x_preferred":[
        "Vita"
    ],
    "name:fas_x_preferred":[
        "\u0648\u06cc\u062a\u0627"
    ],
    "name:fin_x_preferred":[
        "Vita"
    ],
    "name:fra_x_preferred":[
        "Vita"
    ],
    "name:glg_x_preferred":[
        "Vita"
    ],
    "name:hun_x_preferred":[
        "Vita"
    ],
    "name:ita_x_preferred":[
        "Vita"
    ],
    "name:jpn_x_preferred":[
        "\u30f4\u30a3\u30fc\u30bf"
    ],
    "name:lav_x_preferred":[
        "Vita"
    ],
    "name:msa_x_preferred":[
        "Vita"
    ],
    "name:nld_x_preferred":[
        "Vita"
    ],
    "name:pol_x_preferred":[
        "Vita"
    ],
    "name:por_x_preferred":[
        "Vita"
    ],
    "name:rus_x_preferred":[
        "\u0412\u0438\u0442\u0430"
    ],
    "name:scn_x_preferred":[
        "Vita"
    ],
    "name:slv_x_preferred":[
        "Vita"
    ],
    "name:spa_x_preferred":[
        "Vita"
    ],
    "name:swe_x_preferred":[
        "Vita"
    ],
    "name:ukr_x_preferred":[
        "\u0412\u0456\u0442\u0430"
    ],
    "name:und_x_variant":[
        "Vlta",
        "Vita"
    ],
    "name:vie_x_preferred":[
        "Vita"
    ],
    "name:war_x_preferred":[
        "Vita"
    ],
    "name:zho_x_preferred":[
        "Vita"
    ],
    "wof:name":"Vita",
    "wof:placetype":"locality"
},
  "geometry": {"coordinates":[40.32972,-14.52861],"type":"Point"}
}