{
  "type": "Feature",
  "properties": {
    "gn:admin1_code":"6.0",
    "gn:asciiname":"Vita",
    "gn:cc2":"MZ",
    "gn:country_code":"MZ",
    "gn:dem":200,
    "gn:feature_class":"P",
    "gn:feature_code":"PPL",
    "gn:name":"Vita",
    "gn:population":0,
    "gn:timezone":"Africa/Maputo",
    "iso:country":"MZ",
    "name:und_x_variant":[
        "Vlta",
        "Vita"
    ],
    "wof:name":"Vita",
    "wof:placetype":"locality"
},
  "geometry": {"coordinates":[40.32972,-14.52861],"type":"Point"}
}