{
  "type": "Feature",
  "properties": {
    "gn:admin1_code":"9",
    "gn:asciiname":"Mecolome",
    "gn:country_code":"MZ",
    "gn:dem":259,
    "gn:feature_class":"P",
    "gn:feature_code":"PPL",
    "gn:name":"Mec\u00f3lom\u00e8",
    "gn:population":0,
    "gn:timezone":"Africa/Maputo",
    "iso:country":"MZ",
    "wof:name":"Mecolome",
    "wof:placetype":"locality"
},
  "geometry": {"coordinates":[38.00583,-16.22611],"type":"Point"}
}