{
  "type": "Feature",
  "properties": {
    "gn:admin1_code":"9",
    "gn:asciiname":"Antonio",
    "gn:country_code":"MZ",
    "gn:dem":219,
    "gn:feature_class":"P",
    "gn:feature_code":"PPL",
    "gn:name":"Ant\u00f3nio",
    "gn:population":0,
    "gn:timezone":"Africa/Maputo",
    "iso:country":"MZ",
    "wof:name":"Antonio",
    "wof:placetype":"locality"
},
  "geometry": {"coordinates":[37.08444,-16.68639],"type":"Point"}
}