{
  "type": "Feature",
  "properties": {
    "gn:admin1_code":"4.0",
    "gn:asciiname":"Salambe",
    "gn:country_code":"MZ",
    "gn:dem":195,
    "gn:feature_class":"P",
    "gn:feature_code":"PPL",
    "gn:name":"Salambe",
    "gn:population":0,
    "gn:timezone":"Africa/Maputo",
    "iso:country":"MZ",
    "wof:name":"Salambe",
    "wof:placetype":"locality"
},
  "geometry": {"coordinates":[32.05,-25.21667],"type":"Point"}
}