{
  "type": "Feature",
  "properties": {
    "gn:admin1_code":"1",
    "gn:asciiname":"Amice",
    "gn:country_code":"MZ",
    "gn:dem":68,
    "gn:feature_class":"P",
    "gn:feature_code":"PPL",
    "gn:name":"Amice",
    "gn:population":0,
    "gn:timezone":"Africa/Maputo",
    "iso:country":"MZ",
    "name:bel_x_preferred":[
        "\u0413\u0443\u043c\u0435\u0440\u0430\u043b"
    ],
    "name:ces_x_preferred":[
        "Humer\u00e1l"
    ],
    "name:deu_x_preferred":[
        "Amikt"
    ],
    "name:eml_x_preferred":[
        "Am\u00ect"
    ],
    "name:epo_x_preferred":[
        "Amikto"
    ],
    "name:fin_x_preferred":[
        "Amikti"
    ],
    "name:fra_x_preferred":[
        "Amict"
    ],
    "name:hrv_x_preferred":[
        "Amikt"
    ],
    "name:ind_x_preferred":[
        "Amik"
    ],
    "name:ita_x_preferred":[
        "Amitto"
    ],
    "name:kor_x_preferred":[
        "\uac1c\ub450\ud3ec"
    ],
    "name:lat_x_preferred":[
        "Amictus liturgicus"
    ],
    "name:nld_x_preferred":[
        "Amict"
    ],
    "name:nor_x_preferred":[
        "Amikt"
    ],
    "name:pol_x_preferred":[
        "Humera\u0142"
    ],
    "name:por_x_preferred":[
        "Amito"
    ],
    "name:rus_x_preferred":[
        "\u0410\u043c\u0438\u043a\u0442"
    ],
    "name:spa_x_preferred":[
        "Amito"
    ],
    "name:swa_x_preferred":[
        "Amikto"
    ],
    "name:swe_x_preferred":[
        "Halslin"
    ],
    "name:ukr_x_preferred":[
        "\u0410\u043c\u0456\u043a\u0442"
    ],
    "name:zho_x_preferred":[
        "\u65b9\u9818\u5dfe"
    ],
    "wof:name":"Amice",
    "wof:placetype":"locality"
},
  "geometry": {"coordinates":[40.36694,-12.44417],"type":"Point"}
}