{
  "type": "Feature",
  "properties": {
    "gn:admin1_code":"1",
    "gn:asciiname":"Amice",
    "gn:country_code":"MZ",
    "gn:dem":68,
    "gn:feature_class":"P",
    "gn:feature_code":"PPL",
    "gn:name":"Amice",
    "gn:population":0,
    "gn:timezone":"Africa/Maputo",
    "iso:country":"MZ",
    "wof:name":"Amice",
    "wof:placetype":"locality"
},
  "geometry": {"coordinates":[40.36694,-12.44417],"type":"Point"}
}