{
  "type": "Feature",
  "properties": {
    "gn:admin1_code":"2.0",
    "gn:asciiname":"Chefe Dolene",
    "gn:country_code":"MZ",
    "gn:dem":45,
    "gn:feature_class":"P",
    "gn:feature_code":"PPL",
    "gn:name":"Chefe Dolene",
    "gn:population":0,
    "gn:timezone":"Africa/Maputo",
    "iso:country":"MZ",
    "wof:name":"Chefe Dolene",
    "wof:placetype":"locality"
},
  "geometry": {"coordinates":[34.13028,-24.82806],"type":"Point"}
}