{
  "type": "Feature",
  "properties": {
    "gn:admin1_code":"9",
    "gn:asciiname":"Arijuane",
    "gn:country_code":"MZ",
    "gn:dem":78,
    "gn:feature_class":"P",
    "gn:feature_code":"PPL",
    "gn:name":"Arijuane",
    "gn:population":0,
    "gn:timezone":"Africa/Maputo",
    "iso:country":"MZ",
    "wof:name":"Arijuane",
    "wof:placetype":"locality"
},
  "geometry": {"coordinates":[37.30917,-17.28917],"type":"Point"}
}