{
  "type": "Feature",
  "properties": {
    "gn:admin1_code":"2.0",
    "gn:asciiname":"Macanhane",
    "gn:country_code":"MZ",
    "gn:dem":145,
    "gn:feature_class":"P",
    "gn:feature_code":"PPL",
    "gn:name":"Macanhane",
    "gn:population":0,
    "gn:timezone":"Africa/Maputo",
    "iso:country":"MZ",
    "wof:name":"Macanhane",
    "wof:placetype":"locality"
},
  "geometry": {"coordinates":[32.55860999999999,-23.21306],"type":"Point"}
}