{
  "type": "Feature",
  "properties": {
    "gn:admin1_code":"9",
    "gn:asciiname":"Namecumua",
    "gn:country_code":"MZ",
    "gn:dem":686,
    "gn:feature_class":"P",
    "gn:feature_code":"PPL",
    "gn:name":"Namec\u00famua",
    "gn:population":0,
    "gn:timezone":"Africa/Maputo",
    "iso:country":"MZ",
    "wof:name":"Namecumua",
    "wof:placetype":"locality"
},
  "geometry": {"coordinates":[36.31556,-15.78944],"type":"Point"}
}