{
  "type": "Feature",
  "properties": {
    "gn:admin1_code":"0",
    "gn:asciiname":"Foia",
    "gn:country_code":"MZ",
    "gn:dem":426,
    "gn:feature_class":"P",
    "gn:feature_code":"PPL",
    "gn:name":"Foia",
    "gn:population":0,
    "gn:timezone":"Africa/Maputo",
    "iso:country":"MZ",
    "name:por_x_preferred":[
        "Foia"
    ],
    "wof:name":"Foia",
    "wof:placetype":"locality"
},
  "geometry": {"coordinates":[31.46667,-16.03333],"type":"Point"}
}