{
  "type": "Feature",
  "properties": {
    "gn:admin1_code":"4",
    "gn:asciiname":"Cutane",
    "gn:country_code":"MZ",
    "gn:dem":18,
    "gn:feature_class":"P",
    "gn:feature_code":"PPL",
    "gn:name":"Cutane",
    "gn:population":0,
    "gn:timezone":"Africa/Maputo",
    "iso:country":"MZ",
    "wof:name":"Cutane",
    "wof:placetype":"locality"
},
  "geometry": {"coordinates":[32.92472,-25.09111],"type":"Point"}
}