{
  "type": "Feature",
  "properties": {
    "gn:admin1_code":"10",
    "gn:asciiname":"Bomo",
    "gn:country_code":"MZ",
    "gn:dem":599,
    "gn:feature_class":"P",
    "gn:feature_code":"PPL",
    "gn:name":"Bomo",
    "gn:population":0,
    "gn:timezone":"Africa/Maputo",
    "iso:country":"MZ",
    "wof:name":"Bomo",
    "wof:placetype":"locality"
},
  "geometry": {"coordinates":[33.20667,-18.14861],"type":"Point"}
}