{
  "type": "Feature",
  "properties": {
    "gn:admin1_code":"6",
    "gn:asciiname":"Reco",
    "gn:country_code":"MZ",
    "gn:dem":50,
    "gn:feature_class":"P",
    "gn:feature_code":"PPL",
    "gn:name":"Rec\u00f3",
    "gn:population":0,
    "gn:timezone":"Africa/Maputo",
    "iso:country":"MZ",
    "wof:name":"Reco",
    "wof:placetype":"locality"
},
  "geometry": {"coordinates":[40.20361,-15.65444],"type":"Point"}
}