{
  "type": "Feature",
  "properties": {
    "gn:admin1_code":"2",
    "gn:asciiname":"Jamite",
    "gn:country_code":"MZ",
    "gn:dem":45,
    "gn:feature_class":"P",
    "gn:feature_code":"PPL",
    "gn:name":"Jamite",
    "gn:population":0,
    "gn:timezone":"Africa/Maputo",
    "iso:country":"MZ",
    "wof:name":"Jamite",
    "wof:placetype":"locality"
},
  "geometry": {"coordinates":[33.46472,-24.92028],"type":"Point"}
}