{
  "type": "Feature",
  "properties": {
    "gn:admin1_code":"9.0",
    "gn:asciiname":"Chefe Intinha",
    "gn:country_code":"MZ",
    "gn:dem":246,
    "gn:feature_class":"P",
    "gn:feature_code":"PPL",
    "gn:name":"Chefe Intinha",
    "gn:population":0,
    "gn:timezone":"Africa/Maputo",
    "iso:country":"MZ",
    "wof:name":"Chefe Intinha",
    "wof:placetype":"locality"
},
  "geometry": {"coordinates":[37.12528,-16.45111],"type":"Point"}
}