{
  "type": "Feature",
  "properties": {
    "gn:admin1_code":"2.0",
    "gn:asciiname":"Machoane",
    "gn:country_code":"MZ",
    "gn:dem":55,
    "gn:feature_class":"P",
    "gn:feature_code":"PPL",
    "gn:name":"Machoane",
    "gn:population":0,
    "gn:timezone":"Africa/Maputo",
    "iso:country":"MZ",
    "wof:name":"Machoane",
    "wof:placetype":"locality"
},
  "geometry": {"coordinates":[33.22472,-23.95917],"type":"Point"}
}