{
  "type": "Feature",
  "properties": {
    "gn:admin1_code":"0.0",
    "gn:asciiname":"Xaue",
    "gn:country_code":"MZ",
    "gn:dem":21,
    "gn:feature_class":"P",
    "gn:feature_code":"PPL",
    "gn:name":"Xau\u00e9",
    "gn:population":0,
    "gn:timezone":"Africa/Maputo",
    "iso:country":"MZ",
    "wof:name":"Xaue",
    "wof:placetype":"locality"
},
  "geometry": {"coordinates":[34.45,-19.16667],"type":"Point"}
}