{
  "type": "Feature",
  "properties": {
    "gn:admin1_code":"5",
    "gn:asciiname":"M'sucossa",
    "gn:country_code":"MZ",
    "gn:dem":520,
    "gn:feature_class":"P",
    "gn:feature_code":"PPL",
    "gn:name":"M\u2019sucossa",
    "gn:population":0,
    "gn:timezone":"Africa/Maputo",
    "iso:country":"MZ",
    "wof:name":"M'sucossa",
    "wof:placetype":"locality"
},
  "geometry": {"coordinates":[34.07722,-18.55778],"type":"Point"}
}