{
  "type": "Feature",
  "properties": {
    "gn:admin1_code":"0",
    "gn:asciiname":"Metiquia",
    "gn:country_code":"MZ",
    "gn:dem":341,
    "gn:feature_class":"P",
    "gn:feature_code":"PPL",
    "gn:name":"Metiquia",
    "gn:population":0,
    "gn:timezone":"Africa/Maputo",
    "iso:country":"MZ",
    "wof:name":"Metiquia",
    "wof:placetype":"locality"
},
  "geometry": {"coordinates":[39.45,-14.06667],"type":"Point"}
}