{
  "type": "Feature",
  "properties": {
    "gn:admin1_code":"4",
    "gn:asciiname":"Matongomane",
    "gn:country_code":"MZ",
    "gn:dem":69,
    "gn:feature_class":"P",
    "gn:feature_code":"PPL",
    "gn:name":"Matongomane",
    "gn:population":0,
    "gn:timezone":"Africa/Maputo",
    "iso:country":"MZ",
    "wof:name":"Matongomane",
    "wof:placetype":"locality"
},
  "geometry": {"coordinates":[32.49361,-24.7725],"type":"Point"}
}