{
  "type": "Feature",
  "properties": {
    "gn:admin1_code":"8",
    "gn:asciiname":"Mutarara",
    "gn:country_code":"MZ",
    "gn:dem":66,
    "gn:feature_class":"P",
    "gn:feature_code":"PPL",
    "gn:name":"Mutarara",
    "gn:population":0,
    "gn:timezone":"Africa/Maputo",
    "iso:country":"MZ",
    "wof:name":"Mutarara",
    "wof:placetype":"locality"
},
  "geometry": {"coordinates":[35.07389000000001,-17.44],"type":"Point"}
}