{
  "type": "Feature",
  "properties": {
    "gn:admin1_code":"10",
    "gn:asciiname":"Machaze",
    "gn:country_code":"MZ",
    "gn:dem":261,
    "gn:feature_class":"P",
    "gn:feature_code":"PPL",
    "gn:name":"Machaze",
    "gn:population":0,
    "gn:timezone":"Africa/Maputo",
    "iso:country":"MZ",
    "wof:name":"Machaze",
    "wof:placetype":"locality"
},
  "geometry": {"coordinates":[33.40417,-20.80389],"type":"Point"}
}