{
  "type": "Feature",
  "properties": {
    "gn:admin1_code":"6",
    "gn:asciiname":"Agostinho",
    "gn:country_code":"MZ",
    "gn:dem":7,
    "gn:feature_class":"P",
    "gn:feature_code":"PPL",
    "gn:name":"Agostinho",
    "gn:population":0,
    "gn:timezone":"Africa/Maputo",
    "iso:country":"MZ",
    "name:por_x_preferred":[
        "Agostinho"
    ],
    "wof:name":"Agostinho",
    "wof:placetype":"locality"
},
  "geometry": {"coordinates":[40.14333,-15.91028],"type":"Point"}
}