{
  "type": "Feature",
  "properties": {
    "gn:admin1_code":"3.0",
    "gn:asciiname":"Lazaro",
    "gn:country_code":"MZ",
    "gn:dem":126,
    "gn:feature_class":"P",
    "gn:feature_code":"PPL",
    "gn:name":"L\u00e1zaro",
    "gn:population":0,
    "gn:timezone":"Africa/Maputo",
    "iso:country":"MZ",
    "wof:name":"Lazaro",
    "wof:placetype":"locality"
},
  "geometry": {"coordinates":[34.17583,-22.53361],"type":"Point"}
}