{
  "type": "Feature",
  "properties": {
    "gn:admin1_code":"3.0",
    "gn:asciiname":"Dimba",
    "gn:country_code":"MZ",
    "gn:dem":145,
    "gn:feature_class":"P",
    "gn:feature_code":"PPL",
    "gn:name":"Dimba",
    "gn:population":0,
    "gn:timezone":"Africa/Maputo",
    "iso:country":"MZ",
    "name:ara_x_preferred":[
        "\u062f\u064a\u0645\u0628\u0627"
    ],
    "name:azb_x_preferred":[
        "\u062f\u06cc\u0645\u0628\u0627"
    ],
    "name:bul_x_preferred":[
        "\u0414\u0438\u043c\u0431\u0430"
    ],
    "name:deu_x_preferred":[
        "Dimba"
    ],
    "name:fas_x_preferred":[
        "\u062f\u06cc\u0645\u0628\u0627"
    ],
    "name:fra_x_preferred":[
        "Dimba"
    ],
    "name:ita_x_preferred":[
        "Dimba"
    ],
    "name:pol_x_preferred":[
        "Dimba"
    ],
    "name:por_x_preferred":[
        "Dimba"
    ],
    "name:tgk_x_preferred":[
        "\u0414\u0438\u043c\u0431\u0430"
    ],
    "name:vie_x_preferred":[
        "Dimba"
    ],
    "wof:name":"Dimba",
    "wof:placetype":"locality"
},
  "geometry": {"coordinates":[34.21972,-21.81417],"type":"Point"}
}