{
  "type": "Feature",
  "properties": {
    "gn:admin1_code":"10",
    "gn:asciiname":"Mazechita",
    "gn:country_code":"MZ",
    "gn:dem":210,
    "gn:feature_class":"P",
    "gn:feature_code":"PPL",
    "gn:name":"Mazechita",
    "gn:population":0,
    "gn:timezone":"Africa/Maputo",
    "iso:country":"MZ",
    "wof:name":"Mazechita",
    "wof:placetype":"locality"
},
  "geometry": {"coordinates":[33.66583,-20.735],"type":"Point"}
}