{
  "type": "Feature",
  "properties": {
    "gn:admin1_code":"2.0",
    "gn:asciiname":"Muaqueleluane",
    "gn:country_code":"MZ",
    "gn:dem":82,
    "gn:feature_class":"P",
    "gn:feature_code":"PPL",
    "gn:name":"Muaqueleluane",
    "gn:population":0,
    "gn:timezone":"Africa/Maputo",
    "iso:country":"MZ",
    "wof:name":"Muaqueleluane",
    "wof:placetype":"locality"
},
  "geometry": {"coordinates":[33.44611,-22.71139],"type":"Point"}
}