{
  "type": "Feature",
  "properties": {
    "gn:admin1_code":"9",
    "gn:asciiname":"Jone",
    "gn:country_code":"MZ",
    "gn:dem":300,
    "gn:feature_class":"P",
    "gn:feature_code":"PPL",
    "gn:name":"Jone",
    "gn:population":0,
    "gn:timezone":"Africa/Maputo",
    "iso:country":"MZ",
    "wof:name":"Jone",
    "wof:placetype":"locality"
},
  "geometry": {"coordinates":[37.16917,-16.3575],"type":"Point"}
}