{
  "type": "Feature",
  "properties": {
    "gn:admin1_code":"10.0",
    "gn:asciiname":"Choa",
    "gn:country_code":"MZ",
    "gn:dem":1425,
    "gn:feature_class":"P",
    "gn:feature_code":"PPL",
    "gn:name":"Choa",
    "gn:population":0,
    "gn:timezone":"Africa/Maputo",
    "iso:country":"MZ",
    "wof:name":"Choa",
    "wof:placetype":"locality"
},
  "geometry": {"coordinates":[33.0125,-18.04111],"type":"Point"}
}