{
  "type": "Feature",
  "properties": {
    "gn:admin1_code":"5",
    "gn:asciiname":"Maringue",
    "gn:country_code":"MZ",
    "gn:dem":204,
    "gn:feature_class":"P",
    "gn:feature_code":"PPL",
    "gn:name":"Maringue",
    "gn:population":0,
    "gn:timezone":"Africa/Maputo",
    "iso:country":"MZ",
    "wof:name":"Maringue",
    "wof:placetype":"locality"
},
  "geometry": {"coordinates":[34.39056,-17.96444],"type":"Point"}
}