{
  "type": "Feature",
  "properties": {
    "gn:admin1_code":"7",
    "gn:asciiname":"Chefe Aiamo",
    "gn:country_code":"MZ",
    "gn:dem":610,
    "gn:feature_class":"P",
    "gn:feature_code":"PPL",
    "gn:name":"Chefe Aiamo",
    "gn:population":0,
    "gn:timezone":"Africa/Maputo",
    "iso:country":"MZ",
    "wof:name":"Chefe Aiamo",
    "wof:placetype":"locality"
},
  "geometry": {"coordinates":[36.72833,-14.38917],"type":"Point"}
}