{
  "type": "Feature",
  "properties": {
    "gn:admin1_code":"1.0",
    "gn:asciiname":"Uapila",
    "gn:country_code":"MZ",
    "gn:dem":344,
    "gn:feature_class":"P",
    "gn:feature_code":"PPL",
    "gn:name":"Uapila",
    "gn:population":0,
    "gn:timezone":"Africa/Maputo",
    "iso:country":"MZ",
    "name:azb_x_preferred":[
        "\u06cc\u0648\u067e\u06cc\u0644\u0627"
    ],
    "name:fas_x_preferred":[
        "\u06cc\u0648\u067e\u06cc\u0644\u0627"
    ],
    "name:urd_x_preferred":[
        "\u06cc\u0648\u0627\u067e\u06cc\u0644\u0627"
    ],
    "wof:name":"Uapila",
    "wof:placetype":"locality"
},
  "geometry": {"coordinates":[39.86667,-12.925],"type":"Point"}
}