{
  "type": "Feature",
  "properties": {
    "gn:admin1_code":"8",
    "gn:asciiname":"Aldeia Chitondo",
    "gn:country_code":"MZ",
    "gn:dem":282,
    "gn:feature_class":"P",
    "gn:feature_code":"PPL",
    "gn:name":"Aldeia Chitondo",
    "gn:population":0,
    "gn:timezone":"Africa/Maputo",
    "iso:country":"MZ",
    "wof:name":"Aldeia Chitondo",
    "wof:placetype":"locality"
},
  "geometry": {"coordinates":[33.07833,-16.5225],"type":"Point"}
}