{
  "type": "Feature",
  "properties": {
    "gn:admin1_code":"1",
    "gn:asciiname":"Rucha",
    "gn:country_code":"MZ",
    "gn:dem":103,
    "gn:feature_class":"P",
    "gn:feature_code":"PPL",
    "gn:name":"Rucha",
    "gn:population":0,
    "gn:timezone":"Africa/Maputo",
    "iso:country":"MZ",
    "wof:name":"Rucha",
    "wof:placetype":"locality"
},
  "geometry": {"coordinates":[40.44194,-12.09278],"type":"Point"}
}