{
  "type": "Feature",
  "properties": {
    "gn:admin1_code":"2.0",
    "gn:asciiname":"Davide",
    "gn:country_code":"MZ",
    "gn:dem":62,
    "gn:feature_class":"P",
    "gn:feature_code":"PPL",
    "gn:name":"Davide",
    "gn:population":0,
    "gn:timezone":"Africa/Maputo",
    "iso:country":"MZ",
    "name:deu_x_preferred":[
        "Davide"
    ],
    "name:ita_x_preferred":[
        "Davide"
    ],
    "name:slv_x_preferred":[
        "Davide"
    ],
    "wof:name":"Davide",
    "wof:placetype":"locality"
},
  "geometry": {"coordinates":[33.25583,-23.90639],"type":"Point"}
}