{
  "type": "Feature",
  "properties": {
    "gn:admin1_code":"7",
    "gn:asciiname":"Aldeia Nkolongue",
    "gn:country_code":"MZ",
    "gn:dem":476,
    "gn:feature_class":"P",
    "gn:feature_code":"PPL",
    "gn:name":"Aldeia Nkolongue",
    "gn:population":0,
    "gn:timezone":"Africa/Maputo",
    "iso:country":"MZ",
    "wof:name":"Aldeia Nkolongue",
    "wof:placetype":"locality"
},
  "geometry": {"coordinates":[34.7625,-12.93806],"type":"Point"}
}