{
  "type": "Feature",
  "properties": {
    "gn:admin1_code":"0",
    "gn:asciiname":"Chigunha",
    "gn:country_code":"MZ",
    "gn:dem":105,
    "gn:feature_class":"P",
    "gn:feature_code":"PPL",
    "gn:name":"Chigunha",
    "gn:population":0,
    "gn:timezone":"Africa/Maputo",
    "iso:country":"MZ",
    "wof:name":"Chigunha",
    "wof:placetype":"locality"
},
  "geometry": {"coordinates":[34.05,-21.16667],"type":"Point"}
}