{
  "type": "Feature",
  "properties": {
    "gn:admin1_code":"7",
    "gn:asciiname":"Neruculo",
    "gn:country_code":"MZ",
    "gn:dem":725,
    "gn:feature_class":"P",
    "gn:feature_code":"PPL",
    "gn:name":"Neruculo",
    "gn:population":0,
    "gn:timezone":"Africa/Maputo",
    "iso:country":"MZ",
    "wof:name":"Neruculo",
    "wof:placetype":"locality"
},
  "geometry": {"coordinates":[35.98194,-13.61861],"type":"Point"}
}