{
  "type": "Feature",
  "properties": {
    "gn:admin1_code":"7",
    "gn:asciiname":"Corota",
    "gn:cc2":"MZ",
    "gn:country_code":"MZ",
    "gn:dem":620,
    "gn:feature_class":"P",
    "gn:feature_code":"PPL",
    "gn:name":"Corota",
    "gn:population":0,
    "gn:timezone":"Africa/Maputo",
    "iso:country":"MZ",
    "name:und_x_variant":[
        "Carota",
        "Corota"
    ],
    "wof:name":"Corota",
    "wof:placetype":"locality"
},
  "geometry": {"coordinates":[36.52139,-13.3875],"type":"Point"}
}