{
  "type": "Feature",
  "properties": {
    "gn:admin1_code":"1",
    "gn:asciiname":"Madonda",
    "gn:country_code":"MZ",
    "gn:dem":572,
    "gn:feature_class":"P",
    "gn:feature_code":"PPL",
    "gn:name":"Madonda",
    "gn:population":0,
    "gn:timezone":"Africa/Maputo",
    "iso:country":"MZ",
    "wof:name":"Madonda",
    "wof:placetype":"locality"
},
  "geometry": {"coordinates":[39.79056,-11.71417],"type":"Point"}
}