{
  "type": "Feature",
  "properties": {
    "gn:admin1_code":"9",
    "gn:asciiname":"Peha",
    "gn:country_code":"MZ",
    "gn:dem":27,
    "gn:feature_class":"P",
    "gn:feature_code":"PPL",
    "gn:name":"Peha",
    "gn:population":0,
    "gn:timezone":"Africa/Maputo",
    "iso:country":"MZ",
    "name:bul_x_preferred":[
        "\u041f\u0435\u0445\u0430"
    ],
    "name:fra_x_preferred":[
        "Peha"
    ],
    "name:pol_x_preferred":[
        "Peha"
    ],
    "name:rus_x_preferred":[
        "Peha"
    ],
    "name:slk_x_preferred":[
        "Peha"
    ],
    "name:ukr_x_preferred":[
        "Peha"
    ],
    "wof:name":"Peha",
    "wof:placetype":"locality"
},
  "geometry": {"coordinates":[37.84083,-17.20333],"type":"Point"}
}