{
  "type": "Feature",
  "properties": {
    "gn:admin1_code":"10",
    "gn:asciiname":"Matararique",
    "gn:country_code":"MZ",
    "gn:dem":692,
    "gn:feature_class":"P",
    "gn:feature_code":"PPL",
    "gn:name":"Matararique",
    "gn:population":0,
    "gn:timezone":"Africa/Maputo",
    "iso:country":"MZ",
    "wof:name":"Matararique",
    "wof:placetype":"locality"
},
  "geometry": {"coordinates":[33.46194000000001,-19.14917],"type":"Point"}
}