{
  "type": "Feature",
  "properties": {
    "gn:admin1_code":"0",
    "gn:asciiname":"Cutche",
    "gn:country_code":"MZ",
    "gn:dem":756,
    "gn:feature_class":"P",
    "gn:feature_code":"PPL",
    "gn:name":"Cutche",
    "gn:population":0,
    "gn:timezone":"Africa/Maputo",
    "iso:country":"MZ",
    "wof:name":"Cutche",
    "wof:placetype":"locality"
},
  "geometry": {"coordinates":[35.16667,-16.93333],"type":"Point"}
}