{
  "type": "Feature",
  "properties": {
    "gn:admin1_code":"6",
    "gn:asciiname":"Muma",
    "gn:country_code":"MZ",
    "gn:dem":93,
    "gn:feature_class":"P",
    "gn:feature_code":"PPL",
    "gn:name":"Muma",
    "gn:population":0,
    "gn:timezone":"Africa/Maputo",
    "iso:country":"MZ",
    "name:ceb_x_preferred":[
        "Muma"
    ],
    "name:swe_x_preferred":[
        "Muma"
    ],
    "wof:name":"Muma",
    "wof:placetype":"locality"
},
  "geometry": {"coordinates":[39.97167,-15.71944],"type":"Point"}
}