{
  "type": "Feature",
  "properties": {
    "gn:admin1_code":"10.0",
    "gn:asciiname":"Vuraipingo",
    "gn:country_code":"MZ",
    "gn:dem":632,
    "gn:feature_class":"P",
    "gn:feature_code":"PPL",
    "gn:name":"Vuraipingo",
    "gn:population":0,
    "gn:timezone":"Africa/Maputo",
    "iso:country":"MZ",
    "wof:name":"Vuraipingo",
    "wof:placetype":"locality"
},
  "geometry": {"coordinates":[33.10417,-18.97167],"type":"Point"}
}