{
  "type": "Feature",
  "properties": {
    "gn:admin1_code":"5.0",
    "gn:asciiname":"Zimucacaca",
    "gn:country_code":"MZ",
    "gn:dem":166,
    "gn:feature_class":"P",
    "gn:feature_code":"PPL",
    "gn:name":"Zimucaca\u00e7a",
    "gn:population":0,
    "gn:timezone":"Africa/Maputo",
    "iso:country":"MZ",
    "wof:name":"Zimucacaca",
    "wof:placetype":"locality"
},
  "geometry": {"coordinates":[34.14694,-20.09333],"type":"Point"}
}