{
  "type": "Feature",
  "properties": {
    "gn:admin1_code":"3.0",
    "gn:asciiname":"Saul",
    "gn:country_code":"MZ",
    "gn:dem":63,
    "gn:feature_class":"P",
    "gn:feature_code":"PPL",
    "gn:name":"Sa\u00fal",
    "gn:population":0,
    "gn:timezone":"Africa/Maputo",
    "iso:country":"MZ",
    "name:afr_x_preferred":[
        "Saul"
    ],
    "name:ara_x_preferred":[
        "\u0634\u0627\u0624\u0648\u0644 \u0627\u0644\u0645\u0644\u0643"
    ],
    "name:arz_x_preferred":[
        "\u0634\u0627\u0624\u0644"
    ],
    "name:azb_x_preferred":[
        "\u0637\u0627\u0644\u0648\u062a"
    ],
    "name:bel_x_preferred":[
        "\u0421\u0430\u0443\u043b"
    ],
    "name:bre_x_preferred":[
        "Shaoul"
    ],
    "name:bul_x_preferred":[
        "\u0421\u0430\u0443\u043b"
    ],
    "name:cat_x_preferred":[
        "Sa\u00fcl"
    ],
    "name:ces_x_preferred":[
        "Saul"
    ],
    "name:cym_x_preferred":[
        "Saul"
    ],
    "name:dan_x_preferred":[
        "Kong Saul"
    ],
    "name:deu_x_preferred":[
        "Saul"
    ],
    "name:epo_x_preferred":[
        "\u015caul"
    ],
    "name:eus_x_preferred":[
        "Saul"
    ],
    "name:fas_x_preferred":[
        "\u0637\u0627\u0644\u0648\u062a"
    ],
    "name:fin_x_preferred":[
        "Saul"
    ],
    "name:fra_x_preferred":[
        "Sa\u00fcl"
    ],
    "name:heb_x_preferred":[
        "\u05e9\u05d0\u05d5\u05dc"
    ],
    "name:hrv_x_preferred":[
        "\u0160aul"
    ],
    "name:hye_x_preferred":[
        "\u054d\u0561\u057e\u0578\u0582\u0572"
    ],
    "name:ind_x_preferred":[
        "Saul"
    ],
    "name:ita_x_preferred":[
        "Saul"
    ],
    "name:jpn_x_preferred":[
        "\u30b5\u30a6\u30eb"
    ],
    "name:kat_x_preferred":[
        "\u10e1\u10d0\u10e3\u10da\u10d8"
    ],
    "name:kur_x_preferred":[
        "\u015eaw\u00fbl"
    ],
    "name:lat_x_preferred":[
        "Saul"
    ],
    "name:lav_x_preferred":[
        "Sauls"
    ],
    "name:lit_x_preferred":[
        "Saulius"
    ],
    "name:mal_x_preferred":[
        "\u0d36\u0d57\u0d7d"
    ],
    "name:mlg_x_preferred":[
        "Saoly"
    ],
    "name:msa_x_preferred":[
        "Talut"
    ],
    "name:nld_x_preferred":[
        "Saul"
    ],
    "name:nor_x_preferred":[
        "Saul"
    ],
    "name:oci_x_preferred":[
        "Sa\u00fcl"
    ],
    "name:pol_x_preferred":[
        "Saul"
    ],
    "name:por_x_preferred":[
        "Saul"
    ],
    "name:ron_x_preferred":[
        "Saul"
    ],
    "name:rus_x_preferred":[
        "\u0421\u0430\u0443\u043b"
    ],
    "name:sco_x_preferred":[
        "Saul"
    ],
    "name:slk_x_preferred":[
        "Saul"
    ],
    "name:spa_x_preferred":[
        "Sa\u00fal"
    ],
    "name:srp_x_preferred":[
        "\u0421\u0430\u0443\u043b"
    ],
    "name:swa_x_preferred":[
        "Mfalme Sauli"
    ],
    "name:swe_x_preferred":[
        "Saul"
    ],
    "name:tam_x_preferred":[
        "\u0b9a\u0bb5\u0bc1\u0bb2\u0bcd"
    ],
    "name:tur_x_preferred":[
        "T\u00e2l\u00fbt"
    ],
    "name:ukr_x_preferred":[
        "\u0421\u0430\u0443\u043b"
    ],
    "name:urd_x_preferred":[
        "\u0633\u0627\u0624\u0644"
    ],
    "name:xmf_x_preferred":[
        "\u10e1\u10d0\u10e3\u10da\u10d8"
    ],
    "name:yid_x_preferred":[
        "\u05e9\u05d0\u05d5\u05dc \u05d4\u05de\u05dc\u05da"
    ],
    "name:zho_x_preferred":[
        "\u6383\u7f85\u738b"
    ],
    "wof:name":"Saul",
    "wof:placetype":"locality"
},
  "geometry": {"coordinates":[34.96028,-21.92083],"type":"Point"}
}