{
  "type": "Feature",
  "properties": {
    "gn:admin1_code":"3.0",
    "gn:asciiname":"Saul",
    "gn:country_code":"MZ",
    "gn:dem":63,
    "gn:feature_class":"P",
    "gn:feature_code":"PPL",
    "gn:name":"Sa\u00fal",
    "gn:population":0,
    "gn:timezone":"Africa/Maputo",
    "iso:country":"MZ",
    "wof:name":"Saul",
    "wof:placetype":"locality"
},
  "geometry": {"coordinates":[34.96028,-21.92083],"type":"Point"}
}