{
  "type": "Feature",
  "properties": {
    "gn:admin1_code":"3.0",
    "gn:asciiname":"Zacarias",
    "gn:country_code":"MZ",
    "gn:dem":43,
    "gn:feature_class":"P",
    "gn:feature_code":"PPL",
    "gn:name":"Zacarias",
    "gn:population":0,
    "gn:timezone":"Africa/Maputo",
    "iso:country":"MZ",
    "wof:name":"Zacarias",
    "wof:placetype":"locality"
},
  "geometry": {"coordinates":[35.19944,-22.48639],"type":"Point"}
}