{
  "type": "Feature",
  "properties": {
    "gn:admin1_code":"1.0",
    "gn:asciiname":"T'chivanga",
    "gn:country_code":"MZ",
    "gn:dem":102,
    "gn:feature_class":"P",
    "gn:feature_code":"PPL",
    "gn:name":"T\u2019chivanga",
    "gn:population":0,
    "gn:timezone":"Africa/Maputo",
    "iso:country":"MZ",
    "wof:name":"T'chivanga",
    "wof:placetype":"locality"
},
  "geometry": {"coordinates":[40.24167,-11.84528],"type":"Point"}
}