{
  "type": "Feature",
  "properties": {
    "gn:admin1_code":"10.0",
    "gn:asciiname":"Techecachela",
    "gn:country_code":"MZ",
    "gn:dem":257,
    "gn:feature_class":"P",
    "gn:feature_code":"PPL",
    "gn:name":"Techecachela",
    "gn:population":0,
    "gn:timezone":"Africa/Maputo",
    "iso:country":"MZ",
    "wof:name":"Techecachela",
    "wof:placetype":"locality"
},
  "geometry": {"coordinates":[33.47861,-20.72611],"type":"Point"}
}