{
  "type": "Feature",
  "properties": {
    "gn:admin1_code":"3",
    "gn:asciiname":"Mazuvucane",
    "gn:country_code":"MZ",
    "gn:dem":89,
    "gn:feature_class":"P",
    "gn:feature_code":"PPL",
    "gn:name":"Mazuvucane",
    "gn:population":0,
    "gn:timezone":"Africa/Maputo",
    "iso:country":"MZ",
    "wof:name":"Mazuvucane",
    "wof:placetype":"locality"
},
  "geometry": {"coordinates":[33.29083,-22.53333],"type":"Point"}
}