{
  "type": "Feature",
  "properties": {
    "gn:admin1_code":"3",
    "gn:asciiname":"Maqueme",
    "gn:country_code":"MZ",
    "gn:dem":99,
    "gn:feature_class":"P",
    "gn:feature_code":"PPL",
    "gn:name":"Maqueme",
    "gn:population":0,
    "gn:timezone":"Africa/Maputo",
    "iso:country":"MZ",
    "wof:name":"Maqueme",
    "wof:placetype":"locality"
},
  "geometry": {"coordinates":[33.83889,-22.87611],"type":"Point"}
}