{
  "type": "Feature",
  "properties": {
    "gn:admin1_code":"9",
    "gn:asciiname":"Arijamo",
    "gn:cc2":"MZ",
    "gn:country_code":"MZ",
    "gn:dem":245,
    "gn:feature_class":"P",
    "gn:feature_code":"PPL",
    "gn:name":"Arijamo",
    "gn:population":0,
    "gn:timezone":"Africa/Maputo",
    "iso:country":"MZ",
    "name:und_x_variant":[
        "Arijama",
        "Arijamo"
    ],
    "wof:name":"Arijamo",
    "wof:placetype":"locality"
},
  "geometry": {"coordinates":[36.80833,-16.46167],"type":"Point"}
}