{
  "type": "Feature",
  "properties": {
    "gn:admin1_code":"1",
    "gn:asciiname":"Cobre",
    "gn:country_code":"MZ",
    "gn:dem":40,
    "gn:feature_class":"P",
    "gn:feature_code":"PPL",
    "gn:name":"Cobre",
    "gn:population":0,
    "gn:timezone":"Africa/Maputo",
    "iso:country":"MZ",
    "wof:name":"Cobre",
    "wof:placetype":"locality"
},
  "geometry": {"coordinates":[40.42944,-11.8925],"type":"Point"}
}