{
  "type": "Feature",
  "properties": {
    "gn:admin1_code":"3.0",
    "gn:asciiname":"Macuanane",
    "gn:country_code":"MZ",
    "gn:dem":136,
    "gn:feature_class":"P",
    "gn:feature_code":"PPL",
    "gn:name":"Macuanane",
    "gn:population":0,
    "gn:timezone":"Africa/Maputo",
    "iso:country":"MZ",
    "wof:name":"Macuanane",
    "wof:placetype":"locality"
},
  "geometry": {"coordinates":[34.85805999999999,-22.45194],"type":"Point"}
}