{
  "type": "Feature",
  "properties": {
    "gn:admin1_code":"8",
    "gn:asciiname":"Chissavo",
    "gn:country_code":"MZ",
    "gn:dem":428,
    "gn:feature_class":"P",
    "gn:feature_code":"PPL",
    "gn:name":"Chissavo",
    "gn:population":0,
    "gn:timezone":"Africa/Maputo",
    "iso:country":"MZ",
    "wof:name":"Chissavo",
    "wof:placetype":"locality"
},
  "geometry": {"coordinates":[30.40361,-15.27389],"type":"Point"}
}