{
  "type": "Feature",
  "properties": {
    "gn:admin1_code":"5",
    "gn:asciiname":"Chirangaza",
    "gn:country_code":"MZ",
    "gn:dem":255,
    "gn:feature_class":"P",
    "gn:feature_code":"PPL",
    "gn:name":"Chirangaza",
    "gn:population":0,
    "gn:timezone":"Africa/Maputo",
    "iso:country":"MZ",
    "wof:name":"Chirangaza",
    "wof:placetype":"locality"
},
  "geometry": {"coordinates":[33.65722,-20.45167],"type":"Point"}
}