{
  "type": "Feature",
  "properties": {
    "gn:admin1_code":"0",
    "gn:asciiname":"Caiunga",
    "gn:country_code":"MZ",
    "gn:dem":565,
    "gn:feature_class":"P",
    "gn:feature_code":"PPL",
    "gn:name":"Caiunga",
    "gn:population":0,
    "gn:timezone":"Africa/Maputo",
    "iso:country":"MZ",
    "wof:name":"Caiunga",
    "wof:placetype":"locality"
},
  "geometry": {"coordinates":[34.96667,-13.55],"type":"Point"}
}