{
  "type": "Feature",
  "properties": {
    "gn:admin1_code":"0",
    "gn:asciiname":"Cazemba",
    "gn:country_code":"MZ",
    "gn:dem":957,
    "gn:feature_class":"P",
    "gn:feature_code":"PPL",
    "gn:name":"Cazemba",
    "gn:population":0,
    "gn:timezone":"Africa/Maputo",
    "iso:country":"MZ",
    "wof:name":"Cazemba",
    "wof:placetype":"locality"
},
  "geometry": {"coordinates":[30.76667,-15.15],"type":"Point"}
}