{
  "type": "Feature",
  "properties": {
    "gn:admin1_code":"10",
    "gn:asciiname":"Chicogo",
    "gn:country_code":"MZ",
    "gn:dem":257,
    "gn:feature_class":"P",
    "gn:feature_code":"PPL",
    "gn:name":"Chicogo",
    "gn:population":0,
    "gn:timezone":"Africa/Maputo",
    "iso:country":"MZ",
    "wof:name":"Chicogo",
    "wof:placetype":"locality"
},
  "geometry": {"coordinates":[33.40889,-20.80889],"type":"Point"}
}