{
  "type": "Feature",
  "properties": {
    "gn:admin1_code":"1",
    "gn:asciiname":"Amea",
    "gn:country_code":"MZ",
    "gn:dem":221,
    "gn:feature_class":"P",
    "gn:feature_code":"PPL",
    "gn:name":"Amea",
    "gn:population":0,
    "gn:timezone":"Africa/Maputo",
    "iso:country":"MZ",
    "wof:name":"Amea",
    "wof:placetype":"locality"
},
  "geometry": {"coordinates":[39.92694,-11.46667],"type":"Point"}
}