{
  "type": "Feature",
  "properties": {
    "gn:admin1_code":"8",
    "gn:asciiname":"Thongoe",
    "gn:country_code":"MZ",
    "gn:dem":570,
    "gn:feature_class":"P",
    "gn:feature_code":"PPL",
    "gn:name":"Thongo\u00e9",
    "gn:population":0,
    "gn:timezone":"Africa/Maputo",
    "iso:country":"MZ",
    "wof:name":"Thongoe",
    "wof:placetype":"locality"
},
  "geometry": {"coordinates":[30.7325,-15.37889],"type":"Point"}
}