{
  "type": "Feature",
  "properties": {
    "gn:admin1_code":"6.0",
    "gn:asciiname":"Tagoto",
    "gn:country_code":"MZ",
    "gn:dem":105,
    "gn:feature_class":"P",
    "gn:feature_code":"PPL",
    "gn:name":"Tagoto",
    "gn:population":0,
    "gn:timezone":"Africa/Maputo",
    "iso:country":"MZ",
    "wof:name":"Tagoto",
    "wof:placetype":"locality"
},
  "geometry": {"coordinates":[40.52139,-14.46083],"type":"Point"}
}