{
  "type": "Feature",
  "properties": {
    "gn:admin1_code":"9",
    "gn:asciiname":"Naide",
    "gn:country_code":"MZ",
    "gn:dem":705,
    "gn:feature_class":"P",
    "gn:feature_code":"PPL",
    "gn:name":"Naide",
    "gn:population":0,
    "gn:timezone":"Africa/Maputo",
    "iso:country":"MZ",
    "wof:name":"Naide",
    "wof:placetype":"locality"
},
  "geometry": {"coordinates":[36.24111,-15.79528],"type":"Point"}
}