{
  "type": "Feature",
  "properties": {
    "gn:admin1_code":"9",
    "gn:asciiname":"Marieta",
    "gn:country_code":"MZ",
    "gn:dem":696,
    "gn:feature_class":"P",
    "gn:feature_code":"PPL",
    "gn:name":"Marieta",
    "gn:population":0,
    "gn:timezone":"Africa/Maputo",
    "iso:country":"MZ",
    "wof:name":"Marieta",
    "wof:placetype":"locality"
},
  "geometry": {"coordinates":[37.01611,-15.12],"type":"Point"}
}