{
  "type": "Feature",
  "properties": {
    "gn:admin1_code":"3.0",
    "gn:asciiname":"Tejo",
    "gn:country_code":"MZ",
    "gn:dem":99,
    "gn:feature_class":"P",
    "gn:feature_code":"PPL",
    "gn:name":"Tejo",
    "gn:population":0,
    "gn:timezone":"Africa/Maputo",
    "iso:country":"MZ",
    "name:ben_x_preferred":[
        "\u09a4\u09c7\u099c\u09cb"
    ],
    "name:deu_x_preferred":[
        "Tejo"
    ],
    "name:epo_x_preferred":[
        "Tejo"
    ],
    "name:fra_x_preferred":[
        "Tejo"
    ],
    "name:hin_x_preferred":[
        "\u0924\u0947\u091c\u094b"
    ],
    "name:hun_x_preferred":[
        "Tejo"
    ],
    "name:nld_x_preferred":[
        "Tejo"
    ],
    "name:pol_x_preferred":[
        "Tejo"
    ],
    "name:por_x_preferred":[
        "Tejo"
    ],
    "name:spa_x_preferred":[
        "Tejo"
    ],
    "name:swe_x_preferred":[
        "Tejo"
    ],
    "name:urd_x_preferred":[
        "\u062a\u06cc\u062c\u0648"
    ],
    "wof:name":"Tejo",
    "wof:placetype":"locality"
},
  "geometry": {"coordinates":[35.22417,-23.42833],"type":"Point"}
}