{
  "type": "Feature",
  "properties": {
    "gn:admin1_code":"5.0",
    "gn:asciiname":"Pemene Chibila",
    "gn:country_code":"MZ",
    "gn:dem":77,
    "gn:feature_class":"P",
    "gn:feature_code":"PPL",
    "gn:name":"Pemene Chibila",
    "gn:population":0,
    "gn:timezone":"Africa/Maputo",
    "iso:country":"MZ",
    "wof:name":"Pemene Chibila",
    "wof:placetype":"locality"
},
  "geometry": {"coordinates":[34.58389,-20.97694],"type":"Point"}
}