{
  "type": "Feature",
  "properties": {
    "gn:admin1_code":"1",
    "gn:asciiname":"Manica",
    "gn:country_code":"MZ",
    "gn:dem":148,
    "gn:feature_class":"P",
    "gn:feature_code":"PPL",
    "gn:name":"Manica",
    "gn:population":0,
    "gn:timezone":"Africa/Maputo",
    "iso:country":"MZ",
    "name:deu_x_preferred":[
        "Manica"
    ],
    "name:fra_x_preferred":[
        "Manica"
    ],
    "name:heb_x_preferred":[
        "\u05de\u05e0\u05d9\u05e7\u05d0\u05dc\u05d0\u05e0\u05d3"
    ],
    "name:hun_x_preferred":[
        "Manica"
    ],
    "name:ita_x_preferred":[
        "Manica"
    ],
    "name:pol_x_preferred":[
        "Manica"
    ],
    "name:por_x_preferred":[
        "Manica"
    ],
    "name:rus_x_preferred":[
        "\u041c\u0430\u043d\u0438\u043a\u0430"
    ],
    "name:ukr_x_preferred":[
        "\u041c\u0430\u043d\u0456\u043a\u0430"
    ],
    "wof:name":"Manica",
    "wof:placetype":"locality"
},
  "geometry": {"coordinates":[40.41917,-12.08972],"type":"Point"}
}