{
  "type": "Feature",
  "properties": {
    "gn:admin1_code":"1",
    "gn:asciiname":"Manica",
    "gn:country_code":"MZ",
    "gn:dem":148,
    "gn:feature_class":"P",
    "gn:feature_code":"PPL",
    "gn:name":"Manica",
    "gn:population":0,
    "gn:timezone":"Africa/Maputo",
    "iso:country":"MZ",
    "wof:name":"Manica",
    "wof:placetype":"locality"
},
  "geometry": {"coordinates":[40.41917,-12.08972],"type":"Point"}
}