{
  "type": "Feature",
  "properties": {
    "gn:admin1_code":"5",
    "gn:asciiname":"Macurine",
    "gn:country_code":"MZ",
    "gn:dem":186,
    "gn:feature_class":"P",
    "gn:feature_code":"PPL",
    "gn:name":"Macurine",
    "gn:population":0,
    "gn:timezone":"Africa/Maputo",
    "iso:country":"MZ",
    "wof:name":"Macurine",
    "wof:placetype":"locality"
},
  "geometry": {"coordinates":[33.82611,-20.56194],"type":"Point"}
}