{
  "type": "Feature",
  "properties": {
    "gn:admin1_code":"2",
    "gn:asciiname":"Chidungane",
    "gn:country_code":"MZ",
    "gn:dem":79,
    "gn:feature_class":"P",
    "gn:feature_code":"PPL",
    "gn:name":"Chidungane",
    "gn:population":0,
    "gn:timezone":"Africa/Maputo",
    "iso:country":"MZ",
    "wof:name":"Chidungane",
    "wof:placetype":"locality"
},
  "geometry": {"coordinates":[32.47639,-23.63556],"type":"Point"}
}