{
  "type": "Feature",
  "properties": {
    "gn:admin1_code":"6.0",
    "gn:asciiname":"Uaneline",
    "gn:country_code":"MZ",
    "gn:dem":382,
    "gn:feature_class":"P",
    "gn:feature_code":"PPL",
    "gn:name":"Uaneline",
    "gn:population":0,
    "gn:timezone":"Africa/Maputo",
    "iso:country":"MZ",
    "wof:name":"Uaneline",
    "wof:placetype":"locality"
},
  "geometry": {"coordinates":[39.66056,-14.63972],"type":"Point"}
}