{
  "type": "Feature",
  "properties": {
    "gn:admin1_code":"1",
    "gn:asciiname":"Humo Mualavaca",
    "gn:country_code":"MZ",
    "gn:dem":375,
    "gn:feature_class":"P",
    "gn:feature_code":"PPL",
    "gn:name":"Humo Mualavaca",
    "gn:population":0,
    "gn:timezone":"Africa/Maputo",
    "iso:country":"MZ",
    "wof:name":"Humo Mualavaca",
    "wof:placetype":"locality"
},
  "geometry": {"coordinates":[38.82722,-13.97],"type":"Point"}
}