{
  "type": "Feature",
  "properties": {
    "gn:admin1_code":"7",
    "gn:asciiname":"Chembela",
    "gn:country_code":"MZ",
    "gn:dem":1135,
    "gn:feature_class":"P",
    "gn:feature_code":"PPL",
    "gn:name":"Chembela",
    "gn:population":0,
    "gn:timezone":"Africa/Maputo",
    "iso:country":"MZ",
    "wof:name":"Chembela",
    "wof:placetype":"locality"
},
  "geometry": {"coordinates":[35.55917,-13.20889],"type":"Point"}
}