{
  "type": "Feature",
  "properties": {
    "gn:admin1_code":"3",
    "gn:asciiname":"Chimusse",
    "gn:country_code":"MZ",
    "gn:dem":107,
    "gn:feature_class":"P",
    "gn:feature_code":"PPL",
    "gn:name":"Chimusse",
    "gn:population":0,
    "gn:timezone":"Africa/Maputo",
    "iso:country":"MZ",
    "wof:name":"Chimusse",
    "wof:placetype":"locality"
},
  "geometry": {"coordinates":[34.13417,-23.15111],"type":"Point"}
}