{
  "type": "Feature",
  "properties": {
    "gn:admin1_code":"5",
    "gn:asciiname":"Benete",
    "gn:country_code":"MZ",
    "gn:dem":221,
    "gn:feature_class":"P",
    "gn:feature_code":"PPL",
    "gn:name":"Benete",
    "gn:population":0,
    "gn:timezone":"Africa/Maputo",
    "iso:country":"MZ",
    "name:bos_x_preferred":[
        "Benete"
    ],
    "name:hrv_x_preferred":[
        "Benete"
    ],
    "name:nld_x_preferred":[
        "Benete"
    ],
    "name:pol_x_preferred":[
        "Benete"
    ],
    "name:ron_x_preferred":[
        "Benete"
    ],
    "name:slv_x_preferred":[
        "Benete"
    ],
    "name:ukr_x_preferred":[
        "\u0411\u0435\u043d\u0435\u0442\u0435"
    ],
    "wof:name":"Benete",
    "wof:placetype":"locality"
},
  "geometry": {"coordinates":[33.59917,-20.47278],"type":"Point"}
}