{
  "type": "Feature",
  "properties": {
    "gn:admin1_code":"2.0",
    "gn:asciiname":"Joao Monteiro",
    "gn:country_code":"MZ",
    "gn:dem":56,
    "gn:feature_class":"P",
    "gn:feature_code":"PPL",
    "gn:name":"Jo\u00e3o Monteiro",
    "gn:population":0,
    "gn:timezone":"Africa/Maputo",
    "iso:country":"MZ",
    "wof:name":"Joao Monteiro",
    "wof:placetype":"locality"
},
  "geometry": {"coordinates":[32.98444,-24.9925],"type":"Point"}
}