{
  "type": "Feature",
  "properties": {
    "gn:admin1_code":"6",
    "gn:asciiname":"Nauaua",
    "gn:country_code":"MZ",
    "gn:dem":360,
    "gn:feature_class":"P",
    "gn:feature_code":"PPL",
    "gn:name":"Nauaua",
    "gn:population":0,
    "gn:timezone":"Africa/Maputo",
    "iso:country":"MZ",
    "wof:name":"Nauaua",
    "wof:placetype":"locality"
},
  "geometry": {"coordinates":[38.99556,-14.1075],"type":"Point"}
}