{
  "type": "Feature",
  "properties": {
    "gn:admin1_code":"3",
    "gn:asciiname":"Nhamageu",
    "gn:country_code":"MZ",
    "gn:dem":39,
    "gn:feature_class":"P",
    "gn:feature_code":"PPL",
    "gn:name":"Nhamageu",
    "gn:population":0,
    "gn:timezone":"Africa/Maputo",
    "iso:country":"MZ",
    "wof:name":"Nhamageu",
    "wof:placetype":"locality"
},
  "geometry": {"coordinates":[35.03639,-24.61861],"type":"Point"}
}