{
  "type": "Feature",
  "properties": {
    "gn:admin1_code":"9",
    "gn:asciiname":"Melungose",
    "gn:country_code":"MZ",
    "gn:dem":614,
    "gn:feature_class":"P",
    "gn:feature_code":"PPL",
    "gn:name":"Melungose",
    "gn:population":0,
    "gn:timezone":"Africa/Maputo",
    "iso:country":"MZ",
    "wof:name":"Melungose",
    "wof:placetype":"locality"
},
  "geometry": {"coordinates":[35.70694,-16.16],"type":"Point"}
}