{
  "type": "Feature",
  "properties": {
    "gn:admin1_code":"9",
    "gn:asciiname":"Gurue",
    "gn:country_code":"MZ",
    "gn:dem":722,
    "gn:feature_class":"P",
    "gn:feature_code":"PPL",
    "gn:name":"Gur\u00fa\u00e8",
    "gn:population":0,
    "gn:timezone":"Africa/Maputo",
    "iso:country":"MZ",
    "name:cat_x_preferred":[
        "Gur\u00fa\u00e8"
    ],
    "name:ceb_x_preferred":[
        "Gur\u00fa\u00e8"
    ],
    "name:deu_x_preferred":[
        "Guru\u00e9"
    ],
    "name:epo_x_preferred":[
        "Gur\u00fa\u00e8"
    ],
    "name:fin_x_preferred":[
        "Guru\u00e9"
    ],
    "name:fra_x_preferred":[
        "Guru\u00e9"
    ],
    "name:hrv_x_preferred":[
        "Guru\u00e9"
    ],
    "name:ita_x_preferred":[
        "Guru\u00e9"
    ],
    "name:kat_x_preferred":[
        "\u10d2\u10e3\u10e0\u10e3\u10d4"
    ],
    "name:lit_x_preferred":[
        "Guruj\u0117"
    ],
    "name:pol_x_preferred":[
        "Gur\u00fa\u00e8"
    ],
    "name:por_x_preferred":[
        "Guru\u00e9"
    ],
    "name:ron_x_preferred":[
        "Gur\u00fa\u00e8"
    ],
    "name:rus_x_preferred":[
        "\u0413\u0443\u0440\u0443\u044d"
    ],
    "name:swa_x_preferred":[
        "Guru\u00e9"
    ],
    "name:ukr_x_preferred":[
        "\u0413\u0443\u0440\u0443\u0435"
    ],
    "name:und_x_variant":[
        "Guru\u00e9",
        "Vila Junqueiro"
    ],
    "name:zho_x_preferred":[
        "\u53e4\u9b6f\u57c3"
    ],
    "wof:name":"Gurue",
    "wof:placetype":"locality"
},
  "geometry": {"coordinates":[36.97778,-15.46694],"type":"Point"}
}