{
  "type": "Feature",
  "properties": {
    "gn:admin1_code":"9",
    "gn:asciiname":"Gurue",
    "gn:country_code":"MZ",
    "gn:dem":722,
    "gn:feature_class":"P",
    "gn:feature_code":"PPL",
    "gn:name":"Gur\u00fa\u00e8",
    "gn:population":0,
    "gn:timezone":"Africa/Maputo",
    "iso:country":"MZ",
    "name:und_x_variant":[
        "Guru\u00e9",
        "Vila Junqueiro"
    ],
    "wof:name":"Gurue",
    "wof:placetype":"locality"
},
  "geometry": {"coordinates":[36.97778,-15.46694],"type":"Point"}
}