{
  "type": "Feature",
  "properties": {
    "gn:admin1_code":"2",
    "gn:asciiname":"Marrenguele",
    "gn:country_code":"MZ",
    "gn:dem":85,
    "gn:feature_class":"P",
    "gn:feature_code":"PPL",
    "gn:name":"Marrenguele",
    "gn:population":0,
    "gn:timezone":"Africa/Maputo",
    "iso:country":"MZ",
    "wof:name":"Marrenguele",
    "wof:placetype":"locality"
},
  "geometry": {"coordinates":[32.23111,-23.88972],"type":"Point"}
}