{
  "type": "Feature",
  "properties": {
    "gn:admin1_code":"7.0",
    "gn:asciiname":"Rapala",
    "gn:country_code":"MZ",
    "gn:dem":751,
    "gn:feature_class":"P",
    "gn:feature_code":"PPL",
    "gn:name":"Rapala",
    "gn:population":0,
    "gn:timezone":"Africa/Maputo",
    "iso:country":"MZ",
    "wof:name":"Rapala",
    "wof:placetype":"locality"
},
  "geometry": {"coordinates":[36.45,-14.02111],"type":"Point"}
}