{
  "type": "Feature",
  "properties": {
    "gn:admin1_code":"2.0",
    "gn:asciiname":"Canjuane",
    "gn:country_code":"MZ",
    "gn:dem":88,
    "gn:feature_class":"P",
    "gn:feature_code":"PPL",
    "gn:name":"Canjuane",
    "gn:population":0,
    "gn:timezone":"Africa/Maputo",
    "iso:country":"MZ",
    "wof:name":"Canjuane",
    "wof:placetype":"locality"
},
  "geometry": {"coordinates":[33.43861,-22.775],"type":"Point"}
}