{
  "type": "Feature",
  "properties": {
    "gn:admin1_code":"0",
    "gn:asciiname":"Buto",
    "gn:country_code":"MZ",
    "gn:dem":637,
    "gn:feature_class":"P",
    "gn:feature_code":"PPL",
    "gn:name":"Buto",
    "gn:population":0,
    "gn:timezone":"Africa/Maputo",
    "iso:country":"MZ",
    "wof:name":"Buto",
    "wof:placetype":"locality"
},
  "geometry": {"coordinates":[35.91667,-14.68333],"type":"Point"}
}