{
  "type": "Feature",
  "properties": {
    "gn:admin1_code":"8",
    "gn:asciiname":"Chituza",
    "gn:country_code":"MZ",
    "gn:dem":833,
    "gn:feature_class":"P",
    "gn:feature_code":"PPL",
    "gn:name":"Chituza",
    "gn:population":0,
    "gn:timezone":"Africa/Maputo",
    "iso:country":"MZ",
    "wof:name":"Chituza",
    "wof:placetype":"locality"
},
  "geometry": {"coordinates":[31.23861,-15.06694],"type":"Point"}
}