{
  "type": "Feature",
  "properties": {
    "gn:admin1_code":"9.0",
    "gn:asciiname":"Chefe Tocota",
    "gn:cc2":"MZ",
    "gn:country_code":"MZ",
    "gn:dem":680,
    "gn:feature_class":"P",
    "gn:feature_code":"PPL",
    "gn:name":"Chefe Tocota",
    "gn:population":0,
    "gn:timezone":"Africa/Maputo",
    "iso:country":"MZ",
    "name:und_x_variant":[
        "Toc\u00f3ta",
        "Chefe Tocota"
    ],
    "wof:name":"Chefe Tocota",
    "wof:placetype":"locality"
},
  "geometry": {"coordinates":[35.85889,-15.94861],"type":"Point"}
}