{
  "type": "Feature",
  "properties": {
    "gn:admin1_code":"9",
    "gn:asciiname":"Madal",
    "gn:country_code":"MZ",
    "gn:dem":14,
    "gn:feature_class":"P",
    "gn:feature_code":"PPL",
    "gn:name":"Madal",
    "gn:population":0,
    "gn:timezone":"Africa/Maputo",
    "iso:country":"MZ",
    "name:cat_x_preferred":[
        "Madal"
    ],
    "name:nep_x_preferred":[
        "\u092e\u093e\u0926\u0932"
    ],
    "name:spa_x_preferred":[
        "Madal"
    ],
    "wof:name":"Madal",
    "wof:placetype":"locality"
},
  "geometry": {"coordinates":[36.96056,-17.90389],"type":"Point"}
}