{
  "type": "Feature",
  "properties": {
    "gn:admin1_code":"10",
    "gn:asciiname":"Mauisse",
    "gn:country_code":"MZ",
    "gn:dem":222,
    "gn:feature_class":"P",
    "gn:feature_code":"PPL",
    "gn:name":"Mauisse",
    "gn:population":0,
    "gn:timezone":"Africa/Maputo",
    "iso:country":"MZ",
    "wof:name":"Mauisse",
    "wof:placetype":"locality"
},
  "geometry": {"coordinates":[33.095,-20.64222],"type":"Point"}
}