{
  "type": "Feature",
  "properties": {
    "gn:admin1_code":"3.0",
    "gn:asciiname":"Tavane",
    "gn:country_code":"MZ",
    "gn:dem":51,
    "gn:feature_class":"P",
    "gn:feature_code":"PPL",
    "gn:name":"Tavane",
    "gn:population":0,
    "gn:timezone":"Africa/Maputo",
    "iso:country":"MZ",
    "wof:name":"Tavane",
    "wof:placetype":"locality"
},
  "geometry": {"coordinates":[34.93222,-21.64306],"type":"Point"}
}