{
  "type": "Feature",
  "properties": {
    "gn:admin1_code":"8.0",
    "gn:asciiname":"Tchafuco",
    "gn:country_code":"MZ",
    "gn:dem":290,
    "gn:feature_class":"P",
    "gn:feature_code":"PPL",
    "gn:name":"Tchafuco",
    "gn:population":0,
    "gn:timezone":"Africa/Maputo",
    "iso:country":"MZ",
    "wof:name":"Tchafuco",
    "wof:placetype":"locality"
},
  "geometry": {"coordinates":[33.0475,-15.81667],"type":"Point"}
}