{
  "type": "Feature",
  "properties": {
    "gn:admin1_code":"4.0",
    "gn:asciiname":"Uampechene",
    "gn:country_code":"MZ",
    "gn:dem":57,
    "gn:feature_class":"P",
    "gn:feature_code":"PPL",
    "gn:name":"Uampechene",
    "gn:population":0,
    "gn:timezone":"Africa/Maputo",
    "iso:country":"MZ",
    "wof:name":"Uampechene",
    "wof:placetype":"locality"
},
  "geometry": {"coordinates":[32.38278,-25.76472],"type":"Point"}
}