{
  "type": "Feature",
  "properties": {
    "gn:admin1_code":"7.0",
    "gn:asciiname":"Uitelele",
    "gn:country_code":"MZ",
    "gn:dem":982,
    "gn:feature_class":"P",
    "gn:feature_code":"PPL",
    "gn:name":"Uitelele",
    "gn:population":0,
    "gn:timezone":"Africa/Maputo",
    "iso:country":"MZ",
    "wof:name":"Uitelele",
    "wof:placetype":"locality"
},
  "geometry": {"coordinates":[35.74194,-13.20306],"type":"Point"}
}