{
  "type": "Feature",
  "properties": {
    "gn:admin1_code":"10",
    "gn:asciiname":"Mapombera",
    "gn:country_code":"MZ",
    "gn:dem":690,
    "gn:feature_class":"P",
    "gn:feature_code":"PPL",
    "gn:name":"Mapombera",
    "gn:population":0,
    "gn:timezone":"Africa/Maputo",
    "iso:country":"MZ",
    "wof:name":"Mapombera",
    "wof:placetype":"locality"
},
  "geometry": {"coordinates":[33.04889,-19.63639],"type":"Point"}
}