{
  "type": "Feature",
  "properties": {
    "gn:admin1_code":"1",
    "gn:asciiname":"Chefe Ahonamoro",
    "gn:country_code":"MZ",
    "gn:dem":305,
    "gn:feature_class":"P",
    "gn:feature_code":"PPL",
    "gn:name":"Chefe Ahonamoro",
    "gn:population":0,
    "gn:timezone":"Africa/Maputo",
    "iso:country":"MZ",
    "wof:name":"Chefe Ahonamoro",
    "wof:placetype":"locality"
},
  "geometry": {"coordinates":[39.79444,-13.40389],"type":"Point"}
}