{
  "type": "Feature",
  "properties": {
    "gn:admin1_code":"5",
    "gn:asciiname":"Chiminba",
    "gn:country_code":"MZ",
    "gn:dem":2,
    "gn:feature_class":"P",
    "gn:feature_code":"PPL",
    "gn:name":"Chiminba",
    "gn:population":0,
    "gn:timezone":"Africa/Maputo",
    "iso:country":"MZ",
    "wof:name":"Chiminba",
    "wof:placetype":"locality"
},
  "geometry": {"coordinates":[34.745,-20.59333],"type":"Point"}
}