{
  "type": "Feature",
  "properties": {
    "gn:admin1_code":"1",
    "gn:asciiname":"Muinea",
    "gn:country_code":"MZ",
    "gn:dem":292,
    "gn:feature_class":"P",
    "gn:feature_code":"PPL",
    "gn:name":"Muinea",
    "gn:population":0,
    "gn:timezone":"Africa/Maputo",
    "iso:country":"MZ",
    "wof:name":"Muinea",
    "wof:placetype":"locality"
},
  "geometry": {"coordinates":[39.12361,-14.00389],"type":"Point"}
}