{
  "type": "Feature",
  "properties": {
    "gn:admin1_code":"4",
    "gn:asciiname":"Chizumbane",
    "gn:country_code":"MZ",
    "gn:dem":341,
    "gn:feature_class":"P",
    "gn:feature_code":"PPL",
    "gn:name":"Chizumbane",
    "gn:population":0,
    "gn:timezone":"Africa/Maputo",
    "iso:country":"MZ",
    "wof:name":"Chizumbane",
    "wof:placetype":"locality"
},
  "geometry": {"coordinates":[31.95917,-24.24861],"type":"Point"}
}