{
  "type": "Feature",
  "properties": {
    "gn:admin1_code":"9",
    "gn:asciiname":"Muavula",
    "gn:country_code":"MZ",
    "gn:dem":300,
    "gn:feature_class":"P",
    "gn:feature_code":"PPL",
    "gn:name":"Mu\u00e1vula",
    "gn:population":0,
    "gn:timezone":"Africa/Maputo",
    "iso:country":"MZ",
    "wof:name":"Muavula",
    "wof:placetype":"locality"
},
  "geometry": {"coordinates":[36.67361,-16.86083],"type":"Point"}
}