{
  "type": "Feature",
  "properties": {
    "gn:admin1_code":"7",
    "gn:asciiname":"Maziviri",
    "gn:country_code":"MZ",
    "gn:dem":279,
    "gn:feature_class":"P",
    "gn:feature_code":"PPL",
    "gn:name":"Maziviri",
    "gn:population":0,
    "gn:timezone":"Africa/Maputo",
    "iso:country":"MZ",
    "wof:name":"Maziviri",
    "wof:placetype":"locality"
},
  "geometry": {"coordinates":[37.80139000000001,-12.275],"type":"Point"}
}