{
  "type": "Feature",
  "properties": {
    "gn:admin1_code":"10",
    "gn:asciiname":"Cadduca",
    "gn:country_code":"MZ",
    "gn:dem":221,
    "gn:feature_class":"P",
    "gn:feature_code":"PPL",
    "gn:name":"Cadduca",
    "gn:population":0,
    "gn:timezone":"Africa/Maputo",
    "iso:country":"MZ",
    "wof:name":"Cadduca",
    "wof:placetype":"locality"
},
  "geometry": {"coordinates":[33.90111,-19.17583],"type":"Point"}
}