{
  "type": "Feature",
  "properties": {
    "gn:admin1_code":"8",
    "gn:asciiname":"Ngoza",
    "gn:country_code":"MZ",
    "gn:dem":1012,
    "gn:feature_class":"P",
    "gn:feature_code":"PPL",
    "gn:name":"Ngoza",
    "gn:population":0,
    "gn:timezone":"Africa/Maputo",
    "iso:country":"MZ",
    "wof:name":"Ngoza",
    "wof:placetype":"locality"
},
  "geometry": {"coordinates":[31.92611,-14.43917],"type":"Point"}
}