{
  "type": "Feature",
  "properties": {
    "gn:admin1_code":"2",
    "gn:asciiname":"Majecuza",
    "gn:country_code":"MZ",
    "gn:dem":30,
    "gn:feature_class":"P",
    "gn:feature_code":"PPL",
    "gn:name":"Majecuza",
    "gn:population":0,
    "gn:timezone":"Africa/Maputo",
    "iso:country":"MZ",
    "name:und_x_variant":[
        "Majicuza",
        "Muchola"
    ],
    "wof:name":"Majecuza",
    "wof:placetype":"locality"
},
  "geometry": {"coordinates":[33.58833,-24.405],"type":"Point"}
}