{
  "type": "Feature",
  "properties": {
    "gn:admin1_code":"4",
    "gn:asciiname":"Jafar",
    "gn:country_code":"MZ",
    "gn:dem":24,
    "gn:feature_class":"P",
    "gn:feature_code":"PPL",
    "gn:name":"Jafar",
    "gn:population":0,
    "gn:timezone":"Africa/Maputo",
    "iso:country":"MZ",
    "wof:name":"Jafar",
    "wof:placetype":"locality"
},
  "geometry": {"coordinates":[32.65139,-25.80639],"type":"Point"}
}