{
  "type": "Feature",
  "properties": {
    "gn:admin1_code":"2.0",
    "gn:asciiname":"Armando",
    "gn:country_code":"MZ",
    "gn:dem":58,
    "gn:feature_class":"P",
    "gn:feature_code":"PPL",
    "gn:name":"Armando",
    "gn:population":0,
    "gn:timezone":"Africa/Maputo",
    "iso:country":"MZ",
    "wof:name":"Armando",
    "wof:placetype":"locality"
},
  "geometry": {"coordinates":[33.42472,-23.87167],"type":"Point"}
}