{
  "type": "Feature",
  "properties": {
    "gn:admin1_code":"2.0",
    "gn:asciiname":"Armando",
    "gn:country_code":"MZ",
    "gn:dem":58,
    "gn:feature_class":"P",
    "gn:feature_code":"PPL",
    "gn:name":"Armando",
    "gn:population":0,
    "gn:timezone":"Africa/Maputo",
    "iso:country":"MZ",
    "name:dan_x_preferred":[
        "Armando"
    ],
    "name:deu_x_preferred":[
        "Armando"
    ],
    "name:fra_x_preferred":[
        "Armando"
    ],
    "name:ita_x_preferred":[
        "Armando"
    ],
    "name:lat_x_preferred":[
        "Armandus"
    ],
    "name:rus_x_preferred":[
        "\u0410\u0440\u043c\u0430\u043d\u0434\u043e"
    ],
    "name:tur_x_preferred":[
        "Armando"
    ],
    "wof:name":"Armando",
    "wof:placetype":"locality"
},
  "geometry": {"coordinates":[33.42472,-23.87167],"type":"Point"}
}