{
  "type": "Feature",
  "properties": {
    "gn:admin1_code":"2.0",
    "gn:asciiname":"Tavene",
    "gn:country_code":"MZ",
    "gn:dem":2,
    "gn:feature_class":"P",
    "gn:feature_code":"PPL",
    "gn:name":"Tavene",
    "gn:population":0,
    "gn:timezone":"Africa/Maputo",
    "iso:country":"MZ",
    "wof:name":"Tavene",
    "wof:placetype":"locality"
},
  "geometry": {"coordinates":[33.64944000000001,-25.05972],"type":"Point"}
}