{
  "type": "Feature",
  "properties": {
    "gn:admin1_code":"1",
    "gn:asciiname":"Menhula",
    "gn:country_code":"MZ",
    "gn:dem":317,
    "gn:feature_class":"P",
    "gn:feature_code":"PPL",
    "gn:name":"Menhula",
    "gn:population":0,
    "gn:timezone":"Africa/Maputo",
    "iso:country":"MZ",
    "wof:name":"Menhula",
    "wof:placetype":"locality"
},
  "geometry": {"coordinates":[39.93278,-13.12139],"type":"Point"}
}