{
  "type": "Feature",
  "properties": {
    "gn:admin1_code":"1",
    "gn:asciiname":"Macomia",
    "gn:country_code":"MZ",
    "gn:dem":360,
    "gn:feature_class":"P",
    "gn:feature_code":"PPL",
    "gn:name":"Macomia",
    "gn:population":0,
    "gn:timezone":"Africa/Maputo",
    "iso:country":"MZ",
    "wof:name":"Macomia",
    "wof:placetype":"locality"
},
  "geometry": {"coordinates":[40.12083,-12.24667],"type":"Point"}
}