{
  "type": "Feature",
  "properties": {
    "gn:admin1_code":"2",
    "gn:asciiname":"Machulane",
    "gn:country_code":"MZ",
    "gn:dem":93,
    "gn:feature_class":"P",
    "gn:feature_code":"PPL",
    "gn:name":"Machulane",
    "gn:population":0,
    "gn:timezone":"Africa/Maputo",
    "iso:country":"MZ",
    "wof:name":"Machulane",
    "wof:placetype":"locality"
},
  "geometry": {"coordinates":[34.09083,-24.59389],"type":"Point"}
}