{
  "type": "Feature",
  "properties": {
    "gn:admin1_code":"2.0",
    "gn:asciiname":"Djane",
    "gn:country_code":"MZ",
    "gn:dem":128,
    "gn:feature_class":"P",
    "gn:feature_code":"PPL",
    "gn:name":"Djane",
    "gn:population":0,
    "gn:timezone":"Africa/Maputo",
    "iso:country":"MZ",
    "wof:name":"Djane",
    "wof:placetype":"locality"
},
  "geometry": {"coordinates":[32.50194,-22.69778],"type":"Point"}
}