{
  "type": "Feature",
  "properties": {
    "gn:admin1_code":"9",
    "gn:asciiname":"Augusto",
    "gn:country_code":"MZ",
    "gn:dem":171,
    "gn:feature_class":"P",
    "gn:feature_code":"PPL",
    "gn:name":"Augusto",
    "gn:population":0,
    "gn:timezone":"Africa/Maputo",
    "iso:country":"MZ",
    "name:bre_x_preferred":[
        "Augusto"
    ],
    "name:deu_x_preferred":[
        "Augusto"
    ],
    "name:ita_x_preferred":[
        "Augusto"
    ],
    "name:nor_x_preferred":[
        "Augusto"
    ],
    "name:spa_x_preferred":[
        "Augusto"
    ],
    "wof:name":"Augusto",
    "wof:placetype":"locality"
},
  "geometry": {"coordinates":[37.11,-16.78889],"type":"Point"}
}