{
  "type": "Feature",
  "properties": {
    "gn:admin1_code":"7.0",
    "gn:asciiname":"Quita",
    "gn:country_code":"MZ",
    "gn:dem":521,
    "gn:feature_class":"P",
    "gn:feature_code":"PPL",
    "gn:name":"Quita",
    "gn:population":0,
    "gn:timezone":"Africa/Maputo",
    "iso:country":"MZ",
    "wof:name":"Quita",
    "wof:placetype":"locality"
},
  "geometry": {"coordinates":[37.43139,-14.02694],"type":"Point"}
}