{
  "type": "Feature",
  "properties": {
    "gn:admin1_code":"9.0",
    "gn:asciiname":"Uateca",
    "gn:country_code":"MZ",
    "gn:dem":50,
    "gn:feature_class":"P",
    "gn:feature_code":"PPL",
    "gn:name":"Uat\u00e9ca",
    "gn:population":0,
    "gn:timezone":"Africa/Maputo",
    "iso:country":"MZ",
    "wof:name":"Uateca",
    "wof:placetype":"locality"
},
  "geometry": {"coordinates":[37.00583,-17.36694],"type":"Point"}
}