{
  "type": "Feature",
  "properties": {
    "gn:admin1_code":"9",
    "gn:asciiname":"Latia",
    "gn:country_code":"MZ",
    "gn:dem":25,
    "gn:feature_class":"P",
    "gn:feature_code":"PPL",
    "gn:name":"Latia",
    "gn:population":0,
    "gn:timezone":"Africa/Maputo",
    "iso:country":"MZ",
    "name:ceb_x_preferred":[
        "Latia"
    ],
    "name:deu_x_preferred":[
        "Latia"
    ],
    "name:nld_x_preferred":[
        "Latia"
    ],
    "name:rus_x_preferred":[
        "Latiidae"
    ],
    "name:swe_x_preferred":[
        "Latia"
    ],
    "name:war_x_preferred":[
        "Latia"
    ],
    "wof:name":"Latia",
    "wof:placetype":"locality"
},
  "geometry": {"coordinates":[37.01472,-17.41889],"type":"Point"}
}