{
  "type": "Feature",
  "properties": {
    "gn:admin1_code":"0",
    "gn:asciiname":"Jomali",
    "gn:country_code":"MZ",
    "gn:dem":247,
    "gn:feature_class":"P",
    "gn:feature_code":"PPL",
    "gn:name":"J\u00f3mali",
    "gn:population":0,
    "gn:timezone":"Africa/Maputo",
    "iso:country":"MZ",
    "wof:name":"Jomali",
    "wof:placetype":"locality"
},
  "geometry": {"coordinates":[37.83333,-16.21667],"type":"Point"}
}