{
  "type": "Feature",
  "properties": {
    "gn:admin1_code":"4",
    "gn:asciiname":"Martins",
    "gn:country_code":"MZ",
    "gn:dem":78,
    "gn:feature_class":"P",
    "gn:feature_code":"PPL",
    "gn:name":"Martins",
    "gn:population":0,
    "gn:timezone":"Africa/Maputo",
    "iso:country":"MZ",
    "name:ceb_x_preferred":[
        "Martins"
    ],
    "name:deu_x_preferred":[
        "Martins"
    ],
    "name:fas_x_preferred":[
        "\u0645\u0627\u0631\u062a\u06cc\u0646\u0633"
    ],
    "name:fin_x_preferred":[
        "Martins"
    ],
    "name:fra_x_preferred":[
        "Martins"
    ],
    "name:ita_x_preferred":[
        "Martins"
    ],
    "name:lav_x_preferred":[
        "Martins"
    ],
    "name:por_x_preferred":[
        "Martins"
    ],
    "name:rus_x_preferred":[
        "\u041c\u0430\u0440\u0442\u0438\u043d\u0448"
    ],
    "name:swe_x_preferred":[
        "Martins"
    ],
    "name:ukr_x_preferred":[
        "\u041c\u0430\u0440\u0442\u0456\u043d\u0448"
    ],
    "wof:name":"Martins",
    "wof:placetype":"locality"
},
  "geometry": {"coordinates":[32.21083,-25.26556],"type":"Point"}
}