{
  "type": "Feature",
  "properties": {
    "gn:admin1_code":"3.0",
    "gn:asciiname":"Francisco",
    "gn:country_code":"MZ",
    "gn:dem":40,
    "gn:feature_class":"P",
    "gn:feature_code":"PPL",
    "gn:name":"Francisco",
    "gn:population":0,
    "gn:timezone":"Africa/Maputo",
    "iso:country":"MZ",
    "wof:name":"Francisco",
    "wof:placetype":"locality"
},
  "geometry": {"coordinates":[35.14194000000001,-22.29889],"type":"Point"}
}