{
  "type": "Feature",
  "properties": {
    "gn:admin1_code":"1",
    "gn:asciiname":"Mcopia",
    "gn:country_code":"MZ",
    "gn:dem":329,
    "gn:feature_class":"P",
    "gn:feature_code":"PPL",
    "gn:name":"Mc\u00f3pia",
    "gn:population":0,
    "gn:timezone":"Africa/Maputo",
    "iso:country":"MZ",
    "wof:name":"Mcopia",
    "wof:placetype":"locality"
},
  "geometry": {"coordinates":[39.45667,-12.70889],"type":"Point"}
}