{
  "type": "Feature",
  "properties": {
    "gn:admin1_code":"2",
    "gn:asciiname":"Chisselane",
    "gn:country_code":"MZ",
    "gn:dem":192,
    "gn:feature_class":"P",
    "gn:feature_code":"PPL",
    "gn:name":"Chisselane",
    "gn:population":0,
    "gn:timezone":"Africa/Maputo",
    "iso:country":"MZ",
    "name:und_x_variant":[
        "Chitelane"
    ],
    "wof:name":"Chisselane",
    "wof:placetype":"locality"
},
  "geometry": {"coordinates":[31.54861,-22.44139],"type":"Point"}
}