{
  "type": "Feature",
  "properties": {
    "gn:admin1_code":"4",
    "gn:asciiname":"Ringane",
    "gn:country_code":"MZ",
    "gn:dem":101,
    "gn:feature_class":"P",
    "gn:feature_code":"PPL",
    "gn:name":"Ringane",
    "gn:population":0,
    "gn:timezone":"Africa/Maputo",
    "iso:country":"MZ",
    "wof:name":"Ringane",
    "wof:placetype":"locality"
},
  "geometry": {"coordinates":[32.045,-25.46111],"type":"Point"}
}