{
  "type": "Feature",
  "properties": {
    "gn:admin1_code":"9.0",
    "gn:asciiname":"Uadaga",
    "gn:country_code":"MZ",
    "gn:dem":105,
    "gn:feature_class":"P",
    "gn:feature_code":"PPL",
    "gn:name":"U\u00e1dag\u00e0",
    "gn:population":0,
    "gn:timezone":"Africa/Maputo",
    "iso:country":"MZ",
    "wof:name":"Uadaga",
    "wof:placetype":"locality"
},
  "geometry": {"coordinates":[36.6275,-17.23082999999999],"type":"Point"}
}