{
  "type": "Feature",
  "properties": {
    "gn:admin1_code":"9",
    "gn:asciiname":"Madera",
    "gn:country_code":"MZ",
    "gn:dem":29,
    "gn:feature_class":"P",
    "gn:feature_code":"PPL",
    "gn:name":"Madera",
    "gn:population":0,
    "gn:timezone":"Africa/Maputo",
    "iso:country":"MZ",
    "name:bar_x_preferred":[
        "Madera"
    ],
    "name:ceb_x_preferred":[
        "Madera"
    ],
    "name:deu_x_preferred":[
        "Madera"
    ],
    "name:fra_x_preferred":[
        "Madera"
    ],
    "name:ita_x_preferred":[
        "Madera"
    ],
    "name:nld_x_preferred":[
        "Madera"
    ],
    "name:pol_x_preferred":[
        "Madera"
    ],
    "name:por_x_preferred":[
        "Madera"
    ],
    "name:rus_x_preferred":[
        "\u041c\u0430\u0434\u0435\u0440\u0430"
    ],
    "name:spa_x_preferred":[
        "Madera"
    ],
    "name:srp_x_preferred":[
        "\u041c\u0430\u0434\u0435\u0440\u0430"
    ],
    "name:swe_x_preferred":[
        "Madera"
    ],
    "name:ukr_x_preferred":[
        "\u041c\u0430\u0434\u0435\u0440\u0430"
    ],
    "wof:name":"Madera",
    "wof:placetype":"locality"
},
  "geometry": {"coordinates":[37.51806,-17.13694],"type":"Point"}
}