{
  "type": "Feature",
  "properties": {
    "gn:admin1_code":"10",
    "gn:asciiname":"Mecanhira",
    "gn:country_code":"MZ",
    "gn:dem":588,
    "gn:feature_class":"P",
    "gn:feature_code":"PPL",
    "gn:name":"Mecanhira",
    "gn:population":0,
    "gn:timezone":"Africa/Maputo",
    "iso:country":"MZ",
    "wof:name":"Mecanhira",
    "wof:placetype":"locality"
},
  "geometry": {"coordinates":[33.425,-19.34639],"type":"Point"}
}