{
  "type": "Feature",
  "properties": {
    "gn:admin1_code":"3.0",
    "gn:asciiname":"Cabo Mapassela",
    "gn:country_code":"MZ",
    "gn:dem":132,
    "gn:feature_class":"P",
    "gn:feature_code":"PPL",
    "gn:name":"Cabo Mapassela",
    "gn:population":0,
    "gn:timezone":"Africa/Maputo",
    "iso:country":"MZ",
    "wof:name":"Cabo Mapassela",
    "wof:placetype":"locality"
},
  "geometry": {"coordinates":[34.78805999999999,-24.04806],"type":"Point"}
}