{
  "type": "Feature",
  "properties": {
    "gn:admin1_code":"7",
    "gn:asciiname":"Acuirindi",
    "gn:country_code":"MZ",
    "gn:dem":603,
    "gn:feature_class":"P",
    "gn:feature_code":"PPL",
    "gn:name":"Acuirindi",
    "gn:population":0,
    "gn:timezone":"Africa/Maputo",
    "iso:country":"MZ",
    "wof:name":"Acuirindi",
    "wof:placetype":"locality"
},
  "geometry": {"coordinates":[34.81389,-12.96083],"type":"Point"}
}