{
  "type": "Feature",
  "properties": {
    "gn:admin1_code":"3",
    "gn:asciiname":"Mafumane",
    "gn:country_code":"MZ",
    "gn:dem":109,
    "gn:feature_class":"P",
    "gn:feature_code":"PPL",
    "gn:name":"Mafumane",
    "gn:population":0,
    "gn:timezone":"Africa/Maputo",
    "iso:country":"MZ",
    "wof:name":"Mafumane",
    "wof:placetype":"locality"
},
  "geometry": {"coordinates":[34.75694,-23.97472],"type":"Point"}
}