{
  "type": "Feature",
  "properties": {
    "gn:admin1_code":"7",
    "gn:asciiname":"Chefe Namicoio",
    "gn:cc2":"MZ",
    "gn:country_code":"MZ",
    "gn:dem":712,
    "gn:feature_class":"P",
    "gn:feature_code":"PPL",
    "gn:name":"Chefe Namicoio",
    "gn:population":0,
    "gn:timezone":"Africa/Maputo",
    "iso:country":"MZ",
    "name:und_x_variant":[
        "Namicoio",
        "Namecoio",
        "Chefe Namicoio"
    ],
    "wof:name":"Chefe Namicoio",
    "wof:placetype":"locality"
},
  "geometry": {"coordinates":[35.86667,-14.105],"type":"Point"}
}