{
  "type": "Feature",
  "properties": {
    "gn:admin1_code":"7",
    "gn:asciiname":"Caluloma",
    "gn:country_code":"MZ",
    "gn:dem":680,
    "gn:feature_class":"P",
    "gn:feature_code":"PPL",
    "gn:name":"Caluloma",
    "gn:population":0,
    "gn:timezone":"Africa/Maputo",
    "iso:country":"MZ",
    "wof:name":"Caluloma",
    "wof:placetype":"locality"
},
  "geometry": {"coordinates":[35.17972,-12.25222],"type":"Point"}
}