{
  "type": "Feature",
  "properties": {
    "gn:admin1_code":"0.0",
    "gn:asciiname":"Xapala",
    "gn:country_code":"MZ",
    "gn:dem":-9999,
    "gn:feature_class":"P",
    "gn:feature_code":"PPL",
    "gn:name":"Xapala",
    "gn:population":0,
    "gn:timezone":"Africa/Maputo",
    "iso:country":"MZ",
    "wof:name":"Xapala",
    "wof:placetype":"locality"
},
  "geometry": {"coordinates":[40.71667,-14.35],"type":"Point"}
}