{
  "type": "Feature",
  "properties": {
    "gn:admin1_code":"3.0",
    "gn:asciiname":"Cabo mahena",
    "gn:country_code":"MZ",
    "gn:dem":81,
    "gn:feature_class":"P",
    "gn:feature_code":"PPL",
    "gn:name":"Cabo mahena",
    "gn:population":0,
    "gn:timezone":"Africa/Maputo",
    "iso:country":"MZ",
    "wof:name":"Cabo mahena",
    "wof:placetype":"locality"
},
  "geometry": {"coordinates":[35.07139,-24.33028],"type":"Point"}
}