{
  "type": "Feature",
  "properties": {
    "gn:admin1_code":"1",
    "gn:asciiname":"Nimo",
    "gn:country_code":"MZ",
    "gn:dem":769,
    "gn:feature_class":"P",
    "gn:feature_code":"PPL",
    "gn:name":"Nimo",
    "gn:population":0,
    "gn:timezone":"Africa/Maputo",
    "iso:country":"MZ",
    "name:deu_x_preferred":[
        "Nimo"
    ],
    "name:epo_x_preferred":[
        "Nimo"
    ],
    "wof:name":"Nimo",
    "wof:placetype":"locality"
},
  "geometry": {"coordinates":[39.62167,-11.72306],"type":"Point"}
}