{
  "type": "Feature",
  "properties": {
    "gn:admin1_code":"0",
    "gn:asciiname":"Capine",
    "gn:country_code":"MZ",
    "gn:dem":314,
    "gn:feature_class":"P",
    "gn:feature_code":"PPL",
    "gn:name":"Capine",
    "gn:population":0,
    "gn:timezone":"Africa/Maputo",
    "iso:country":"MZ",
    "wof:name":"Capine",
    "wof:placetype":"locality"
},
  "geometry": {"coordinates":[39.93333,-11.43333],"type":"Point"}
}