{
  "type": "Feature",
  "properties": {
    "gn:admin1_code":"3",
    "gn:asciiname":"Marruco",
    "gn:country_code":"MZ",
    "gn:dem":149,
    "gn:feature_class":"P",
    "gn:feature_code":"PPL",
    "gn:name":"Marruco",
    "gn:population":0,
    "gn:timezone":"Africa/Maputo",
    "iso:country":"MZ",
    "wof:name":"Marruco",
    "wof:placetype":"locality"
},
  "geometry": {"coordinates":[34.50417,-22.84],"type":"Point"}
}