{
  "type": "Feature",
  "properties": {
    "gn:admin1_code":"10.0",
    "gn:asciiname":"Txonze",
    "gn:country_code":"MZ",
    "gn:dem":562,
    "gn:feature_class":"P",
    "gn:feature_code":"PPL",
    "gn:name":"Txonze",
    "gn:population":0,
    "gn:timezone":"Africa/Maputo",
    "iso:country":"MZ",
    "wof:name":"Txonze",
    "wof:placetype":"locality"
},
  "geometry": {"coordinates":[33.65583,-17.95472000000001],"type":"Point"}
}