{
  "type": "Feature",
  "properties": {
    "gn:admin1_code":"3.0",
    "gn:asciiname":"Uasselane",
    "gn:country_code":"MZ",
    "gn:dem":117,
    "gn:feature_class":"P",
    "gn:feature_code":"PPL",
    "gn:name":"Uasselane",
    "gn:population":0,
    "gn:timezone":"Africa/Maputo",
    "iso:country":"MZ",
    "wof:name":"Uasselane",
    "wof:placetype":"locality"
},
  "geometry": {"coordinates":[34.92361,-22.45306],"type":"Point"}
}