{
  "type": "Feature",
  "properties": {
    "gn:admin1_code":"5",
    "gn:asciiname":"Muchuachua",
    "gn:country_code":"MZ",
    "gn:dem":125,
    "gn:feature_class":"P",
    "gn:feature_code":"PPL",
    "gn:name":"Muchuachua",
    "gn:population":0,
    "gn:timezone":"Africa/Maputo",
    "iso:country":"MZ",
    "wof:name":"Muchuachua",
    "wof:placetype":"locality"
},
  "geometry": {"coordinates":[34.11667,-21.22306],"type":"Point"}
}