{
  "type": "Feature",
  "properties": {
    "gn:admin1_code":"10",
    "gn:asciiname":"Chicanequisso",
    "gn:country_code":"MZ",
    "gn:dem":225,
    "gn:feature_class":"P",
    "gn:feature_code":"PPL",
    "gn:name":"Chicanequisso",
    "gn:population":0,
    "gn:timezone":"Africa/Maputo",
    "iso:country":"MZ",
    "wof:name":"Chicanequisso",
    "wof:placetype":"locality"
},
  "geometry": {"coordinates":[33.09556,-20.63389],"type":"Point"}
}