{
  "type": "Feature",
  "properties": {
    "gn:admin1_code":"7.0",
    "gn:asciiname":"Uanavexa",
    "gn:country_code":"MZ",
    "gn:dem":646,
    "gn:feature_class":"P",
    "gn:feature_code":"PPL",
    "gn:name":"Uanavexa",
    "gn:population":0,
    "gn:timezone":"Africa/Maputo",
    "iso:country":"MZ",
    "wof:name":"Uanavexa",
    "wof:placetype":"locality"
},
  "geometry": {"coordinates":[36.55694,-13.47361],"type":"Point"}
}