{
  "type": "Feature",
  "properties": {
    "gn:admin1_code":"1",
    "gn:asciiname":"Cavanca",
    "gn:country_code":"MZ",
    "gn:dem":124,
    "gn:feature_class":"P",
    "gn:feature_code":"PPL",
    "gn:name":"Cavanca",
    "gn:population":0,
    "gn:timezone":"Africa/Maputo",
    "iso:country":"MZ",
    "wof:name":"Cavanca",
    "wof:placetype":"locality"
},
  "geometry": {"coordinates":[39.7475,-12.09389],"type":"Point"}
}