{
  "type": "Feature",
  "properties": {
    "gn:admin1_code":"9",
    "gn:asciiname":"Muata",
    "gn:cc2":"MZ",
    "gn:country_code":"MZ",
    "gn:dem":201,
    "gn:feature_class":"P",
    "gn:feature_code":"PPL",
    "gn:name":"Muata",
    "gn:population":0,
    "gn:timezone":"Africa/Maputo",
    "iso:country":"MZ",
    "name:und_x_variant":[
        "Muaco",
        "Muata"
    ],
    "wof:name":"Muata",
    "wof:placetype":"locality"
},
  "geometry": {"coordinates":[37.91,-16.56861],"type":"Point"}
}