{
  "type": "Feature",
  "properties": {
    "gn:admin1_code":"10.0",
    "gn:asciiname":"Aldeia Julius Nyerere",
    "gn:country_code":"MZ",
    "gn:dem":532,
    "gn:feature_class":"P",
    "gn:feature_code":"PPL",
    "gn:name":"Aldeia Julius Nyerere",
    "gn:population":0,
    "gn:timezone":"Africa/Maputo",
    "iso:country":"MZ",
    "wof:name":"Aldeia Julius Nyerere",
    "wof:placetype":"locality"
},
  "geometry": {"coordinates":[33.27944,-18.07222],"type":"Point"}
}