{
  "type": "Feature",
  "properties": {
    "gn:admin1_code":"5",
    "gn:asciiname":"Magota",
    "gn:country_code":"MZ",
    "gn:dem":79,
    "gn:feature_class":"P",
    "gn:feature_code":"PPL",
    "gn:name":"Magota",
    "gn:population":0,
    "gn:timezone":"Africa/Maputo",
    "iso:country":"MZ",
    "wof:name":"Magota",
    "wof:placetype":"locality"
},
  "geometry": {"coordinates":[34.09944,-21.26333],"type":"Point"}
}