{
  "type": "Feature",
  "properties": {
    "gn:admin1_code":"1",
    "gn:asciiname":"Aiuba",
    "gn:country_code":"MZ",
    "gn:dem":565,
    "gn:feature_class":"P",
    "gn:feature_code":"PPL",
    "gn:name":"Ai\u00faba",
    "gn:population":0,
    "gn:timezone":"Africa/Maputo",
    "iso:country":"MZ",
    "wof:name":"Aiuba",
    "wof:placetype":"locality"
},
  "geometry": {"coordinates":[38.42889,-13.58583],"type":"Point"}
}