{
  "type": "Feature",
  "properties": {
    "gn:admin1_code":"6",
    "gn:asciiname":"Jamal",
    "gn:country_code":"MZ",
    "gn:dem":109,
    "gn:feature_class":"P",
    "gn:feature_code":"PPL",
    "gn:name":"Jamal",
    "gn:population":0,
    "gn:timezone":"Africa/Maputo",
    "iso:country":"MZ",
    "wof:name":"Jamal",
    "wof:placetype":"locality"
},
  "geometry": {"coordinates":[40.69417,-14.53472],"type":"Point"}
}