{
  "type": "Feature",
  "properties": {
    "gn:admin1_code":"10.0",
    "gn:asciiname":"Chiconha",
    "gn:country_code":"MZ",
    "gn:dem":716,
    "gn:feature_class":"P",
    "gn:feature_code":"PPL",
    "gn:name":"Chiconha",
    "gn:population":0,
    "gn:timezone":"Africa/Maputo",
    "iso:country":"MZ",
    "wof:name":"Chiconha",
    "wof:placetype":"locality"
},
  "geometry": {"coordinates":[33.18056,-19.36278],"type":"Point"}
}