{
  "type": "Feature",
  "properties": {
    "gn:admin1_code":"1",
    "gn:asciiname":"Regulo Nemoto",
    "gn:cc2":"MZ",
    "gn:country_code":"MZ",
    "gn:dem":69,
    "gn:feature_class":"P",
    "gn:feature_code":"PPL",
    "gn:name":"R\u00e9gulo Nemoto",
    "gn:population":0,
    "gn:timezone":"Africa/Maputo",
    "iso:country":"MZ",
    "name:und_x_variant":[
        "Nemoto",
        "R\u00e9gulo Nemoto"
    ],
    "wof:name":"Regulo Nemoto",
    "wof:placetype":"locality"
},
  "geometry": {"coordinates":[40.34889,-13.35556],"type":"Point"}
}