{
  "type": "Feature",
  "properties": {
    "gn:admin1_code":"1",
    "gn:asciiname":"Chiure",
    "gn:country_code":"MZ",
    "gn:dem":343,
    "gn:feature_class":"P",
    "gn:feature_code":"PPL",
    "gn:name":"Chi\u00fare",
    "gn:population":0,
    "gn:timezone":"Africa/Maputo",
    "iso:country":"MZ",
    "name:cat_x_preferred":[
        "Chi\u00fare"
    ],
    "name:ell_x_preferred":[
        "\u03a4\u03c3\u03b9\u03bf\u03cd\u03c1\u03b5"
    ],
    "name:ita_x_preferred":[
        "Chi\u00fare"
    ],
    "name:pol_x_preferred":[
        "Chi\u00fare"
    ],
    "name:por_x_preferred":[
        "Chi\u00fare"
    ],
    "name:und_x_variant":[
        "Chi\u00fare"
    ],
    "name:zho_x_preferred":[
        "\u5947\u70cf\u96f7"
    ],
    "wof:name":"Chiure",
    "wof:placetype":"locality"
},
  "geometry": {"coordinates":[39.78167,-13.3825],"type":"Point"}
}