{
  "type": "Feature",
  "properties": {
    "gn:admin1_code":"0",
    "gn:asciiname":"Ambissane",
    "gn:country_code":"MZ",
    "gn:dem":158,
    "gn:feature_class":"P",
    "gn:feature_code":"PPL",
    "gn:name":"Ambissane",
    "gn:population":0,
    "gn:timezone":"Africa/Maputo",
    "iso:country":"MZ",
    "wof:name":"Ambissane",
    "wof:placetype":"locality"
},
  "geometry": {"coordinates":[34.38333,-21.93333],"type":"Point"}
}