{
  "type": "Feature",
  "properties": {
    "gn:admin1_code":"6",
    "gn:asciiname":"Pestana",
    "gn:country_code":"MZ",
    "gn:dem":356,
    "gn:feature_class":"P",
    "gn:feature_code":"PPL",
    "gn:name":"Pestana",
    "gn:population":0,
    "gn:timezone":"Africa/Maputo",
    "iso:country":"MZ",
    "wof:name":"Pestana",
    "wof:placetype":"locality"
},
  "geometry": {"coordinates":[39.16917,-15.18194],"type":"Point"}
}