{
  "type": "Feature",
  "properties": {
    "gn:admin1_code":"8.0",
    "gn:asciiname":"Valice",
    "gn:country_code":"MZ",
    "gn:dem":384,
    "gn:feature_class":"P",
    "gn:feature_code":"PPL",
    "gn:name":"Valice",
    "gn:population":0,
    "gn:timezone":"Africa/Maputo",
    "iso:country":"MZ",
    "name:cat_x_preferred":[
        "Valice"
    ],
    "name:epo_x_preferred":[
        "Valice"
    ],
    "name:eus_x_preferred":[
        "Valice"
    ],
    "name:hun_x_preferred":[
        "Als\u00f3v\u00e1ly"
    ],
    "name:ita_x_preferred":[
        "Valice"
    ],
    "name:msa_x_preferred":[
        "Valice"
    ],
    "name:nld_x_preferred":[
        "Valice"
    ],
    "name:pol_x_preferred":[
        "Valice"
    ],
    "name:ron_x_preferred":[
        "Valice"
    ],
    "name:slk_x_preferred":[
        "Valice"
    ],
    "name:spa_x_preferred":[
        "Valice"
    ],
    "name:srp_x_preferred":[
        "\u0412\u0430\u043b\u0438\u0446\u0435"
    ],
    "name:ukr_x_preferred":[
        "\u0412\u0430\u043b\u0456\u0446\u0435"
    ],
    "name:war_x_preferred":[
        "Valice"
    ],
    "wof:name":"Valice",
    "wof:placetype":"locality"
},
  "geometry": {"coordinates":[33.24028,-15.63917],"type":"Point"}
}