{
  "type": "Feature",
  "properties": {
    "gn:admin1_code":"1",
    "gn:asciiname":"Magaia",
    "gn:country_code":"MZ",
    "gn:dem":11,
    "gn:feature_class":"P",
    "gn:feature_code":"PPL",
    "gn:name":"Magaia",
    "gn:population":0,
    "gn:timezone":"Africa/Maputo",
    "iso:country":"MZ",
    "wof:name":"Magaia",
    "wof:placetype":"locality"
},
  "geometry": {"coordinates":[40.36056,-11.30444],"type":"Point"}
}