{
  "type": "Feature",
  "properties": {
    "gn:admin1_code":"3.0",
    "gn:asciiname":"Setela",
    "gn:country_code":"MZ",
    "gn:dem":91,
    "gn:feature_class":"P",
    "gn:feature_code":"PPL",
    "gn:name":"Setela",
    "gn:population":0,
    "gn:timezone":"Africa/Maputo",
    "iso:country":"MZ",
    "wof:name":"Setela",
    "wof:placetype":"locality"
},
  "geometry": {"coordinates":[35.21167,-22.86861],"type":"Point"}
}