{
  "type": "Feature",
  "properties": {
    "gn:admin1_code":"1",
    "gn:asciiname":"Natugo",
    "gn:country_code":"MZ",
    "gn:dem":72,
    "gn:feature_class":"P",
    "gn:feature_code":"PPL",
    "gn:name":"Natugo",
    "gn:population":0,
    "gn:timezone":"Africa/Maputo",
    "iso:country":"MZ",
    "wof:name":"Natugo",
    "wof:placetype":"locality"
},
  "geometry": {"coordinates":[40.37278,-12.69139],"type":"Point"}
}