{
  "type": "Feature",
  "properties": {
    "gn:admin1_code":"6",
    "gn:asciiname":"Cabo Nauaxa",
    "gn:country_code":"MZ",
    "gn:dem":347,
    "gn:feature_class":"P",
    "gn:feature_code":"PPL",
    "gn:name":"Cabo Nauaxa",
    "gn:population":0,
    "gn:timezone":"Africa/Maputo",
    "iso:country":"MZ",
    "wof:name":"Cabo Nauaxa",
    "wof:placetype":"locality"
},
  "geometry": {"coordinates":[39.89444,-13.87778],"type":"Point"}
}