{
  "type": "Feature",
  "properties": {
    "gn:admin1_code":"6",
    "gn:asciiname":"Gemane",
    "gn:country_code":"MZ",
    "gn:dem":504,
    "gn:feature_class":"P",
    "gn:feature_code":"PPL",
    "gn:name":"Gemane",
    "gn:population":0,
    "gn:timezone":"Africa/Maputo",
    "iso:country":"MZ",
    "wof:name":"Gemane",
    "wof:placetype":"locality"
},
  "geometry": {"coordinates":[37.45194,-14.53917],"type":"Point"}
}