{
  "type": "Feature",
  "properties": {
    "gn:admin1_code":"10",
    "gn:asciiname":"Mutaringo",
    "gn:country_code":"MZ",
    "gn:dem":240,
    "gn:feature_class":"P",
    "gn:feature_code":"PPL",
    "gn:name":"Mutaringo",
    "gn:population":0,
    "gn:timezone":"Africa/Maputo",
    "iso:country":"MZ",
    "wof:name":"Mutaringo",
    "wof:placetype":"locality"
},
  "geometry": {"coordinates":[33.52917,-20.72111],"type":"Point"}
}