{
  "type": "Feature",
  "properties": {
    "gn:admin1_code":"3",
    "gn:asciiname":"Cometela",
    "gn:country_code":"MZ",
    "gn:dem":166,
    "gn:feature_class":"P",
    "gn:feature_code":"PPL",
    "gn:name":"Cometela",
    "gn:population":0,
    "gn:timezone":"Africa/Maputo",
    "iso:country":"MZ",
    "wof:name":"Cometela",
    "wof:placetype":"locality"
},
  "geometry": {"coordinates":[34.48361,-21.84306],"type":"Point"}
}