{
  "type": "Feature",
  "properties": {
    "gn:admin1_code":"3.0",
    "gn:asciiname":"Satane",
    "gn:country_code":"MZ",
    "gn:dem":119,
    "gn:feature_class":"P",
    "gn:feature_code":"PPL",
    "gn:name":"Satane",
    "gn:population":0,
    "gn:timezone":"Africa/Maputo",
    "iso:country":"MZ",
    "wof:name":"Satane",
    "wof:placetype":"locality"
},
  "geometry": {"coordinates":[34.75833,-21.88],"type":"Point"}
}