{
  "type": "Feature",
  "properties": {
    "gn:admin1_code":"6",
    "gn:asciiname":"Assuate",
    "gn:country_code":"MZ",
    "gn:dem":209,
    "gn:feature_class":"P",
    "gn:feature_code":"PPL",
    "gn:name":"Assuate",
    "gn:population":0,
    "gn:timezone":"Africa/Maputo",
    "iso:country":"MZ",
    "wof:name":"Assuate",
    "wof:placetype":"locality"
},
  "geometry": {"coordinates":[39.96194000000001,-14.80361],"type":"Point"}
}