{
  "type": "Feature",
  "properties": {
    "gn:admin1_code":"7",
    "gn:asciiname":"Aldeia Namacungua",
    "gn:country_code":"MZ",
    "gn:dem":482,
    "gn:feature_class":"P",
    "gn:feature_code":"PPL",
    "gn:name":"Aldeia Namacungua",
    "gn:population":0,
    "gn:timezone":"Africa/Maputo",
    "iso:country":"MZ",
    "wof:name":"Aldeia Namacungua",
    "wof:placetype":"locality"
},
  "geometry": {"coordinates":[34.71056,-12.41222],"type":"Point"}
}