{
  "type": "Feature",
  "properties": {
    "gn:admin1_code":"3.0",
    "gn:asciiname":"Valente",
    "gn:country_code":"MZ",
    "gn:dem":110,
    "gn:feature_class":"P",
    "gn:feature_code":"PPL",
    "gn:name":"Valente",
    "gn:population":0,
    "gn:timezone":"Africa/Maputo",
    "iso:country":"MZ",
    "wof:name":"Valente",
    "wof:placetype":"locality"
},
  "geometry": {"coordinates":[34.76306,-23.66806],"type":"Point"}
}