{
  "type": "Feature",
  "properties": {
    "gn:admin1_code":"10",
    "gn:asciiname":"Magudo",
    "gn:country_code":"MZ",
    "gn:dem":153,
    "gn:feature_class":"P",
    "gn:feature_code":"PPL",
    "gn:name":"Magudo",
    "gn:population":0,
    "gn:timezone":"Africa/Maputo",
    "iso:country":"MZ",
    "wof:name":"Magudo",
    "wof:placetype":"locality"
},
  "geometry": {"coordinates":[33.30472,-19.88278],"type":"Point"}
}