{
  "type": "Feature",
  "properties": {
    "gn:admin1_code":"6",
    "gn:asciiname":"Maleque",
    "gn:country_code":"MZ",
    "gn:dem":98,
    "gn:feature_class":"P",
    "gn:feature_code":"PPL",
    "gn:name":"M\u00e1leque",
    "gn:population":0,
    "gn:timezone":"Africa/Maputo",
    "iso:country":"MZ",
    "wof:name":"Maleque",
    "wof:placetype":"locality"
},
  "geometry": {"coordinates":[39.31667,-15.88944],"type":"Point"}
}