{
  "type": "Feature",
  "properties": {
    "gn:admin1_code":"8",
    "gn:asciiname":"Dique",
    "gn:country_code":"MZ",
    "gn:dem":250,
    "gn:feature_class":"P",
    "gn:feature_code":"PPL",
    "gn:name":"Dique",
    "gn:population":0,
    "gn:timezone":"Africa/Maputo",
    "iso:country":"MZ",
    "wof:name":"Dique",
    "wof:placetype":"locality"
},
  "geometry": {"coordinates":[33.0375,-16.69889],"type":"Point"}
}