{
  "type": "Feature",
  "properties": {
    "gn:admin1_code":"6",
    "gn:asciiname":"Cangauche",
    "gn:country_code":"MZ",
    "gn:dem":183,
    "gn:feature_class":"P",
    "gn:feature_code":"PPL",
    "gn:name":"Canga\u00fache",
    "gn:population":0,
    "gn:timezone":"Africa/Maputo",
    "iso:country":"MZ",
    "wof:name":"Cangauche",
    "wof:placetype":"locality"
},
  "geometry": {"coordinates":[40.13417000000001,-13.63056],"type":"Point"}
}