{
  "type": "Feature",
  "properties": {
    "gn:admin1_code":"0",
    "gn:asciiname":"Dielo",
    "gn:country_code":"MZ",
    "gn:dem":-9999,
    "gn:feature_class":"P",
    "gn:feature_code":"PPL",
    "gn:name":"Dielo",
    "gn:population":0,
    "gn:timezone":"Africa/Maputo",
    "iso:country":"MZ",
    "wof:name":"Dielo",
    "wof:placetype":"locality"
},
  "geometry": {"coordinates":[40.23333,-15.95],"type":"Point"}
}