{
  "type": "Feature",
  "properties": {
    "gn:admin1_code":"9",
    "gn:asciiname":"Munepa",
    "gn:cc2":"MZ",
    "gn:country_code":"MZ",
    "gn:dem":709,
    "gn:feature_class":"P",
    "gn:feature_code":"PPL",
    "gn:name":"Munepa",
    "gn:population":0,
    "gn:timezone":"Africa/Maputo",
    "iso:country":"MZ",
    "name:und_x_variant":[
        "Mn\u00e9pa",
        "Munepa"
    ],
    "wof:name":"Munepa",
    "wof:placetype":"locality"
},
  "geometry": {"coordinates":[37.60472,-15.28139],"type":"Point"}
}