{
  "type": "Feature",
  "properties": {
    "gn:admin1_code":"0.0",
    "gn:asciiname":"Wikson",
    "gn:country_code":"MZ",
    "gn:dem":1453,
    "gn:feature_class":"P",
    "gn:feature_code":"PPL",
    "gn:name":"Wikson",
    "gn:population":0,
    "gn:timezone":"Africa/Maputo",
    "iso:country":"MZ",
    "wof:name":"Wikson",
    "wof:placetype":"locality"
},
  "geometry": {"coordinates":[34.45,-14.51667],"type":"Point"}
}