{
  "type": "Feature",
  "properties": {
    "gn:admin1_code":"6.0",
    "gn:asciiname":"Puetua",
    "gn:country_code":"MZ",
    "gn:dem":213,
    "gn:feature_class":"P",
    "gn:feature_code":"PPL",
    "gn:name":"Puetua",
    "gn:population":0,
    "gn:timezone":"Africa/Maputo",
    "iso:country":"MZ",
    "wof:name":"Puetua",
    "wof:placetype":"locality"
},
  "geometry": {"coordinates":[40.38167,-13.84111],"type":"Point"}
}