{
  "type": "Feature",
  "properties": {
    "gn:admin1_code":"10",
    "gn:asciiname":"Chapanga",
    "gn:country_code":"MZ",
    "gn:dem":634,
    "gn:feature_class":"P",
    "gn:feature_code":"PPL",
    "gn:name":"Chapanga",
    "gn:population":0,
    "gn:timezone":"Africa/Maputo",
    "iso:country":"MZ",
    "wof:name":"Chapanga",
    "wof:placetype":"locality"
},
  "geometry": {"coordinates":[33.21556,-17.8475],"type":"Point"}
}