{
  "type": "Feature",
  "properties": {
    "gn:admin1_code":"7",
    "gn:asciiname":"Daraimo",
    "gn:country_code":"MZ",
    "gn:dem":518,
    "gn:feature_class":"P",
    "gn:feature_code":"PPL",
    "gn:name":"Daraimo",
    "gn:population":0,
    "gn:timezone":"Africa/Maputo",
    "iso:country":"MZ",
    "wof:name":"Daraimo",
    "wof:placetype":"locality"
},
  "geometry": {"coordinates":[37.71694,-13.80528],"type":"Point"}
}