{
  "type": "Feature",
  "properties": {
    "gn:admin1_code":"2",
    "gn:asciiname":"Banguene",
    "gn:country_code":"MZ",
    "gn:dem":45,
    "gn:feature_class":"P",
    "gn:feature_code":"PPL",
    "gn:name":"Banguene",
    "gn:population":0,
    "gn:timezone":"Africa/Maputo",
    "iso:country":"MZ",
    "wof:name":"Banguene",
    "wof:placetype":"locality"
},
  "geometry": {"coordinates":[32.76889,-24.25056],"type":"Point"}
}