{
  "type": "Feature",
  "properties": {
    "gn:admin1_code":"9",
    "gn:asciiname":"Macuboda",
    "gn:country_code":"MZ",
    "gn:dem":126,
    "gn:feature_class":"P",
    "gn:feature_code":"PPL",
    "gn:name":"Macuboda",
    "gn:population":0,
    "gn:timezone":"Africa/Maputo",
    "iso:country":"MZ",
    "wof:name":"Macuboda",
    "wof:placetype":"locality"
},
  "geometry": {"coordinates":[37.36583,-16.86389],"type":"Point"}
}