{
  "type": "Feature",
  "properties": {
    "gn:admin1_code":"6.0",
    "gn:asciiname":"Ribaue",
    "gn:country_code":"MZ",
    "gn:dem":533,
    "gn:feature_class":"P",
    "gn:feature_code":"PPL",
    "gn:name":"Rib\u00e1u\u00e9",
    "gn:population":0,
    "gn:timezone":"Africa/Maputo",
    "iso:country":"MZ",
    "name:cat_x_preferred":[
        "Rib\u00e1u\u00e8"
    ],
    "name:deu_x_preferred":[
        "Ribau\u00e8"
    ],
    "name:por_x_preferred":[
        "Ribau\u00e9"
    ],
    "name:spa_x_preferred":[
        "Rib\u00e0u\u00e9"
    ],
    "name:und_x_variant":[
        "Rib\u00e1u\u00e9"
    ],
    "name:zho_x_preferred":[
        "\u5229\u5df4\u97cb"
    ],
    "wof:name":"Ribaue",
    "wof:placetype":"locality"
},
  "geometry": {"coordinates":[38.32167000000001,-14.94278],"type":"Point"}
}