{
  "type": "Feature",
  "properties": {
    "gn:admin1_code":"3.0",
    "gn:asciiname":"Jose",
    "gn:country_code":"MZ",
    "gn:dem":41,
    "gn:feature_class":"P",
    "gn:feature_code":"PPL",
    "gn:name":"Jos\u00e9",
    "gn:population":0,
    "gn:timezone":"Africa/Maputo",
    "iso:country":"MZ",
    "name:ceb_x_preferred":[
        "Jose"
    ],
    "name:deu_x_preferred":[
        "Jose"
    ],
    "name:heb_x_preferred":[
        "\u05e8\u05d1\u05d9 \u05d9\u05d5\u05e1\u05d9"
    ],
    "name:ita_x_preferred":[
        "Jose"
    ],
    "name:nld_x_preferred":[
        "Jose"
    ],
    "name:rus_x_preferred":[
        "\u0418\u043e\u0441\u0435"
    ],
    "name:sco_x_preferred":[
        "Jose"
    ],
    "name:swe_x_preferred":[
        "Jose"
    ],
    "name:ukr_x_preferred":[
        "\u0425\u043e\u0441\u0435"
    ],
    "wof:name":"Jose",
    "wof:placetype":"locality"
},
  "geometry": {"coordinates":[35.20361,-22.11611],"type":"Point"}
}