{
  "type": "Feature",
  "properties": {
    "gn:admin1_code":"8",
    "gn:asciiname":"Massimbe",
    "gn:country_code":"MZ",
    "gn:dem":236,
    "gn:feature_class":"P",
    "gn:feature_code":"PPL",
    "gn:name":"Massimb\u00ea",
    "gn:population":0,
    "gn:timezone":"Africa/Maputo",
    "iso:country":"MZ",
    "wof:name":"Massimbe",
    "wof:placetype":"locality"
},
  "geometry": {"coordinates":[33.32028,-15.98167],"type":"Point"}
}