{
  "type": "Feature",
  "properties": {
    "gn:admin1_code":"8",
    "gn:asciiname":"Mandjane",
    "gn:country_code":"MZ",
    "gn:dem":606,
    "gn:feature_class":"P",
    "gn:feature_code":"PPL",
    "gn:name":"Mandjane",
    "gn:population":0,
    "gn:timezone":"Africa/Maputo",
    "iso:country":"MZ",
    "wof:name":"Mandjane",
    "wof:placetype":"locality"
},
  "geometry": {"coordinates":[33.42583,-15.13861],"type":"Point"}
}