{
  "type": "Feature",
  "properties": {
    "gn:admin1_code":"0",
    "gn:asciiname":"Jamal",
    "gn:country_code":"MZ",
    "gn:dem":486,
    "gn:feature_class":"P",
    "gn:feature_code":"PPL",
    "gn:name":"Jamal",
    "gn:population":0,
    "gn:timezone":"Africa/Maputo",
    "iso:country":"MZ",
    "name:ara_x_preferred":[
        "\u062c\u0645\u0627\u0644"
    ],
    "name:aze_x_preferred":[
        "Camal"
    ],
    "name:bul_x_preferred":[
        "\u0414\u0436\u0430\u043c\u0430\u043b"
    ],
    "name:deu_x_preferred":[
        "Dscham\u0101l"
    ],
    "name:ita_x_preferred":[
        "Jamal"
    ],
    "name:rus_x_preferred":[
        "\u0414\u0436\u0430\u043c\u0430\u043b\u044c"
    ],
    "name:swe_x_preferred":[
        "Jamal"
    ],
    "name:tur_x_preferred":[
        "Cem\u00e2l"
    ],
    "wof:name":"Jamal",
    "wof:placetype":"locality"
},
  "geometry": {"coordinates":[39.08333,-13.01667],"type":"Point"}
}