{
  "type": "Feature",
  "properties": {
    "gn:admin1_code":"5.0",
    "gn:asciiname":"Cantina de Centro Agricolo Orizidola",
    "gn:country_code":"MZ",
    "gn:dem":17,
    "gn:feature_class":"P",
    "gn:feature_code":"PPL",
    "gn:name":"Cantina de Centro Agricolo Orizidola",
    "gn:population":0,
    "gn:timezone":"Africa/Maputo",
    "iso:country":"MZ",
    "wof:name":"Cantina de Centro Agricolo Orizidola",
    "wof:placetype":"locality"
},
  "geometry": {"coordinates":[35.83528,-18.16583],"type":"Point"}
}