{
  "type": "Feature",
  "properties": {
    "gn:admin1_code":"3",
    "gn:asciiname":"Ofica",
    "gn:country_code":"MZ",
    "gn:dem":134,
    "gn:feature_class":"P",
    "gn:feature_code":"PPL",
    "gn:name":"Ofi\u00e7a",
    "gn:population":0,
    "gn:timezone":"Africa/Maputo",
    "iso:country":"MZ",
    "wof:name":"Ofica",
    "wof:placetype":"locality"
},
  "geometry": {"coordinates":[34.75917,-22.505],"type":"Point"}
}