{
  "type": "Feature",
  "properties": {
    "gn:admin1_code":"5",
    "gn:asciiname":"Estofo",
    "gn:country_code":"MZ",
    "gn:dem":300,
    "gn:feature_class":"P",
    "gn:feature_code":"PPL",
    "gn:name":"Estofo",
    "gn:population":0,
    "gn:timezone":"Africa/Maputo",
    "iso:country":"MZ",
    "wof:name":"Estofo",
    "wof:placetype":"locality"
},
  "geometry": {"coordinates":[33.88556,-20.25611],"type":"Point"}
}