{
  "type": "Feature",
  "properties": {
    "gn:admin1_code":"5.0",
    "gn:asciiname":"Jemete",
    "gn:country_code":"MZ",
    "gn:dem":239,
    "gn:feature_class":"P",
    "gn:feature_code":"PPL",
    "gn:name":"Jemete",
    "gn:population":0,
    "gn:timezone":"Africa/Maputo",
    "iso:country":"MZ",
    "wof:name":"Jemete",
    "wof:placetype":"locality"
},
  "geometry": {"coordinates":[33.7225,-20.60333],"type":"Point"}
}