{
  "type": "Feature",
  "properties": {
    "gn:admin1_code":"10",
    "gn:asciiname":"Maquine",
    "gn:country_code":"MZ",
    "gn:dem":115,
    "gn:feature_class":"P",
    "gn:feature_code":"PPL",
    "gn:name":"Maquine",
    "gn:population":0,
    "gn:timezone":"Africa/Maputo",
    "iso:country":"MZ",
    "wof:name":"Maquine",
    "wof:placetype":"locality"
},
  "geometry": {"coordinates":[33.74806,-21.10083],"type":"Point"}
}