{
  "type": "Feature",
  "properties": {
    "gn:admin1_code":"7",
    "gn:asciiname":"Jomanda",
    "gn:country_code":"MZ",
    "gn:dem":1210,
    "gn:feature_class":"P",
    "gn:feature_code":"PPL",
    "gn:name":"Jomanda",
    "gn:population":0,
    "gn:timezone":"Africa/Maputo",
    "iso:country":"MZ",
    "wof:name":"Jomanda",
    "wof:placetype":"locality"
},
  "geometry": {"coordinates":[35.34139000000001,-13.26889],"type":"Point"}
}