{
  "type": "Feature",
  "properties": {
    "gn:admin1_code":"5",
    "gn:asciiname":"Marire",
    "gn:country_code":"MZ",
    "gn:dem":124,
    "gn:feature_class":"P",
    "gn:feature_code":"PPL",
    "gn:name":"Marire",
    "gn:population":0,
    "gn:timezone":"Africa/Maputo",
    "iso:country":"MZ",
    "wof:name":"Marire",
    "wof:placetype":"locality"
},
  "geometry": {"coordinates":[33.56972,-20.30472],"type":"Point"}
}