{
  "type": "Feature",
  "properties": {
    "gn:admin1_code":"9",
    "gn:asciiname":"Regulo Jajo",
    "gn:cc2":"MZ",
    "gn:country_code":"MZ",
    "gn:dem":301,
    "gn:feature_class":"P",
    "gn:feature_code":"PPL",
    "gn:name":"R\u00e9gulo Jajo",
    "gn:population":0,
    "gn:timezone":"Africa/Maputo",
    "iso:country":"MZ",
    "name:und_x_variant":[
        "Jajo",
        "R\u00e9gulo Jajo"
    ],
    "wof:name":"Regulo Jajo",
    "wof:placetype":"locality"
},
  "geometry": {"coordinates":[37.51917,-16.27],"type":"Point"}
}