{
  "type": "Feature",
  "properties": {
    "gn:admin1_code":"4",
    "gn:asciiname":"Chale",
    "gn:country_code":"MZ",
    "gn:dem":50,
    "gn:feature_class":"P",
    "gn:feature_code":"PPL",
    "gn:name":"Chale",
    "gn:population":0,
    "gn:timezone":"Africa/Maputo",
    "iso:country":"MZ",
    "name:ceb_x_preferred":[
        "Chale"
    ],
    "name:cym_x_preferred":[
        "Chale"
    ],
    "name:fas_x_preferred":[
        "\u0686\u06cc\u0644"
    ],
    "name:fra_x_preferred":[
        "Chale"
    ],
    "name:ita_x_preferred":[
        "Chale"
    ],
    "name:mal_x_preferred":[
        "\u0d37\u0d3e\u0d32\u0d47"
    ],
    "name:nld_x_preferred":[
        "Chale"
    ],
    "name:pol_x_preferred":[
        "Chale"
    ],
    "name:swe_x_preferred":[
        "Chale"
    ],
    "wof:name":"Chale",
    "wof:placetype":"locality"
},
  "geometry": {"coordinates":[32.55,-26.18333],"type":"Point"}
}