{
  "type": "Feature",
  "properties": {
    "gn:admin1_code":"3.0",
    "gn:asciiname":"Chefe Muamudua",
    "gn:country_code":"MZ",
    "gn:dem":36,
    "gn:feature_class":"P",
    "gn:feature_code":"PPL",
    "gn:name":"Chefe Muam\u00fadua",
    "gn:population":0,
    "gn:timezone":"Africa/Maputo",
    "iso:country":"MZ",
    "wof:name":"Chefe Muamudua",
    "wof:placetype":"locality"
},
  "geometry": {"coordinates":[35.30972,-24.15],"type":"Point"}
}