{
  "type": "Feature",
  "properties": {
    "gn:admin1_code":"8",
    "gn:asciiname":"Chamburuca",
    "gn:country_code":"MZ",
    "gn:dem":156,
    "gn:feature_class":"P",
    "gn:feature_code":"PPL",
    "gn:name":"Chamburuca",
    "gn:population":0,
    "gn:timezone":"Africa/Maputo",
    "iso:country":"MZ",
    "wof:name":"Chamburuca",
    "wof:placetype":"locality"
},
  "geometry": {"coordinates":[33.53083,-16.43222],"type":"Point"}
}