{
  "type": "Feature",
  "properties": {
    "gn:admin1_code":"8",
    "gn:asciiname":"Toma",
    "gn:country_code":"MZ",
    "gn:dem":305,
    "gn:feature_class":"P",
    "gn:feature_code":"PPL",
    "gn:name":"Toma",
    "gn:population":0,
    "gn:timezone":"Africa/Maputo",
    "iso:country":"MZ",
    "wof:name":"Toma",
    "wof:placetype":"locality"
},
  "geometry": {"coordinates":[33.18972,-16.36139],"type":"Point"}
}