{
  "type": "Feature",
  "properties": {
    "gn:admin1_code":"6",
    "gn:asciiname":"Laria",
    "gn:country_code":"MZ",
    "gn:dem":281,
    "gn:feature_class":"P",
    "gn:feature_code":"PPL",
    "gn:name":"Laria",
    "gn:population":0,
    "gn:timezone":"Africa/Maputo",
    "iso:country":"MZ",
    "wof:name":"Laria",
    "wof:placetype":"locality"
},
  "geometry": {"coordinates":[40.11,-14.59472],"type":"Point"}
}