{
  "type": "Feature",
  "properties": {
    "gn:admin1_code":"4",
    "gn:asciiname":"D'jeca",
    "gn:country_code":"MZ",
    "gn:dem":179,
    "gn:feature_class":"P",
    "gn:feature_code":"PPL",
    "gn:name":"D\u2019jeca",
    "gn:population":0,
    "gn:timezone":"Africa/Maputo",
    "iso:country":"MZ",
    "wof:name":"D'jeca",
    "wof:placetype":"locality"
},
  "geometry": {"coordinates":[32.05222,-24.41611],"type":"Point"}
}