{
  "type": "Feature",
  "properties": {
    "gn:admin1_code":"2",
    "gn:asciiname":"Massimbe",
    "gn:country_code":"MZ",
    "gn:dem":112,
    "gn:feature_class":"P",
    "gn:feature_code":"PPL",
    "gn:name":"Massimbe",
    "gn:population":0,
    "gn:timezone":"Africa/Maputo",
    "iso:country":"MZ",
    "wof:name":"Massimbe",
    "wof:placetype":"locality"
},
  "geometry": {"coordinates":[32.30444,-23.30833],"type":"Point"}
}