{
  "type": "Feature",
  "properties": {
    "gn:admin1_code":"3",
    "gn:asciiname":"Chigavane",
    "gn:country_code":"MZ",
    "gn:dem":67,
    "gn:feature_class":"P",
    "gn:feature_code":"PPL",
    "gn:name":"Chigavane",
    "gn:population":0,
    "gn:timezone":"Africa/Maputo",
    "iso:country":"MZ",
    "wof:name":"Chigavane",
    "wof:placetype":"locality"
},
  "geometry": {"coordinates":[34.235,-21.37806],"type":"Point"}
}