{
  "type": "Feature",
  "properties": {
    "gn:admin1_code":"5.0",
    "gn:asciiname":"Bazar",
    "gn:country_code":"MZ",
    "gn:dem":424,
    "gn:feature_class":"P",
    "gn:feature_code":"PPL",
    "gn:name":"Bazar",
    "gn:population":0,
    "gn:timezone":"Africa/Maputo",
    "iso:country":"MZ",
    "name:aze_x_preferred":[
        "Bazar"
    ],
    "name:cat_x_preferred":[
        "Bazar"
    ],
    "name:ceb_x_preferred":[
        "Bazar"
    ],
    "name:eus_x_preferred":[
        "Bazar"
    ],
    "name:fra_x_preferred":[
        "Bazar"
    ],
    "name:glg_x_preferred":[
        "Bazar"
    ],
    "name:kat_x_preferred":[
        "\u10d1\u10d0\u10d6\u10d0\u10e0\u10d8"
    ],
    "name:nld_x_preferred":[
        "Bazar"
    ],
    "name:nor_x_preferred":[
        "Bazar"
    ],
    "name:ron_x_preferred":[
        "Bazar"
    ],
    "name:slv_x_preferred":[
        "Bazar"
    ],
    "name:spa_x_preferred":[
        "Bazar"
    ],
    "name:swe_x_preferred":[
        "Bazar"
    ],
    "wof:name":"Bazar",
    "wof:placetype":"locality"
},
  "geometry": {"coordinates":[34.09528,-18.65417],"type":"Point"}
}