{
  "type": "Feature",
  "properties": {
    "gn:admin1_code":"5",
    "gn:asciiname":"Joao-Gueli",
    "gn:country_code":"MZ",
    "gn:dem":219,
    "gn:feature_class":"P",
    "gn:feature_code":"PPL",
    "gn:name":"Jo\u00e3o-Gueli",
    "gn:population":0,
    "gn:timezone":"Africa/Maputo",
    "iso:country":"MZ",
    "wof:name":"Joao-Gueli",
    "wof:placetype":"locality"
},
  "geometry": {"coordinates":[34.28389,-18.46833],"type":"Point"}
}