{
  "type": "Feature",
  "properties": {
    "gn:admin1_code":"10",
    "gn:asciiname":"Mapai",
    "gn:country_code":"MZ",
    "gn:dem":194,
    "gn:feature_class":"P",
    "gn:feature_code":"PPL",
    "gn:name":"Mapai",
    "gn:population":0,
    "gn:timezone":"Africa/Maputo",
    "iso:country":"MZ",
    "name:ara_x_preferred":[
        "\u0645\u0627\u0628\u0627\u064a"
    ],
    "name:bul_x_preferred":[
        "\u041c\u0430\u043f\u0430\u0438"
    ],
    "name:cat_x_preferred":[
        "Mappay"
    ],
    "name:ces_x_preferred":[
        "Mapaj"
    ],
    "name:dan_x_preferred":[
        "Mapai"
    ],
    "name:deu_x_preferred":[
        "Awoda#Mapai"
    ],
    "name:fas_x_preferred":[
        "\u0645\u0627\u067e\u0627\u06cc"
    ],
    "name:fra_x_preferred":[
        "Mapa\u00ef"
    ],
    "name:heb_x_preferred":[
        "\u05de\u05e4\u05d0\"\u05d9"
    ],
    "name:ind_x_preferred":[
        "Mapai"
    ],
    "name:ita_x_preferred":[
        "Mapai"
    ],
    "name:jav_x_preferred":[
        "Mapai"
    ],
    "name:jpn_x_preferred":[
        "\u30de\u30d1\u30a4"
    ],
    "name:msa_x_preferred":[
        "Mapai"
    ],
    "name:nor_x_preferred":[
        "Mapai"
    ],
    "name:pol_x_preferred":[
        "Mapai"
    ],
    "name:por_x_preferred":[
        "Mapai"
    ],
    "name:slk_x_preferred":[
        "Mapaj"
    ],
    "name:spa_x_preferred":[
        "Mapai"
    ],
    "name:swe_x_preferred":[
        "Mapai"
    ],
    "name:ukr_x_preferred":[
        "\u041c\u0430\u043f\u0430\u0457"
    ],
    "name:ukr_x_variant":[
        "\u041c\u0430\u043f\u0430\u0439"
    ],
    "name:urd_x_preferred":[
        "\u0645\u0627\u067e\u0627\u0626\u06cc"
    ],
    "name:vie_x_preferred":[
        "Mapai"
    ],
    "name:yid_x_preferred":[
        "\u05de\u05e4\u05d0\"\u05d9"
    ],
    "name:zho_x_preferred":[
        "\u4ee5\u8272\u5217\u5730\u5de5\u4eba\u515a"
    ],
    "wof:name":"Mapai",
    "wof:placetype":"locality"
},
  "geometry": {"coordinates":[33.62944,-20.81],"type":"Point"}
}