{
  "type": "Feature",
  "properties": {
    "gn:admin1_code":"10",
    "gn:asciiname":"Mapai",
    "gn:country_code":"MZ",
    "gn:dem":194,
    "gn:feature_class":"P",
    "gn:feature_code":"PPL",
    "gn:name":"Mapai",
    "gn:population":0,
    "gn:timezone":"Africa/Maputo",
    "iso:country":"MZ",
    "wof:name":"Mapai",
    "wof:placetype":"locality"
},
  "geometry": {"coordinates":[33.62944,-20.81],"type":"Point"}
}