{
  "type": "Feature",
  "properties": {
    "gn:admin1_code":"5",
    "gn:asciiname":"Matongua",
    "gn:country_code":"MZ",
    "gn:dem":44,
    "gn:feature_class":"P",
    "gn:feature_code":"PPL",
    "gn:name":"Matongua",
    "gn:population":0,
    "gn:timezone":"Africa/Maputo",
    "iso:country":"MZ",
    "wof:name":"Matongua",
    "wof:placetype":"locality"
},
  "geometry": {"coordinates":[34.20333,-20.74667],"type":"Point"}
}