{
  "type": "Feature",
  "properties": {
    "gn:admin1_code":"9",
    "gn:asciiname":"Mucuruma",
    "gn:country_code":"MZ",
    "gn:dem":42,
    "gn:feature_class":"P",
    "gn:feature_code":"PPL",
    "gn:name":"Mucuruma",
    "gn:population":0,
    "gn:timezone":"Africa/Maputo",
    "iso:country":"MZ",
    "wof:name":"Mucuruma",
    "wof:placetype":"locality"
},
  "geometry": {"coordinates":[37.76722,-17.07694],"type":"Point"}
}