{
  "type": "Feature",
  "properties": {
    "gn:admin1_code":"6.0",
    "gn:asciiname":"Regulo Mutana",
    "gn:country_code":"MZ",
    "gn:dem":51,
    "gn:feature_class":"P",
    "gn:feature_code":"PPL",
    "gn:name":"R\u00e9gulo Mutana",
    "gn:population":0,
    "gn:timezone":"Africa/Maputo",
    "iso:country":"MZ",
    "wof:name":"Regulo Mutana",
    "wof:placetype":"locality"
},
  "geometry": {"coordinates":[39.02278,-16.55556],"type":"Point"}
}