{
  "type": "Feature",
  "properties": {
    "gn:admin1_code":"5",
    "gn:asciiname":"Micheu",
    "gn:country_code":"MZ",
    "gn:dem":28,
    "gn:feature_class":"P",
    "gn:feature_code":"PPL",
    "gn:name":"Micheu",
    "gn:population":0,
    "gn:timezone":"Africa/Maputo",
    "iso:country":"MZ",
    "wof:name":"Micheu",
    "wof:placetype":"locality"
},
  "geometry": {"coordinates":[34.44667,-19.08361],"type":"Point"}
}