{
  "type": "Feature",
  "properties": {
    "gn:admin1_code":"3.0",
    "gn:asciiname":"Vungane",
    "gn:country_code":"MZ",
    "gn:dem":77,
    "gn:feature_class":"P",
    "gn:feature_code":"PPL",
    "gn:name":"Vungane",
    "gn:population":0,
    "gn:timezone":"Africa/Maputo",
    "iso:country":"MZ",
    "wof:name":"Vungane",
    "wof:placetype":"locality"
},
  "geometry": {"coordinates":[34.91333,-24.66556],"type":"Point"}
}