{
  "type": "Feature",
  "properties": {
    "gn:admin1_code":"0",
    "gn:asciiname":"Natebe",
    "gn:country_code":"MZ",
    "gn:dem":581,
    "gn:feature_class":"P",
    "gn:feature_code":"PPL",
    "gn:name":"Natebe",
    "gn:population":0,
    "gn:timezone":"Africa/Maputo",
    "iso:country":"MZ",
    "wof:name":"Natebe",
    "wof:placetype":"locality"
},
  "geometry": {"coordinates":[36.15,-16.16667],"type":"Point"}
}