{
  "type": "Feature",
  "properties": {
    "gn:admin1_code":"3",
    "gn:asciiname":"Mangarrelane",
    "gn:country_code":"MZ",
    "gn:dem":129,
    "gn:feature_class":"P",
    "gn:feature_code":"PPL",
    "gn:name":"Mangarrelane",
    "gn:population":0,
    "gn:timezone":"Africa/Maputo",
    "iso:country":"MZ",
    "wof:name":"Mangarrelane",
    "wof:placetype":"locality"
},
  "geometry": {"coordinates":[33.93611,-22.24556],"type":"Point"}
}