{
  "type": "Feature",
  "properties": {
    "gn:admin1_code":"3.0",
    "gn:asciiname":"Zefanias",
    "gn:country_code":"MZ",
    "gn:dem":180,
    "gn:feature_class":"P",
    "gn:feature_code":"PPL",
    "gn:name":"Zefanias",
    "gn:population":0,
    "gn:timezone":"Africa/Maputo",
    "iso:country":"MZ",
    "wof:name":"Zefanias",
    "wof:placetype":"locality"
},
  "geometry": {"coordinates":[34.36278,-21.65111],"type":"Point"}
}