{
  "type": "Feature",
  "properties": {
    "gn:admin1_code":"6",
    "gn:asciiname":"Manduvi",
    "gn:country_code":"MZ",
    "gn:dem":86,
    "gn:feature_class":"P",
    "gn:feature_code":"PPL",
    "gn:name":"Manduvi",
    "gn:population":0,
    "gn:timezone":"Africa/Maputo",
    "iso:country":"MZ",
    "wof:name":"Manduvi",
    "wof:placetype":"locality"
},
  "geometry": {"coordinates":[40.45389,-14.96889],"type":"Point"}
}