{
  "type": "Feature",
  "properties": {
    "gn:admin1_code":"1",
    "gn:asciiname":"Alfandega",
    "gn:country_code":"MZ",
    "gn:dem":1,
    "gn:feature_class":"P",
    "gn:feature_code":"PPL",
    "gn:name":"Alf\u00e2ndega",
    "gn:population":0,
    "gn:timezone":"Africa/Maputo",
    "iso:country":"MZ",
    "wof:name":"Alfandega",
    "wof:placetype":"locality"
},
  "geometry": {"coordinates":[40.51889,-10.58417],"type":"Point"}
}