{
  "type": "Feature",
  "properties": {
    "gn:admin1_code":"5",
    "gn:asciiname":"Nhamo",
    "gn:country_code":"MZ",
    "gn:dem":58,
    "gn:feature_class":"P",
    "gn:feature_code":"PPL",
    "gn:name":"Nhamo",
    "gn:population":0,
    "gn:timezone":"Africa/Maputo",
    "iso:country":"MZ",
    "wof:name":"Nhamo",
    "wof:placetype":"locality"
},
  "geometry": {"coordinates":[34.29333,-20.51417],"type":"Point"}
}