{
  "type": "Feature",
  "properties": {
    "iso:country":"MZ",
    "name:und_x_variant":[
        "Barra de Limpopo"
    ],
    "qs:gn_country":"MZ",
    "qs:gn_fcode":"PPL",
    "qs:gn_pop":0,
    "qs:name":"Zongoene",
    "qs:name_adm0":"Mo\u00e7ambique",
    "qs:name_adm1":"Gaza",
    "qs:photos":49,
    "qs:photos_1k":10,
    "qs:photos_9k":1,
    "qs:photos_9r":2,
    "qs:photos_all":49,
    "qs:photos_sr":2,
    "qs:placetype":"Town",
    "qs:pop_sr":"0",
    "qs:woe_adm0":23424902,
    "wof:name":"Zongoene",
    "wof:placetype":"locality"
},
  "geometry": {"coordinates":[33.5275,-25.18194],"type":"Point"}
}