{
  "type": "Feature",
  "properties": {
    "gn:admin1_code":"9",
    "gn:asciiname":"Merenha",
    "gn:country_code":"MZ",
    "gn:dem":67,
    "gn:feature_class":"P",
    "gn:feature_code":"PPL",
    "gn:name":"Merenha",
    "gn:population":0,
    "gn:timezone":"Africa/Maputo",
    "iso:country":"MZ",
    "wof:name":"Merenha",
    "wof:placetype":"locality"
},
  "geometry": {"coordinates":[37.84417,-17.10333],"type":"Point"}
}