{
  "type": "Feature",
  "properties": {
    "gn:admin1_code":"2.0",
    "gn:asciiname":"Chilengue",
    "gn:country_code":"MZ",
    "gn:dem":65,
    "gn:feature_class":"P",
    "gn:feature_code":"PPL",
    "gn:name":"Chilengue",
    "gn:population":0,
    "gn:timezone":"Africa/Maputo",
    "iso:country":"MZ",
    "wof:name":"Chilengue",
    "wof:placetype":"locality"
},
  "geometry": {"coordinates":[33.21889,-25.21611],"type":"Point"}
}