{
  "type": "Feature",
  "properties": {
    "gn:admin1_code":"9",
    "gn:asciiname":"Nhacua",
    "gn:country_code":"MZ",
    "gn:dem":25,
    "gn:feature_class":"P",
    "gn:feature_code":"PPL",
    "gn:name":"Nhacua",
    "gn:population":0,
    "gn:timezone":"Africa/Maputo",
    "iso:country":"MZ",
    "wof:name":"Nhacua",
    "wof:placetype":"locality"
},
  "geometry": {"coordinates":[36.86139,-17.46972],"type":"Point"}
}