{
  "type": "Feature",
  "properties": {
    "gn:admin1_code":"10",
    "gn:asciiname":"Fureme",
    "gn:country_code":"MZ",
    "gn:dem":709,
    "gn:feature_class":"P",
    "gn:feature_code":"PPL",
    "gn:name":"Fureme",
    "gn:population":0,
    "gn:timezone":"Africa/Maputo",
    "iso:country":"MZ",
    "wof:name":"Fureme",
    "wof:placetype":"locality"
},
  "geometry": {"coordinates":[32.97333,-18.50556],"type":"Point"}
}