{
  "type": "Feature",
  "properties": {
    "gn:admin1_code":"1",
    "gn:asciiname":"Netali",
    "gn:country_code":"MZ",
    "gn:dem":401,
    "gn:feature_class":"P",
    "gn:feature_code":"PPL",
    "gn:name":"Netali",
    "gn:population":0,
    "gn:timezone":"Africa/Maputo",
    "iso:country":"MZ",
    "wof:name":"Netali",
    "wof:placetype":"locality"
},
  "geometry": {"coordinates":[39.42167,-13.40278],"type":"Point"}
}