{
  "type": "Feature",
  "properties": {
    "gn:admin1_code":"4",
    "gn:asciiname":"Mucote",
    "gn:country_code":"MZ",
    "gn:dem":31,
    "gn:feature_class":"P",
    "gn:feature_code":"PPL",
    "gn:name":"Mucote",
    "gn:population":0,
    "gn:timezone":"Africa/Maputo",
    "iso:country":"MZ",
    "wof:name":"Mucote",
    "wof:placetype":"locality"
},
  "geometry": {"coordinates":[32.74194,-25.28417],"type":"Point"}
}