{
  "type": "Feature",
  "properties": {
    "gn:admin1_code":"7",
    "gn:asciiname":"Napaico",
    "gn:country_code":"MZ",
    "gn:dem":649,
    "gn:feature_class":"P",
    "gn:feature_code":"PPL",
    "gn:name":"Napa\u00edco",
    "gn:population":0,
    "gn:timezone":"Africa/Maputo",
    "iso:country":"MZ",
    "wof:name":"Napaico",
    "wof:placetype":"locality"
},
  "geometry": {"coordinates":[36.10861,-13.59806],"type":"Point"}
}