{
  "type": "Feature",
  "properties": {
    "gn:admin1_code":"8",
    "gn:asciiname":"Farau",
    "gn:country_code":"MZ",
    "gn:dem":483,
    "gn:feature_class":"P",
    "gn:feature_code":"PPL",
    "gn:name":"Farau",
    "gn:population":0,
    "gn:timezone":"Africa/Maputo",
    "iso:country":"MZ",
    "wof:name":"Farau",
    "wof:placetype":"locality"
},
  "geometry": {"coordinates":[33.73778,-15.34278],"type":"Point"}
}