{
  "type": "Feature",
  "properties": {
    "gn:admin1_code":"8.0",
    "gn:asciiname":"Sandaluzi",
    "gn:cc2":"MZ",
    "gn:country_code":"MZ",
    "gn:dem":880,
    "gn:feature_class":"P",
    "gn:feature_code":"PPL",
    "gn:name":"Sandaluzi",
    "gn:population":0,
    "gn:timezone":"Africa/Maputo",
    "iso:country":"MZ",
    "name:und_x_variant":[
        "Sandaluxi",
        "Sandaluzi"
    ],
    "wof:name":"Sandaluzi",
    "wof:placetype":"locality"
},
  "geometry": {"coordinates":[31.37556,-14.96278],"type":"Point"}
}