{
  "type": "Feature",
  "properties": {
    "gn:admin1_code":"2.0",
    "gn:asciiname":"Pequenino",
    "gn:country_code":"MZ",
    "gn:dem":89,
    "gn:feature_class":"P",
    "gn:feature_code":"PPL",
    "gn:name":"Pequenino",
    "gn:population":0,
    "gn:timezone":"Africa/Maputo",
    "iso:country":"MZ",
    "wof:name":"Pequenino",
    "wof:placetype":"locality"
},
  "geometry": {"coordinates":[32.89639,-22.75083],"type":"Point"}
}