{
  "type": "Feature",
  "properties": {
    "gn:admin1_code":"9",
    "gn:asciiname":"Regulo Mucarrua",
    "gn:cc2":"MZ",
    "gn:country_code":"MZ",
    "gn:dem":103,
    "gn:feature_class":"P",
    "gn:feature_code":"PPL",
    "gn:name":"R\u00e9gulo Mucarrua",
    "gn:population":0,
    "gn:timezone":"Africa/Maputo",
    "iso:country":"MZ",
    "name:und_x_variant":[
        "Mecarua",
        "R\u00e9gulo Mucarrua"
    ],
    "wof:name":"Regulo Mucarrua",
    "wof:placetype":"locality"
},
  "geometry": {"coordinates":[37.87972,-16.85417],"type":"Point"}
}