{
  "type": "Feature",
  "properties": {
    "gn:admin1_code":"1",
    "gn:asciiname":"Napalave",
    "gn:country_code":"MZ",
    "gn:dem":517,
    "gn:feature_class":"P",
    "gn:feature_code":"PPL",
    "gn:name":"Napalave",
    "gn:population":0,
    "gn:timezone":"Africa/Maputo",
    "iso:country":"MZ",
    "wof:name":"Napalave",
    "wof:placetype":"locality"
},
  "geometry": {"coordinates":[39.10583,-13.22333],"type":"Point"}
}