{
  "type": "Feature",
  "properties": {
    "gn:admin1_code":"8",
    "gn:asciiname":"Cauere",
    "gn:country_code":"MZ",
    "gn:dem":641,
    "gn:feature_class":"P",
    "gn:feature_code":"PPL",
    "gn:name":"Cauere",
    "gn:population":0,
    "gn:timezone":"Africa/Maputo",
    "iso:country":"MZ",
    "wof:name":"Cauere",
    "wof:placetype":"locality"
},
  "geometry": {"coordinates":[33.27361,-14.98833],"type":"Point"}
}