{
  "type": "Feature",
  "properties": {
    "gn:admin1_code":"3",
    "gn:asciiname":"Chicuimo",
    "gn:cc2":"MZ",
    "gn:country_code":"MZ",
    "gn:dem":92,
    "gn:feature_class":"P",
    "gn:feature_code":"PPL",
    "gn:name":"Chicuimo",
    "gn:population":0,
    "gn:timezone":"Africa/Maputo",
    "iso:country":"MZ",
    "name:und_x_variant":[
        "Chissuca",
        "Chicuimo"
    ],
    "wof:name":"Chicuimo",
    "wof:placetype":"locality"
},
  "geometry": {"coordinates":[34.12306,-23.36222],"type":"Point"}
}