{
  "type": "Feature",
  "properties": {
    "gn:admin1_code":"8.0",
    "gn:asciiname":"Viola",
    "gn:country_code":"MZ",
    "gn:dem":190,
    "gn:feature_class":"P",
    "gn:feature_code":"PPL",
    "gn:name":"Viola",
    "gn:population":0,
    "gn:timezone":"Africa/Maputo",
    "iso:country":"MZ",
    "wof:name":"Viola",
    "wof:placetype":"locality"
},
  "geometry": {"coordinates":[33.37667,-16.53667],"type":"Point"}
}