{
  "type": "Feature",
  "properties": {
    "gn:admin1_code":"6.0",
    "gn:asciiname":"Muendazi",
    "gn:country_code":"MZ",
    "gn:dem":143,
    "gn:feature_class":"P",
    "gn:feature_code":"PPL",
    "gn:name":"Muendazi",
    "gn:population":0,
    "gn:timezone":"Africa/Maputo",
    "iso:country":"MZ",
    "wof:name":"Muendazi",
    "wof:placetype":"locality"
},
  "geometry": {"coordinates":[40.67207,-14.66829],"type":"Point"}
}