{
  "type": "Feature",
  "properties": {
    "gn:admin1_code":"3",
    "gn:asciiname":"Meloi Natal",
    "gn:cc2":"MZ",
    "gn:country_code":"MZ",
    "gn:dem":42,
    "gn:feature_class":"P",
    "gn:feature_code":"PPL",
    "gn:name":"Meloi Natal",
    "gn:population":0,
    "gn:timezone":"Africa/Maputo",
    "iso:country":"MZ",
    "name:und_x_variant":[
        "Natalia",
        "Meloi Natal"
    ],
    "wof:name":"Meloi Natal",
    "wof:placetype":"locality"
},
  "geometry": {"coordinates":[35.17194,-21.48556],"type":"Point"}
}