{
  "type": "Feature",
  "properties": {
    "gn:admin1_code":"2.0",
    "gn:asciiname":"Chelene",
    "gn:country_code":"MZ",
    "gn:dem":39,
    "gn:feature_class":"P",
    "gn:feature_code":"PPL",
    "gn:name":"Chelene",
    "gn:population":0,
    "gn:timezone":"Africa/Maputo",
    "iso:country":"MZ",
    "wof:name":"Chelene",
    "wof:placetype":"locality"
},
  "geometry": {"coordinates":[33.93694,-24.11889],"type":"Point"}
}