{
  "type": "Feature",
  "properties": {
    "gn:admin1_code":"6",
    "gn:asciiname":"Amissi",
    "gn:country_code":"MZ",
    "gn:dem":532,
    "gn:feature_class":"P",
    "gn:feature_code":"PPL",
    "gn:name":"Amissi",
    "gn:population":0,
    "gn:timezone":"Africa/Maputo",
    "iso:country":"MZ",
    "wof:name":"Amissi",
    "wof:placetype":"locality"
},
  "geometry": {"coordinates":[37.45583,-14.63972],"type":"Point"}
}