{
  "type": "Feature",
  "properties": {
    "gn:admin1_code":"8",
    "gn:asciiname":"Macane",
    "gn:country_code":"MZ",
    "gn:dem":465,
    "gn:feature_class":"P",
    "gn:feature_code":"PPL",
    "gn:name":"Macane",
    "gn:population":0,
    "gn:timezone":"Africa/Maputo",
    "iso:country":"MZ",
    "wof:name":"Macane",
    "wof:placetype":"locality"
},
  "geometry": {"coordinates":[32.66056,-15.36333],"type":"Point"}
}