{
  "type": "Feature",
  "properties": {
    "gn:admin1_code":"6",
    "gn:asciiname":"Raute",
    "gn:country_code":"MZ",
    "gn:dem":259,
    "gn:feature_class":"P",
    "gn:feature_code":"PPL",
    "gn:name":"Raute",
    "gn:population":0,
    "gn:timezone":"Africa/Maputo",
    "iso:country":"MZ",
    "name:deu_x_preferred":[
        "Raute"
    ],
    "wof:name":"Raute",
    "wof:placetype":"locality"
},
  "geometry": {"coordinates":[39.45833,-15.53278],"type":"Point"}
}