{
  "type": "Feature",
  "properties": {
    "gn:admin1_code":"3.0",
    "gn:asciiname":"Cabo Gulela",
    "gn:country_code":"MZ",
    "gn:dem":35,
    "gn:feature_class":"P",
    "gn:feature_code":"PPL",
    "gn:name":"Cabo Gulela",
    "gn:population":0,
    "gn:timezone":"Africa/Maputo",
    "iso:country":"MZ",
    "wof:name":"Cabo Gulela",
    "wof:placetype":"locality"
},
  "geometry": {"coordinates":[35.05556,-24.48472000000001],"type":"Point"}
}