{
  "type": "Feature",
  "properties": {
    "gn:admin1_code":"2.0",
    "gn:asciiname":"Tchaila",
    "gn:country_code":"MZ",
    "gn:dem":57,
    "gn:feature_class":"P",
    "gn:feature_code":"PPL",
    "gn:name":"Tchaila",
    "gn:population":0,
    "gn:timezone":"Africa/Maputo",
    "iso:country":"MZ",
    "wof:name":"Tchaila",
    "wof:placetype":"locality"
},
  "geometry": {"coordinates":[33.81111,-23.22361],"type":"Point"}
}