{
  "type": "Feature",
  "properties": {
    "gn:admin1_code":"2.0",
    "gn:asciiname":"Chefe Cuambe",
    "gn:country_code":"MZ",
    "gn:dem":82,
    "gn:feature_class":"P",
    "gn:feature_code":"PPL",
    "gn:name":"Chefe Cuambe",
    "gn:population":0,
    "gn:timezone":"Africa/Maputo",
    "iso:country":"MZ",
    "wof:name":"Chefe Cuambe",
    "wof:placetype":"locality"
},
  "geometry": {"coordinates":[33.81722,-24.82111],"type":"Point"}
}