{
  "type": "Feature",
  "properties": {
    "gn:admin1_code":"2.0",
    "gn:asciiname":"Davide Gege",
    "gn:country_code":"MZ",
    "gn:dem":33,
    "gn:feature_class":"P",
    "gn:feature_code":"PPL",
    "gn:name":"Davide Gege",
    "gn:population":0,
    "gn:timezone":"Africa/Maputo",
    "iso:country":"MZ",
    "wof:name":"Davide Gege",
    "wof:placetype":"locality"
},
  "geometry": {"coordinates":[34.21028,-24.70028],"type":"Point"}
}