{
  "type": "Feature",
  "properties": {
    "gn:admin1_code":"6",
    "gn:asciiname":"Firmino",
    "gn:country_code":"MZ",
    "gn:dem":446,
    "gn:feature_class":"P",
    "gn:feature_code":"PPL",
    "gn:name":"Firmino",
    "gn:population":0,
    "gn:timezone":"Africa/Maputo",
    "iso:country":"MZ",
    "name:deu_x_preferred":[
        "Firmino"
    ],
    "name:por_x_preferred":[
        "Firmino"
    ],
    "name:ukr_x_preferred":[
        "\u0424\u0456\u0440\u043c\u0456\u043d\u043e"
    ],
    "wof:name":"Firmino",
    "wof:placetype":"locality"
},
  "geometry": {"coordinates":[39.38361,-14.59222],"type":"Point"}
}