{
  "type": "Feature",
  "properties": {
    "gn:admin1_code":"1",
    "gn:asciiname":"Micongo",
    "gn:country_code":"MZ",
    "gn:dem":901,
    "gn:feature_class":"P",
    "gn:feature_code":"PPL",
    "gn:name":"Micongo",
    "gn:population":0,
    "gn:timezone":"Africa/Maputo",
    "iso:country":"MZ",
    "wof:name":"Micongo",
    "wof:placetype":"locality"
},
  "geometry": {"coordinates":[39.49361,-11.53194],"type":"Point"}
}