{
  "type": "Feature",
  "properties": {
    "gn:admin1_code":"9",
    "gn:asciiname":"Porraca",
    "gn:country_code":"MZ",
    "gn:dem":738,
    "gn:feature_class":"P",
    "gn:feature_code":"PPL",
    "gn:name":"Porraca",
    "gn:population":0,
    "gn:timezone":"Africa/Maputo",
    "iso:country":"MZ",
    "wof:name":"Porraca",
    "wof:placetype":"locality"
},
  "geometry": {"coordinates":[37.21083,-15.47222],"type":"Point"}
}