{
  "type": "Feature",
  "properties": {
    "gn:admin1_code":"3",
    "gn:asciiname":"Cabo Gala",
    "gn:cc2":"MZ",
    "gn:country_code":"MZ",
    "gn:dem":97,
    "gn:feature_class":"P",
    "gn:feature_code":"PPL",
    "gn:name":"Cabo Gala",
    "gn:population":0,
    "gn:timezone":"Africa/Maputo",
    "iso:country":"MZ",
    "name:und_x_variant":[
        "Gala",
        "Cabo Gala"
    ],
    "wof:name":"Cabo Gala",
    "wof:placetype":"locality"
},
  "geometry": {"coordinates":[35.17722,-24.17083],"type":"Point"}
}