{
  "type": "Feature",
  "properties": {
    "gn:admin1_code":"3",
    "gn:asciiname":"Mazarete",
    "gn:cc2":"MZ",
    "gn:country_code":"MZ",
    "gn:dem":6,
    "gn:feature_class":"P",
    "gn:feature_code":"PPL",
    "gn:name":"Mazarete",
    "gn:population":0,
    "gn:timezone":"Africa/Maputo",
    "iso:country":"MZ",
    "name:arg_x_preferred":[
        "Mazarete"
    ],
    "name:ast_x_preferred":[
        "Mazarete"
    ],
    "name:cat_x_preferred":[
        "Mazarete"
    ],
    "name:ceb_x_preferred":[
        "Mazarete"
    ],
    "name:epo_x_preferred":[
        "Mazarete"
    ],
    "name:eus_x_preferred":[
        "Mazarete"
    ],
    "name:fra_x_preferred":[
        "Mazarete"
    ],
    "name:hun_x_preferred":[
        "Mazarete"
    ],
    "name:hye_x_preferred":[
        "\u0544\u0561\u057d\u0561\u0580\u0565\u057f\u0565"
    ],
    "name:ina_x_preferred":[
        "Mazarete"
    ],
    "name:ita_x_preferred":[
        "Mazarete"
    ],
    "name:kaz_x_preferred":[
        "\u041c\u0430\u0441\u0430\u0440\u0435\u0442\u0435"
    ],
    "name:msa_x_preferred":[
        "Mazarete"
    ],
    "name:nld_x_preferred":[
        "Mazarete"
    ],
    "name:oci_x_preferred":[
        "Mazarete"
    ],
    "name:pol_x_preferred":[
        "Mazarete"
    ],
    "name:por_x_preferred":[
        "Mazarete"
    ],
    "name:rus_x_preferred":[
        "\u041c\u0430\u0441\u0430\u0440\u0435\u0442\u0435"
    ],
    "name:spa_x_preferred":[
        "Mazarete"
    ],
    "name:swe_x_preferred":[
        "Mazarete"
    ],
    "name:ukr_x_preferred":[
        "\u041c\u0430\u0441\u0430\u0440\u0435\u0442\u0435"
    ],
    "name:und_x_variant":[
        "Madamo",
        "Mazarete"
    ],
    "name:vie_x_preferred":[
        "Mazarete"
    ],
    "name:war_x_preferred":[
        "Mazarete"
    ],
    "name:zho_x_preferred":[
        "\u9a6c\u8428\u96f7\u7279"
    ],
    "wof:name":"Mazarete",
    "wof:placetype":"locality"
},
  "geometry": {"coordinates":[35.46361,-22.09833],"type":"Point"}
}