{
  "type": "Feature",
  "properties": {
    "gn:admin1_code":"10",
    "gn:asciiname":"Caniaculo",
    "gn:country_code":"MZ",
    "gn:dem":284,
    "gn:feature_class":"P",
    "gn:feature_code":"PPL",
    "gn:name":"Caniaculo",
    "gn:population":0,
    "gn:timezone":"Africa/Maputo",
    "iso:country":"MZ",
    "wof:name":"Caniaculo",
    "wof:placetype":"locality"
},
  "geometry": {"coordinates":[33.80139,-16.76778],"type":"Point"}
}