{
  "type": "Feature",
  "properties": {
    "gn:admin1_code":"4",
    "gn:asciiname":"Manhalase",
    "gn:country_code":"MZ",
    "gn:dem":488,
    "gn:feature_class":"P",
    "gn:feature_code":"PPL",
    "gn:name":"Manhalase",
    "gn:population":0,
    "gn:timezone":"Africa/Maputo",
    "iso:country":"MZ",
    "wof:name":"Manhalase",
    "wof:placetype":"locality"
},
  "geometry": {"coordinates":[32.04972,-25.95306],"type":"Point"}
}