{
  "type": "Feature",
  "properties": {
    "gn:admin1_code":"2.0",
    "gn:asciiname":"Regedor Siaia",
    "gn:country_code":"MZ",
    "gn:dem":97,
    "gn:feature_class":"P",
    "gn:feature_code":"PPL",
    "gn:name":"Regedor Siaia",
    "gn:population":0,
    "gn:timezone":"Africa/Maputo",
    "iso:country":"MZ",
    "wof:name":"Regedor Siaia",
    "wof:placetype":"locality"
},
  "geometry": {"coordinates":[33.76444,-24.95389],"type":"Point"}
}