{
  "type": "Feature",
  "properties": {
    "gn:admin1_code":"2.0",
    "gn:asciiname":"Aldeia Comunais III Congresso",
    "gn:country_code":"MZ",
    "gn:dem":66,
    "gn:feature_class":"P",
    "gn:feature_code":"PPL",
    "gn:name":"Aldeia Comunais III Congresso",
    "gn:population":0,
    "gn:timezone":"Africa/Maputo",
    "iso:country":"MZ",
    "wof:name":"Aldeia Comunais III Congresso",
    "wof:placetype":"locality"
},
  "geometry": {"coordinates":[32.50639,-24.16417],"type":"Point"}
}