{
  "type": "Feature",
  "properties": {
    "gn:admin1_code":"5",
    "gn:asciiname":"Macuvuia",
    "gn:country_code":"MZ",
    "gn:dem":69,
    "gn:feature_class":"P",
    "gn:feature_code":"PPL",
    "gn:name":"Macuvuia",
    "gn:population":0,
    "gn:timezone":"Africa/Maputo",
    "iso:country":"MZ",
    "wof:name":"Macuvuia",
    "wof:placetype":"locality"
},
  "geometry": {"coordinates":[34.16806,-20.59694],"type":"Point"}
}