{
  "type": "Feature",
  "properties": {
    "gn:admin1_code":"8",
    "gn:asciiname":"Coutinho",
    "gn:country_code":"MZ",
    "gn:dem":474,
    "gn:feature_class":"P",
    "gn:feature_code":"PPL",
    "gn:name":"Coutinho",
    "gn:population":0,
    "gn:timezone":"Africa/Maputo",
    "iso:country":"MZ",
    "name:por_x_preferred":[
        "Coutinho"
    ],
    "wof:name":"Coutinho",
    "wof:placetype":"locality"
},
  "geometry": {"coordinates":[31.58863,-16.06311],"type":"Point"}
}