{
  "type": "Feature",
  "properties": {
    "gn:admin1_code":"9",
    "gn:asciiname":"Naoloxe",
    "gn:country_code":"MZ",
    "gn:dem":442,
    "gn:feature_class":"P",
    "gn:feature_code":"PPL",
    "gn:name":"Naoloxe",
    "gn:population":0,
    "gn:timezone":"Africa/Maputo",
    "iso:country":"MZ",
    "wof:name":"Naoloxe",
    "wof:placetype":"locality"
},
  "geometry": {"coordinates":[37.70389,-15.9525],"type":"Point"}
}