{
  "type": "Feature",
  "properties": {
    "gn:admin1_code":"8",
    "gn:asciiname":"Cachene",
    "gn:country_code":"MZ",
    "gn:dem":1405,
    "gn:feature_class":"P",
    "gn:feature_code":"PPL",
    "gn:name":"Cachene",
    "gn:population":0,
    "gn:timezone":"Africa/Maputo",
    "iso:country":"MZ",
    "wof:name":"Cachene",
    "wof:placetype":"locality"
},
  "geometry": {"coordinates":[34.47639,-14.58333],"type":"Point"}
}