{
  "type": "Feature",
  "properties": {
    "gn:admin1_code":"2.0",
    "gn:asciiname":"Massunguine",
    "gn:country_code":"MZ",
    "gn:dem":189,
    "gn:feature_class":"P",
    "gn:feature_code":"PPL",
    "gn:name":"Massunguine",
    "gn:population":0,
    "gn:timezone":"Africa/Maputo",
    "iso:country":"MZ",
    "wof:name":"Massunguine",
    "wof:placetype":"locality"
},
  "geometry": {"coordinates":[31.77528,-23.43278],"type":"Point"}
}