{
  "type": "Feature",
  "properties": {
    "gn:admin1_code":"5",
    "gn:asciiname":"Cubimbe",
    "gn:country_code":"MZ",
    "gn:dem":196,
    "gn:feature_class":"P",
    "gn:feature_code":"PPL",
    "gn:name":"Cubimbe",
    "gn:population":0,
    "gn:timezone":"Africa/Maputo",
    "iso:country":"MZ",
    "wof:name":"Cubimbe",
    "wof:placetype":"locality"
},
  "geometry": {"coordinates":[33.85805999999999,-20.49667],"type":"Point"}
}