{
  "type": "Feature",
  "properties": {
    "gn:admin1_code":"0",
    "gn:asciiname":"Mavume",
    "gn:country_code":"MZ",
    "gn:dem":139,
    "gn:feature_class":"P",
    "gn:feature_code":"PPL",
    "gn:name":"Mavume",
    "gn:population":0,
    "gn:timezone":"Africa/Maputo",
    "iso:country":"MZ",
    "wof:name":"Mavume",
    "wof:placetype":"locality"
},
  "geometry": {"coordinates":[34.48333,-21.43333],"type":"Point"}
}