{
  "type": "Feature",
  "properties": {
    "gn:admin1_code":"10",
    "gn:asciiname":"Matalasse",
    "gn:country_code":"MZ",
    "gn:dem":337,
    "gn:feature_class":"P",
    "gn:feature_code":"PPL",
    "gn:name":"Matalasse",
    "gn:population":0,
    "gn:timezone":"Africa/Maputo",
    "iso:country":"MZ",
    "wof:name":"Matalasse",
    "wof:placetype":"locality"
},
  "geometry": {"coordinates":[33.29222,-20.85389],"type":"Point"}
}