{
  "type": "Feature",
  "properties": {
    "gn:admin1_code":"7",
    "gn:asciiname":"Mapinge",
    "gn:country_code":"MZ",
    "gn:dem":922,
    "gn:feature_class":"P",
    "gn:feature_code":"PPL",
    "gn:name":"Mapinge",
    "gn:population":0,
    "gn:timezone":"Africa/Maputo",
    "iso:country":"MZ",
    "wof:name":"Mapinge",
    "wof:placetype":"locality"
},
  "geometry": {"coordinates":[35.62833,-13.95806],"type":"Point"}
}