{
  "type": "Feature",
  "properties": {
    "gn:admin1_code":"10.0",
    "gn:asciiname":"Nguawala",
    "gn:country_code":"MZ",
    "gn:dem":552,
    "gn:feature_class":"P",
    "gn:feature_code":"PPL",
    "gn:name":"Nguawala",
    "gn:population":0,
    "gn:timezone":"Africa/Maputo",
    "iso:country":"MZ",
    "wof:name":"Nguawala",
    "wof:placetype":"locality"
},
  "geometry": {"coordinates":[33.60361,-18.41306],"type":"Point"}
}