{
  "type": "Feature",
  "properties": {
    "gn:admin1_code":"3.0",
    "gn:asciiname":"Cat. Episcopal Bambela",
    "gn:country_code":"MZ",
    "gn:dem":83,
    "gn:feature_class":"P",
    "gn:feature_code":"PPL",
    "gn:name":"Cat. Episcopal Bambela",
    "gn:population":0,
    "gn:timezone":"Africa/Maputo",
    "iso:country":"MZ",
    "wof:name":"Cat. Episcopal Bambela",
    "wof:placetype":"locality"
},
  "geometry": {"coordinates":[35.13694,-24.25639],"type":"Point"}
}