{
  "type": "Feature",
  "properties": {
    "gn:admin1_code":"3",
    "gn:asciiname":"Mabongo",
    "gn:country_code":"MZ",
    "gn:dem":47,
    "gn:feature_class":"P",
    "gn:feature_code":"PPL",
    "gn:name":"Mabongo",
    "gn:population":0,
    "gn:timezone":"Africa/Maputo",
    "iso:country":"MZ",
    "wof:name":"Mabongo",
    "wof:placetype":"locality"
},
  "geometry": {"coordinates":[34.875,-21.27167],"type":"Point"}
}