{
  "type": "Feature",
  "properties": {
    "gn:admin1_code":"1",
    "gn:asciiname":"Chipembe",
    "gn:country_code":"MZ",
    "gn:dem":536,
    "gn:feature_class":"P",
    "gn:feature_code":"PPL",
    "gn:name":"Chipembe",
    "gn:population":0,
    "gn:timezone":"Africa/Maputo",
    "iso:country":"MZ",
    "wof:name":"Chipembe",
    "wof:placetype":"locality"
},
  "geometry": {"coordinates":[38.55889000000001,-13.19861],"type":"Point"}
}