{
  "type": "Feature",
  "properties": {
    "gn:admin1_code":"9",
    "gn:asciiname":"Mamala",
    "gn:country_code":"MZ",
    "gn:dem":285,
    "gn:feature_class":"P",
    "gn:feature_code":"PPL",
    "gn:name":"Mamala",
    "gn:population":0,
    "gn:timezone":"Africa/Maputo",
    "iso:country":"MZ",
    "wof:name":"Mamala",
    "wof:placetype":"locality"
},
  "geometry": {"coordinates":[38.57583,-15.95556],"type":"Point"}
}