{
  "type": "Feature",
  "properties": {
    "gn:admin1_code":"1.0",
    "gn:asciiname":"Poja",
    "gn:country_code":"MZ",
    "gn:dem":295,
    "gn:feature_class":"P",
    "gn:feature_code":"PPL",
    "gn:name":"Poja",
    "gn:population":0,
    "gn:timezone":"Africa/Maputo",
    "iso:country":"MZ",
    "wof:name":"Poja",
    "wof:placetype":"locality"
},
  "geometry": {"coordinates":[39.66694,-11.14444],"type":"Point"}
}