{
  "type": "Feature",
  "properties": {
    "gn:admin1_code":"1",
    "gn:asciiname":"Cambir",
    "gn:country_code":"MZ",
    "gn:dem":504,
    "gn:feature_class":"P",
    "gn:feature_code":"PPL",
    "gn:name":"Cambir",
    "gn:population":0,
    "gn:timezone":"Africa/Maputo",
    "iso:country":"MZ",
    "wof:name":"Cambir",
    "wof:placetype":"locality"
},
  "geometry": {"coordinates":[38.95333,-13.25306],"type":"Point"}
}