{
  "type": "Feature",
  "properties": {
    "gn:admin1_code":"5.0",
    "gn:asciiname":"Zeja",
    "gn:country_code":"MZ",
    "gn:dem":193,
    "gn:feature_class":"P",
    "gn:feature_code":"PPL",
    "gn:name":"Zeja",
    "gn:population":0,
    "gn:timezone":"Africa/Maputo",
    "iso:country":"MZ",
    "wof:name":"Zeja",
    "wof:placetype":"locality"
},
  "geometry": {"coordinates":[33.77417,-20.62222],"type":"Point"}
}