{
  "type": "Feature",
  "properties": {
    "gn:admin1_code":"6",
    "gn:asciiname":"Parani",
    "gn:country_code":"MZ",
    "gn:dem":581,
    "gn:feature_class":"P",
    "gn:feature_code":"PPL",
    "gn:name":"Paran\u00ed",
    "gn:population":0,
    "gn:timezone":"Africa/Maputo",
    "iso:country":"MZ",
    "wof:name":"Parani",
    "wof:placetype":"locality"
},
  "geometry": {"coordinates":[37.88083,-14.92972],"type":"Point"}
}