{
  "type": "Feature",
  "properties": {
    "gn:admin1_code":"0",
    "gn:asciiname":"Cheringa",
    "gn:country_code":"MZ",
    "gn:dem":98,
    "gn:feature_class":"P",
    "gn:feature_code":"PPL",
    "gn:name":"Cheringa",
    "gn:population":0,
    "gn:timezone":"Africa/Maputo",
    "iso:country":"MZ",
    "wof:name":"Cheringa",
    "wof:placetype":"locality"
},
  "geometry": {"coordinates":[32.26667,-25.01667],"type":"Point"}
}