{
  "type": "Feature",
  "properties": {
    "gn:admin1_code":"2.0",
    "gn:asciiname":"M. Vilanculos",
    "gn:country_code":"MZ",
    "gn:dem":51,
    "gn:feature_class":"P",
    "gn:feature_code":"PPL",
    "gn:name":"M. Vilanculos",
    "gn:population":0,
    "gn:timezone":"Africa/Maputo",
    "iso:country":"MZ",
    "wof:name":"M. Vilanculos",
    "wof:placetype":"locality"
},
  "geometry": {"coordinates":[34.32,-24.50833],"type":"Point"}
}