{
  "type": "Feature",
  "properties": {
    "gn:admin1_code":"3.0",
    "gn:asciiname":"Shelene",
    "gn:country_code":"MZ",
    "gn:dem":123,
    "gn:feature_class":"P",
    "gn:feature_code":"PPL",
    "gn:name":"Shelene",
    "gn:population":0,
    "gn:timezone":"Africa/Maputo",
    "iso:country":"MZ",
    "wof:name":"Shelene",
    "wof:placetype":"locality"
},
  "geometry": {"coordinates":[34.29917,-22.94917],"type":"Point"}
}