{
  "type": "Feature",
  "properties": {
    "gn:admin1_code":"0",
    "gn:asciiname":"Chavieque",
    "gn:country_code":"MZ",
    "gn:dem":213,
    "gn:feature_class":"P",
    "gn:feature_code":"PPL",
    "gn:name":"Chavieque",
    "gn:population":0,
    "gn:timezone":"Africa/Maputo",
    "iso:country":"MZ",
    "wof:name":"Chavieque",
    "wof:placetype":"locality"
},
  "geometry": {"coordinates":[40.13333,-14.71667],"type":"Point"}
}