{
  "type": "Feature",
  "properties": {
    "gn:admin1_code":"6",
    "gn:asciiname":"Gago",
    "gn:country_code":"MZ",
    "gn:dem":94,
    "gn:feature_class":"P",
    "gn:feature_code":"PPL",
    "gn:name":"Gago",
    "gn:population":0,
    "gn:timezone":"Africa/Maputo",
    "iso:country":"MZ",
    "name:rus_x_preferred":[
        "\u0413\u0430\u0433\u043e"
    ],
    "name:spa_x_preferred":[
        "Gago"
    ],
    "wof:name":"Gago",
    "wof:placetype":"locality"
},
  "geometry": {"coordinates":[40.21556,-15.02611],"type":"Point"}
}