{
  "type": "Feature",
  "properties": {
    "gn:admin1_code":"5",
    "gn:asciiname":"Mecupe",
    "gn:country_code":"MZ",
    "gn:dem":89,
    "gn:feature_class":"P",
    "gn:feature_code":"PPL",
    "gn:name":"Mecupe",
    "gn:population":0,
    "gn:timezone":"Africa/Maputo",
    "iso:country":"MZ",
    "wof:name":"Mecupe",
    "wof:placetype":"locality"
},
  "geometry": {"coordinates":[33.74610999999999,-20.12611],"type":"Point"}
}