{
  "type": "Feature",
  "properties": {
    "gn:admin1_code":"0",
    "gn:asciiname":"Norte",
    "gn:country_code":"MZ",
    "gn:dem":4,
    "gn:feature_class":"P",
    "gn:feature_code":"PPL",
    "gn:name":"Norte",
    "gn:population":0,
    "gn:timezone":"Africa/Maputo",
    "iso:country":"MZ",
    "wof:name":"Norte",
    "wof:placetype":"locality"
},
  "geometry": {"coordinates":[36.73333,-18.05],"type":"Point"}
}