{
  "type": "Feature",
  "properties": {
    "gn:admin1_code":"2",
    "gn:asciiname":"Chigombe",
    "gn:country_code":"MZ",
    "gn:dem":69,
    "gn:feature_class":"P",
    "gn:feature_code":"PPL",
    "gn:name":"Chigombe",
    "gn:population":0,
    "gn:timezone":"Africa/Maputo",
    "iso:country":"MZ",
    "wof:name":"Chigombe",
    "wof:placetype":"locality"
},
  "geometry": {"coordinates":[33.2075,-23.3425],"type":"Point"}
}