{
  "type": "Feature",
  "properties": {
    "gn:admin1_code":"3",
    "gn:asciiname":"Alfiado",
    "gn:cc2":"MZ",
    "gn:country_code":"MZ",
    "gn:dem":49,
    "gn:feature_class":"P",
    "gn:feature_code":"PPL",
    "gn:name":"Alfiado",
    "gn:population":0,
    "gn:timezone":"Africa/Maputo",
    "iso:country":"MZ",
    "name:und_x_variant":[
        "Mucumbe",
        "Alfiado"
    ],
    "wof:name":"Alfiado",
    "wof:placetype":"locality"
},
  "geometry": {"coordinates":[35.25306,-22.71472],"type":"Point"}
}